Workbook

Sheet Weekly Data
A1: DataPath — Weekly Performance Tracker (2025–2026)
A2: One row per week. Blue text = enter from dashboard. Monthly subtotal rows auto-calculate. Filter by Year/Month columns. Freeze panes set on row 4.
F3: ConnectWise | G3: ConnectWise | H3: ConnectWise | I3: ConnectWise | J3: ConnectWise | K3: Computed | L3: ConnectWise | M3: ConnectWise | N3: ConnectWise | O3: ConnectWise | P3: ConnectWise | Q3: ConnectWise | R3: ConnectWise | S3: Sage | T3: Sage | U3: Sage | V3: Computed | W3: Computed | X3: Sage | Y3: Computed | Z3: Sage | AA3: Sage | AB3: Computed | AC3: ConnectWise | AD3: ConnectWise | AE3: ConnectWise | AF3: ConnectWise | AG3: ConnectWise | AH3: ConnectWise | AI3: ConnectWise | AJ3: ConnectWise | AK3: HubSpot | AL3: HubSpot | AM3: HubSpot | AN3: HubSpot
A4: Year | B4: Month | C4: Wk # | D4: Week Range | E4: Date Key | F4: Total Rev Won | G4: NRR | H4: Recur Rev (Mo) | I4: Recur Rev (Ann) | J4: Target | K4: % of Target | L4: Joel Walker | M4: Nathan La Fleche | N4: Dan Sturdivant | O4: Jay Harvey | P4: Ricky Maestas | Q4: Maria Martinez | R4: Julissa Martinez | S4: P&L Gross Sales | T4: P&L COGS | U4: P&L Gross Margin | V4: P&L GM % | W4: Won vs Billed Gap | X4: Cash on Hand | Y4: DSO | Z4: AR Total | AA4: AP Total | AB4: Payroll % Rev | AC4: Tickets Created | AD4: Tickets Resolved | AE4: Open Tickets | AF4: Avg Resolution (hrs) | AG4: SLA Compliance % | AH4: Svc Util (THUNDR) | AI4: Proj Util (TopGun) | AJ4: Company Util | AK4: Pipeline Value | AL4: Proposals Sent | AM4: Win Rate % | AN4: Opportunities
A5: 2025 | B5: Jan | C5: 1 | D5: Jan 06 – Jan 10 | E5: 2025-01-06 | K5: =IF(AND(F5<>"",J5<>"",J5<>0),F5/J5*100,"") | U5: =IF(AND(S5<>"",T5<>""),S5-T5,"") | V5: =IF(AND(U5<>"",S5<>"",S5<>0),U5/S5*100,"") | W5: =IF(AND(F5<>"",S5<>""),F5-S5,"")
A6: 2025 | B6: Jan | C6: 2 | D6: Jan 13 – Jan 17 | E6: 2025-01-13 | K6: =IF(AND(F6<>"",J6<>"",J6<>0),F6/J6*100,"") | U6: =IF(AND(S6<>"",T6<>""),S6-T6,"") | V6: =IF(AND(U6<>"",S6<>"",S6<>0),U6/S6*100,"") | W6: =IF(AND(F6<>"",S6<>""),F6-S6,"")
A7: 2025 | B7: Jan | C7: 3 | D7: Jan 20 – Jan 24 | E7: 2025-01-20 | K7: =IF(AND(F7<>"",J7<>"",J7<>0),F7/J7*100,"") | U7: =IF(AND(S7<>"",T7<>""),S7-T7,"") | V7: =IF(AND(U7<>"",S7<>"",S7<>0),U7/S7*100,"") | W7: =IF(AND(F7<>"",S7<>""),F7-S7,"")
A8: 2025 | B8: Jan | C8: 4 | D8: Jan 27 – Jan 31 | E8: 2025-01-27 | K8: =IF(AND(F8<>"",J8<>"",J8<>0),F8/J8*100,"") | U8: =IF(AND(S8<>"",T8<>""),S8-T8,"") | V8: =IF(AND(U8<>"",S8<>"",S8<>0),U8/S8*100,"") | W8: =IF(AND(F8<>"",S8<>""),F8-S8,"")
A9: 2025 | B9: Jan | D9: Jan 2025 TOTAL | F9: =IFERROR(SUM(F5:F8),"") -> 0 | G9: =IFERROR(SUM(G5:G8),"") -> 0 | H9: =IFERROR(LOOKUP(2,1/(H5:H8<>""),H5:H8),"") | I9: =IFERROR(LOOKUP(2,1/(I5:I8<>""),I5:I8),"") | J9: =IFERROR(LOOKUP(2,1/(J5:J8<>""),J5:J8),"") | K9: =IFERROR(LOOKUP(2,1/(K5:K8<>""),K5:K8),"") | L9: =IFERROR(SUM(L5:L8),"") -> 0 | M9: =IFERROR(SUM(M5:M8),"") -> 0 | N9: =IFERROR(SUM(N5:N8),"") -> 0 | O9: =IFERROR(SUM(O5:O8),"") -> 0 | P9: =IFERROR(SUM(P5:P8),"") -> 0 | Q9: =IFERROR(SUM(Q5:Q8),"") -> 0 | R9: =IFERROR(SUM(R5:R8),"") -> 0 | S9: =IFERROR(LOOKUP(2,1/(S5:S8<>""),S5:S8),"") | T9: =IFERROR(LOOKUP(2,1/(T5:T8<>""),T5:T8),"") | U9: =IFERROR(LOOKUP(2,1/(U5:U8<>""),U5:U8),"") | V9: =IFERROR(LOOKUP(2,1/(V5:V8<>""),V5:V8),"") | W9: =IFERROR(LOOKUP(2,1/(W5:W8<>""),W5:W8),"") | X9: =IFERROR(LOOKUP(2,1/(X5:X8<>""),X5:X8),"") | Y9: =IFERROR(LOOKUP(2,1/(Y5:Y8<>""),Y5:Y8),"") | Z9: =IFERROR(LOOKUP(2,1/(Z5:Z8<>""),Z5:Z8),"") | ... AB9: =IFERROR(LOOKUP(2,1/(AB5:AB8<>""),AB5:AB8),"") | AC9: =IFERROR(SUM(AC5:AC8),"") -> 0 | AD9: =IFERROR(SUM(AD5:AD8),"") -> 0 | AE9: =IFERROR(LOOKUP(2,1/(AE5:AE8<>""),AE5:AE8),"") | AF9: =IFERROR(LOOKUP(2,1/(AF5:AF8<>""),AF5:AF8),"") | AG9: =IFERROR(LOOKUP(2,1/(AG5:AG8<>""),AG5:AG8),"") | AH9: =IFERROR(LOOKUP(2,1/(AH5:AH8<>""),AH5:AH8),"") | AI9: =IFERROR(LOOKUP(2,1/(AI5:AI8<>""),AI5:AI8),"") | AJ9: =IFERROR(LOOKUP(2,1/(AJ5:AJ8<>""),AJ5:AJ8),"") | AK9: =IFERROR(LOOKUP(2,1/(AK5:AK8<>""),AK5:AK8),"") | AL9: =IFERROR(LOOKUP(2,1/(AL5:AL8<>""),AL5:AL8),"") | ... AN9: =IFERROR(LOOKUP(2,1/(AN5:AN8<>""),AN5:AN8),"")
A10: 2025 | B10: Feb | C10: 5 | D10: Feb 03 – Feb 07 | E10: 2025-02-03 | K10: =IF(AND(F10<>"",J10<>"",J10<>0),F10/J10*100,"") | U10: =IF(AND(S10<>"",T10<>""),S10-T10,"") | V10: =IF(AND(U10<>"",S10<>"",S10<>0),U10/S10*100,"") | W10: =IF(AND(F10<>"",S10<>""),F10-S10,"")
A11: 2025 | B11: Feb | C11: 6 | D11: Feb 10 – Feb 14 | E11: 2025-02-10 | K11: =IF(AND(F11<>"",J11<>"",J11<>0),F11/J11*100,"") | U11: =IF(AND(S11<>"",T11<>""),S11-T11,"") | V11: =IF(AND(U11<>"",S11<>"",S11<>0),U11/S11*100,"") | W11: =IF(AND(F11<>"",S11<>""),F11-S11,"")
A12: 2025 | B12: Feb | C12: 7 | D12: Feb 17 – Feb 21 | E12: 2025-02-17 | K12: =IF(AND(F12<>"",J12<>"",J12<>0),F12/J12*100,"") | U12: =IF(AND(S12<>"",T12<>""),S12-T12,"") | V12: =IF(AND(U12<>"",S12<>"",S12<>0),U12/S12*100,"") | W12: =IF(AND(F12<>"",S12<>""),F12-S12,"")
A13: 2025 | B13: Feb | C13: 8 | D13: Feb 24 – Feb 28 | E13: 2025-02-24 | K13: =IF(AND(F13<>"",J13<>"",J13<>0),F13/J13*100,"") | U13: =IF(AND(S13<>"",T13<>""),S13-T13,"") | V13: =IF(AND(U13<>"",S13<>"",S13<>0),U13/S13*100,"") | W13: =IF(AND(F13<>"",S13<>""),F13-S13,"")
A14: 2025 | B14: Feb | D14: Feb 2025 TOTAL | F14: =IFERROR(SUM(F10:F13),"") -> 0 | G14: =IFERROR(SUM(G10:G13),"") -> 0 | H14: =IFERROR(LOOKUP(2,1/(H10:H13<>""),H10:H13),"") | I14: =IFERROR(LOOKUP(2,1/(I10:I13<>""),I10:I13),"") | J14: =IFERROR(LOOKUP(2,1/(J10:J13<>""),J10:J13),"") | K14: =IFERROR(LOOKUP(2,1/(K10:K13<>""),K10:K13),"") | L14: =IFERROR(SUM(L10:L13),"") -> 0 | M14: =IFERROR(SUM(M10:M13),"") -> 0 | N14: =IFERROR(SUM(N10:N13),"") -> 0 | O14: =IFERROR(SUM(O10:O13),"") -> 0 | P14: =IFERROR(SUM(P10:P13),"") -> 0 | Q14: =IFERROR(SUM(Q10:Q13),"") -> 0 | R14: =IFERROR(SUM(R10:R13),"") -> 0 | S14: =IFERROR(LOOKUP(2,1/(S10:S13<>""),S10:S13),"") | T14: =IFERROR(LOOKUP(2,1/(T10:T13<>""),T10:T13),"") | U14: =IFERROR(LOOKUP(2,1/(U10:U13<>""),U10:U13),"") | V14: =IFERROR(LOOKUP(2,1/(V10:V13<>""),V10:V13),"") | W14: =IFERROR(LOOKUP(2,1/(W10:W13<>""),W10:W13),"") | X14: =IFERROR(LOOKUP(2,1/(X10:X13<>""),X10:X13),"") | Y14: =IFERROR(LOOKUP(2,1/(Y10:Y13<>""),Y10:Y13),"") | Z14: =IFERROR(LOOKUP(2,1/(Z10:Z13<>""),Z10:Z13),"") | ... AB14: =IFERROR(LOOKUP(2,1/(AB10:AB13<>""),AB10:AB13),"") | AC14: =IFERROR(SUM(AC10:AC13),"") -> 0 | AD14: =IFERROR(SUM(AD10:AD13),"") -> 0 | AE14: =IFERROR(LOOKUP(2,1/(AE10:AE13<>""),AE10:AE13),"") | AF14: =IFERROR(LOOKUP(2,1/(AF10:AF13<>""),AF10:AF13),"") | AG14: =IFERROR(LOOKUP(2,1/(AG10:AG13<>""),AG10:AG13),"") | AH14: =IFERROR(LOOKUP(2,1/(AH10:AH13<>""),AH10:AH13),"") | AI14: =IFERROR(LOOKUP(2,1/(AI10:AI13<>""),AI10:AI13),"") | AJ14: =IFERROR(LOOKUP(2,1/(AJ10:AJ13<>""),AJ10:AJ13),"") | AK14: =IFERROR(LOOKUP(2,1/(AK10:AK13<>""),AK10:AK13),"") | AL14: =IFERROR(LOOKUP(2,1/(AL10:AL13<>""),AL10:AL13),"") | ... AN14: =IFERROR(LOOKUP(2,1/(AN10:AN13<>""),AN10:AN13),"")
A15: 2025 | B15: Mar | C15: 9 | D15: Mar 03 – Mar 07 | E15: 2025-03-03 | K15: =IF(AND(F15<>"",J15<>"",J15<>0),F15/J15*100,"") | U15: =IF(AND(S15<>"",T15<>""),S15-T15,"") | V15: =IF(AND(U15<>"",S15<>"",S15<>0),U15/S15*100,"") | W15: =IF(AND(F15<>"",S15<>""),F15-S15,"")
A16: 2025 | B16: Mar | C16: 10 | D16: Mar 10 – Mar 14 | E16: 2025-03-10 | K16: =IF(AND(F16<>"",J16<>"",J16<>0),F16/J16*100,"") | U16: =IF(AND(S16<>"",T16<>""),S16-T16,"") | V16: =IF(AND(U16<>"",S16<>"",S16<>0),U16/S16*100,"") | W16: =IF(AND(F16<>"",S16<>""),F16-S16,"")
A17: 2025 | B17: Mar | C17: 11 | D17: Mar 17 – Mar 21 | E17: 2025-03-17 | K17: =IF(AND(F17<>"",J17<>"",J17<>0),F17/J17*100,"") | U17: =IF(AND(S17<>"",T17<>""),S17-T17,"") | V17: =IF(AND(U17<>"",S17<>"",S17<>0),U17/S17*100,"") | W17: =IF(AND(F17<>"",S17<>""),F17-S17,"")
A18: 2025 | B18: Mar | C18: 12 | D18: Mar 24 – Mar 28 | E18: 2025-03-24 | K18: =IF(AND(F18<>"",J18<>"",J18<>0),F18/J18*100,"") | U18: =IF(AND(S18<>"",T18<>""),S18-T18,"") | V18: =IF(AND(U18<>"",S18<>"",S18<>0),U18/S18*100,"") | W18: =IF(AND(F18<>"",S18<>""),F18-S18,"")
A19: 2025 | B19: Mar | C19: 13 | D19: Mar 31 – Apr 04 | E19: 2025-03-31 | K19: =IF(AND(F19<>"",J19<>"",J19<>0),F19/J19*100,"") | U19: =IF(AND(S19<>"",T19<>""),S19-T19,"") | V19: =IF(AND(U19<>"",S19<>"",S19<>0),U19/S19*100,"") | W19: =IF(AND(F19<>"",S19<>""),F19-S19,"")
A20: 2025 | B20: Mar | D20: Mar 2025 TOTAL | F20: =IFERROR(SUM(F15:F19),"") -> 0 | G20: =IFERROR(SUM(G15:G19),"") -> 0 | H20: =IFERROR(LOOKUP(2,1/(H15:H19<>""),H15:H19),"") | I20: =IFERROR(LOOKUP(2,1/(I15:I19<>""),I15:I19),"") | J20: =IFERROR(LOOKUP(2,1/(J15:J19<>""),J15:J19),"") | K20: =IFERROR(LOOKUP(2,1/(K15:K19<>""),K15:K19),"") | L20: =IFERROR(SUM(L15:L19),"") -> 0 | M20: =IFERROR(SUM(M15:M19),"") -> 0 | N20: =IFERROR(SUM(N15:N19),"") -> 0 | O20: =IFERROR(SUM(O15:O19),"") -> 0 | P20: =IFERROR(SUM(P15:P19),"") -> 0 | Q20: =IFERROR(SUM(Q15:Q19),"") -> 0 | R20: =IFERROR(SUM(R15:R19),"") -> 0 | S20: =IFERROR(LOOKUP(2,1/(S15:S19<>""),S15:S19),"") | T20: =IFERROR(LOOKUP(2,1/(T15:T19<>""),T15:T19),"") | U20: =IFERROR(LOOKUP(2,1/(U15:U19<>""),U15:U19),"") | V20: =IFERROR(LOOKUP(2,1/(V15:V19<>""),V15:V19),"") | W20: =IFERROR(LOOKUP(2,1/(W15:W19<>""),W15:W19),"") | X20: =IFERROR(LOOKUP(2,1/(X15:X19<>""),X15:X19),"") | Y20: =IFERROR(LOOKUP(2,1/(Y15:Y19<>""),Y15:Y19),"") | Z20: =IFERROR(LOOKUP(2,1/(Z15:Z19<>""),Z15:Z19),"") | ... AB20: =IFERROR(LOOKUP(2,1/(AB15:AB19<>""),AB15:AB19),"") | AC20: =IFERROR(SUM(AC15:AC19),"") -> 0 | AD20: =IFERROR(SUM(AD15:AD19),"") -> 0 | AE20: =IFERROR(LOOKUP(2,1/(AE15:AE19<>""),AE15:AE19),"") | AF20: =IFERROR(LOOKUP(2,1/(AF15:AF19<>""),AF15:AF19),"") | AG20: =IFERROR(LOOKUP(2,1/(AG15:AG19<>""),AG15:AG19),"") | AH20: =IFERROR(LOOKUP(2,1/(AH15:AH19<>""),AH15:AH19),"") | AI20: =IFERROR(LOOKUP(2,1/(AI15:AI19<>""),AI15:AI19),"") | AJ20: =IFERROR(LOOKUP(2,1/(AJ15:AJ19<>""),AJ15:AJ19),"") | AK20: =IFERROR(LOOKUP(2,1/(AK15:AK19<>""),AK15:AK19),"") | AL20: =IFERROR(LOOKUP(2,1/(AL15:AL19<>""),AL15:AL19),"") | ... AN20: =IFERROR(LOOKUP(2,1/(AN15:AN19<>""),AN15:AN19),"")
A21: 2025 | B21: Apr | C21: 14 | D21: Apr 07 – Apr 11 | E21: 2025-04-07 | K21: =IF(AND(F21<>"",J21<>"",J21<>0),F21/J21*100,"") | U21: =IF(AND(S21<>"",T21<>""),S21-T21,"") | V21: =IF(AND(U21<>"",S21<>"",S21<>0),U21/S21*100,"") | W21: =IF(AND(F21<>"",S21<>""),F21-S21,"")
A22: 2025 | B22: Apr | C22: 15 | D22: Apr 14 – Apr 18 | E22: 2025-04-14 | K22: =IF(AND(F22<>"",J22<>"",J22<>0),F22/J22*100,"") | U22: =IF(AND(S22<>"",T22<>""),S22-T22,"") | V22: =IF(AND(U22<>"",S22<>"",S22<>0),U22/S22*100,"") | W22: =IF(AND(F22<>"",S22<>""),F22-S22,"")
A23: 2025 | B23: Apr | C23: 16 | D23: Apr 21 – Apr 25 | E23: 2025-04-21 | K23: =IF(AND(F23<>"",J23<>"",J23<>0),F23/J23*100,"") | U23: =IF(AND(S23<>"",T23<>""),S23-T23,"") | V23: =IF(AND(U23<>"",S23<>"",S23<>0),U23/S23*100,"") | W23: =IF(AND(F23<>"",S23<>""),F23-S23,"")
A24: 2025 | B24: Apr | C24: 17 | D24: Apr 28 – May 02 | E24: 2025-04-28 | K24: =IF(AND(F24<>"",J24<>"",J24<>0),F24/J24*100,"") | U24: =IF(AND(S24<>"",T24<>""),S24-T24,"") | V24: =IF(AND(U24<>"",S24<>"",S24<>0),U24/S24*100,"") | W24: =IF(AND(F24<>"",S24<>""),F24-S24,"")
A25: 2025 | B25: Apr | D25: Apr 2025 TOTAL | F25: =IFERROR(SUM(F21:F24),"") -> 0 | G25: =IFERROR(SUM(G21:G24),"") -> 0 | H25: =IFERROR(LOOKUP(2,1/(H21:H24<>""),H21:H24),"") | I25: =IFERROR(LOOKUP(2,1/(I21:I24<>""),I21:I24),"") | J25: =IFERROR(LOOKUP(2,1/(J21:J24<>""),J21:J24),"") | K25: =IFERROR(LOOKUP(2,1/(K21:K24<>""),K21:K24),"") | L25: =IFERROR(SUM(L21:L24),"") -> 0 | M25: =IFERROR(SUM(M21:M24),"") -> 0 | N25: =IFERROR(SUM(N21:N24),"") -> 0 | O25: =IFERROR(SUM(O21:O24),"") -> 0 | P25: =IFERROR(SUM(P21:P24),"") -> 0 | Q25: =IFERROR(SUM(Q21:Q24),"") -> 0 | R25: =IFERROR(SUM(R21:R24),"") -> 0 | S25: =IFERROR(LOOKUP(2,1/(S21:S24<>""),S21:S24),"") | T25: =IFERROR(LOOKUP(2,1/(T21:T24<>""),T21:T24),"") | U25: =IFERROR(LOOKUP(2,1/(U21:U24<>""),U21:U24),"") | V25: =IFERROR(LOOKUP(2,1/(V21:V24<>""),V21:V24),"") | W25: =IFERROR(LOOKUP(2,1/(W21:W24<>""),W21:W24),"") | X25: =IFERROR(LOOKUP(2,1/(X21:X24<>""),X21:X24),"") | Y25: =IFERROR(LOOKUP(2,1/(Y21:Y24<>""),Y21:Y24),"") | Z25: =IFERROR(LOOKUP(2,1/(Z21:Z24<>""),Z21:Z24),"") | ... AB25: =IFERROR(LOOKUP(2,1/(AB21:AB24<>""),AB21:AB24),"") | AC25: =IFERROR(SUM(AC21:AC24),"") -> 0 | AD25: =IFERROR(SUM(AD21:AD24),"") -> 0 | AE25: =IFERROR(LOOKUP(2,1/(AE21:AE24<>""),AE21:AE24),"") | AF25: =IFERROR(LOOKUP(2,1/(AF21:AF24<>""),AF21:AF24),"") | AG25: =IFERROR(LOOKUP(2,1/(AG21:AG24<>""),AG21:AG24),"") | AH25: =IFERROR(LOOKUP(2,1/(AH21:AH24<>""),AH21:AH24),"") | AI25: =IFERROR(LOOKUP(2,1/(AI21:AI24<>""),AI21:AI24),"") | AJ25: =IFERROR(LOOKUP(2,1/(AJ21:AJ24<>""),AJ21:AJ24),"") | AK25: =IFERROR(LOOKUP(2,1/(AK21:AK24<>""),AK21:AK24),"") | AL25: =IFERROR(LOOKUP(2,1/(AL21:AL24<>""),AL21:AL24),"") | ... AN25: =IFERROR(LOOKUP(2,1/(AN21:AN24<>""),AN21:AN24),"")
A26: 2025 | B26: May | C26: 18 | D26: May 05 – May 09 | E26: 2025-05-05 | K26: =IF(AND(F26<>"",J26<>"",J26<>0),F26/J26*100,"") | U26: =IF(AND(S26<>"",T26<>""),S26-T26,"") | V26: =IF(AND(U26<>"",S26<>"",S26<>0),U26/S26*100,"") | W26: =IF(AND(F26<>"",S26<>""),F26-S26,"")
A27: 2025 | B27: May | C27: 19 | D27: May 12 – May 16 | E27: 2025-05-12 | K27: =IF(AND(F27<>"",J27<>"",J27<>0),F27/J27*100,"") | U27: =IF(AND(S27<>"",T27<>""),S27-T27,"") | V27: =IF(AND(U27<>"",S27<>"",S27<>0),U27/S27*100,"") | W27: =IF(AND(F27<>"",S27<>""),F27-S27,"")
A28: 2025 | B28: May | C28: 20 | D28: May 19 – May 23 | E28: 2025-05-19 | K28: =IF(AND(F28<>"",J28<>"",J28<>0),F28/J28*100,"") | U28: =IF(AND(S28<>"",T28<>""),S28-T28,"") | V28: =IF(AND(U28<>"",S28<>"",S28<>0),U28/S28*100,"") | W28: =IF(AND(F28<>"",S28<>""),F28-S28,"")
A29: 2025 | B29: May | C29: 21 | D29: May 26 – May 30 | E29: 2025-05-26 | K29: =IF(AND(F29<>"",J29<>"",J29<>0),F29/J29*100,"") | U29: =IF(AND(S29<>"",T29<>""),S29-T29,"") | V29: =IF(AND(U29<>"",S29<>"",S29<>0),U29/S29*100,"") | W29: =IF(AND(F29<>"",S29<>""),F29-S29,"")
A30: 2025 | B30: May | D30: May 2025 TOTAL | F30: =IFERROR(SUM(F26:F29),"") -> 0 | G30: =IFERROR(SUM(G26:G29),"") -> 0 | H30: =IFERROR(LOOKUP(2,1/(H26:H29<>""),H26:H29),"") | I30: =IFERROR(LOOKUP(2,1/(I26:I29<>""),I26:I29),"") | J30: =IFERROR(LOOKUP(2,1/(J26:J29<>""),J26:J29),"") | K30: =IFERROR(LOOKUP(2,1/(K26:K29<>""),K26:K29),"") | L30: =IFERROR(SUM(L26:L29),"") -> 0 | M30: =IFERROR(SUM(M26:M29),"") -> 0 | N30: =IFERROR(SUM(N26:N29),"") -> 0 | O30: =IFERROR(SUM(O26:O29),"") -> 0 | P30: =IFERROR(SUM(P26:P29),"") -> 0 | Q30: =IFERROR(SUM(Q26:Q29),"") -> 0 | R30: =IFERROR(SUM(R26:R29),"") -> 0 | S30: =IFERROR(LOOKUP(2,1/(S26:S29<>""),S26:S29),"") | T30: =IFERROR(LOOKUP(2,1/(T26:T29<>""),T26:T29),"") | U30: =IFERROR(LOOKUP(2,1/(U26:U29<>""),U26:U29),"") | V30: =IFERROR(LOOKUP(2,1/(V26:V29<>""),V26:V29),"") | W30: =IFERROR(LOOKUP(2,1/(W26:W29<>""),W26:W29),"") | X30: =IFERROR(LOOKUP(2,1/(X26:X29<>""),X26:X29),"") | Y30: =IFERROR(LOOKUP(2,1/(Y26:Y29<>""),Y26:Y29),"") | Z30: =IFERROR(LOOKUP(2,1/(Z26:Z29<>""),Z26:Z29),"") | ... AB30: =IFERROR(LOOKUP(2,1/(AB26:AB29<>""),AB26:AB29),"") | AC30: =IFERROR(SUM(AC26:AC29),"") -> 0 | AD30: =IFERROR(SUM(AD26:AD29),"") -> 0 | AE30: =IFERROR(LOOKUP(2,1/(AE26:AE29<>""),AE26:AE29),"") | AF30: =IFERROR(LOOKUP(2,1/(AF26:AF29<>""),AF26:AF29),"") | AG30: =IFERROR(LOOKUP(2,1/(AG26:AG29<>""),AG26:AG29),"") | AH30: =IFERROR(LOOKUP(2,1/(AH26:AH29<>""),AH26:AH29),"") | AI30: =IFERROR(LOOKUP(2,1/(AI26:AI29<>""),AI26:AI29),"") | AJ30: =IFERROR(LOOKUP(2,1/(AJ26:AJ29<>""),AJ26:AJ29),"") | AK30: =IFERROR(LOOKUP(2,1/(AK26:AK29<>""),AK26:AK29),"") | AL30: =IFERROR(LOOKUP(2,1/(AL26:AL29<>""),AL26:AL29),"") | ... AN30: =IFERROR(LOOKUP(2,1/(AN26:AN29<>""),AN26:AN29),"")
A31: 2025 | B31: Jun | C31: 22 | D31: Jun 02 – Jun 06 | E31: 2025-06-02 | K31: =IF(AND(F31<>"",J31<>"",J31<>0),F31/J31*100,"") | U31: =IF(AND(S31<>"",T31<>""),S31-T31,"") | V31: =IF(AND(U31<>"",S31<>"",S31<>0),U31/S31*100,"") | W31: =IF(AND(F31<>"",S31<>""),F31-S31,"")
A32: 2025 | B32: Jun | C32: 23 | D32: Jun 09 – Jun 13 | E32: 2025-06-09 | K32: =IF(AND(F32<>"",J32<>"",J32<>0),F32/J32*100,"") | U32: =IF(AND(S32<>"",T32<>""),S32-T32,"") | V32: =IF(AND(U32<>"",S32<>"",S32<>0),U32/S32*100,"") | W32: =IF(AND(F32<>"",S32<>""),F32-S32,"")
A33: 2025 | B33: Jun | C33: 24 | D33: Jun 16 – Jun 20 | E33: 2025-06-16 | K33: =IF(AND(F33<>"",J33<>"",J33<>0),F33/J33*100,"") | U33: =IF(AND(S33<>"",T33<>""),S33-T33,"") | V33: =IF(AND(U33<>"",S33<>"",S33<>0),U33/S33*100,"") | W33: =IF(AND(F33<>"",S33<>""),F33-S33,"")
A34: 2025 | B34: Jun | C34: 25 | D34: Jun 23 – Jun 27 | E34: 2025-06-23 | K34: =IF(AND(F34<>"",J34<>"",J34<>0),F34/J34*100,"") | U34: =IF(AND(S34<>"",T34<>""),S34-T34,"") | V34: =IF(AND(U34<>"",S34<>"",S34<>0),U34/S34*100,"") | W34: =IF(AND(F34<>"",S34<>""),F34-S34,"")
A35: 2025 | B35: Jun | C35: 26 | D35: Jun 30 – Jul 04 | E35: 2025-06-30 | K35: =IF(AND(F35<>"",J35<>"",J35<>0),F35/J35*100,"") | U35: =IF(AND(S35<>"",T35<>""),S35-T35,"") | V35: =IF(AND(U35<>"",S35<>"",S35<>0),U35/S35*100,"") | W35: =IF(AND(F35<>"",S35<>""),F35-S35,"")
A36: 2025 | B36: Jun | D36: Jun 2025 TOTAL | F36: =IFERROR(SUM(F31:F35),"") -> 0 | G36: =IFERROR(SUM(G31:G35),"") -> 0 | H36: =IFERROR(LOOKUP(2,1/(H31:H35<>""),H31:H35),"") | I36: =IFERROR(LOOKUP(2,1/(I31:I35<>""),I31:I35),"") | J36: =IFERROR(LOOKUP(2,1/(J31:J35<>""),J31:J35),"") | K36: =IFERROR(LOOKUP(2,1/(K31:K35<>""),K31:K35),"") | L36: =IFERROR(SUM(L31:L35),"") -> 0 | M36: =IFERROR(SUM(M31:M35),"") -> 0 | N36: =IFERROR(SUM(N31:N35),"") -> 0 | O36: =IFERROR(SUM(O31:O35),"") -> 0 | P36: =IFERROR(SUM(P31:P35),"") -> 0 | Q36: =IFERROR(SUM(Q31:Q35),"") -> 0 | R36: =IFERROR(SUM(R31:R35),"") -> 0 | S36: =IFERROR(LOOKUP(2,1/(S31:S35<>""),S31:S35),"") | T36: =IFERROR(LOOKUP(2,1/(T31:T35<>""),T31:T35),"") | U36: =IFERROR(LOOKUP(2,1/(U31:U35<>""),U31:U35),"") | V36: =IFERROR(LOOKUP(2,1/(V31:V35<>""),V31:V35),"") | W36: =IFERROR(LOOKUP(2,1/(W31:W35<>""),W31:W35),"") | X36: =IFERROR(LOOKUP(2,1/(X31:X35<>""),X31:X35),"") | Y36: =IFERROR(LOOKUP(2,1/(Y31:Y35<>""),Y31:Y35),"") | Z36: =IFERROR(LOOKUP(2,1/(Z31:Z35<>""),Z31:Z35),"") | ... AB36: =IFERROR(LOOKUP(2,1/(AB31:AB35<>""),AB31:AB35),"") | AC36: =IFERROR(SUM(AC31:AC35),"") -> 0 | AD36: =IFERROR(SUM(AD31:AD35),"") -> 0 | AE36: =IFERROR(LOOKUP(2,1/(AE31:AE35<>""),AE31:AE35),"") | AF36: =IFERROR(LOOKUP(2,1/(AF31:AF35<>""),AF31:AF35),"") | AG36: =IFERROR(LOOKUP(2,1/(AG31:AG35<>""),AG31:AG35),"") | AH36: =IFERROR(LOOKUP(2,1/(AH31:AH35<>""),AH31:AH35),"") | AI36: =IFERROR(LOOKUP(2,1/(AI31:AI35<>""),AI31:AI35),"") | AJ36: =IFERROR(LOOKUP(2,1/(AJ31:AJ35<>""),AJ31:AJ35),"") | AK36: =IFERROR(LOOKUP(2,1/(AK31:AK35<>""),AK31:AK35),"") | AL36: =IFERROR(LOOKUP(2,1/(AL31:AL35<>""),AL31:AL35),"") | ... AN36: =IFERROR(LOOKUP(2,1/(AN31:AN35<>""),AN31:AN35),"")
A37: 2025 | B37: Jul | C37: 27 | D37: Jul 07 – Jul 11 | E37: 2025-07-07 | K37: =IF(AND(F37<>"",J37<>"",J37<>0),F37/J37*100,"") | U37: =IF(AND(S37<>"",T37<>""),S37-T37,"") | V37: =IF(AND(U37<>"",S37<>"",S37<>0),U37/S37*100,"") | W37: =IF(AND(F37<>"",S37<>""),F37-S37,"")
A38: 2025 | B38: Jul | C38: 28 | D38: Jul 14 – Jul 18 | E38: 2025-07-14 | K38: =IF(AND(F38<>"",J38<>"",J38<>0),F38/J38*100,"") | U38: =IF(AND(S38<>"",T38<>""),S38-T38,"") | V38: =IF(AND(U38<>"",S38<>"",S38<>0),U38/S38*100,"") | W38: =IF(AND(F38<>"",S38<>""),F38-S38,"")
A39: 2025 | B39: Jul | C39: 29 | D39: Jul 21 – Jul 25 | E39: 2025-07-21 | K39: =IF(AND(F39<>"",J39<>"",J39<>0),F39/J39*100,"") | U39: =IF(AND(S39<>"",T39<>""),S39-T39,"") | V39: =IF(AND(U39<>"",S39<>"",S39<>0),U39/S39*100,"") | W39: =IF(AND(F39<>"",S39<>""),F39-S39,"")
A40: 2025 | B40: Jul | C40: 30 | D40: Jul 28 – Aug 01 | E40: 2025-07-28 | K40: =IF(AND(F40<>"",J40<>"",J40<>0),F40/J40*100,"") | U40: =IF(AND(S40<>"",T40<>""),S40-T40,"") | V40: =IF(AND(U40<>"",S40<>"",S40<>0),U40/S40*100,"") | W40: =IF(AND(F40<>"",S40<>""),F40-S40,"")
A41: 2025 | B41: Jul | D41: Jul 2025 TOTAL | F41: =IFERROR(SUM(F37:F40),"") -> 0 | G41: =IFERROR(SUM(G37:G40),"") -> 0 | H41: =IFERROR(LOOKUP(2,1/(H37:H40<>""),H37:H40),"") | I41: =IFERROR(LOOKUP(2,1/(I37:I40<>""),I37:I40),"") | J41: =IFERROR(LOOKUP(2,1/(J37:J40<>""),J37:J40),"") | K41: =IFERROR(LOOKUP(2,1/(K37:K40<>""),K37:K40),"") | L41: =IFERROR(SUM(L37:L40),"") -> 0 | M41: =IFERROR(SUM(M37:M40),"") -> 0 | N41: =IFERROR(SUM(N37:N40),"") -> 0 | O41: =IFERROR(SUM(O37:O40),"") -> 0 | P41: =IFERROR(SUM(P37:P40),"") -> 0 | Q41: =IFERROR(SUM(Q37:Q40),"") -> 0 | R41: =IFERROR(SUM(R37:R40),"") -> 0 | S41: =IFERROR(LOOKUP(2,1/(S37:S40<>""),S37:S40),"") | T41: =IFERROR(LOOKUP(2,1/(T37:T40<>""),T37:T40),"") | U41: =IFERROR(LOOKUP(2,1/(U37:U40<>""),U37:U40),"") | V41: =IFERROR(LOOKUP(2,1/(V37:V40<>""),V37:V40),"") | W41: =IFERROR(LOOKUP(2,1/(W37:W40<>""),W37:W40),"") | X41: =IFERROR(LOOKUP(2,1/(X37:X40<>""),X37:X40),"") | Y41: =IFERROR(LOOKUP(2,1/(Y37:Y40<>""),Y37:Y40),"") | Z41: =IFERROR(LOOKUP(2,1/(Z37:Z40<>""),Z37:Z40),"") | ... AB41: =IFERROR(LOOKUP(2,1/(AB37:AB40<>""),AB37:AB40),"") | AC41: =IFERROR(SUM(AC37:AC40),"") -> 0 | AD41: =IFERROR(SUM(AD37:AD40),"") -> 0 | AE41: =IFERROR(LOOKUP(2,1/(AE37:AE40<>""),AE37:AE40),"") | AF41: =IFERROR(LOOKUP(2,1/(AF37:AF40<>""),AF37:AF40),"") | AG41: =IFERROR(LOOKUP(2,1/(AG37:AG40<>""),AG37:AG40),"") | AH41: =IFERROR(LOOKUP(2,1/(AH37:AH40<>""),AH37:AH40),"") | AI41: =IFERROR(LOOKUP(2,1/(AI37:AI40<>""),AI37:AI40),"") | AJ41: =IFERROR(LOOKUP(2,1/(AJ37:AJ40<>""),AJ37:AJ40),"") | AK41: =IFERROR(LOOKUP(2,1/(AK37:AK40<>""),AK37:AK40),"") | AL41: =IFERROR(LOOKUP(2,1/(AL37:AL40<>""),AL37:AL40),"") | ... AN41: =IFERROR(LOOKUP(2,1/(AN37:AN40<>""),AN37:AN40),"")
A42: 2025 | B42: Aug | C42: 31 | D42: Aug 04 – Aug 08 | E42: 2025-08-04 | K42: =IF(AND(F42<>"",J42<>"",J42<>0),F42/J42*100,"") | U42: =IF(AND(S42<>"",T42<>""),S42-T42,"") | V42: =IF(AND(U42<>"",S42<>"",S42<>0),U42/S42*100,"") | W42: =IF(AND(F42<>"",S42<>""),F42-S42,"")
A43: 2025 | B43: Aug | C43: 32 | D43: Aug 11 – Aug 15 | E43: 2025-08-11 | K43: =IF(AND(F43<>"",J43<>"",J43<>0),F43/J43*100,"") | U43: =IF(AND(S43<>"",T43<>""),S43-T43,"") | V43: =IF(AND(U43<>"",S43<>"",S43<>0),U43/S43*100,"") | W43: =IF(AND(F43<>"",S43<>""),F43-S43,"")
A44: 2025 | B44: Aug | C44: 33 | D44: Aug 18 – Aug 22 | E44: 2025-08-18 | K44: =IF(AND(F44<>"",J44<>"",J44<>0),F44/J44*100,"") | U44: =IF(AND(S44<>"",T44<>""),S44-T44,"") | V44: =IF(AND(U44<>"",S44<>"",S44<>0),U44/S44*100,"") | W44: =IF(AND(F44<>"",S44<>""),F44-S44,"")
A45: 2025 | B45: Aug | C45: 34 | D45: Aug 25 – Aug 29 | E45: 2025-08-25 | K45: =IF(AND(F45<>"",J45<>"",J45<>0),F45/J45*100,"") | U45: =IF(AND(S45<>"",T45<>""),S45-T45,"") | V45: =IF(AND(U45<>"",S45<>"",S45<>0),U45/S45*100,"") | W45: =IF(AND(F45<>"",S45<>""),F45-S45,"")
A46: 2025 | B46: Aug | D46: Aug 2025 TOTAL | F46: =IFERROR(SUM(F42:F45),"") -> 0 | G46: =IFERROR(SUM(G42:G45),"") -> 0 | H46: =IFERROR(LOOKUP(2,1/(H42:H45<>""),H42:H45),"") | I46: =IFERROR(LOOKUP(2,1/(I42:I45<>""),I42:I45),"") | J46: =IFERROR(LOOKUP(2,1/(J42:J45<>""),J42:J45),"") | K46: =IFERROR(LOOKUP(2,1/(K42:K45<>""),K42:K45),"") | L46: =IFERROR(SUM(L42:L45),"") -> 0 | M46: =IFERROR(SUM(M42:M45),"") -> 0 | N46: =IFERROR(SUM(N42:N45),"") -> 0 | O46: =IFERROR(SUM(O42:O45),"") -> 0 | P46: =IFERROR(SUM(P42:P45),"") -> 0 | Q46: =IFERROR(SUM(Q42:Q45),"") -> 0 | R46: =IFERROR(SUM(R42:R45),"") -> 0 | S46: =IFERROR(LOOKUP(2,1/(S42:S45<>""),S42:S45),"") | T46: =IFERROR(LOOKUP(2,1/(T42:T45<>""),T42:T45),"") | U46: =IFERROR(LOOKUP(2,1/(U42:U45<>""),U42:U45),"") | V46: =IFERROR(LOOKUP(2,1/(V42:V45<>""),V42:V45),"") | W46: =IFERROR(LOOKUP(2,1/(W42:W45<>""),W42:W45),"") | X46: =IFERROR(LOOKUP(2,1/(X42:X45<>""),X42:X45),"") | Y46: =IFERROR(LOOKUP(2,1/(Y42:Y45<>""),Y42:Y45),"") | Z46: =IFERROR(LOOKUP(2,1/(Z42:Z45<>""),Z42:Z45),"") | ... AB46: =IFERROR(LOOKUP(2,1/(AB42:AB45<>""),AB42:AB45),"") | AC46: =IFERROR(SUM(AC42:AC45),"") -> 0 | AD46: =IFERROR(SUM(AD42:AD45),"") -> 0 | AE46: =IFERROR(LOOKUP(2,1/(AE42:AE45<>""),AE42:AE45),"") | AF46: =IFERROR(LOOKUP(2,1/(AF42:AF45<>""),AF42:AF45),"") | AG46: =IFERROR(LOOKUP(2,1/(AG42:AG45<>""),AG42:AG45),"") | AH46: =IFERROR(LOOKUP(2,1/(AH42:AH45<>""),AH42:AH45),"") | AI46: =IFERROR(LOOKUP(2,1/(AI42:AI45<>""),AI42:AI45),"") | AJ46: =IFERROR(LOOKUP(2,1/(AJ42:AJ45<>""),AJ42:AJ45),"") | AK46: =IFERROR(LOOKUP(2,1/(AK42:AK45<>""),AK42:AK45),"") | AL46: =IFERROR(LOOKUP(2,1/(AL42:AL45<>""),AL42:AL45),"") | ... AN46: =IFERROR(LOOKUP(2,1/(AN42:AN45<>""),AN42:AN45),"")
A47: 2025 | B47: Sep | C47: 35 | D47: Sep 01 – Sep 05 | E47: 2025-09-01 | K47: =IF(AND(F47<>"",J47<>"",J47<>0),F47/J47*100,"") | U47: =IF(AND(S47<>"",T47<>""),S47-T47,"") | V47: =IF(AND(U47<>"",S47<>"",S47<>0),U47/S47*100,"") | W47: =IF(AND(F47<>"",S47<>""),F47-S47,"") | X47: 667603
A48: 2025 | B48: Sep | C48: 36 | D48: Sep 08 – Sep 12 | E48: 2025-09-08 | K48: =IF(AND(F48<>"",J48<>"",J48<>0),F48/J48*100,"") | U48: =IF(AND(S48<>"",T48<>""),S48-T48,"") | V48: =IF(AND(U48<>"",S48<>"",S48<>0),U48/S48*100,"") | W48: =IF(AND(F48<>"",S48<>""),F48-S48,"") | X48: 578285
A49: 2025 | B49: Sep | C49: 37 | D49: Sep 15 – Sep 19 | E49: 2025-09-15 | K49: =IF(AND(F49<>"",J49<>"",J49<>0),F49/J49*100,"") | U49: =IF(AND(S49<>"",T49<>""),S49-T49,"") | V49: =IF(AND(U49<>"",S49<>"",S49<>0),U49/S49*100,"") | W49: =IF(AND(F49<>"",S49<>""),F49-S49,"") | X49: 505399
A50: 2025 | B50: Sep | C50: 38 | D50: Sep 22 – Sep 26 | E50: 2025-09-22 | K50: =IF(AND(F50<>"",J50<>"",J50<>0),F50/J50*100,"") | U50: =IF(AND(S50<>"",T50<>""),S50-T50,"") | V50: =IF(AND(U50<>"",S50<>"",S50<>0),U50/S50*100,"") | W50: =IF(AND(F50<>"",S50<>""),F50-S50,"") | X50: 352316
A51: 2025 | B51: Sep | C51: 39 | D51: Sep 29 – Oct 03 | E51: 2025-09-29 | K51: =IF(AND(F51<>"",J51<>"",J51<>0),F51/J51*100,"") | U51: =IF(AND(S51<>"",T51<>""),S51-T51,"") | V51: =IF(AND(U51<>"",S51<>"",S51<>0),U51/S51*100,"") | W51: =IF(AND(F51<>"",S51<>""),F51-S51,"") | X51: 296137
A52: 2025 | B52: Sep | D52: Sep 2025 TOTAL | F52: =IFERROR(SUM(F47:F51),"") -> 0 | G52: =IFERROR(SUM(G47:G51),"") -> 0 | H52: =IFERROR(LOOKUP(2,1/(H47:H51<>""),H47:H51),"") | I52: =IFERROR(LOOKUP(2,1/(I47:I51<>""),I47:I51),"") | J52: =IFERROR(LOOKUP(2,1/(J47:J51<>""),J47:J51),"") | K52: =IFERROR(LOOKUP(2,1/(K47:K51<>""),K47:K51),"") | L52: =IFERROR(SUM(L47:L51),"") -> 0 | M52: =IFERROR(SUM(M47:M51),"") -> 0 | N52: =IFERROR(SUM(N47:N51),"") -> 0 | O52: =IFERROR(SUM(O47:O51),"") -> 0 | P52: =IFERROR(SUM(P47:P51),"") -> 0 | Q52: =IFERROR(SUM(Q47:Q51),"") -> 0 | R52: =IFERROR(SUM(R47:R51),"") -> 0 | S52: =IFERROR(LOOKUP(2,1/(S47:S51<>""),S47:S51),"") | T52: =IFERROR(LOOKUP(2,1/(T47:T51<>""),T47:T51),"") | U52: =IFERROR(LOOKUP(2,1/(U47:U51<>""),U47:U51),"") | V52: =IFERROR(LOOKUP(2,1/(V47:V51<>""),V47:V51),"") | W52: =IFERROR(LOOKUP(2,1/(W47:W51<>""),W47:W51),"") | X52: =IFERROR(LOOKUP(2,1/(X47:X51<>""),X47:X51),"") -> 296137 | Y52: =IFERROR(LOOKUP(2,1/(Y47:Y51<>""),Y47:Y51),"") | Z52: =IFERROR(LOOKUP(2,1/(Z47:Z51<>""),Z47:Z51),"") | ... AB52: =IFERROR(LOOKUP(2,1/(AB47:AB51<>""),AB47:AB51),"") | AC52: =IFERROR(SUM(AC47:AC51),"") -> 0 | AD52: =IFERROR(SUM(AD47:AD51),"") -> 0 | AE52: =IFERROR(LOOKUP(2,1/(AE47:AE51<>""),AE47:AE51),"") | AF52: =IFERROR(LOOKUP(2,1/(AF47:AF51<>""),AF47:AF51),"") | AG52: =IFERROR(LOOKUP(2,1/(AG47:AG51<>""),AG47:AG51),"") | AH52: =IFERROR(LOOKUP(2,1/(AH47:AH51<>""),AH47:AH51),"") | AI52: =IFERROR(LOOKUP(2,1/(AI47:AI51<>""),AI47:AI51),"") | AJ52: =IFERROR(LOOKUP(2,1/(AJ47:AJ51<>""),AJ47:AJ51),"") | AK52: =IFERROR(LOOKUP(2,1/(AK47:AK51<>""),AK47:AK51),"") | AL52: =IFERROR(LOOKUP(2,1/(AL47:AL51<>""),AL47:AL51),"") | ... AN52: =IFERROR(LOOKUP(2,1/(AN47:AN51<>""),AN47:AN51),"")
A53: 2025 | B53: Oct | C53: 40 | D53: Oct 06 – Oct 10 | E53: 2025-10-06 | K53: =IF(AND(F53<>"",J53<>"",J53<>0),F53/J53*100,"") | U53: =IF(AND(S53<>"",T53<>""),S53-T53,"") | V53: =IF(AND(U53<>"",S53<>"",S53<>0),U53/S53*100,"") | W53: =IF(AND(F53<>"",S53<>""),F53-S53,"") | X53: 356012
A54: 2025 | B54: Oct | C54: 41 | D54: Oct 13 – Oct 17 | E54: 2025-10-13 | K54: =IF(AND(F54<>"",J54<>"",J54<>0),F54/J54*100,"") | U54: =IF(AND(S54<>"",T54<>""),S54-T54,"") | V54: =IF(AND(U54<>"",S54<>"",S54<>0),U54/S54*100,"") | W54: =IF(AND(F54<>"",S54<>""),F54-S54,"") | X54: 768863
A55: 2025 | B55: Oct | C55: 42 | D55: Oct 20 – Oct 24 | E55: 2025-10-20 | K55: =IF(AND(F55<>"",J55<>"",J55<>0),F55/J55*100,"") | U55: =IF(AND(S55<>"",T55<>""),S55-T55,"") | V55: =IF(AND(U55<>"",S55<>"",S55<>0),U55/S55*100,"") | W55: =IF(AND(F55<>"",S55<>""),F55-S55,"") | X55: 1110988
A56: 2025 | B56: Oct | C56: 43 | D56: Oct 27 – Oct 31 | E56: 2025-10-27 | K56: =IF(AND(F56<>"",J56<>"",J56<>0),F56/J56*100,"") | U56: =IF(AND(S56<>"",T56<>""),S56-T56,"") | V56: =IF(AND(U56<>"",S56<>"",S56<>0),U56/S56*100,"") | W56: =IF(AND(F56<>"",S56<>""),F56-S56,"") | X56: 1392460
A57: 2025 | B57: Oct | D57: Oct 2025 TOTAL | F57: =IFERROR(SUM(F53:F56),"") -> 0 | G57: =IFERROR(SUM(G53:G56),"") -> 0 | H57: =IFERROR(LOOKUP(2,1/(H53:H56<>""),H53:H56),"") | I57: =IFERROR(LOOKUP(2,1/(I53:I56<>""),I53:I56),"") | J57: =IFERROR(LOOKUP(2,1/(J53:J56<>""),J53:J56),"") | K57: =IFERROR(LOOKUP(2,1/(K53:K56<>""),K53:K56),"") | L57: =IFERROR(SUM(L53:L56),"") -> 0 | M57: =IFERROR(SUM(M53:M56),"") -> 0 | N57: =IFERROR(SUM(N53:N56),"") -> 0 | O57: =IFERROR(SUM(O53:O56),"") -> 0 | P57: =IFERROR(SUM(P53:P56),"") -> 0 | Q57: =IFERROR(SUM(Q53:Q56),"") -> 0 | R57: =IFERROR(SUM(R53:R56),"") -> 0 | S57: =IFERROR(LOOKUP(2,1/(S53:S56<>""),S53:S56),"") | T57: =IFERROR(LOOKUP(2,1/(T53:T56<>""),T53:T56),"") | U57: =IFERROR(LOOKUP(2,1/(U53:U56<>""),U53:U56),"") | V57: =IFERROR(LOOKUP(2,1/(V53:V56<>""),V53:V56),"") | W57: =IFERROR(LOOKUP(2,1/(W53:W56<>""),W53:W56),"") | X57: =IFERROR(LOOKUP(2,1/(X53:X56<>""),X53:X56),"") -> 1392460 | Y57: =IFERROR(LOOKUP(2,1/(Y53:Y56<>""),Y53:Y56),"") | Z57: =IFERROR(LOOKUP(2,1/(Z53:Z56<>""),Z53:Z56),"") | ... AB57: =IFERROR(LOOKUP(2,1/(AB53:AB56<>""),AB53:AB56),"") | AC57: =IFERROR(SUM(AC53:AC56),"") -> 0 | AD57: =IFERROR(SUM(AD53:AD56),"") -> 0 | AE57: =IFERROR(LOOKUP(2,1/(AE53:AE56<>""),AE53:AE56),"") | AF57: =IFERROR(LOOKUP(2,1/(AF53:AF56<>""),AF53:AF56),"") | AG57: =IFERROR(LOOKUP(2,1/(AG53:AG56<>""),AG53:AG56),"") | AH57: =IFERROR(LOOKUP(2,1/(AH53:AH56<>""),AH53:AH56),"") | AI57: =IFERROR(LOOKUP(2,1/(AI53:AI56<>""),AI53:AI56),"") | AJ57: =IFERROR(LOOKUP(2,1/(AJ53:AJ56<>""),AJ53:AJ56),"") | AK57: =IFERROR(LOOKUP(2,1/(AK53:AK56<>""),AK53:AK56),"") | AL57: =IFERROR(LOOKUP(2,1/(AL53:AL56<>""),AL53:AL56),"") | ... AN57: =IFERROR(LOOKUP(2,1/(AN53:AN56<>""),AN53:AN56),"")
A58: 2025 | B58: Nov | C58: 44 | D58: Nov 03 – Nov 07 | E58: 2025-11-03 | K58: =IF(AND(F58<>"",J58<>"",J58<>0),F58/J58*100,"") | U58: =IF(AND(S58<>"",T58<>""),S58-T58,"") | V58: =IF(AND(U58<>"",S58<>"",S58<>0),U58/S58*100,"") | W58: =IF(AND(F58<>"",S58<>""),F58-S58,"") | X58: 1774834
A59: 2025 | B59: Nov | C59: 45 | D59: Nov 10 – Nov 14 | E59: 2025-11-10 | K59: =IF(AND(F59<>"",J59<>"",J59<>0),F59/J59*100,"") | U59: =IF(AND(S59<>"",T59<>""),S59-T59,"") | V59: =IF(AND(U59<>"",S59<>"",S59<>0),U59/S59*100,"") | W59: =IF(AND(F59<>"",S59<>""),F59-S59,"") | X59: 2240239
A60: 2025 | B60: Nov | C60: 46 | D60: Nov 17 – Nov 21 | E60: 2025-11-17 | K60: =IF(AND(F60<>"",J60<>"",J60<>0),F60/J60*100,"") | U60: =IF(AND(S60<>"",T60<>""),S60-T60,"") | V60: =IF(AND(U60<>"",S60<>"",S60<>0),U60/S60*100,"") | W60: =IF(AND(F60<>"",S60<>""),F60-S60,"") | X60: 3053626
A61: 2025 | B61: Nov | C61: 47 | D61: Nov 24 – Nov 28 | E61: 2025-11-24 | K61: =IF(AND(F61<>"",J61<>"",J61<>0),F61/J61*100,"") | U61: =IF(AND(S61<>"",T61<>""),S61-T61,"") | V61: =IF(AND(U61<>"",S61<>"",S61<>0),U61/S61*100,"") | W61: =IF(AND(F61<>"",S61<>""),F61-S61,"") | X61: 2992325
A62: 2025 | B62: Nov | D62: Nov 2025 TOTAL | F62: =IFERROR(SUM(F58:F61),"") -> 0 | G62: =IFERROR(SUM(G58:G61),"") -> 0 | H62: =IFERROR(LOOKUP(2,1/(H58:H61<>""),H58:H61),"") | I62: =IFERROR(LOOKUP(2,1/(I58:I61<>""),I58:I61),"") | J62: =IFERROR(LOOKUP(2,1/(J58:J61<>""),J58:J61),"") | K62: =IFERROR(LOOKUP(2,1/(K58:K61<>""),K58:K61),"") | L62: =IFERROR(SUM(L58:L61),"") -> 0 | M62: =IFERROR(SUM(M58:M61),"") -> 0 | N62: =IFERROR(SUM(N58:N61),"") -> 0 | O62: =IFERROR(SUM(O58:O61),"") -> 0 | P62: =IFERROR(SUM(P58:P61),"") -> 0 | Q62: =IFERROR(SUM(Q58:Q61),"") -> 0 | R62: =IFERROR(SUM(R58:R61),"") -> 0 | S62: =IFERROR(LOOKUP(2,1/(S58:S61<>""),S58:S61),"") | T62: =IFERROR(LOOKUP(2,1/(T58:T61<>""),T58:T61),"") | U62: =IFERROR(LOOKUP(2,1/(U58:U61<>""),U58:U61),"") | V62: =IFERROR(LOOKUP(2,1/(V58:V61<>""),V58:V61),"") | W62: =IFERROR(LOOKUP(2,1/(W58:W61<>""),W58:W61),"") | X62: =IFERROR(LOOKUP(2,1/(X58:X61<>""),X58:X61),"") -> 2992325 | Y62: =IFERROR(LOOKUP(2,1/(Y58:Y61<>""),Y58:Y61),"") | Z62: =IFERROR(LOOKUP(2,1/(Z58:Z61<>""),Z58:Z61),"") | ... AB62: =IFERROR(LOOKUP(2,1/(AB58:AB61<>""),AB58:AB61),"") | AC62: =IFERROR(SUM(AC58:AC61),"") -> 0 | AD62: =IFERROR(SUM(AD58:AD61),"") -> 0 | AE62: =IFERROR(LOOKUP(2,1/(AE58:AE61<>""),AE58:AE61),"") | AF62: =IFERROR(LOOKUP(2,1/(AF58:AF61<>""),AF58:AF61),"") | AG62: =IFERROR(LOOKUP(2,1/(AG58:AG61<>""),AG58:AG61),"") | AH62: =IFERROR(LOOKUP(2,1/(AH58:AH61<>""),AH58:AH61),"") | AI62: =IFERROR(LOOKUP(2,1/(AI58:AI61<>""),AI58:AI61),"") | AJ62: =IFERROR(LOOKUP(2,1/(AJ58:AJ61<>""),AJ58:AJ61),"") | AK62: =IFERROR(LOOKUP(2,1/(AK58:AK61<>""),AK58:AK61),"") | AL62: =IFERROR(LOOKUP(2,1/(AL58:AL61<>""),AL58:AL61),"") | ... AN62: =IFERROR(LOOKUP(2,1/(AN58:AN61<>""),AN58:AN61),"")
A63: 2025 | B63: Dec | C63: 48 | D63: Dec 01 – Dec 05 | E63: 2025-12-01 | K63: =IF(AND(F63<>"",J63<>"",J63<>0),F63/J63*100,"") | U63: =IF(AND(S63<>"",T63<>""),S63-T63,"") | V63: =IF(AND(U63<>"",S63<>"",S63<>0),U63/S63*100,"") | W63: =IF(AND(F63<>"",S63<>""),F63-S63,"") | X63: 3133802
A64: 2025 | B64: Dec | C64: 49 | D64: Dec 08 – Dec 12 | E64: 2025-12-08 | K64: =IF(AND(F64<>"",J64<>"",J64<>0),F64/J64*100,"") | U64: =IF(AND(S64<>"",T64<>""),S64-T64,"") | V64: =IF(AND(U64<>"",S64<>"",S64<>0),U64/S64*100,"") | W64: =IF(AND(F64<>"",S64<>""),F64-S64,"")
A65: 2025 | B65: Dec | C65: 50 | D65: Dec 15 – Dec 19 | E65: 2025-12-15 | K65: =IF(AND(F65<>"",J65<>"",J65<>0),F65/J65*100,"") | U65: =IF(AND(S65<>"",T65<>""),S65-T65,"") | V65: =IF(AND(U65<>"",S65<>"",S65<>0),U65/S65*100,"") | W65: =IF(AND(F65<>"",S65<>""),F65-S65,"")
A66: 2025 | B66: Dec | C66: 51 | D66: Dec 22 – Dec 26 | E66: 2025-12-22 | K66: =IF(AND(F66<>"",J66<>"",J66<>0),F66/J66*100,"") | U66: =IF(AND(S66<>"",T66<>""),S66-T66,"") | V66: =IF(AND(U66<>"",S66<>"",S66<>0),U66/S66*100,"") | W66: =IF(AND(F66<>"",S66<>""),F66-S66,"")
A67: 2025 | B67: Dec | C67: 52 | D67: Dec 29 – Jan 02 | E67: 2025-12-29 | K67: =IF(AND(F67<>"",J67<>"",J67<>0),F67/J67*100,"") | U67: =IF(AND(S67<>"",T67<>""),S67-T67,"") | V67: =IF(AND(U67<>"",S67<>"",S67<>0),U67/S67*100,"") | W67: =IF(AND(F67<>"",S67<>""),F67-S67,"")
A68: 2026 | B68: Jan | C68: 1 | D68: Jan 05 – Jan 09 | E68: 2026-01-05 | K68: =IF(AND(F68<>"",J68<>"",J68<>0),F68/J68*100,"") | U68: =IF(AND(S68<>"",T68<>""),S68-T68,"") | V68: =IF(AND(U68<>"",S68<>"",S68<>0),U68/S68*100,"") | W68: =IF(AND(F68<>"",S68<>""),F68-S68,"")
A69: 2026 | B69: Jan | C69: 2 | D69: Jan 12 – Jan 16 | E69: 2026-01-12 | K69: =IF(AND(F69<>"",J69<>"",J69<>0),F69/J69*100,"") | U69: =IF(AND(S69<>"",T69<>""),S69-T69,"") | V69: =IF(AND(U69<>"",S69<>"",S69<>0),U69/S69*100,"") | W69: =IF(AND(F69<>"",S69<>""),F69-S69,"")
A70: 2026 | B70: Jan | C70: 3 | D70: Jan 19 – Jan 23 | E70: 2026-01-19 | K70: =IF(AND(F70<>"",J70<>"",J70<>0),F70/J70*100,"") | U70: =IF(AND(S70<>"",T70<>""),S70-T70,"") | V70: =IF(AND(U70<>"",S70<>"",S70<>0),U70/S70*100,"") | W70: =IF(AND(F70<>"",S70<>""),F70-S70,"")
A71: 2026 | B71: Jan | C71: 4 | D71: Jan 26 – Jan 30 | E71: 2026-01-26 | K71: =IF(AND(F71<>"",J71<>"",J71<>0),F71/J71*100,"") | S71: 1385716 | T71: 855465 | U71: 530251 | V71: =IF(AND(U71<>"",S71<>"",S71<>0),U71/S71*100,"") -> 38.265489 | W71: =IF(AND(F71<>"",S71<>""),F71-S71,"") | X71: 3133802 | AB71: 32.8
A72: 2026 | B72: Jan | D72: Jan 2026 TOTAL | F72: =IFERROR(SUM(F68:F71),"") -> 0 | G72: =IFERROR(SUM(G68:G71),"") -> 0 | H72: =IFERROR(LOOKUP(2,1/(H68:H71<>""),H68:H71),"") | I72: =IFERROR(LOOKUP(2,1/(I68:I71<>""),I68:I71),"") | J72: =IFERROR(LOOKUP(2,1/(J68:J71<>""),J68:J71),"") | K72: =IFERROR(LOOKUP(2,1/(K68:K71<>""),K68:K71),"") | L72: =IFERROR(SUM(L68:L71),"") -> 0 | M72: =IFERROR(SUM(M68:M71),"") -> 0 | N72: =IFERROR(SUM(N68:N71),"") -> 0 | O72: =IFERROR(SUM(O68:O71),"") -> 0 | P72: =IFERROR(SUM(P68:P71),"") -> 0 | Q72: =IFERROR(SUM(Q68:Q71),"") -> 0 | R72: =IFERROR(SUM(R68:R71),"") -> 0 | S72: =IFERROR(LOOKUP(2,1/(S68:S71<>""),S68:S71),"") -> 1385716 | T72: =IFERROR(LOOKUP(2,1/(T68:T71<>""),T68:T71),"") -> 855465 | U72: =IFERROR(LOOKUP(2,1/(U68:U71<>""),U68:U71),"") -> 530251 | V72: =IFERROR(LOOKUP(2,1/(V68:V71<>""),V68:V71),"") -> 38.265489 | W72: =IFERROR(LOOKUP(2,1/(W68:W71<>""),W68:W71),"") | X72: =IFERROR(LOOKUP(2,1/(X68:X71<>""),X68:X71),"") -> 3133802 | Y72: =IFERROR(LOOKUP(2,1/(Y68:Y71<>""),Y68:Y71),"") | Z72: =IFERROR(LOOKUP(2,1/(Z68:Z71<>""),Z68:Z71),"") | ... AB72: =IFERROR(LOOKUP(2,1/(AB68:AB71<>""),AB68:AB71),"") -> 32.8 | AC72: =IFERROR(SUM(AC68:AC71),"") -> 0 | AD72: =IFERROR(SUM(AD68:AD71),"") -> 0 | AE72: =IFERROR(LOOKUP(2,1/(AE68:AE71<>""),AE68:AE71),"") | AF72: =IFERROR(LOOKUP(2,1/(AF68:AF71<>""),AF68:AF71),"") | AG72: =IFERROR(LOOKUP(2,1/(AG68:AG71<>""),AG68:AG71),"") | AH72: =IFERROR(LOOKUP(2,1/(AH68:AH71<>""),AH68:AH71),"") | AI72: =IFERROR(LOOKUP(2,1/(AI68:AI71<>""),AI68:AI71),"") | AJ72: =IFERROR(LOOKUP(2,1/(AJ68:AJ71<>""),AJ68:AJ71),"") | AK72: =IFERROR(LOOKUP(2,1/(AK68:AK71<>""),AK68:AK71),"") | AL72: =IFERROR(LOOKUP(2,1/(AL68:AL71<>""),AL68:AL71),"") | ... AN72: =IFERROR(LOOKUP(2,1/(AN68:AN71<>""),AN68:AN71),"")
A73: 2026 | B73: Feb | C73: 5 | D73: Feb 02 – Feb 06 | E73: 2026-02-02 | K73: =IF(AND(F73<>"",J73<>"",J73<>0),F73/J73*100,"") | U73: =IF(AND(S73<>"",T73<>""),S73-T73,"") | V73: =IF(AND(U73<>"",S73<>"",S73<>0),U73/S73*100,"") | W73: =IF(AND(F73<>"",S73<>""),F73-S73,"")
A74: 2026 | B74: Feb | C74: 6 | D74: Feb 09 – Feb 13 | E74: 2026-02-09 | K74: =IF(AND(F74<>"",J74<>"",J74<>0),F74/J74*100,"") | U74: =IF(AND(S74<>"",T74<>""),S74-T74,"") | V74: =IF(AND(U74<>"",S74<>"",S74<>0),U74/S74*100,"") | W74: =IF(AND(F74<>"",S74<>""),F74-S74,"")
A75: 2026 | B75: Feb | C75: 7 | D75: Feb 16 – Feb 20 | E75: 2026-02-16 | K75: =IF(AND(F75<>"",J75<>"",J75<>0),F75/J75*100,"") | U75: =IF(AND(S75<>"",T75<>""),S75-T75,"") | V75: =IF(AND(U75<>"",S75<>"",S75<>0),U75/S75*100,"") | W75: =IF(AND(F75<>"",S75<>""),F75-S75,"")
A76: 2026 | B76: Feb | C76: 8 | D76: Feb 23 – Feb 27 | E76: 2026-02-23 | F76: 782928 | G76: 384814 | H76: 33176 | I76: 398114 | J76: 753233 | K76: =IF(AND(F76<>"",J76<>"",J76<>0),F76/J76*100,"") -> 103.94234 | L76: 208743 | M76: 204237 | N76: 158604 | O76: 125747 | P76: 79177 | Q76: 5913 | R76: 508 | S76: 1292505 | T76: 678686 | U76: 613819 | V76: =IF(AND(U76<>"",S76<>"",S76<>0),U76/S76*100,"") -> 47.490648 | W76: =IF(AND(F76<>"",S76<>""),F76-S76,"") -> -509577 | X76: 3076658 | Y76: 40 | Z76: 1432806 | AA76: 5207610 | AB76: 24.5 | AG76: 96.9 | AK76: 453948 | AL76: 16 | AM76: 29 | AN76: 396
A77: 2026 | B77: Feb | D77: Feb 2026 TOTAL | F77: =IFERROR(SUM(F73:F76),"") -> 782928 | G77: =IFERROR(SUM(G73:G76),"") -> 384814 | H77: =IFERROR(LOOKUP(2,1/(H73:H76<>""),H73:H76),"") -> 33176 | I77: =IFERROR(LOOKUP(2,1/(I73:I76<>""),I73:I76),"") -> 398114 | J77: =IFERROR(LOOKUP(2,1/(J73:J76<>""),J73:J76),"") -> 753233 | K77: =IFERROR(LOOKUP(2,1/(K73:K76<>""),K73:K76),"") -> 103.94234 | L77: =IFERROR(SUM(L73:L76),"") -> 208743 | M77: =IFERROR(SUM(M73:M76),"") -> 204237 | N77: =IFERROR(SUM(N73:N76),"") -> 158604 | O77: =IFERROR(SUM(O73:O76),"") -> 125747 | P77: =IFERROR(SUM(P73:P76),"") -> 79177 | Q77: =IFERROR(SUM(Q73:Q76),"") -> 5913 | R77: =IFERROR(SUM(R73:R76),"") -> 508 | S77: =IFERROR(LOOKUP(2,1/(S73:S76<>""),S73:S76),"") -> 1292505 | T77: =IFERROR(LOOKUP(2,1/(T73:T76<>""),T73:T76),"") -> 678686 | U77: =IFERROR(LOOKUP(2,1/(U73:U76<>""),U73:U76),"") -> 613819 | V77: =IFERROR(LOOKUP(2,1/(V73:V76<>""),V73:V76),"") -> 47.490648 | W77: =IFERROR(LOOKUP(2,1/(W73:W76<>""),W73:W76),"") -> -509577 | X77: =IFERROR(LOOKUP(2,1/(X73:X76<>""),X73:X76),"") -> 3076658 | Y77: =IFERROR(LOOKUP(2,1/(Y73:Y76<>""),Y73:Y76),"") -> 40 | Z77: =IFERROR(LOOKUP(2,1/(Z73:Z76<>""),Z73:Z76),"") -> 1432806 | ... AB77: =IFERROR(LOOKUP(2,1/(AB73:AB76<>""),AB73:AB76),"") -> 24.5 | AC77: =IFERROR(SUM(AC73:AC76),"") -> 0 | AD77: =IFERROR(SUM(AD73:AD76),"") -> 0 | AE77: =IFERROR(LOOKUP(2,1/(AE73:AE76<>""),AE73:AE76),"") | AF77: =IFERROR(LOOKUP(2,1/(AF73:AF76<>""),AF73:AF76),"") | AG77: =IFERROR(LOOKUP(2,1/(AG73:AG76<>""),AG73:AG76),"") -> 96.9 | AH77: =IFERROR(LOOKUP(2,1/(AH73:AH76<>""),AH73:AH76),"") | AI77: =IFERROR(LOOKUP(2,1/(AI73:AI76<>""),AI73:AI76),"") | AJ77: =IFERROR(LOOKUP(2,1/(AJ73:AJ76<>""),AJ73:AJ76),"") | AK77: =IFERROR(LOOKUP(2,1/(AK73:AK76<>""),AK73:AK76),"") -> 453948 | AL77: =IFERROR(LOOKUP(2,1/(AL73:AL76<>""),AL73:AL76),"") -> 16 | ... AN77: =IFERROR(LOOKUP(2,1/(AN73:AN76<>""),AN73:AN76),"") -> 396
A78: 2026 | B78: Mar | C78: 9 | D78: Mar 02 – Mar 06 | E78: 2026-03-02 | K78: =IF(AND(F78<>"",J78<>"",J78<>0),F78/J78*100,"") | U78: =IF(AND(S78<>"",T78<>""),S78-T78,"") | V78: =IF(AND(U78<>"",S78<>"",S78<>0),U78/S78*100,"") | W78: =IF(AND(F78<>"",S78<>""),F78-S78,"") | AC78: 532 | AD78: 532 | AE78: 187 | AF78: 5.66 | AG78: 92.7 | AH78: 70 | AI78: 57.5 | AJ78: 63.5
A79: 2026 | B79: Mar | C79: 10 | D79: Mar 09 – Mar 13 | E79: 2026-03-09 | K79: =IF(AND(F79<>"",J79<>"",J79<>0),F79/J79*100,"") | U79: =IF(AND(S79<>"",T79<>""),S79-T79,"") | V79: =IF(AND(U79<>"",S79<>"",S79<>0),U79/S79*100,"") | W79: =IF(AND(F79<>"",S79<>""),F79-S79,"")
A80: 2026 | B80: Mar | C80: 11 | D80: Mar 16 – Mar 20 | E80: 2026-03-16 | K80: =IF(AND(F80<>"",J80<>"",J80<>0),F80/J80*100,"") | U80: =IF(AND(S80<>"",T80<>""),S80-T80,"") | V80: =IF(AND(U80<>"",S80<>"",S80<>0),U80/S80*100,"") | W80: =IF(AND(F80<>"",S80<>""),F80-S80,"")
A81: 2026 | B81: Mar | C81: 12 | D81: Mar 23 – Mar 27 | E81: 2026-03-23 | K81: =IF(AND(F81<>"",J81<>"",J81<>0),F81/J81*100,"") | U81: =IF(AND(S81<>"",T81<>""),S81-T81,"") | V81: =IF(AND(U81<>"",S81<>"",S81<>0),U81/S81*100,"") | W81: =IF(AND(F81<>"",S81<>""),F81-S81,"") | AG81: 92.2 | AK81: 453948 | AN81: 396
A82: 2026 | B82: Mar | C82: 13 | D82: Mar 30 – Apr 03 | E82: 2026-03-30 | K82: =IF(AND(F82<>"",J82<>"",J82<>0),F82/J82*100,"") | U82: =IF(AND(S82<>"",T82<>""),S82-T82,"") | V82: =IF(AND(U82<>"",S82<>"",S82<>0),U82/S82*100,"") | W82: =IF(AND(F82<>"",S82<>""),F82-S82,"")
A83: 2026 | B83: Mar | D83: Mar 2026 TOTAL | F83: =IFERROR(SUM(F78:F82),"") -> 0 | G83: =IFERROR(SUM(G78:G82),"") -> 0 | H83: =IFERROR(LOOKUP(2,1/(H78:H82<>""),H78:H82),"") | I83: =IFERROR(LOOKUP(2,1/(I78:I82<>""),I78:I82),"") | J83: =IFERROR(LOOKUP(2,1/(J78:J82<>""),J78:J82),"") | K83: =IFERROR(LOOKUP(2,1/(K78:K82<>""),K78:K82),"") | L83: =IFERROR(SUM(L78:L82),"") -> 0 | M83: =IFERROR(SUM(M78:M82),"") -> 0 | N83: =IFERROR(SUM(N78:N82),"") -> 0 | O83: =IFERROR(SUM(O78:O82),"") -> 0 | P83: =IFERROR(SUM(P78:P82),"") -> 0 | Q83: =IFERROR(SUM(Q78:Q82),"") -> 0 | R83: =IFERROR(SUM(R78:R82),"") -> 0 | S83: =IFERROR(LOOKUP(2,1/(S78:S82<>""),S78:S82),"") | T83: =IFERROR(LOOKUP(2,1/(T78:T82<>""),T78:T82),"") | U83: =IFERROR(LOOKUP(2,1/(U78:U82<>""),U78:U82),"") | V83: =IFERROR(LOOKUP(2,1/(V78:V82<>""),V78:V82),"") | W83: =IFERROR(LOOKUP(2,1/(W78:W82<>""),W78:W82),"") | X83: =IFERROR(LOOKUP(2,1/(X78:X82<>""),X78:X82),"") | Y83: =IFERROR(LOOKUP(2,1/(Y78:Y82<>""),Y78:Y82),"") | Z83: =IFERROR(LOOKUP(2,1/(Z78:Z82<>""),Z78:Z82),"") | ... AB83: =IFERROR(LOOKUP(2,1/(AB78:AB82<>""),AB78:AB82),"") | AC83: =IFERROR(SUM(AC78:AC82),"") -> 532 | AD83: =IFERROR(SUM(AD78:AD82),"") -> 532 | AE83: =IFERROR(LOOKUP(2,1/(AE78:AE82<>""),AE78:AE82),"") -> 187 | AF83: =IFERROR(LOOKUP(2,1/(AF78:AF82<>""),AF78:AF82),"") -> 5.66 | AG83: =IFERROR(LOOKUP(2,1/(AG78:AG82<>""),AG78:AG82),"") -> 92.2 | AH83: =IFERROR(LOOKUP(2,1/(AH78:AH82<>""),AH78:AH82),"") -> 70 | AI83: =IFERROR(LOOKUP(2,1/(AI78:AI82<>""),AI78:AI82),"") -> 57.5 | AJ83: =IFERROR(LOOKUP(2,1/(AJ78:AJ82<>""),AJ78:AJ82),"") -> 63.5 | AK83: =IFERROR(LOOKUP(2,1/(AK78:AK82<>""),AK78:AK82),"") -> 453948 | AL83: =IFERROR(LOOKUP(2,1/(AL78:AL82<>""),AL78:AL82),"") | ... AN83: =IFERROR(LOOKUP(2,1/(AN78:AN82<>""),AN78:AN82),"") -> 396
A84: 2026 | B84: Apr | C84: 14 | D84: Apr 06 – Apr 10 | E84: 2026-04-06 | K84: =IF(AND(F84<>"",J84<>"",J84<>0),F84/J84*100,"") | U84: =IF(AND(S84<>"",T84<>""),S84-T84,"") | V84: =IF(AND(U84<>"",S84<>"",S84<>0),U84/S84*100,"") | W84: =IF(AND(F84<>"",S84<>""),F84-S84,"")
A85: 2026 | B85: Apr | C85: 15 | D85: Apr 13 – Apr 17 | E85: 2026-04-13 | K85: =IF(AND(F85<>"",J85<>"",J85<>0),F85/J85*100,"") | U85: =IF(AND(S85<>"",T85<>""),S85-T85,"") | V85: =IF(AND(U85<>"",S85<>"",S85<>0),U85/S85*100,"") | W85: =IF(AND(F85<>"",S85<>""),F85-S85,"")
A86: 2026 | B86: Apr | C86: 16 | D86: Apr 20 – Apr 24 | E86: 2026-04-20 | K86: =IF(AND(F86<>"",J86<>"",J86<>0),F86/J86*100,"") | U86: =IF(AND(S86<>"",T86<>""),S86-T86,"") | V86: =IF(AND(U86<>"",S86<>"",S86<>0),U86/S86*100,"") | W86: =IF(AND(F86<>"",S86<>""),F86-S86,"")
A87: 2026 | B87: Apr | C87: 17 | D87: Apr 27 – May 01 | E87: 2026-04-27 | K87: =IF(AND(F87<>"",J87<>"",J87<>0),F87/J87*100,"") | U87: =IF(AND(S87<>"",T87<>""),S87-T87,"") | V87: =IF(AND(U87<>"",S87<>"",S87<>0),U87/S87*100,"") | W87: =IF(AND(F87<>"",S87<>""),F87-S87,"")
A88: 2026 | B88: Apr | D88: Apr 2026 TOTAL | F88: =IFERROR(SUM(F84:F87),"") -> 0 | G88: =IFERROR(SUM(G84:G87),"") -> 0 | H88: =IFERROR(LOOKUP(2,1/(H84:H87<>""),H84:H87),"") | I88: =IFERROR(LOOKUP(2,1/(I84:I87<>""),I84:I87),"") | J88: =IFERROR(LOOKUP(2,1/(J84:J87<>""),J84:J87),"") | K88: =IFERROR(LOOKUP(2,1/(K84:K87<>""),K84:K87),"") | L88: =IFERROR(SUM(L84:L87),"") -> 0 | M88: =IFERROR(SUM(M84:M87),"") -> 0 | N88: =IFERROR(SUM(N84:N87),"") -> 0 | O88: =IFERROR(SUM(O84:O87),"") -> 0 | P88: =IFERROR(SUM(P84:P87),"") -> 0 | Q88: =IFERROR(SUM(Q84:Q87),"") -> 0 | R88: =IFERROR(SUM(R84:R87),"") -> 0 | S88: =IFERROR(LOOKUP(2,1/(S84:S87<>""),S84:S87),"") | T88: =IFERROR(LOOKUP(2,1/(T84:T87<>""),T84:T87),"") | U88: =IFERROR(LOOKUP(2,1/(U84:U87<>""),U84:U87),"") | V88: =IFERROR(LOOKUP(2,1/(V84:V87<>""),V84:V87),"") | W88: =IFERROR(LOOKUP(2,1/(W84:W87<>""),W84:W87),"") | X88: =IFERROR(LOOKUP(2,1/(X84:X87<>""),X84:X87),"") | Y88: =IFERROR(LOOKUP(2,1/(Y84:Y87<>""),Y84:Y87),"") | Z88: =IFERROR(LOOKUP(2,1/(Z84:Z87<>""),Z84:Z87),"") | ... AB88: =IFERROR(LOOKUP(2,1/(AB84:AB87<>""),AB84:AB87),"") | AC88: =IFERROR(SUM(AC84:AC87),"") -> 0 | AD88: =IFERROR(SUM(AD84:AD87),"") -> 0 | AE88: =IFERROR(LOOKUP(2,1/(AE84:AE87<>""),AE84:AE87),"") | AF88: =IFERROR(LOOKUP(2,1/(AF84:AF87<>""),AF84:AF87),"") | AG88: =IFERROR(LOOKUP(2,1/(AG84:AG87<>""),AG84:AG87),"") | AH88: =IFERROR(LOOKUP(2,1/(AH84:AH87<>""),AH84:AH87),"") | AI88: =IFERROR(LOOKUP(2,1/(AI84:AI87<>""),AI84:AI87),"") | AJ88: =IFERROR(LOOKUP(2,1/(AJ84:AJ87<>""),AJ84:AJ87),"") | AK88: =IFERROR(LOOKUP(2,1/(AK84:AK87<>""),AK84:AK87),"") | AL88: =IFERROR(LOOKUP(2,1/(AL84:AL87<>""),AL84:AL87),"") | ... AN88: =IFERROR(LOOKUP(2,1/(AN84:AN87<>""),AN84:AN87),"")
A89: 2026 | B89: May | C89: 18 | D89: May 04 – May 08 | E89: 2026-05-04 | K89: =IF(AND(F89<>"",J89<>"",J89<>0),F89/J89*100,"") | U89: =IF(AND(S89<>"",T89<>""),S89-T89,"") | V89: =IF(AND(U89<>"",S89<>"",S89<>0),U89/S89*100,"") | W89: =IF(AND(F89<>"",S89<>""),F89-S89,"")
A90: 2026 | B90: May | C90: 19 | D90: May 11 – May 15 | E90: 2026-05-11 | K90: =IF(AND(F90<>"",J90<>"",J90<>0),F90/J90*100,"") | U90: =IF(AND(S90<>"",T90<>""),S90-T90,"") | V90: =IF(AND(U90<>"",S90<>"",S90<>0),U90/S90*100,"") | W90: =IF(AND(F90<>"",S90<>""),F90-S90,"")
A91: 2026 | B91: May | C91: 20 | D91: May 18 – May 22 | E91: 2026-05-18 | K91: =IF(AND(F91<>"",J91<>"",J91<>0),F91/J91*100,"") | U91: =IF(AND(S91<>"",T91<>""),S91-T91,"") | V91: =IF(AND(U91<>"",S91<>"",S91<>0),U91/S91*100,"") | W91: =IF(AND(F91<>"",S91<>""),F91-S91,"")
A92: 2026 | B92: May | C92: 21 | D92: May 25 – May 29 | E92: 2026-05-25 | K92: =IF(AND(F92<>"",J92<>"",J92<>0),F92/J92*100,"") | U92: =IF(AND(S92<>"",T92<>""),S92-T92,"") | V92: =IF(AND(U92<>"",S92<>"",S92<>0),U92/S92*100,"") | W92: =IF(AND(F92<>"",S92<>""),F92-S92,"")
A93: 2026 | B93: May | D93: May 2026 TOTAL | F93: =IFERROR(SUM(F89:F92),"") -> 0 | G93: =IFERROR(SUM(G89:G92),"") -> 0 | H93: =IFERROR(LOOKUP(2,1/(H89:H92<>""),H89:H92),"") | I93: =IFERROR(LOOKUP(2,1/(I89:I92<>""),I89:I92),"") | J93: =IFERROR(LOOKUP(2,1/(J89:J92<>""),J89:J92),"") | K93: =IFERROR(LOOKUP(2,1/(K89:K92<>""),K89:K92),"") | L93: =IFERROR(SUM(L89:L92),"") -> 0 | M93: =IFERROR(SUM(M89:M92),"") -> 0 | N93: =IFERROR(SUM(N89:N92),"") -> 0 | O93: =IFERROR(SUM(O89:O92),"") -> 0 | P93: =IFERROR(SUM(P89:P92),"") -> 0 | Q93: =IFERROR(SUM(Q89:Q92),"") -> 0 | R93: =IFERROR(SUM(R89:R92),"") -> 0 | S93: =IFERROR(LOOKUP(2,1/(S89:S92<>""),S89:S92),"") | T93: =IFERROR(LOOKUP(2,1/(T89:T92<>""),T89:T92),"") | U93: =IFERROR(LOOKUP(2,1/(U89:U92<>""),U89:U92),"") | V93: =IFERROR(LOOKUP(2,1/(V89:V92<>""),V89:V92),"") | W93: =IFERROR(LOOKUP(2,1/(W89:W92<>""),W89:W92),"") | X93: =IFERROR(LOOKUP(2,1/(X89:X92<>""),X89:X92),"") | Y93: =IFERROR(LOOKUP(2,1/(Y89:Y92<>""),Y89:Y92),"") | Z93: =IFERROR(LOOKUP(2,1/(Z89:Z92<>""),Z89:Z92),"") | ... AB93: =IFERROR(LOOKUP(2,1/(AB89:AB92<>""),AB89:AB92),"") | AC93: =IFERROR(SUM(AC89:AC92),"") -> 0 | AD93: =IFERROR(SUM(AD89:AD92),"") -> 0 | AE93: =IFERROR(LOOKUP(2,1/(AE89:AE92<>""),AE89:AE92),"") | AF93: =IFERROR(LOOKUP(2,1/(AF89:AF92<>""),AF89:AF92),"") | AG93: =IFERROR(LOOKUP(2,1/(AG89:AG92<>""),AG89:AG92),"") | AH93: =IFERROR(LOOKUP(2,1/(AH89:AH92<>""),AH89:AH92),"") | AI93: =IFERROR(LOOKUP(2,1/(AI89:AI92<>""),AI89:AI92),"") | AJ93: =IFERROR(LOOKUP(2,1/(AJ89:AJ92<>""),AJ89:AJ92),"") | AK93: =IFERROR(LOOKUP(2,1/(AK89:AK92<>""),AK89:AK92),"") | AL93: =IFERROR(LOOKUP(2,1/(AL89:AL92<>""),AL89:AL92),"") | ... AN93: =IFERROR(LOOKUP(2,1/(AN89:AN92<>""),AN89:AN92),"")
A94: 2026 | B94: Jun | C94: 22 | D94: Jun 01 – Jun 05 | E94: 2026-06-01 | K94: =IF(AND(F94<>"",J94<>"",J94<>0),F94/J94*100,"") | U94: =IF(AND(S94<>"",T94<>""),S94-T94,"") | V94: =IF(AND(U94<>"",S94<>"",S94<>0),U94/S94*100,"") | W94: =IF(AND(F94<>"",S94<>""),F94-S94,"")
A95: 2026 | B95: Jun | C95: 23 | D95: Jun 08 – Jun 12 | E95: 2026-06-08 | K95: =IF(AND(F95<>"",J95<>"",J95<>0),F95/J95*100,"") | U95: =IF(AND(S95<>"",T95<>""),S95-T95,"") | V95: =IF(AND(U95<>"",S95<>"",S95<>0),U95/S95*100,"") | W95: =IF(AND(F95<>"",S95<>""),F95-S95,"")
A96: 2026 | B96: Jun | C96: 24 | D96: Jun 15 – Jun 19 | E96: 2026-06-15 | K96: =IF(AND(F96<>"",J96<>"",J96<>0),F96/J96*100,"") | U96: =IF(AND(S96<>"",T96<>""),S96-T96,"") | V96: =IF(AND(U96<>"",S96<>"",S96<>0),U96/S96*100,"") | W96: =IF(AND(F96<>"",S96<>""),F96-S96,"")
A97: 2026 | B97: Jun | C97: 25 | D97: Jun 22 – Jun 26 | E97: 2026-06-22 | K97: =IF(AND(F97<>"",J97<>"",J97<>0),F97/J97*100,"") | U97: =IF(AND(S97<>"",T97<>""),S97-T97,"") | V97: =IF(AND(U97<>"",S97<>"",S97<>0),U97/S97*100,"") | W97: =IF(AND(F97<>"",S97<>""),F97-S97,"")
A98: 2026 | B98: Jun | C98: 26 | D98: Jun 29 – Jul 03 | E98: 2026-06-29 | K98: =IF(AND(F98<>"",J98<>"",J98<>0),F98/J98*100,"") | U98: =IF(AND(S98<>"",T98<>""),S98-T98,"") | V98: =IF(AND(U98<>"",S98<>"",S98<>0),U98/S98*100,"") | W98: =IF(AND(F98<>"",S98<>""),F98-S98,"")
A99: 2026 | B99: Jun | D99: Jun 2026 TOTAL | F99: =IFERROR(SUM(F94:F98),"") -> 0 | G99: =IFERROR(SUM(G94:G98),"") -> 0 | H99: =IFERROR(LOOKUP(2,1/(H94:H98<>""),H94:H98),"") | I99: =IFERROR(LOOKUP(2,1/(I94:I98<>""),I94:I98),"") | J99: =IFERROR(LOOKUP(2,1/(J94:J98<>""),J94:J98),"") | K99: =IFERROR(LOOKUP(2,1/(K94:K98<>""),K94:K98),"") | L99: =IFERROR(SUM(L94:L98),"") -> 0 | M99: =IFERROR(SUM(M94:M98),"") -> 0 | N99: =IFERROR(SUM(N94:N98),"") -> 0 | O99: =IFERROR(SUM(O94:O98),"") -> 0 | P99: =IFERROR(SUM(P94:P98),"") -> 0 | Q99: =IFERROR(SUM(Q94:Q98),"") -> 0 | R99: =IFERROR(SUM(R94:R98),"") -> 0 | S99: =IFERROR(LOOKUP(2,1/(S94:S98<>""),S94:S98),"") | T99: =IFERROR(LOOKUP(2,1/(T94:T98<>""),T94:T98),"") | U99: =IFERROR(LOOKUP(2,1/(U94:U98<>""),U94:U98),"") | V99: =IFERROR(LOOKUP(2,1/(V94:V98<>""),V94:V98),"") | W99: =IFERROR(LOOKUP(2,1/(W94:W98<>""),W94:W98),"") | X99: =IFERROR(LOOKUP(2,1/(X94:X98<>""),X94:X98),"") | Y99: =IFERROR(LOOKUP(2,1/(Y94:Y98<>""),Y94:Y98),"") | Z99: =IFERROR(LOOKUP(2,1/(Z94:Z98<>""),Z94:Z98),"") | ... AB99: =IFERROR(LOOKUP(2,1/(AB94:AB98<>""),AB94:AB98),"") | AC99: =IFERROR(SUM(AC94:AC98),"") -> 0 | AD99: =IFERROR(SUM(AD94:AD98),"") -> 0 | AE99: =IFERROR(LOOKUP(2,1/(AE94:AE98<>""),AE94:AE98),"") | AF99: =IFERROR(LOOKUP(2,1/(AF94:AF98<>""),AF94:AF98),"") | AG99: =IFERROR(LOOKUP(2,1/(AG94:AG98<>""),AG94:AG98),"") | AH99: =IFERROR(LOOKUP(2,1/(AH94:AH98<>""),AH94:AH98),"") | AI99: =IFERROR(LOOKUP(2,1/(AI94:AI98<>""),AI94:AI98),"") | AJ99: =IFERROR(LOOKUP(2,1/(AJ94:AJ98<>""),AJ94:AJ98),"") | AK99: =IFERROR(LOOKUP(2,1/(AK94:AK98<>""),AK94:AK98),"") | AL99: =IFERROR(LOOKUP(2,1/(AL94:AL98<>""),AL94:AL98),"") | ... AN99: =IFERROR(LOOKUP(2,1/(AN94:AN98<>""),AN94:AN98),"")
A100: 2026 | B100: Jul | C100: 27 | D100: Jul 06 – Jul 10 | E100: 2026-07-06 | K100: =IF(AND(F100<>"",J100<>"",J100<>0),F100/J100*100,"") | U100: =IF(AND(S100<>"",T100<>""),S100-T100,"") | V100: =IF(AND(U100<>"",S100<>"",S100<>0),U100/S100*100,"") | W100: =IF(AND(F100<>"",S100<>""),F100-S100,"")
...

Sheet Monthly Dashboard
A1: DataPath — Monthly Dashboard (Auto-Populated from Weekly Data)
A2: All values auto-calculated from Weekly Data sheet. Cumulative metrics (revenue, tickets) are summed; snapshot metrics (cash, utilization) use end-of-month value.
A4: ── 2025 ──
A5: Metric | B5: Jan | C5: Feb | D5: Mar | E5: Apr | F5: May | G5: Jun | H5: Jul | I5: Aug | J5: Sep | K5: Oct | L5: Nov | M5: Dec | N5: YTD
A6: Total Revenue Won | B6: ='Weekly Data'!F9 -> 0 | C6: ='Weekly Data'!F14 -> 0 | D6: ='Weekly Data'!F20 -> 0 | E6: ='Weekly Data'!F25 -> 0 | F6: ='Weekly Data'!F30 -> 0 | G6: ='Weekly Data'!F36 -> 0 | H6: ='Weekly Data'!F41 -> 0 | I6: ='Weekly Data'!F46 -> 0 | J6: ='Weekly Data'!F52 -> 0 | K6: ='Weekly Data'!F57 -> 0 | L6: ='Weekly Data'!F62 -> 0 | N6: =SUM(B6:M6) -> 0
A7: NRR | B7: ='Weekly Data'!G9 -> 0 | C7: ='Weekly Data'!G14 -> 0 | D7: ='Weekly Data'!G20 -> 0 | E7: ='Weekly Data'!G25 -> 0 | F7: ='Weekly Data'!G30 -> 0 | G7: ='Weekly Data'!G36 -> 0 | H7: ='Weekly Data'!G41 -> 0 | I7: ='Weekly Data'!G46 -> 0 | J7: ='Weekly Data'!G52 -> 0 | K7: ='Weekly Data'!G57 -> 0 | L7: ='Weekly Data'!G62 -> 0 | N7: =SUM(B7:M7) -> 0
A8: Recurring Revenue (Mo) | B8: ='Weekly Data'!H9 | C8: ='Weekly Data'!H14 | D8: ='Weekly Data'!H20 | E8: ='Weekly Data'!H25 | F8: ='Weekly Data'!H30 | G8: ='Weekly Data'!H36 | H8: ='Weekly Data'!H41 | I8: ='Weekly Data'!H46 | J8: ='Weekly Data'!H52 | K8: ='Weekly Data'!H57 | L8: ='Weekly Data'!H62 | N8: =IFERROR(LOOKUP(2,1/(B8:M8<>""),B8:M8),"")
A9: P&L Gross Sales | B9: ='Weekly Data'!S9 | C9: ='Weekly Data'!S14 | D9: ='Weekly Data'!S20 | E9: ='Weekly Data'!S25 | F9: ='Weekly Data'!S30 | G9: ='Weekly Data'!S36 | H9: ='Weekly Data'!S41 | I9: ='Weekly Data'!S46 | J9: ='Weekly Data'!S52 | K9: ='Weekly Data'!S57 | L9: ='Weekly Data'!S62 | N9: =IFERROR(LOOKUP(2,1/(B9:M9<>""),B9:M9),"")
A10: P&L Gross Margin | B10: ='Weekly Data'!U9 | C10: ='Weekly Data'!U14 | D10: ='Weekly Data'!U20 | E10: ='Weekly Data'!U25 | F10: ='Weekly Data'!U30 | G10: ='Weekly Data'!U36 | H10: ='Weekly Data'!U41 | I10: ='Weekly Data'!U46 | J10: ='Weekly Data'!U52 | K10: ='Weekly Data'!U57 | L10: ='Weekly Data'!U62 | N10: =IFERROR(LOOKUP(2,1/(B10:M10<>""),B10:M10),"")
A11: P&L GM % | B11: ='Weekly Data'!V9 | C11: ='Weekly Data'!V14 | D11: ='Weekly Data'!V20 | E11: ='Weekly Data'!V25 | F11: ='Weekly Data'!V30 | G11: ='Weekly Data'!V36 | H11: ='Weekly Data'!V41 | I11: ='Weekly Data'!V46 | J11: ='Weekly Data'!V52 | K11: ='Weekly Data'!V57 | L11: ='Weekly Data'!V62 | N11: =IFERROR(AVERAGE(B11:M11),"")
A12: Won vs Billed Gap | B12: ='Weekly Data'!W9 | C12: ='Weekly Data'!W14 | D12: ='Weekly Data'!W20 | E12: ='Weekly Data'!W25 | F12: ='Weekly Data'!W30 | G12: ='Weekly Data'!W36 | H12: ='Weekly Data'!W41 | I12: ='Weekly Data'!W46 | J12: ='Weekly Data'!W52 | K12: ='Weekly Data'!W57 | L12: ='Weekly Data'!W62 | N12: =IFERROR(LOOKUP(2,1/(B12:M12<>""),B12:M12),"")
A13: Cash on Hand | B13: ='Weekly Data'!X9 | C13: ='Weekly Data'!X14 | D13: ='Weekly Data'!X20 | E13: ='Weekly Data'!X25 | F13: ='Weekly Data'!X30 | G13: ='Weekly Data'!X36 | H13: ='Weekly Data'!X41 | I13: ='Weekly Data'!X46 | J13: ='Weekly Data'!X52 -> 296137 | K13: ='Weekly Data'!X57 -> 1392460 | L13: ='Weekly Data'!X62 -> 2992325 | N13: =IFERROR(LOOKUP(2,1/(B13:M13<>""),B13:M13),"") -> 2992325
A14: DSO | B14: ='Weekly Data'!Y9 | C14: ='Weekly Data'!Y14 | D14: ='Weekly Data'!Y20 | E14: ='Weekly Data'!Y25 | F14: ='Weekly Data'!Y30 | G14: ='Weekly Data'!Y36 | H14: ='Weekly Data'!Y41 | I14: ='Weekly Data'!Y46 | J14: ='Weekly Data'!Y52 | K14: ='Weekly Data'!Y57 | L14: ='Weekly Data'!Y62 | N14: =IFERROR(LOOKUP(2,1/(B14:M14<>""),B14:M14),"")
A15: AR Total | B15: ='Weekly Data'!Z9 | C15: ='Weekly Data'!Z14 | D15: ='Weekly Data'!Z20 | E15: ='Weekly Data'!Z25 | F15: ='Weekly Data'!Z30 | G15: ='Weekly Data'!Z36 | H15: ='Weekly Data'!Z41 | I15: ='Weekly Data'!Z46 | J15: ='Weekly Data'!Z52 | K15: ='Weekly Data'!Z57 | L15: ='Weekly Data'!Z62 | N15: =IFERROR(LOOKUP(2,1/(B15:M15<>""),B15:M15),"")
A16: AP Total | B16: ='Weekly Data'!AA9 | C16: ='Weekly Data'!AA14 | D16: ='Weekly Data'!AA20 | E16: ='Weekly Data'!AA25 | F16: ='Weekly Data'!AA30 | G16: ='Weekly Data'!AA36 | H16: ='Weekly Data'!AA41 | I16: ='Weekly Data'!AA46 | J16: ='Weekly Data'!AA52 | K16: ='Weekly Data'!AA57 | L16: ='Weekly Data'!AA62 | N16: =IFERROR(LOOKUP(2,1/(B16:M16<>""),B16:M16),"")
A17: Payroll % Revenue | B17: ='Weekly Data'!AB9 | C17: ='Weekly Data'!AB14 | D17: ='Weekly Data'!AB20 | E17: ='Weekly Data'!AB25 | F17: ='Weekly Data'!AB30 | G17: ='Weekly Data'!AB36 | H17: ='Weekly Data'!AB41 | I17: ='Weekly Data'!AB46 | J17: ='Weekly Data'!AB52 | K17: ='Weekly Data'!AB57 | L17: ='Weekly Data'!AB62 | N17: =IFERROR(AVERAGE(B17:M17),"")
A18: Tickets Created | B18: ='Weekly Data'!AC9 -> 0 | C18: ='Weekly Data'!AC14 -> 0 | D18: ='Weekly Data'!AC20 -> 0 | E18: ='Weekly Data'!AC25 -> 0 | F18: ='Weekly Data'!AC30 -> 0 | G18: ='Weekly Data'!AC36 -> 0 | H18: ='Weekly Data'!AC41 -> 0 | I18: ='Weekly Data'!AC46 -> 0 | J18: ='Weekly Data'!AC52 -> 0 | K18: ='Weekly Data'!AC57 -> 0 | L18: ='Weekly Data'!AC62 -> 0 | N18: =SUM(B18:M18) -> 0
A19: Tickets Resolved | B19: ='Weekly Data'!AD9 -> 0 | C19: ='Weekly Data'!AD14 -> 0 | D19: ='Weekly Data'!AD20 -> 0 | E19: ='Weekly Data'!AD25 -> 0 | F19: ='Weekly Data'!AD30 -> 0 | G19: ='Weekly Data'!AD36 -> 0 | H19: ='Weekly Data'!AD41 -> 0 | I19: ='Weekly Data'!AD46 -> 0 | J19: ='Weekly Data'!AD52 -> 0 | K19: ='Weekly Data'!AD57 -> 0 | L19: ='Weekly Data'!AD62 -> 0 | N19: =SUM(B19:M19) -> 0
A20: Avg Resolution (hrs) | B20: ='Weekly Data'!AF9 | C20: ='Weekly Data'!AF14 | D20: ='Weekly Data'!AF20 | E20: ='Weekly Data'!AF25 | F20: ='Weekly Data'!AF30 | G20: ='Weekly Data'!AF36 | H20: ='Weekly Data'!AF41 | I20: ='Weekly Data'!AF46 | J20: ='Weekly Data'!AF52 | K20: ='Weekly Data'!AF57 | L20: ='Weekly Data'!AF62 | N20: =IFERROR(AVERAGE(B20:M20),"")
A21: Company Utilization % | B21: ='Weekly Data'!AJ9 | C21: ='Weekly Data'!AJ14 | D21: ='Weekly Data'!AJ20 | E21: ='Weekly Data'!AJ25 | F21: ='Weekly Data'!AJ30 | G21: ='Weekly Data'!AJ36 | H21: ='Weekly Data'!AJ41 | I21: ='Weekly Data'!AJ46 | J21: ='Weekly Data'!AJ52 | K21: ='Weekly Data'!AJ57 | L21: ='Weekly Data'!AJ62 | N21: =IFERROR(AVERAGE(B21:M21),"")
A22: Pipeline Value | B22: ='Weekly Data'!AK9 | C22: ='Weekly Data'!AK14 | D22: ='Weekly Data'!AK20 | E22: ='Weekly Data'!AK25 | F22: ='Weekly Data'!AK30 | G22: ='Weekly Data'!AK36 | H22: ='Weekly Data'!AK41 | I22: ='Weekly Data'!AK46 | J22: ='Weekly Data'!AK52 | K22: ='Weekly Data'!AK57 | L22: ='Weekly Data'!AK62 | N22: =IFERROR(LOOKUP(2,1/(B22:M22<>""),B22:M22),"")
A23: Win Rate % | B23: ='Weekly Data'!AM9 | C23: ='Weekly Data'!AM14 | D23: ='Weekly Data'!AM20 | E23: ='Weekly Data'!AM25 | F23: ='Weekly Data'!AM30 | G23: ='Weekly Data'!AM36 | H23: ='Weekly Data'!AM41 | I23: ='Weekly Data'!AM46 | J23: ='Weekly Data'!AM52 | K23: ='Weekly Data'!AM57 | L23: ='Weekly Data'!AM62 | N23: =IFERROR(AVERAGE(B23:M23),"")
A25: Revenue Won by Rep — 2025
A26: Joel Walker | B26: ='Weekly Data'!L9 -> 0 | C26: ='Weekly Data'!L14 -> 0 | D26: ='Weekly Data'!L20 -> 0 | E26: ='Weekly Data'!L25 -> 0 | F26: ='Weekly Data'!L30 -> 0 | G26: ='Weekly Data'!L36 -> 0 | H26: ='Weekly Data'!L41 -> 0 | I26: ='Weekly Data'!L46 -> 0 | J26: ='Weekly Data'!L52 -> 0 | K26: ='Weekly Data'!L57 -> 0 | L26: ='Weekly Data'!L62 -> 0 | N26: =SUM(B26:M26) -> 0
A27: Nathan La Fleche | B27: ='Weekly Data'!M9 -> 0 | C27: ='Weekly Data'!M14 -> 0 | D27: ='Weekly Data'!M20 -> 0 | E27: ='Weekly Data'!M25 -> 0 | F27: ='Weekly Data'!M30 -> 0 | G27: ='Weekly Data'!M36 -> 0 | H27: ='Weekly Data'!M41 -> 0 | I27: ='Weekly Data'!M46 -> 0 | J27: ='Weekly Data'!M52 -> 0 | K27: ='Weekly Data'!M57 -> 0 | L27: ='Weekly Data'!M62 -> 0 | N27: =SUM(B27:M27) -> 0
A28: Dan Sturdivant | B28: ='Weekly Data'!N9 -> 0 | C28: ='Weekly Data'!N14 -> 0 | D28: ='Weekly Data'!N20 -> 0 | E28: ='Weekly Data'!N25 -> 0 | F28: ='Weekly Data'!N30 -> 0 | G28: ='Weekly Data'!N36 -> 0 | H28: ='Weekly Data'!N41 -> 0 | I28: ='Weekly Data'!N46 -> 0 | J28: ='Weekly Data'!N52 -> 0 | K28: ='Weekly Data'!N57 -> 0 | L28: ='Weekly Data'!N62 -> 0 | N28: =SUM(B28:M28) -> 0
A29: Jay Harvey | B29: ='Weekly Data'!O9 -> 0 | C29: ='Weekly Data'!O14 -> 0 | D29: ='Weekly Data'!O20 -> 0 | E29: ='Weekly Data'!O25 -> 0 | F29: ='Weekly Data'!O30 -> 0 | G29: ='Weekly Data'!O36 -> 0 | H29: ='Weekly Data'!O41 -> 0 | I29: ='Weekly Data'!O46 -> 0 | J29: ='Weekly Data'!O52 -> 0 | K29: ='Weekly Data'!O57 -> 0 | L29: ='Weekly Data'!O62 -> 0 | N29: =SUM(B29:M29) -> 0
A30: Ricky Maestas | B30: ='Weekly Data'!P9 -> 0 | C30: ='Weekly Data'!P14 -> 0 | D30: ='Weekly Data'!P20 -> 0 | E30: ='Weekly Data'!P25 -> 0 | F30: ='Weekly Data'!P30 -> 0 | G30: ='Weekly Data'!P36 -> 0 | H30: ='Weekly Data'!P41 -> 0 | I30: ='Weekly Data'!P46 -> 0 | J30: ='Weekly Data'!P52 -> 0 | K30: ='Weekly Data'!P57 -> 0 | L30: ='Weekly Data'!P62 -> 0 | N30: =SUM(B30:M30) -> 0
A31: Maria Martinez | B31: ='Weekly Data'!Q9 -> 0 | C31: ='Weekly Data'!Q14 -> 0 | D31: ='Weekly Data'!Q20 -> 0 | E31: ='Weekly Data'!Q25 -> 0 | F31: ='Weekly Data'!Q30 -> 0 | G31: ='Weekly Data'!Q36 -> 0 | H31: ='Weekly Data'!Q41 -> 0 | I31: ='Weekly Data'!Q46 -> 0 | J31: ='Weekly Data'!Q52 -> 0 | K31: ='Weekly Data'!Q57 -> 0 | L31: ='Weekly Data'!Q62 -> 0 | N31: =SUM(B31:M31) -> 0
A32: Julissa Martinez | B32: ='Weekly Data'!R9 -> 0 | C32: ='Weekly Data'!R14 -> 0 | D32: ='Weekly Data'!R20 -> 0 | E32: ='Weekly Data'!R25 -> 0 | F32: ='Weekly Data'!R30 -> 0 | G32: ='Weekly Data'!R36 -> 0 | H32: ='Weekly Data'!R41 -> 0 | I32: ='Weekly Data'!R46 -> 0 | J32: ='Weekly Data'!R52 -> 0 | K32: ='Weekly Data'!R57 -> 0 | L32: ='Weekly Data'!R62 -> 0 | N32: =SUM(B32:M32) -> 0
A33: TEAM TOTAL | B33: =SUM(B26:B32) -> 0 | C33: =SUM(C26:C32) -> 0 | D33: =SUM(D26:D32) -> 0 | E33: =SUM(E26:E32) -> 0 | F33: =SUM(F26:F32) -> 0 | G33: =SUM(G26:G32) -> 0 | H33: =SUM(H26:H32) -> 0 | I33: =SUM(I26:I32) -> 0 | ... N33: =SUM(N26:N32) -> 0
A35: ── 2026 ──
A36: Metric | B36: Jan | C36: Feb | D36: Mar | E36: Apr | F36: May | G36: Jun | H36: Jul | I36: Aug | J36: Sep | K36: Oct | L36: Nov | M36: Dec | N36: YTD
A37: Total Revenue Won | B37: ='Weekly Data'!F72 -> 0 | C37: ='Weekly Data'!F77 -> 782928 | D37: ='Weekly Data'!F83 -> 0 | E37: ='Weekly Data'!F88 -> 0 | F37: ='Weekly Data'!F93 -> 0 | G37: ='Weekly Data'!F99 -> 0 | H37: ='Weekly Data'!F104 -> 0 | I37: ='Weekly Data'!F110 -> 0 | J37: ='Weekly Data'!F115 -> 0 | K37: ='Weekly Data'!F120 -> 0 | L37: ='Weekly Data'!F126 -> 0 | M37: ='Weekly Data'!F131 -> 0 | N37: =SUM(B37:M37) -> 782928
A38: NRR | B38: ='Weekly Data'!G72 -> 0 | C38: ='Weekly Data'!G77 -> 384814 | D38: ='Weekly Data'!G83 -> 0 | E38: ='Weekly Data'!G88 -> 0 | F38: ='Weekly Data'!G93 -> 0 | G38: ='Weekly Data'!G99 -> 0 | H38: ='Weekly Data'!G104 -> 0 | I38: ='Weekly Data'!G110 -> 0 | J38: ='Weekly Data'!G115 -> 0 | K38: ='Weekly Data'!G120 -> 0 | L38: ='Weekly Data'!G126 -> 0 | M38: ='Weekly Data'!G131 -> 0 | N38: =SUM(B38:M38) -> 384814
A39: Recurring Revenue (Mo) | B39: ='Weekly Data'!H72 | C39: ='Weekly Data'!H77 -> 33176 | D39: ='Weekly Data'!H83 | E39: ='Weekly Data'!H88 | F39: ='Weekly Data'!H93 | G39: ='Weekly Data'!H99 | H39: ='Weekly Data'!H104 | I39: ='Weekly Data'!H110 | J39: ='Weekly Data'!H115 | K39: ='Weekly Data'!H120 | L39: ='Weekly Data'!H126 | M39: ='Weekly Data'!H131 | N39: =IFERROR(LOOKUP(2,1/(B39:M39<>""),B39:M39),"") -> 33176
A40: P&L Gross Sales | B40: ='Weekly Data'!S72 -> 1385716 | C40: ='Weekly Data'!S77 -> 1292505 | D40: ='Weekly Data'!S83 | E40: ='Weekly Data'!S88 | F40: ='Weekly Data'!S93 | G40: ='Weekly Data'!S99 | H40: ='Weekly Data'!S104 | I40: ='Weekly Data'!S110 | J40: ='Weekly Data'!S115 | K40: ='Weekly Data'!S120 | L40: ='Weekly Data'!S126 | M40: ='Weekly Data'!S131 | N40: =IFERROR(LOOKUP(2,1/(B40:M40<>""),B40:M40),"") -> 1292505
A41: P&L Gross Margin | B41: ='Weekly Data'!U72 -> 530251 | C41: ='Weekly Data'!U77 -> 613819 | D41: ='Weekly Data'!U83 | E41: ='Weekly Data'!U88 | F41: ='Weekly Data'!U93 | G41: ='Weekly Data'!U99 | H41: ='Weekly Data'!U104 | I41: ='Weekly Data'!U110 | J41: ='Weekly Data'!U115 | K41: ='Weekly Data'!U120 | L41: ='Weekly Data'!U126 | M41: ='Weekly Data'!U131 | N41: =IFERROR(LOOKUP(2,1/(B41:M41<>""),B41:M41),"") -> 613819
A42: P&L GM % | B42: ='Weekly Data'!V72 -> 38.265489 | C42: ='Weekly Data'!V77 -> 47.490648 | D42: ='Weekly Data'!V83 | E42: ='Weekly Data'!V88 | F42: ='Weekly Data'!V93 | G42: ='Weekly Data'!V99 | H42: ='Weekly Data'!V104 | I42: ='Weekly Data'!V110 | J42: ='Weekly Data'!V115 | K42: ='Weekly Data'!V120 | L42: ='Weekly Data'!V126 | M42: ='Weekly Data'!V131 | N42: =IFERROR(AVERAGE(B42:M42),"") -> 42.878068
A43: Won vs Billed Gap | B43: ='Weekly Data'!W72 | C43: ='Weekly Data'!W77 -> -509577 | D43: ='Weekly Data'!W83 | E43: ='Weekly Data'!W88 | F43: ='Weekly Data'!W93 | G43: ='Weekly Data'!W99 | H43: ='Weekly Data'!W104 | I43: ='Weekly Data'!W110 | J43: ='Weekly Data'!W115 | K43: ='Weekly Data'!W120 | L43: ='Weekly Data'!W126 | M43: ='Weekly Data'!W131 | N43: =IFERROR(LOOKUP(2,1/(B43:M43<>""),B43:M43),"") -> -509577
A44: Cash on Hand | B44: ='Weekly Data'!X72 -> 3133802 | C44: ='Weekly Data'!X77 -> 3076658 | D44: ='Weekly Data'!X83 | E44: ='Weekly Data'!X88 | F44: ='Weekly Data'!X93 | G44: ='Weekly Data'!X99 | H44: ='Weekly Data'!X104 | I44: ='Weekly Data'!X110 | J44: ='Weekly Data'!X115 | K44: ='Weekly Data'!X120 | L44: ='Weekly Data'!X126 | M44: ='Weekly Data'!X131 | N44: =IFERROR(LOOKUP(2,1/(B44:M44<>""),B44:M44),"") -> 3076658
A45: DSO | B45: ='Weekly Data'!Y72 | C45: ='Weekly Data'!Y77 -> 40 | D45: ='Weekly Data'!Y83 | E45: ='Weekly Data'!Y88 | F45: ='Weekly Data'!Y93 | G45: ='Weekly Data'!Y99 | H45: ='Weekly Data'!Y104 | I45: ='Weekly Data'!Y110 | J45: ='Weekly Data'!Y115 | K45: ='Weekly Data'!Y120 | L45: ='Weekly Data'!Y126 | M45: ='Weekly Data'!Y131 | N45: =IFERROR(LOOKUP(2,1/(B45:M45<>""),B45:M45),"") -> 40
A46: AR Total | B46: ='Weekly Data'!Z72 | C46: ='Weekly Data'!Z77 -> 1432806 | D46: ='Weekly Data'!Z83 | E46: ='Weekly Data'!Z88 | F46: ='Weekly Data'!Z93 | G46: ='Weekly Data'!Z99 | H46: ='Weekly Data'!Z104 | I46: ='Weekly Data'!Z110 | J46: ='Weekly Data'!Z115 | K46: ='Weekly Data'!Z120 | L46: ='Weekly Data'!Z126 | M46: ='Weekly Data'!Z131 | N46: =IFERROR(LOOKUP(2,1/(B46:M46<>""),B46:M46),"") -> 1432806
A47: AP Total | B47: ='Weekly Data'!AA72 | C47: ='Weekly Data'!AA77 -> 5207610 | D47: ='Weekly Data'!AA83 | E47: ='Weekly Data'!AA88 | F47: ='Weekly Data'!AA93 | G47: ='Weekly Data'!AA99 | H47: ='Weekly Data'!AA104 | I47: ='Weekly Data'!AA110 | J47: ='Weekly Data'!AA115 | K47: ='Weekly Data'!AA120 | L47: ='Weekly Data'!AA126 | M47: ='Weekly Data'!AA131 | N47: =IFERROR(LOOKUP(2,1/(B47:M47<>""),B47:M47),"") -> 5207610
A48: Payroll % Revenue | B48: ='Weekly Data'!AB72 -> 32.8 | C48: ='Weekly Data'!AB77 -> 24.5 | D48: ='Weekly Data'!AB83 | E48: ='Weekly Data'!AB88 | F48: ='Weekly Data'!AB93 | G48: ='Weekly Data'!AB99 | H48: ='Weekly Data'!AB104 | I48: ='Weekly Data'!AB110 | J48: ='Weekly Data'!AB115 | K48: ='Weekly Data'!AB120 | L48: ='Weekly Data'!AB126 | M48: ='Weekly Data'!AB131 | N48: =IFERROR(AVERAGE(B48:M48),"") -> 28.65
A49: Tickets Created | B49: ='Weekly Data'!AC72 -> 0 | C49: ='Weekly Data'!AC77 -> 0 | D49: ='Weekly Data'!AC83 -> 532 | E49: ='Weekly Data'!AC88 -> 0 | F49: ='Weekly Data'!AC93 -> 0 | G49: ='Weekly Data'!AC99 -> 0 | H49: ='Weekly Data'!AC104 -> 0 | I49: ='Weekly Data'!AC110 -> 0 | J49: ='Weekly Data'!AC115 -> 0 | K49: ='Weekly Data'!AC120 -> 0 | L49: ='Weekly Data'!AC126 -> 0 | M49: ='Weekly Data'!AC131 -> 0 | N49: =SUM(B49:M49) -> 532
A50: Tickets Resolved | B50: ='Weekly Data'!AD72 -> 0 | C50: ='Weekly Data'!AD77 -> 0 | D50: ='Weekly Data'!AD83 -> 532 | E50: ='Weekly Data'!AD88 -> 0 | F50: ='Weekly Data'!AD93 -> 0 | G50: ='Weekly Data'!AD99 -> 0 | H50: ='Weekly Data'!AD104 -> 0 | I50: ='Weekly Data'!AD110 -> 0 | J50: ='Weekly Data'!AD115 -> 0 | K50: ='Weekly Data'!AD120 -> 0 | L50: ='Weekly Data'!AD126 -> 0 | M50: ='Weekly Data'!AD131 -> 0 | N50: =SUM(B50:M50) -> 532
A51: Avg Resolution (hrs) | B51: ='Weekly Data'!AF72 | C51: ='Weekly Data'!AF77 | D51: ='Weekly Data'!AF83 -> 5.66 | E51: ='Weekly Data'!AF88 | F51: ='Weekly Data'!AF93 | G51: ='Weekly Data'!AF99 | H51: ='Weekly Data'!AF104 | I51: ='Weekly Data'!AF110 | J51: ='Weekly Data'!AF115 | K51: ='Weekly Data'!AF120 | L51: ='Weekly Data'!AF126 | M51: ='Weekly Data'!AF131 | N51: =IFERROR(AVERAGE(B51:M51),"") -> 5.66
A52: Company Utilization % | B52: ='Weekly Data'!AJ72 | C52: ='Weekly Data'!AJ77 | D52: ='Weekly Data'!AJ83 -> 63.5 | E52: ='Weekly Data'!AJ88 | F52: ='Weekly Data'!AJ93 | G52: ='Weekly Data'!AJ99 | H52: ='Weekly Data'!AJ104 | I52: ='Weekly Data'!AJ110 | J52: ='Weekly Data'!AJ115 | K52: ='Weekly Data'!AJ120 | L52: ='Weekly Data'!AJ126 | M52: ='Weekly Data'!AJ131 | N52: =IFERROR(AVERAGE(B52:M52),"") -> 63.5
A53: Pipeline Value | B53: ='Weekly Data'!AK72 | C53: ='Weekly Data'!AK77 -> 453948 | D53: ='Weekly Data'!AK83 -> 453948 | E53: ='Weekly Data'!AK88 | F53: ='Weekly Data'!AK93 | G53: ='Weekly Data'!AK99 | H53: ='Weekly Data'!AK104 | I53: ='Weekly Data'!AK110 | J53: ='Weekly Data'!AK115 | K53: ='Weekly Data'!AK120 | L53: ='Weekly Data'!AK126 | M53: ='Weekly Data'!AK131 | N53: =IFERROR(LOOKUP(2,1/(B53:M53<>""),B53:M53),"") -> 453948
A54: Win Rate % | B54: ='Weekly Data'!AM72 | C54: ='Weekly Data'!AM77 -> 29 | D54: ='Weekly Data'!AM83 | E54: ='Weekly Data'!AM88 | F54: ='Weekly Data'!AM93 | G54: ='Weekly Data'!AM99 | H54: ='Weekly Data'!AM104 | I54: ='Weekly Data'!AM110 | J54: ='Weekly Data'!AM115 | K54: ='Weekly Data'!AM120 | L54: ='Weekly Data'!AM126 | M54: ='Weekly Data'!AM131 | N54: =IFERROR(AVERAGE(B54:M54),"") -> 29
A56: Revenue Won by Rep — 2026
A57: Joel Walker | B57: ='Weekly Data'!L72 -> 0 | C57: ='Weekly Data'!L77 -> 208743 | D57: ='Weekly Data'!L83 -> 0 | E57: ='Weekly Data'!L88 -> 0 | F57: ='Weekly Data'!L93 -> 0 | G57: ='Weekly Data'!L99 -> 0 | H57: ='Weekly Data'!L104 -> 0 | I57: ='Weekly Data'!L110 -> 0 | J57: ='Weekly Data'!L115 -> 0 | K57: ='Weekly Data'!L120 -> 0 | L57: ='Weekly Data'!L126 -> 0 | M57: ='Weekly Data'!L131 -> 0 | N57: =SUM(B57:M57) -> 208743
A58: Nathan La Fleche | B58: ='Weekly Data'!M72 -> 0 | C58: ='Weekly Data'!M77 -> 204237 | D58: ='Weekly Data'!M83 -> 0 | E58: ='Weekly Data'!M88 -> 0 | F58: ='Weekly Data'!M93 -> 0 | G58: ='Weekly Data'!M99 -> 0 | H58: ='Weekly Data'!M104 -> 0 | I58: ='Weekly Data'!M110 -> 0 | J58: ='Weekly Data'!M115 -> 0 | K58: ='Weekly Data'!M120 -> 0 | L58: ='Weekly Data'!M126 -> 0 | M58: ='Weekly Data'!M131 -> 0 | N58: =SUM(B58:M58) -> 204237
A59: Dan Sturdivant | B59: ='Weekly Data'!N72 -> 0 | C59: ='Weekly Data'!N77 -> 158604 | D59: ='Weekly Data'!N83 -> 0 | E59: ='Weekly Data'!N88 -> 0 | F59: ='Weekly Data'!N93 -> 0 | G59: ='Weekly Data'!N99 -> 0 | H59: ='Weekly Data'!N104 -> 0 | I59: ='Weekly Data'!N110 -> 0 | J59: ='Weekly Data'!N115 -> 0 | K59: ='Weekly Data'!N120 -> 0 | L59: ='Weekly Data'!N126 -> 0 | M59: ='Weekly Data'!N131 -> 0 | N59: =SUM(B59:M59) -> 158604
A60: Jay Harvey | B60: ='Weekly Data'!O72 -> 0 | C60: ='Weekly Data'!O77 -> 125747 | D60: ='Weekly Data'!O83 -> 0 | E60: ='Weekly Data'!O88 -> 0 | F60: ='Weekly Data'!O93 -> 0 | G60: ='Weekly Data'!O99 -> 0 | H60: ='Weekly Data'!O104 -> 0 | I60: ='Weekly Data'!O110 -> 0 | J60: ='Weekly Data'!O115 -> 0 | K60: ='Weekly Data'!O120 -> 0 | L60: ='Weekly Data'!O126 -> 0 | M60: ='Weekly Data'!O131 -> 0 | N60: =SUM(B60:M60) -> 125747
A61: Ricky Maestas | B61: ='Weekly Data'!P72 -> 0 | C61: ='Weekly Data'!P77 -> 79177 | D61: ='Weekly Data'!P83 -> 0 | E61: ='Weekly Data'!P88 -> 0 | F61: ='Weekly Data'!P93 -> 0 | G61: ='Weekly Data'!P99 -> 0 | H61: ='Weekly Data'!P104 -> 0 | I61: ='Weekly Data'!P110 -> 0 | J61: ='Weekly Data'!P115 -> 0 | K61: ='Weekly Data'!P120 -> 0 | L61: ='Weekly Data'!P126 -> 0 | M61: ='Weekly Data'!P131 -> 0 | N61: =SUM(B61:M61) -> 79177
A62: Maria Martinez | B62: ='Weekly Data'!Q72 -> 0 | C62: ='Weekly Data'!Q77 -> 5913 | D62: ='Weekly Data'!Q83 -> 0 | E62: ='Weekly Data'!Q88 -> 0 | F62: ='Weekly Data'!Q93 -> 0 | G62: ='Weekly Data'!Q99 -> 0 | H62: ='Weekly Data'!Q104 -> 0 | I62: ='Weekly Data'!Q110 -> 0 | J62: ='Weekly Data'!Q115 -> 0 | K62: ='Weekly Data'!Q120 -> 0 | L62: ='Weekly Data'!Q126 -> 0 | M62: ='Weekly Data'!Q131 -> 0 | N62: =SUM(B62:M62) -> 5913
A63: Julissa Martinez | B63: ='Weekly Data'!R72 -> 0 | C63: ='Weekly Data'!R77 -> 508 | D63: ='Weekly Data'!R83 -> 0 | E63: ='Weekly Data'!R88 -> 0 | F63: ='Weekly Data'!R93 -> 0 | G63: ='Weekly Data'!R99 -> 0 | H63: ='Weekly Data'!R104 -> 0 | I63: ='Weekly Data'!R110 -> 0 | J63: ='Weekly Data'!R115 -> 0 | K63: ='Weekly Data'!R120 -> 0 | L63: ='Weekly Data'!R126 -> 0 | M63: ='Weekly Data'!R131 -> 0 | N63: =SUM(B63:M63) -> 508
A64: TEAM TOTAL | B64: =SUM(B57:B63) -> 0 | C64: =SUM(C57:C63) -> 782929 | D64: =SUM(D57:D63) -> 0 | E64: =SUM(E57:E63) -> 0 | F64: =SUM(F57:F63) -> 0 | G64: =SUM(G57:G63) -> 0 | H64: =SUM(H57:H63) -> 0 | I64: =SUM(I57:I63) -> 0 | ... N64: =SUM(N57:N63) -> 782929

Sheet WoW Trends
A1: DataPath — Week-over-Week Change Tracker
A2: Auto-calculated deltas between consecutive weeks. Positive changes in green, negative in red (reversed for cost metrics).
A4: Metric | B4: Jan 05 | C4: Jan 12 | D4: Jan 19 | E4: Jan 26 | F4: Feb 02 | G4: Feb 09 | H4: Feb 16 | I4: Feb 23 | J4: Mar 02 | K4: Mar 09 | L4: Mar 16 | M4: Mar 23 | N4: Mar 30 | O4: Apr 06 | P4: Apr 13 | Q4: Apr 20 | R4: Apr 27 | S4: May 04 | T4: May 11 | U4: May 18 | V4: May 25 | W4: Jun 01 | X4: Jun 08 | Y4: Jun 15 | Z4: Jun 22 | AA4: Jun 29
A5: Total Rev Won (Δ) | B5: =IFERROR(INDEX('Weekly Data'!F:$F,MATCH("2026-01-05",'Weekly Data'!$E:$E,0)),"") -> 0 | C5: =IFERROR(INDEX('Weekly Data'!F:$F,MATCH("2026-01-12",'Weekly Data'!$E:$E,0))-INDEX('Weekly Data'!F:$F,MATCH("2026-01-05",'Weekly Data'!$E:$E,0)),"") -> 0 | D5: =IFERROR(INDEX('Weekly Data'!F:$F,MATCH("2026-01-19",'Weekly Data'!$E:$E,0))-INDEX('Weekly Data'!F:$F,MATCH("2026-01-12",'Weekly Data'!$E:$E,0)),"") -> 0 | E5: =IFERROR(INDEX('Weekly Data'!F:$F,MATCH("2026-01-26",'Weekly Data'!$E:$E,0))-INDEX('Weekly Data'!F:$F,MATCH("2026-01-19",'Weekly Data'!$E:$E,0)),"") -> 0 | F5: =IFERROR(INDEX('Weekly Data'!F:$F,MATCH("2026-02-02",'Weekly Data'!$E:$E,0))-INDEX('Weekly Data'!F:$F,MATCH("2026-01-26",'Weekly Data'!$E:$E,0)),"") -> 0 | G5: =IFERROR(INDEX('Weekly Data'!F:$F,MATCH("2026-02-09",'Weekly Data'!$E:$E,0))-INDEX('Weekly Data'!F:$F,MATCH("2026-02-02",'Weekly Data'!$E:$E,0)),"") -> 0 | H5: =IFERROR(INDEX('Weekly Data'!F:$F,MATCH("2026-02-16",'Weekly Data'!$E:$E,0))-INDEX('Weekly Data'!F:$F,MATCH("2026-02-09",'Weekly Data'!$E:$E,0)),"") -> 0 | I5: =IFERROR(INDEX('Weekly Data'!F:$F,MATCH("2026-02-23",'Weekly Data'!$E:$E,0))-INDEX('Weekly Data'!F:$F,MATCH("2026-02-16",'Weekly Data'!$E:$E,0)),"") -> 782928 | J5: =IFERROR(INDEX('Weekly Data'!F:$F,MATCH("2026-03-02",'Weekly Data'!$E:$E,0))-INDEX('Weekly Data'!F:$F,MATCH("2026-02-23",'Weekly Data'!$E:$E,0)),"") -> -782928 | K5: =IFERROR(INDEX('Weekly Data'!F:$F,MATCH("2026-03-09",'Weekly Data'!$E:$E,0))-INDEX('Weekly Data'!F:$F,MATCH("2026-03-02",'Weekly Data'!$E:$E,0)),"") -> 0 | L5: =IFERROR(INDEX('Weekly Data'!F:$F,MATCH("2026-03-16",'Weekly Data'!$E:$E,0))-INDEX('Weekly Data'!F:$F,MATCH("2026-03-09",'Weekly Data'!$E:$E,0)),"") -> 0 | M5: =IFERROR(INDEX('Weekly Data'!F:$F,MATCH("2026-03-23",'Weekly Data'!$E:$E,0))-INDEX('Weekly Data'!F:$F,MATCH("2026-03-16",'Weekly Data'!$E:$E,0)),"") -> 0 | N5: =IFERROR(INDEX('Weekly Data'!F:$F,MATCH("2026-03-30",'Weekly Data'!$E:$E,0))-INDEX('Weekly Data'!F:$F,MATCH("2026-03-23",'Weekly Data'!$E:$E,0)),"") -> 0 | O5: =IFERROR(INDEX('Weekly Data'!F:$F,MATCH("2026-04-06",'Weekly Data'!$E:$E,0))-INDEX('Weekly Data'!F:$F,MATCH("2026-03-30",'Weekly Data'!$E:$E,0)),"") -> 0 | P5: =IFERROR(INDEX('Weekly Data'!F:$F,MATCH("2026-04-13",'Weekly Data'!$E:$E,0))-INDEX('Weekly Data'!F:$F,MATCH("2026-04-06",'Weekly Data'!$E:$E,0)),"") -> 0 | Q5: =IFERROR(INDEX('Weekly Data'!F:$F,MATCH("2026-04-20",'Weekly Data'!$E:$E,0))-INDEX('Weekly Data'!F:$F,MATCH("2026-04-13",'Weekly Data'!$E:$E,0)),"") -> 0 | R5: =IFERROR(INDEX('Weekly Data'!F:$F,MATCH("2026-04-27",'Weekly Data'!$E:$E,0))-INDEX('Weekly Data'!F:$F,MATCH("2026-04-20",'Weekly Data'!$E:$E,0)),"") -> 0 | S5: =IFERROR(INDEX('Weekly Data'!F:$F,MATCH("2026-05-04",'Weekly Data'!$E:$E,0))-INDEX('Weekly Data'!F:$F,MATCH("2026-04-27",'Weekly Data'!$E:$E,0)),"") -> 0 | T5: =IFERROR(INDEX('Weekly Data'!F:$F,MATCH("2026-05-11",'Weekly Data'!$E:$E,0))-INDEX('Weekly Data'!F:$F,MATCH("2026-05-04",'Weekly Data'!$E:$E,0)),"") -> 0 | U5: =IFERROR(INDEX('Weekly Data'!F:$F,MATCH("2026-05-18",'Weekly Data'!$E:$E,0))-INDEX('Weekly Data'!F:$F,MATCH("2026-05-11",'Weekly Data'!$E:$E,0)),"") -> 0 | V5: =IFERROR(INDEX('Weekly Data'!F:$F,MATCH("2026-05-25",'Weekly Data'!$E:$E,0))-INDEX('Weekly Data'!F:$F,MATCH("2026-05-18",'Weekly Data'!$E:$E,0)),"") -> 0 | W5: =IFERROR(INDEX('Weekly Data'!F:$F,MATCH("2026-06-01",'Weekly Data'!$E:$E,0))-INDEX('Weekly Data'!F:$F,MATCH("2026-05-25",'Weekly Data'!$E:$E,0)),"") -> 0 | X5: =IFERROR(INDEX('Weekly Data'!F:$F,MATCH("2026-06-08",'Weekly Data'!$E:$E,0))-INDEX('Weekly Data'!F:$F,MATCH("2026-06-01",'Weekly Data'!$E:$E,0)),"") -> 0 | Y5: =IFERROR(INDEX('Weekly Data'!F:$F,MATCH("2026-06-15",'Weekly Data'!$E:$E,0))-INDEX('Weekly Data'!F:$F,MATCH("2026-06-08",'Weekly Data'!$E:$E,0)),"") -> 0 | Z5: =IFERROR(INDEX('Weekly Data'!F:$F,MATCH("2026-06-22",'Weekly Data'!$E:$E,0))-INDEX('Weekly Data'!F:$F,MATCH("2026-06-15",'Weekly Data'!$E:$E,0)),"") -> 0 | AA5: =IFERROR(INDEX('Weekly Data'!F:$F,MATCH("2026-06-29",'Weekly Data'!$E:$E,0))-INDEX('Weekly Data'!F:$F,MATCH("2026-06-22",'Weekly Data'!$E:$E,0)),"") -> 0
A6: P&L Gross Sales (Δ) | B6: =IFERROR(INDEX('Weekly Data'!S:$S,MATCH("2026-01-05",'Weekly Data'!$E:$E,0)),"") -> 0 | C6: =IFERROR(INDEX('Weekly Data'!S:$S,MATCH("2026-01-12",'Weekly Data'!$E:$E,0))-INDEX('Weekly Data'!S:$S,MATCH("2026-01-05",'Weekly Data'!$E:$E,0)),"") -> 0 | D6: =IFERROR(INDEX('Weekly Data'!S:$S,MATCH("2026-01-19",'Weekly Data'!$E:$E,0))-INDEX('Weekly Data'!S:$S,MATCH("2026-01-12",'Weekly Data'!$E:$E,0)),"") -> 0 | E6: =IFERROR(INDEX('Weekly Data'!S:$S,MATCH("2026-01-26",'Weekly Data'!$E:$E,0))-INDEX('Weekly Data'!S:$S,MATCH("2026-01-19",'Weekly Data'!$E:$E,0)),"") -> 1385716 | F6: =IFERROR(INDEX('Weekly Data'!S:$S,MATCH("2026-02-02",'Weekly Data'!$E:$E,0))-INDEX('Weekly Data'!S:$S,MATCH("2026-01-26",'Weekly Data'!$E:$E,0)),"") -> -1385716 | G6: =IFERROR(INDEX('Weekly Data'!S:$S,MATCH("2026-02-09",'Weekly Data'!$E:$E,0))-INDEX('Weekly Data'!S:$S,MATCH("2026-02-02",'Weekly Data'!$E:$E,0)),"") -> 0 | H6: =IFERROR(INDEX('Weekly Data'!S:$S,MATCH("2026-02-16",'Weekly Data'!$E:$E,0))-INDEX('Weekly Data'!S:$S,MATCH("2026-02-09",'Weekly Data'!$E:$E,0)),"") -> 0 | I6: =IFERROR(INDEX('Weekly Data'!S:$S,MATCH("2026-02-23",'Weekly Data'!$E:$E,0))-INDEX('Weekly Data'!S:$S,MATCH("2026-02-16",'Weekly Data'!$E:$E,0)),"") -> 1292505 | J6: =IFERROR(INDEX('Weekly Data'!S:$S,MATCH("2026-03-02",'Weekly Data'!$E:$E,0))-INDEX('Weekly Data'!S:$S,MATCH("2026-02-23",'Weekly Data'!$E:$E,0)),"") -> -1292505 | K6: =IFERROR(INDEX('Weekly Data'!S:$S,MATCH("2026-03-09",'Weekly Data'!$E:$E,0))-INDEX('Weekly Data'!S:$S,MATCH("2026-03-02",'Weekly Data'!$E:$E,0)),"") -> 0 | L6: =IFERROR(INDEX('Weekly Data'!S:$S,MATCH("2026-03-16",'Weekly Data'!$E:$E,0))-INDEX('Weekly Data'!S:$S,MATCH("2026-03-09",'Weekly Data'!$E:$E,0)),"") -> 0 | M6: =IFERROR(INDEX('Weekly Data'!S:$S,MATCH("2026-03-23",'Weekly Data'!$E:$E,0))-INDEX('Weekly Data'!S:$S,MATCH("2026-03-16",'Weekly Data'!$E:$E,0)),"") -> 0 | N6: =IFERROR(INDEX('Weekly Data'!S:$S,MATCH("2026-03-30",'Weekly Data'!$E:$E,0))-INDEX('Weekly Data'!S:$S,MATCH("2026-03-23",'Weekly Data'!$E:$E,0)),"") -> 0 | O6: =IFERROR(INDEX('Weekly Data'!S:$S,MATCH("2026-04-06",'Weekly Data'!$E:$E,0))-INDEX('Weekly Data'!S:$S,MATCH("2026-03-30",'Weekly Data'!$E:$E,0)),"") -> 0 | P6: =IFERROR(INDEX('Weekly Data'!S:$S,MATCH("2026-04-13",'Weekly Data'!$E:$E,0))-INDEX('Weekly Data'!S:$S,MATCH("2026-04-06",'Weekly Data'!$E:$E,0)),"") -> 0 | Q6: =IFERROR(INDEX('Weekly Data'!S:$S,MATCH("2026-04-20",'Weekly Data'!$E:$E,0))-INDEX('Weekly Data'!S:$S,MATCH("2026-04-13",'Weekly Data'!$E:$E,0)),"") -> 0 | R6: =IFERROR(INDEX('Weekly Data'!S:$S,MATCH("2026-04-27",'Weekly Data'!$E:$E,0))-INDEX('Weekly Data'!S:$S,MATCH("2026-04-20",'Weekly Data'!$E:$E,0)),"") -> 0 | S6: =IFERROR(INDEX('Weekly Data'!S:$S,MATCH("2026-05-04",'Weekly Data'!$E:$E,0))-INDEX('Weekly Data'!S:$S,MATCH("2026-04-27",'Weekly Data'!$E:$E,0)),"") -> 0 | T6: =IFERROR(INDEX('Weekly Data'!S:$S,MATCH("2026-05-11",'Weekly Data'!$E:$E,0))-INDEX('Weekly Data'!S:$S,MATCH("2026-05-04",'Weekly Data'!$E:$E,0)),"") -> 0 | U6: =IFERROR(INDEX('Weekly Data'!S:$S,MATCH("2026-05-18",'Weekly Data'!$E:$E,0))-INDEX('Weekly Data'!S:$S,MATCH("2026-05-11",'Weekly Data'!$E:$E,0)),"") -> 0 | V6: =IFERROR(INDEX('Weekly Data'!S:$S,MATCH("2026-05-25",'Weekly Data'!$E:$E,0))-INDEX('Weekly Data'!S:$S,MATCH("2026-05-18",'Weekly Data'!$E:$E,0)),"") -> 0 | W6: =IFERROR(INDEX('Weekly Data'!S:$S,MATCH("2026-06-01",'Weekly Data'!$E:$E,0))-INDEX('Weekly Data'!S:$S,MATCH("2026-05-25",'Weekly Data'!$E:$E,0)),"") -> 0 | X6: =IFERROR(INDEX('Weekly Data'!S:$S,MATCH("2026-06-08",'Weekly Data'!$E:$E,0))-INDEX('Weekly Data'!S:$S,MATCH("2026-06-01",'Weekly Data'!$E:$E,0)),"") -> 0 | Y6: =IFERROR(INDEX('Weekly Data'!S:$S,MATCH("2026-06-15",'Weekly Data'!$E:$E,0))-INDEX('Weekly Data'!S:$S,MATCH("2026-06-08",'Weekly Data'!$E:$E,0)),"") -> 0 | Z6: =IFERROR(INDEX('Weekly Data'!S:$S,MATCH("2026-06-22",'Weekly Data'!$E:$E,0))-INDEX('Weekly Data'!S:$S,MATCH("2026-06-15",'Weekly Data'!$E:$E,0)),"") -> 0 | AA6: =IFERROR(INDEX('Weekly Data'!S:$S,MATCH("2026-06-29",'Weekly Data'!$E:$E,0))-INDEX('Weekly Data'!S:$S,MATCH("2026-06-22",'Weekly Data'!$E:$E,0)),"") -> 0
A7: Cash on Hand (Δ) | B7: =IFERROR(INDEX('Weekly Data'!X:$X,MATCH("2026-01-05",'Weekly Data'!$E:$E,0)),"") -> 0 | C7: =IFERROR(INDEX('Weekly Data'!X:$X,MATCH("2026-01-12",'Weekly Data'!$E:$E,0))-INDEX('Weekly Data'!X:$X,MATCH("2026-01-05",'Weekly Data'!$E:$E,0)),"") -> 0 | D7: =IFERROR(INDEX('Weekly Data'!X:$X,MATCH("2026-01-19",'Weekly Data'!$E:$E,0))-INDEX('Weekly Data'!X:$X,MATCH("2026-01-12",'Weekly Data'!$E:$E,0)),"") -> 0 | E7: =IFERROR(INDEX('Weekly Data'!X:$X,MATCH("2026-01-26",'Weekly Data'!$E:$E,0))-INDEX('Weekly Data'!X:$X,MATCH("2026-01-19",'Weekly Data'!$E:$E,0)),"") -> 3133802 | F7: =IFERROR(INDEX('Weekly Data'!X:$X,MATCH("2026-02-02",'Weekly Data'!$E:$E,0))-INDEX('Weekly Data'!X:$X,MATCH("2026-01-26",'Weekly Data'!$E:$E,0)),"") -> -3133802 | G7: =IFERROR(INDEX('Weekly Data'!X:$X,MATCH("2026-02-09",'Weekly Data'!$E:$E,0))-INDEX('Weekly Data'!X:$X,MATCH("2026-02-02",'Weekly Data'!$E:$E,0)),"") -> 0 | H7: =IFERROR(INDEX('Weekly Data'!X:$X,MATCH("2026-02-16",'Weekly Data'!$E:$E,0))-INDEX('Weekly Data'!X:$X,MATCH("2026-02-09",'Weekly Data'!$E:$E,0)),"") -> 0 | I7: =IFERROR(INDEX('Weekly Data'!X:$X,MATCH("2026-02-23",'Weekly Data'!$E:$E,0))-INDEX('Weekly Data'!X:$X,MATCH("2026-02-16",'Weekly Data'!$E:$E,0)),"") -> 3076658 | J7: =IFERROR(INDEX('Weekly Data'!X:$X,MATCH("2026-03-02",'Weekly Data'!$E:$E,0))-INDEX('Weekly Data'!X:$X,MATCH("2026-02-23",'Weekly Data'!$E:$E,0)),"") -> -3076658 | K7: =IFERROR(INDEX('Weekly Data'!X:$X,MATCH("2026-03-09",'Weekly Data'!$E:$E,0))-INDEX('Weekly Data'!X:$X,MATCH("2026-03-02",'Weekly Data'!$E:$E,0)),"") -> 0 | L7: =IFERROR(INDEX('Weekly Data'!X:$X,MATCH("2026-03-16",'Weekly Data'!$E:$E,0))-INDEX('Weekly Data'!X:$X,MATCH("2026-03-09",'Weekly Data'!$E:$E,0)),"") -> 0 | M7: =IFERROR(INDEX('Weekly Data'!X:$X,MATCH("2026-03-23",'Weekly Data'!$E:$E,0))-INDEX('Weekly Data'!X:$X,MATCH("2026-03-16",'Weekly Data'!$E:$E,0)),"") -> 0 | N7: =IFERROR(INDEX('Weekly Data'!X:$X,MATCH("2026-03-30",'Weekly Data'!$E:$E,0))-INDEX('Weekly Data'!X:$X,MATCH("2026-03-23",'Weekly Data'!$E:$E,0)),"") -> 0 | O7: =IFERROR(INDEX('Weekly Data'!X:$X,MATCH("2026-04-06",'Weekly Data'!$E:$E,0))-INDEX('Weekly Data'!X:$X,MATCH("2026-03-30",'Weekly Data'!$E:$E,0)),"") -> 0 | P7: =IFERROR(INDEX('Weekly Data'!X:$X,MATCH("2026-04-13",'Weekly Data'!$E:$E,0))-INDEX('Weekly Data'!X:$X,MATCH("2026-04-06",'Weekly Data'!$E:$E,0)),"") -> 0 | Q7: =IFERROR(INDEX('Weekly Data'!X:$X,MATCH("2026-04-20",'Weekly Data'!$E:$E,0))-INDEX('Weekly Data'!X:$X,MATCH("2026-04-13",'Weekly Data'!$E:$E,0)),"") -> 0 | R7: =IFERROR(INDEX('Weekly Data'!X:$X,MATCH("2026-04-27",'Weekly Data'!$E:$E,0))-INDEX('Weekly Data'!X:$X,MATCH("2026-04-20",'Weekly Data'!$E:$E,0)),"") -> 0 | S7: =IFERROR(INDEX('Weekly Data'!X:$X,MATCH("2026-05-04",'Weekly Data'!$E:$E,0))-INDEX('Weekly Data'!X:$X,MATCH("2026-04-27",'Weekly Data'!$E:$E,0)),"") -> 0 | T7: =IFERROR(INDEX('Weekly Data'!X:$X,MATCH("2026-05-11",'Weekly Data'!$E:$E,0))-INDEX('Weekly Data'!X:$X,MATCH("2026-05-04",'Weekly Data'!$E:$E,0)),"") -> 0 | U7: =IFERROR(INDEX('Weekly Data'!X:$X,MATCH("2026-05-18",'Weekly Data'!$E:$E,0))-INDEX('Weekly Data'!X:$X,MATCH("2026-05-11",'Weekly Data'!$E:$E,0)),"") -> 0 | V7: =IFERROR(INDEX('Weekly Data'!X:$X,MATCH("2026-05-25",'Weekly Data'!$E:$E,0))-INDEX('Weekly Data'!X:$X,MATCH("2026-05-18",'Weekly Data'!$E:$E,0)),"") -> 0 | W7: =IFERROR(INDEX('Weekly Data'!X:$X,MATCH("2026-06-01",'Weekly Data'!$E:$E,0))-INDEX('Weekly Data'!X:$X,MATCH("2026-05-25",'Weekly Data'!$E:$E,0)),"") -> 0 | X7: =IFERROR(INDEX('Weekly Data'!X:$X,MATCH("2026-06-08",'Weekly Data'!$E:$E,0))-INDEX('Weekly Data'!X:$X,MATCH("2026-06-01",'Weekly Data'!$E:$E,0)),"") -> 0 | Y7: =IFERROR(INDEX('Weekly Data'!X:$X,MATCH("2026-06-15",'Weekly Data'!$E:$E,0))-INDEX('Weekly Data'!X:$X,MATCH("2026-06-08",'Weekly Data'!$E:$E,0)),"") -> 0 | Z7: =IFERROR(INDEX('Weekly Data'!X:$X,MATCH("2026-06-22",'Weekly Data'!$E:$E,0))-INDEX('Weekly Data'!X:$X,MATCH("2026-06-15",'Weekly Data'!$E:$E,0)),"") -> 0 | AA7: =IFERROR(INDEX('Weekly Data'!X:$X,MATCH("2026-06-29",'Weekly Data'!$E:$E,0))-INDEX('Weekly Data'!X:$X,MATCH("2026-06-22",'Weekly Data'!$E:$E,0)),"") -> 0
A8: DSO (Δ) | B8: =IFERROR(INDEX('Weekly Data'!Y:$Y,MATCH("2026-01-05",'Weekly Data'!$E:$E,0)),"") -> 0 | C8: =IFERROR(INDEX('Weekly Data'!Y:$Y,MATCH("2026-01-12",'Weekly Data'!$E:$E,0))-INDEX('Weekly Data'!Y:$Y,MATCH("2026-01-05",'Weekly Data'!$E:$E,0)),"") -> 0 | D8: =IFERROR(INDEX('Weekly Data'!Y:$Y,MATCH("2026-01-19",'Weekly Data'!$E:$E,0))-INDEX('Weekly Data'!Y:$Y,MATCH("2026-01-12",'Weekly Data'!$E:$E,0)),"") -> 0 | E8: =IFERROR(INDEX('Weekly Data'!Y:$Y,MATCH("2026-01-26",'Weekly Data'!$E:$E,0))-INDEX('Weekly Data'!Y:$Y,MATCH("2026-01-19",'Weekly Data'!$E:$E,0)),"") -> 0 | F8: =IFERROR(INDEX('Weekly Data'!Y:$Y,MATCH("2026-02-02",'Weekly Data'!$E:$E,0))-INDEX('Weekly Data'!Y:$Y,MATCH("2026-01-26",'Weekly Data'!$E:$E,0)),"") -> 0 | G8: =IFERROR(INDEX('Weekly Data'!Y:$Y,MATCH("2026-02-09",'Weekly Data'!$E:$E,0))-INDEX('Weekly Data'!Y:$Y,MATCH("2026-02-02",'Weekly Data'!$E:$E,0)),"") -> 0 | H8: =IFERROR(INDEX('Weekly Data'!Y:$Y,MATCH("2026-02-16",'Weekly Data'!$E:$E,0))-INDEX('Weekly Data'!Y:$Y,MATCH("2026-02-09",'Weekly Data'!$E:$E,0)),"") -> 0 | I8: =IFERROR(INDEX('Weekly Data'!Y:$Y,MATCH("2026-02-23",'Weekly Data'!$E:$E,0))-INDEX('Weekly Data'!Y:$Y,MATCH("2026-02-16",'Weekly Data'!$E:$E,0)),"") -> 40 | J8: =IFERROR(INDEX('Weekly Data'!Y:$Y,MATCH("2026-03-02",'Weekly Data'!$E:$E,0))-INDEX('Weekly Data'!Y:$Y,MATCH("2026-02-23",'Weekly Data'!$E:$E,0)),"") -> -40 | K8: =IFERROR(INDEX('Weekly Data'!Y:$Y,MATCH("2026-03-09",'Weekly Data'!$E:$E,0))-INDEX('Weekly Data'!Y:$Y,MATCH("2026-03-02",'Weekly Data'!$E:$E,0)),"") -> 0 | L8: =IFERROR(INDEX('Weekly Data'!Y:$Y,MATCH("2026-03-16",'Weekly Data'!$E:$E,0))-INDEX('Weekly Data'!Y:$Y,MATCH("2026-03-09",'Weekly Data'!$E:$E,0)),"") -> 0 | M8: =IFERROR(INDEX('Weekly Data'!Y:$Y,MATCH("2026-03-23",'Weekly Data'!$E:$E,0))-INDEX('Weekly Data'!Y:$Y,MATCH("2026-03-16",'Weekly Data'!$E:$E,0)),"") -> 0 | N8: =IFERROR(INDEX('Weekly Data'!Y:$Y,MATCH("2026-03-30",'Weekly Data'!$E:$E,0))-INDEX('Weekly Data'!Y:$Y,MATCH("2026-03-23",'Weekly Data'!$E:$E,0)),"") -> 0 | O8: =IFERROR(INDEX('Weekly Data'!Y:$Y,MATCH("2026-04-06",'Weekly Data'!$E:$E,0))-INDEX('Weekly Data'!Y:$Y,MATCH("2026-03-30",'Weekly Data'!$E:$E,0)),"") -> 0 | P8: =IFERROR(INDEX('Weekly Data'!Y:$Y,MATCH("2026-04-13",'Weekly Data'!$E:$E,0))-INDEX('Weekly Data'!Y:$Y,MATCH("2026-04-06",'Weekly Data'!$E:$E,0)),"") -> 0 | Q8: =IFERROR(INDEX('Weekly Data'!Y:$Y,MATCH("2026-04-20",'Weekly Data'!$E:$E,0))-INDEX('Weekly Data'!Y:$Y,MATCH("2026-04-13",'Weekly Data'!$E:$E,0)),"") -> 0 | R8: =IFERROR(INDEX('Weekly Data'!Y:$Y,MATCH("2026-04-27",'Weekly Data'!$E:$E,0))-INDEX('Weekly Data'!Y:$Y,MATCH("2026-04-20",'Weekly Data'!$E:$E,0)),"") -> 0 | S8: =IFERROR(INDEX('Weekly Data'!Y:$Y,MATCH("2026-05-04",'Weekly Data'!$E:$E,0))-INDEX('Weekly Data'!Y:$Y,MATCH("2026-04-27",'Weekly Data'!$E:$E,0)),"") -> 0 | T8: =IFERROR(INDEX('Weekly Data'!Y:$Y,MATCH("2026-05-11",'Weekly Data'!$E:$E,0))-INDEX('Weekly Data'!Y:$Y,MATCH("2026-05-04",'Weekly Data'!$E:$E,0)),"") -> 0 | U8: =IFERROR(INDEX('Weekly Data'!Y:$Y,MATCH("2026-05-18",'Weekly Data'!$E:$E,0))-INDEX('Weekly Data'!Y:$Y,MATCH("2026-05-11",'Weekly Data'!$E:$E,0)),"") -> 0 | V8: =IFERROR(INDEX('Weekly Data'!Y:$Y,MATCH("2026-05-25",'Weekly Data'!$E:$E,0))-INDEX('Weekly Data'!Y:$Y,MATCH("2026-05-18",'Weekly Data'!$E:$E,0)),"") -> 0 | W8: =IFERROR(INDEX('Weekly Data'!Y:$Y,MATCH("2026-06-01",'Weekly Data'!$E:$E,0))-INDEX('Weekly Data'!Y:$Y,MATCH("2026-05-25",'Weekly Data'!$E:$E,0)),"") -> 0 | X8: =IFERROR(INDEX('Weekly Data'!Y:$Y,MATCH("2026-06-08",'Weekly Data'!$E:$E,0))-INDEX('Weekly Data'!Y:$Y,MATCH("2026-06-01",'Weekly Data'!$E:$E,0)),"") -> 0 | Y8: =IFERROR(INDEX('Weekly Data'!Y:$Y,MATCH("2026-06-15",'Weekly Data'!$E:$E,0))-INDEX('Weekly Data'!Y:$Y,MATCH("2026-06-08",'Weekly Data'!$E:$E,0)),"") -> 0 | Z8: =IFERROR(INDEX('Weekly Data'!Y:$Y,MATCH("2026-06-22",'Weekly Data'!$E:$E,0))-INDEX('Weekly Data'!Y:$Y,MATCH("2026-06-15",'Weekly Data'!$E:$E,0)),"") -> 0 | AA8: =IFERROR(INDEX('Weekly Data'!Y:$Y,MATCH("2026-06-29",'Weekly Data'!$E:$E,0))-INDEX('Weekly Data'!Y:$Y,MATCH("2026-06-22",'Weekly Data'!$E:$E,0)),"") -> 0
A9: Tickets Created (Δ) | B9: =IFERROR(INDEX('Weekly Data'!AC:$AC,MATCH("2026-01-05",'Weekly Data'!$E:$E,0)),"") -> 0 | C9: =IFERROR(INDEX('Weekly Data'!AC:$AC,MATCH("2026-01-12",'Weekly Data'!$E:$E,0))-INDEX('Weekly Data'!AC:$AC,MATCH("2026-01-05",'Weekly Data'!$E:$E,0)),"") -> 0 | D9: =IFERROR(INDEX('Weekly Data'!AC:$AC,MATCH("2026-01-19",'Weekly Data'!$E:$E,0))-INDEX('Weekly Data'!AC:$AC,MATCH("2026-01-12",'Weekly Data'!$E:$E,0)),"") -> 0 | E9: =IFERROR(INDEX('Weekly Data'!AC:$AC,MATCH("2026-01-26",'Weekly Data'!$E:$E,0))-INDEX('Weekly Data'!AC:$AC,MATCH("2026-01-19",'Weekly Data'!$E:$E,0)),"") -> 0 | F9: =IFERROR(INDEX('Weekly Data'!AC:$AC,MATCH("2026-02-02",'Weekly Data'!$E:$E,0))-INDEX('Weekly Data'!AC:$AC,MATCH("2026-01-26",'Weekly Data'!$E:$E,0)),"") -> 0 | G9: =IFERROR(INDEX('Weekly Data'!AC:$AC,MATCH("2026-02-09",'Weekly Data'!$E:$E,0))-INDEX('Weekly Data'!AC:$AC,MATCH("2026-02-02",'Weekly Data'!$E:$E,0)),"") -> 0 | H9: =IFERROR(INDEX('Weekly Data'!AC:$AC,MATCH("2026-02-16",'Weekly Data'!$E:$E,0))-INDEX('Weekly Data'!AC:$AC,MATCH("2026-02-09",'Weekly Data'!$E:$E,0)),"") -> 0 | I9: =IFERROR(INDEX('Weekly Data'!AC:$AC,MATCH("2026-02-23",'Weekly Data'!$E:$E,0))-INDEX('Weekly Data'!AC:$AC,MATCH("2026-02-16",'Weekly Data'!$E:$E,0)),"") -> 0 | J9: =IFERROR(INDEX('Weekly Data'!AC:$AC,MATCH("2026-03-02",'Weekly Data'!$E:$E,0))-INDEX('Weekly Data'!AC:$AC,MATCH("2026-02-23",'Weekly Data'!$E:$E,0)),"") -> 532 | K9: =IFERROR(INDEX('Weekly Data'!AC:$AC,MATCH("2026-03-09",'Weekly Data'!$E:$E,0))-INDEX('Weekly Data'!AC:$AC,MATCH("2026-03-02",'Weekly Data'!$E:$E,0)),"") -> -532 | L9: =IFERROR(INDEX('Weekly Data'!AC:$AC,MATCH("2026-03-16",'Weekly Data'!$E:$E,0))-INDEX('Weekly Data'!AC:$AC,MATCH("2026-03-09",'Weekly Data'!$E:$E,0)),"") -> 0 | M9: =IFERROR(INDEX('Weekly Data'!AC:$AC,MATCH("2026-03-23",'Weekly Data'!$E:$E,0))-INDEX('Weekly Data'!AC:$AC,MATCH("2026-03-16",'Weekly Data'!$E:$E,0)),"") -> 0 | N9: =IFERROR(INDEX('Weekly Data'!AC:$AC,MATCH("2026-03-30",'Weekly Data'!$E:$E,0))-INDEX('Weekly Data'!AC:$AC,MATCH("2026-03-23",'Weekly Data'!$E:$E,0)),"") -> 0 | O9: =IFERROR(INDEX('Weekly Data'!AC:$AC,MATCH("2026-04-06",'Weekly Data'!$E:$E,0))-INDEX('Weekly Data'!AC:$AC,MATCH("2026-03-30",'Weekly Data'!$E:$E,0)),"") -> 0 | P9: =IFERROR(INDEX('Weekly Data'!AC:$AC,MATCH("2026-04-13",'Weekly Data'!$E:$E,0))-INDEX('Weekly Data'!AC:$AC,MATCH("2026-04-06",'Weekly Data'!$E:$E,0)),"") -> 0 | Q9: =IFERROR(INDEX('Weekly Data'!AC:$AC,MATCH("2026-04-20",'Weekly Data'!$E:$E,0))-INDEX('Weekly Data'!AC:$AC,MATCH("2026-04-13",'Weekly Data'!$E:$E,0)),"") -> 0 | R9: =IFERROR(INDEX('Weekly Data'!AC:$AC,MATCH("2026-04-27",'Weekly Data'!$E:$E,0))-INDEX('Weekly Data'!AC:$AC,MATCH("2026-04-20",'Weekly Data'!$E:$E,0)),"") -> 0 | S9: =IFERROR(INDEX('Weekly Data'!AC:$AC,MATCH("2026-05-04",'Weekly Data'!$E:$E,0))-INDEX('Weekly Data'!AC:$AC,MATCH("2026-04-27",'Weekly Data'!$E:$E,0)),"") -> 0 | T9: =IFERROR(INDEX('Weekly Data'!AC:$AC,MATCH("2026-05-11",'Weekly Data'!$E:$E,0))-INDEX('Weekly Data'!AC:$AC,MATCH("2026-05-04",'Weekly Data'!$E:$E,0)),"") -> 0 | U9: =IFERROR(INDEX('Weekly Data'!AC:$AC,MATCH("2026-05-18",'Weekly Data'!$E:$E,0))-INDEX('Weekly Data'!AC:$AC,MATCH("2026-05-11",'Weekly Data'!$E:$E,0)),"") -> 0 | V9: =IFERROR(INDEX('Weekly Data'!AC:$AC,MATCH("2026-05-25",'Weekly Data'!$E:$E,0))-INDEX('Weekly Data'!AC:$AC,MATCH("2026-05-18",'Weekly Data'!$E:$E,0)),"") -> 0 | W9: =IFERROR(INDEX('Weekly Data'!AC:$AC,MATCH("2026-06-01",'Weekly Data'!$E:$E,0))-INDEX('Weekly Data'!AC:$AC,MATCH("2026-05-25",'Weekly Data'!$E:$E,0)),"") -> 0 | X9: =IFERROR(INDEX('Weekly Data'!AC:$AC,MATCH("2026-06-08",'Weekly Data'!$E:$E,0))-INDEX('Weekly Data'!AC:$AC,MATCH("2026-06-01",'Weekly Data'!$E:$E,0)),"") -> 0 | Y9: =IFERROR(INDEX('Weekly Data'!AC:$AC,MATCH("2026-06-15",'Weekly Data'!$E:$E,0))-INDEX('Weekly Data'!AC:$AC,MATCH("2026-06-08",'Weekly Data'!$E:$E,0)),"") -> 0 | Z9: =IFERROR(INDEX('Weekly Data'!AC:$AC,MATCH("2026-06-22",'Weekly Data'!$E:$E,0))-INDEX('Weekly Data'!AC:$AC,MATCH("2026-06-15",'Weekly Data'!$E:$E,0)),"") -> 0 | AA9: =IFERROR(INDEX('Weekly Data'!AC:$AC,MATCH("2026-06-29",'Weekly Data'!$E:$E,0))-INDEX('Weekly Data'!AC:$AC,MATCH("2026-06-22",'Weekly Data'!$E:$E,0)),"") -> 0
A10: Tickets Resolved (Δ) | B10: =IFERROR(INDEX('Weekly Data'!AD:$AD,MATCH("2026-01-05",'Weekly Data'!$E:$E,0)),"") -> 0 | C10: =IFERROR(INDEX('Weekly Data'!AD:$AD,MATCH("2026-01-12",'Weekly Data'!$E:$E,0))-INDEX('Weekly Data'!AD:$AD,MATCH("2026-01-05",'Weekly Data'!$E:$E,0)),"") -> 0 | D10: =IFERROR(INDEX('Weekly Data'!AD:$AD,MATCH("2026-01-19",'Weekly Data'!$E:$E,0))-INDEX('Weekly Data'!AD:$AD,MATCH("2026-01-12",'Weekly Data'!$E:$E,0)),"") -> 0 | E10: =IFERROR(INDEX('Weekly Data'!AD:$AD,MATCH("2026-01-26",'Weekly Data'!$E:$E,0))-INDEX('Weekly Data'!AD:$AD,MATCH("2026-01-19",'Weekly Data'!$E:$E,0)),"") -> 0 | F10: =IFERROR(INDEX('Weekly Data'!AD:$AD,MATCH("2026-02-02",'Weekly Data'!$E:$E,0))-INDEX('Weekly Data'!AD:$AD,MATCH("2026-01-26",'Weekly Data'!$E:$E,0)),"") -> 0 | G10: =IFERROR(INDEX('Weekly Data'!AD:$AD,MATCH("2026-02-09",'Weekly Data'!$E:$E,0))-INDEX('Weekly Data'!AD:$AD,MATCH("2026-02-02",'Weekly Data'!$E:$E,0)),"") -> 0 | H10: =IFERROR(INDEX('Weekly Data'!AD:$AD,MATCH("2026-02-16",'Weekly Data'!$E:$E,0))-INDEX('Weekly Data'!AD:$AD,MATCH("2026-02-09",'Weekly Data'!$E:$E,0)),"") -> 0 | I10: =IFERROR(INDEX('Weekly Data'!AD:$AD,MATCH("2026-02-23",'Weekly Data'!$E:$E,0))-INDEX('Weekly Data'!AD:$AD,MATCH("2026-02-16",'Weekly Data'!$E:$E,0)),"") -> 0 | J10: =IFERROR(INDEX('Weekly Data'!AD:$AD,MATCH("2026-03-02",'Weekly Data'!$E:$E,0))-INDEX('Weekly Data'!AD:$AD,MATCH("2026-02-23",'Weekly Data'!$E:$E,0)),"") -> 532 | K10: =IFERROR(INDEX('Weekly Data'!AD:$AD,MATCH("2026-03-09",'Weekly Data'!$E:$E,0))-INDEX('Weekly Data'!AD:$AD,MATCH("2026-03-02",'Weekly Data'!$E:$E,0)),"") -> -532 | L10: =IFERROR(INDEX('Weekly Data'!AD:$AD,MATCH("2026-03-16",'Weekly Data'!$E:$E,0))-INDEX('Weekly Data'!AD:$AD,MATCH("2026-03-09",'Weekly Data'!$E:$E,0)),"") -> 0 | M10: =IFERROR(INDEX('Weekly Data'!AD:$AD,MATCH("2026-03-23",'Weekly Data'!$E:$E,0))-INDEX('Weekly Data'!AD:$AD,MATCH("2026-03-16",'Weekly Data'!$E:$E,0)),"") -> 0 | N10: =IFERROR(INDEX('Weekly Data'!AD:$AD,MATCH("2026-03-30",'Weekly Data'!$E:$E,0))-INDEX('Weekly Data'!AD:$AD,MATCH("2026-03-23",'Weekly Data'!$E:$E,0)),"") -> 0 | O10: =IFERROR(INDEX('Weekly Data'!AD:$AD,MATCH("2026-04-06",'Weekly Data'!$E:$E,0))-INDEX('Weekly Data'!AD:$AD,MATCH("2026-03-30",'Weekly Data'!$E:$E,0)),"") -> 0 | P10: =IFERROR(INDEX('Weekly Data'!AD:$AD,MATCH("2026-04-13",'Weekly Data'!$E:$E,0))-INDEX('Weekly Data'!AD:$AD,MATCH("2026-04-06",'Weekly Data'!$E:$E,0)),"") -> 0 | Q10: =IFERROR(INDEX('Weekly Data'!AD:$AD,MATCH("2026-04-20",'Weekly Data'!$E:$E,0))-INDEX('Weekly Data'!AD:$AD,MATCH("2026-04-13",'Weekly Data'!$E:$E,0)),"") -> 0 | R10: =IFERROR(INDEX('Weekly Data'!AD:$AD,MATCH("2026-04-27",'Weekly Data'!$E:$E,0))-INDEX('Weekly Data'!AD:$AD,MATCH("2026-04-20",'Weekly Data'!$E:$E,0)),"") -> 0 | S10: =IFERROR(INDEX('Weekly Data'!AD:$AD,MATCH("2026-05-04",'Weekly Data'!$E:$E,0))-INDEX('Weekly Data'!AD:$AD,MATCH("2026-04-27",'Weekly Data'!$E:$E,0)),"") -> 0 | T10: =IFERROR(INDEX('Weekly Data'!AD:$AD,MATCH("2026-05-11",'Weekly Data'!$E:$E,0))-INDEX('Weekly Data'!AD:$AD,MATCH("2026-05-04",'Weekly Data'!$E:$E,0)),"") -> 0 | U10: =IFERROR(INDEX('Weekly Data'!AD:$AD,MATCH("2026-05-18",'Weekly Data'!$E:$E,0))-INDEX('Weekly Data'!AD:$AD,MATCH("2026-05-11",'Weekly Data'!$E:$E,0)),"") -> 0 | V10: =IFERROR(INDEX('Weekly Data'!AD:$AD,MATCH("2026-05-25",'Weekly Data'!$E:$E,0))-INDEX('Weekly Data'!AD:$AD,MATCH("2026-05-18",'Weekly Data'!$E:$E,0)),"") -> 0 | W10: =IFERROR(INDEX('Weekly Data'!AD:$AD,MATCH("2026-06-01",'Weekly Data'!$E:$E,0))-INDEX('Weekly Data'!AD:$AD,MATCH("2026-05-25",'Weekly Data'!$E:$E,0)),"") -> 0 | X10: =IFERROR(INDEX('Weekly Data'!AD:$AD,MATCH("2026-06-08",'Weekly Data'!$E:$E,0))-INDEX('Weekly Data'!AD:$AD,MATCH("2026-06-01",'Weekly Data'!$E:$E,0)),"") -> 0 | Y10: =IFERROR(INDEX('Weekly Data'!AD:$AD,MATCH("2026-06-15",'Weekly Data'!$E:$E,0))-INDEX('Weekly Data'!AD:$AD,MATCH("2026-06-08",'Weekly Data'!$E:$E,0)),"") -> 0 | Z10: =IFERROR(INDEX('Weekly Data'!AD:$AD,MATCH("2026-06-22",'Weekly Data'!$E:$E,0))-INDEX('Weekly Data'!AD:$AD,MATCH("2026-06-15",'Weekly Data'!$E:$E,0)),"") -> 0 | AA10: =IFERROR(INDEX('Weekly Data'!AD:$AD,MATCH("2026-06-29",'Weekly Data'!$E:$E,0))-INDEX('Weekly Data'!AD:$AD,MATCH("2026-06-22",'Weekly Data'!$E:$E,0)),"") -> 0
A11: Avg Resolution (hrs) (Δ) | B11: =IFERROR(INDEX('Weekly Data'!AF:$AF,MATCH("2026-01-05",'Weekly Data'!$E:$E,0)),"") -> 0 | C11: =IFERROR(INDEX('Weekly Data'!AF:$AF,MATCH("2026-01-12",'Weekly Data'!$E:$E,0))-INDEX('Weekly Data'!AF:$AF,MATCH("2026-01-05",'Weekly Data'!$E:$E,0)),"") -> 0 | D11: =IFERROR(INDEX('Weekly Data'!AF:$AF,MATCH("2026-01-19",'Weekly Data'!$E:$E,0))-INDEX('Weekly Data'!AF:$AF,MATCH("2026-01-12",'Weekly Data'!$E:$E,0)),"") -> 0 | E11: =IFERROR(INDEX('Weekly Data'!AF:$AF,MATCH("2026-01-26",'Weekly Data'!$E:$E,0))-INDEX('Weekly Data'!AF:$AF,MATCH("2026-01-19",'Weekly Data'!$E:$E,0)),"") -> 0 | F11: =IFERROR(INDEX('Weekly Data'!AF:$AF,MATCH("2026-02-02",'Weekly Data'!$E:$E,0))-INDEX('Weekly Data'!AF:$AF,MATCH("2026-01-26",'Weekly Data'!$E:$E,0)),"") -> 0 | G11: =IFERROR(INDEX('Weekly Data'!AF:$AF,MATCH("2026-02-09",'Weekly Data'!$E:$E,0))-INDEX('Weekly Data'!AF:$AF,MATCH("2026-02-02",'Weekly Data'!$E:$E,0)),"") -> 0 | H11: =IFERROR(INDEX('Weekly Data'!AF:$AF,MATCH("2026-02-16",'Weekly Data'!$E:$E,0))-INDEX('Weekly Data'!AF:$AF,MATCH("2026-02-09",'Weekly Data'!$E:$E,0)),"") -> 0 | I11: =IFERROR(INDEX('Weekly Data'!AF:$AF,MATCH("2026-02-23",'Weekly Data'!$E:$E,0))-INDEX('Weekly Data'!AF:$AF,MATCH("2026-02-16",'Weekly Data'!$E:$E,0)),"") -> 0 | J11: =IFERROR(INDEX('Weekly Data'!AF:$AF,MATCH("2026-03-02",'Weekly Data'!$E:$E,0))-INDEX('Weekly Data'!AF:$AF,MATCH("2026-02-23",'Weekly Data'!$E:$E,0)),"") -> 5.66 | K11: =IFERROR(INDEX('Weekly Data'!AF:$AF,MATCH("2026-03-09",'Weekly Data'!$E:$E,0))-INDEX('Weekly Data'!AF:$AF,MATCH("2026-03-02",'Weekly Data'!$E:$E,0)),"") -> -5.66 | L11: =IFERROR(INDEX('Weekly Data'!AF:$AF,MATCH("2026-03-16",'Weekly Data'!$E:$E,0))-INDEX('Weekly Data'!AF:$AF,MATCH("2026-03-09",'Weekly Data'!$E:$E,0)),"") -> 0 | M11: =IFERROR(INDEX('Weekly Data'!AF:$AF,MATCH("2026-03-23",'Weekly Data'!$E:$E,0))-INDEX('Weekly Data'!AF:$AF,MATCH("2026-03-16",'Weekly Data'!$E:$E,0)),"") -> 0 | N11: =IFERROR(INDEX('Weekly Data'!AF:$AF,MATCH("2026-03-30",'Weekly Data'!$E:$E,0))-INDEX('Weekly Data'!AF:$AF,MATCH("2026-03-23",'Weekly Data'!$E:$E,0)),"") -> 0 | O11: =IFERROR(INDEX('Weekly Data'!AF:$AF,MATCH("2026-04-06",'Weekly Data'!$E:$E,0))-INDEX('Weekly Data'!AF:$AF,MATCH("2026-03-30",'Weekly Data'!$E:$E,0)),"") -> 0 | P11: =IFERROR(INDEX('Weekly Data'!AF:$AF,MATCH("2026-04-13",'Weekly Data'!$E:$E,0))-INDEX('Weekly Data'!AF:$AF,MATCH("2026-04-06",'Weekly Data'!$E:$E,0)),"") -> 0 | Q11: =IFERROR(INDEX('Weekly Data'!AF:$AF,MATCH("2026-04-20",'Weekly Data'!$E:$E,0))-INDEX('Weekly Data'!AF:$AF,MATCH("2026-04-13",'Weekly Data'!$E:$E,0)),"") -> 0 | R11: =IFERROR(INDEX('Weekly Data'!AF:$AF,MATCH("2026-04-27",'Weekly Data'!$E:$E,0))-INDEX('Weekly Data'!AF:$AF,MATCH("2026-04-20",'Weekly Data'!$E:$E,0)),"") -> 0 | S11: =IFERROR(INDEX('Weekly Data'!AF:$AF,MATCH("2026-05-04",'Weekly Data'!$E:$E,0))-INDEX('Weekly Data'!AF:$AF,MATCH("2026-04-27",'Weekly Data'!$E:$E,0)),"") -> 0 | T11: =IFERROR(INDEX('Weekly Data'!AF:$AF,MATCH("2026-05-11",'Weekly Data'!$E:$E,0))-INDEX('Weekly Data'!AF:$AF,MATCH("2026-05-04",'Weekly Data'!$E:$E,0)),"") -> 0 | U11: =IFERROR(INDEX('Weekly Data'!AF:$AF,MATCH("2026-05-18",'Weekly Data'!$E:$E,0))-INDEX('Weekly Data'!AF:$AF,MATCH("2026-05-11",'Weekly Data'!$E:$E,0)),"") -> 0 | V11: =IFERROR(INDEX('Weekly Data'!AF:$AF,MATCH("2026-05-25",'Weekly Data'!$E:$E,0))-INDEX('Weekly Data'!AF:$AF,MATCH("2026-05-18",'Weekly Data'!$E:$E,0)),"") -> 0 | W11: =IFERROR(INDEX('Weekly Data'!AF:$AF,MATCH("2026-06-01",'Weekly Data'!$E:$E,0))-INDEX('Weekly Data'!AF:$AF,MATCH("2026-05-25",'Weekly Data'!$E:$E,0)),"") -> 0 | X11: =IFERROR(INDEX('Weekly Data'!AF:$AF,MATCH("2026-06-08",'Weekly Data'!$E:$E,0))-INDEX('Weekly Data'!AF:$AF,MATCH("2026-06-01",'Weekly Data'!$E:$E,0)),"") -> 0 | Y11: =IFERROR(INDEX('Weekly Data'!AF:$AF,MATCH("2026-06-15",'Weekly Data'!$E:$E,0))-INDEX('Weekly Data'!AF:$AF,MATCH("2026-06-08",'Weekly Data'!$E:$E,0)),"") -> 0 | Z11: =IFERROR(INDEX('Weekly Data'!AF:$AF,MATCH("2026-06-22",'Weekly Data'!$E:$E,0))-INDEX('Weekly Data'!AF:$AF,MATCH("2026-06-15",'Weekly Data'!$E:$E,0)),"") -> 0 | AA11: =IFERROR(INDEX('Weekly Data'!AF:$AF,MATCH("2026-06-29",'Weekly Data'!$E:$E,0))-INDEX('Weekly Data'!AF:$AF,MATCH("2026-06-22",'Weekly Data'!$E:$E,0)),"") -> 0
A12: Company Util % (Δ) | B12: =IFERROR(INDEX('Weekly Data'!AJ:$AJ,MATCH("2026-01-05",'Weekly Data'!$E:$E,0)),"") -> 0 | C12: =IFERROR(INDEX('Weekly Data'!AJ:$AJ,MATCH("2026-01-12",'Weekly Data'!$E:$E,0))-INDEX('Weekly Data'!AJ:$AJ,MATCH("2026-01-05",'Weekly Data'!$E:$E,0)),"") -> 0 | D12: =IFERROR(INDEX('Weekly Data'!AJ:$AJ,MATCH("2026-01-19",'Weekly Data'!$E:$E,0))-INDEX('Weekly Data'!AJ:$AJ,MATCH("2026-01-12",'Weekly Data'!$E:$E,0)),"") -> 0 | E12: =IFERROR(INDEX('Weekly Data'!AJ:$AJ,MATCH("2026-01-26",'Weekly Data'!$E:$E,0))-INDEX('Weekly Data'!AJ:$AJ,MATCH("2026-01-19",'Weekly Data'!$E:$E,0)),"") -> 0 | F12: =IFERROR(INDEX('Weekly Data'!AJ:$AJ,MATCH("2026-02-02",'Weekly Data'!$E:$E,0))-INDEX('Weekly Data'!AJ:$AJ,MATCH("2026-01-26",'Weekly Data'!$E:$E,0)),"") -> 0 | G12: =IFERROR(INDEX('Weekly Data'!AJ:$AJ,MATCH("2026-02-09",'Weekly Data'!$E:$E,0))-INDEX('Weekly Data'!AJ:$AJ,MATCH("2026-02-02",'Weekly Data'!$E:$E,0)),"") -> 0 | H12: =IFERROR(INDEX('Weekly Data'!AJ:$AJ,MATCH("2026-02-16",'Weekly Data'!$E:$E,0))-INDEX('Weekly Data'!AJ:$AJ,MATCH("2026-02-09",'Weekly Data'!$E:$E,0)),"") -> 0 | I12: =IFERROR(INDEX('Weekly Data'!AJ:$AJ,MATCH("2026-02-23",'Weekly Data'!$E:$E,0))-INDEX('Weekly Data'!AJ:$AJ,MATCH("2026-02-16",'Weekly Data'!$E:$E,0)),"") -> 0 | J12: =IFERROR(INDEX('Weekly Data'!AJ:$AJ,MATCH("2026-03-02",'Weekly Data'!$E:$E,0))-INDEX('Weekly Data'!AJ:$AJ,MATCH("2026-02-23",'Weekly Data'!$E:$E,0)),"") -> 63.5 | K12: =IFERROR(INDEX('Weekly Data'!AJ:$AJ,MATCH("2026-03-09",'Weekly Data'!$E:$E,0))-INDEX('Weekly Data'!AJ:$AJ,MATCH("2026-03-02",'Weekly Data'!$E:$E,0)),"") -> -63.5 | L12: =IFERROR(INDEX('Weekly Data'!AJ:$AJ,MATCH("2026-03-16",'Weekly Data'!$E:$E,0))-INDEX('Weekly Data'!AJ:$AJ,MATCH("2026-03-09",'Weekly Data'!$E:$E,0)),"") -> 0 | M12: =IFERROR(INDEX('Weekly Data'!AJ:$AJ,MATCH("2026-03-23",'Weekly Data'!$E:$E,0))-INDEX('Weekly Data'!AJ:$AJ,MATCH("2026-03-16",'Weekly Data'!$E:$E,0)),"") -> 0 | N12: =IFERROR(INDEX('Weekly Data'!AJ:$AJ,MATCH("2026-03-30",'Weekly Data'!$E:$E,0))-INDEX('Weekly Data'!AJ:$AJ,MATCH("2026-03-23",'Weekly Data'!$E:$E,0)),"") -> 0 | O12: =IFERROR(INDEX('Weekly Data'!AJ:$AJ,MATCH("2026-04-06",'Weekly Data'!$E:$E,0))-INDEX('Weekly Data'!AJ:$AJ,MATCH("2026-03-30",'Weekly Data'!$E:$E,0)),"") -> 0 | P12: =IFERROR(INDEX('Weekly Data'!AJ:$AJ,MATCH("2026-04-13",'Weekly Data'!$E:$E,0))-INDEX('Weekly Data'!AJ:$AJ,MATCH("2026-04-06",'Weekly Data'!$E:$E,0)),"") -> 0 | Q12: =IFERROR(INDEX('Weekly Data'!AJ:$AJ,MATCH("2026-04-20",'Weekly Data'!$E:$E,0))-INDEX('Weekly Data'!AJ:$AJ,MATCH("2026-04-13",'Weekly Data'!$E:$E,0)),"") -> 0 | R12: =IFERROR(INDEX('Weekly Data'!AJ:$AJ,MATCH("2026-04-27",'Weekly Data'!$E:$E,0))-INDEX('Weekly Data'!AJ:$AJ,MATCH("2026-04-20",'Weekly Data'!$E:$E,0)),"") -> 0 | S12: =IFERROR(INDEX('Weekly Data'!AJ:$AJ,MATCH("2026-05-04",'Weekly Data'!$E:$E,0))-INDEX('Weekly Data'!AJ:$AJ,MATCH("2026-04-27",'Weekly Data'!$E:$E,0)),"") -> 0 | T12: =IFERROR(INDEX('Weekly Data'!AJ:$AJ,MATCH("2026-05-11",'Weekly Data'!$E:$E,0))-INDEX('Weekly Data'!AJ:$AJ,MATCH("2026-05-04",'Weekly Data'!$E:$E,0)),"") -> 0 | U12: =IFERROR(INDEX('Weekly Data'!AJ:$AJ,MATCH("2026-05-18",'Weekly Data'!$E:$E,0))-INDEX('Weekly Data'!AJ:$AJ,MATCH("2026-05-11",'Weekly Data'!$E:$E,0)),"") -> 0 | V12: =IFERROR(INDEX('Weekly Data'!AJ:$AJ,MATCH("2026-05-25",'Weekly Data'!$E:$E,0))-INDEX('Weekly Data'!AJ:$AJ,MATCH("2026-05-18",'Weekly Data'!$E:$E,0)),"") -> 0 | W12: =IFERROR(INDEX('Weekly Data'!AJ:$AJ,MATCH("2026-06-01",'Weekly Data'!$E:$E,0))-INDEX('Weekly Data'!AJ:$AJ,MATCH("2026-05-25",'Weekly Data'!$E:$E,0)),"") -> 0 | X12: =IFERROR(INDEX('Weekly Data'!AJ:$AJ,MATCH("2026-06-08",'Weekly Data'!$E:$E,0))-INDEX('Weekly Data'!AJ:$AJ,MATCH("2026-06-01",'Weekly Data'!$E:$E,0)),"") -> 0 | Y12: =IFERROR(INDEX('Weekly Data'!AJ:$AJ,MATCH("2026-06-15",'Weekly Data'!$E:$E,0))-INDEX('Weekly Data'!AJ:$AJ,MATCH("2026-06-08",'Weekly Data'!$E:$E,0)),"") -> 0 | Z12: =IFERROR(INDEX('Weekly Data'!AJ:$AJ,MATCH("2026-06-22",'Weekly Data'!$E:$E,0))-INDEX('Weekly Data'!AJ:$AJ,MATCH("2026-06-15",'Weekly Data'!$E:$E,0)),"") -> 0 | AA12: =IFERROR(INDEX('Weekly Data'!AJ:$AJ,MATCH("2026-06-29",'Weekly Data'!$E:$E,0))-INDEX('Weekly Data'!AJ:$AJ,MATCH("2026-06-22",'Weekly Data'!$E:$E,0)),"") -> 0
A13: Pipeline Value (Δ) | B13: =IFERROR(INDEX('Weekly Data'!AK:$AK,MATCH("2026-01-05",'Weekly Data'!$E:$E,0)),"") -> 0 | C13: =IFERROR(INDEX('Weekly Data'!AK:$AK,MATCH("2026-01-12",'Weekly Data'!$E:$E,0))-INDEX('Weekly Data'!AK:$AK,MATCH("2026-01-05",'Weekly Data'!$E:$E,0)),"") -> 0 | D13: =IFERROR(INDEX('Weekly Data'!AK:$AK,MATCH("2026-01-19",'Weekly Data'!$E:$E,0))-INDEX('Weekly Data'!AK:$AK,MATCH("2026-01-12",'Weekly Data'!$E:$E,0)),"") -> 0 | E13: =IFERROR(INDEX('Weekly Data'!AK:$AK,MATCH("2026-01-26",'Weekly Data'!$E:$E,0))-INDEX('Weekly Data'!AK:$AK,MATCH("2026-01-19",'Weekly Data'!$E:$E,0)),"") -> 0 | F13: =IFERROR(INDEX('Weekly Data'!AK:$AK,MATCH("2026-02-02",'Weekly Data'!$E:$E,0))-INDEX('Weekly Data'!AK:$AK,MATCH("2026-01-26",'Weekly Data'!$E:$E,0)),"") -> 0 | G13: =IFERROR(INDEX('Weekly Data'!AK:$AK,MATCH("2026-02-09",'Weekly Data'!$E:$E,0))-INDEX('Weekly Data'!AK:$AK,MATCH("2026-02-02",'Weekly Data'!$E:$E,0)),"") -> 0 | H13: =IFERROR(INDEX('Weekly Data'!AK:$AK,MATCH("2026-02-16",'Weekly Data'!$E:$E,0))-INDEX('Weekly Data'!AK:$AK,MATCH("2026-02-09",'Weekly Data'!$E:$E,0)),"") -> 0 | I13: =IFERROR(INDEX('Weekly Data'!AK:$AK,MATCH("2026-02-23",'Weekly Data'!$E:$E,0))-INDEX('Weekly Data'!AK:$AK,MATCH("2026-02-16",'Weekly Data'!$E:$E,0)),"") -> 453948 | J13: =IFERROR(INDEX('Weekly Data'!AK:$AK,MATCH("2026-03-02",'Weekly Data'!$E:$E,0))-INDEX('Weekly Data'!AK:$AK,MATCH("2026-02-23",'Weekly Data'!$E:$E,0)),"") -> -453948 | K13: =IFERROR(INDEX('Weekly Data'!AK:$AK,MATCH("2026-03-09",'Weekly Data'!$E:$E,0))-INDEX('Weekly Data'!AK:$AK,MATCH("2026-03-02",'Weekly Data'!$E:$E,0)),"") -> 0 | L13: =IFERROR(INDEX('Weekly Data'!AK:$AK,MATCH("2026-03-16",'Weekly Data'!$E:$E,0))-INDEX('Weekly Data'!AK:$AK,MATCH("2026-03-09",'Weekly Data'!$E:$E,0)),"") -> 0 | M13: =IFERROR(INDEX('Weekly Data'!AK:$AK,MATCH("2026-03-23",'Weekly Data'!$E:$E,0))-INDEX('Weekly Data'!AK:$AK,MATCH("2026-03-16",'Weekly Data'!$E:$E,0)),"") -> 453948 | N13: =IFERROR(INDEX('Weekly Data'!AK:$AK,MATCH("2026-03-30",'Weekly Data'!$E:$E,0))-INDEX('Weekly Data'!AK:$AK,MATCH("2026-03-23",'Weekly Data'!$E:$E,0)),"") -> -453948 | O13: =IFERROR(INDEX('Weekly Data'!AK:$AK,MATCH("2026-04-06",'Weekly Data'!$E:$E,0))-INDEX('Weekly Data'!AK:$AK,MATCH("2026-03-30",'Weekly Data'!$E:$E,0)),"") -> 0 | P13: =IFERROR(INDEX('Weekly Data'!AK:$AK,MATCH("2026-04-13",'Weekly Data'!$E:$E,0))-INDEX('Weekly Data'!AK:$AK,MATCH("2026-04-06",'Weekly Data'!$E:$E,0)),"") -> 0 | Q13: =IFERROR(INDEX('Weekly Data'!AK:$AK,MATCH("2026-04-20",'Weekly Data'!$E:$E,0))-INDEX('Weekly Data'!AK:$AK,MATCH("2026-04-13",'Weekly Data'!$E:$E,0)),"") -> 0 | R13: =IFERROR(INDEX('Weekly Data'!AK:$AK,MATCH("2026-04-27",'Weekly Data'!$E:$E,0))-INDEX('Weekly Data'!AK:$AK,MATCH("2026-04-20",'Weekly Data'!$E:$E,0)),"") -> 0 | S13: =IFERROR(INDEX('Weekly Data'!AK:$AK,MATCH("2026-05-04",'Weekly Data'!$E:$E,0))-INDEX('Weekly Data'!AK:$AK,MATCH("2026-04-27",'Weekly Data'!$E:$E,0)),"") -> 0 | T13: =IFERROR(INDEX('Weekly Data'!AK:$AK,MATCH("2026-05-11",'Weekly Data'!$E:$E,0))-INDEX('Weekly Data'!AK:$AK,MATCH("2026-05-04",'Weekly Data'!$E:$E,0)),"") -> 0 | U13: =IFERROR(INDEX('Weekly Data'!AK:$AK,MATCH("2026-05-18",'Weekly Data'!$E:$E,0))-INDEX('Weekly Data'!AK:$AK,MATCH("2026-05-11",'Weekly Data'!$E:$E,0)),"") -> 0 | V13: =IFERROR(INDEX('Weekly Data'!AK:$AK,MATCH("2026-05-25",'Weekly Data'!$E:$E,0))-INDEX('Weekly Data'!AK:$AK,MATCH("2026-05-18",'Weekly Data'!$E:$E,0)),"") -> 0 | W13: =IFERROR(INDEX('Weekly Data'!AK:$AK,MATCH("2026-06-01",'Weekly Data'!$E:$E,0))-INDEX('Weekly Data'!AK:$AK,MATCH("2026-05-25",'Weekly Data'!$E:$E,0)),"") -> 0 | X13: =IFERROR(INDEX('Weekly Data'!AK:$AK,MATCH("2026-06-08",'Weekly Data'!$E:$E,0))-INDEX('Weekly Data'!AK:$AK,MATCH("2026-06-01",'Weekly Data'!$E:$E,0)),"") -> 0 | Y13: =IFERROR(INDEX('Weekly Data'!AK:$AK,MATCH("2026-06-15",'Weekly Data'!$E:$E,0))-INDEX('Weekly Data'!AK:$AK,MATCH("2026-06-08",'Weekly Data'!$E:$E,0)),"") -> 0 | Z13: =IFERROR(INDEX('Weekly Data'!AK:$AK,MATCH("2026-06-22",'Weekly Data'!$E:$E,0))-INDEX('Weekly Data'!AK:$AK,MATCH("2026-06-15",'Weekly Data'!$E:$E,0)),"") -> 0 | AA13: =IFERROR(INDEX('Weekly Data'!AK:$AK,MATCH("2026-06-29",'Weekly Data'!$E:$E,0))-INDEX('Weekly Data'!AK:$AK,MATCH("2026-06-22",'Weekly Data'!$E:$E,0)),"") -> 0

Sheet Revenue Lag
A1: DataPath — Revenue Recognition Lag Tracker
A2: Tracks the gap between Revenue Won (ConnectWise) and P&L Recognized (Sage). Won ≠ Billed — equipment/service delivery lag.
A4: Period | B4: Revenue Won | C4: P&L Recognized | D4: Gap ($) | E4: Gap (%) | F4: Notes / Explanation
A5: Jan 2025 | D5: =IF(AND(B5<>"",C5<>""),C5-B5,"") | E5: =IF(AND(B5<>"",B5<>0),(C5-B5)/B5*100,"")
A6: Feb 2025 | D6: =IF(AND(B6<>"",C6<>""),C6-B6,"") | E6: =IF(AND(B6<>"",B6<>0),(C6-B6)/B6*100,"")
A7: Mar 2025 | D7: =IF(AND(B7<>"",C7<>""),C7-B7,"") | E7: =IF(AND(B7<>"",B7<>0),(C7-B7)/B7*100,"")
A8: Apr 2025 | D8: =IF(AND(B8<>"",C8<>""),C8-B8,"") | E8: =IF(AND(B8<>"",B8<>0),(C8-B8)/B8*100,"")
A9: May 2025 | D9: =IF(AND(B9<>"",C9<>""),C9-B9,"") | E9: =IF(AND(B9<>"",B9<>0),(C9-B9)/B9*100,"")
A10: Jun 2025 | D10: =IF(AND(B10<>"",C10<>""),C10-B10,"") | E10: =IF(AND(B10<>"",B10<>0),(C10-B10)/B10*100,"")
A11: Jul 2025 | D11: =IF(AND(B11<>"",C11<>""),C11-B11,"") | E11: =IF(AND(B11<>"",B11<>0),(C11-B11)/B11*100,"")
A12: Aug 2025 | D12: =IF(AND(B12<>"",C12<>""),C12-B12,"") | E12: =IF(AND(B12<>"",B12<>0),(C12-B12)/B12*100,"")
A13: Sep 2025 | D13: =IF(AND(B13<>"",C13<>""),C13-B13,"") | E13: =IF(AND(B13<>"",B13<>0),(C13-B13)/B13*100,"")
A14: Oct 2025 | D14: =IF(AND(B14<>"",C14<>""),C14-B14,"") | E14: =IF(AND(B14<>"",B14<>0),(C14-B14)/B14*100,"")
A15: Nov 2025 | D15: =IF(AND(B15<>"",C15<>""),C15-B15,"") | E15: =IF(AND(B15<>"",B15<>0),(C15-B15)/B15*100,"")
A16: Dec 2025 | D16: =IF(AND(B16<>"",C16<>""),C16-B16,"") | E16: =IF(AND(B16<>"",B16<>0),(C16-B16)/B16*100,"")
A17: Jan 2026 | C17: 1385716 | D17: =IF(AND(B17<>"",C17<>""),C17-B17,"") | E17: =IF(AND(B17<>"",B17<>0),(C17-B17)/B17*100,"")
A18: Feb 2026 | B18: 782928 | C18: 1292505 | D18: =IF(AND(B18<>"",C18<>""),C18-B18,"") -> 509577 | E18: =IF(AND(B18<>"",B18<>0),(C18-B18)/B18*100,"") -> 65.086062 | F18: P&L ($1.29M) > Won ($783K): P&L includes recurring revenue + prior carryover billing not in CW Won report
A19: Mar 2026 | D19: =IF(AND(B19<>"",C19<>""),C19-B19,"") | E19: =IF(AND(B19<>"",B19<>0),(C19-B19)/B19*100,"")
A20: Apr 2026 | D20: =IF(AND(B20<>"",C20<>""),C20-B20,"") | E20: =IF(AND(B20<>"",B20<>0),(C20-B20)/B20*100,"")
A21: May 2026 | D21: =IF(AND(B21<>"",C21<>""),C21-B21,"") | E21: =IF(AND(B21<>"",B21<>0),(C21-B21)/B21*100,"")
A22: Jun 2026 | D22: =IF(AND(B22<>"",C22<>""),C22-B22,"") | E22: =IF(AND(B22<>"",B22<>0),(C22-B22)/B22*100,"")
A23: Jul 2026 | D23: =IF(AND(B23<>"",C23<>""),C23-B23,"") | E23: =IF(AND(B23<>"",B23<>0),(C23-B23)/B23*100,"")
A24: Aug 2026 | D24: =IF(AND(B24<>"",C24<>""),C24-B24,"") | E24: =IF(AND(B24<>"",B24<>0),(C24-B24)/B24*100,"")
A25: Sep 2026 | D25: =IF(AND(B25<>"",C25<>""),C25-B25,"") | E25: =IF(AND(B25<>"",B25<>0),(C25-B25)/B25*100,"")
A26: Oct 2026 | D26: =IF(AND(B26<>"",C26<>""),C26-B26,"") | E26: =IF(AND(B26<>"",B26<>0),(C26-B26)/B26*100,"")
A27: Nov 2026 | D27: =IF(AND(B27<>"",C27<>""),C27-B27,"") | E27: =IF(AND(B27<>"",B27<>0),(C27-B27)/B27*100,"")
A28: Dec 2026 | D28: =IF(AND(B28<>"",C28<>""),C28-B28,"") | E28: =IF(AND(B28<>"",B28<>0),(C28-B28)/B28*100,"")
