Workbook

Sheet Combined Company
B1: Month 1 ($) | C1: Month 1 (%) | D1: Month 2 ($) | E1: Month 2 (%) | F1: Month 3 ($) | G1: Month 3 (%) | H1: Month 4 ($) | I1: Month 4 (%) | J1: Month 5 ($) | K1: Month 5 (%) | L1: Month 6 ($) | M1: Month 6 (%) | N1: Month 7 ($) | O1: Month 7 (%) | P1: Month 8 ($) | Q1: Month 8 (%) | R1: Month 9 ($) | S1: Month 9 (%) | T1: Month 10 ($) | U1: Month 10 (%) | V1: Month 11 ($) | W1: Month 11 (%) | X1: Month 12 ($) | Y1: Month 12 (%) | Z1: 12 Month Totals | AE1: Last 3 Months Average | AF1: Last 3 Months Sparkline
A2: Location | B2: All Locations | D2: All Locations | F2: All Locations | H2: All Locations | I2: All Locations | J2: All Locations | L2: All Locations | N2: All Locations | P2: All Locations | R2: All Locations | T2: All Locations | V2: All Locations | X2: All Locations | Y2: All Locations | Z2: All Locations
A3: Month | B3: 01/31/2023 | D3: 02/28/2023 | F3: 03/31/2023 | H3: 45046 | J3: 45077 | L3: 45107 | N3: 45138 | P3: 45169 | R3: 45199 | T3: 45230 | V3: 45260 | X3: 45291
A4: Days in Month | B4: 31 | D4: 28 | F4: 31 | H4: 30 | J4: 31 | L4: 30 | N4: 31 | P4: 31 | R4: 30 | T4: 31 | V4: 30 | X4: 31
A5: Quarter | B5: 1 | D5: 1 | F5: 1 | H5: 2 | J5: 2 | L5: 2 | N5: 3 | P5: 3 | R5: 3 | T5: 4 | V5: 4 | X5: 4
A6: Year | B6: 2023 | D6: 2023 | F6: 2023 | H6: 2023 | J6: 2023 | L6: 2023 | N6: 2023 | P6: 2023 | R6: 2023 | T6: 2023 | V6: 2023 | X6: 2023
A8: Revenue
A9: Managed IT Services (Recurring IT & Security) | B9: 618563 | C9: =B9/B$17 -> 0.22468648 | D9: 622840 | E9: =D9/D$17 -> 0.30671741 | F9: 676399 | G9: =F9/F$17 -> 0.33281178 | H9: 804317 | I9: =H9/H$17 -> 0.40143331 | J9: 771921 | K9: =J9/J$17 -> 0.31925728 | L9: 816214 | M9: =L9/L$17 -> 0.38111759 | N9: 723940 | O9: =N9/N$17 -> 0.31939286 | P9: 716281 | Q9: =P9/P$17 -> 0.23202932 | R9: 633625 | S9: =R9/R$17 -> 0.24088304 | T9: 592078 | U9: =T9/T$17 -> 0.31310444 | V9: 635168 | W9: =V9/V$17 -> 0.23958921 | X9: 464521 | Y9: =X9/X$17 -> 0.24529537 | Z9: =SUM(B9,D9,F9,H9,J9,L9,N9,P9,R9,T9,V9,X9) -> 8075867 | AE9: =IFERROR(AVERAGE(R9,T9,V9),0) -> 620290.33
A10: Cloud (Private Cloud Only as of 4/1/23) | B10: 482810 | C10: =B10/B$17 -> 0.17537563 | D10: 477754 | E10: =D10/D$17 -> 0.23526984 | F10: 507829 | G10: =F10/F$17 -> 0.24986949 | H10: 70464 | I10: =H10/H$17 -> 0.035168468 | J10: 70467 | K10: =J10/J$17 -> 0.029144307 | L10: 68677 | M10: =L10/L$17 -> 0.032067586 | N10: 63312 | O10: =N10/N$17 -> 0.027932426 | P10: 58680 | Q10: =P10/P$17 -> 0.019008574 | R10: 49426 | S10: =R10/R$17 -> 0.018790112 | T10: 33323 | U10: =T10/T$17 -> 0.017621968 | V10: 34007 | W10: =V10/V$17 -> 0.012827646 | X10: 19383 | Y10: =X10/X$17 -> 0.010235404 | Z10: =SUM(B10,D10,F10,H10,J10,L10,N10,P10,R10,T10,V10,X10) -> 1936132 | AE10: =IFERROR(AVERAGE(R10,T10,V10),0) -> 38918.667
A11: Recurring Resale (Includes previouse Cloud sales) | C11: =B11/B$17 -> 0 | E11: =D11/D$17 -> 0 | G11: =F11/F$17 -> 0 | H11: 251582 | I11: =H11/H$17 -> 0.12556417 | J11: 298554 | K11: =J11/J$17 -> 0.12347836 | L11: 299810 | M11: =L11/L$17 -> 0.13999131 | N11: 289268 | O11: =N11/N$17 -> 0.12762126 | P11: 291785 | Q11: =P11/P$17 -> 0.094519713 | R11: 270887 | S11: =R11/R$17 -> 0.10298218 | T11: 267726 | U11: =T11/T$17 -> 0.14157966 | V11: 242938 | W11: =V11/V$17 -> 0.091637682 | X11: 213581 | Y11: =X11/X$17 -> 0.11278377 | Z11: =SUM(B11,D11,F11,H11,J11,L11,N11,P11,R11,T11,V11,X11) -> 2426131 | AE11: =IFERROR(AVERAGE(R11,T11,V11),0) -> 260517
A12: Project Services | B12: 98569 | C12: =B12/B$17 -> 0.035804149 | D12: 139411 | E12: =D12/D$17 -> 0.068652914 | F12: 106978 | G12: =F12/F$17 -> 0.052636888 | H12: 87200 | I12: =H12/H$17 -> 0.043521379 | J12: 157359 | K12: =J12/J$17 -> 0.065081797 | L12: 58967 | M12: =L12/L$17 -> 0.027533662 | N12: 180502 | O12: =N12/N$17 -> 0.079635121 | P12: 176019 | Q12: =P12/P$17 -> 0.057018919 | R12: 124873 | S12: =R12/R$17 -> 0.047472539 | T12: 84028 | U12: =T12/T$17 -> 0.044435936 | V12: 39227 | W12: =V12/V$17 -> 0.014796661 | X12: 57136 | Y12: =X12/X$17 -> 0.030171287 | Z12: =SUM(B12,D12,F12,H12,J12,L12,N12,P12,R12,T12,V12,X12) -> 1310269 | AE12: =IFERROR(AVERAGE(R12,T12,V12),0) -> 82709.333
A13: Subcontracted Services | B13: 63823 | C13: =B13/B$17 -> 0.023183031 | D13: 78469 | E13: =D13/D$17 -> 0.03864204 | F13: 40805 | G13: =F13/F$17 -> 0.020077476 | H13: 30033 | I13: =H13/H$17 -> 0.014989422 | J13: 36525 | K13: =J13/J$17 -> 0.015106302 | L13: 26588 | M13: =L13/L$17 -> 0.012414826 | N13: 162366 | O13: =N13/N$17 -> 0.071633755 | P13: 60247 | Q13: =P13/P$17 -> 0.019516182 | R13: 28290 | S13: =R13/R$17 -> 0.010754912 | T13: 30162 | U13: =T13/T$17 -> 0.015950358 | V13: 18990 | W13: =V13/V$17 -> 0.0071631427 | X13: 2427 | Y13: =X13/X$17 -> 0.0012816038 | Z13: =SUM(B13,D13,F13,H13,J13,L13,N13,P13,R13,T13,V13,X13) -> 578725 | AE13: =IFERROR(AVERAGE(R13,T13,V13),0) -> 25814
A14: Product Sales | B14: 1465094 | C14: =B14/B$17 -> 0.53217993 | D14: 681484 | E14: =D14/D$17 -> 0.33559663 | F14: 671999 | G14: =F14/F$17 -> 0.33064682 | H14: 746285 | I14: =H14/H$17 -> 0.37246963 | J14: 1072158 | K14: =J14/J$17 -> 0.44343171 | L14: 854343 | M14: =L14/L$17 -> 0.39892129 | N14: 835308 | O14: =N14/N$17 -> 0.36852696 | P14: 1773163 | Q14: =P14/P$17 -> 0.57439162 | R14: 1500169 | S14: =R14/R$17 -> 0.57031409 | T14: 873395 | U14: =T14/T$17 -> 0.46187134 | V14: 1659476 | W14: =V14/V$17 -> 0.62596437 | X14: 1123606 | Y14: =X14/X$17 -> 0.59333239 | Z14: =SUM(B14,D14,F14,H14,J14,L14,N14,P14,R14,T14,V14,X14) -> 13256480 | AE14: =IFERROR(AVERAGE(R14,T14,V14),0) -> 1344346.7
A15: Commissions | B15: 24146 | C15: =B15/B$17 -> 0.0087707796 | D15: 30706 | E15: =D15/D$17 -> 0.015121162 | F15: 28436 | G15: =F15/F$17 -> 0.013991499 | H15: 13732 | I15: =H15/H$17 -> 0.0068536189 | J15: 10881 | K15: =J15/J$17 -> 0.0045002513 | L15: 17034 | M15: =L15/L$17 -> 0.0079537437 | N15: 11917 | O15: =N15/N$17 -> 0.0052576245 | P15: 10853 | Q15: =P15/P$17 -> 0.0035156792 | R15: 23156 | S15: =R15/R$17 -> 0.0088031368 | T15: 10280 | U15: =T15/T$17 -> 0.0054363001 | V15: 21265 | W15: =V15/V$17 -> 0.0080212865 | X15: 13067 | Y15: =X15/X$17 -> 0.0069001717 | Z15: =SUM(B15,D15,F15,H15,J15,L15,N15,P15,R15,T15,V15,X15) -> 215473 | AE15: =IFERROR(AVERAGE(R15,T15,V15),0) -> 18233.667
A16: Sales Returns and Discounts | B16: 0 | C16: =B16/B$17 -> 0 | D16: 0 | E16: =D16/D$17 -> 0 | F16: 69 | G16: =F16/F$17 -> 3.3950394e-05 | H16: 0 | I16: =H16/H$17 -> 0 | J16: 0 | K16: =J16/J$17 -> 0 | L16: 0 | M16: =L16/L$17 -> 0 | N16: 0 | O16: =N16/N$17 -> 0 | P16: 0 | Q16: =P16/P$17 -> 0 | R16: 0 | S16: =R16/R$17 -> 0 | T16: 0 | U16: =T16/T$17 -> 0 | V16: 0 | W16: =V16/V$17 -> 0 | Y16: =X16/X$17 -> 0 | Z16: =SUM(B16,D16,F16,H16,J16,L16,N16,P16,R16,T16,V16,X16) -> 69 | AE16: =IFERROR(AVERAGE(R16,T16,V16),0) -> 0
A17: Total Revenue | B17: 2753005 | C17: =B17/B$17 -> 1 | D17: 2030664 | E17: =D17/D$17 -> 1 | F17: 2032377 | G17: =F17/F$17 -> 1 | H17: 2003613 | I17: =H17/H$17 -> 1 | J17: =SUM(J9:J16) -> 2417865 | K17: =J17/J$17 -> 1 | L17: =SUM(L9:L16) -> 2141633 | M17: =L17/L$17 -> 1 | N17: =SUM(N9:N16) -> 2266613 | O17: =N17/N$17 -> 1 | P17: =SUM(P9:P16) -> 3087028 | Q17: =P17/P$17 -> 1 | R17: =SUM(R9:R16) -> 2630426 | S17: =R17/R$17 -> 1 | T17: =SUM(T9:T16) -> 1890992 | U17: =T17/T$17 -> 1 | V17: =SUM(V9:V16) -> 2651071 | W17: =V17/V$17 -> 1 | X17: =SUM(X9:X16) -> 1893721 | Y17: =X17/X$17 -> 1 | Z17: =SUM(B17,D17,F17,H17,J17,L17,N17,P17,R17,T17,V17,X17) -> 27799008 | AE17: =IFERROR(AVERAGE(R17:V17),0) -> 1434498.2
A20: Cost of Goods and Services
A21: Managed IT Service Costs | B21: 61481 | C21: =B21/B$17 -> 0.022332324 | D21: 87723 | E21: =D21/D$17 -> 0.04319917 | F21: 99230 | G21: =F21/F$17 -> 0.048824603 | H21: 27668 | I21: =H21/H$17 -> 0.013809054 | J21: 29657 | K21: =J21/J$17 -> 0.01226578 | L21: 20710 | M21: =L21/L$17 -> 0.0096701909 | N21: 25579 | O21: =N21/N$17 -> 0.01128512 | P21: 40069 | Q21: =P21/P$17 -> 0.012979798 | R21: 9079 | S21: =R21/R$17 -> 0.0034515322 | T21: 18714 | U21: =T21/T$17 -> 0.009896393 | V21: 19429 | W21: =V21/V$17 -> 0.0073287362 | X21: 19840 | Y21: =X21/X$17 -> 0.010476728 | Z21: =SUM(F21,H21,J21,L21,N21,P21,R21,T21,V21,X21) -> 309975 | AE21: =IFERROR(AVERAGE(R21:V21),0) -> 9444.4027
A22: Cloud Service Costs | B22: 147592 | C22: =B22/B$17 -> 0.053611236 | D22: 152612 | E22: =D22/D$17 -> 0.075153743 | F22: 153032 | G22: =F22/F$17 -> 0.075297054 | H22: 39868 | I22: =H22/H$17 -> 0.019898054 | J22: 40621 | K22: =J22/J$17 -> 0.016800359 | L22: 52167 | M22: =L22/L$17 -> 0.024358515 | N22: 42698 | O22: =N22/N$17 -> 0.018837799 | P22: 26890 | Q22: =P22/P$17 -> 0.0087106434 | R22: 42899 | S22: =R22/R$17 -> 0.016308765 | T22: 12623 | U22: =T22/T$17 -> 0.0066753323 | V22: 17899 | W22: =V22/V$17 -> 0.006751611 | X22: 13321 | Y22: =X22/X$17 -> 0.0070342991 | Z22: =SUM(F22,H22,J22,L22,N22,P22,R22,T22,V22,X22) -> 442018 | AE22: =IFERROR(AVERAGE(R22:V22),0) -> 14684.205
A23: Recurring Resale Costs | C23: =B23/B$17 -> 0 | E23: =D23/D$17 -> 0 | G23: =F23/F$17 -> 0 | H23: 190790 | I23: =H23/H$17 -> 0.09522298 | J23: 179145 | K23: =J23/J$17 -> 0.074092226 | L23: 212008 | M23: =L23/L$17 -> 0.098993618 | N23: 146217 | O23: =N23/N$17 -> 0.064509027 | P23: 204709 | Q23: =P23/P$17 -> 0.066312648 | R23: 179856 | S23: =R23/R$17 -> 0.068375237 | T23: 181262 | U23: =T23/T$17 -> 0.095855509 | V23: 167095 | W23: =V23/V$17 -> 0.063029244 | X23: 148195 | Y23: =X23/X$17 -> 0.078255984 | Z23: =SUM(F23,H23,J23,L23,N23,P23,R23,T23,V23,X23) -> 1609277
A24: Project Service Costs | B24: 0 | C24: =B24/B$17 -> 0 | D24: 942 | E24: =D24/D$17 -> 0.00046388767 | F24: 1071 | G24: =F24/F$17 -> 0.00052696916 | H24: 0 | I24: =H24/H$17 -> 0 | J24: 0 | K24: =J24/J$17 -> 0 | L24: 0 | M24: =L24/L$17 -> 0 | N24: 0 | O24: =N24/N$17 -> 0 | P24: 525 | Q24: =P24/P$17 -> 0.00017006648 | R24: 5449 | S24: =R24/R$17 -> 0.0020715276 | T24: 2916 | U24: =T24/T$17 -> 0.0015420478 | V24: 0 | W24: =V24/V$17 -> 0 | X24: 0 | Y24: =X24/X$17 -> 0 | Z24: =SUM(F24,H24,J24,L24,N24,P24,R24,T24,V24,X24) -> 9961 | AE24: =IFERROR(AVERAGE(R24:V24),0) -> 1673.0007
A25: Subcontractor Service Costs | B25: 53982 | C25: =B25/B$17 -> 0.019608392 | D25: 66267 | E25: =D25/D$17 -> 0.032633168 | F25: 33571 | G25: =F25/F$17 -> 0.016518097 | H25: 25077 | I25: =H25/H$17 -> 0.01251589 | J25: 30438 | K25: =J25/J$17 -> 0.012588792 | L25: 22057 | M25: =L25/L$17 -> 0.01029915 | N25: 138134 | O25: =N25/N$17 -> 0.060942914 | P25: 50205 | Q25: =P25/P$17 -> 0.016263215 | R25: 30005 | S25: =R25/R$17 -> 0.011406898 | T25: 24662 | U25: =T25/T$17 -> 0.013041832 | V25: 15781 | W25: =V25/V$17 -> 0.0059526886 | X25: 1290 | Y25: =X25/X$17 -> 0.00068119855 | Z25: =SUM(F25,H25,J25,L25,N25,P25,R25,T25,V25,X25) -> 371220 | AE25: =IFERROR(AVERAGE(R25:V25),0) -> 14089.605
A26: Product Sales Costs | B26: 1229969 | C26: =B26/B$17 -> 0.44677325 | D26: 544122 | E26: =D26/D$17 -> 0.26795275 | F26: 544407 | G26: =F26/F$17 -> 0.26786713 | H26: 631866 | I26: =H26/H$17 -> 0.3153633 | J26: 905546 | K26: =J26/J$17 -> 0.37452298 | L26: 727333 | M26: =L26/L$17 -> 0.33961608 | N26: 731290 | O26: =N26/N$17 -> 0.32263558 | P26: 1462308 | Q26: =P26/P$17 -> 0.47369444 | R26: 1269641 | S26: =R26/R$17 -> 0.48267505 | T26: 702933 | U26: =T26/T$17 -> 0.37172711 | V26: 1400739 | W26: =V26/V$17 -> 0.52836721 | X26: 943687 | Y26: =X26/X$17 -> 0.4983242 | Z26: =SUM(F26,H26,J26,L26,N26,P26,R26,T26,V26,X26) -> 9319750 | AE26: =IFERROR(AVERAGE(R26:V26),0) -> 674662.77
A27: Total COGS | B27: 1493024 | C27: =B27/B$17 -> 0.5423252 | D27: 851666 | E27: =D27/D$17 -> 0.41940272 | F27: 831311 | G27: =F27/F$17 -> 0.40903386 | H27: 915269 | I27: =H27/H$17 -> 0.45680927 | J27: =SUM(J21:J26) -> 1185407 | K27: =J27/J$17 -> 0.49027014 | L27: =SUM(L21:L26) -> 1034275 | M27: =L27/L$17 -> 0.48293755 | N27: =SUM(N21:N26) -> 1083918 | O27: =N27/N$17 -> 0.47821044 | P27: =SUM(P21:P26) -> 1784706 | Q27: =P27/P$17 -> 0.57813081 | R27: =SUM(R21:R26) -> 1536929 | S27: =R27/R$17 -> 0.58428901 | T27: =SUM(T21:T26) -> 943110 | U27: =T27/T$17 -> 0.49873823 | V27: =SUM(V21:V26) -> 1620943 | W27: =V27/V$17 -> 0.61142949 | X27: =SUM(X21:X26) -> 1126333 | Y27: =X27/X$17 -> 0.59477241 | Z27: =SUM(F27,H27,J27,L27,N27,P27,R27,T27,V27,X27) -> 12062201 | AE27: =IFERROR(AVERAGE(R27:V27),0) -> 820196.62
Z28: =SUM(F28,H28,J28,L28,N28,P28,R28,T28,V28,X28) -> 0
A29: Gross Profit | B29: 1259981 | C29: =B29/B$17 -> 0.4576748 | D29: 1178998 | E29: =D29/D$17 -> 0.58059728 | F29: 1201066 | G29: =F29/F$17 -> 0.59096614 | H29: 1088344 | I29: =H29/H$17 -> 0.54319073 | J29: =+J17-J27 -> 1232458 | K29: =J29/J$17 -> 0.50972986 | L29: =+L17-L27 -> 1107358 | M29: =L29/L$17 -> 0.51706245 | N29: =+N17-N27 -> 1182695 | O29: =N29/N$17 -> 0.52178956 | P29: =+P17-P27 -> 1302322 | Q29: =P29/P$17 -> 0.42186919 | R29: =+R17-R27 -> 1093497 | S29: =R29/R$17 -> 0.41571099 | T29: =+T17-T27 -> 947882 | U29: =T29/T$17 -> 0.50126177 | V29: =+V17-V27 -> 1030128 | W29: =V29/V$17 -> 0.38857051 | X29: =+X17-X27 -> 767388 | Y29: =X29/X$17 -> 0.40522759 | Z29: =SUM(F29,H29,J29,L29,N29,P29,R29,T29,V29,X29) -> 10953138 | AE29: =IFERROR(AVERAGE(R29:V29),0) -> 614301.58
A30: Gross Profit % | B30: 0.4576748 | C30: =C29/C17 -> 0.4576748 | D30: 0.58059728 | E30: =E29/E17 -> 0.58059728 | F30: 0.59096614 | G30: =G29/G17 -> 0.59096614 | H30: 0.54319073 | I30: =I29/I17 -> 0.54319073 | J30: =J29/J17 -> 0.50972986 | K30: =K29/K17 -> 0.50972986 | L30: =L29/L17 -> 0.51706245 | M30: =M29/M17 -> 0.51706245 | N30: =N29/N17 -> 0.52178956 | O30: =O29/O17 -> 0.52178956 | P30: =P29/P17 -> 0.42186919 | ... Z30: =Z29/Z17 -> 0.39401183
A32: Operating Expenses
A33: General & Admin Expenses
A34: Charitable Contributions | B34: 1000 | C34: =B34/B$17 -> 0.00036323944 | D34: 1515 | E34: =D34/D$17 -> 0.00074606139 | F34: 2250 | G34: =F34/F$17 -> 0.0011070781 | H34: 5500 | I34: =H34/H$17 -> 0.0027450411 | J34: 3195 | K34: =J34/J$17 -> 0.0013214137 | L34: 5733 | M34: =L34/L$17 -> 0.0026769292 | N34: 2000 | O34: =N34/N$17 -> 0.00088237383 | P34: 2906 | Q34: =P34/P$17 -> 0.00094135848 | R34: 1990 | S34: =R34/R$17 -> 0.00075653145 | T34: 4549 | U34: =T34/T$17 -> 0.0024056157 | V34: 0 | W34: =V34/V$17 -> 0 | X34: 2120 | Y34: =X34/X$17 -> 0.0011194891 | Z34: =SUM(B34,D34,F34,H34,J34,L34,N34,P34,R34,T34,V34,X34) -> 32758 | AE34: =IFERROR(AVERAGE(R34:V34),0) -> 1307.8006
A35: Education | B35: 384 | C35: =B35/B$17 -> 0.00013948395 | D35: 747 | E35: =D35/D$17 -> 0.00036785997 | F35: 551 | G35: =F35/F$17 -> 0.00027111112 | H35: 30 | I35: =H35/H$17 -> 1.4972951e-05 | J35: 195 | K35: =J35/J$17 -> 8.0649664e-05 | L35: 3530 | M35: =L35/L$17 -> 0.0016482749 | N35: 580 | O35: =N35/N$17 -> 0.00025588841 | P35: 741 | Q35: =P35/P$17 -> 0.0002400367 | R35: 288 | S35: =R35/R$17 -> 0.00010948797 | T35: 393 | U35: =T35/T$17 -> 0.00020782743 | V35: 613 | W35: =V35/V$17 -> 0.0002312273 | X35: 386 | Y35: =X35/X$17 -> 0.0002038315 | Z35: =SUM(B35,D35,F35,H35,J35,L35,N35,P35,R35,T35,V35,X35) -> 8438 | AE35: =IFERROR(AVERAGE(R35:V35),0) -> 258.80006
A36: Finance Charges | B36: 5925 | C36: =B36/B$17 -> 0.0021521937 | D36: 10413 | E36: =D36/D$17 -> 0.0051278794 | F36: 5218 | G36: =F36/F$17 -> 0.002567437 | H36: 5293 | I36: =H36/H$17 -> 0.0026417277 | J36: 4211 | K36: =J36/J$17 -> 0.0017416192 | L36: 6331 | M36: =L36/L$17 -> 0.0029561554 | N36: 3452 | O36: =N36/N$17 -> 0.0015229772 | P36: 6117 | Q36: =P36/P$17 -> 0.0019815175 | R36: 3960 | S36: =R36/R$17 -> 0.0015054596 | T36: 4108 | U36: =T36/T$17 -> 0.0021724047 | V36: 7324 | W36: =V36/V$17 -> 0.0027626571 | X36: 4182 | Y36: =X36/X$17 -> 0.0022083506 | Z36: =SUM(B36,D36,F36,H36,J36,L36,N36,P36,R36,T36,V36,X36) -> 66534 | AE36: =IFERROR(AVERAGE(R36:V36),0) -> 3078.4007
A37: Travel, Meals and Entertainment | B37: 6909 | C37: =B37/B$17 -> 0.0025096213 | D37: 22230 | E37: =D37/D$17 -> 0.010947158 | F37: 23841 | G37: =F37/F$17 -> 0.011730599 | H37: 9221 | I37: =H37/H$17 -> 0.0046021862 | J37: 14196 | K37: =J37/J$17 -> 0.0058712955 | L37: 12582 | M37: =L37/L$17 -> 0.0058749562 | N37: 8217 | O37: =N37/N$17 -> 0.0036252329 | P37: 8361 | Q37: =P37/P$17 -> 0.0027084302 | R37: 16892 | S37: =R37/R$17 -> 0.0064217735 | T37: 16986 | U37: =T37/T$17 -> 0.0089825869 | V37: 22674 | W37: =V37/V$17 -> 0.0085527698 | X37: 9671 | Y37: =X37/X$17 -> 0.0051068769 | Z37: =SUM(B37,D37,F37,H37,J37,L37,N37,P37,R37,T37,V37,X37) -> 171780 | AE37: =IFERROR(AVERAGE(R37:V37),0) -> 11310.403
A38: Office Supplies | B38: 11061 | C38: =B38/B$17 -> 0.0040177915 | D38: 15433 | E38: =D38/D$17 -> 0.0075999772 | F38: 25552 | G38: =F38/F$17 -> 0.012572471 | H38: 5873 | I38: =H38/H$17 -> 0.0029312048 | J38: 10971 | K38: =J38/J$17 -> 0.0045374742 | L38: 9129 | M38: =L38/L$17 -> 0.0042626351 | N38: 6500 | O38: =N38/N$17 -> 0.002867715 | P38: 12606 | Q38: =P38/P$17 -> 0.0040835392 | R38: 10500 | S38: =R38/R$17 -> 0.0039917489 | T38: 8851 | U38: =T38/T$17 -> 0.0046806121 | V38: 9384 | W38: =V38/V$17 -> 0.0035397015 | X38: 12390 | Y38: =X38/X$17 -> 0.0065426744 | Z38: =SUM(B38,D38,F38,H38,J38,L38,N38,P38,R38,T38,V38,X38) -> 138250 | AE38: =IFERROR(AVERAGE(R38:V38),0) -> 5747.0017
A39: Total General and Admin Expenses | B39: 25279 | C39: =B39/B$17 -> 0.0091823299 | D39: 50338 | E39: =D39/D$17 -> 0.024788936 | F39: 57412 | G39: =F39/F$17 -> 0.028248696 | H39: 25917 | I39: =H39/H$17 -> 0.012935133 | J39: 32768 | K39: =J39/J$17 -> 0.013552452 | L39: 37305 | M39: =L39/L$17 -> 0.017418951 | N39: 20749 | O39: =N39/N$17 -> 0.0091541873 | P39: 30731 | Q39: =P39/P$17 -> 0.0099548822 | R39: 33630 | S39: =R39/R$17 -> 0.012785001 | T39: 34886 | U39: =T39/T$17 -> 0.018448518 | V39: 39995 | W39: =V39/V$17 -> 0.015086356 | X39: 28749 | Y39: =X39/X$17 -> 0.015181223 | Z39: =SUM(B39,D39,F39,H39,J39,L39,N39,P39,R39,T39,V39,X39) -> 417759 | AE39: =IFERROR(AVERAGE(R39:V39),0) -> 21702.206
A41: Marketing and Advertising Expenses | B41: 430 | C41: =B41/B$17 -> 0.00015619296 | D41: 6417 | E41: =D41/D$17 -> 0.0031600501 | F41: 1910 | G41: =F41/F$17 -> 0.00093978627 | H41: 4000 | I41: =H41/H$17 -> 0.0019963935 | J41: 5896 | K41: =J41/J$17 -> 0.002438515 | L41: 5720 | M41: =L41/L$17 -> 0.0026708591 | N41: 7191 | O41: =N41/N$17 -> 0.0031725751 | P41: 7283 | Q41: =P41/P$17 -> 0.0023592271 | R41: 8952 | S41: =R41/R$17 -> 0.003403251 | T41: 15252 | U41: =T41/T$17 -> 0.0080656079 | V41: 6862 | W41: =V41/V$17 -> 0.0025883879 | X41: 5872 | Y41: =X41/X$17 -> 0.0031007736 | Z41: =SUM(B41,D41,F41,H41,J41,L41,N41,P41,R41,T41,V41,X41) -> 75785 | AE41: =IFERROR(AVERAGE(R41:V41),0) -> 6213.2023
A43: Payroll and Related Expenses | B43: 541229 | C43: =B43/B$17 -> 0.19659572 | D43: 580256 | E43: =D43/D$17 -> 0.28574693 | F43: 696257 | G43: =F43/F$17 -> 0.3425826 | H43: 604704 | I43: =H43/H$17 -> 0.30180679 | J43: 653761 | K43: =J43/J$17 -> 0.27038772 | L43: 653739 | M43: =L43/L$17 -> 0.30525258 | N43: 626338 | O43: =N43/N$17 -> 0.27633213 | P43: 621699 | Q43: =P43/P$17 -> 0.20139079 | R43: 601845 | S43: =R43/R$17 -> 0.22880134 | T43: 581106 | U43: =T43/T$17 -> 0.3073022 | V43: 577214 | W43: =V43/V$17 -> 0.21772861 | X43: 228687 | Y43: =X43/X$17 -> 0.12076066 | Z43: =SUM(B43,D43,F43,H43,J43,L43,N43,P43,R43,T43,V43,X43) -> 6966835 | AE43: =IFERROR(AVERAGE(R43:V43),0) -> 352033.11
A45: Utilities and Facilities | B45: 36312 | C45: =B45/B$17 -> 0.013189951 | D45: 38163 | E45: =D45/D$17 -> 0.01879336 | F45: 34502 | G45: =F45/F$17 -> 0.016976181 | H45: 35778 | I45: =H45/H$17 -> 0.017856742 | K45: =J45/J$17 -> 0 | L45: 38163 | M45: =L45/L$17 -> 0.01781958 | N45: 28934 | O45: =N45/N$17 -> 0.012765302 | P45: 37666 | Q45: =P45/P$17 -> 0.012201379 | R45: 45659 | S45: =R45/R$17 -> 0.017358025 | T45: 36689 | U45: =T45/T$17 -> 0.019401986 | V45: 21278 | W45: =V45/V$17 -> 0.0080261902 | X45: 9891 | Y45: =X45/X$17 -> 0.0052230503 | Z45: =SUM(B45,D45,F45,H45,J45,L45,N45,P45,R45,T45,V45,X45) -> 363035 | AE45: =IFERROR(AVERAGE(R45:V45),0) -> 20725.207
A47: Ops and Maint. Expenses
A48: Automobile Expenses | C48: =B48/B$17 -> 0 | E48: =D48/D$17 -> 0 | G48: =F48/F$17 -> 0 | H48: 13580 | I48: =H48/H$17 -> 0.006777756 | K48: =J48/J$17 -> 0 | M48: =L48/L$17 -> 0 | O48: =N48/N$17 -> 0 | P48: 17399 | Q48: =P48/P$17 -> 0.0056361653 | R48: 14359 | S48: =R48/R$17 -> 0.0054588116 | T48: 16439 | U48: =T48/T$17 -> 0.0086933208 | V48: 15551 | W48: =V48/V$17 -> 0.0058659312 | X48: 18765 | Y48: =X48/X$17 -> 0.0099090626 | Z48: =SUM(B48,D48,F48,H48,J48,L48,N48,P48,R48,T48,V48,X48) -> 96093 | AE48: =IFERROR(AVERAGE(R48:V48),0) -> 9269.8028
A49: Professional Services | C49: =B49/B$17 -> 0 | E49: =D49/D$17 -> 0 | G49: =F49/F$17 -> 0 | H49: 44878 | I49: =H49/H$17 -> 0.022398537 | K49: =J49/J$17 -> 0 | M49: =L49/L$17 -> 0 | O49: =N49/N$17 -> 0 | P49: 29352 | Q49: =P49/P$17 -> 0.0095081742 | R49: 20853 | S49: =R49/R$17 -> 0.0079276132 | T49: 52286 | U49: =T49/T$17 -> 0.027650038 | V49: 39734 | W49: =V49/V$17 -> 0.014987905 | X49: 21898 | Y49: =X49/X$17 -> 0.011563477 | Z49: =SUM(B49,D49,F49,H49,J49,L49,N49,P49,R49,T49,V49,X49) -> 209001 | AE49: =IFERROR(AVERAGE(R49:V49),0) -> 22574.607
A50: Software and Maintenance | C50: =B50/B$17 -> 0 | E50: =D50/D$17 -> 0 | G50: =F50/F$17 -> 0 | H50: 11529 | I50: =H50/H$17 -> 0.0057541052 | K50: =J50/J$17 -> 0 | M50: =L50/L$17 -> 0 | O50: =N50/N$17 -> 0 | P50: 13578 | Q50: =P50/P$17 -> 0.0043984052 | R50: 24959 | S50: =R50/R$17 -> 0.0094885771 | T50: 15674 | U50: =T50/T$17 -> 0.0082887712 | V50: 34952 | W50: =V50/V$17 -> 0.013184106 | X50: 25275 | Y50: =X50/X$17 -> 0.013346739 | Z50: =SUM(B50,D50,F50,H50,J50,L50,N50,P50,R50,T50,V50,X50) -> 125967 | AE50: =IFERROR(AVERAGE(R50:V50),0) -> 15117.004
A51: Other Operating Expense | C51: =B51/B$17 -> 0 | E51: =D51/D$17 -> 0 | G51: =F51/F$17 -> 0 | H51: 0 | I51: =H51/H$17 -> 0 | K51: =J51/J$17 -> 0 | M51: =L51/L$17 -> 0 | O51: =N51/N$17 -> 0 | P51: 0 | Q51: =P51/P$17 -> 0 | S51: =R51/R$17 -> 0 | T51: 0 | U51: =T51/T$17 -> 0 | V51: 0 | W51: =V51/V$17 -> 0 | X51: 0 | Y51: =X51/X$17 -> 0 | Z51: =SUM(B51,D51,F51,H51,J51,L51,N51,P51,R51,T51,V51,X51) -> 0 | AE51: =IFERROR(AVERAGE(R51:V51),0) -> 0
A52: Total Ops and Maint. Expenses | B52: 45055 | C52: =B52/B$17 -> 0.016365753 | D52: 64157 | E52: =D52/D$17 -> 0.031594099 | F52: 51614 | G52: =F52/F$17 -> 0.025395879 | H52: 69987 | I52: =H52/H$17 -> 0.034930398 | J52: 34870 | K52: =J52/J$17 -> 0.014421814 | L52: 31758 | M52: =L52/L$17 -> 0.014828871 | N52: 61214 | O52: =N52/N$17 -> 0.027006816 | P52: 60329 | Q52: =P52/P$17 -> 0.019542745 | R52: 60161 | S52: =R52/R$17 -> 0.0228712 | T52: 84399 | U52: =T52/T$17 -> 0.04463213 | V52: 90237 | W52: =V52/V$17 -> 0.034037942 | X52: 65938 | Y52: =X52/X$17 -> 0.034819279 | Z52: =SUM(B52,D52,F52,H52,J52,L52,N52,P52,R52,T52,V52,X52) -> 719719 | AE52: =IFERROR(AVERAGE(R52:V52),0) -> 46959.414
A54: Taxes and Insurance
A55: Insurance | C55: =B55/B$17 -> 0 | E55: =D55/D$17 -> 0 | G55: =F55/F$17 -> 0 | H55: 4272 | I55: =H55/H$17 -> 0.0021321483 | J55: 6612 | K55: =J55/J$17 -> 0.002734644 | L55: 5919 | M55: =L55/L$17 -> 0.0027637789 | N55: 6527 | O55: =N55/N$17 -> 0.002879627 | P55: 7661 | Q55: =P55/P$17 -> 0.0024816749 | R55: 11258 | S55: =R55/R$17 -> 0.0042799151 | T55: 5689 | U55: =T55/T$17 -> 0.0030084739 | V55: 4396 | W55: =V55/V$17 -> 0.0016581978 | X55: 6317 | Y55: =X55/X$17 -> 0.0033357607 | Z55: =SUM(B55,D55,F55,H55,J55,L55,N55,P55,R55,T55,V55,X55) -> 58651 | AE55: =IFERROR(AVERAGE(R55:V55),0) -> 4268.6015
A56: Taxes | H56: 0 | J56: 0 | L56: 0 | N56: 6442 | P56: 0 | R56: 0 | V56: 2 | X56: 0 | Z56: =SUM(B56,D56,F56,H56,J56,L56,N56,P56,R56,T56,V56,X56) -> 6444 | AE56: =IFERROR(AVERAGE(R56:V56),0) -> 1
A57: Total Taxes and Insurance | B57: 27328 | C57: =B57/B$17 -> 0.0099266075 | D57: 11065 | E57: =D57/D$17 -> 0.0054489566 | F57: 19054 | G57: =F57/F$17 -> 0.0093752291 | H57: 4272 | I57: =H57/H$17 -> 0.0021321483 | J57: 6612 | K57: =J57/J$17 -> 0.002734644 | L57: 2919 | M57: =L57/L$17 -> 0.0013629786 | N57: 12969 | O57: =N57/N$17 -> 0.0057217531 | P57: 7661 | Q57: =P57/P$17 -> 0.0024816749 | R57: 11258 | S57: =R57/R$17 -> 0.0042799151 | T57: 5689 | U57: =T57/T$17 -> 0.0030084739 | V57: 4398 | W57: =V57/V$17 -> 0.0016589522 | X57: 6317 | Y57: =X57/X$17 -> 0.0033357607 | Z57: =SUM(B57,D57,F57,H57,J57,L57,N57,P57,R57,T57,V57,X57) -> 119542 | AE57: =IFERROR(AVERAGE(R57:V57),0) -> 4269.0015
A58: Total Operating Expenses | B58: 675633 | C58: =B58/B$17 -> 0.24541655 | D58: 750396 | E58: =D58/D$17 -> 0.36953233 | F58: 860749 | G58: =F58/F$17 -> 0.42351837 | H58: 744658 | I58: =H58/H$17 -> 0.3716576 | J58: 790453 | K58: =J58/J$17 -> 0.32692189 | L58: 768174 | M58: =L58/L$17 -> 0.35868611 | N58: 757395 | O58: =N58/N$17 -> 0.33415276 | P58: 765368 | Q58: =P58/P$17 -> 0.24793037 | R58: 731505 | S58: =R58/R$17 -> 0.27809374 | T58: 758021 | U58: =T58/T$17 -> 0.40085891 | V58: 755656 | W58: =V58/V$17 -> 0.28503801 | X58: 901781 | Y58: =X58/X$17 -> 0.47619528 | Z58: =SUM(B58,D58,F58,H58,J58,L58,N58,P58,R58,T58,V58,X58) -> 9259789 | AE58: =IFERROR(AVERAGE(R58:V58),0) -> 449036.54
Z59: =SUM(F59,H59,J59,L59,N59,P59,R59,T59,V59,X59) -> 0
A60: Net Operating Income | B60: 584348 | C60: =B60/B$17 -> 0.21225824 | D60: 428602 | E60: =D60/D$17 -> 0.21106495 | F60: 340317 | G60: =F60/F$17 -> 0.16744777 | H60: 343686 | I60: =H60/H$17 -> 0.17153313 | J60: =J29-J58 -> 442005 | K60: =J60/J$17 -> 0.18280797 | L60: =L29-L58 -> 339184 | M60: =L60/L$17 -> 0.15837634 | N60: =N29-N58 -> 425300 | O60: =N60/N$17 -> 0.1876368 | P60: =P29-P58 -> 536954 | Q60: =P60/P$17 -> 0.17393882 | R60: =R29-R58 -> 361992 | S60: =R60/R$17 -> 0.13761725 | T60: =T29-T58 -> 189861 | U60: =T60/T$17 -> 0.10040286 | V60: =V29-V58 -> 274472 | W60: =V60/V$17 -> 0.1035325 | X60: =X29-X58 -> -134393 | Y60: =X60/X$17 -> -0.070967687 | Z60: =SUM(B60,D60,F60,H60,J60,L60,N60,P60,R60,T60,V60,X60) -> 4132328 | AE60: =IFERROR(AVERAGE(R60:V60),0) -> 165265.05
A61: Net Operating Income % | B61: 0.1046489 | C61: =C60/C17 -> 0.21225824 | D61: 0.10159366 | E61: =E60/E17 -> 0.21106495 | F61: 0.21225824 | G61: =G60/G17 -> 0.16744777 | H61: 0.21106495 | I61: =I60/I17 -> 0.17153313 | J61: 0.16744777 | K61: =K60/K17 -> 0.18280797 | L61: 0.17153313 | M61: =M60/M17 -> 0.15837634 | N61: =N60/N17 -> 0.1876368 | O61: =O60/O17 -> 0.1876368 | P61: =P60/P17 -> 0.17393882 | Q61: =Q60/Q17 -> 0.17393882 | R61: =R60/R17 -> 0.13761725 | S61: =S60/S17 -> 0.13761725 | T61: =T60/T17 -> 0.10040286 | ... Z61: =Z60/Z17 -> 0.1486502
A63: Other Income (Expense)
A64: Other Income
A65: Interest Income | B65: 0 | D65: 0 | F65: 0 | H65: 0 | J65: 0 | N65: 781 | P65: 0 | R65: 0 | X65: 468 | Z65: =SUM(B65,D65,F65,H65,J65,L65,N65,P65,R65,T65,V65,X65) -> 1249 | AE65: =IFERROR(AVERAGE(R65:V65),0) -> 0
A66: Other Income | B66: 0 | C66: =B66/B$17 -> 0 | D66: 20 | E66: =D66/D$17 -> 9.8489952e-06 | F66: 0 | G66: =F66/F$17 -> 0 | H66: 0 | I66: =H66/H$17 -> 0 | J66: 504 | K66: =J66/J$17 -> 0.00020844836 | M66: =L66/L$17 -> 0 | N66: 2256 | O66: =N66/N$17 -> 0.00099531768 | P66: 0 | Q66: =P66/P$17 -> 0 | R66: 1433 | S66: =R66/R$17 -> 0.00054477868 | T66: 0 | U66: =T66/T$17 -> 0 | W66: =V66/V$17 -> 0 | X66: 454000 | Y66: =X66/X$17 -> 0.23973964 | Z66: =SUM(B66,D66,F66,H66,J66,L66,N66,P66,R66,T66,V66,X66) -> 458213 | AE66: =IFERROR(AVERAGE(R66:V66),0) -> 358.25014
A67: Total Other Income | B67: 0 | C67: =B67/B$17 -> 0 | D67: 20 | E67: =D67/D$17 -> 9.8489952e-06 | F67: 0 | G67: =F67/F$17 -> 0 | H67: 0 | I67: =H67/H$17 -> 0 | J67: 504 | K67: =J67/J$17 -> 0.00020844836 | M67: =L67/L$17 -> 0 | N67: =+N66+N65 -> 3037 | O67: =N67/N$17 -> 0.0013398847 | P67: 0 | Q67: =P67/P$17 -> 0 | R67: 1433 | S67: =R67/R$17 -> 0.00054477868 | T67: 0 | U67: =T67/T$17 -> 0 | V67: 916 | W67: =V67/V$17 -> 0.00034552073 | X67: =+X66+X65 -> 454468 | Y67: =X67/X$17 -> 0.23998678 | Z67: =SUM(B67,D67,F67,H67,J67,L67,N67,P67,R67,T67,V67,X67) -> 460378 | AE67: =IFERROR(AVERAGE(R67:V67),0) -> 469.80011
A69: Other Expense
A70: Interest Expenses | B70: -10982 | C70: =B70/B$17 -> -0.0039890956 | D70: -2758 | E70: =D70/D$17 -> -0.0013581764 | F70: -10982 | G70: =F70/F$17 -> -0.005403525 | H70: -11178 | I70: =H70/H$17 -> -0.0055789217 | J70: -11489 | K70: =J70/J$17 -> -0.0047517128 | L70: -11541 | M70: =L70/L$17 -> -0.0053888785 | N70: -11356 | O70: =N70/N$17 -> -0.0050101186 | P70: -11869 | Q70: =P70/P$17 -> -0.0038447983 | R70: -11145 | S70: =R70/R$17 -> -0.0042369563 | T70: -10330 | U70: =T70/T$17 -> -0.0054627412 | V70: -11177 | W70: =V70/V$17 -> -0.0042160319 | X70: -11078 | Y70: =X70/X$17 -> -0.0058498586 | Z70: =SUM(B70,D70,F70,H70,J70,L70,N70,P70,R70,T70,V70,X70) -> -125885 | AE70: =IFERROR(AVERAGE(R70:V70),0) -> -6530.4019
A71: Partnership Expenses | B71: -9822 | C71: =B71/B$17 -> -0.0035677378 | D71: -19616 | E71: =D71/D$17 -> -0.0096598945 | F71: -9917 | G71: =F71/F$17 -> -0.0048795081 | H71: -17067 | I71: =H71/H$17 -> -0.008518112 | J71: -18300 | K71: =J71/J$17 -> -0.0075686608 | L71: -14252 | M71: =L71/L$17 -> -0.006654735 | N71: -29295 | O71: =N71/N$17 -> -0.012924571 | P71: -21259 | Q71: =P71/P$17 -> -0.0068865589 | R71: -14497 | S71: =R71/R$17 -> -0.0055112746 | T71: -16176 | U71: =T71/T$17 -> -0.0085542403 | V71: -22239 | W71: =V71/V$17 -> -0.0083886852 | X71: -33345 | Y71: =X71/X$17 -> -0.01760819 | Z71: =SUM(B71,D71,F71,H71,J71,L71,N71,P71,R71,T71,V71,X71) -> -225785 | AE71: =IFERROR(AVERAGE(R71:V71),0) -> -10582.403
A72: Other Expenses | B72: -1 | C72: =B72/B$17 -> -3.6323944e-07 | D72: -12 | E72: =D72/D$17 -> -5.9093971e-06 | F72: -2 | G72: =F72/F$17 -> -9.8406939e-07 | H72: 0 | I72: =H72/H$17 -> 0 | J72: 0 | K72: =J72/J$17 -> 0 | L72: 0 | M72: =L72/L$17 -> 0 | N72: 0 | O72: =N72/N$17 -> 0 | P72: 0 | Q72: =P72/P$17 -> 0 | R72: 0 | S72: =R72/R$17 -> 0 | T72: 0 | U72: =T72/T$17 -> 0 | V72: 0 | W72: =V72/V$17 -> 0 | X72: 0 | Y72: =X72/X$17 -> 0 | Z72: =SUM(B72,D72,F72,H72,J72,L72,N72,P72,R72,T72,V72,X72) -> -15 | AE72: =IFERROR(AVERAGE(R72:V72),0) -> 0
A73: Total Other Expense | B73: =SUM(B70:B72) -> -20805 | C73: =B73/B$17 -> -0.0075571966 | D73: =SUM(D70:D72) -> -22386 | E73: =D73/D$17 -> -0.01102398 | F73: =SUM(F70:F72) -> -20901 | G73: =F73/F$17 -> -0.010284017 | H73: =SUM(H70:H72) -> -28245 | I73: =H73/H$17 -> -0.014097034 | J73: =SUM(J70:J72) -> -29789 | K73: =J73/J$17 -> -0.012320374 | L73: =SUM(L70:L72) -> -25793 | M73: =L73/L$17 -> -0.012043613 | N73: =SUM(N70:N72) -> -40651 | O73: =N73/N$17 -> -0.017934689 | P73: =SUM(P70:P72) -> -33128 | Q73: =P73/P$17 -> -0.010731357 | R73: =SUM(R70:R72) -> -25642 | S73: =R73/R$17 -> -0.0097482309 | T73: =SUM(T70:T72) -> -26506 | U73: =T73/T$17 -> -0.014016982 | V73: =SUM(V70:V72) -> -33416 | W73: =V73/V$17 -> -0.012604717 | X73: =SUM(X70:X72) -> -44423 | Y73: =X73/X$17 -> -0.023458049 | Z73: =SUM(B73,D73,F73,H73,J73,L73,N73,P73,R73,T73,V73,X73) -> -351685 | AE73: =IFERROR(AVERAGE(R73:V73),0) -> -17112.805
A74: Total Other Income (Expense) | B74: =+B73+B67 -> -20805 | C74: =B74/B$17 -> -0.0075571966 | D74: =+D73+D67 -> -22366 | E74: =D74/D$17 -> -0.011014131 | F74: =+F73+F67 -> -20901 | G74: =F74/F$17 -> -0.010284017 | H74: =+H73+H67 -> -28245 | I74: =H74/H$17 -> -0.014097034 | J74: =+J73+J67 -> -29285 | K74: =J74/J$17 -> -0.012111925 | L74: =+L73+L67 -> -25793 | M74: =L74/L$17 -> -0.012043613 | N74: =+N73+N67 -> -37614 | O74: =N74/N$17 -> -0.016594805 | P74: =+P73+P67 -> -33128 | Q74: =P74/P$17 -> -0.010731357 | R74: =+R73+R67 -> -24209 | S74: =R74/R$17 -> -0.0092034522 | T74: =+T73+T67 -> -26506 | U74: =T74/T$17 -> -0.014016982 | V74: -32500 | W74: =V74/V$17 -> -0.012259196 | X74: 408597 | Y74: =X74/X$17 -> 0.2157641 | Z74: =SUM(B74,D74,F74,H74,J74,L74,N74,P74,R74,T74,V74,X74) -> 107245 | AE74: =IFERROR(AVERAGE(R74:V74),0) -> -16643.005
A76: Income Taxes
A77: State and Local Taxes | B77: 7548 | C77: =B77/B$17 -> 0.0027417313 | D77: 1516 | E77: =D77/D$17 -> 0.00074655384 | F77: 0 | G77: =F77/F$17 -> 0 | H77: 94 | I77: =H77/H$17 -> 4.6915248e-05 | J77: 441 | K77: =J77/J$17 -> 0.00018239232 | M77: =L77/L$17 -> 0 | N77: 0 | O77: =N77/N$17 -> 0 | P77: 42 | Q77: =P77/P$17 -> 1.3605319e-05 | R77: 6689 | S77: =R77/R$17 -> 0.0025429341 | T77: 0 | U77: =T77/T$17 -> 0 | V77: 7562 | W77: =V77/V$17 -> 0.0028524321 | X77: 0 | Y77: =X77/X$17 -> 0 | Z77: =SUM(B77,D77,F77,H77,J77,L77,N77,P77,R77,T77,V77,X77) -> 23892 | AE77: =IFERROR(AVERAGE(R77:V77),0) -> 2850.2005
A78: Total Income Taxes | B78: 7548 | C78: =B78/B$17 -> 0.0027417313 | D78: 1516 | E78: =D78/D$17 -> 0.00074655384 | F78: 0 | G78: =F78/F$17 -> 0 | H78: 94 | I78: =H78/H$17 -> 4.6915248e-05 | J78: 441 | K78: =J78/J$17 -> 0.00018239232 | L78: 3419 | M78: =L78/L$17 -> 0.0015964453 | N78: 0 | O78: =N78/N$17 -> 0 | P78: 42 | Q78: =P78/P$17 -> 1.3605319e-05 | R78: 6689 | S78: =R78/R$17 -> 0.0025429341 | T78: 0 | U78: =T78/T$17 -> 0 | V78: 7562 | W78: =V78/V$17 -> 0.0028524321 | X78: 0 | Y78: =X78/X$17 -> 0 | Z78: =SUM(B78,D78,F78,H78,J78,L78,N78,P78,R78,T78,V78,X78) -> 27311 | AE78: =IFERROR(AVERAGE(R78:V78),0) -> 2850.2005
A80: Net Income (Loss) | B80: =+B60+B74-B78 -> 555995 | C80: =B80/B$17 -> 0.20195931 | D80: =+D60+D74-D78 -> 404720 | E80: =D80/D$17 -> 0.19930427 | F80: =+F60+F74-F78 -> 319416 | G80: =F80/F$17 -> 0.15716375 | H80: =+H60+H74-H78 -> 315347 | I80: =H80/H$17 -> 0.15738918 | J80: =+J60+J74-J78 -> 412279 | K80: =J80/J$17 -> 0.17051366 | L80: =+L60+L74-L78 -> 309972 | M80: =L80/L$17 -> 0.14473628 | N80: =+N60+N74-N78 -> 387686 | O80: =N80/N$17 -> 0.17104199 | P80: =+P60+P74-P78 -> 503784 | Q80: =P80/P$17 -> 0.16319386 | R80: =+R60+R74-R78 -> 331094 | S80: =R80/R$17 -> 0.12587087 | T80: =+T60+T74-T78 -> 163355 | U80: =T80/T$17 -> 0.086385876 | V80: =+V60+V74-V78 -> 234410 | W80: =V80/V$17 -> 0.088420868 | X80: =+X60+X74-X78 -> 274204 | Y80: =X80/X$17 -> 0.14479641 | Z80: =SUM(B80,D80,F80,H80,J80,L80,N80,P80,R80,T80,V80,X80) -> 4212262 | AE80: =IFERROR(AVERAGE(R80:V80),0) -> 145771.84
A81: Net Profit % | B81: =B80/B17 -> 0.20195931 | C81: =C80/C17 -> 0.20195931 | D81: 0.088640687 | E81: =E80/E17 -> 0.19930427 | F81: 0.20466617 | G81: =G80/G17 -> 0.15716375 | H81: 0.19710942 | I81: =I80/I17 -> 0.15738918 | J81: 0.15282155 | K81: =K80/K17 -> 0.17051366 | L81: 0.15695346 | M81: =M80/M17 -> 0.14473628 | N81: =N80/N17 -> 0.17104199 | O81: =O80/O17 -> 0.17104199 | P81: =P80/P17 -> 0.16319386 | Q81: =Q80/Q17 -> 0.16319386 | R81: =R80/R17 -> 0.12587087 | S81: =S80/S17 -> 0.12587087 | T81: =T80/T17 -> 0.086385876 | ... Z81: =Z80/Z17 -> 0.15152562
V82: 234411
A87: Gross Profit % | B87: =B29/B17 -> 0.4576748 | C87: =C29/C17 -> 0.4576748 | D87: =D29/D17 -> 0.58059728 | E87: =E29/E17 -> 0.58059728 | F87: =F29/F17 -> 0.59096614 | G87: =G29/G17 -> 0.59096614 | H87: =H29/H17 -> 0.54319073 | I87: =I29/I17 -> 0.54319073 | ... Z87: =Z29/Z17 -> 0.39401183
A88: Net Operating Income % | B88: =B60/B17 -> 0.21225824 | C88: =C60/C17 -> 0.21225824 | D88: =D60/D17 -> 0.21106495 | E88: =E60/E17 -> 0.21106495 | F88: =F60/F17 -> 0.16744777 | G88: =G60/G17 -> 0.16744777 | H88: =H60/H17 -> 0.17153313 | I88: =I60/I17 -> 0.17153313 | ... Z88: =Z60/Z17 -> 0.1486502
A89: Net Profit % | B89: =B80/B17 -> 0.20195931 | C89: =C80/C17 -> 0.20195931 | D89: =D80/D17 -> 0.19930427 | E89: =E80/E17 -> 0.19930427 | F89: =F80/F17 -> 0.15716375 | G89: =G80/G17 -> 0.15716375 | H89: =H80/H17 -> 0.15738918 | I89: =I80/I17 -> 0.15738918 | ... Z89: =Z80/Z17 -> 0.15152562
A90: Payroll to Total Revenue % | B90: =IFERROR(B43/B17,0) -> 0.19659572 | C90: =IFERROR(C43/C17,0) -> 0.19659572 | D90: =IFERROR(D43/D17,0) -> 0.28574693 | E90: =IFERROR(E43/E17,0) -> 0.28574693 | F90: =IFERROR(F43/F17,0) -> 0.3425826 | G90: =IFERROR(G43/G17,0) -> 0.3425826 | H90: =IFERROR(H43/H17,0) -> 0.30180679 | I90: =IFERROR(I43/I17,0) -> 0.30180679 | ... Z90: =IFERROR(Z43/Z17,0) -> 0.25061452
A91: Payroll to Services Revenue % | B91: =IFERROR(B43/SUM(B9,B10,B11,B12),0) -> 0.45104597 | C91: =IFERROR(C43/SUM(C9,C10,C11,C12),0) -> 0.45104597 | D91: =IFERROR(D43/SUM(D9,D10,D11,D12),0) -> 0.4679465 | E91: =IFERROR(E43/SUM(E9,E10,E11,E12),0) -> 0.4679465 | F91: =IFERROR(F43/SUM(F9,F10,F11,F12),0) -> 0.53922999 | G91: =IFERROR(G43/SUM(G9,G10,G11,G12),0) -> 0.53922999 | H91: =IFERROR(H43/SUM(H9,H10,H11,H12),0) -> 0.4982881 | I91: =IFERROR(I43/SUM(I9,I10,I11,I12),0) -> 0.4982881 | ... Z91: =IFERROR(Z43/SUM(Z9,Z10,Z11,Z12),0) -> 0.50673791
A92: Payroll to Services + Product Margin % | B92: =IFERROR(B43/(SUM(B9,B10,B11,B12)+(B13+B14-B25-B26)),0) -> 0.37457679 | C92: =IFERROR(C43/(SUM(C9,C10,C11,C12)+(C13+C14-C25-C26)),0) -> 0.37457679 | D92: =IFERROR(D43/(SUM(D9,D10,D11,D12)+(D13+D14-D25-D26)),0) -> 0.41757984 | E92: =IFERROR(E43/(SUM(E9,E10,E11,E12)+(E13+E14-E25-E26)),0) -> 0.41757984 | F92: =IFERROR(F43/(SUM(F9,F10,F11,F12)+(F13+F14-F25-F26)),0) -> 0.48824781 | G92: =IFERROR(G43/(SUM(G9,G10,G11,G12)+(G13+G14-G25-G26)),0) -> 0.48824781 | H92: =IFERROR(H43/(SUM(H9,H10,H11,H12)+(H13+H14-H25-H26)),0) -> 0.45366251 | I92: =IFERROR(I43/(SUM(I9,I10,I11,I12)+(I13+I14-I25-I26)),0) -> 0.45366251 | ... Z92: =IFERROR(Z43/(SUM(Z9,Z10,Z11,Z12)+(Z13+Z14-Z25-Z26)),0) -> 0.38936889
A93: Product (One Time) Sales Profit % | B93: =(B14-B26)/B14 -> 0.16048458 | C93: =(C14-C26)/C14 -> 0.16048458 | D93: =(D14-D26)/D14 -> 0.20156306 | E93: =(E14-E26)/E14 -> 0.20156306 | F93: =(F14-F26)/F14 -> 0.18986933 | G93: =(G14-G26)/G14 -> 0.18986933 | H93: =(H14-H26)/H14 -> 0.1533181 | I93: =(I14-I26)/I14 -> 0.1533181 | ... Z93: =(Z14-Z26)/Z14 -> 0.29696646
A94: Product (One Time) Sales Profit $ | B94: =B14-B26 -> 235125 | C94: =C14-C26 -> 0.085406674 | D94: =D14-D26 -> 137362 | E94: =E14-E26 -> 0.067643884 | F94: =F14-F26 -> 127592 | G94: =G14-G26 -> 0.062779691 | H94: =H14-H26 -> 114419 | I94: =I14-I26 -> 0.057106337 | ... Z94: =Z14-Z26 -> 3936730
A95: Product Sales % of Total Revenue | B95: =B14/B17 -> 0.53217993 | C95: =C14/C17 -> 0.53217993 | D95: =D14/D17 -> 0.33559663 | E95: =E14/E17 -> 0.33559663 | F95: =F14/F17 -> 0.33064682 | G95: =G14/G17 -> 0.33064682 | H95: =H14/H17 -> 0.37246963 | I95: =I14/I17 -> 0.37246963 | ... Z95: =Z14/Z17 -> 0.47686881

Sheet Ohio
B1: Month 1 ($) | C1: Month 1 (%) | D1: Month 2 ($) | E1: Month 2 (%) | F1: Month 3 ($) | G1: Month 3 (%) | H1: Month 4 ($) | I1: Month 4 (%) | J1: Month 5 ($) | K1: Month 5 (%) | L1: Month 6 ($) | M1: Month 6 (%) | N1: Month 7 ($) | O1: Month 7 (%) | P1: Month 8 ($) | Q1: Month 8 (%) | R1: Month 9 ($) | S1: Month 9 (%) | T1: Month 10 ($) | U1: Month 10 (%) | V1: Month 11 ($) | W1: Month 11 (%) | X1: Month 12 ($) | Y1: Month 12 (%) | Z1: 12 Month Totals | AA1: 12 Month Average | AB1: 3 Month Average | AD1: 10 Month Sparkline | AE1: Last 3 Months Average | AF1: Last 3 Months Sparkline | AG1: Target $ | AH1: Target % | AI1: Swag for Neutral | AJ1: Dashboard | AK1: Annual Budget Q1 * 4 | AL1: Monthly Budget | AM1: Notes:
A2: Location | B2: Ohio | D2: Ohio | F2: Ohio | H2: Ohio | J2: Ohio | L2: Ohio | N2: Ohio | P2: Ohio | R2: Ohio | T2: Ohio | V2: Ohio | X2: Ohio | Y2: All Locations | Z2: Ohio | AA2: Ohio | AB2: Ohio
A3: Month | B3: ='Combined Company'!B3 -> 01/31/2023 | D3: ='Combined Company'!D3 -> 02/28/2023 | F3: ='Combined Company'!F3 -> 03/31/2023 | H3: ='Combined Company'!H3 -> 45046 | J3: ='Combined Company'!J3 -> 45077 | L3: ='Combined Company'!L3 -> 45107 | N3: ='Combined Company'!N3 -> 45138 | P3: ='Combined Company'!P3 -> 45169 | R3: ='Combined Company'!R3 -> 45199 | T3: ='Combined Company'!T3 -> 45230 | V3: ='Combined Company'!V3 -> 45260 | X3: ='Combined Company'!X3 -> 45291
A4: Days in Month | B4: ='Combined Company'!B4 -> 31 | D4: ='Combined Company'!D4 -> 28 | F4: ='Combined Company'!F4 -> 31 | H4: ='Combined Company'!H4 -> 30 | J4: ='Combined Company'!J4 -> 31 | L4: ='Combined Company'!L4 -> 30 | N4: ='Combined Company'!N4 -> 31 | P4: ='Combined Company'!P4 -> 31 | R4: ='Combined Company'!R4 -> 30 | T4: ='Combined Company'!T4 -> 31 | V4: ='Combined Company'!V4 -> 30 | X4: ='Combined Company'!X4 -> 31
A5: Quarter | B5: ='Combined Company'!B5 -> 1 | D5: ='Combined Company'!D5 -> 1 | F5: ='Combined Company'!F5 -> 1 | H5: ='Combined Company'!H5 -> 2 | J5: ='Combined Company'!J5 -> 2 | L5: ='Combined Company'!L5 -> 2 | N5: ='Combined Company'!N5 -> 3 | P5: ='Combined Company'!P5 -> 3 | R5: ='Combined Company'!R5 -> 3 | T5: ='Combined Company'!T5 -> 4 | V5: ='Combined Company'!V5 -> 4 | X5: ='Combined Company'!X5 -> 4
A6: Year | B6: ='Combined Company'!B6 -> 2023 | D6: ='Combined Company'!D6 -> 2023 | F6: ='Combined Company'!F6 -> 2023 | H6: ='Combined Company'!H6 -> 2023 | J6: ='Combined Company'!J6 -> 2023 | L6: ='Combined Company'!L6 -> 2023 | N6: ='Combined Company'!N6 -> 2023 | P6: ='Combined Company'!P6 -> 2023 | R6: ='Combined Company'!R6 -> 2023 | T6: ='Combined Company'!T6 -> 2023 | V6: ='Combined Company'!V6 -> 2023 | X6: ='Combined Company'!X6 -> 2023
A8: Revenue
A9: Managed IT Services (Recurring IT & Security) | B9: 102223 | C9: =B9/B$17 -> 0.35615909 | D9: 101637 | E9: =D9/D$17 -> 0.152503 | F9: 133979 | G9: =F9/F$17 -> 0.34186427 | H9: 157213 | I9: =H9/H$17 -> 0.26697404 | J9: 99474 | K9: =J9/J$17 -> 0.096427377 | L9: 109822 | M9: =L9/L$17 -> 0.23772745 | N9: 97176 | O9: =N9/N$17 -> 0.11439563 | P9: 121475 | Q9: =P9/P$17 -> 0.10535103 | R9: 103635 | S9: =R9/R$17 -> 0.11605744 | T9: 115881 | U9: =T9/T$17 -> 0.16262904 | V9: 113271 | W9: =V9/V$17 -> 0.33496571 | X9: 115351 | Y9: =X9/X$17 -> 0.15040048 | Z9: =SUM(B9,D9,F9,H9,J9,L9,N9,P9,R9,T9,V9,X9) -> 1371137 | AA9: =IFERROR(AVERAGE(B9,D9,F9,H9,J9,L9,N9,P9,R9,T9,V9,X9),0) -> 114261.42 | AB9: =IFERROR(AVERAGE(T9,V9,X9),0) -> 114834.33 | AE9: =IFERROR(AVERAGE(R9,T9,V9),0) -> 110929 | AK9: =SUM(T9,V9,X9)*4 -> 1378012 | AL9: =AK9/12 -> 114834.33
A10: Cloud (Private Cloud Only as of 4/1/23) | B10: 43961 | C10: =B10/B$17 -> 0.15316621 | D10: 7683 | E10: =D10/D$17 -> 0.011528091 | F10: 31895 | G10: =F10/F$17 -> 0.081384104 | H10: 161 | I10: =H10/H$17 -> 0.000273405 | J10: 184 | K10: =J10/J$17 -> 0.00017836457 | L10: 177 | M10: =L10/L$17 -> 0.00038314508 | N10: 161 | O10: =N10/N$17 -> 0.00018952927 | P10: 0 | Q10: =P10/P$17 -> 0 | R10: 0 | S10: =R10/R$17 -> 0 | T10: 0 | U10: =T10/T$17 -> 0 | V10: 0 | W10: =V10/V$17 -> 0 | X10: 0 | Y10: =X10/X$17 -> 0 | Z10: =SUM(B10,D10,F10,H10,J10,L10,N10,P10,R10,T10,V10,X10) -> 84222 | AA10: =IFERROR(AVERAGE(B10,D10,F10,H10,J10,L10,N10,P10,R10,T10,V10,X10),0) -> 7018.5 | AB10: =IFERROR(AVERAGE(T10,V10,X10),0) -> 0 | AE10: =IFERROR(AVERAGE(R10,T10,V10),0) -> 0 | AK10: =SUM(T10,V10,X10)*4 -> 0 | AL10: =AK10/12 -> 0
A11: Recurring Resale (Includes previouse Cloud sales) | C11: =B11/B$17 -> 0 | E11: =D11/D$17 -> 0 | G11: =F11/F$17 -> 0 | H11: 13167 | I11: =H11/H$17 -> 0.022359774 | J11: 12214 | K11: =J11/J$17 -> 0.011839918 | L11: 13079 | M11: =L11/L$17 -> 0.028311607 | N11: 6002 | O11: =N11/N$17 -> 0.0070655571 | P11: 11891 | Q11: =P11/P$17 -> 0.010312649 | R11: 13655 | S11: =R11/R$17 -> 0.015291787 | T11: 17769 | U11: =T11/T$17 -> 0.024937267 | V11: 17622 | W11: =V11/V$17 -> 0.052111889 | X11: 17987 | Y11: =X11/X$17 -> 0.023452362 | Z11: =SUM(B11,D11,F11,H11,J11,L11,N11,P11,R11,T11,V11,X11) -> 123386 | AA11: =IFERROR(AVERAGE(B11,D11,F11,H11,J11,L11,N11,P11,R11,T11,V11,X11),0) -> 13709.556 | AB11: =IFERROR(AVERAGE(T11,V11,X11),0) -> 17792.667 | AK11: =(X11*3)*4 -> 215844 | AL11: =AK11/12 -> 17987 | AM11: *Just started tracking in April - Use (April * 3) * 4
A12: Project Services | B12: 59765 | C12: =B12/B$17 -> 0.20822954 | D12: 113090 | E12: =D12/D$17 -> 0.16968786 | F12: 72796 | G12: =F12/F$17 -> 0.18574815 | H12: 11734 | I12: =H12/H$17 -> 0.0199263 | J12: 80606 | K12: =J12/J$17 -> 0.078137253 | L12: 42267 | M12: =L12/L$17 -> 0.091493746 | N12: 92912 | O12: =N12/N$17 -> 0.10937605 | P12: 108496 | Q12: =P12/P$17 -> 0.094094792 | R12: 75466 | S12: =R12/R$17 -> 0.0845119 | T12: 71848 | U12: =T12/T$17 -> 0.10083251 | V12: 11245 | W12: =V12/V$17 -> 0.033253784 | X12: 31148 | Y12: =X12/X$17 -> 0.04061234 | Z12: =SUM(B12,D12,F12,H12,J12,L12,N12,P12,R12,T12,V12,X12) -> 771373 | AA12: =IFERROR(AVERAGE(B12,D12,F12,H12,J12,L12,N12,P12,R12,T12,V12,X12),0) -> 64281.083 | AB12: =IFERROR(AVERAGE(T12,V12,X12),0) -> 38080.333 | AE12: =IFERROR(AVERAGE(R12,T12,V12),0) -> 52853 | AK12: =SUM(T12,V12,X12)*4 -> 456964 | AL12: =AK12/12 -> 38080.333
A13: Subcontracted Services | B13: 0 | C13: =B13/B$17 -> 0 | D13: 1592 | E13: =D13/D$17 -> 0.0023887441 | F13: 145 | G13: =F13/F$17 -> 0.00036998574 | H13: 987 | I13: =H13/H$17 -> 0.0016760915 | J13: 0 | K13: =J13/J$17 -> 0 | L13: 0 | M13: =L13/L$17 -> 0 | N13: 0 | O13: =N13/N$17 -> 0 | P13: 0 | Q13: =P13/P$17 -> 0 | R13: 5929 | S13: =R13/R$17 -> 0.0066396928 | T13: 1108 | U13: =T13/T$17 -> 0.001554983 | V13: 1820 | W13: =V13/V$17 -> 0.0053821154 | X13: 2427 | Y13: =X13/X$17 -> 0.0031644456 | Z13: =SUM(B13,D13,F13,H13,J13,L13,N13,P13,R13,T13,V13,X13) -> 14008 | AA13: =IFERROR(AVERAGE(B13,D13,F13,H13,J13,L13,N13,P13,R13,T13,V13,X13),0) -> 1167.3333 | AB13: =IFERROR(AVERAGE(T13,V13,X13),0) -> 1785 | AE13: =IFERROR(AVERAGE(R13,T13,V13),0) -> 2952.3333 | AK13: =SUM(T13,V13,X13)*4 -> 21420 | AL13: =AK13/12 -> 1785
A14: Product Sales | B14: 81066 | C14: =B14/B$17 -> 0.28244517 | D14: 442457 | E14: =D14/D$17 -> 0.6638923 | F14: 153161 | G14: =F14/F$17 -> 0.39080955 | H14: 405608 | I14: =H14/H$17 -> 0.6887904 | J14: 839117 | K14: =J14/J$17 -> 0.81341709 | L14: 296621 | M14: =L14/L$17 -> 0.64208405 | N14: 653222 | O14: =N14/N$17 -> 0.76897323 | P14: 911188 | Q14: =P14/P$17 -> 0.79024153 | R14: 685651 | S14: =R14/R$17 -> 0.76783809 | T14: 499231 | U14: =T14/T$17 -> 0.70062789 | V14: 187218 | W14: =V14/V$17 -> 0.55364224 | X14: 591430 | Y14: =X14/X$17 -> 0.7711364 | Z14: =SUM(B14,D14,F14,H14,J14,L14,N14,P14,R14,T14,V14,X14) -> 5745970 | AA14: =IFERROR(AVERAGE(B14,D14,F14,H14,J14,L14,N14,P14,R14,T14,V14,X14),0) -> 478830.83 | AB14: =IFERROR(AVERAGE(T14,V14,X14),0) -> 425959.67 | AE14: =IFERROR(AVERAGE(R14,T14,V14),0) -> 457366.67 | AK14: =SUM(T14,V14,X14)*4 -> 5111516 | AL14: =AK14/12 -> 425959.67
A15: Commissions | B15: 0 | C15: =B15/B$17 -> 0 | D15: 0 | E15: =D15/D$17 -> 0 | F15: 0 | G15: =F15/F$17 -> 0 | H15: 0 | I15: =H15/H$17 -> 0 | J15: 0 | K15: =J15/J$17 -> 0 | L15: 0 | M15: =L15/L$17 -> 0 | N15: 0 | O15: =N15/N$17 -> 0 | Q15: =P15/P$17 -> 0 | R15: 8627 | S15: =R15/R$17 -> 0.0096610946 | T15: 6711 | U15: =T15/T$17 -> 0.0094183129 | V15: 6981 | W15: =V15/V$17 -> 0.020644257 | X15: 8616 | Y15: =X15/X$17 -> 0.011233977 | Z15: =SUM(B15,D15,F15,H15,J15,L15,N15,P15,R15,T15,V15,X15) -> 30935 | AA15: =IFERROR(AVERAGE(B15,D15,F15,H15,J15,L15,N15,P15,R15,T15,V15,X15),0) -> 2812.2727 | AB15: =IFERROR(AVERAGE(T15,V15,X15),0) -> 7436 | AE15: =IFERROR(AVERAGE(R15,T15,V15),0) -> 7439.6667 | AK15: =SUM(T15,V15,X15)*4 -> 89232 | AL15: =AK15/12 -> 7436
A16: Sales Returns and Discounts | C16: =B16/B$17 -> 0 | E16: =D16/D$17 -> 0 | F16: 69 | G16: =F16/F$17 -> 0.00017606218 | H16: 0 | I16: =H16/H$17 -> 0 | J16: 0 | K16: =J16/J$17 -> 0 | L16: 0 | M16: =L16/L$17 -> 0 | N16: 0 | O16: =N16/N$17 -> 0 | Q16: =P16/P$17 -> 0 | R16: 0 | S16: =R16/R$17 -> 0 | T16: 0 | U16: =T16/T$17 -> 0 | V16: 0 | W16: =V16/V$17 -> 0 | X16: 0 | Y16: =X16/X$17 -> 0 | Z16: =SUM(B16,D16,F16,H16,J16,L16,N16,P16,R16,T16,V16,X16) -> 69 | AA16: =IFERROR(AVERAGE(B16,D16,F16,H16,J16,L16,N16,P16,R16,T16,V16,X16),0) -> 7.6666667 | AB16: =IFERROR(AVERAGE(T16,V16,X16),0) -> 0 | AE16: =IFERROR(AVERAGE(R16,T16,V16),0) -> 0 | AK16: =SUM(T16,V16,X16)*4 -> 0 | AL16: =AK16/12 -> 0
A17: Total Revenue | B17: 287015 | C17: =B17/B$17 -> 1 | D17: 666459 | E17: =D17/D$17 -> 1 | F17: 391907 | G17: =F17/F$17 -> 1 | H17: 588870 | I17: =H17/H$17 -> 1 | J17: =SUM(J9:J16) -> 1031595 | K17: =J17/J$17 -> 1 | L17: =SUM(L9:L16) -> 461966 | M17: =L17/L$17 -> 1 | N17: =SUM(N9:N16) -> 849473 | O17: =N17/N$17 -> 1 | P17: =SUM(P9:P16) -> 1153050 | Q17: =P17/P$17 -> 1 | R17: =SUM(R9:R16) -> 892963 | S17: =R17/R$17 -> 1 | T17: =SUM(T9:T16) -> 712548 | U17: =T17/T$17 -> 1 | V17: =SUM(V9:V16) -> 338157 | W17: =V17/V$17 -> 1 | X17: =SUM(X9:X16) -> 766959 | Y17: =X17/X$17 -> 1 | Z17: =SUM(B17,D17,F17,H17,J17,L17,N17,P17,R17,T17,V17,X17) -> 8140962 | AA17: =IFERROR(AVERAGE(B17,D17,F17,H17,J17,L17,N17,P17,R17,T17,V17,X17),0) -> 678413.5 | AB17: =IFERROR(AVERAGE(T17,V17,X17),0) -> 605888 | AE17: =IFERROR(AVERAGE(R17:V17),0) -> 388734 | AK17: =SUM(T17,V17,X17)*4 -> 7270656 | AL17: =AK17/12 -> 605888
A20: Cost of Goods and Services
A21: Managed IT Service Costs | B21: 18619 | C21: =B21/B$17 -> 0.064871174 | D21: 24994 | E21: =D21/D$17 -> 0.037502682 | F21: 45087 | G21: =F21/F$17 -> 0.11504515 | H21: 6029 | I21: =H21/H$17 -> 0.010238253 | J21: 6080 | K21: =J21/J$17 -> 0.0058937858 | L21: 1069 | M21: =L21/L$17 -> 0.0023140231 | N21: 6052 | O21: =N21/N$17 -> 0.0071244171 | P21: 11012 | Q21: =P21/P$17 -> 0.0095503231 | R21: 1382 | S21: =R21/R$17 -> 0.0015476565 | T21: 5640 | U21: =T21/T$17 -> 0.0079152562 | V21: 6486 | W21: =V21/V$17 -> 0.01918044 | X21: 5547 | Y21: =X21/X$17 -> 0.0072324596 | Z21: =SUM(F21,H21,J21,L21,N21,P21,R21,T21,V21,X21) -> 94384 | AA21: =IFERROR(AVERAGE(B21,D21,F21,H21,J21,L21,N21,P21,R21,T21,V21,X21),0) -> 11499.75 | AB21: =IFERROR(AVERAGE(T21,V21,X21),0) -> 5891 | AE21: =IFERROR(AVERAGE(R21:V21),0) -> 2701.6019 | AK21: =SUM(T21,V21,X21)*4 -> 70692 | AL21: =AK21/12 -> 5891
A22: Cloud Service Costs | B22: 4135 | C22: =B22/B$17 -> 0.014406913 | D22: 2185 | E22: =D22/D$17 -> 0.0032785213 | F22: 5390 | G22: =F22/F$17 -> 0.013753263 | H22: 109 | I22: =H22/H$17 -> 0.00018510028 | J22: 407 | K22: =J22/J$17 -> 0.00039453468 | L22: 246 | M22: =L22/L$17 -> 0.00053250672 | N22: 105 | O22: =N22/N$17 -> 0.00012360605 | P22: 17 | Q22: =P22/P$17 -> 1.4743506e-05 | R22: 17 | S22: =R22/R$17 -> 1.9037743e-05 | T22: 17 | U22: =T22/T$17 -> 2.3858042e-05 | V22: 17 | W22: =V22/V$17 -> 5.0272507e-05 | X22: 17 | Y22: =X22/X$17 -> 2.2165461e-05 | Z22: =SUM(F22,H22,J22,L22,N22,P22,R22,T22,V22,X22) -> 6342 | AA22: =IFERROR(AVERAGE(B22,D22,F22,H22,J22,L22,N22,P22,R22,T22,V22,X22),0) -> 1055.1667 | AB22: =IFERROR(AVERAGE(T22,V22,X22),0) -> 17 | AE22: =IFERROR(AVERAGE(R22:V22),0) -> 10.200009 | AK22: =SUM(T22,V22,X22)*4 -> 204 | AL22: =AK22/12 -> 17
A23: Recurring Resale Costs | C23: =B23/B$17 -> 0 | E23: =D23/D$17 -> 0 | G23: =F23/F$17 -> 0 | H23: 5031 | I23: =H23/H$17 -> 0.0085434816 | J23: 6543 | K23: =J23/J$17 -> 0.0063426054 | L23: 7471 | M23: =L23/L$17 -> 0.016172186 | N23: 4127 | O23: =N23/N$17 -> 0.0048583063 | P23: 5998 | Q23: =P23/P$17 -> 0.0052018559 | R23: 7779 | S23: =R23/R$17 -> 0.0087114472 | T23: 10243 | U23: =T23/T$17 -> 0.014375172 | V23: 9387 | W23: =V23/V$17 -> 0.027759295 | X23: 9666 | Y23: =X23/X$17 -> 0.012603021 | Z23: =SUM(F23,H23,J23,L23,N23,P23,R23,T23,V23,X23) -> 66245 | AA23: =IFERROR(AVERAGE(B23,D23,F23,H23,J23,L23,N23,P23,R23,T23,V23,X23),0) -> 7360.5556 | AB23: =IFERROR(AVERAGE(T23,V23,X23),0) -> 9765.3333 | AK23: =(X23*3)*4 -> 115992 | AL23: =AK23/12 -> 9666 | AM23: *Just started tracking in April - Use (April * 3) * 4
A24: Project Service Costs | C24: =B24/B$17 -> 0 | D24: 942 | E24: =D24/D$17 -> 0.0014134403 | F24: 1071 | G24: =F24/F$17 -> 0.0027327912 | H24: 0 | I24: =H24/H$17 -> 0 | J24: 0 | K24: =J24/J$17 -> 0 | L24: 0 | M24: =L24/L$17 -> 0 | N24: 0 | O24: =N24/N$17 -> 0 | P24: 525 | Q24: =P24/P$17 -> 0.00045531417 | R24: 5449 | S24: =R24/R$17 -> 0.0061021565 | T24: 877 | U24: =T24/T$17 -> 0.0012307943 | V24: 0 | W24: =V24/V$17 -> 0 | X24: 0 | Y24: =X24/X$17 -> 0 | Z24: =SUM(F24,H24,J24,L24,N24,P24,R24,T24,V24,X24) -> 7922 | AA24: =IFERROR(AVERAGE(B24,D24,F24,H24,J24,L24,N24,P24,R24,T24,V24,X24),0) -> 805.81818 | AB24: =IFERROR(AVERAGE(T24,V24,X24),0) -> 292.33333 | AE24: =IFERROR(AVERAGE(R24:V24),0) -> 1265.2015 | AK24: =SUM(T24,V24,X24)*4 -> 3508 | AL24: =AK24/12 -> 292.33333
A25: Subcontractor Service Costs | B25: 795 | C25: =B25/B$17 -> 0.0027698901 | D25: 2816 | E25: =D25/D$17 -> 0.0042253162 | F25: 102 | G25: =F25/F$17 -> 0.00026026583 | H25: 871 | I25: =H25/H$17 -> 0.001479104 | J25: 0 | K25: =J25/J$17 -> 0 | L25: 0 | M25: =L25/L$17 -> 0 | N25: 4 | O25: =N25/N$17 -> 4.7088018e-06 | P25: 0 | Q25: =P25/P$17 -> 0 | R25: 3321 | S25: =R25/R$17 -> 0.0037190791 | T25: 450 | U25: =T25/T$17 -> 0.0006315364 | V25: 1400 | W25: =V25/V$17 -> 0.0041400888 | X25: 1290 | Y25: =X25/X$17 -> 0.0016819674 | Z25: =SUM(F25,H25,J25,L25,N25,P25,R25,T25,V25,X25) -> 7438 | AA25: =IFERROR(AVERAGE(B25,D25,F25,H25,J25,L25,N25,P25,R25,T25,V25,X25),0) -> 920.75 | AB25: =IFERROR(AVERAGE(T25,V25,X25),0) -> 1046.6667 | AE25: =IFERROR(AVERAGE(R25:V25),0) -> 1034.2009 | AK25: =SUM(T25,V25,X25)*4 -> 12560 | AL25: =AK25/12 -> 1046.6667
A26: Product Sales Costs | B26: 68603 | C26: =B26/B$17 -> 0.23902235 | D26: 335871 | E26: =D26/D$17 -> 0.50396348 | F26: 128558 | G26: =F26/F$17 -> 0.32803191 | H26: 335659 | I26: =H26/H$17 -> 0.57000526 | J26: 707631 | K26: =J26/J$17 -> 0.68595815 | L26: 249562 | M26: =L26/L$17 -> 0.54021725 | N26: 567432 | O26: =N26/N$17 -> 0.66798121 | P26: 715251 | Q26: =P26/P$17 -> 0.62031222 | R26: 572663 | S26: =R26/R$17 -> 0.64130653 | T26: 400895 | U26: =T26/T$17 -> 0.56262175 | V26: 153639 | W26: =V26/V$17 -> 0.45434221 | X26: 493536 | Y26: =X26/X$17 -> 0.64349724 | Z26: =SUM(F26,H26,J26,L26,N26,P26,R26,T26,V26,X26) -> 4324826 | AA26: =IFERROR(AVERAGE(B26,D26,F26,H26,J26,L26,N26,P26,R26,T26,V26,X26),0) -> 394108.33 | AB26: =IFERROR(AVERAGE(T26,V26,X26),0) -> 349356.67 | AE26: =IFERROR(AVERAGE(R26:V26),0) -> 225439.64 | AK26: =SUM(T26,V26,X26)*4 -> 4192280 | AL26: =AK26/12 -> 349356.67
A27: Total COGS | B27: 92152 | C27: =B27/B$17 -> 0.32107033 | D27: 366808 | E27: =D27/D$17 -> 0.55038344 | F27: 180208 | G27: =F27/F$17 -> 0.45982338 | H27: 347699 | I27: =H27/H$17 -> 0.5904512 | J27: =SUM(J21:J26) -> 720661 | K27: =J27/J$17 -> 0.69858908 | L27: =SUM(L21:L26) -> 258348 | M27: =L27/L$17 -> 0.55923596 | N27: =SUM(N21:N26) -> 577720 | O27: =N27/N$17 -> 0.68009225 | P27: =SUM(P21:P26) -> 732803 | Q27: =P27/P$17 -> 0.63553445 | R27: =SUM(R21:R26) -> 590611 | S27: =R27/R$17 -> 0.6614059 | T27: =SUM(T21:T26) -> 418122 | U27: =T27/T$17 -> 0.58679836 | V27: =SUM(V21:V26) -> 170929 | W27: =V27/V$17 -> 0.50547231 | X27: =SUM(X21:X26) -> 510056 | Y27: =X27/X$17 -> 0.66503685 | Z27: =SUM(F27,H27,J27,L27,N27,P27,R27,T27,V27,X27) -> 4507157 | AA27: =IFERROR(AVERAGE(B27,D27,F27,H27,J27,L27,N27,P27,R27,T27,V27,X27),0) -> 413843.08 | AB27: =IFERROR(AVERAGE(T27,V27,X27),0) -> 366369 | AE27: =IFERROR(AVERAGE(R27:V27),0) -> 235932.65 | AK27: =SUM(T27,V27,X27)*4 -> 4396428 | AL27: =AK27/12 -> 366369
Z28: =SUM(F28,H28,J28,L28,N28,P28,R28,T28,V28,X28) -> 0 | AA28: =IFERROR(AVERAGE(F28,H28,J28,L28,N28,P28,R28,T28,V28,X28),0) -> 0 | AB28: =IFERROR(AVERAGE(T28,V28,X28),0) -> 0
A29: Gross Profit | B29: 194863 | C29: =B29/B$17 -> 0.67892967 | D29: 299651 | E29: =D29/D$17 -> 0.44961656 | F29: 211699 | G29: =F29/F$17 -> 0.54017662 | H29: 241171 | I29: =H29/H$17 -> 0.4095488 | J29: =+J17-J27 -> 310934 | K29: =J29/J$17 -> 0.30141092 | L29: =+L17-L27 -> 203618 | M29: =L29/L$17 -> 0.44076404 | N29: =+N17-N27 -> 271753 | O29: =N29/N$17 -> 0.31990775 | P29: =+P17-P27 -> 420247 | Q29: =P29/P$17 -> 0.36446555 | R29: =+R17-R27 -> 302352 | S29: =R29/R$17 -> 0.3385941 | T29: =+T17-T27 -> 294426 | U29: =T29/T$17 -> 0.41320164 | V29: =+V17-V27 -> 167228 | W29: =V29/V$17 -> 0.49452769 | X29: =+X17-X27 -> 256903 | Y29: =X29/X$17 -> 0.33496315 | Z29: =SUM(F29,H29,J29,L29,N29,P29,R29,T29,V29,X29) -> 2680331 | AA29: =IFERROR(AVERAGE(B29,D29,F29,H29,J29,L29,N29,P29,R29,T29,V29,X29),0) -> 264570.42 | AB29: =IFERROR(AVERAGE(T29,V29,X29),0) -> 239519 | AE29: =IFERROR(AVERAGE(R29:V29),0) -> 152801.35 | AK29: =SUM(T29,V29,X29)*4 -> 2874228 | AL29: =AK29/12 -> 239519
A30: Gross Profit % | B30: =B29/B17 -> 0.67892967 | C30: =C29/C17 -> 0.67892967 | D30: =D29/D17 -> 0.44961656 | E30: =E29/E17 -> 0.44961656 | F30: =F29/F17 -> 0.54017662 | G30: =G29/G17 -> 0.54017662 | H30: =H29/H17 -> 0.4095488 | I30: =I29/I17 -> 0.4095488 | ... AB30: =AB29/AB17 -> 0.39531894 | AH30: 0.55
A32: Operating Expenses
A33: General & Admin Expenses
A34: Charitable Contributions | C34: =B34/B$17 -> 0 | E34: =D34/D$17 -> 0 | G34: =F34/F$17 -> 0 | H34: 0 | I34: =H34/H$17 -> 0 | J34: 0 | K34: =J34/J$17 -> 0 | L34: 0 | M34: =L34/L$17 -> 0 | N34: 0 | O34: =N34/N$17 -> 0 | P34: 0 | Q34: =P34/P$17 -> 0 | R34: 0 | S34: =R34/R$17 -> 0 | T34: 0 | U34: =T34/T$17 -> 0 | V34: 0 | W34: =V34/V$17 -> 0 | X34: 0 | Y34: =X34/X$17 -> 0 | Z34: =SUM(B34,D34,F34,H34,J34,L34,N34,P34,R34,T34,V34,X34) -> 0 | AA34: =IFERROR(AVERAGE(B34,D34,F34,H34,J34,L34,N34,P34,R34,T34,V34,X34),0) -> 0 | AB34: =IFERROR(AVERAGE(T34,V34,X34),0) -> 0 | AE34: =IFERROR(AVERAGE(R34:V34),0) -> 0 | AK34: =SUM(T34,V34,X34)*4 -> 0 | AL34: =AK34/12 -> 0
A35: Education | C35: =B35/B$17 -> 0 | E35: =D35/D$17 -> 0 | G35: =F35/F$17 -> 0 | H35: 0 | I35: =H35/H$17 -> 0 | J35: 0 | K35: =J35/J$17 -> 0 | L35: 0 | M35: =L35/L$17 -> 0 | N35: 0 | O35: =N35/N$17 -> 0 | P35: 150 | Q35: =P35/P$17 -> 0.00013008976 | R35: 0 | S35: =R35/R$17 -> 0 | T35: 129 | U35: =T35/T$17 -> 0.00018104044 | V35: 471 | W35: =V35/V$17 -> 0.0013928442 | X35: 63 | Y35: =X35/X$17 -> 8.2142592e-05 | Z35: =SUM(B35,D35,F35,H35,J35,L35,N35,P35,R35,T35,V35,X35) -> 813 | AA35: =IFERROR(AVERAGE(B35,D35,F35,H35,J35,L35,N35,P35,R35,T35,V35,X35),0) -> 90.333333 | AB35: =IFERROR(AVERAGE(T35,V35,X35),0) -> 221 | AE35: =IFERROR(AVERAGE(R35:V35),0) -> 120.00004 | AK35: =SUM(T35,V35,X35)*4 -> 2652 | AL35: =AK35/12 -> 221
A36: Finance Charges | C36: =B36/B$17 -> 0 | E36: =D36/D$17 -> 0 | G36: =F36/F$17 -> 0 | H36: 0 | I36: =H36/H$17 -> 0 | J36: 0 | K36: =J36/J$17 -> 0 | L36: 775 | M36: =L36/L$17 -> 0.0016776126 | N36: 0 | O36: =N36/N$17 -> 0 | P36: 0 | Q36: =P36/P$17 -> 0 | R36: 0 | S36: =R36/R$17 -> 0 | T36: 0 | U36: =T36/T$17 -> 0 | V36: 0 | W36: =V36/V$17 -> 0 | X36: 205 | Y36: =X36/X$17 -> 0.00026728939 | Z36: =SUM(B36,D36,F36,H36,J36,L36,N36,P36,R36,T36,V36,X36) -> 980 | AA36: =IFERROR(AVERAGE(B36,D36,F36,H36,J36,L36,N36,P36,R36,T36,V36,X36),0) -> 108.88889 | AB36: =IFERROR(AVERAGE(T36,V36,X36),0) -> 68.333333 | AE36: =IFERROR(AVERAGE(R36:V36),0) -> 0 | AK36: =SUM(T36,V36,X36)*4 -> 820 | AL36: =AK36/12 -> 68.333333
A37: Travel, Meals and Entertainment | C37: =B37/B$17 -> 0 | E37: =D37/D$17 -> 0 | G37: =F37/F$17 -> 0 | H37: 836 | I37: =H37/H$17 -> 0.0014196682 | J37: 1101 | K37: =J37/J$17 -> 0.0010672793 | L37: 993 | M37: =L37/L$17 -> 0.0021495088 | N37: 3856 | O37: =N37/N$17 -> 0.0045392849 | P37: 477 | Q37: =P37/P$17 -> 0.00041368544 | R37: 5504 | S37: =R37/R$17 -> 0.0061637492 | T37: 1815 | U37: =T37/T$17 -> 0.0025471968 | V37: 6145 | W37: =V37/V$17 -> 0.018172033 | X37: 766 | Y37: =X37/X$17 -> 0.00099874961 | Z37: =SUM(B37,D37,F37,H37,J37,L37,N37,P37,R37,T37,V37,X37) -> 21493 | AA37: =IFERROR(AVERAGE(B37,D37,F37,H37,J37,L37,N37,P37,R37,T37,V37,X37),0) -> 2388.1111 | AB37: =IFERROR(AVERAGE(T37,V37,X37),0) -> 2908.6667 | AE37: =IFERROR(AVERAGE(R37:V37),0) -> 2692.8017 | AK37: =SUM(T37,V37,X37)*4 -> 34904 | AL37: =AK37/12 -> 2908.6667
A38: Office Supplies | C38: =B38/B$17 -> 0 | E38: =D38/D$17 -> 0 | G38: =F38/F$17 -> 0 | H38: 1364 | I38: =H38/H$17 -> 0.0023163007 | J38: 2208 | K38: =J38/J$17 -> 0.0021403749 | L38: 1838 | M38: =L38/L$17 -> 0.0039786478 | N38: 680 | O38: =N38/N$17 -> 0.00080049631 | P38: 3809 | Q38: =P38/P$17 -> 0.0033034127 | R38: 1162 | S38: =R38/R$17 -> 0.0013012857 | T38: 2234 | U38: =T38/T$17 -> 0.0031352274 | V38: 4125 | W38: =V38/V$17 -> 0.012198476 | X38: 1075 | Y38: =X38/X$17 -> 0.0014016395 | Z38: =SUM(B38,D38,F38,H38,J38,L38,N38,P38,R38,T38,V38,X38) -> 18495 | AA38: =IFERROR(AVERAGE(B38,D38,F38,H38,J38,L38,N38,P38,R38,T38,V38,X38),0) -> 2055 | AB38: =IFERROR(AVERAGE(T38,V38,X38),0) -> 2478 | AE38: =IFERROR(AVERAGE(R38:V38),0) -> 1504.2009 | AK38: =SUM(T38,V38,X38)*4 -> 29736 | AL38: =AK38/12 -> 2478
A39: Total General and Admin Expenses | B39: 2124 | C39: =B39/B$17 -> 0.0074003101 | D39: 6964 | E39: =D39/D$17 -> 0.010449255 | F39: 14713 | G39: =F39/F$17 -> 0.03754207 | H39: 2200 | I39: =H39/H$17 -> 0.0037359689 | J39: 3309 | K39: =J39/J$17 -> 0.0032076542 | L39: =SUM(L34:L38) -> 3606 | M39: =L39/L$17 -> 0.0078057693 | N39: =SUM(N34:N38) -> 4536 | O39: =N39/N$17 -> 0.0053397813 | P39: =SUM(P34:P38) -> 4436 | Q39: =P39/P$17 -> 0.0038471879 | R39: =SUM(R34:R38) -> 6666 | S39: =R39/R$17 -> 0.0074650349 | T39: 4178 | U39: =T39/T$17 -> 0.0058634646 | V39: 10741 | W39: =V39/V$17 -> 0.031763353 | X39: 2109 | Y39: =X39/X$17 -> 0.002749821 | Z39: =SUM(B39,D39,F39,H39,J39,L39,N39,P39,R39,T39,V39,X39) -> 65582 | AA39: =IFERROR(AVERAGE(B39,D39,F39,H39,J39,L39,N39,P39,R39,T39,V39,X39),0) -> 5465.1667 | AB39: =IFERROR(AVERAGE(T39,V39,X39),0) -> 5676 | AE39: =IFERROR(AVERAGE(R39:V39),0) -> 4317.0027 | AK39: =SUM(T39,V39,X39)*4 -> 68112 | AL39: =AK39/12 -> 5676
A41: Marketing and Advertising Expenses | B41: 0 | C41: =B41/B$17 -> 0 | D41: 881 | E41: =D41/D$17 -> 0.0013219118 | F41: 114 | G41: =F41/F$17 -> 0.00029088534 | H41: 0 | I41: =H41/H$17 -> 0 | J41: 552 | K41: =J41/J$17 -> 0.00053509371 | L41: 881 | M41: =L41/L$17 -> 0.0019070668 | N41: 0 | O41: =N41/N$17 -> 0 | P41: 0 | Q41: =P41/P$17 -> 0 | R41: 704 | S41: =R41/R$17 -> 0.00078838653 | T41: 0 | U41: =T41/T$17 -> 0 | V41: 1763 | W41: =V41/V$17 -> 0.0052135547 | X41: 0 | Y41: =X41/X$17 -> 0 | Z41: =SUM(B41,D41,F41,H41,J41,L41,N41,P41,R41,T41,V41,X41) -> 4895 | AA41: =IFERROR(AVERAGE(B41,D41,F41,H41,J41,L41,N41,P41,R41,T41,V41,X41),0) -> 407.91667 | AB41: =IFERROR(AVERAGE(T41,V41,X41),0) -> 587.66667 | AE41: =IFERROR(AVERAGE(R41:V41),0) -> 493.40016 | AK41: =SUM(T41,V41,X41)*4 -> 7052 | AL41: =AK41/12 -> 587.66667
A43: Payroll and Related Expenses | B43: 153559 | C43: =B43/B$17 -> 0.53502082 | D43: 162014 | E43: =D43/D$17 -> 0.24309672 | F43: 204141 | G43: =F43/F$17 -> 0.52089144 | H43: 175391 | I43: =H43/H$17 -> 0.29784333 | J43: 212999 | K43: =J43/J$17 -> 0.20647541 | L43: 196658 | M43: =L43/L$17 -> 0.425698 | N43: 204141 | O43: =N43/N$17 -> 0.24031488 | P43: 224572 | Q43: =P43/P$17 -> 0.19476345 | R43: 171146 | S43: =R43/R$17 -> 0.1916608 | T43: 186315 | U43: =T43/T$17 -> 0.26147712 | V43: 159037 | W43: =V43/V$17 -> 0.47030521 | X43: 228687 | Y43: =X43/X$17 -> 0.2981737 | Z43: =SUM(B43,D43,F43,H43,J43,L43,N43,P43,R43,T43,V43,X43) -> 2278660 | AA43: =IFERROR(AVERAGE(B43,D43,F43,H43,J43,L43,N43,P43,R43,T43,V43,X43),0) -> 189888.33 | AB43: =IFERROR(AVERAGE(T43,V43,X43),0) -> 191346.33 | AE43: =IFERROR(AVERAGE(R43:V43),0) -> 103299.69 | AK43: =SUM(T43,V43,X43)*4 -> 2296156 | AL43: =AK43/12 -> 191346.33
A45: Utilities and Facilities | B45: 11249 | C45: =B45/B$17 -> 0.039193074 | D45: 13838 | E45: =D45/D$17 -> 0.020763468 | F45: 11127 | G45: =F45/F$17 -> 0.02839194 | H45: 13009 | I45: =H45/H$17 -> 0.022091463 | J45: 11860 | K45: =J45/J$17 -> 0.01149676 | L45: 10344 | M45: =L45/L$17 -> 0.022391258 | N45: 5532 | O45: =N45/N$17 -> 0.0065122729 | P45: 11243 | Q45: =P45/P$17 -> 0.0097506613 | R45: 16607 | S45: =R45/R$17 -> 0.018597635 | T45: 8996 | U45: =T45/T$17 -> 0.012625114 | V45: 14349 | W45: =V45/V$17 -> 0.042432953 | X45: 9891 | Y45: =X45/X$17 -> 0.012896387 | Z45: =SUM(B45,D45,F45,H45,J45,L45,N45,P45,R45,T45,V45,X45) -> 138045 | AA45: =IFERROR(AVERAGE(B45,D45,F45,H45,J45,L45,N45,P45,R45,T45,V45,X45),0) -> 11503.75 | AB45: =IFERROR(AVERAGE(T45,V45,X45),0) -> 11078.667 | AE45: =IFERROR(AVERAGE(R45:V45),0) -> 7990.4062 | AK45: =SUM(T45,V45,X45)*4 -> 132944 | AL45: =AK45/12 -> 11078.667
A47: Ops and Maint. Expenses
A48: Automobile Expenses | C48: =B48/B$17 -> 0 | E48: =D48/D$17 -> 0 | G48: =F48/F$17 -> 0 | H48: 7044 | I48: =H48/H$17 -> 0.011961893 | J48: 9102 | K48: =J48/J$17 -> 0.00882323 | M48: =L48/L$17 -> 0 | O48: =N48/N$17 -> 0 | P48: 9019 | Q48: =P48/P$17 -> 0.0078218638 | R48: 7925 | S48: =R48/R$17 -> 0.0088749478 | T48: 7783 | U48: =T48/T$17 -> 0.010922773 | V48: 8157 | W48: =V48/V$17 -> 0.024121932 | X48: 10770 | Y48: =X48/X$17 -> 0.014042472 | Z48: =SUM(B48,D48,F48,H48,J48,L48,N48,P48,R48,T48,V48,X48) -> 59800 | AA48: =IFERROR(AVERAGE(B48,D48,F48,H48,J48,L48,N48,P48,R48,T48,V48,X48),0) -> 8542.8571 | AB48: =IFERROR(AVERAGE(T48,V48,X48),0) -> 8903.3333 | AE48: =IFERROR(AVERAGE(R48:V48),0) -> 4773.004 | AK48: =SUM(T48,V48,X48)*4 -> 106840 | AL48: =AK48/12 -> 8903.3333
A49: Professional Services | C49: =B49/B$17 -> 0 | E49: =D49/D$17 -> 0 | G49: =F49/F$17 -> 0 | H49: 2167 | I49: =H49/H$17 -> 0.0036799294 | J49: 0 | K49: =J49/J$17 -> 0 | M49: =L49/L$17 -> 0 | O49: =N49/N$17 -> 0 | P49: 0 | Q49: =P49/P$17 -> 0 | R49: 0 | S49: =R49/R$17 -> 0 | T49: 11666 | U49: =T49/T$17 -> 0.01637223 | V49: 1292 | W49: =V49/V$17 -> 0.0038207105 | X49: 1250 | Y49: =X49/X$17 -> 0.0016298133 | Z49: =SUM(B49,D49,F49,H49,J49,L49,N49,P49,R49,T49,V49,X49) -> 16375 | AA49: =IFERROR(AVERAGE(B49,D49,F49,H49,J49,L49,N49,P49,R49,T49,V49,X49),0) -> 2339.2857 | AB49: =IFERROR(AVERAGE(T49,V49,X49),0) -> 4736 | AE49: =IFERROR(AVERAGE(R49:V49),0) -> 2591.6033 | AK49: =SUM(T49,V49,X49)*4 -> 56832 | AL49: =AK49/12 -> 4736
A50: Software and Maintenance | C50: =B50/B$17 -> 0 | E50: =D50/D$17 -> 0 | G50: =F50/F$17 -> 0 | H50: 397 | I50: =H50/H$17 -> 0.00067417257 | J50: 2743 | K50: =J50/J$17 -> 0.0026589892 | M50: =L50/L$17 -> 0 | O50: =N50/N$17 -> 0 | P50: 1702 | Q50: =P50/P$17 -> 0.0014760852 | R50: 6455 | S50: =R50/R$17 -> 0.007228743 | T50: 3902 | U50: =T50/T$17 -> 0.0054761223 | V50: 10604 | W50: =V50/V$17 -> 0.031358215 | X50: 5176 | Y50: =X50/X$17 -> 0.006748731 | Z50: =SUM(B50,D50,F50,H50,J50,L50,N50,P50,R50,T50,V50,X50) -> 30979 | AA50: =IFERROR(AVERAGE(B50,D50,F50,H50,J50,L50,N50,P50,R50,T50,V50,X50),0) -> 4425.5714 | AB50: =IFERROR(AVERAGE(T50,V50,X50),0) -> 6560.6667 | AE50: =IFERROR(AVERAGE(R50:V50),0) -> 4192.2025 | AK50: =SUM(T50,V50,X50)*4 -> 78728 | AL50: =AK50/12 -> 6560.6667
A51: Other Operating Expense | C51: =B51/B$17 -> 0 | E51: =D51/D$17 -> 0 | G51: =F51/F$17 -> 0 | H51: 0 | I51: =H51/H$17 -> 0 | J51: 0 | K51: =J51/J$17 -> 0 | M51: =L51/L$17 -> 0 | O51: =N51/N$17 -> 0 | P51: 0 | Q51: =P51/P$17 -> 0 | R51: 0 | S51: =R51/R$17 -> 0 | T51: 0 | U51: =T51/T$17 -> 0 | V51: 0 | W51: =V51/V$17 -> 0 | X51: 0 | Y51: =X51/X$17 -> 0 | Z51: =SUM(B51,D51,F51,H51,J51,L51,N51,P51,R51,T51,V51,X51) -> 0 | AA51: =IFERROR(AVERAGE(B51,D51,F51,H51,J51,L51,N51,P51,R51,T51,V51,X51),0) -> 0 | AB51: =IFERROR(AVERAGE(T51,V51,X51),0) -> 0 | AE51: =IFERROR(AVERAGE(R51:V51),0) -> 0 | AK51: =SUM(T51,V51,X51)*4 -> 0 | AL51: =AK51/12 -> 0
A52: Total Ops and Maint. Expenses | B52: 8846 | C52: =B52/B$17 -> 0.030820689 | D52: 6649 | E52: =D52/D$17 -> 0.0099766077 | F52: 15522 | G52: =F52/F$17 -> 0.039606335 | H52: 9608 | I52: =H52/H$17 -> 0.016315995 | J52: 11845 | K52: =J52/J$17 -> 0.011482219 | L52: 3841 | M52: =L52/L$17 -> 0.0083144647 | N52: 13605 | O52: =N52/N$17 -> 0.016015812 | P52: 10721 | Q52: =P52/P$17 -> 0.0092979489 | R52: 14380 | S52: =R52/R$17 -> 0.016103691 | T52: 23351 | U52: =T52/T$17 -> 0.032771126 | V52: 20053 | W52: =V52/V$17 -> 0.059300857 | X52: 17195 | Y52: =X52/X$17 -> 0.022419712 | Z52: =SUM(B52,D52,F52,H52,J52,L52,N52,P52,R52,T52,V52,X52) -> 155616 | AA52: =IFERROR(AVERAGE(B52,D52,F52,H52,J52,L52,N52,P52,R52,T52,V52,X52),0) -> 12968 | AB52: =IFERROR(AVERAGE(T52,V52,X52),0) -> 20199.667 | AE52: =IFERROR(AVERAGE(R52:V52),0) -> 11556.81 | AK52: =SUM(T52,V52,X52)*4 -> 242396 | AL52: =AK52/12 -> 20199.667
A54: Taxes and Insurance
A55: Insurance | C55: =B55/B$17 -> 0 | E55: =D55/D$17 -> 0 | G55: =F55/F$17 -> 0 | H55: 1862 | I55: =H55/H$17 -> 0.0031619882 | J55: 787 | K55: =J55/J$17 -> 0.00076289629 | L55: 2201 | M55: =L55/L$17 -> 0.0047644199 | N55: 1298 | O55: =N55/N$17 -> 0.0015280062 | P55: 1647 | Q55: =P55/P$17 -> 0.0014283856 | R55: 1646 | S55: =R55/R$17 -> 0.0018433015 | T55: 949 | U55: =T55/T$17 -> 0.0013318401 | V55: 1646 | W55: =V55/V$17 -> 0.0048675615 | X55: 2345 | Y55: =X55/X$17 -> 0.0030575298 | Z55: =SUM(B55,D55,F55,H55,J55,L55,N55,P55,R55,T55,V55,X55) -> 14381 | AA55: =IFERROR(AVERAGE(B55,D55,F55,H55,J55,L55,N55,P55,R55,T55,V55,X55),0) -> 1597.8889 | AB55: =IFERROR(AVERAGE(T55,V55,X55),0) -> 1646.6667 | AE55: =IFERROR(AVERAGE(R55:V55),0) -> 848.20064 | AK55: =SUM(T55,V55,X55)*4 -> 19760 | AL55: =AK55/12 -> 1646.6667
A56: Taxes | H56: 0 | J56: 0 | P56: 0 | R56: 0 | T56: 0 | Z56: =SUM(B56,D56,F56,H56,J56,L56,N56,P56,R56,T56,V56,X56) -> 0 | AA56: =IFERROR(AVERAGE(B56,D56,F56,H56,J56,L56,N56,P56,R56,T56,V56,X56),0) -> 0 | AB56: =IFERROR(AVERAGE(T56,V56,X56),0) -> 0 | AE56: =IFERROR(AVERAGE(R56:V56),0) -> 0 | AK56: =SUM(T56,V56,X56)*4 -> 0 | AL56: =AK56/12 -> 0
A57: Total Taxes and Insurance | B57: 1851 | C57: =B57/B$17 -> 0.0064491403 | D57: 2678 | E57: =D57/D$17 -> 0.0040182517 | F57: 1851 | G57: =F57/F$17 -> 0.0047230593 | H57: 1862 | I57: =H57/H$17 -> 0.0031619882 | J57: 787 | K57: =J57/J$17 -> 0.00076289629 | L57: 2201 | M57: =L57/L$17 -> 0.0047644199 | N57: 1298 | O57: =N57/N$17 -> 0.0015280062 | P57: 1647 | Q57: =P57/P$17 -> 0.0014283856 | R57: 1646 | S57: =R57/R$17 -> 0.0018433015 | T57: 949 | U57: =T57/T$17 -> 0.0013318401 | V57: 0 | W57: =V57/V$17 -> 0 | X57: 2345 | Y57: =X57/X$17 -> 0.0030575298 | Z57: =SUM(B57,D57,F57,H57,J57,L57,N57,P57,R57,T57,V57,X57) -> 19115 | AA57: =IFERROR(AVERAGE(B57,D57,F57,H57,J57,L57,N57,P57,R57,T57,V57,X57),0) -> 1592.9167 | AB57: =IFERROR(AVERAGE(T57,V57,X57),0) -> 1098 | AE57: =IFERROR(AVERAGE(R57:V57),0) -> 519.00064 | AK57: =SUM(T57,V57,X57)*4 -> 13176 | AL57: =AK57/12 -> 1098
A58: Total Operating Expenses | B58: 177629 | C58: =B58/B$17 -> 0.61888403 | D58: 193024 | E58: =D58/D$17 -> 0.28962622 | F58: 247468 | G58: =F58/F$17 -> 0.63144573 | H58: 202070 | I58: =H58/H$17 -> 0.34314874 | J58: 241352 | K58: =J58/J$17 -> 0.23396003 | L58: 216650 | M58: =L58/L$17 -> 0.46897391 | N58: 235628 | O58: =N58/N$17 -> 0.27738139 | P58: 252619 | Q58: =P58/P$17 -> 0.21908764 | R58: 211149 | S58: =R58/R$17 -> 0.23645885 | T58: 223789 | U58: =T58/T$17 -> 0.31406867 | V58: 207589 | W58: =V58/V$17 -> 0.61388349 | X58: 260226 | Y58: =X58/X$17 -> 0.33929584 | Z58: =SUM(B58,D58,F58,H58,J58,L58,N58,P58,R58,T58,V58,X58) -> 2669193 | AA58: =IFERROR(AVERAGE(B58,D58,F58,H58,J58,L58,N58,P58,R58,T58,V58,X58),0) -> 222432.75 | AB58: =IFERROR(AVERAGE(T58,V58,X58),0) -> 230534.67 | AE58: =IFERROR(AVERAGE(R58:V58),0) -> 128505.51 | AK58: =SUM(T58,V58,X58)*4 -> 2766416 | AL58: =AK58/12 -> 230534.67
Z59: =SUM(F59,H59,J59,L59,N59,P59,R59,T59,V59,X59) -> 0 | AA59: =IFERROR(AVERAGE(F59,H59,J59,L59,N59,P59,R59,T59,V59,X59),0) -> 0 | AB59: =IFERROR(AVERAGE(T59,V59,X59),0) -> 0
A60: Net Operating Income | B60: =B29-B58 -> 17234 | C60: =B60/B$17 -> 0.060045642 | D60: =D29-D58 -> 106627 | E60: =D60/D$17 -> 0.15999034 | F60: =F29-F58 -> -35769 | G60: =F60/F$17 -> -0.091269102 | H60: =H29-H58 -> 39101 | I60: =H60/H$17 -> 0.066400054 | J60: =J29-J58 -> 69582 | K60: =J60/J$17 -> 0.067450889 | L60: =L29-L58 -> -13032 | M60: =L60/L$17 -> -0.028209868 | N60: =N29-N58 -> 36125 | O60: =N60/N$17 -> 0.042526366 | P60: =P29-P58 -> 167628 | Q60: =P60/P$17 -> 0.14537791 | R60: =R29-R58 -> 91203 | S60: =R60/R$17 -> 0.10213525 | T60: =T29-T58 -> 70637 | U60: =T60/T$17 -> 0.099132971 | V60: =V29-V58 -> -40361 | W60: =V60/V$17 -> -0.1193558 | X60: =X29-X58 -> -3323 | Y60: =X60/X$17 -> -0.0043326958 | Z60: =SUM(B60,D60,F60,H60,J60,L60,N60,P60,R60,T60,V60,X60) -> 505652 | AA60: =IFERROR(AVERAGE(B60,D60,F60,H60,J60,L60,N60,P60,R60,T60,V60,X60),0) -> 42137.667 | AB60: =IFERROR(AVERAGE(T60,V60,X60),0) -> 8984.3333 | AE60: =IFERROR(AVERAGE(R60:V60),0) -> 24295.84 | AK60: =SUM(T60,V60,X60)*4 -> 107812 | AL60: =AK60/12 -> 8984.3333
A61: Net Operating Income % | B61: =B60/B17 -> 0.060045642 | C61: =C60/C17 -> 0.060045642 | D61: =D60/D17 -> 0.15999034 | E61: =E60/E17 -> 0.15999034 | F61: =F60/F17 -> -0.091269102 | G61: =G60/G17 -> -0.091269102 | H61: =H60/H17 -> 0.066400054 | I61: =I60/I17 -> 0.066400054 | ... Z61: =Z60/Z17 -> 0.06211207 | AA61: =IFERROR(AVERAGE(F61,H61,J61,L61,N61,P61,R61,T61,V61,X61),0) -> 0.027985597 | AB61: =AVERAGE(T61,V61,X61) -> -0.0081851757
A63: Other Income (Expense)
A64: Other Income
A65: Interest Income | Z65: =SUM(B65,D65,F65,H65,J65,L65,N65,P65,R65,T65,V65,X65) -> 0 | AA65: =IFERROR(AVERAGE(B65,D65,F65,H65,J65,L65,N65,P65,R65,T65,V65,X65),0) -> 0 | AB65: =IFERROR(AVERAGE(T65,V65,X65),0) -> 0 | AE65: =IFERROR(AVERAGE(R65:V65),0) -> 0 | AK65: =SUM(T65,V65,X65)*4 -> 0 | AL65: =AK65/12 -> 0
A66: Other Income | B66: 0 | C66: 0 | D66: 0 | E66: 0 | F66: 0 | G66: 0 | H66: 0 | I66: 0 | J66: 0 | K66: 0 | L66: 0 | M66: 0 | N66: 0 | P66: 2256 | Q66: 0 | R66: 0 | S66: 0 | T66: 0 | U66: 0 | V66: 0 | W66: 0 | X66: 0 | Z66: =SUM(B66,D66,F66,H66,J66,L66,N66,P66,R66,T66,V66,X66) -> 2256 | AA66: =IFERROR(AVERAGE(B66,D66,F66,H66,J66,L66,N66,P66,R66,T66,V66,X66),0) -> 188 | AB66: =IFERROR(AVERAGE(T66,V66,X66),0) -> 0 | AE66: =IFERROR(AVERAGE(R66:V66),0) -> 0 | AK66: =SUM(T66,V66,X66)*4 -> 0 | AL66: =AK66/12 -> 0
A67: Total Other Income | B67: 0 | C67: 0 | D67: 0 | E67: 0 | F67: 0 | G67: 0 | H67: 0 | I67: 0 | J67: 0 | K67: 0 | L67: 0 | M67: 0 | N67: 0 | P67: 0 | Q67: 0 | R67: 0 | S67: 0 | T67: 0 | U67: 0 | V67: 0 | W67: 0 | X67: 0 | Z67: =SUM(B67,D67,F67,H67,J67,L67,N67,P67,R67,T67,V67,X67) -> 0 | AA67: =IFERROR(AVERAGE(B67,D67,F67,H67,J67,L67,N67,P67,R67,T67,V67,X67),0) -> 0 | AB67: =IFERROR(AVERAGE(T67,V67,X67),0) -> 0 | AE67: =IFERROR(AVERAGE(R67:V67),0) -> 0 | AK67: =SUM(T67,V67,X67)*4 -> 0 | AL67: =AK67/12 -> 0
AK68: =SUM(T68,V68,X68)*4 -> 0
A69: Other Expense | AK69: =SUM(T69,V69,X69)*4 -> 0 | AL69: =AK69/12 -> 0
A70: Interest Expenses | B70: -9515 | D70: -17711 | F70: -1372 | H70: -9487 | J70: -9224 | L70: -9179 | N70: -9132 | P70: -9086 | R70: -9441 | T70: -9541 | V70: -9745 | X70: -6862 | Z70: =SUM(B70,D70,F70,H70,J70,L70,N70,P70,R70,T70,V70,X70) -> -110295 | AA70: =IFERROR(AVERAGE(B70,D70,F70,H70,J70,L70,N70,P70,R70,T70,V70,X70),0) -> -9191.25 | AB70: =IFERROR(AVERAGE(T70,V70,X70),0) -> -8716 | AE70: =IFERROR(AVERAGE(R70:V70),0) -> -9575.6667 | AK70: =SUM(T70,V70,X70)*4 -> -104592 | AL70: =AK70/12 -> -8716
A71: Partnership Expenses | Z71: =SUM(B71,D71,F71,H71,J71,L71,N71,P71,R71,T71,V71,X71) -> 0 | AA71: =IFERROR(AVERAGE(B71,D71,F71,H71,J71,L71,N71,P71,R71,T71,V71,X71),0) -> 0 | AB71: =IFERROR(AVERAGE(T71,V71,X71),0) -> 0 | AE71: =IFERROR(AVERAGE(R71:V71),0) -> 0 | AK71: =SUM(T71,V71,X71)*4 -> 0 | AL71: =AK71/12 -> 0
A72: Other Expenses | Z72: =SUM(B72,D72,F72,H72,J72,L72,N72,P72,R72,T72,V72,X72) -> 0 | AA72: =IFERROR(AVERAGE(B72,D72,F72,H72,J72,L72,N72,P72,R72,T72,V72,X72),0) -> 0 | AB72: =IFERROR(AVERAGE(T72,V72,X72),0) -> 0 | AE72: =IFERROR(AVERAGE(R72:V72),0) -> 0 | AK72: =SUM(T72,V72,X72)*4 -> 0 | AL72: =AK72/12 -> 0
A73: Total Other Expense | Z73: =SUM(B73,D73,F73,H73,J73,L73,N73,P73,R73,T73,V73,X73) -> 0 | AA73: =IFERROR(AVERAGE(B73,D73,F73,H73,J73,L73,N73,P73,R73,T73,V73,X73),0) -> 0 | AB73: =IFERROR(AVERAGE(T73,V73,X73),0) -> 0 | AE73: =IFERROR(AVERAGE(R73:V73),0) -> 0 | AK73: =SUM(T73,V73,X73)*4 -> 0 | AL73: =AK73/12 -> 0
A74: Total Other Income (Expense) | B74: -9515 | D74: -17711 | F74: -1372 | H74: -9487 | J74: -9224 | L74: -9179 | N74: -9132 | P74: -6830 | R74: -9441 | T74: -9541 | V74: -9725 | X74: -6862 | Z74: =SUM(B74,D74,F74,H74,J74,L74,N74,P74,R74,T74,V74,X74) -> -108019 | AA74: =IFERROR(AVERAGE(B74,D74,F74,H74,J74,L74,N74,P74,R74,T74,V74,X74),0) -> -9001.5833 | AB74: =IFERROR(AVERAGE(T74,V74,X74),0) -> -8709.3333 | AE74: =IFERROR(AVERAGE(R74:V74),0) -> -9569 | AK74: =SUM(T74,V74,X74)*4 -> -104512 | AL74: =AK74/12 -> -8709.3333
A76: Income Taxes
A77: State and Local Taxes | T77: 0 | V77: 7562 | Z77: =SUM(B77,D77,F77,H77,J77,L77,N77,P77,R77,T77,V77,X77) -> 7562 | AA77: =IFERROR(AVERAGE(B77,D77,F77,H77,J77,L77,N77,P77,R77,T77,V77,X77),0) -> 3781 | AB77: =IFERROR(AVERAGE(T77,V77,X77),0) -> 3781 | AE77: =IFERROR(AVERAGE(R77:V77),0) -> 3781 | AK77: =SUM(T77,V77,X77)*4 -> 30248 | AL77: =AK77/12 -> 2520.6667
A78: Total Income Taxes | T78: 0 | V78: 7562 | Z78: =SUM(B78,D78,F78,H78,J78,L78,N78,P78,R78,T78,V78,X78) -> 7562 | AA78: =IFERROR(AVERAGE(B78,D78,F78,H78,J78,L78,N78,P78,R78,T78,V78,X78),0) -> 3781 | AB78: =IFERROR(AVERAGE(T78,V78,X78),0) -> 3781 | AE78: =IFERROR(AVERAGE(R78:V78),0) -> 3781 | AK78: =SUM(T78,V78,X78)*4 -> 30248 | AL78: =AK78/12 -> 2520.6667
AA79: =IFERROR(AVERAGE(F79,H79,J79,L79,N79,P79,R79,T79,V79,X79),0) -> 0 | AB79: =IFERROR(AVERAGE(T79,V79,X79),0) -> 0
A80: Net Income (Loss) | B80: 37272 | D80: -59877 | F80: 8984 | H80: 7747 | J80: 97403 | L80: -44948 | N80: 29969 | P80: =+P60+P74 -> 160798 | R80: =+R60+R74 -> 81762 | T80: =+T60+T74 -> 61096 | V80: =+V60+V74-V78 -> -57648 | X80: =+X60+X74-X78 -> -10185 | Z80: =SUM(B80,D80,F80,H80,J80,L80,N80,P80,R80,T80,V80,X80) -> 312373 | AA80: =IFERROR(AVERAGE(B80,D80,F80,H80,J80,L80,N80,P80,R80,T80,V80,X80),0) -> 26031.083 | AB80: =IFERROR(AVERAGE(T80,V80,X80),0) -> -2245.6667 | AE80: =IFERROR(AVERAGE(R80:V80),0) -> 28403.333 | AK80: =SUM(T80,V80,X80)*4 -> -26948 | AL80: =AK80/12 -> -2245.6667
A81: Net Profit % | B81: =B80/B17 -> 0.12986081 | C81: =C80/C17 -> 0 | D81: =D80/D17 -> -0.089843486 | E81: =E80/E17 -> 0 | F81: =F80/F17 -> 0.022923806 | G81: =G80/G17 -> 0 | H81: =H80/H17 -> 0.013155705 | I81: =I80/I17 -> 0 | ... Z81: =Z80/Z17 -> 0.038370527 | AA81: =IFERROR(AVERAGE(F81,H81,J81,L81,N81,P81,R81,T81,V81,X81),0) -> 0.020148496 | AB81: =AVERAGE(T81,V81,X81) -> -0.03267125
A86: Ohio Revenue - Annual Target $10.8M / $900k per month | B86: 900000 | D86: 900000 | F86: 900000 | H86: 900000 | J86: 900000 | L86: 900000 | N86: 900000 | P86: 900000 | R86: 900000 | T86: 900000 | V86: 900000 | X86: 900000 | Z86: =SUM(F86,H86,J86,L86,N86,P86,R86,T86,V86,X86) -> 9000000
A87: Actual Revenue | B87: =B17 -> 287015 | C87: =C17 -> 1 | D87: =D17 -> 666459 | E87: =E17 -> 1 | F87: =F17 -> 391907 | G87: =G17 -> 1 | H87: =H17 -> 588870 | I87: =I17 -> 1 | ... P87: =P17 -> 1153050 | R87: =R17 -> 892963 | S87: =S17 -> 1 | T87: =T17 -> 712548 | U87: =U17 -> 1 | V87: =V17 -> 338157 | W87: =W17 -> 1 | X87: =X17 -> 766959 | Z87: =SUM(F87,H87,J87,L87,N87,P87,R87,T87,V87,X87) -> 7187488
A88: Actual - Goal (Over or Under Goal) | B88: =B87-B86 -> -612985 | C88: =C87-C86 -> 1 | D88: =D87-D86 -> -233541 | E88: =E87-E86 -> 1 | F88: =F87-F86 -> -508093 | G88: =G87-G86 -> 1 | H88: =H87-H86 -> -311130 | I88: =I87-I86 -> 1 | ... P88: =P87-P86 -> 253050 | R88: =R87-R86 -> -7037 | S88: =S87-S86 -> 1 | T88: =T87-T86 -> -187452 | U88: =U87-U86 -> 1 | V88: =V87-V86 -> -561843 | W88: =W87-W86 -> 1 | X88: =X87-X86 -> -133041 | Z88: =SUM(F88,H88,J88,L88,N88,P88,R88,T88,V88,X88) -> -1812512
A90: Ohio Profit Percentage Goal 15% profit
A91: Ohio Minimum Profit - $900k / $75k per month | B91: 75000 | C91: 75000 | D91: 75000 | E91: 75000 | F91: 75000 | G91: 75000 | H91: 75000 | I91: 75000 | J91: 75000 | K91: 75000 | L91: 75000 | M91: 75000 | N91: 75000 | O91: 75000 | P91: 75000 | R91: 75000 | S91: 75000 | T91: 75000 | U91: 75000 | V91: 75000 | W91: 75000 | X91: 75000 | Z91: =SUM(F91,H91,J91,L91,N91,P91,R91,T91,V91,X91) -> 750000
A92: Ohio Actual Net Operating Profit | B92: =B60 -> 17234 | C92: =C60 -> 0.060045642 | D92: =D60 -> 106627 | E92: =E60 -> 0.15999034 | F92: =F60 -> -35769 | G92: =G60 -> -0.091269102 | H92: =H60 -> 39101 | I92: =I60 -> 0.066400054 | ... P92: =P60 -> 167628 | R92: =R60 -> 91203 | S92: =S60 -> 0.10213525 | T92: =T60 -> 70637 | U92: =U60 -> 0.099132971 | V92: =V60 -> -40361 | W92: =W60 -> -0.1193558 | X92: =X60 -> -3323 | Z92: =SUM(F92,H92,J92,L92,N92,P92,R92,T92,V92,X92) -> 381791
A93: Actual - Goal (Over or Under Goal) | B93: =B92-B91 -> -57766 | C93: =C92-C91 -> -74999.94 | D93: =D92-D91 -> 31627 | E93: =E92-E91 -> -74999.84 | F93: =F92-F91 -> -110769 | G93: =G92-G91 -> -75000.091 | H93: =H92-H91 -> -35899 | I93: =I92-I91 -> -74999.934 | ... P93: =P92-P91 -> 92628 | R93: =R92-R91 -> 16203 | S93: =S92-S91 -> -74999.898 | T93: =T92-T91 -> -4363 | U93: =U92-U91 -> -74999.901 | V93: =V92-V91 -> -115361 | W93: =W92-W91 -> -75000.119 | X93: =X92-X91 -> -78323 | Z93: =SUM(F93,H93,J93,L93,N93,P93,R93,T93,V93,X93) -> -368209
A95: Gross Profit % | B95: =B29/B17 -> 0.67892967 | C95: =C29/C17 -> 0.67892967 | D95: =D29/D17 -> 0.44961656 | E95: =E29/E17 -> 0.44961656 | F95: =F29/F17 -> 0.54017662 | G95: =G29/G17 -> 0.54017662 | H95: =H29/H17 -> 0.4095488 | I95: =I29/I17 -> 0.4095488 | ... Z95: =Z29/Z17 -> 0.32924008 | AA95: =IFERROR(AVERAGE(F95,H95,J95,L95,N95,P95,R95,T95,V95,X95),0) -> 0.39575603 | AB95: =AVERAGE(T95,V95,X95) -> 0.41423082
A96: Net Operating Income % | B96: =B60/B17 -> 0.060045642 | C96: =C60/C17 -> 0.060045642 | D96: =D60/D17 -> 0.15999034 | E96: =E60/E17 -> 0.15999034 | F96: =F60/F17 -> -0.091269102 | G96: =G60/G17 -> -0.091269102 | H96: =H60/H17 -> 0.066400054 | I96: =I60/I17 -> 0.066400054 | ... Z96: =Z60/Z17 -> 0.06211207 | AA96: =IFERROR(AVERAGE(F96,H96,J96,L96,N96,P96,R96,T96,V96,X96),0) -> 0.027985597 | AB96: =AVERAGE(T96,V96,X96) -> -0.0081851757
A97: Net Profit % | B97: =B80/B17 -> 0.12986081 | C97: =C80/C17 -> 0 | D97: =D80/D17 -> -0.089843486 | E97: =E80/E17 -> 0 | F97: =F80/F17 -> 0.022923806 | G97: =G80/G17 -> 0 | H97: =H80/H17 -> 0.013155705 | I97: =I80/I17 -> 0 | ... Z97: =Z80/Z17 -> 0.038370527 | AA97: =IFERROR(AVERAGE(F97,H97,J97,L97,N97,P97,R97,T97,V97,X97),0) -> 0.020148496 | AB97: =AVERAGE(T97,V97,X97) -> -0.03267125
A98: Payroll to Total Revenue % | B98: =IFERROR(B43/B17,0) -> 0.53502082 | C98: =IFERROR(C43/C17,0) -> 0.53502082 | D98: =IFERROR(D43/D17,0) -> 0.24309672 | E98: =IFERROR(E43/E17,0) -> 0.24309672 | F98: =IFERROR(F43/F17,0) -> 0.52089144 | G98: =IFERROR(G43/G17,0) -> 0.52089144 | H98: =IFERROR(H43/H17,0) -> 0.29784333 | I98: =IFERROR(I43/I17,0) -> 0.29784333 | ... Z98: =IFERROR(Z43/Z17,0) -> 0.27990058 | AA98: =IFERROR(AVERAGE(F98,H98,J98,L98,N98,P98,R98,T98,V98,X98),0) -> 0.31076033 | AB98: =AVERAGE(T98,V98,X98) -> 0.34331868
A99: Payroll to Services Revenue % | B99: =IFERROR(B43/SUM(B9,B10,B11,B12),0) -> 0.74561663 | C99: =IFERROR(C43/SUM(C9,C10,C11,C12),0) -> 0.74561663 | D99: =IFERROR(D43/SUM(D9,D10,D11,D12),0) -> 0.72844746 | E99: =IFERROR(E43/SUM(E9,E10,E11,E12),0) -> 0.72844746 | F99: =IFERROR(F43/SUM(F9,F10,F11,F12),0) -> 0.85532744 | G99: =IFERROR(G43/SUM(G9,G10,G11,G12),0) -> 0.85532744 | H99: =IFERROR(H43/SUM(H9,H10,H11,H12),0) -> 0.96223289 | I99: =IFERROR(I43/SUM(I9,I10,I11,I12),0) -> 0.96223289 | ... Z99: =IFERROR(Z43/SUM(Z9,Z10,Z11,Z12),0) -> 0.96959387 | AA99: =IFERROR(AVERAGE(F99,H99,J99,L99,N99,P99,R99,T99,V99,X99),0) -> 1.0386016 | AB99: =AVERAGE(T99,V99,X99) -> 1.1386185
A100: Payroll to Services + Product Margin % | B100: =IFERROR(B43/(SUM(B9,B10,B11,B12)+(B13+B14-B25-B26)),0) -> 0.70563881 | C100: =IFERROR(C43/(SUM(C9,C10,C11,C12)+(C13+C14-C25-C26)),0) -> 0.70563881 | D100: =IFERROR(D43/(SUM(D9,D10,D11,D12)+(D13+D14-D25-D26)),0) -> 0.49428871 | E100: =IFERROR(E43/(SUM(E9,E10,E11,E12)+(E13+E14-E25-E26)),0) -> 0.49428871 | F100: =IFERROR(F43/(SUM(F9,F10,F11,F12)+(F13+F14-F25-F26)),0) -> 0.77527002 | G100: =IFERROR(G43/(SUM(G9,G10,G11,G12)+(G13+G14-G25-G26)),0) -> 0.77527002 | H100: =IFERROR(H43/(SUM(H9,H10,H11,H12)+(H13+H14-H25-H26)),0) -> 0.69505825 | I100: =IFERROR(I43/(SUM(I9,I10,I11,I12)+(I13+I14-I25-I26)),0) -> 0.69505825 | ... Z100: =IFERROR(Z43/(SUM(Z9,Z10,Z11,Z12)+(Z13+Z14-Z25-Z26)),0) -> 0.60316605 | AA100: =IFERROR(AVERAGE(F100,H100,J100,L100,N100,P100,R100,T100,V100,X100),0) -> 0.72281048 | AB100: =AVERAGE(T100,V100,X100) -> 0.79421028
A101: Product (One Time) Sales Profit % | B101: =(B14-B26)/B14 -> 0.15373893 | C101: =(C14-C26)/C14 -> 0.15373893 | D101: =(D14-D26)/D14 -> 0.24089573 | E101: =(E14-E26)/E14 -> 0.24089573 | F101: =IFERROR(F44/(SUM(F10,F11,F12,F13)+(F14+F15-F26-F27)),0) -> 0 | G101: =(G14-G26)/G14 -> 0.16063489 | H101: =(H14-H26)/H14 -> 0.17245469 | I101: =(I14-I26)/I14 -> 0.17245469 | J101: =(J14-J26)/J14 -> 0.15669567 | K101: =(K14-K26)/K14 -> 0.15669567 | L101: =(L14-L26)/L14 -> 0.15865026 | M101: =(M14-M26)/M14 -> 0.15865026 | N101: =(N14-N26)/N14 -> 0.1313336 | ... Z101: =(Z14-Z26)/Z14 -> 0.24732882 | AA101: =IFERROR(AVERAGE(F101,H101,J101,L101,N101,P101,R101,T101,V101,X101),0) -> 0.15408118 | AB101: =AVERAGE(T101,V101,X101) -> 0.18061785
A102: Product (One Time) Sales Profit $ | B102: =B14-B26 -> 12463 | C102: =C14-C26 -> 0.043422818 | D102: =D14-D26 -> 106586 | E102: =E14-E26 -> 0.15992882 | F102: =F14-F26 -> 24603 | G102: =G14-G26 -> 0.062777649 | H102: =H14-H26 -> 69949 | I102: =I14-I26 -> 0.11878513 | ... Z102: =Z14-Z26 -> 1421144 | AA102: =IFERROR(AVERAGE(F102,H102,J102,L102,N102,P102,R102,T102,V102,X102),0) -> 89762.1 | AB102: =AVERAGE(T102,V102,X102) -> 76603
A103: Product Sales % of Total Revenue | B103: =B14/B17 -> 0.28244517 | C103: =C14/C17 -> 0.28244517 | D103: =D14/D17 -> 0.6638923 | E103: =E14/E17 -> 0.6638923 | F103: =F14/F17 -> 0.39080955 | G103: =G14/G17 -> 0.39080955 | H103: =H14/H17 -> 0.6887904 | I103: =I14/I17 -> 0.6887904 | ... Z103: =Z14/Z17 -> 0.70580971 | AA103: =IFERROR(AVERAGE(F103,H103,J103,L103,N103,P103,R103,T103,V103,X103),0) -> 0.68875605 | AB103: =AVERAGE(T103,V103,X103) -> 0.67513551
A106: On Separate Tab
A107: Variance to Budget
A108: Variance to trend month over month
A109: Variance to trend month 3 month avg
A111: Sales $/Profit Needed to Break Even
A112: Recurring Revenue | B112: =SUM(B9:B11,B15) -> 146184 | C112: =SUM(C9:C11,C15) -> 0.5093253 | D112: =SUM(D9:D11,D15) -> 109320 | E112: =SUM(E9:E11,E15) -> 0.1640311 | F112: =SUM(F9:F11,F15) -> 165874 | G112: =SUM(G9:G11,G15) -> 0.42324837 | H112: =SUM(H9:H11,H15) -> 170541 | I112: =SUM(I9:I11,I15) -> 0.28960721 | ... P112: =SUM(P9:P11,P15) -> 133366 | R112: =SUM(R9:R11,R15) -> 125917 | S112: =SUM(S9:S11,S15) -> 0.14101032 | T112: =SUM(T9:T11,T15) -> 140361 | U112: =SUM(U9:U11,U15) -> 0.19698462 | V112: =SUM(V9:V11,V15) -> 137874 | W112: =SUM(W9:W11,W15) -> 0.40772186 | X112: =SUM(X9:X11,X15) -> 141954 | Z112: =SUM(F112:V112) -> 1212223.5
Z113: =SUM(F113:V113) -> 0
A114: Total Expenses (not including Product COGS or Subcontractor) | B114: =B23+B22+B21+B39+B41+B43+B45+B52+B57 -> 200383 | C114: =C23+C22+C21+C39+C41+C43+C45+C52+C57 -> 0.69816212 | D114: =D23+D22+D21+D39+D41+D43+D45+D52+D57 -> 220203 | E114: =E23+E22+E21+E39+E41+E43+E45+E52+E57 -> 0.33040742 | F114: =F23+F22+F21+F39+F41+F43+F45+F52+F57 -> 297945 | G114: =G23+G22+G21+G39+G41+G43+G45+G52+G57 -> 0.76024414 | H114: =H23+H22+H21+H39+H41+H43+H45+H52+H57 -> 213239 | I114: =I23+I22+I21+I39+I41+I43+I45+I52+I57 -> 0.36211558 | ... Y114: =Y23+Y22+Y21+Y39+Y41+Y43+Y45+Y52+Y57 -> 0.35915479 | Z114: =SUM(F114:V114) -> 2182777
A115: Recurring Profit/Loss (GAP) | B115: =B112-B114 -> -54199 | D115: =D112-D114 -> -110883 | F115: =F112-F114 -> -132071 | H115: =H112-H114 -> -42698 | J115: =J112-J114 -> -142510 | L115: =L112-L114 -> -103239 | N115: =N112-N114 -> -136057 | P115: =SUM(P11:P13,P17) -> 1273437 | R115: =R112-R114 -> -94410 | T115: =T112-T114 -> -99328 | V115: =V112-V114 -> -83959 | X115: =SUM(X11:X13,X17) -> 818521 | Z115: =Z112-Z114 -> -970553.41
A116: Product/Project Sales needed @ 15% to Break Even | B116: =B115/0.15 -> -361326.67 | D116: =D115/0.15 -> -739220 | F116: =F115/0.15 -> -880473.33 | H116: =H115/0.15 -> -284653.33 | J116: =J115/0.15 -> -950066.67 | L116: =L115/0.15 -> -688260 | N116: =N115/0.15 -> -907046.67 | P116: =SUM(P12:P14,P18) -> 1019684 | R116: =R115/0.15 -> -629400 | T116: =T115/0.15 -> -662186.67 | V116: =V115/0.15 -> -559726.67 | X116: =SUM(X12:X14,X18) -> 625005
A118: 15% of Revenue (Profit Target)
A119: Product/Project Sales Needed for 15% Profit
A120: Minimum Rev. Target
A121: *Other cost when we sell more (Commission) %
...

Sheet California Calculated
B1: Month 1 ($) | C1: Month 1 (%) | D1: Month 2 ($) | E1: Month 2 (%) | F1: Month 3 ($) | G1: Month 3 (%) | H1: Month 4 ($) | I1: Month 4 (%) | J1: Month 5 ($) | K1: Month 5 (%) | L1: Month 6 ($) | M1: Month 6 (%) | N1: Month 7 ($) | O1: Month 7 (%) | P1: Month 8 ($) | Q1: Month 8 (%) | R1: Month 9 ($) | S1: Month 9 (%) | T1: Month 10 ($) | U1: Month 10 (%) | V1: Month 11 ($) | W1: Month 11 (%) | X1: Month 12 ($) | Y1: Month 12 (%) | Z1: 12 Month Totals | AA1: 12 Month Average | AB1: 3 Month Average | AD1: 9 Month Sparkline | AE1: Last 3 Months Average | AF1: Last 3 Months Sparkline | AG1: Target $ | AH1: Target % | AI1: Swag for Neutral | AJ1: Dashboard | AK1: Annual Budget Q1 * 4 | AL1: Monthly Budget | AM1: Notes:
A2: Location | B2: California | D2: California | F2: California | H2: California | J2: California | L2: California | N2: California | P2: California | Q2: All Locations | R2: California | T2: California | V2: California | X2: California | Y2: All Locations | Z2: All Locations | AA2: All Locations | AB2: All Locations
A3: Month | B3: =+'Combined Company'!B3 -> 01/31/2023 | D3: =+'Combined Company'!D3 -> 02/28/2023 | F3: =+'Combined Company'!F3 -> 03/31/2023 | H3: =+'Combined Company'!H3 -> 45046 | J3: =+'Combined Company'!J3 -> 45077 | L3: =+'Combined Company'!L3 -> 45107 | N3: =+'Combined Company'!N3 -> 45138 | P3: =+'Combined Company'!P3 -> 45169 | R3: =+'Combined Company'!R3 -> 45199 | T3: =+'Combined Company'!T3 -> 45230 | V3: =+'Combined Company'!V3 -> 45260 | X3: =+'Combined Company'!X3 -> 45291
A4: Days in Month | B4: =+'Combined Company'!B4 -> 31 | D4: =+'Combined Company'!D4 -> 28 | F4: =+'Combined Company'!F4 -> 31 | H4: =+'Combined Company'!H4 -> 30 | J4: =+'Combined Company'!J4 -> 31 | L4: =+'Combined Company'!L4 -> 30 | N4: =+'Combined Company'!N4 -> 31 | P4: =+'Combined Company'!P4 -> 31 | R4: =+'Combined Company'!R4 -> 30 | T4: =+'Combined Company'!T4 -> 31 | V4: =+'Combined Company'!V4 -> 30 | X4: =+'Combined Company'!X4 -> 31
A5: Quarter | B5: =+'Combined Company'!B5 -> 1 | D5: =+'Combined Company'!D5 -> 1 | F5: =+'Combined Company'!F5 -> 1 | H5: =+'Combined Company'!H5 -> 2 | J5: =+'Combined Company'!J5 -> 2 | L5: =+'Combined Company'!L5 -> 2 | N5: =+'Combined Company'!N5 -> 3 | P5: =+'Combined Company'!P5 -> 3 | R5: =+'Combined Company'!R5 -> 3 | T5: =+'Combined Company'!T5 -> 4 | V5: =+'Combined Company'!V5 -> 4 | X5: =+'Combined Company'!X5 -> 4
A6: Year | B6: =+'Combined Company'!B6 -> 2023 | D6: =+'Combined Company'!D6 -> 2023 | F6: =+'Combined Company'!F6 -> 2023 | H6: =+'Combined Company'!H6 -> 2023 | J6: =+'Combined Company'!J6 -> 2023 | L6: =+'Combined Company'!L6 -> 2023 | N6: =+'Combined Company'!N6 -> 2023 | P6: =+'Combined Company'!P6 -> 2023 | R6: =+'Combined Company'!R6 -> 2023 | T6: =+'Combined Company'!T6 -> 2023 | V6: =+'Combined Company'!V6 -> 2023 | X6: =+'Combined Company'!X6 -> 2023
A8: Revenue
A9: Managed IT Services (Recurring IT & Security) | B9: =+'Combined Company'!B9-Ohio!B9 -> 516340 | C9: =B9/B$17 -> 0.20938447 | D9: =+'Combined Company'!D9-Ohio!D9 -> 521203 | E9: =D9/D$17 -> 0.38205622 | F9: =+'Combined Company'!F9-Ohio!F9 -> 542420 | G9: =F9/F$17 -> 0.33064914 | H9: =+'Combined Company'!H9-Ohio!H9 -> 647104 | I9: =H9/H$17 -> 0.45740039 | J9: =+'Combined Company'!J9-Ohio!J9 -> 672447 | K9: =J9/J$17 -> 0.4850765 | L9: =+'Combined Company'!L9-Ohio!L9 -> 706392 | M9: =L9/L$17 -> 0.42055479 | N9: =+'Combined Company'!N9-Ohio!N9 -> 626764 | O9: =N9/N$17 -> 0.44227388 | P9: =+'Combined Company'!P9-Ohio!P9 -> 594806 | Q9: =P9/P$17 -> 0.30755572 | R9: =+'Combined Company'!R9-Ohio!R9 -> 529990 | S9: =R9/R$17 -> 0.30503671 | T9: =+'Combined Company'!T9-Ohio!T9 -> 476197 | U9: =T9/T$17 -> 0.40408963 | V9: =+'Combined Company'!V9-Ohio!V9 -> 521897 | W9: =V9/V$17 -> 0.22564479 | X9: =+'Combined Company'!X9-Ohio!X9 -> 349170 | Y9: =X9/X$17 -> 0.30988798 | Z9: =SUM(B9,D9,F9,H9,J9,L9,N9,P9,R9,T9,V9,X9) -> 6704730 | AA9: =IFERROR(AVERAGE(B9,D9,F9,H9,J9,L9,N9,P9,R9,T9,V9,X9),0) -> 558727.5 | AB9: =IFERROR(AVERAGE(T9,V9,X9),0) -> 449088 | AE9: =IFERROR(AVERAGE(R9,T9,V9),0) -> 509361.33 | AK9: =SUM(T9,V9,X9)*4 -> 5389056 | AL9: =AK9/12 -> 449088
A10: Cloud (Private Cloud Only as of 4/1/23) | B10: =+'Combined Company'!B10-Ohio!B10 -> 438849 | C10: =B10/B$17 -> 0.17796058 | D10: =+'Combined Company'!D10-Ohio!D10 -> 470071 | E10: =D10/D$17 -> 0.34457505 | F10: =+'Combined Company'!F10-Ohio!F10 -> 475934 | G10: =F10/F$17 -> 0.29012051 | H10: =+'Combined Company'!H10-Ohio!H10 -> 70303 | I10: =H10/H$17 -> 0.049693124 | J10: =+'Combined Company'!J10-Ohio!J10 -> 70283 | K10: =J10/J$17 -> 0.050699359 | L10: =+'Combined Company'!L10-Ohio!L10 -> 68500 | M10: =L10/L$17 -> 0.040781893 | N10: =+'Combined Company'!N10-Ohio!N10 -> 63151 | O10: =N10/N$17 -> 0.044562287 | P10: =+'Combined Company'!P10-Ohio!P10 -> 58680 | Q10: =P10/P$17 -> 0.030341607 | R10: =+'Combined Company'!R10-Ohio!R10 -> 49426 | S10: =R10/R$17 -> 0.028447224 | T10: =+'Combined Company'!T10-Ohio!T10 -> 33323 | U10: =T10/T$17 -> 0.028277118 | V10: =+'Combined Company'!V10-Ohio!V10 -> 34007 | W10: =V10/V$17 -> 0.014703097 | X10: =+'Combined Company'!X10-Ohio!X10 -> 19383 | Y10: =X10/X$17 -> 0.017202391 | Z10: =SUM(B10,D10,F10,H10,J10,L10,N10,P10,R10,T10,V10,X10) -> 1851910 | AA10: =IFERROR(AVERAGE(B10,D10,F10,H10,J10,L10,N10,P10,R10,T10,V10,X10),0) -> 154325.83 | AB10: =IFERROR(AVERAGE(T10,V10,X10),0) -> 28904.333 | AE10: =IFERROR(AVERAGE(R10,T10,V10),0) -> 38918.667 | AK10: =SUM(T10,V10,X10)*4 -> 346852 | AL10: =AK10/12 -> 28904.333
A11: Recurring Resale (Includes previouse Cloud sales) | B11: =+'Combined Company'!B11-Ohio!B11 -> 0 | C11: =B11/B$17 -> 0 | D11: =+'Combined Company'!D11-Ohio!D11 -> 0 | E11: =D11/D$17 -> 0 | F11: =+'Combined Company'!F11-Ohio!F11 -> 0 | G11: =F11/F$17 -> 0 | H11: =+'Combined Company'!H11-Ohio!H11 -> 238415 | I11: =H11/H$17 -> 0.16852177 | J11: =+'Combined Company'!J11-Ohio!J11 -> 286340 | K11: =J11/J$17 -> 0.20655428 | L11: =+'Combined Company'!L11-Ohio!L11 -> 286731 | M11: =L11/L$17 -> 0.17070705 | N11: =+'Combined Company'!N11-Ohio!N11 -> 283266 | O11: =N11/N$17 -> 0.19988569 | P11: =+'Combined Company'!P11-Ohio!P11 -> 279894 | Q11: =P11/P$17 -> 0.1447245 | R11: =+'Combined Company'!R11-Ohio!R11 -> 257232 | S11: =R11/R$17 -> 0.14805035 | T11: =+'Combined Company'!T11-Ohio!T11 -> 249957 | U11: =T11/T$17 -> 0.21210766 | V11: =+'Combined Company'!V11-Ohio!V11 -> 225316 | W11: =V11/V$17 -> 0.097416506 | X11: =+'Combined Company'!X11-Ohio!X11 -> 195594 | Y11: =X11/X$17 -> 0.17358945 | Z11: =SUM(B11,D11,F11,H11,J11,L11,N11,P11,R11,T11,V11,X11) -> 2302745 | AA11: =IFERROR(AVERAGE(B11,D11,F11,H11,J11,L11,N11,P11,R11,T11,V11,X11),0) -> 191895.42 | AB11: =IFERROR(AVERAGE(T11,V11,X11),0) -> 223622.33 | AE11: =IFERROR(AVERAGE(R11,T11,V11),0) -> 244168.33 | AK11: =SUM(T11,V11,X11)*4 -> 2683468 | AL11: =AK11/12 -> 223622.33 | AM11: *Just started tracking in April - Use April * 4
A12: Project Services | B12: =+'Combined Company'!B12-Ohio!B12 -> 38804 | C12: =B12/B$17 -> 0.015735668 | D12: =+'Combined Company'!D12-Ohio!D12 -> 26321 | E12: =D12/D$17 -> 0.019294021 | F12: =+'Combined Company'!F12-Ohio!F12 -> 34182 | G12: =F12/F$17 -> 0.020836711 | H12: =+'Combined Company'!H12-Ohio!H12 -> 75466 | I12: =H12/H$17 -> 0.053342551 | J12: =+'Combined Company'!J12-Ohio!J12 -> 76753 | K12: =J12/J$17 -> 0.055366559 | L12: =+'Combined Company'!L12-Ohio!L12 -> 16700 | M12: =L12/L$17 -> 0.0099424469 | N12: =+'Combined Company'!N12-Ohio!N12 -> 87590 | O12: =N12/N$17 -> 0.061807584 | P12: =+'Combined Company'!P12-Ohio!P12 -> 67523 | Q12: =P12/P$17 -> 0.034914048 | R12: =+'Combined Company'!R12-Ohio!R12 -> 49407 | S12: =R12/R$17 -> 0.028436289 | T12: =+'Combined Company'!T12-Ohio!T12 -> 12180 | U12: =T12/T$17 -> 0.010335663 | V12: =+'Combined Company'!V12-Ohio!V12 -> 27982 | W12: =V12/V$17 -> 0.012098158 | X12: =+'Combined Company'!X12-Ohio!X12 -> 25988 | Y12: =X12/X$17 -> 0.023064321 | Z12: =SUM(B12,D12,F12,H12,J12,L12,N12,P12,R12,T12,V12,X12) -> 538896 | AA12: =IFERROR(AVERAGE(B12,D12,F12,H12,J12,L12,N12,P12,R12,T12,V12,X12),0) -> 44908 | AB12: =IFERROR(AVERAGE(T12,V12,X12),0) -> 22050 | AE12: =IFERROR(AVERAGE(R12,T12,V12),0) -> 29856.333 | AK12: =SUM(T12,V12,X12)*4 -> 264600 | AL12: =AK12/12 -> 22050
A13: Subcontracted Services | B13: =+'Combined Company'!B13-Ohio!B13 -> 63823 | C13: =B13/B$17 -> 0.025881289 | D13: =+'Combined Company'!D13-Ohio!D13 -> 76877 | E13: =D13/D$17 -> 0.056352967 | F13: =+'Combined Company'!F13-Ohio!F13 -> 40660 | G13: =F13/F$17 -> 0.02478558 | H13: =+'Combined Company'!H13-Ohio!H13 -> 29046 | I13: =H13/H$17 -> 0.020530937 | J13: =+'Combined Company'!J13-Ohio!J13 -> 36525 | K13: =J13/J$17 -> 0.026347681 | L13: =+'Combined Company'!L13-Ohio!L13 -> 26588 | M13: =L13/L$17 -> 0.015829328 | N13: =+'Combined Company'!N13-Ohio!N13 -> 162366 | O13: =N13/N$17 -> 0.11457301 | P13: =+'Combined Company'!P13-Ohio!P13 -> 60247 | Q13: =P13/P$17 -> 0.031151854 | R13: =+'Combined Company'!R13-Ohio!R13 -> 22361 | S13: =R13/R$17 -> 0.012869914 | T13: =+'Combined Company'!T13-Ohio!T13 -> 29054 | U13: =T13/T$17 -> 0.024654544 | V13: =+'Combined Company'!V13-Ohio!V13 -> 17170 | W13: =V13/V$17 -> 0.0074235359 | X13: =+'Combined Company'!X13-Ohio!X13 -> 0 | Y13: =X13/X$17 -> 0 | Z13: =SUM(B13,D13,F13,H13,J13,L13,N13,P13,R13,T13,V13,X13) -> 564717 | AA13: =IFERROR(AVERAGE(B13,D13,F13,H13,J13,L13,N13,P13,R13,T13,V13,X13),0) -> 47059.75 | AB13: =IFERROR(AVERAGE(T13,V13,X13),0) -> 15408 | AE13: =IFERROR(AVERAGE(R13,T13,V13),0) -> 22861.667 | AK13: =SUM(T13,V13,X13)*4 -> 184896 | AL13: =AK13/12 -> 15408
A14: Product Sales | B14: =+'Combined Company'!B14-Ohio!B14 -> 1384028 | C14: =B14/B$17 -> 0.5612464 | D14: =+'Combined Company'!D14-Ohio!D14 -> 239027 | E14: =D14/D$17 -> 0.1752134 | F14: =+'Combined Company'!F14-Ohio!F14 -> 518838 | G14: =F14/F$17 -> 0.31627399 | H14: =+'Combined Company'!H14-Ohio!H14 -> 340677 | I14: =H14/H$17 -> 0.24080487 | J14: =+'Combined Company'!J14-Ohio!J14 -> 233041 | K14: =J14/J$17 -> 0.1681065 | L14: =+'Combined Company'!L14-Ohio!L14 -> 557722 | M14: =L14/L$17 -> 0.3320432 | N14: =+'Combined Company'!N14-Ohio!N14 -> 182086 | O14: =N14/N$17 -> 0.12848836 | P14: =+'Combined Company'!P14-Ohio!P14 -> 861975 | Q14: =P14/P$17 -> 0.44570052 | R14: =+'Combined Company'!R14-Ohio!R14 -> 814518 | S14: =R14/R$17 -> 0.46879732 | T14: =+'Combined Company'!T14-Ohio!T14 -> 374164 | U14: =T14/T$17 -> 0.31750681 | V14: =+'Combined Company'!V14-Ohio!V14 -> 1472258 | W14: =V14/V$17 -> 0.63653815 | X14: =+'Combined Company'!X14-Ohio!X14 -> 532176 | Y14: =X14/X$17 -> 0.4723056 | Z14: =SUM(B14,D14,F14,H14,J14,L14,N14,P14,R14,T14,V14,X14) -> 7510510 | AA14: =IFERROR(AVERAGE(B14,D14,F14,H14,J14,L14,N14,P14,R14,T14,V14,X14),0) -> 625875.83 | AB14: =IFERROR(AVERAGE(T14,V14,X14),0) -> 792866 | AE14: =IFERROR(AVERAGE(R14,T14,V14),0) -> 886980 | AK14: =SUM(T14,V14,X14)*4 -> 9514392 | AL14: =AK14/12 -> 792866
A15: Commissions | B15: =+'Combined Company'!B15-Ohio!B15 -> 24146 | C15: =B15/B$17 -> 0.009791605 | D15: =+'Combined Company'!D15-Ohio!D15 -> 30706 | E15: =D15/D$17 -> 0.022508347 | F15: =+'Combined Company'!F15-Ohio!F15 -> 28436 | G15: =F15/F$17 -> 0.017334057 | H15: =+'Combined Company'!H15-Ohio!H15 -> 13732 | I15: =H15/H$17 -> 0.0097063566 | J15: =+'Combined Company'!J15-Ohio!J15 -> 10881 | K15: =J15/J$17 -> 0.0078491203 | L15: =+'Combined Company'!L15-Ohio!L15 -> 17034 | M15: =L15/L$17 -> 0.010141296 | N15: =+'Combined Company'!N15-Ohio!N15 -> 11917 | O15: =N15/N$17 -> 0.0084091903 | P15: =+'Combined Company'!P15-Ohio!P15 -> 10853 | Q15: =P15/P$17 -> 0.0056117495 | R15: =+'Combined Company'!R15-Ohio!R15 -> 14529 | S15: =R15/R$17 -> 0.0083621925 | T15: =+'Combined Company'!T15-Ohio!T15 -> 3569 | U15: =T15/T$17 -> 0.0030285699 | V15: =+'Combined Company'!V15-Ohio!V15 -> 14284 | W15: =V15/V$17 -> 0.0061757592 | X15: =+'Combined Company'!X15-Ohio!X15 -> 4451 | Y15: =X15/X$17 -> 0.0039502575 | Z15: =SUM(B15,D15,F15,H15,J15,L15,N15,P15,R15,T15,V15,X15) -> 184538 | AA15: =IFERROR(AVERAGE(B15,D15,F15,H15,J15,L15,N15,P15,R15,T15,V15,X15),0) -> 15378.167 | AB15: =IFERROR(AVERAGE(T15,V15,X15),0) -> 7434.6667 | AE15: =IFERROR(AVERAGE(R15,T15,V15),0) -> 10794 | AK15: =SUM(T15,V15,X15)*4 -> 89216 | AL15: =AK15/12 -> 7434.6667
A16: Sales Returns and Discounts | B16: =+'Combined Company'!B16-Ohio!B16 -> 0 | C16: =B16/B$17 -> 0 | D16: =+'Combined Company'!D16-Ohio!D16 -> 0 | E16: =D16/D$17 -> 0 | F16: =+'Combined Company'!F16-Ohio!F16 -> 0 | G16: =F16/F$17 -> 0 | H16: =+'Combined Company'!H16-Ohio!H16 -> 0 | I16: =H16/H$17 -> 0 | J16: =+'Combined Company'!J16-Ohio!J16 -> 0 | K16: =J16/J$17 -> 0 | L16: =+'Combined Company'!L16-Ohio!L16 -> 0 | M16: =L16/L$17 -> 0 | N16: =+'Combined Company'!N16-Ohio!N16 -> 0 | O16: =N16/N$17 -> 0 | P16: =+'Combined Company'!P16-Ohio!P16 -> 0 | Q16: =P16/P$17 -> 0 | R16: =+'Combined Company'!R16-Ohio!R16 -> 0 | S16: =R16/R$17 -> 0 | T16: =+'Combined Company'!T16-Ohio!T16 -> 0 | U16: =T16/T$17 -> 0 | V16: =+'Combined Company'!V16-Ohio!V16 -> 0 | W16: =V16/V$17 -> 0 | X16: =+'Combined Company'!X16-Ohio!X16 -> 0 | Y16: =X16/X$17 -> 0 | Z16: =SUM(B16,D16,F16,H16,J16,L16,N16,P16,R16,T16,V16,X16) -> 0 | AA16: =IFERROR(AVERAGE(B16,D16,F16,H16,J16,L16,N16,P16,R16,T16,V16,X16),0) -> 0 | AB16: =IFERROR(AVERAGE(T16,V16,X16),0) -> 0 | AE16: =IFERROR(AVERAGE(R16,T16,V16),0) -> 0 | AK16: =SUM(T16,V16,X16)*4 -> 0 | AL16: =AK16/12 -> 0
A17: Total Revenue | B17: =SUM(B9:B16) -> 2465990 | C17: =B17/B$17 -> 1 | D17: =SUM(D9:D16) -> 1364205 | E17: =D17/D$17 -> 1 | F17: =SUM(F9:F16) -> 1640470 | G17: =F17/F$17 -> 1 | H17: =SUM(H9:H16) -> 1414743 | I17: =H17/H$17 -> 1 | J17: =SUM(J9:J16) -> 1386270 | K17: =J17/J$17 -> 1 | L17: =SUM(L9:L16) -> 1679667 | M17: =L17/L$17 -> 1 | N17: =SUM(N9:N16) -> 1417140 | O17: =N17/N$17 -> 1 | P17: =SUM(P9:P16) -> 1933978 | Q17: =P17/P$17 -> 1 | R17: =SUM(R9:R16) -> 1737463 | S17: =R17/R$17 -> 1 | T17: =SUM(T9:T16) -> 1178444 | U17: =T17/T$17 -> 1 | V17: =SUM(V9:V16) -> 2312914 | W17: =V17/V$17 -> 1 | X17: =SUM(X9:X16) -> 1126762 | Y17: =X17/X$17 -> 1 | Z17: =SUM(B17,D17,F17,H17,J17,L17,N17,P17,R17,T17,V17,X17) -> 19658046 | AA17: =IFERROR(AVERAGE(B17,D17,F17,H17,J17,L17,N17,P17,R17,T17,V17,X17),0) -> 1638170.5 | AB17: =IFERROR(AVERAGE(T17,V17,X17),0) -> 1539373.3 | AE17: =IFERROR(AVERAGE(R17:V17),0) -> 1045764.6 | AG17: $2M for Green, 1.8-2 yellow, less than 1.8 red | AI17: $50k | AK17: =SUM(T17,V17,X17)*4 -> 18472480 | AL17: =AK17/12 -> 1539373.3
A20: Cost of Goods and Services
A21: Managed IT Service Costs | B21: =+'Combined Company'!B21-Ohio!B21 -> 42862 | C21: =B21/B$17 -> 0.017381255 | D21: =+'Combined Company'!D21-Ohio!D21 -> 62729 | E21: =D21/D$17 -> 0.045982092 | F21: =+'Combined Company'!F21-Ohio!F21 -> 54143 | G21: =F21/F$17 -> 0.033004566 | H21: =+'Combined Company'!H21-Ohio!H21 -> 21639 | I21: =H21/H$17 -> 0.015295358 | J21: =+'Combined Company'!J21-Ohio!J21 -> 23577 | K21: =J21/J$17 -> 0.017007509 | L21: =+'Combined Company'!L21-Ohio!L21 -> 19641 | M21: =L21/L$17 -> 0.011693389 | N21: =+'Combined Company'!N21-Ohio!N21 -> 19527 | O21: =N21/N$17 -> 0.013779161 | P21: =+'Combined Company'!P21-Ohio!P21 -> 29057 | Q21: =P21/P$17 -> 0.015024473 | R21: =+'Combined Company'!R21-Ohio!R21 -> 7697 | S21: =R21/R$17 -> 0.0044300224 | T21: =+'Combined Company'!T21-Ohio!T21 -> 13074 | U21: =T21/T$17 -> 0.01109429 | V21: =+'Combined Company'!V21-Ohio!V21 -> 12943 | W21: =V21/V$17 -> 0.0055959711 | X21: =+'Combined Company'!X21-Ohio!X21 -> 14293 | Y21: =X21/X$17 -> 0.012685021 | Z21: =SUM(F21,H21,J21,L21,N21,P21,R21,T21,V21,X21) -> 215591 | AA21: =IFERROR(AVERAGE(B21,D21,F21,H21,J21,L21,N21,P21,R21,T21,V21,X21),0) -> 26765.167 | AB21: =IFERROR(AVERAGE(T21,V21,X21),0) -> 13436.667 | AE21: =IFERROR(AVERAGE(R21:V21),0) -> 6742.8031 | AK21: =SUM(T21,V21,X21)*4 -> 161240 | AL21: =AK21/12 -> 13436.667
A22: Cloud Service Costs | B22: =+'Combined Company'!B22-Ohio!B22 -> 143457 | C22: =B22/B$17 -> 0.058174202 | D22: =+'Combined Company'!D22-Ohio!D22 -> 150427 | E22: =D22/D$17 -> 0.11026715 | F22: =+'Combined Company'!F22-Ohio!F22 -> 147642 | G22: =F22/F$17 -> 0.089999817 | H22: =+'Combined Company'!H22-Ohio!H22 -> 39759 | I22: =H22/H$17 -> 0.028103337 | J22: =+'Combined Company'!J22-Ohio!J22 -> 40214 | K22: =J22/J$17 -> 0.029008779 | L22: =+'Combined Company'!L22-Ohio!L22 -> 51921 | M22: =L22/L$17 -> 0.030911484 | N22: =+'Combined Company'!N22-Ohio!N22 -> 42593 | O22: =N22/N$17 -> 0.030055605 | P22: =+'Combined Company'!P22-Ohio!P22 -> 26873 | Q22: =P22/P$17 -> 0.013895194 | R22: =+'Combined Company'!R22-Ohio!R22 -> 42882 | S22: =R22/R$17 -> 0.024680813 | T22: =+'Combined Company'!T22-Ohio!T22 -> 12606 | U22: =T22/T$17 -> 0.010697157 | V22: =+'Combined Company'!V22-Ohio!V22 -> 17882 | W22: =V22/V$17 -> 0.0077313726 | X22: =+'Combined Company'!X22-Ohio!X22 -> 13304 | Y22: =X22/X$17 -> 0.011807285 | Z22: =SUM(F22,H22,J22,L22,N22,P22,R22,T22,V22,X22) -> 435676 | AA22: =IFERROR(AVERAGE(B22,D22,F22,H22,J22,L22,N22,P22,R22,T22,V22,X22),0) -> 60796.667 | AB22: =IFERROR(AVERAGE(T22,V22,X22),0) -> 14597.333 | AE22: =IFERROR(AVERAGE(R22:V22),0) -> 14674.007 | AK22: =SUM(T22,V22,X22)*4 -> 175168 | AL22: =AK22/12 -> 14597.333
A23: Recurring Resale Costs | B23: =+'Combined Company'!B23-Ohio!B23 -> 0 | D23: =+'Combined Company'!D23-Ohio!D23 -> 0 | F23: =+'Combined Company'!F23-Ohio!F23 -> 0 | H23: =+'Combined Company'!H23-Ohio!H23 -> 185759 | J23: =+'Combined Company'!J23-Ohio!J23 -> 172602 | L23: =+'Combined Company'!L23-Ohio!L23 -> 204537 | N23: =+'Combined Company'!N23-Ohio!N23 -> 142090 | P23: =+'Combined Company'!P23-Ohio!P23 -> 198711 | R23: =+'Combined Company'!R23-Ohio!R23 -> 172077 | T23: =+'Combined Company'!T23-Ohio!T23 -> 171019 | V23: =+'Combined Company'!V23-Ohio!V23 -> 157708 | X23: =+'Combined Company'!X23-Ohio!X23 -> 138529 | Y23: =X23/X$17 -> 0.12294433 | Z23: =SUM(F23,H23,J23,L23,N23,P23,R23,T23,V23,X23) -> 1543032 | AA23: =IFERROR(AVERAGE(B23,D23,F23,H23,J23,L23,N23,P23,R23,T23,V23,X23),0) -> 128586 | AB23: =IFERROR(AVERAGE(T23,V23,X23),0) -> 155752 | AK23: =SUM(T23,V23,X23)*4 -> 1869024
A24: Project Service Costs | B24: =+'Combined Company'!B24-Ohio!B24 -> 0 | C24: =B24/B$17 -> 0 | D24: =+'Combined Company'!D24-Ohio!D24 -> 0 | E24: =D24/D$17 -> 0 | F24: =+'Combined Company'!F24-Ohio!F24 -> 0 | G24: =F24/F$17 -> 0 | H24: =+'Combined Company'!H24-Ohio!H24 -> 0 | I24: =H24/H$17 -> 0 | J24: =+'Combined Company'!J24-Ohio!J24 -> 0 | K24: =J24/J$17 -> 0 | L24: =+'Combined Company'!L24-Ohio!L24 -> 0 | M24: =L24/L$17 -> 0 | N24: =+'Combined Company'!N24-Ohio!N24 -> 0 | O24: =N24/N$17 -> 0 | P24: =+'Combined Company'!P24-Ohio!P24 -> 0 | Q24: =P24/P$17 -> 0 | R24: =+'Combined Company'!R24-Ohio!R24 -> 0 | S24: =R24/R$17 -> 0 | T24: =+'Combined Company'!T24-Ohio!T24 -> 2039 | U24: =T24/T$17 -> 0.0017302477 | V24: =+'Combined Company'!V24-Ohio!V24 -> 0 | W24: =V24/V$17 -> 0 | X24: =+'Combined Company'!X24-Ohio!X24 -> 0 | Y24: =X24/X$17 -> 0 | Z24: =SUM(F24,H24,J24,L24,N24,P24,R24,T24,V24,X24) -> 2039 | AA24: =IFERROR(AVERAGE(B24,D24,F24,H24,J24,L24,N24,P24,R24,T24,V24,X24),0) -> 169.91667 | AB24: =IFERROR(AVERAGE(T24,V24,X24),0) -> 679.66667 | AE24: =IFERROR(AVERAGE(R24:V24),0) -> 407.80035 | AK24: =SUM(T24,V24,X24)*4 -> 8156 | AL24: =AK24/12 -> 679.66667
A25: Subcontractor Service Costs | B25: =+'Combined Company'!B25-Ohio!B25 -> 53187 | C25: =B25/B$17 -> 0.021568214 | D25: =+'Combined Company'!D25-Ohio!D25 -> 63451 | E25: =D25/D$17 -> 0.046511338 | F25: =+'Combined Company'!F25-Ohio!F25 -> 33469 | G25: =F25/F$17 -> 0.02040208 | H25: =+'Combined Company'!H25-Ohio!H25 -> 24206 | I25: =H25/H$17 -> 0.017109821 | J25: =+'Combined Company'!J25-Ohio!J25 -> 30438 | K25: =J25/J$17 -> 0.021956762 | L25: =+'Combined Company'!L25-Ohio!L25 -> 22057 | M25: =L25/L$17 -> 0.01313177 | N25: =+'Combined Company'!N25-Ohio!N25 -> 138130 | O25: =N25/N$17 -> 0.097470963 | P25: =+'Combined Company'!P25-Ohio!P25 -> 50205 | Q25: =P25/P$17 -> 0.025959447 | R25: =+'Combined Company'!R25-Ohio!R25 -> 26684 | S25: =R25/R$17 -> 0.015358025 | T25: =+'Combined Company'!T25-Ohio!T25 -> 24212 | U25: =T25/T$17 -> 0.020545737 | V25: =+'Combined Company'!V25-Ohio!V25 -> 14381 | W25: =V25/V$17 -> 0.0062176977 | X25: =+'Combined Company'!X25-Ohio!X25 -> 0 | Y25: =X25/X$17 -> 0 | Z25: =SUM(F25,H25,J25,L25,N25,P25,R25,T25,V25,X25) -> 363782 | AA25: =IFERROR(AVERAGE(B25,D25,F25,H25,J25,L25,N25,P25,R25,T25,V25,X25),0) -> 40035 | AB25: =IFERROR(AVERAGE(T25,V25,X25),0) -> 12864.333 | AE25: =IFERROR(AVERAGE(R25:V25),0) -> 13055.407 | AK25: =SUM(T25,V25,X25)*4 -> 154372 | AL25: =AK25/12 -> 12864.333
A26: Product Sales Costs | B26: =+'Combined Company'!B26-Ohio!B26 -> 1161366 | C26: =B26/B$17 -> 0.47095325 | D26: =+'Combined Company'!D26-Ohio!D26 -> 208251 | E26: =D26/D$17 -> 0.15265374 | F26: =+'Combined Company'!F26-Ohio!F26 -> 415849 | G26: =F26/F$17 -> 0.25349382 | H26: =+'Combined Company'!H26-Ohio!H26 -> 296207 | I26: =H26/H$17 -> 0.2093716 | J26: =+'Combined Company'!J26-Ohio!J26 -> 197915 | K26: =J26/J$17 -> 0.142768 | L26: =+'Combined Company'!L26-Ohio!L26 -> 477771 | M26: =L26/L$17 -> 0.28444388 | N26: =+'Combined Company'!N26-Ohio!N26 -> 163858 | O26: =N26/N$17 -> 0.11562584 | P26: =+'Combined Company'!P26-Ohio!P26 -> 747057 | Q26: =P26/P$17 -> 0.38627999 | R26: =+'Combined Company'!R26-Ohio!R26 -> 696978 | S26: =R26/R$17 -> 0.40114696 | T26: =+'Combined Company'!T26-Ohio!T26 -> 302038 | U26: =T26/T$17 -> 0.25630238 | V26: =+'Combined Company'!V26-Ohio!V26 -> 1247100 | W26: =V26/V$17 -> 0.53918996 | X26: =+'Combined Company'!X26-Ohio!X26 -> 450151 | Y26: =X26/X$17 -> 0.3995085 | Z26: =SUM(F26,H26,J26,L26,N26,P26,R26,T26,V26,X26) -> 4994924 | AA26: =IFERROR(AVERAGE(B26,D26,F26,H26,J26,L26,N26,P26,R26,T26,V26,X26),0) -> 530378.42 | AB26: =IFERROR(AVERAGE(T26,V26,X26),0) -> 666429.67 | AE26: =IFERROR(AVERAGE(R26:V26),0) -> 449223.33 | AK26: =SUM(T26,V26,X26)*4 -> 7997156 | AL26: =AK26/12 -> 666429.67
A27: Total COGS | B27: =SUM(B21:B26) -> 1400872 | C27: =B27/B$17 -> 0.56807692 | D27: =SUM(D21:D26) -> 484858 | E27: =D27/D$17 -> 0.35541433 | F27: =SUM(F21:F26) -> 651103 | G27: =F27/F$17 -> 0.39690028 | H27: =SUM(H21:H26) -> 567570 | I27: =H27/H$17 -> 0.40118241 | J27: =SUM(J21:J26) -> 464746 | K27: =J27/J$17 -> 0.33524927 | L27: =SUM(L21:L26) -> 775927 | M27: =L27/L$17 -> 0.46195288 | N27: =SUM(N21:N26) -> 506198 | O27: =N27/N$17 -> 0.35719689 | P27: =SUM(P21:P26) -> 1051903 | Q27: =P27/P$17 -> 0.54390639 | R27: =SUM(R21:R26) -> 946318 | S27: =R27/R$17 -> 0.54465505 | T27: =SUM(T21:T26) -> 524988 | U27: =T27/T$17 -> 0.44549253 | V27: =SUM(V21:V26) -> 1450014 | W27: =V27/V$17 -> 0.62692085 | X27: =SUM(X21:X26) -> 616277 | Y27: =X27/X$17 -> 0.54694514 | Z27: =SUM(F27,H27,J27,L27,N27,P27,R27,T27,V27,X27) -> 7555044 | AA27: =IFERROR(AVERAGE(B27,D27,F27,H27,J27,L27,N27,P27,R27,T27,V27,X27),0) -> 786731.17 | AB27: =IFERROR(AVERAGE(T27,V27,X27),0) -> 863759.67 | AE27: =IFERROR(AVERAGE(R27:V27),0) -> 584264.2 | AK27: =SUM(T27,V27,X27)*4 -> 10365116 | AL27: =AK27/12 -> 863759.67
Z28: =SUM(F28,H28,J28,L28,N28,P28,R28,T28,V28,X28) -> 0 | AA28: =IFERROR(AVERAGE(F28,H28,J28,L28,N28,P28,R28,T28,V28,X28),0) -> 0 | AB28: =IFERROR(AVERAGE(T28,V28,X28),0) -> 0
A29: Gross Profit | B29: =+B17-B27 -> 1065118 | C29: =B29/B$17 -> 0.43192308 | D29: =+D17-D27 -> 879347 | E29: =D29/D$17 -> 0.64458567 | F29: =+F17-F27 -> 989367 | G29: =F29/F$17 -> 0.60309972 | H29: =+H17-H27 -> 847173 | I29: =H29/H$17 -> 0.59881759 | J29: =+J17-J27 -> 921524 | K29: =J29/J$17 -> 0.66475073 | L29: =+L17-L27 -> 903740 | M29: =L29/L$17 -> 0.53804712 | N29: =+N17-N27 -> 910942 | O29: =N29/N$17 -> 0.64280311 | P29: =+P17-P27 -> 882075 | Q29: =P29/P$17 -> 0.45609361 | R29: =+R17-R27 -> 791145 | S29: =R29/R$17 -> 0.45534495 | T29: =+T17-T27 -> 653456 | U29: =T29/T$17 -> 0.55450747 | V29: =+V17-V27 -> 862900 | W29: =V29/V$17 -> 0.37307915 | X29: =+X17-X27 -> 510485 | Y29: =X29/X$17 -> 0.45305486 | Z29: =SUM(F29,H29,J29,L29,N29,P29,R29,T29,V29,X29) -> 8272807 | AA29: =IFERROR(AVERAGE(B29,D29,F29,H29,J29,L29,N29,P29,R29,T29,V29,X29),0) -> 851439.33 | AB29: =IFERROR(AVERAGE(T29,V29,X29),0) -> 675613.67 | AE29: =IFERROR(AVERAGE(R29:V29),0) -> 461500.4 | AK29: =SUM(T29,V29,X29)*4 -> 8107364 | AL29: =AK29/12 -> 675613.67
A30: Gross Profit % | B30: 0.58670021 | C30: =C29/C17 -> 0.43192308 | D30: 0.58670021 | E30: =E29/E17 -> 0.64458567 | F30: 0.58670021 | G30: =G29/G17 -> 0.60309972 | H30: 0.58670021 | I30: =I29/I17 -> 0.59881759 | J30: 0.58670021 | K30: =K29/K17 -> 0.66475073 | L30: 0.58670021 | M30: =M29/M17 -> 0.53804712 | N30: 0.58670021 | O30: =O29/O17 -> 0.64280311 | P30: 0.58670021 | Q30: =Q29/Q17 -> 0.45609361 | R30: 0.58670021 | S30: =S29/S17 -> 0.45534495 | T30: 0.58670021 | U30: =U29/U17 -> 0.55450747 | V30: 0.58670021 | W30: =W29/W17 -> 0.37307915 | X30: 0.58670021 | Y30: =Y29/Y17 -> 0.45305486 | Z30: =Z29/Z17 -> 0.42083567 | AA30: =AA29/AA17 -> 0.51975013 | AB30: =AB29/AB17 -> 0.43888877 | AH30: 0.55
A32: Operating Expenses
A33: General & Admin Expenses
A34: Charitable Contributions | B34: =+'Combined Company'!B34-Ohio!B34 -> 1000 | C34: =B34/B$17 -> 0.00040551665 | D34: =+'Combined Company'!D34-Ohio!D34 -> 1515 | E34: =D34/D$17 -> 0.0011105369 | F34: =+'Combined Company'!F34-Ohio!F34 -> 2250 | G34: =F34/F$17 -> 0.0013715582 | H34: =+'Combined Company'!H34-Ohio!H34 -> 5500 | I34: =H34/H$17 -> 0.0038876319 | J34: =+'Combined Company'!J34-Ohio!J34 -> 3195 | K34: =J34/J$17 -> 0.0023047458 | L34: =+'Combined Company'!L34-Ohio!L34 -> 5733 | M34: =L34/L$17 -> 0.0034131765 | N34: =+'Combined Company'!N34-Ohio!N34 -> 2000 | O34: =N34/N$17 -> 0.0014112932 | P34: =+'Combined Company'!P34-Ohio!P34 -> 2906 | Q34: =P34/P$17 -> 0.0015026024 | R34: =+'Combined Company'!R34-Ohio!R34 -> 1990 | S34: =R34/R$17 -> 0.0011453481 | T34: =+'Combined Company'!T34-Ohio!T34 -> 4549 | U34: =T34/T$17 -> 0.0038601749 | V34: =+'Combined Company'!V34-Ohio!V34 -> 0 | W34: =V34/V$17 -> 0 | X34: =+'Combined Company'!X34-Ohio!X34 -> 2120 | Y34: =X34/X$17 -> 0.0018814976 | Z34: =SUM(B34,D34,F34,H34,J34,L34,N34,P34,R34,T34,V34,X34) -> 32758 | AA34: =IFERROR(AVERAGE(B34,D34,F34,H34,J34,L34,N34,P34,R34,T34,V34,X34),0) -> 2729.8333 | AB34: =IFERROR(AVERAGE(T34,V34,X34),0) -> 2223 | AE34: =IFERROR(AVERAGE(R34:V34),0) -> 1307.801 | AK34: =SUM(T34,V34,X34)*4 -> 26676 | AL34: =AK34/12 -> 2223
A35: Education | B35: =+'Combined Company'!B35-Ohio!B35 -> 384 | C35: =B35/B$17 -> 0.00015571839 | D35: =+'Combined Company'!D35-Ohio!D35 -> 747 | E35: =D35/D$17 -> 0.00054757166 | F35: =+'Combined Company'!F35-Ohio!F35 -> 551 | G35: =F35/F$17 -> 0.00033587935 | H35: =+'Combined Company'!H35-Ohio!H35 -> 30 | I35: =H35/H$17 -> 2.1205265e-05 | J35: =+'Combined Company'!J35-Ohio!J35 -> 195 | K35: =J35/J$17 -> 0.00014066524 | L35: =+'Combined Company'!L35-Ohio!L35 -> 3530 | M35: =L35/L$17 -> 0.002101607 | N35: =+'Combined Company'!N35-Ohio!N35 -> 580 | O35: =N35/N$17 -> 0.00040927502 | P35: =+'Combined Company'!P35-Ohio!P35 -> 591 | Q35: =P35/P$17 -> 0.00030558776 | R35: =+'Combined Company'!R35-Ohio!R35 -> 288 | S35: =R35/R$17 -> 0.00016575893 | T35: =+'Combined Company'!T35-Ohio!T35 -> 264 | U35: =T35/T$17 -> 0.00022402422 | V35: =+'Combined Company'!V35-Ohio!V35 -> 142 | W35: =V35/V$17 -> 6.1394414e-05 | X35: =+'Combined Company'!X35-Ohio!X35 -> 323 | Y35: =X35/X$17 -> 0.00028666213 | Z35: =SUM(B35,D35,F35,H35,J35,L35,N35,P35,R35,T35,V35,X35) -> 7625 | AA35: =IFERROR(AVERAGE(B35,D35,F35,H35,J35,L35,N35,P35,R35,T35,V35,X35),0) -> 635.41667 | AB35: =IFERROR(AVERAGE(T35,V35,X35),0) -> 243 | AE35: =IFERROR(AVERAGE(R35:V35),0) -> 138.80008 | AK35: =SUM(T35,V35,X35)*4 -> 2916 | AL35: =AK35/12 -> 243
A36: Finance Charges | B36: =+'Combined Company'!B36-Ohio!B36 -> 5925 | C36: =B36/B$17 -> 0.0024026861 | D36: =+'Combined Company'!D36-Ohio!D36 -> 10413 | E36: =D36/D$17 -> 0.007633017 | F36: =+'Combined Company'!F36-Ohio!F36 -> 5218 | G36: =F36/F$17 -> 0.0031807957 | H36: =+'Combined Company'!H36-Ohio!H36 -> 5293 | I36: =H36/H$17 -> 0.0037413156 | J36: =+'Combined Company'!J36-Ohio!J36 -> 4211 | K36: =J36/J$17 -> 0.0030376478 | L36: =+'Combined Company'!L36-Ohio!L36 -> 5556 | M36: =L36/L$17 -> 0.0033077985 | N36: =+'Combined Company'!N36-Ohio!N36 -> 3452 | O36: =N36/N$17 -> 0.002435892 | P36: =+'Combined Company'!P36-Ohio!P36 -> 6117 | Q36: =P36/P$17 -> 0.0031629109 | R36: =+'Combined Company'!R36-Ohio!R36 -> 3960 | S36: =R36/R$17 -> 0.0022791852 | T36: =+'Combined Company'!T36-Ohio!T36 -> 4108 | U36: =T36/T$17 -> 0.0034859527 | V36: =+'Combined Company'!V36-Ohio!V36 -> 7324 | W36: =V36/V$17 -> 0.0031665682 | X36: =+'Combined Company'!X36-Ohio!X36 -> 3977 | Y36: =X36/X$17 -> 0.003529583 | Z36: =SUM(B36,D36,F36,H36,J36,L36,N36,P36,R36,T36,V36,X36) -> 65554 | AA36: =IFERROR(AVERAGE(B36,D36,F36,H36,J36,L36,N36,P36,R36,T36,V36,X36),0) -> 5462.8333 | AB36: =IFERROR(AVERAGE(T36,V36,X36),0) -> 5136.3333 | AE36: =IFERROR(AVERAGE(R36:V36),0) -> 3078.4012 | AK36: =SUM(T36,V36,X36)*4 -> 61636 | AL36: =AK36/12 -> 5136.3333
A37: Travel, Meals and Entertainment | B37: =+'Combined Company'!B37-Ohio!B37 -> 6909 | C37: =B37/B$17 -> 0.0028017145 | D37: =+'Combined Company'!D37-Ohio!D37 -> 22230 | E37: =D37/D$17 -> 0.016295205 | F37: =+'Combined Company'!F37-Ohio!F37 -> 23841 | G37: =F37/F$17 -> 0.01453303 | H37: =+'Combined Company'!H37-Ohio!H37 -> 8385 | I37: =H37/H$17 -> 0.0059268715 | J37: =+'Combined Company'!J37-Ohio!J37 -> 13095 | K37: =J37/J$17 -> 0.0094462118 | L37: =+'Combined Company'!L37-Ohio!L37 -> 11589 | M37: =L37/L$17 -> 0.0068995819 | N37: =+'Combined Company'!N37-Ohio!N37 -> 4361 | O37: =N37/N$17 -> 0.0030773248 | P37: =+'Combined Company'!P37-Ohio!P37 -> 7884 | Q37: =P37/P$17 -> 0.0040765717 | R37: =+'Combined Company'!R37-Ohio!R37 -> 11388 | S37: =R37/R$17 -> 0.0065543842 | T37: =+'Combined Company'!T37-Ohio!T37 -> 15171 | U37: =T37/T$17 -> 0.012873756 | V37: =+'Combined Company'!V37-Ohio!V37 -> 16529 | W37: =V37/V$17 -> 0.0071463963 | X37: =+'Combined Company'!X37-Ohio!X37 -> 8905 | Y37: =X37/X$17 -> 0.0079031774 | Z37: =SUM(B37,D37,F37,H37,J37,L37,N37,P37,R37,T37,V37,X37) -> 150287 | AA37: =IFERROR(AVERAGE(B37,D37,F37,H37,J37,L37,N37,P37,R37,T37,V37,X37),0) -> 12523.917 | AB37: =IFERROR(AVERAGE(T37,V37,X37),0) -> 13535 | AE37: =IFERROR(AVERAGE(R37:V37),0) -> 8617.6039 | AK37: =SUM(T37,V37,X37)*4 -> 162420 | AL37: =AK37/12 -> 13535
A38: Office Supplies | B38: =+'Combined Company'!B38-Ohio!B38 -> 11061 | C38: =B38/B$17 -> 0.0044854196 | D38: =+'Combined Company'!D38-Ohio!D38 -> 15433 | E38: =D38/D$17 -> 0.011312816 | F38: =+'Combined Company'!F38-Ohio!F38 -> 25552 | G38: =F38/F$17 -> 0.015576024 | H38: =+'Combined Company'!H38-Ohio!H38 -> 4509 | I38: =H38/H$17 -> 0.0031871513 | J38: =+'Combined Company'!J38-Ohio!J38 -> 8763 | K38: =J38/J$17 -> 0.0063212794 | L38: =+'Combined Company'!L38-Ohio!L38 -> 7291 | M38: =L38/L$17 -> 0.0043407413 | N38: =+'Combined Company'!N38-Ohio!N38 -> 5820 | O38: =N38/N$17 -> 0.0041068631 | P38: =+'Combined Company'!P38-Ohio!P38 -> 8797 | Q38: =P38/P$17 -> 0.0045486557 | R38: =+'Combined Company'!R38-Ohio!R38 -> 9338 | S38: =R38/R$17 -> 0.0053745029 | T38: =+'Combined Company'!T38-Ohio!T38 -> 6617 | U38: =T38/T$17 -> 0.0056150313 | V38: =+'Combined Company'!V38-Ohio!V38 -> 5259 | W38: =V38/V$17 -> 0.0022737551 | X38: =+'Combined Company'!X38-Ohio!X38 -> 11315 | Y38: =X38/X$17 -> 0.01004205 | Z38: =SUM(B38,D38,F38,H38,J38,L38,N38,P38,R38,T38,V38,X38) -> 119755 | AA38: =IFERROR(AVERAGE(B38,D38,F38,H38,J38,L38,N38,P38,R38,T38,V38,X38),0) -> 9979.5833 | AB38: =IFERROR(AVERAGE(T38,V38,X38),0) -> 7730.3333 | AE38: =IFERROR(AVERAGE(R38:V38),0) -> 4242.8022 | AK38: =SUM(T38,V38,X38)*4 -> 92764 | AL38: =AK38/12 -> 7730.3333
A39: Total General and Admin Expenses | B39: =+'Combined Company'!B39-Ohio!B39 -> 23155 | C39: =B39/B$17 -> 0.009389738 | D39: =+'Combined Company'!D39-Ohio!D39 -> 43374 | E39: =D39/D$17 -> 0.031794342 | F39: =+'Combined Company'!F39-Ohio!F39 -> 42699 | G39: =F39/F$17 -> 0.026028516 | H39: =+'Combined Company'!H39-Ohio!H39 -> 23717 | I39: =H39/H$17 -> 0.016764176 | J39: =+'Combined Company'!J39-Ohio!J39 -> 29459 | K39: =J39/J$17 -> 0.02125055 | L39: =+'Combined Company'!L39-Ohio!L39 -> 33699 | M39: =L39/L$17 -> 0.020062905 | N39: =+'Combined Company'!N39-Ohio!N39 -> 16213 | O39: =N39/N$17 -> 0.011440648 | P39: =+'Combined Company'!P39-Ohio!P39 -> 26295 | Q39: =P39/P$17 -> 0.013596328 | R39: =+'Combined Company'!R39-Ohio!R39 -> 26964 | S39: =R39/R$17 -> 0.015519179 | T39: =+'Combined Company'!T39-Ohio!T39 -> 30708 | U39: =T39/T$17 -> 0.02605809 | V39: =+'Combined Company'!V39-Ohio!V39 -> 29254 | W39: =V39/V$17 -> 0.012648114 | X39: =+'Combined Company'!X39-Ohio!X39 -> 26640 | Y39: =X39/X$17 -> 0.02364297 | Z39: =SUM(B39,D39,F39,H39,J39,L39,N39,P39,R39,T39,V39,X39) -> 352177 | AA39: =IFERROR(AVERAGE(B39,D39,F39,H39,J39,L39,N39,P39,R39,T39,V39,X39),0) -> 29348.083 | AB39: =IFERROR(AVERAGE(T39,V39,X39),0) -> 28867.333 | AE39: =IFERROR(AVERAGE(R39:V39),0) -> 17385.208 | AK39: =SUM(T39,V39,X39)*4 -> 346408 | AL39: =AK39/12 -> 28867.333
A41: Marketing and Advertising Expenses | B41: =+'Combined Company'!B41-Ohio!B41 -> 430 | C41: =B41/B$17 -> 0.00017437216 | D41: =+'Combined Company'!D41-Ohio!D41 -> 5536 | E41: =D41/D$17 -> 0.0040580411 | F41: =+'Combined Company'!F41-Ohio!F41 -> 1796 | G41: =F41/F$17 -> 0.0010948082 | H41: =+'Combined Company'!H41-Ohio!H41 -> 4000 | I41: =H41/H$17 -> 0.0028273686 | J41: =+'Combined Company'!J41-Ohio!J41 -> 5344 | K41: =J41/J$17 -> 0.0038549489 | L41: =+'Combined Company'!L41-Ohio!L41 -> 4839 | M41: =L41/L$17 -> 0.0028809282 | N41: =+'Combined Company'!N41-Ohio!N41 -> 7191 | O41: =N41/N$17 -> 0.0050743046 | P41: =+'Combined Company'!P41-Ohio!P41 -> 7283 | Q41: =P41/P$17 -> 0.0037658133 | R41: =+'Combined Company'!R41-Ohio!R41 -> 8248 | S41: =R41/R$17 -> 0.0047471515 | T41: =+'Combined Company'!T41-Ohio!T41 -> 15252 | U41: =T41/T$17 -> 0.01294249 | V41: =+'Combined Company'!V41-Ohio!V41 -> 5099 | W41: =V41/V$17 -> 0.0022045783 | X41: =+'Combined Company'!X41-Ohio!X41 -> 5872 | Y41: =X41/X$17 -> 0.0052113934 | Z41: =SUM(B41,D41,F41,H41,J41,L41,N41,P41,R41,T41,V41,X41) -> 70890 | AA41: =IFERROR(AVERAGE(B41,D41,F41,H41,J41,L41,N41,P41,R41,T41,V41,X41),0) -> 5907.5 | AB41: =IFERROR(AVERAGE(T41,V41,X41),0) -> 8741 | AE41: =IFERROR(AVERAGE(R41:V41),0) -> 5719.8035 | AK41: =SUM(T41,V41,X41)*4 -> 104892 | AL41: =AK41/12 -> 8741
A43: Payroll and Related Expenses | B43: =+'Combined Company'!B43-Ohio!B43 -> 387670 | C43: =B43/B$17 -> 0.15720664 | D43: =+'Combined Company'!D43-Ohio!D43 -> 418242 | E43: =D43/D$17 -> 0.30658295 | F43: =+'Combined Company'!F43-Ohio!F43 -> 492116 | G43: =F43/F$17 -> 0.29998476 | H43: =+'Combined Company'!H43-Ohio!H43 -> 429313 | I43: =H43/H$17 -> 0.30345653 | J43: =+'Combined Company'!J43-Ohio!J43 -> 440762 | K43: =J43/J$17 -> 0.31794816 | L43: =+'Combined Company'!L43-Ohio!L43 -> 457081 | M43: =L43/L$17 -> 0.27212596 | N43: =+'Combined Company'!N43-Ohio!N43 -> 422197 | O43: =N43/N$17 -> 0.29792187 | P43: =+'Combined Company'!P43-Ohio!P43 -> 397127 | Q43: =P43/P$17 -> 0.20534205 | R43: =+'Combined Company'!R43-Ohio!R43 -> 430699 | S43: =R43/R$17 -> 0.2478896 | T43: =+'Combined Company'!T43-Ohio!T43 -> 394791 | U43: =T43/T$17 -> 0.3350104 | V43: =+'Combined Company'!V43-Ohio!V43 -> 418177 | W43: =V43/V$17 -> 0.18080093 | X43: =+'Combined Company'!X43-Ohio!X43 -> 0 | Y43: =X43/X$17 -> 0 | Z43: =SUM(B43,D43,F43,H43,J43,L43,N43,P43,R43,T43,V43,X43) -> 4688175 | AA43: =IFERROR(AVERAGE(B43,D43,F43,H43,J43,L43,N43,P43,R43,T43,V43,X43),0) -> 390681.25 | AB43: =IFERROR(AVERAGE(T43,V43,X43),0) -> 270989.33 | AE43: =IFERROR(AVERAGE(R43:V43),0) -> 248733.52 | AK43: =SUM(T43,V43,X43)*4 -> 3251872 | AL43: =AK43/12 -> 270989.33
A45: Utilities and Facilities | B45: =+'Combined Company'!B45-Ohio!B45 -> 25063 | C45: =B45/B$17 -> 0.010163464 | D45: =+'Combined Company'!D45-Ohio!D45 -> 24325 | E45: =D45/D$17 -> 0.017830898 | F45: =+'Combined Company'!F45-Ohio!F45 -> 23375 | G45: =F45/F$17 -> 0.014248965 | H45: =+'Combined Company'!H45-Ohio!H45 -> 22769 | I45: =H45/H$17 -> 0.016094089 | J45: =+'Combined Company'!J45-Ohio!J45 -> -11860 | K45: =J45/J$17 -> -0.0085553319 | L45: =+'Combined Company'!L45-Ohio!L45 -> 27819 | M45: =L45/L$17 -> 0.016562211 | N45: =+'Combined Company'!N45-Ohio!N45 -> 23402 | O45: =N45/N$17 -> 0.016513541 | P45: =+'Combined Company'!P45-Ohio!P45 -> 26423 | Q45: =P45/P$17 -> 0.013662513 | R45: =+'Combined Company'!R45-Ohio!R45 -> 29052 | S45: =R45/R$17 -> 0.016720932 | T45: =+'Combined Company'!T45-Ohio!T45 -> 27693 | U45: =T45/T$17 -> 0.023499632 | V45: =+'Combined Company'!V45-Ohio!V45 -> 6929 | W45: =V45/V$17 -> 0.002995788 | X45: =+'Combined Company'!X45-Ohio!X45 -> 0 | Y45: =X45/X$17 -> 0 | Z45: =SUM(B45,D45,F45,H45,J45,L45,N45,P45,R45,T45,V45,X45) -> 224990 | AA45: =IFERROR(AVERAGE(B45,D45,F45,H45,J45,L45,N45,P45,R45,T45,V45,X45),0) -> 18749.167 | AB45: =IFERROR(AVERAGE(T45,V45,X45),0) -> 11540.667 | AE45: =IFERROR(AVERAGE(R45:V45),0) -> 12734.808 | AK45: =SUM(T45,V45,X45)*4 -> 138488 | AL45: =AK45/12 -> 11540.667
A47: Ops and Maint. Expenses
A48: Automobile Expenses | B48: =+'Combined Company'!B48-Ohio!B48 -> 0 | C48: =B48/B$17 -> 0 | D48: =+'Combined Company'!D48-Ohio!D48 -> 0 | E48: =D48/D$17 -> 0 | F48: =+'Combined Company'!F48-Ohio!F48 -> 0 | G48: =F48/F$17 -> 0 | H48: =+'Combined Company'!H48-Ohio!H48 -> 6536 | I48: =H48/H$17 -> 0.0046199204 | J48: =+'Combined Company'!J48-Ohio!J48 -> -9102 | K48: =J48/J$17 -> -0.0065658205 | L48: =+'Combined Company'!L48-Ohio!L48 -> 0 | M48: =L48/L$17 -> 0 | N48: =+'Combined Company'!N48-Ohio!N48 -> 0 | O48: =N48/N$17 -> 0 | Q48: =P48/P$17 -> 0 | S48: =R48/R$17 -> 0 | U48: =T48/T$17 -> 0 | V48: =+'Combined Company'!V48-Ohio!V48 -> 7394 | W48: =V48/V$17 -> 0.0031968331 | X48: =+'Combined Company'!X48-Ohio!X48 -> 7995 | Y48: =X48/X$17 -> 0.0070955535 | Z48: =SUM(B48,D48,F48,H48,J48,L48,N48,P48,R48,T48,V48,X48) -> 12823 | AA48: =IFERROR(AVERAGE(B48,D48,F48,H48,J48,L48,N48,P48,R48,T48,V48,X48),0) -> 1424.7778 | AB48: =IFERROR(AVERAGE(T48,V48,X48),0) -> 7694.5 | AE48: =IFERROR(AVERAGE(R48:V48),0) -> 2464.6667 | AK48: =SUM(T48,V48,X48)*4 -> 61556 | AL48: =AK48/12 -> 5129.6667
A49: Professional Services | B49: =+'Combined Company'!B49-Ohio!B49 -> 0 | C49: =B49/B$17 -> 0 | D49: =+'Combined Company'!D49-Ohio!D49 -> 0 | E49: =D49/D$17 -> 0 | F49: =+'Combined Company'!F49-Ohio!F49 -> 0 | G49: =F49/F$17 -> 0 | H49: =+'Combined Company'!H49-Ohio!H49 -> 42711 | I49: =H49/H$17 -> 0.030189936 | J49: =+'Combined Company'!J49-Ohio!J49 -> 0 | K49: =J49/J$17 -> 0 | L49: =+'Combined Company'!L49-Ohio!L49 -> 0 | M49: =L49/L$17 -> 0 | N49: =+'Combined Company'!N49-Ohio!N49 -> 0 | O49: =N49/N$17 -> 0 | Q49: =P49/P$17 -> 0 | S49: =R49/R$17 -> 0 | U49: =T49/T$17 -> 0 | V49: =+'Combined Company'!V49-Ohio!V49 -> 38442 | W49: =V49/V$17 -> 0.016620592 | X49: =+'Combined Company'!X49-Ohio!X49 -> 20648 | Y49: =X49/X$17 -> 0.018325077 | Z49: =SUM(B49,D49,F49,H49,J49,L49,N49,P49,R49,T49,V49,X49) -> 101801 | AA49: =IFERROR(AVERAGE(B49,D49,F49,H49,J49,L49,N49,P49,R49,T49,V49,X49),0) -> 11311.222 | AB49: =IFERROR(AVERAGE(T49,V49,X49),0) -> 29545 | AE49: =IFERROR(AVERAGE(R49:V49),0) -> 12814 | AK49: =SUM(T49,V49,X49)*4 -> 236360 | AL49: =AK49/12 -> 19696.667
A50: Software and Maintenance | B50: =+'Combined Company'!B50-Ohio!B50 -> 0 | C50: =B50/B$17 -> 0 | D50: =+'Combined Company'!D50-Ohio!D50 -> 0 | E50: =D50/D$17 -> 0 | F50: =+'Combined Company'!F50-Ohio!F50 -> 0 | G50: =F50/F$17 -> 0 | H50: =+'Combined Company'!H50-Ohio!H50 -> 11132 | I50: =H50/H$17 -> 0.0078685669 | J50: =+'Combined Company'!J50-Ohio!J50 -> -2743 | K50: =J50/J$17 -> -0.001978691 | L50: =+'Combined Company'!L50-Ohio!L50 -> 0 | M50: =L50/L$17 -> 0 | N50: =+'Combined Company'!N50-Ohio!N50 -> 0 | O50: =N50/N$17 -> 0 | Q50: =P50/P$17 -> 0 | S50: =R50/R$17 -> 0 | U50: =T50/T$17 -> 0 | V50: =+'Combined Company'!V50-Ohio!V50 -> 24348 | W50: =V50/V$17 -> 0.01052698 | X50: =+'Combined Company'!X50-Ohio!X50 -> 20099 | Y50: =X50/X$17 -> 0.01783784 | Z50: =SUM(B50,D50,F50,H50,J50,L50,N50,P50,R50,T50,V50,X50) -> 52836 | AA50: =IFERROR(AVERAGE(B50,D50,F50,H50,J50,L50,N50,P50,R50,T50,V50,X50),0) -> 5870.6667 | AB50: =IFERROR(AVERAGE(T50,V50,X50),0) -> 22223.5 | AE50: =IFERROR(AVERAGE(R50:V50),0) -> 8116 | AK50: =SUM(T50,V50,X50)*4 -> 177788 | AL50: =AK50/12 -> 14815.667
A51: Other Operating Expense | B51: =+'Combined Company'!B51-Ohio!B51 -> 0 | C51: =B51/B$17 -> 0 | D51: =+'Combined Company'!D51-Ohio!D51 -> 0 | E51: =D51/D$17 -> 0 | F51: =+'Combined Company'!F51-Ohio!F51 -> 0 | G51: =F51/F$17 -> 0 | H51: =+'Combined Company'!H51-Ohio!H51 -> 0 | I51: =H51/H$17 -> 0 | J51: =+'Combined Company'!J51-Ohio!J51 -> 0 | K51: =J51/J$17 -> 0 | L51: =+'Combined Company'!L51-Ohio!L51 -> 0 | M51: =L51/L$17 -> 0 | N51: =+'Combined Company'!N51-Ohio!N51 -> 0 | O51: =N51/N$17 -> 0 | Q51: =P51/P$17 -> 0 | S51: =R51/R$17 -> 0 | U51: =T51/T$17 -> 0 | V51: =+'Combined Company'!V51-Ohio!V51 -> 0 | W51: =V51/V$17 -> 0 | X51: =+'Combined Company'!X51-Ohio!X51 -> 0 | Y51: =X51/X$17 -> 0 | Z51: =SUM(B51,D51,F51,H51,J51,L51,N51,P51,R51,T51,V51,X51) -> 0 | AA51: =IFERROR(AVERAGE(B51,D51,F51,H51,J51,L51,N51,P51,R51,T51,V51,X51),0) -> 0 | AB51: =IFERROR(AVERAGE(T51,V51,X51),0) -> 0 | AE51: =IFERROR(AVERAGE(R51:V51),0) -> 0 | AK51: =SUM(T51,V51,X51)*4 -> 0 | AL51: =AK51/12 -> 0
A52: Total Ops and Maint. Expenses | B52: =+'Combined Company'!B52-Ohio!B52 -> 36209 | C52: =B52/B$17 -> 0.014683352 | D52: =+'Combined Company'!D52-Ohio!D52 -> 57508 | E52: =D52/D$17 -> 0.042154955 | F52: =+'Combined Company'!F52-Ohio!F52 -> 36092 | G52: =F52/F$17 -> 0.022001012 | H52: =+'Combined Company'!H52-Ohio!H52 -> 60379 | I52: =H52/H$17 -> 0.042678423 | J52: =+'Combined Company'!J52-Ohio!J52 -> 23025 | K52: =J52/J$17 -> 0.016609319 | L52: =+'Combined Company'!L52-Ohio!L52 -> 27917 | M52: =L52/L$17 -> 0.016620556 | N52: =+'Combined Company'!N52-Ohio!N52 -> 47609 | O52: =N52/N$17 -> 0.033595128 | P52: =+'Combined Company'!P52-Ohio!P52 -> 49608 | Q52: =P52/P$17 -> 0.025650757 | R52: =+'Combined Company'!R52-Ohio!R52 -> 45781 | S52: =R52/R$17 -> 0.026349338 | T52: =+'Combined Company'!T52-Ohio!T52 -> 61048 | U52: =T52/T$17 -> 0.051803904 | V52: =+'Combined Company'!V52-Ohio!V52 -> 70184 | W52: =V52/V$17 -> 0.030344405 | X52: =+'Combined Company'!X52-Ohio!X52 -> 48743 | Y52: =X52/X$17 -> 0.043259357 | Z52: =SUM(B52,D52,F52,H52,J52,L52,N52,P52,R52,T52,V52,X52) -> 564103 | AA52: =IFERROR(AVERAGE(B52,D52,F52,H52,J52,L52,N52,P52,R52,T52,V52,X52),0) -> 47008.583 | AB52: =IFERROR(AVERAGE(T52,V52,X52),0) -> 59991.667 | AE52: =IFERROR(AVERAGE(R52:V52),0) -> 35402.616 | AK52: =SUM(T52,V52,X52)*4 -> 719900 | AL52: =AK52/12 -> 59991.667
A54: Taxes and Insurance
A55: Insurance | B55: =+'Combined Company'!B55-Ohio!B55 -> 0 | C55: =B55/B$17 -> 0 | D55: =+'Combined Company'!D55-Ohio!D55 -> 0 | E55: =D55/D$17 -> 0 | F55: =+'Combined Company'!F55-Ohio!F55 -> 0 | G55: =F55/F$17 -> 0 | H55: =+'Combined Company'!H55-Ohio!H55 -> 2410 | I55: =H55/H$17 -> 0.0017034896 | J55: =+'Combined Company'!J55-Ohio!J55 -> 5825 | K55: =J55/J$17 -> 0.0042019231 | L55: =+'Combined Company'!L55-Ohio!L55 -> 3718 | M55: =L55/L$17 -> 0.002213534 | N55: =+'Combined Company'!N55-Ohio!N55 -> 5229 | O55: =N55/N$17 -> 0.003689826 | P55: =+'Combined Company'!P55-Ohio!P55 -> 6014 | Q55: =P55/P$17 -> 0.0031096527 | R55: =+'Combined Company'!R55-Ohio!R55 -> 9612 | S55: =R55/R$17 -> 0.0055322041 | T55: =+'Combined Company'!T55-Ohio!T55 -> 4740 | U55: =T55/T$17 -> 0.0040222531 | V55: =+'Combined Company'!V55-Ohio!V55 -> 2750 | W55: =V55/V$17 -> 0.0011889763 | X55: =+'Combined Company'!X55-Ohio!X55 -> 3972 | Y55: =X55/X$17 -> 0.0035251455 | Z55: =SUM(B55,D55,F55,H55,J55,L55,N55,P55,R55,T55,V55,X55) -> 44270 | AA55: =IFERROR(AVERAGE(B55,D55,F55,H55,J55,L55,N55,P55,R55,T55,V55,X55),0) -> 3689.1667 | AB55: =IFERROR(AVERAGE(T55,V55,X55),0) -> 3820.6667 | AE55: =IFERROR(AVERAGE(R55:V55),0) -> 3420.4019 | AK55: =SUM(T55,V55,X55)*4 -> 45848 | AL55: =AK55/12 -> 3820.6667
A56: Taxes | B56: =+'Combined Company'!B56-Ohio!B56 -> 0 | D56: =+'Combined Company'!D56-Ohio!D56 -> 0 | F56: =+'Combined Company'!F56-Ohio!F56 -> 0 | H56: =+'Combined Company'!H56-Ohio!H56 -> 0 | J56: =+'Combined Company'!J56-Ohio!J56 -> 0 | L56: =+'Combined Company'!L56-Ohio!L56 -> 0 | N56: =+'Combined Company'!N56-Ohio!N56 -> 6442 | P56: =+'Combined Company'!P56-Ohio!P56 -> 0 | R56: =+'Combined Company'!R56-Ohio!R56 -> 0 | T56: =+'Combined Company'!T56-Ohio!T56 -> 0 | V56: =+'Combined Company'!V56-Ohio!V56 -> 2 | X56: =+'Combined Company'!X56-Ohio!X56 -> 0 | Z56: =SUM(B56,D56,F56,H56,J56,L56,N56,P56,R56,T56,V56,X56) -> 6444 | AA56: =IFERROR(AVERAGE(B56,D56,F56,H56,J56,L56,N56,P56,R56,T56,V56,X56),0) -> 537 | AB56: =IFERROR(AVERAGE(T56,V56,X56),0) -> 0.66666667 | AE56: =IFERROR(AVERAGE(R56:V56),0) -> 0.66666667 | AK56: =SUM(T56,V56,X56)*4 -> 8 | AL56: =AK56/12 -> 0.66666667
A57: Total Taxes and Insurance | B57: =+'Combined Company'!B57-Ohio!B57 -> 25477 | C57: =B57/B$17 -> 0.010331348 | D57: =+'Combined Company'!D57-Ohio!D57 -> 8387 | E57: =D57/D$17 -> 0.006147903 | F57: =+'Combined Company'!F57-Ohio!F57 -> 17203 | G57: =F57/F$17 -> 0.010486629 | H57: =+'Combined Company'!H57-Ohio!H57 -> 2410 | I57: =H57/H$17 -> 0.0017034896 | J57: =+'Combined Company'!J57-Ohio!J57 -> 5825 | K57: =J57/J$17 -> 0.0042019231 | L57: =+'Combined Company'!L57-Ohio!L57 -> 718 | M57: =L57/L$17 -> 0.00042746568 | N57: =+'Combined Company'!N57-Ohio!N57 -> 11671 | O57: =N57/N$17 -> 0.0082356013 | P57: =+'Combined Company'!P57-Ohio!P57 -> 6014 | Q57: =P57/P$17 -> 0.0031096527 | R57: =+'Combined Company'!R57-Ohio!R57 -> 9612 | S57: =R57/R$17 -> 0.0055322041 | T57: =+'Combined Company'!T57-Ohio!T57 -> 4740 | U57: =T57/T$17 -> 0.0040222531 | V57: =+'Combined Company'!V57-Ohio!V57 -> 4398 | W57: =V57/V$17 -> 0.0019014974 | X57: =+'Combined Company'!X57-Ohio!X57 -> 3972 | Y57: =X57/X$17 -> 0.0035251455 | Z57: =SUM(B57,D57,F57,H57,J57,L57,N57,P57,R57,T57,V57,X57) -> 100427 | AA57: =IFERROR(AVERAGE(B57,D57,F57,H57,J57,L57,N57,P57,R57,T57,V57,X57),0) -> 8368.9167 | AB57: =IFERROR(AVERAGE(T57,V57,X57),0) -> 4370 | AE57: =IFERROR(AVERAGE(R57:V57),0) -> 3750.0019 | AK57: =SUM(T57,V57,X57)*4 -> 52440 | AL57: =AK57/12 -> 4370
A58: Total Operating Expenses | B58: =+'Combined Company'!B58-Ohio!B58 -> 498004 | C58: =B58/B$17 -> 0.20194891 | D58: =+'Combined Company'!D58-Ohio!D58 -> 557372 | E58: =D58/D$17 -> 0.40856909 | F58: =+'Combined Company'!F58-Ohio!F58 -> 613281 | G58: =F58/F$17 -> 0.37384469 | H58: =+'Combined Company'!H58-Ohio!H58 -> 542588 | I58: =H58/H$17 -> 0.38352407 | J58: =+'Combined Company'!J58-Ohio!J58 -> 549101 | K58: =J58/J$17 -> 0.39609961 | L58: =+'Combined Company'!L58-Ohio!L58 -> 551524 | M58: =L58/L$17 -> 0.32835318 | N58: =+'Combined Company'!N58-Ohio!N58 -> 521767 | O58: =N58/N$17 -> 0.3681831 | P58: =+'Combined Company'!P58-Ohio!P58 -> 512749 | Q58: =P58/P$17 -> 0.26512659 | R58: =+'Combined Company'!R58-Ohio!R58 -> 520356 | S58: =R58/R$17 -> 0.29949185 | T58: =+'Combined Company'!T58-Ohio!T58 -> 534232 | U58: =T58/T$17 -> 0.45333677 | V58: =+'Combined Company'!V58-Ohio!V58 -> 548067 | W58: =V58/V$17 -> 0.23695952 | X58: =+'Combined Company'!X58-Ohio!X58 -> 641555 | Y58: =X58/X$17 -> 0.56937934 | Z58: =SUM(B58,D58,F58,H58,J58,L58,N58,P58,R58,T58,V58,X58) -> 6590596 | AA58: =IFERROR(AVERAGE(B58,D58,F58,H58,J58,L58,N58,P58,R58,T58,V58,X58),0) -> 549216.33 | AB58: =IFERROR(AVERAGE(T58,V58,X58),0) -> 574618 | AE58: =IFERROR(AVERAGE(R58:V58),0) -> 320531.15 | AK58: =SUM(T58,V58,X58)*4 -> 6895416 | AL58: =AK58/12 -> 574618
Z59: =SUM(F59,H59,J59,L59,N59,P59,R59,T59,V59,X59) -> 0 | AA59: =IFERROR(AVERAGE(F59,H59,J59,L59,N59,P59,R59,T59,V59,X59),0) -> 0 | AB59: =IFERROR(AVERAGE(T59,V59,X59),0) -> 0
A60: Net Operating Income | B60: =+'Combined Company'!B60-Ohio!B60 -> 567114 | C60: =B60/B$17 -> 0.22997417 | D60: =+'Combined Company'!D60-Ohio!D60 -> 321975 | E60: =D60/D$17 -> 0.23601658 | F60: =+'Combined Company'!F60-Ohio!F60 -> 376086 | G60: =F60/F$17 -> 0.22925503 | H60: =+'Combined Company'!H60-Ohio!H60 -> 304585 | I60: =H60/H$17 -> 0.21529352 | J60: =+'Combined Company'!J60-Ohio!J60 -> 372423 | K60: =J60/J$17 -> 0.26865113 | L60: =+'Combined Company'!L60-Ohio!L60 -> 352216 | M60: =L60/L$17 -> 0.20969395 | N60: =+'Combined Company'!N60-Ohio!N60 -> 389175 | O60: =N60/N$17 -> 0.27462001 | P60: =+'Combined Company'!P60-Ohio!P60 -> 369326 | Q60: =P60/P$17 -> 0.19096701 | R60: =+'Combined Company'!R60-Ohio!R60 -> 270789 | S60: =R60/R$17 -> 0.1558531 | T60: =+'Combined Company'!T60-Ohio!T60 -> 119224 | U60: =T60/T$17 -> 0.1011707 | V60: =+'Combined Company'!V60-Ohio!V60 -> 314833 | W60: =V60/V$17 -> 0.13611963 | X60: =+'Combined Company'!X60-Ohio!X60 -> -131070 | Y60: =X60/X$17 -> -0.11632448 | Z60: =SUM(B60,D60,F60,H60,J60,L60,N60,P60,R60,T60,V60,X60) -> 3626676 | AA60: =IFERROR(AVERAGE(B60,D60,F60,H60,J60,L60,N60,P60,R60,T60,V60,X60),0) -> 302223 | AB60: =IFERROR(AVERAGE(T60,V60,X60),0) -> 100995.67 | AE60: =IFERROR(AVERAGE(R60:V60),0) -> 140969.25 | AK60: =SUM(T60,V60,X60)*4 -> 1211948 | AL60: =AK60/12 -> 100995.67
A61: Net Operating Income % | B61: 0.13475409 | C61: =C60/C17 -> 0.22997417 | D61: 0.13475409 | E61: =E60/E17 -> 0.23601658 | F61: 0.13475409 | G61: =G60/G17 -> 0.22925503 | H61: 0.13475409 | I61: =I60/I17 -> 0.21529352 | J61: 0.13475409 | K61: =K60/K17 -> 0.26865113 | L61: 0.13475409 | M61: =M60/M17 -> 0.20969395 | N61: 0.13475409 | O61: =O60/O17 -> 0.27462001 | P61: 0.13475409 | Q61: =Q60/Q17 -> 0.19096701 | R61: 0.13475409 | S61: =S60/S17 -> 0.1558531 | T61: 0.13475409 | U61: =U60/U17 -> 0.1011707 | V61: 0.13475409 | W61: =W60/W17 -> 0.13611963 | X61: 0.13475409 | Y61: =Y60/Y17 -> -0.11632448 | Z61: =Z60/Z17 -> 0.18448812 | AA61: =IFERROR(AVERAGE(F61,H61,J61,L61,N61,P61,R61,T61,V61,X61),0) -> 0.13475409 | AB61: =AVERAGE(T61,V61,X61) -> 0.13475409
A63: Other Income (Expense)
A64: Other Income
A65: Interest Income | B65: =+'Combined Company'!B65-Ohio!B65 -> 0 | D65: 0 | F65: 0 | H65: 0 | J65: 0 | L65: 0 | N65: 0 | R65: =+'Combined Company'!R65-Ohio!R65 -> 0 | T65: =+'Combined Company'!T65-Ohio!T65 -> 0 | V65: =+'Combined Company'!V65-Ohio!V65 -> 0 | X65: =+'Combined Company'!X65-Ohio!X65 -> 468 | Z65: =SUM(B65,D65,F65,H65,J65,L65,N65,P65,R65,T65,V65,X65) -> 468 | AA65: =IFERROR(AVERAGE(B65,D65,F65,H65,J65,L65,N65,P65,R65,T65,V65,X65),0) -> 42.545455 | AB65: =IFERROR(AVERAGE(T65,V65,X65),0) -> 156 | AE65: =IFERROR(AVERAGE(R65:V65),0) -> 0 | AK65: =SUM(T65,V65,X65)*4 -> 1872 | AL65: =AK65/12 -> 156
A66: Other Income | B66: =+'Combined Company'!B66-Ohio!B66 -> 0 | C66: =B66/B$17 -> 0 | D66: 57624 | E66: =D66/D$17 -> 0.042239986 | F66: 0 | G66: =F66/F$17 -> 0 | H66: 20 | I66: =H66/H$17 -> 1.4136843e-05 | J66: 0 | K66: =J66/J$17 -> 0 | L66: 0 | M66: =L66/L$17 -> 0 | N66: 504 | O66: =N66/N$17 -> 0.00035564588 | Q66: =P66/P$17 -> 0 | R66: =+'Combined Company'!R66-Ohio!R66 -> 1433 | S66: =R66/R$17 -> 0.00082476576 | T66: =+'Combined Company'!T66-Ohio!T66 -> 0 | U66: =T66/T$17 -> 0 | V66: =+'Combined Company'!V66-Ohio!V66 -> 0 | W66: =V66/V$17 -> 0 | X66: =+'Combined Company'!X66-Ohio!X66 -> 454000 | Y66: =X66/X$17 -> 0.40292449 | Z66: =SUM(B66,D66,F66,H66,J66,L66,N66,P66,R66,T66,V66,X66) -> 513581 | AA66: =IFERROR(AVERAGE(B66,D66,F66,H66,J66,L66,N66,P66,R66,T66,V66,X66),0) -> 46689.182 | AB66: =IFERROR(AVERAGE(T66,V66,X66),0) -> 151333.33 | AE66: =IFERROR(AVERAGE(R66:V66),0) -> 286.60016 | AK66: =SUM(T66,V66,X66)*4 -> 1816000 | AL66: =AK66/12 -> 151333.33
A67: Total Other Income | B67: =+'Combined Company'!B67-Ohio!B67 -> 0 | C67: =B67/B$17 -> 0 | D67: 57624 | E67: =D67/D$17 -> 0.042239986 | F67: 0 | G67: =F67/F$17 -> 0 | H67: 20 | I67: =H67/H$17 -> 1.4136843e-05 | J67: 0 | K67: =J67/J$17 -> 0 | L67: 0 | M67: =L67/L$17 -> 0 | N67: 504 | O67: =N67/N$17 -> 0.00035564588 | Q67: =P67/P$17 -> 0 | R67: =+'Combined Company'!R67-Ohio!R67 -> 1433 | S67: =R67/R$17 -> 0.00082476576 | T67: =+'Combined Company'!T67-Ohio!T67 -> 0 | U67: =T67/T$17 -> 0 | V67: =+'Combined Company'!V67-Ohio!V67 -> 916 | W67: =V67/V$17 -> 0.00039603721 | X67: =+'Combined Company'!X67-Ohio!X67 -> 454468 | Y67: =X67/X$17 -> 0.40333984 | Z67: =SUM(B67,D67,F67,H67,J67,L67,N67,P67,R67,T67,V67,X67) -> 514965 | AA67: =IFERROR(AVERAGE(B67,D67,F67,H67,J67,L67,N67,P67,R67,T67,V67,X67),0) -> 46815 | AB67: =IFERROR(AVERAGE(T67,V67,X67),0) -> 151794.67 | AE67: =IFERROR(AVERAGE(R67:V67),0) -> 469.80016 | AK67: =SUM(T67,V67,X67)*4 -> 1821536 | AL67: =AK67/12 -> 151794.67
AK68: =SUM(T68,V68,X68)*4 -> 0
A69: Other Expense | AK69: =SUM(T69,V69,X69)*4 -> 0 | AL69: =AK69/12 -> 0
A70: Interest Expenses | B70: =+'Combined Company'!B70-Ohio!B70 -> -1467 | C70: =B70/B$17 -> -0.00059489292 | D70: -9919 | E70: =D70/D$17 -> -0.0072709014 | F70: -28403 | G70: =F70/F$17 -> -0.017313941 | H70: -2758 | I70: =H70/H$17 -> -0.0019494707 | J70: -10982 | K70: =J70/J$17 -> -0.0079219777 | L70: -11178 | M70: =L70/L$17 -> -0.0066548905 | N70: -11489 | O70: =N70/N$17 -> -0.0081071736 | P70: -11541 | Q70: =P70/P$17 -> -0.0059674929 | R70: =+'Combined Company'!R70-Ohio!R70 -> -1704 | S70: =R70/R$17 -> -0.00098074031 | T70: =+'Combined Company'!T70-Ohio!T70 -> -789 | U70: =T70/T$17 -> -0.00066952694 | V70: =+'Combined Company'!V70-Ohio!V70 -> -1432 | W70: =V70/V$17 -> -0.0006191324 | X70: =+'Combined Company'!X70-Ohio!X70 -> -4216 | Y70: =X70/X$17 -> -0.0037416952 | Z70: =SUM(B70,D70,F70,H70,J70,L70,N70,P70,R70,T70,V70,X70) -> -95878 | AA70: =IFERROR(AVERAGE(B70,D70,F70,H70,J70,L70,N70,P70,R70,T70,V70,X70),0) -> -7989.8333 | AB70: =IFERROR(AVERAGE(T70,V70,X70),0) -> -2145.6667 | AE70: =IFERROR(AVERAGE(R70:V70),0) -> -785.00033 | AK70: =SUM(T70,V70,X70)*4 -> -25748 | AL70: =AK70/12 -> -2145.6667
A71: Partnership Expenses | B71: =+'Combined Company'!B71-Ohio!B71 -> -9822 | C71: =B71/B$17 -> -0.0039829845 | D71: -18678 | E71: =D71/D$17 -> -0.013691491 | F71: -21179 | G71: =F71/F$17 -> -0.012910324 | H71: -19616 | I71: =H71/H$17 -> -0.013865416 | J71: -9917 | K71: =J71/J$17 -> -0.0071537291 | L71: -17067 | M71: =L71/L$17 -> -0.010160943 | N71: -18300 | O71: =N71/N$17 -> -0.012913332 | P71: -14252 | Q71: =P71/P$17 -> -0.0073692669 | R71: =+'Combined Company'!R71-Ohio!R71 -> -14497 | S71: =R71/R$17 -> -0.0083437748 | T71: =+'Combined Company'!T71-Ohio!T71 -> -16176 | U71: =T71/T$17 -> -0.013726575 | V71: =+'Combined Company'!V71-Ohio!V71 -> -22239 | W71: =V71/V$17 -> -0.0096151435 | X71: =+'Combined Company'!X71-Ohio!X71 -> -33345 | Y71: =X71/X$17 -> -0.02959365 | Z71: =SUM(B71,D71,F71,H71,J71,L71,N71,P71,R71,T71,V71,X71) -> -215088 | AA71: =IFERROR(AVERAGE(B71,D71,F71,H71,J71,L71,N71,P71,R71,T71,V71,X71),0) -> -17924 | AB71: =IFERROR(AVERAGE(T71,V71,X71),0) -> -23920 | AE71: =IFERROR(AVERAGE(R71:V71),0) -> -10582.404 | AK71: =SUM(T71,V71,X71)*4 -> -287040 | AL71: =AK71/12 -> -23920
A72: Other Expenses | B72: =+'Combined Company'!B72-Ohio!B72 -> -1 | C72: =B72/B$17 -> -4.0551665e-07 | D72: 0 | E72: =D72/D$17 -> 0 | F72: 0 | G72: =F72/F$17 -> 0 | H72: -12 | I72: =H72/H$17 -> -8.4821059e-06 | J72: -2 | K72: =J72/J$17 -> -1.4427204e-06 | L72: 0 | M72: =L72/L$17 -> 0 | N72: 0 | O72: =N72/N$17 -> 0 | P72: 0 | Q72: =P72/P$17 -> 0 | R72: =+'Combined Company'!R72-Ohio!R72 -> 0 | S72: =R72/R$17 -> 0 | T72: =+'Combined Company'!T72-Ohio!T72 -> 0 | U72: =T72/T$17 -> 0 | V72: =+'Combined Company'!V72-Ohio!V72 -> 0 | W72: =V72/V$17 -> 0 | X72: =+'Combined Company'!X72-Ohio!X72 -> 0 | Y72: =X72/X$17 -> 0 | Z72: =SUM(B72,D72,F72,H72,J72,L72,N72,P72,R72,T72,V72,X72) -> -15 | AA72: =IFERROR(AVERAGE(B72,D72,F72,H72,J72,L72,N72,P72,R72,T72,V72,X72),0) -> -1.25 | AB72: =IFERROR(AVERAGE(T72,V72,X72),0) -> 0 | AE72: =IFERROR(AVERAGE(R72:V72),0) -> 0 | AK72: =SUM(T72,V72,X72)*4 -> 0 | AL72: =AK72/12 -> 0
A73: Total Other Expense | B73: =+'Combined Company'!B73-Ohio!B73 -> -20805 | C73: =B73/B$17 -> -0.0084367739 | D73: 29027 | E73: =D73/D$17 -> 0.021277594 | F73: -49582 | G73: =F73/F$17 -> -0.030224265 | H73: -22366 | I73: =H73/H$17 -> -0.015809232 | J73: -20901 | K73: =J73/J$17 -> -0.015077149 | L73: -28245 | M73: =L73/L$17 -> -0.016815833 | N73: -29285 | O73: =N73/N$17 -> -0.02066486 | P73: -25793 | Q73: =P73/P$17 -> -0.01333676 | R73: =+'Combined Company'!R73-Ohio!R73 -> -25642 | S73: =R73/R$17 -> -0.0147583 | T73: =+'Combined Company'!T73-Ohio!T73 -> -26506 | U73: =T73/T$17 -> -0.022492371 | V73: =+'Combined Company'!V73-Ohio!V73 -> -33416 | W73: =V73/V$17 -> -0.014447576 | X73: =+'Combined Company'!X73-Ohio!X73 -> -44423 | Y73: =X73/X$17 -> -0.039425362 | Z73: =SUM(B73,D73,F73,H73,J73,L73,N73,P73,R73,T73,V73,X73) -> -297937 | AA73: =IFERROR(AVERAGE(B73,D73,F73,H73,J73,L73,N73,P73,R73,T73,V73,X73),0) -> -24828.083 | AB73: =IFERROR(AVERAGE(T73,V73,X73),0) -> -34781.667 | AE73: =IFERROR(AVERAGE(R73:V73),0) -> -17112.807 | AK73: =SUM(T73,V73,X73)*4 -> -417380 | AL73: =AK73/12 -> -34781.667
A74: Total Other Income (Expense) | B74: =+'Combined Company'!B74-Ohio!B74 -> -11290 | C74: =B74/B$17 -> -0.004578283 | D74: 29027 | E74: =D74/D$17 -> 0.021277594 | F74: -49582 | G74: =F74/F$17 -> -0.030224265 | H74: -22366 | I74: =H74/H$17 -> -0.015809232 | J74: -20901 | K74: =J74/J$17 -> -0.015077149 | L74: -28245 | M74: =L74/L$17 -> -0.016815833 | N74: -29285 | O74: =N74/N$17 -> -0.02066486 | P74: -25793 | Q74: =P74/P$17 -> -0.01333676 | R74: =+'Combined Company'!R74-Ohio!R74 -> -14768 | S74: =R74/R$17 -> -0.0084997493 | T74: =+'Combined Company'!T74-Ohio!T74 -> -16965 | U74: =T74/T$17 -> -0.014396102 | V74: =+'Combined Company'!V74-Ohio!V74 -> -22775 | W74: =V74/V$17 -> -0.0098468858 | X74: =+'Combined Company'!X74-Ohio!X74 -> 415459 | Y74: =X74/X$17 -> 0.36871939 | Z74: =SUM(B74,D74,F74,H74,J74,L74,N74,P74,R74,T74,V74,X74) -> 202516 | AA74: =IFERROR(AVERAGE(B74,D74,F74,H74,J74,L74,N74,P74,R74,T74,V74,X74),0) -> 16876.333 | AB74: =IFERROR(AVERAGE(T74,V74,X74),0) -> 125239.67 | AE74: =IFERROR(AVERAGE(R74:V74),0) -> -10901.605 | AK74: =SUM(T74,V74,X74)*4 -> 1502876 | AL74: =AK74/12 -> 125239.67
A76: Income Taxes
A77: State and Local Taxes | B77: =+'Combined Company'!B77-Ohio!B77 -> 7548 | C77: =B77/B$17 -> 0.0030608397 | D77: 2641 | E77: =D77/D$17 -> 0.0019359261 | F77: 7548 | G77: =F77/F$17 -> 0.0046011204 | H77: 1516 | I77: =H77/H$17 -> 0.0010715727 | J77: 0 | K77: =J77/J$17 -> 0 | L77: 94 | M77: =L77/L$17 -> 5.5963474e-05 | N77: 441 | O77: =N77/N$17 -> 0.00031119014 | Q77: =P77/P$17 -> 0 | R77: =+'Combined Company'!R77-Ohio!R77 -> 6689 | S77: =R77/R$17 -> 0.0038498662 | T77: =+'Combined Company'!T77-Ohio!T77 -> 0 | U77: =T77/T$17 -> 0 | V77: =+'Combined Company'!V77-Ohio!V77 -> 0 | W77: =V77/V$17 -> 0 | X77: =+'Combined Company'!X77-Ohio!X77 -> 0 | Y77: =X77/X$17 -> 0 | Z77: =SUM(B77,D77,F77,H77,J77,L77,N77,P77,R77,T77,V77,X77) -> 26477 | AA77: =IFERROR(AVERAGE(B77,D77,F77,H77,J77,L77,N77,P77,R77,T77,V77,X77),0) -> 2407 | AB77: =IFERROR(AVERAGE(T77,V77,X77),0) -> 0 | AE77: =IFERROR(AVERAGE(R77:V77),0) -> 1337.8008 | AK77: =SUM(T77,V77,X77)*4 -> 0 | AL77: =AK77/12 -> 0
A78: Total Income Taxes | B78: =+'Combined Company'!B78-Ohio!B78 -> 7548 | C78: =B78/B$17 -> 0.0030608397 | D78: 2641 | E78: =D78/D$17 -> 0.0019359261 | F78: 7548 | G78: =F78/F$17 -> 0.0046011204 | H78: 1516 | I78: =H78/H$17 -> 0.0010715727 | J78: 0 | K78: =J78/J$17 -> 0 | L78: 94 | M78: =L78/L$17 -> 5.5963474e-05 | N78: 441 | O78: =N78/N$17 -> 0.00031119014 | P78: 3419 | Q78: =P78/P$17 -> 0.0017678588 | R78: =+'Combined Company'!R78-Ohio!R78 -> 6689 | S78: =R78/R$17 -> 0.0038498662 | T78: =+'Combined Company'!T78-Ohio!T78 -> 0 | U78: =T78/T$17 -> 0 | V78: =+'Combined Company'!V78-Ohio!V78 -> 0 | W78: =V78/V$17 -> 0 | X78: =+'Combined Company'!X78-Ohio!X78 -> 0 | Y78: =X78/X$17 -> 0 | Z78: =SUM(B78,D78,F78,H78,J78,L78,N78,P78,R78,T78,V78,X78) -> 29896 | AA78: =IFERROR(AVERAGE(B78,D78,F78,H78,J78,L78,N78,P78,R78,T78,V78,X78),0) -> 2491.3333 | AB78: =IFERROR(AVERAGE(T78,V78,X78),0) -> 0 | AE78: =IFERROR(AVERAGE(R78:V78),0) -> 1337.8008 | AK78: =SUM(T78,V78,X78)*4 -> 0 | AL78: =AK78/12 -> 0
R79: =+'Combined Company'!R79-Ohio!R79 -> 0 | T79: =+'Combined Company'!T79-Ohio!T79 -> 0 | V79: =+'Combined Company'!V79-Ohio!V79 -> 0 | X79: =+'Combined Company'!X79-Ohio!X79 -> 0 | AA79: =IFERROR(AVERAGE(F79,H79,J79,L79,N79,P79,R79,T79,V79,X79),0) -> 0 | AB79: =IFERROR(AVERAGE(T79,V79,X79),0) -> 0
A80: Net Income (Loss) | B80: =+'Combined Company'!B80-Ohio!B80 -> 518723 | C80: =B80/B$17 -> 0.21035081 | D80: 164095 | E80: =D80/D$17 -> 0.12028617 | F80: 70493 | G80: =F80/F$17 -> 0.042971222 | H80: 163431 | I80: =H80/H$17 -> 0.11551992 | J80: 563447 | K80: =J80/J$17 -> 0.40644824 | L80: 400263 | M80: =L80/L$17 -> 0.23829902 | N80: 310591 | O80: =N80/N$17 -> 0.21916748 | P80: 314474 | Q80: =P80/P$17 -> 0.16260475 | R80: =+'Combined Company'!R80-Ohio!R80 -> 249332 | S80: =R80/R$17 -> 0.14350349 | T80: =+'Combined Company'!T80-Ohio!T80 -> 102259 | U80: =T80/T$17 -> 0.086774594 | V80: =+'Combined Company'!V80-Ohio!V80 -> 292058 | W80: =V80/V$17 -> 0.12627275 | X80: =+'Combined Company'!X80-Ohio!X80 -> 284389 | Y80: =X80/X$17 -> 0.25239492 | Z80: =SUM(B80,D80,F80,H80,J80,L80,N80,P80,R80,T80,V80,X80) -> 3433555 | AA80: =IFERROR(AVERAGE(B80,D80,F80,H80,J80,L80,N80,P80,R80,T80,V80,X80),0) -> 286129.58 | AB80: =IFERROR(AVERAGE(T80,V80,X80),0) -> 226235.33 | AE80: =IFERROR(AVERAGE(R80:V80),0) -> 128729.85 | AK80: =SUM(T80,V80,X80)*4 -> 2714824 | AL80: =AK80/12 -> 226235.33
A81: Net Profit % | B81: 0.099004239 | C81: =C80/C17 -> 0.21035081 | D81: 0.099256251 | E81: =E80/E17 -> 0.12028617 | F81: 0.057803179 | G81: =G80/G17 -> 0.042971222 | H81: 0.088640687 | I81: =I80/I17 -> 0.11551992 | J81: 0.20466617 | K81: =K80/K17 -> 0.40644824 | L81: 0.19710942 | M81: =M80/M17 -> 0.23829902 | N81: 0.15282155 | O81: =O80/O17 -> 0.21916748 | P81: 0.15695346 | Q81: =Q80/Q17 -> 0.16260475 | R81: =R80/R17 -> 0.14350349 | S81: =S80/S17 -> 0.14350349 | T81: =T80/T17 -> 0.086774594 | U81: =U80/U17 -> 0.086774594 | V81: =V80/V17 -> 0.12627275 | W81: =W80/W17 -> 0.12627275 | X81: =X80/X17 -> 0.25239492 | ... Z81: =Z80/Z17 -> 0.1746641 | AA81: =IFERROR(AVERAGE(F81,H81,J81,L81,N81,P81,R81,T81,V81,X81),0) -> 0.14669402 | AB81: =AVERAGE(T81,V81,X81) -> 0.15514742
A87: Gross Profit % | B87: 0.58670021 | C87: 0.58670021 | D87: 0.50251445 | E87: 0.50251445 | F87: 0.66234589 | G87: 0.66234589 | H87: 0.50223594 | I87: 0.50223594 | J87: 0.4576748 | K87: 0.4576748 | L87: 0.58059728 | M87: 0.58059728 | N87: 0.59096614 | O87: 0.59096614 | P87: 0.54319073 | Q87: 0.54319073 | R87: =R29/R17 -> 0.45534495 | S87: =S29/S17 -> 0.45534495 | T87: =T29/T17 -> 0.55450747 | U87: =U29/U17 -> 0.55450747 | V87: =V29/V17 -> 0.37307915 | W87: =W29/W17 -> 0.37307915 | X87: =X29/X17 -> 0.45305486 | Y87: =Y29/Y17 -> 0.45305486 | Z87: =Z29/Z17 -> 0.42083567 | AA87: =IFERROR(AVERAGE(F87,H87,J87,L87,N87,P87,R87,T87,V87,X87),0) -> 0.51729972 | AB87: =AVERAGE(T87,V87,X87) -> 0.46021383
A88: Net Operating Income % | B88: 0.13475409 | C88: 0.13475409 | D88: 0.083296134 | E88: 0.083296134 | F88: 0.1046489 | G88: 0.1046489 | H88: 0.10159366 | I88: 0.10159366 | J88: 0.21225824 | K88: 0.21225824 | L88: 0.21106495 | M88: 0.21106495 | N88: 0.16744777 | O88: 0.16744777 | P88: 0.17153313 | Q88: 0.17153313 | R88: =R60/R17 -> 0.1558531 | S88: =S60/S17 -> 0.1558531 | T88: =T60/T17 -> 0.1011707 | U88: =U60/U17 -> 0.1011707 | V88: =V60/V17 -> 0.13611963 | W88: =W60/W17 -> 0.13611963 | X88: =X60/X17 -> -0.11632448 | Y88: =Y60/Y17 -> -0.11632448 | Z88: =Z60/Z17 -> 0.18448812 | AA88: =IFERROR(AVERAGE(F88,H88,J88,L88,N88,P88,R88,T88,V88,X88),0) -> 0.12453656 | AB88: =AVERAGE(T88,V88,X88) -> 0.04032195
A89: Net Profit % | B89: 0.099004239 | C89: 0.099004239 | D89: 0.099256251 | E89: 0.099256251 | F89: 0.057803179 | G89: 0.057803179 | H89: 0.088640687 | I89: 0.088640687 | J89: 0.20466617 | K89: 0.20466617 | L89: 0.19710942 | M89: 0.19710942 | N89: 0.15282155 | O89: 0.15282155 | P89: 0.15695346 | Q89: 0.15695346 | R89: =R80/R17 -> 0.14350349 | S89: =S80/S17 -> 0.14350349 | T89: =T80/T17 -> 0.086774594 | U89: =U80/U17 -> 0.086774594 | V89: =V80/V17 -> 0.12627275 | W89: =W80/W17 -> 0.12627275 | X89: =X80/X17 -> 0.25239492 | Y89: =Y80/Y17 -> 0.25239492 | Z89: =Z80/Z17 -> 0.1746641 | AA89: =IFERROR(AVERAGE(F89,H89,J89,L89,N89,P89,R89,T89,V89,X89),0) -> 0.14669402 | AB89: =AVERAGE(T89,V89,X89) -> 0.15514742
A90: Payroll to Total Revenue % | B90: 0.34376694 | C90: 0.34376694 | D90: 0.30355132 | E90: 0.30355132 | F90: 0.43798579 | G90: 0.43798579 | H90: 0.28628711 | I90: 0.28628711 | J90: 0.19659572 | K90: 0.19659572 | L90: 0.28574693 | M90: 0.28574693 | N90: 0.3425826 | O90: 0.3425826 | P90: 0.30180679 | Q90: 0.30180679 | R90: =IFERROR(R43/R17,0) -> 0.2478896 | S90: =IFERROR(S43/S17,0) -> 0.2478896 | T90: =IFERROR(T43/T17,0) -> 0.3350104 | U90: =IFERROR(U43/U17,0) -> 0.3350104 | V90: =IFERROR(V43/V17,0) -> 0.18080093 | W90: =IFERROR(W43/W17,0) -> 0.18080093 | X90: =IFERROR(X43/X17,0) -> 0 | Y90: =IFERROR(Y43/Y17,0) -> 0 | Z90: =IFERROR(Z43/Z17,0) -> 0.23848632 | AA90: =IFERROR(AVERAGE(F90,H90,J90,L90,N90,P90,R90,T90,V90,X90),0) -> 0.26147059 | AB90: =AVERAGE(T90,V90,X90) -> 0.17193711
A91: Payroll to Services Revenue % | B91: 0.55633928 | C91: 0.55633928 | D91: 0.55244206 | E91: 0.55244206 | F91: 0.54513213 | G91: 0.54513213 | H91: 0.46804373 | I91: 0.46804373 | J91: 0.45104597 | K91: 0.45104597 | L91: 0.4679465 | M91: 0.4679465 | N91: 0.53922999 | O91: 0.53922999 | P91: 0.4982881 | Q91: 0.4982881 | R91: =IFERROR(R43/SUM(R9,R10,R11,R12),0) -> 0.48608608 | S91: =IFERROR(S43/SUM(S9,S10,S11,S12),0) -> 0.48608608 | T91: =IFERROR(T43/SUM(T9,T10,T11,T12),0) -> 0.51161462 | U91: =IFERROR(U43/SUM(U9,U10,U11,U12),0) -> 0.51161462 | V91: =IFERROR(V43/SUM(V9,V10,V11,V12),0) -> 0.51677702 | W91: =IFERROR(W43/SUM(W9,W10,W11,W12),0) -> 0.51677702 | X91: =IFERROR(X43/SUM(X9,X10,X11,X12),0) -> 0 | Y91: =IFERROR(Y43/SUM(Y9,Y10,Y11,Y12),0) -> 0 | Z91: =IFERROR(Z43/SUM(Z9,Z10,Z11,Z12),0) -> 0.41130544 | AA91: =IFERROR(AVERAGE(F91,H91,J91,L91,N91,P91,R91,T91,V91,X91),0) -> 0.44841641 | AB91: =AVERAGE(T91,V91,X91) -> 0.34279721
A92: Payroll to Services + Product Margin % | B92: 0.46836963 | C92: 0.46836963 | D92: 0.48012969 | E92: 0.48012969 | F92: 0.52483628 | G92: 0.52483628 | H92: 0.43873702 | I92: 0.43873702 | J92: 0.37457679 | K92: 0.37457679 | L92: 0.41757984 | M92: 0.41757984 | N92: 0.48824781 | O92: 0.48824781 | P92: 0.45366251 | Q92: 0.45366251 | R92: =IFERROR(R43/(SUM(R9,R10,R11,R12)+(R13+R14-R25-R26)),0) -> 0.43101278 | S92: =IFERROR(S43/(SUM(S9,S10,S11,S12)+(S13+S14-S25-S26)),0) -> 0.43101278 | T92: =IFERROR(T43/(SUM(T9,T10,T11,T12)+(T13+T14-T25-T26)),0) -> 0.46521255 | U92: =IFERROR(U43/(SUM(U9,U10,U11,U12)+(U13+U14-U25-U26)),0) -> 0.46521255 | V92: =IFERROR(V43/(SUM(V9,V10,V11,V12)+(V13+V14-V25-V26)),0) -> 0.40319858 | W92: =IFERROR(W43/(SUM(W9,W10,W11,W12)+(W13+W14-W25-W26)),0) -> 0.40319858 | X92: =IFERROR(X43/(SUM(X9,X10,X11,X12)+(X13+X14-X25-X26)),0) -> 0 | Y92: =IFERROR(Y43/(SUM(Y9,Y10,Y11,Y12)+(Y13+Y14-Y25-Y26)),0) -> 0 | Z92: =IFERROR(Z43/(SUM(Z9,Z10,Z11,Z12)+(Z13+Z14-Z25-Z26)),0) -> 0.332146 | AA92: =IFERROR(AVERAGE(F92,H92,J92,L92,N92,P92,R92,T92,V92,X92),0) -> 0.39970642 | AB92: =AVERAGE(T92,V92,X92) -> 0.28947038
A93: Product (One Time) Sales Profit % | B93: 0.33445892 | C93: 0.33445892 | D93: 0.19345428 | E93: 0.19345428 | F93: 0.17797511 | G93: 0.17797511 | H93: 0.10358039 | I93: 0.10358039 | J93: 0.16048458 | K93: 0.16048458 | L93: 0.20156306 | M93: 0.20156306 | N93: 0.18986933 | O93: 0.18986933 | P93: 0.1533181 | Q93: 0.1533181 | R93: =(R14-R26)/R14 -> 0.1443062 | S93: =(S14-S26)/S14 -> 0.1443062 | T93: =(T14-T26)/T14 -> 0.19276574 | U93: =(U14-U26)/U14 -> 0.19276574 | V93: =(V14-V26)/V14 -> 0.15293379 | W93: =(W14-W26)/W14 -> 0.15293379 | X93: =(X14-X26)/X14 -> 0.15413134 | Y93: =(Y14-Y26)/Y14 -> 0.15413134 | Z93: =(Z14-Z26)/Z14 -> 0.3349421 | AA93: =IFERROR(AVERAGE(F93,H93,J93,L93,N93,P93,R93,T93,V93,X93),0) -> 0.16309276 | AB93: =AVERAGE(T93,V93,X93) -> 0.16661029
A94: Product (One Time) Sales Profit $ | B94: 160569.69 | C94: 0.10911266 | D94: 133556 | E94: 0.080784106 | F94: 39343 | G94: 0.032260657 | H94: 67589 | I94: 0.0366585 | J94: 235125 | K94: 0.085406674 | L94: 137362 | M94: 0.067643884 | N94: 127592 | O94: 0.062779691 | P94: 114419 | Q94: 0.057106337 | R94: =R14-R26 -> 117540 | S94: =S14-S26 -> 0.067650361 | T94: =T14-T26 -> 72126 | U94: =U14-U26 -> 0.061204436 | V94: =V14-V26 -> 225158 | W94: =W14-W26 -> 0.097348194 | X94: =X14-X26 -> 82025 | Y94: =Y14-Y26 -> 0.072797095 | Z94: =Z14-Z26 -> 2515586 | AA94: =IFERROR(AVERAGE(F94,H94,J94,L94,N94,P94,R94,T94,V94,X94),0) -> 121827.9 | AB94: =AVERAGE(T94,V94,X94) -> 126436.33
A95: Product Sales % of Total Revenue | B95: 0.32623637 | C95: 0.32623637 | D95: 0.41758758 | E95: 0.41758758 | F95: 0.18126499 | G95: 0.18126499 | H95: 0.35391353 | I95: 0.35391353 | J95: 0.53217993 | K95: 0.53217993 | L95: 0.33559663 | M95: 0.33559663 | N95: 0.33064682 | O95: 0.33064682 | P95: 0.37246963 | Q95: 0.37246963 | R95: =R14/R17 -> 0.46879732 | S95: =S14/S17 -> 0.46879732 | T95: =T14/T17 -> 0.31750681 | U95: =U14/U17 -> 0.31750681 | V95: =V14/V17 -> 0.63653815 | W95: =W14/W17 -> 0.63653815 | X95: =X14/X17 -> 0.4723056 | Y95: =Y14/Y17 -> 0.4723056 | Z95: =Z14/Z17 -> 0.38205781 | AA95: =IFERROR(AVERAGE(F95,H95,J95,L95,N95,P95,R95,T95,V95,X95),0) -> 0.40012194 | AB95: =AVERAGE(T95,V95,X95) -> 0.47545019
A98: On Separate Tab
A99: Variance to Budget
A100: Variance to trend month over month
A101: Variance to trend month 3 month avg
A103: Sales $/Profit Needed to Break Even
A104: Recurring Revenue | B104: 884632.5 | C104: 0.60113841 | D104: 893609 | E104: 0.54051787 | F104: 947637 | G104: 0.77704781 | H104: 1092495 | I104: 0.59254063 | J104: 1125519 | K104: 0.40883289 | L104: 1131300 | M104: 0.55710841 | N104: 1212664 | O104: 0.59667276 | P104: 1140095 | R104: =SUM(R9:R11,R15) -> 851177 | S104: =SUM(S9:S11,S15) -> 0.48989648 | T104: =SUM(T9:T11,T15) -> 763046 | U104: =SUM(U9:U11,U15) -> 0.64750298 | V104: =SUM(V9:V11,V15) -> 795504 | W104: =SUM(W9:W11,W15) -> 0.34394016 | X104: =SUM(X9:X11,X15) -> 568598 | Z104: =SUM(F104:V104) -> 9059441.1
A106: Total Expenses (not including COGS or Subcontractor) | B106: 892436.4 | D106: 911286 | F106: 889247 | H106: 1018342 | J106: 857378 | L106: 979666 | N106: 1093957 | P106: 409246 | R106: =R22+R21+R39+R41+R43+R45+R52+R55 -> 600935 | T106: =T22+T21+T39+T41+T43+T45+T52+T55 -> 559912 | V106: =V22+V21+V39+V41+V43+V45+V52+V55 -> 563218 | X106: =SUM(X10:X12,X16) -> 240965 | Z106: =SUM(F106:V106) -> 6971901
A107: Recurring Profit/Loss (GAP) | B107: -7803.9 | D107: -17677 | F107: 58390 | H107: 74153 | J107: 268141 | L107: 151634 | N107: 118707 | P107: 2372428 | R107: =R104-R106 -> 250242 | T107: =T104-T106 -> 203134 | V107: =V104-V106 -> 232286 | X107: =SUM(X11:X13,X17) -> 1348344 | Z107: =Z104-Z106 -> 2087540.1
A108: Product/Project Sales needed @ 15% to Break Even | B108: -52026 | D108: -117846.67 | F108: 389266.67 | H108: 494353.33 | J108: 1787606.7 | L108: 1010893.3 | N108: 791380 | P108: 863518 | R108: =R107/0.15 -> 1668280 | T108: =T107/0.15 -> 1354226.7 | V108: =V107/0.15 -> 1548573.3 | X108: =SUM(X12:X14,X18) -> 558164
A109: 15% of Revenue (Profit Target)
A110: Product/Project Sales Needed for 15% Profit
A111: Minimum Rev. Target
A112: *Other cost when we sell more (Commission) %
A115: Difference between recurring Profit/Loss vs Total P/L | B115: 343980.79 | D115: 206107.4 | F115: 155386 | H115: 69233 | J115: 113160 | L115: 316207 | N115: 276968 | P115: 221610 | R115: =P60-P107 -> -2003102 | T115: =R60-R107 -> 20547 | V115: =T60-T107 -> -83910 | X115: =V60-V107 -> 82547 | Z115: =Z60-Z107 -> 1539135.9 | AA115: *This section needs works - doesn't add up on Product Sales only $658k
A116: Project Services | B116: 64037.92 | D116: 43186.08 | F116: 27190 | H116: 43417 | J116: 53573 | L116: 98569 | N116: 139411 | P116: 106978 | R116: =P12 -> 67523 | T116: =R12 -> 49407 | V116: =T12 -> 12180 | X116: =V12 -> 27982 | Z116: =Z12 -> 538896 | AA116: *This is profit made from Project Engineers
A117: Difference between P&L gap and project | B117: 279942.87 | D117: 162921.32 | F117: 128196 | H117: 25816 | J117: 59587 | L117: 217638 | N117: 137557 | P117: 114632 | R117: =R115-R116 -> -2070625 | T117: =T115-T116 -> -28860 | V117: =V115-V116 -> -96090 | X117: =X115-X116 -> 54565 | Z117: =Z115-Z116 -> 1000239.9 | AA117: *This is profit made from Product Sales Only
A119: Selling Expenses broken out
A122: To Do's
A123: Dennis to give daily payroll calculations
A127: Profit Goals | B127: Monthly | D127: Annual
A128: California | B128: 250000 | D128: =B128*12 -> 3000000
...

Sheet Modesto & Irvine
B1: Month 1 ($) | C1: Month 1 (%) | D1: Month 2 ($) | E1: Month 2 (%) | F1: Month 3 ($) | G1: Month 3 (%) | H1: Month 4 ($) | I1: Month 4 (%) | J1: Month 5 ($) | K1: Month 5 (%) | L1: Month 6 ($) | M1: Month 6 (%) | N1: Month 7 ($) | O1: Month 7 (%) | P1: Month 8 ($) | Q1: Month 8 (%) | R1: Month 9 ($) | S1: Month 9 (%) | T1: Month 10 ($) | U1: Month 10 (%) | V1: Month 11 ($) | W1: Month 11 (%) | X1: Month 12 ($) | Y1: Month 12 (%) | Z1: 9 Month Totals | AA1: 9 Month Average | AB1: 3 Month Average | AD1: 9 Month Sparkline | AE1: Last 3 Months Average | AF1: Last 3 Months Sparkline | AG1: Target $ | AH1: Target % | AI1: Annual Budget Q1 * 4 | AJ1: Monthly Budget
A2: Location | B2: All Locations | D2: All Locations | F2: All Locations | H2: All Locations | J2: All Locations | L2: All Locations | N2: All Locations | P2: All Locations | R2: All Locations | T2: All Locations | V2: All Locations | X2: All Locations
A3: Month | H3: 07/31/2022 | J3: 08/31/2022 | L3: 09/30/2022 | N3: 10/31/2022 | P3: 11/30/2022 | R3: 12/31/2022 | T3: 01/31/2023 | V3: 02/28/2023 | X3: 03/31/2023
A4: Days in Month | H4: 31 | J4: 31 | L4: 30 | N4: 31 | P4: 30 | R4: 31 | T4: 31 | V4: 28 | X4: 31
A5: Quarter | H5: 3 | J5: 3 | L5: 3 | N5: 4 | P5: 4 | R5: 4 | T5: 1 | V5: 1 | X5: 1
A6: Year | H6: 2022 | J6: 2022 | L6: 2022 | N6: 2022 | P6: 2022 | R6: 2022 | T6: 2023 | V6: 2023 | X6: 2023
A8: Revenue
A9: Subcontracted Services | H9: 57205.93 | I9: =H9/H$16 -> 0.044008621 | J9: 38877.21 | K9: =J9/J$16 -> 0.017734631 | L9: 63688.86 | M9: =L9/L$16 -> 0.043278785 | N9: 42072 | O9: =N9/N$16 -> 0.025448118 | P9: 7422 | Q9: =P9/P$16 -> 0.0060859262 | R9: 45152 | S9: =R9/R$16 -> 0.02448926 | T9: 63823 | U9: =T9/T$16 -> 0.023183031 | V9: 78469 | W9: =V9/V$16 -> 0.03864204 | X9: 40805 | Y9: =X9/X$16 -> 0.020077476 | Z9: =SUM(H9:X9) -> 437515.22 | AA9: =IFERROR(AVERAGE(B9:X9),0) -> 25736.19 | AE9: =IFERROR(AVERAGE(T9,V9,X9),0) -> 61032.333 | AI9: =SUM(T9:X9)*4 -> 732388.25 | AJ9: =AI9/12 -> 61032.354
A10: Product Sales | H10: 404466.23 | I10: =H10/H$16 -> 0.31115657 | J10: 1250315.2 | K10: =J10/J$16 -> 0.57035672 | L10: 480087.93 | M10: =L10/L$16 -> 0.32623637 | N10: 690375 | O10: =N10/N$16 -> 0.41758758 | P10: 221059 | Q10: =P10/P$16 -> 0.18126499 | R10: 652527 | S10: =R10/R$16 -> 0.35391353 | T10: 1465094 | U10: =T10/T$16 -> 0.53217993 | V10: 681484 | W10: =V10/V$16 -> 0.33559663 | X10: 671999 | Y10: =X10/X$16 -> 0.33064682 | Z10: =SUM(H10:X10) -> 6517410.4 | AA10: =IFERROR(AVERAGE(B10:X10),0) -> 383377.08 | AE10: =IFERROR(AVERAGE(T10,V10,X10),0) -> 939525.67 | AI10: =SUM(T10:X10)*4 -> 11274311 | AJ10: =AI10/12 -> 939525.96
A11: Commissions | H11: 5609.51 | I11: =H11/H$16 -> 0.0043154058 | J11: 23356.27 | K11: =J11/J$16 -> 0.010654438 | L11: 18506.84 | M11: =L11/L$16 -> 0.012576038 | N11: 12387 | O11: =N11/N$16 -> 0.0074925329 | P11: 11220 | Q11: =P11/P$16 -> 0.009200228 | R11: 18308 | S11: =R11/R$16 -> 0.0099297789 | T11: 24146 | U11: =T11/T$16 -> 0.0087707796 | V11: 30706 | W11: =V11/V$16 -> 0.015121162 | X11: 28436 | Y11: =X11/X$16 -> 0.013991499 | Z11: =SUM(H11:X11) -> 172675.7 | AA11: =IFERROR(AVERAGE(B11:X11),0) -> 10157.394 | AE11: =IFERROR(AVERAGE(T11,V11,X11),0) -> 27762.667 | AI11: =SUM(T11:X11)*4 -> 333152.1 | AJ11: =AI11/12 -> 27762.675
A12: Cloud | H12: 173821.47 | I12: =H12/H$16 -> 0.13372116 | J12: 325936.92 | K12: =J12/J$16 -> 0.14868276 | L12: 362592.58 | M12: =L12/L$16 -> 0.24639421 | N12: 258324 | O12: =N12/N$16 -> 0.15625261 | P12: 439597 | Q12: =P12/P$16 -> 0.3604628 | R12: 330044 | S12: =R12/R$16 -> 0.17900721 | T12: 482810 | U12: =T12/T$16 -> 0.17537563 | V12: 477754 | W12: =V12/V$16 -> 0.23526984 | X12: 507829 | Y12: =X12/X$16 -> 0.24986949 | Z12: =SUM(H12:X12) -> 3358710.6 | AA12: =IFERROR(AVERAGE(B12:X12),0) -> 197571.21 | AE12: =IFERROR(AVERAGE(T12,V12,X12),0) -> 489464.33 | AI12: =SUM(T12:X12)*4 -> 5873573.6 | AJ12: =AI12/12 -> 489464.47
A13: Project Services | H13: 60454.51 | I13: =H13/H$16 -> 0.046507759 | J13: 64037.92 | K13: =J13/J$16 -> 0.029212201 | L13: 43186.08 | M13: =L13/L$16 -> 0.029346436 | N13: 27190 | O13: =N13/N$16 -> 0.016446433 | P13: 43417 | Q13: =P13/P$16 -> 0.035601274 | R13: 53573 | S13: =R13/R$16 -> 0.02905659 | T13: 98569 | U13: =T13/T$16 -> 0.035804149 | V13: 139411 | W13: =V13/V$16 -> 0.068652914 | X13: 106978 | Y13: =X13/X$16 -> 0.052636888 | Z13: =SUM(H13:X13) -> 636816.8 | AA13: =IFERROR(AVERAGE(B13:X13),0) -> 37459.812 | AE13: =IFERROR(AVERAGE(T13,V13,X13),0) -> 114986 | AI13: =SUM(T13:X13)*4 -> 1379832.4 | AJ13: =AI13/12 -> 114986.03
A14: Managed IT Services | H14: 598322.43 | I14: =H14/H$16 -> 0.46029048 | J14: 489639.99 | K14: =J14/J$16 -> 0.22335925 | L14: 503533.08 | M14: =L14/L$16 -> 0.34216816 | N14: 622898 | O14: =N14/N$16 -> 0.37677272 | P14: 496820 | Q14: =P14/P$16 -> 0.40738478 | R14: 744143 | S14: =R14/R$16 -> 0.40360364 | T14: 618563 | U14: =T14/T$16 -> 0.22468648 | V14: 622840 | W14: =V14/V$16 -> 0.30671741 | X14: 676399 | Y14: =X14/X$16 -> 0.33281178 | Z14: =SUM(H14:X14) -> 5373161.2 | AA14: =IFERROR(AVERAGE(B14:X14),0) -> 316068.31 | AE14: =IFERROR(AVERAGE(T14,V14,X14),0) -> 639267.33 | AI14: =SUM(T14:X14)*4 -> 7671210.1 | AJ14: =AI14/12 -> 639267.51
A15: Sales Returns and Discounts | H15: 0 | I15: =H15/H$16 -> 0 | J15: 0 | K15: =J15/J$16 -> 0 | L15: 0 | M15: =L15/L$16 -> 0 | N15: 0 | O15: =N15/N$16 -> 0 | P15: 0 | Q15: =P15/P$16 -> 0 | R15: 0 | S15: =R15/R$16 -> 0 | T15: 0 | U15: =T15/T$16 -> 0 | V15: 0 | W15: =V15/V$16 -> 0 | X15: 69 | Y15: =X15/X$16 -> 3.3950394e-05 | AA15: =IFERROR(AVERAGE(B15:X15),0) -> 4.0588235 | AE15: =IFERROR(AVERAGE(T15,V15,X15),0) -> 23 | AI15: =SUM(T15:X15)*4 -> 276 | AJ15: =AI15/12 -> 23
A16: Total Revenue | H16: 1299880.1 | I16: =H16/H$16 -> 1 | J16: 2192163.5 | K16: =J16/J$16 -> 1 | L16: 1471595.4 | M16: =L16/L$16 -> 1 | N16: 1653246 | O16: =N16/N$16 -> 1 | P16: 1219535 | Q16: =P16/P$16 -> 1 | R16: 1843747 | S16: =R16/R$16 -> 1 | T16: 2753005 | U16: =T16/T$16 -> 1 | V16: 2030664 | W16: =V16/V$16 -> 1 | X16: 2032377 | Y16: =X16/X$16 -> 1 | Z16: =SUM(H16:X16) -> 16496221 | AA16: =IFERROR(AVERAGE(B16:X16),0) -> 970365.94 | AE16: =IFERROR(AVERAGE(T16:X16),0) -> 1363209.6 | AI16: =SUM(T16:X16)*4 -> 27264192 | AJ16: =AI16/12 -> 2272016
A17: *Excel calc to verify Intacct Totaling | X17: =SUM(X9:X15) -> 2032515 | AI17: =SUM(T17:X17)*4 -> 8130060 | AJ17: =AI17/12 -> 677505
A19: Cost of Goods and Services
A20: Subcontractor Service Costs | H20: 48054.94 | I20: =H20/H$16 -> 0.036968749 | J20: 36085.33 | K20: =J20/J$16 -> 0.016461058 | L20: 53470.72 | M20: =L20/L$16 -> 0.036335205 | N20: 38812 | O20: =N20/N$16 -> 0.02347624 | P20: 8874 | Q20: =P20/P$16 -> 0.0072765439 | R20: 37409 | S20: =R20/R$16 -> 0.02028966 | T20: 53982 | U20: =T20/T$16 -> 0.019608392 | V20: 66267 | W20: =V20/V$16 -> 0.032633168 | X20: 33571 | Y20: =X20/X$16 -> 0.016518097 | Z20: =SUM(H20:X20) -> 376526.18 | AA20: =IFERROR(AVERAGE(B20:X20),0) -> 22148.599 | AE20: =IFERROR(AVERAGE(T20:X20),0) -> 30764.01 | AI20: =SUM(T20:X20)*4 -> 615280.21 | AJ20: =AI20/12 -> 51273.351
A21: Product Sales Cost | H21: 244231.98 | I21: =H21/H$16 -> 0.18788809 | J21: 977075.5 | K21: =J21/J$16 -> 0.44571288 | L21: 319518.24 | M21: =L21/L$16 -> 0.21712371 | N21: 556819 | O21: =N21/N$16 -> 0.33680348 | P21: 181716 | Q21: =P21/P$16 -> 0.14900433 | R21: 584938 | S21: =R21/R$16 -> 0.31725502 | T21: 1229969 | U21: =T21/T$16 -> 0.44677325 | V21: 544122 | W21: =V21/V$16 -> 0.26795275 | X21: 544407 | Y21: =X21/X$16 -> 0.26786713 | Z21: =SUM(H21:X21) -> 5182799.1 | AA21: =IFERROR(AVERAGE(B21:X21),0) -> 304870.53 | AE21: =IFERROR(AVERAGE(T21:X21),0) -> 463699.74 | AI21: =SUM(T21:X21)*4 -> 9273994.9 | AJ21: =AI21/12 -> 772832.9
A22: Cloud Service Costs | H22: 117860.58 | I22: =H22/H$16 -> 0.090670349 | J22: 134209.51 | K22: =J22/J$16 -> 0.0612224 | L22: 124169.95 | M22: =L22/L$16 -> 0.08437778 | N22: 130483 | O22: =N22/N$16 -> 0.078925338 | P22: 146907 | Q22: =P22/P$16 -> 0.12046149 | R22: 129852 | S22: =R22/R$16 -> 0.070428318 | T22: 147592 | U22: =T22/T$16 -> 0.053611236 | V22: 152612 | W22: =V22/V$16 -> 0.075153743 | X22: 153032 | Y22: =X22/X$16 -> 0.075297054 | Z22: =SUM(H22:X22) -> 1236718.7 | AA22: =IFERROR(AVERAGE(B22:X22),0) -> 72748.157 | AE22: =IFERROR(AVERAGE(T22:X22),0) -> 90647.226 | AI22: =SUM(T22:X22)*4 -> 1812944.5 | AJ22: =AI22/12 -> 151078.71
A23: Project Service Costs | I23: =H23/H$16 -> 0 | J23: 137.34 | K23: =J23/J$16 -> 6.2650436e-05 | L23: 0 | M23: =L23/L$16 -> 0 | N23: 1359 | O23: =N23/N$16 -> 0.00082201923 | P23: 2600 | Q23: =P23/P$16 -> 0.0021319601 | R23: 749 | S23: =R23/R$16 -> 0.00040623795 | T23: 0 | U23: =T23/T$16 -> 0 | V23: 942 | W23: =V23/V$16 -> 0.00046388767 | X23: 1071 | Y23: =X23/X$16 -> 0.00052696916 | Z23: =SUM(H23:X23) -> 6858.3439 | AA23: =IFERROR(AVERAGE(B23:X23),0) -> 428.64649 | AE23: =IFERROR(AVERAGE(T23:X23),0) -> 402.60009 | AI23: =SUM(T23:X23)*4 -> 8052.0019 | AJ23: =AI23/12 -> 671.00015
A24: Managed IT Service Costs | H24: 108088.48 | I24: =H24/H$16 -> 0.083152655 | J24: 94927 | K24: =J24/J$16 -> 0.043302883 | L24: 111051.15 | M24: =L24/L$16 -> 0.075463101 | N24: 94993 | O24: =N24/N$16 -> 0.057458479 | P24: 71684 | Q24: =P24/P$16 -> 0.058779781 | R24: 164803 | S24: =R24/R$16 -> 0.089384823 | T24: 61481 | U24: =T24/T$16 -> 0.022332324 | V24: 87723 | W24: =V24/V$16 -> 0.04319917 | X24: 99230 | Y24: =X24/X$16 -> 0.048824603 | Z24: =SUM(H24:X24) -> 893981.1 | AA24: =IFERROR(AVERAGE(B24:X24),0) -> 52587.124 | AE24: =IFERROR(AVERAGE(T24:X24),0) -> 49686.813 | AI24: =SUM(T24:X24)*4 -> 993736.26 | AJ24: =AI24/12 -> 82811.355
A25: Total COGS | H25: 518235.98 | I25: =H25/H$16 -> 0.39867984 | J25: 1242434.7 | K25: =J25/J$16 -> 0.56676187 | L25: 608210.06 | M25: =L25/L$16 -> 0.41329979 | N25: 822466 | O25: =N25/N$16 -> 0.49748555 | P25: 411781 | Q25: =P25/P$16 -> 0.33765411 | R25: 917751 | S25: =R25/R$16 -> 0.49776406 | T25: 1493024 | U25: =T25/T$16 -> 0.5423252 | V25: 851666 | W25: =V25/V$16 -> 0.41940272 | X25: 831311 | Y25: =X25/X$16 -> 0.40903386 | Z25: =SUM(H25:X25) -> 7696883.4 | AA25: =IFERROR(AVERAGE(B25:X25),0) -> 452757.85 | AE25: =IFERROR(AVERAGE(T25:X25),0) -> 635200.39 | AI25: =SUM(T25:X25)*4 -> 12704008 | AJ25: =AI25/12 -> 1058667.3
A27: Gross Profit | H27: 781644.1 | I27: =H27/H$16 -> 0.60132016 | J27: 949728.82 | K27: =J27/J$16 -> 0.43323813 | L27: 863385.31 | M27: =L27/L$16 -> 0.58670021 | N27: 830780 | O27: =N27/N$16 -> 0.50251445 | P27: 807754 | Q27: =P27/P$16 -> 0.66234589 | R27: 925996 | S27: =R27/R$16 -> 0.50223594 | T27: 1259981 | U27: =T27/T$16 -> 0.4576748 | V27: 1178998 | W27: =V27/V$16 -> 0.58059728 | X27: 1201066 | Y27: =X27/X$16 -> 0.59096614 | Z27: =SUM(H27:X27) -> 8799337.6 | AA27: =IFERROR(AVERAGE(B27:X27),0) -> 517608.09 | AE27: =IFERROR(AVERAGE(T27:X27),0) -> 728009.21 | AI27: =SUM(T27:X27)*4 -> 14560184 | AJ27: =AI27/12 -> 1213348.7
AJ28: =AI28/12 -> 0
A29: Operating Expenses | AJ29: =AI29/12 -> 0
A30: General & Admin Expenses | AJ30: =AI30/12 -> 0
A31: Charitable Contributions | H31: 2980 | I31: =H31/H$16 -> 0.0022925192 | J31: 2180 | K31: =J31/J$16 -> 0.00099445137 | L31: 970 | M31: =L31/L$16 -> 0.00065914858 | N31: 1990 | O31: =N31/N$16 -> 0.0012036926 | P31: 1300 | Q31: =P31/P$16 -> 0.0010659801 | R31: 1000 | S31: =R31/R$16 -> 0.00054237376 | T31: 1000 | U31: =T31/T$16 -> 0.00036323944 | V31: 1515 | W31: =V31/V$16 -> 0.00074606139 | X31: 2250 | Y31: =X31/X$16 -> 0.0011070781 | Z31: =SUM(H31:X31) -> 15185.008 | AA31: =IFERROR(AVERAGE(B31:X31),0) -> 893.23576 | AE31: =IFERROR(AVERAGE(T31:X31),0) -> 953.00022 | AI31: =SUM(T31:X31)*4 -> 19060.004 | AJ31: =AI31/12 -> 1588.3337
A32: Education | H32: 910.9 | I32: =H32/H$16 -> 0.00070075695 | J32: 398.9 | K32: =J32/J$16 -> 0.00018196635 | L32: 383.95 | M32: =L32/L$16 -> 0.00026090732 | N32: 1814 | O32: =N32/N$16 -> 0.0010972354 | P32: 2570 | Q32: =P32/P$16 -> 0.0021073606 | R32: 3191 | S32: =R32/R$16 -> 0.0017307147 | T32: 384 | U32: =T32/T$16 -> 0.00013948395 | V32: 747 | W32: =V32/V$16 -> 0.00036785997 | X32: 551 | Y32: =X32/X$16 -> 0.00027111112 | Z32: =SUM(H32:X32) -> 10950.757 | AA32: =IFERROR(AVERAGE(B32:X32),0) -> 644.16215 | AE32: =IFERROR(AVERAGE(T32:X32),0) -> 336.4001 | AI32: =SUM(T32:X32)*4 -> 6728.002 | AJ32: =AI32/12 -> 560.66684
A33: Finance Charges | H33: 26956.98 | I33: =H33/H$16 -> 0.020738051 | J33: 7084.93 | K33: =J33/J$16 -> 0.003231935 | L33: 16412.63 | M33: =L33/L$16 -> 0.01115295 | N33: 8068 | O33: =N33/N$16 -> 0.0048800965 | P33: 5771 | Q33: =P33/P$16 -> 0.0047321315 | R33: 8438 | S33: =R33/R$16 -> 0.0045765498 | T33: 5925 | U33: =T33/T$16 -> 0.0021521937 | V33: 10413 | W33: =V33/V$16 -> 0.0051278794 | X33: 5218 | Y33: =X33/X$16 -> 0.002567437 | Z33: =SUM(H33:X33) -> 94287.597 | AA33: =IFERROR(AVERAGE(B33:X33),0) -> 5546.3292 | AE33: =IFERROR(AVERAGE(T33:X33),0) -> 4311.2015 | AI33: =SUM(T33:X33)*4 -> 86224.029 | AJ33: =AI33/12 -> 7185.3358
A34: Travel, Meals and Entertainment | H34: 96.14 | I34: =H34/H$16 -> 7.3960669e-05 | J34: 13096.32 | K34: =J34/J$16 -> 0.0059741529 | L34: 10074.7 | M34: =L34/L$16 -> 0.0068461074 | N34: 10074 | O34: =N34/N$16 -> 0.006093467 | P34: 7478 | Q34: =P34/P$16 -> 0.0061318453 | R34: 12377 | S34: =R34/R$16 -> 0.0067129601 | T34: 6909 | U34: =T34/T$16 -> 0.0025096213 | V34: 22230 | W34: =V34/V$16 -> 0.010947158 | X34: 23841 | Y34: =X34/X$16 -> 0.011730599 | Z34: =SUM(H34:X34) -> 106176.21 | AA34: =IFERROR(AVERAGE(B34:X34),0) -> 6245.6591 | AE34: =IFERROR(AVERAGE(T34:X34),0) -> 10596.003 | AI34: =SUM(T34:X34)*4 -> 211920.05 | AJ34: =AI34/12 -> 17660.004
A35: Office Supplies | H35: 3556.19 | I35: =H35/H$16 -> 0.0027357831 | J35: 64334.01 | K35: =J35/J$16 -> 0.029347268 | L35: 28913.68 | M35: =L35/L$16 -> 0.019647847 | N35: 28645 | O35: =N35/N$16 -> 0.01732652 | P35: 22933 | Q35: =P35/P$16 -> 0.018804708 | R35: 51599 | S35: =R35/R$16 -> 0.027985944 | T35: 11061 | U35: =T35/T$16 -> 0.0040177915 | V35: 15433 | W35: =V35/V$16 -> 0.0075999772 | X35: 25552 | Y35: =X35/X$16 -> 0.012572471 | Z35: =SUM(H35:X35) -> 252027.01 | AA35: =IFERROR(AVERAGE(B35:X35),0) -> 14825.118 | AE35: =IFERROR(AVERAGE(T35:X35),0) -> 10409.202 | AI35: =SUM(T35:X35)*4 -> 208184.05 | AJ35: =AI35/12 -> 17348.671
A36: Total General and Admin Expenses | H36: 34500.21 | I36: =H36/H$16 -> 0.026541071 | J36: 87094.16 | K36: =J36/J$16 -> 0.039729774 | L36: 56754.96 | M36: =L36/L$16 -> 0.03856696 | N36: 50591 | O36: =N36/N$16 -> 0.030601012 | P36: 40052 | Q36: =P36/P$16 -> 0.032842026 | R36: 76705 | S36: =R36/R$16 -> 0.04160278 | T36: 25279 | U36: =T36/T$16 -> 0.0091823299 | V36: 50338 | W36: =V36/V$16 -> 0.024788936 | X36: 57412 | Y36: =X36/X$16 -> 0.028248696 | Z36: =SUM(H36:X36) -> 478726.57 | AA36: =IFERROR(AVERAGE(B36:X36),0) -> 28160.387 | AE36: =IFERROR(AVERAGE(T36:X36),0) -> 26605.807 | AI36: =SUM(T36:X36)*4 -> 532116.14 | AJ36: =AI36/12 -> 44343.011
A38: Marketing and Advertising Expenses | H38: 1452 | I38: =H38/H$16 -> 0.0011170261 | J38: 10366.09 | K38: =J38/J$16 -> 0.0047287029 | L38: 7135 | M38: =L38/L$16 -> 0.0048484795 | N38: 1662 | O38: =N38/N$16 -> 0.001005295 | P38: 2602 | Q38: =P38/P$16 -> 0.0021336001 | R38: 2202 | S38: =R38/R$16 -> 0.001194307 | T38: 430 | U38: =T38/T$16 -> 0.00015619296 | V38: 6417 | W38: =V38/V$16 -> 0.0031600501 | X38: 1910 | Y38: =X38/X$16 -> 0.00093978627 | Z38: =SUM(H38:X38) -> 34176.108 | AA38: =IFERROR(AVERAGE(B38:X38),0) -> 2010.3593 | AE38: =IFERROR(AVERAGE(T38:X38),0) -> 1751.4007 | AI38: =SUM(T38:X38)*4 -> 35028.013 | AJ38: =AI38/12 -> 2919.0011
A40: Payroll and Related Expenses | H40: 525978.17 | I40: =H40/H$16 -> 0.40463592 | J40: 497007.2 | K40: =J40/J$16 -> 0.22671995 | L40: 505885.84 | M40: =L40/L$16 -> 0.34376694 | N40: 501845 | O40: =N40/N$16 -> 0.30355132 | P40: 534139 | Q40: =P40/P$16 -> 0.43798579 | R40: 527841 | S40: =R40/R$16 -> 0.28628711 | T40: 541229 | U40: =T40/T$16 -> 0.19659572 | V40: 580256 | W40: =V40/V$16 -> 0.28574693 | X40: 696257 | Y40: =X40/X$16 -> 0.3425826 | Z40: =SUM(H40:X40) -> 4910440.7 | AA40: =IFERROR(AVERAGE(B40:X40),0) -> 288849.45 | AE40: =IFERROR(AVERAGE(T40:X40),0) -> 363548.5 | AI40: =SUM(T40:X40)*4 -> 7270969.9 | AJ40: =AI40/12 -> 605914.16
A42: Utilities and Facilities | H42: 36113.67 | I42: =H42/H$16 -> 0.027782309 | J42: 43831.79 | K42: =J42/J$16 -> 0.019994763 | L42: 44707.15 | M42: =L42/L$16 -> 0.030380056 | N42: 51232 | O42: =N42/N$16 -> 0.030988734 | P42: 42505 | Q42: =P42/P$16 -> 0.034853448 | R42: 34135 | S42: =R42/R$16 -> 0.018513928 | T42: 36312 | U42: =T42/T$16 -> 0.013189951 | V42: 38163 | W42: =V42/V$16 -> 0.01879336 | X42: 34502 | Y42: =X42/X$16 -> 0.016976181 | Z42: =SUM(H42:X42) -> 361501.8 | AA42: =IFERROR(AVERAGE(B42:X42),0) -> 21264.812 | AE42: =IFERROR(AVERAGE(T42:X42),0) -> 21795.406 | AI42: =SUM(T42:X42)*4 -> 435908.13 | AJ42: =AI42/12 -> 36325.677
A44: Ops and Maint. Expenses | AJ44: =AI44/12 -> 0
A45: Automobile Expenses | H45: 14064.75 | I45: =H45/H$16 -> 0.010820037 | K45: =J45/J$16 -> 0 | M45: =L45/L$16 -> 0 | O45: =N45/N$16 -> 0 | Q45: =P45/P$16 -> 0 | S45: =R45/R$16 -> 0 | U45: =T45/T$16 -> 0 | W45: =V45/V$16 -> 0 | Y45: =X45/X$16 -> 0 | Z45: =SUM(H45:X45) -> 14064.761 | AA45: =IFERROR(AVERAGE(B45:X45),0) -> 1562.7512 | AE45: =IFERROR(AVERAGE(T45:X45),0) -> 0 | AI45: =SUM(T45:X45)*4 -> 0 | AJ45: =AI45/12 -> 0
A46: Professional Services | H46: 9525.56 | I46: =H46/H$16 -> 0.0073280298 | K46: =J46/J$16 -> 0 | M46: =L46/L$16 -> 0 | O46: =N46/N$16 -> 0 | Q46: =P46/P$16 -> 0 | S46: =R46/R$16 -> 0 | U46: =T46/T$16 -> 0 | W46: =V46/V$16 -> 0 | Y46: =X46/X$16 -> 0 | Z46: =SUM(H46:X46) -> 9525.5673 | AA46: =IFERROR(AVERAGE(B46:X46),0) -> 1058.3964 | AE46: =IFERROR(AVERAGE(T46:X46),0) -> 0 | AI46: =SUM(T46:X46)*4 -> 0 | AJ46: =AI46/12 -> 0
A47: Software and Maintenance | H47: 12615.7 | I47: =H47/H$16 -> 0.0097052799 | K47: =J47/J$16 -> 0 | M47: =L47/L$16 -> 0 | O47: =N47/N$16 -> 0 | Q47: =P47/P$16 -> 0 | S47: =R47/R$16 -> 0 | U47: =T47/T$16 -> 0 | W47: =V47/V$16 -> 0 | Y47: =X47/X$16 -> 0 | Z47: =SUM(H47:X47) -> 12615.71 | AA47: =IFERROR(AVERAGE(B47:X47),0) -> 1401.7455 | AE47: =IFERROR(AVERAGE(T47:X47),0) -> 0 | AI47: =SUM(T47:X47)*4 -> 0 | AJ47: =AI47/12 -> 0
A48: Other Operating Expense | H48: 4293.91 | I48: =H48/H$16 -> 0.0033033124 | K48: =J48/J$16 -> 0 | M48: =L48/L$16 -> 0 | O48: =N48/N$16 -> 0 | Q48: =P48/P$16 -> 0 | S48: =R48/R$16 -> 0 | U48: =T48/T$16 -> 0 | W48: =V48/V$16 -> 0 | Y48: =X48/X$16 -> 0 | Z48: =SUM(H48:X48) -> 4293.9133 | AA48: =IFERROR(AVERAGE(B48:X48),0) -> 477.10148 | AE48: =IFERROR(AVERAGE(T48:X48),0) -> 0 | AI48: =SUM(T48:X48)*4 -> 0 | AJ48: =AI48/12 -> 0
A49: Total Ops and Maint. Expenses | H49: 40499.92 | I49: =H49/H$16 -> 0.031156659 | J49: 30441.46 | K49: =J49/J$16 -> 0.013886492 | L49: 42732.35 | M49: =L49/L$16 -> 0.029038111 | N49: 80480 | O49: =N49/N$16 -> 0.048679991 | P49: 51358 | Q49: =P49/P$16 -> 0.042112772 | R49: 82804 | S49: =R49/R$16 -> 0.044910717 | T49: 45055 | U49: =T49/T$16 -> 0.016365753 | V49: 64157 | W49: =V49/V$16 -> 0.031594099 | X49: 51614 | Y49: =X49/X$16 -> 0.025395879 | Z49: =SUM(H49:X49) -> 489141.99 | AA49: =IFERROR(AVERAGE(B49:X49),0) -> 28773.058 | AE49: =IFERROR(AVERAGE(T49:X49),0) -> 32165.21 | AI49: =SUM(T49:X49)*4 -> 643304.19 | AJ49: =AI49/12 -> 53608.683
A51: Taxes and Insurance | AJ51: =AI51/12 -> 0
A52: Insurance | H52: 15838.92 | I52: =H52/H$16 -> 0.012184909 | K52: =J52/J$16 -> 0 | M52: =L52/L$16 -> 0 | O52: =N52/N$16 -> 0 | Q52: =P52/P$16 -> 0 | S52: =R52/R$16 -> 0 | U52: =T52/T$16 -> 0 | W52: =V52/V$16 -> 0 | Y52: =X52/X$16 -> 0 | Z52: =SUM(H52:X52) -> 15838.932 | AA52: =IFERROR(AVERAGE(B52:X52),0) -> 1759.8814 | AE52: =IFERROR(AVERAGE(T52:X52),0) -> 0 | AI52: =SUM(T52:X52)*4 -> 0 | AJ52: =AI52/12 -> 0
A53: Taxes | H53: 0 | AE53: =IFERROR(AVERAGE(T53:X53),0) -> 0 | AI53: =SUM(T53:X53)*4 -> 0 | AJ53: =AI53/12 -> 0
A54: Total Taxes and Insurance | H54: 15838.92 | I54: =H54/H$16 -> 0.012184909 | J54: -4048.64 | K54: =J54/J$16 -> -0.0018468695 | L54: 7866.51 | M54: =L54/L$16 -> 0.0053455659 | N54: 7261 | O54: =N54/N$16 -> 0.0043919659 | P54: 9475 | Q54: =P54/P$16 -> 0.0077693547 | R54: 14996 | S54: =R54/R$16 -> 0.008133437 | T54: 27328 | U54: =T54/T$16 -> 0.0099266075 | V54: 11065 | W54: =V54/V$16 -> 0.0054489566 | X54: 19054 | Y54: =X54/X$16 -> 0.0093752291 | Z54: =SUM(H54:X54) -> 108835.84 | AA54: =IFERROR(AVERAGE(B54:X54),0) -> 6402.1083 | AE54: =IFERROR(AVERAGE(T54:X54),0) -> 11489.403 | AI54: =SUM(T54:X54)*4 -> 229788.06 | AJ54: =AI54/12 -> 19149.005
A55: Total Operating Expenses | H55: 654382.89 | I55: =H55/H$16 -> 0.50341789 | J55: 664692.06 | K55: =J55/J$16 -> 0.30321281 | L55: 665081.81 | M55: =L55/L$16 -> 0.45194611 | N55: 693071 | O55: =N55/N$16 -> 0.41921831 | P55: 680131 | Q55: =P55/P$16 -> 0.55769699 | R55: 738683 | S55: =R55/R$16 -> 0.40064228 | T55: 675633 | U55: =T55/T$16 -> 0.24541655 | V55: 750396 | W55: =V55/V$16 -> 0.36953233 | X55: 860749 | Y55: =X55/X$16 -> 0.42351837 | Z55: =SUM(H55:X55) -> 6382823 | AA55: =IFERROR(AVERAGE(B55:X55),0) -> 375460.18 | AE55: =IFERROR(AVERAGE(T55:X55),0) -> 457355.72 | AI55: =SUM(T55:X55)*4 -> 9147114.5 | AJ55: =AI55/12 -> 762259.54
AI56: =SUM(T56:X56)*4 -> 0 | AJ56: =AI56/12 -> 0
A57: Net Operating Income | H57: =H27-H55 -> 127261.21 | I57: =H57/H$16 -> 0.09790227 | J57: =J27-J55 -> 285036.76 | K57: =J57/J$16 -> 0.13002532 | L57: =L27-L55 -> 198303.5 | M57: =L57/L$16 -> 0.13475409 | N57: =N27-N55 -> 137709 | O57: =N57/N$16 -> 0.083296134 | P57: =P27-P55 -> 127623 | Q57: =P57/P$16 -> 0.1046489 | R57: =R27-R55 -> 187313 | S57: =R57/R$16 -> 0.10159366 | T57: =T27-T55 -> 584348 | U57: =T57/T$16 -> 0.21225824 | V57: =V27-V55 -> 428602 | W57: =V57/V$16 -> 0.21106495 | X57: =X27-X55 -> 340317 | Y57: =X57/X$16 -> 0.16744777 | Z57: =SUM(H57:X57) -> 2416514.5 | AA57: =IFERROR(AVERAGE(B57:X57),0) -> 142147.91 | AE57: =IFERROR(AVERAGE(T57:X57),0) -> 270653.48 | AI57: =SUM(T57:X57)*4 -> 5413069.7 | AJ57: =AI57/12 -> 451089.14
AJ58: =AI58/12 -> 0
A59: Other Income (Expense) | AJ59: =AI59/12 -> 0
A60: Other Income | AJ60: =AI60/12 -> 0
A61: Interest Income | H61: 0 | J61: 0 | L61: 0 | N61: 0 | P61: 0 | R61: 0 | T61: 0 | V61: 0 | X61: 0 | Z61: =SUM(H61:X61) -> 0 | AA61: =IFERROR(AVERAGE(B61:X61),0) -> 0 | AE61: =IFERROR(AVERAGE(T61:X61),0) -> 0 | AI61: =SUM(T61:X61)*4 -> 0 | AJ61: =AI61/12 -> 0
A62: Other Income | H62: 270.5 | I62: =H62/H$16 -> 0.00020809612 | J62: 0.02 | K62: =J62/J$16 -> 9.1234071e-09 | L62: 0.01 | M62: =L62/L$16 -> 6.7953462e-09 | N62: 57624 | O62: =N62/N$16 -> 0.034855067 | P62: 0 | Q62: =P62/P$16 -> 0 | R62: 20 | S62: =R62/R$16 -> 1.0847475e-05 | T62: 0 | U62: =T62/T$16 -> 0 | V62: 0 | W62: =V62/V$16 -> 0 | X62: 504 | Y62: =X62/X$16 -> 0.00024798549 | Z62: =SUM(H62:X62) -> 58418.565 | AA62: =IFERROR(AVERAGE(B62:X62),0) -> 3436.3862 | AE62: =IFERROR(AVERAGE(T62:X62),0) -> 100.8 | AI62: =SUM(T62:X62)*4 -> 2016 | AJ62: =AI62/12 -> 168
A63: Total Other Income | H63: 270.5 | I63: =H63/H$16 -> 0.00020809612 | J63: 0.02 | K63: =J63/J$16 -> 9.1234071e-09 | L63: 0.01 | M63: =L63/L$16 -> 6.7953462e-09 | N63: 57624 | O63: =N63/N$16 -> 0.034855067 | P63: 0 | Q63: =P63/P$16 -> 0 | R63: 20 | S63: =R63/R$16 -> 1.0847475e-05 | T63: 0 | U63: =T63/T$16 -> 0 | V63: 0 | W63: =V63/V$16 -> 0 | X63: 504 | Y63: =X63/X$16 -> 0.00024798549 | Z63: =SUM(H63:X63) -> 58418.565 | AA63: =IFERROR(AVERAGE(B63:X63),0) -> 3436.3862 | AE63: =IFERROR(AVERAGE(T63:X63),0) -> 100.8 | AI63: =SUM(T63:X63)*4 -> 2016 | AJ63: =AI63/12 -> 168
A65: Other Expense | AI65: =SUM(T65:X65)*4 -> 0 | AJ65: =AI65/12 -> 0
A66: Interest Expenses | I66: =H66/H$16 -> 0 | J66: -25387.29 | K66: =J66/J$16 -> -0.011580929 | L66: -19810.34 | M66: =L66/L$16 -> -0.013461812 | N66: -9919 | O66: =N66/N$16 -> -0.0059997121 | P66: -28403 | Q66: =P66/P$16 -> -0.023290024 | R66: -2758 | S66: =R66/R$16 -> -0.0014958668 | T66: -10982 | U66: =T66/T$16 -> -0.0039890956 | V66: -11178 | W66: =V66/V$16 -> -0.0055046034 | X66: -11489 | Y66: =X66/X$16 -> -0.0056529866 | Z66: =SUM(H66:X66) -> -119926.7 | AA66: =IFERROR(AVERAGE(B66:X66),0) -> -7495.4185 | AE66: =IFERROR(AVERAGE(T66:X66),0) -> -6729.8019 | AI66: =SUM(T66:X66)*4 -> -134596.04 | AJ66: =AI66/12 -> -11216.336
A67: Partnership Expenses | I67: =H67/H$16 -> 0 | J67: -15036.06 | K67: =J67/J$16 -> -0.0068590048 | L67: -32798.99 | M67: =L67/L$16 -> -0.022288049 | N67: -18678 | O67: =N67/N$16 -> -0.011297774 | P67: -21179 | Q67: =P67/P$16 -> -0.017366455 | R67: -19616 | S67: =R67/R$16 -> -0.010639204 | T67: -9917 | U67: =T67/T$16 -> -0.0036022455 | V67: -17067 | W67: =V67/V$16 -> -0.0084046401 | X67: -18300 | Y67: =X67/X$16 -> -0.0090042349 | Z67: =SUM(H67:X67) -> -152592.13 | AA67: =IFERROR(AVERAGE(B67:X67),0) -> -9537.0082 | AE67: =IFERROR(AVERAGE(T67:X67),0) -> -9056.8024 | AI67: =SUM(T67:X67)*4 -> -181136.05 | AJ67: =AI67/12 -> -15094.671
A68: Other Expenses | H68: -42400.66 | I68: =H68/H$16 -> -0.032618901 | J68: -1313.01 | K68: =J68/J$16 -> -0.00059895624 | L68: 0 | M68: =L68/L$16 -> 0 | N68: 0 | O68: =N68/N$16 -> 0 | P68: 0 | Q68: =P68/P$16 -> 0 | R68: -12 | S68: =R68/R$16 -> -6.5084852e-06 | T68: -2 | U68: =T68/T$16 -> -7.2647888e-07 | V68: 0 | W68: =V68/V$16 -> 0 | X68: 0 | Y68: =X68/X$16 -> 0 | Z68: =SUM(H68:X68) -> -43727.703 | AA68: =IFERROR(AVERAGE(B68:X68),0) -> -2572.2178 | AE68: =IFERROR(AVERAGE(T68:X68),0) -> -0.40000015 | AI68: =SUM(T68:X68)*4 -> -8.0000029 | AJ68: =AI68/12 -> -0.66666691
A69: Total Other Expense | H69: -42400.66 | I69: =H69/H$16 -> -0.032618901 | J69: -41736.36 | K69: =J69/J$16 -> -0.01903889 | L69: -52609.33 | M69: =L69/L$16 -> -0.035749861 | N69: 29027 | O69: =N69/N$16 -> 0.017557581 | P69: -49582 | Q69: =P69/P$16 -> -0.04065648 | R69: -22366 | S69: =R69/R$16 -> -0.012130732 | T69: -20901 | U69: =T69/T$16 -> -0.0075920676 | V69: -28245 | W69: =V69/V$16 -> -0.013909243 | X69: -29285 | Y69: =X69/X$16 -> -0.014409236 | Z69: =SUM(H69:X69) -> -258098.49 | AA69: =IFERROR(AVERAGE(B69:X69),0) -> -15182.264 | AE69: =IFERROR(AVERAGE(T69:X69),0) -> -15686.204 | AI69: =SUM(T69:X69)*4 -> -313724.09 | AJ69: =AI69/12 -> -26143.674
A70: Total Other Income (Expense) | H70: -42130.16 | I70: =H70/H$16 -> -0.032410805 | J70: -41736.34 | K70: =J70/J$16 -> -0.019038881 | L70: -52609.32 | M70: =L70/L$16 -> -0.035749854 | N70: 29027 | O70: =N70/N$16 -> 0.017557581 | P70: -49582 | Q70: =P70/P$16 -> -0.04065648 | R70: -22366 | S70: =R70/R$16 -> -0.012130732 | T70: -20901 | U70: =T70/T$16 -> -0.0075920676 | V70: -28245 | W70: =V70/V$16 -> -0.013909243 | X70: -29285 | Y70: =X70/X$16 -> -0.014409236 | Z70: =SUM(H70:X70) -> -257827.96 | AA70: =IFERROR(AVERAGE(B70:X70),0) -> -15166.351 | AE70: =IFERROR(AVERAGE(T70:X70),0) -> -15686.204 | AI70: =SUM(T70:X70)*4 -> -313724.09 | AJ70: =AI70/12 -> -26143.674
A72: Income Taxes | AI72: =SUM(T72:X72)*4 -> 0 | AJ72: =AI72/12 -> 0
A73: State and Local Taxes | H73: 0 | I73: =H73/H$16 -> 0 | J73: -25.77 | K73: =J73/J$16 -> -1.175551e-05 | L73: 0 | M73: =L73/L$16 -> 0 | N73: 2641 | O73: =N73/N$16 -> 0.0015974634 | P73: 7548 | Q73: =P73/P$16 -> 0.0061892443 | R73: 1516 | S73: =R73/R$16 -> 0.00082223863 | T73: 0 | U73: =T73/T$16 -> 0 | V73: 94 | W73: =V73/V$16 -> 4.6290277e-05 | X73: 441 | Y73: =X73/X$16 -> 0.0002169873 | AA73: =IFERROR(AVERAGE(B73:X73),0) -> 718.48463 | AE73: =IFERROR(AVERAGE(T73:X73),0) -> 107.00001 | AI73: =SUM(T73:X73)*4 -> 2140.0002 | AJ73: =AI73/12 -> 178.33335
A74: Total Income Taxes | H74: 0 | I74: =H74/H$16 -> 0 | J74: -25.77 | K74: =J74/J$16 -> -1.175551e-05 | L74: 0 | M74: =L74/L$16 -> 0 | N74: 2641 | O74: =N74/N$16 -> 0.0015974634 | P74: 7548 | Q74: =P74/P$16 -> 0.0061892443 | R74: 1516 | S74: =R74/R$16 -> 0.00082223863 | T74: 0 | U74: =T74/T$16 -> 0 | V74: 94 | W74: =V74/V$16 -> 4.6290277e-05 | X74: 441 | Y74: =X74/X$16 -> 0.0002169873 | AA74: =IFERROR(AVERAGE(B74:X74),0) -> 718.48463 | AE74: =IFERROR(AVERAGE(T74:X74),0) -> 107.00001 | AI74: =SUM(T74:X74)*4 -> 2140.0002 | AJ74: =AI74/12 -> 178.33335
AI75: =SUM(T75:X75)*4 -> 0 | AJ75: =AI75/12 -> 0
A76: Net Income (Loss) | H76: 85131.05 | I76: =H76/H$16 -> 0.065491464 | J76: 243326.19 | K76: =J76/J$16 -> 0.11099819 | L76: 145694.18 | M76: =L76/L$16 -> 0.099004239 | N76: 164095 | O76: =N76/N$16 -> 0.099256251 | P76: 70493 | Q76: =P76/P$16 -> 0.057803179 | R76: 163431 | S76: =R76/R$16 -> 0.088640687 | T76: 563447 | U76: =T76/T$16 -> 0.20466617 | V76: 400263 | W76: =V76/V$16 -> 0.19710942 | X76: 310591 | Y76: =X76/X$16 -> 0.15282155 | Z76: =SUM(H76:X76) -> 2146472.3 | AA76: =IFERROR(AVERAGE(B76:X76),0) -> 126263.08 | AE76: =IFERROR(AVERAGE(T76:X76),0) -> 254860.28 | AI76: =SUM(T76:X76)*4 -> 5097205.6 | AJ76: =AI76/12 -> 424767.13
A80: Gross Profit % | H80: =IFERROR(H27/H16,0) -> 0.60132016 | J80: =IFERROR(J27/J16,0) -> 0.43323813 | L80: =IFERROR(L27/L16,0) -> 0.58670021 | N80: =IFERROR(N27/N16,0) -> 0.50251445 | P80: =IFERROR(P27/P16,0) -> 0.66234589 | R80: =IFERROR(R27/R16,0) -> 0.50223594 | T80: =IFERROR(T27/T16,0) -> 0.4576748 | V80: =IFERROR(V27/V16,0) -> 0.58059728 | X80: =IFERROR(X27/X16,0) -> 0.59096614 | Z80: =IFERROR(Z27/Z16,0) -> 0.53341536
A81: Net Operating Income % | H81: =H57/H16 -> 0.09790227 | J81: =J57/J16 -> 0.13002532 | L81: =L57/L16 -> 0.13475409 | N81: =N57/N16 -> 0.083296134 | P81: =P57/P16 -> 0.1046489 | R81: =R57/R16 -> 0.10159366 | T81: =T57/T16 -> 0.21225824 | V81: =V57/V16 -> 0.21106495 | X81: =X57/X16 -> 0.16744777 | Z81: =Z57/Z16 -> 0.14648898
A82: Net Profit % | H82: =IFERROR(H76/H16,0) -> 0.065491464 | J82: =IFERROR(J76/J16,0) -> 0.11099819 | L82: =IFERROR(L76/L16,0) -> 0.099004239 | N82: =IFERROR(N76/N16,0) -> 0.099256251 | P82: =IFERROR(P76/P16,0) -> 0.057803179 | R82: =IFERROR(R76/R16,0) -> 0.088640687 | T82: =IFERROR(T76/T16,0) -> 0.20466617 | V82: =IFERROR(V76/V16,0) -> 0.19710942 | X82: =IFERROR(X76/X16,0) -> 0.15282155 | Z82: =IFERROR(Z76/Z16,0) -> 0.13011903
A83: Payroll to Total Revenue % | H83: =IFERROR(H40/H16,0) -> 0.40463592 | J83: =IFERROR(J40/J16,0) -> 0.22671995 | L83: =IFERROR(L40/L16,0) -> 0.34376694 | N83: =IFERROR(N40/N16,0) -> 0.30355132 | P83: =IFERROR(P40/P16,0) -> 0.43798579 | R83: =IFERROR(R40/R16,0) -> 0.28628711 | T83: =IFERROR(T40/T16,0) -> 0.19659572 | V83: =IFERROR(V40/V16,0) -> 0.28574693 | X83: =IFERROR(X40/X16,0) -> 0.3425826 | Z83: =IFERROR(Z40/Z16,0) -> 0.29767064
A84: Payroll to Services Revenue % | H84: =IFERROR(H40/SUM(H12,H14),0) -> 0.6811919 | J84: =IFERROR(J40/SUM(J12,J14),0) -> 0.60939342 | L84: =IFERROR(L40/SUM(L12,L14),0) -> 0.58407904 | N84: =IFERROR(N40/SUM(N12,N14),0) -> 0.5694876 | P84: =IFERROR(P40/SUM(P12,P14),0) -> 0.5704072 | R84: =IFERROR(R40/SUM(R12,R14),0) -> 0.49138651 | T84: =IFERROR(T40/SUM(T12,T14),0) -> 0.49141299 | V84: =IFERROR(V40/SUM(V12,V14),0) -> 0.52722076 | X84: =IFERROR(X40/SUM(X12,X14),0) -> 0.58794168 | Z84: =IFERROR(Z40/SUM(Z12,Z14),0) -> 0.56235831
A85: Payroll to Services + Product Margin % | H85: =H40/(H16-H20-H21) -> 0.52201443 | J85: =J40/(J16-J20-J21) -> 0.42154883 | L85: =L40/(L16-L20-L21) -> 0.4604796 | N85: =N40/(N16-N20-N21) -> 0.47450632 | P85: =P40/(P16-P20-P21) -> 0.51911327 | R85: =R40/(R16-R20-R21) -> 0.43216064 | T85: =T40/(T16-T20-T21) -> 0.36842009 | V85: =V40/(V16-V20-V21) -> 0.40855186 | X85: =X40/(X16-X20-X21) -> 0.47872489 | Z85: =Z40/(Z16-Z20-Z21) -> 0.44897938
A86: Product (One Time) Sales Profit % | H86: =H87/H10 -> 0.39616225 | J86: =J87/J10 -> 0.21853665 | L86: =L87/L10 -> 0.33445892 | N86: =N87/N10 -> 0.19345428 | P86: =P87/P10 -> 0.17797511 | R86: =R87/R10 -> 0.10358039 | T86: =T87/T10 -> 0.16048458 | V86: =V87/V10 -> 0.20156306 | X86: =X87/X10 -> 0.18986933 | Z86: =Z87/Z10 -> 0.20477632
A87: Product (One Time) Sales Profit $ | H87: =H10-H21 -> 160234.25 | J87: =J10-J21 -> 273239.69 | L87: =L10-L21 -> 160569.69 | N87: =N10-N21 -> 133556 | P87: =P10-P21 -> 39343 | R87: =R10-R21 -> 67589 | T87: =T10-T21 -> 235125 | V87: =V10-V21 -> 137362 | X87: =X10-X21 -> 127592 | Z87: =Z10-Z21 -> 1334611.3
A88: Product Sales % of Total Revenue
A91: On Separate Tab
A92: Variance to Budget
A93: Variance to trend month over month
A94: Variance to trend month 3 month avg
A96: Sales $/Profit Needed to Break Even
A97: Recurring Revenue | H97: =SUM(H11:H14) -> 838207.92 | J97: =SUM(J11:J14) -> 902971.1 | L97: =SUM(L11:L14) -> 927818.58 | N97: =SUM(N11:N14) -> 920799 | P97: =SUM(P11:P14) -> 991054 | R97: =SUM(R11:R14) -> 1146068 | T97: =SUM(T11:T14) -> 1224088 | V97: =SUM(V11:V14) -> 1270711 | X97: =SUM(X11:X14) -> 1319642 | Z97: =SUM(H97:X97) -> 9541359.6
A98: Total Expenses (not including COGS or Subcontractor) | B98: *look for rec. resale exp. | H98: =H22+H24+H36+H38+H40+H42+H49+H52 -> 880331.95 | J98: =J22+J24+J36+J38+J40+J42+J49+J52 -> 897877.21 | L98: =L22+L24+L36+L38+L40+L42+L49+L52 -> 892436.4 | N98: =N22+N24+N36+N38+N40+N42+N49+N52 -> 911286 | P98: =P22+P24+P36+P38+P40+P42+P49+P52 -> 889247 | R98: =R22+R24+R36+R38+R40+R42+R49+R52 -> 1018342 | T98: =T22+T24+T36+T38+T40+T42+T49+T52 -> 857378 | V98: =V22+V24+V36+V38+V40+V42+V49+V52 -> 979666 | X98: =X22+X24+X36+X38+X40+X42+X49+X52 -> 1093957 | Z98: =SUM(H98:X98) -> 8420521.6
A99: Recurring Profit/Loss (GAP) | H99: =H97-H98 -> -42124.03 | J99: =J97-J98 -> 5093.89 | L99: =L97-L98 -> 35382.18 | N99: =N97-N98 -> 9513 | P99: =P97-P98 -> 101807 | R99: =R97-R98 -> 127726 | T99: =T97-T98 -> 366710 | V99: =V97-V98 -> 291045 | X99: =X97-X98 -> 225685 | Z99: =Z97-Z98 -> 1120838
A100: Product/Project Sales needed @ 15% to Break Even | H100: =H99/0.15 -> -280826.87 | J100: =J99/0.15 -> 33959.267 | L100: =L99/0.15 -> 235881.2 | N100: =N99/0.15 -> 63420 | P100: =P99/0.15 -> 678713.33 | R100: =R99/0.15 -> 851506.67 | T100: =T99/0.15 -> 2444733.3 | V100: =V99/0.15 -> 1940300 | X100: =X99/0.15 -> 1504566.7
A101: 15% of Revenue (Profit Target) | H101: =H16*0.15 -> 194982.01
A102: Product/Project Sales Needed for 15% Profit
A103: Minimum Rev. Target
A104: *Other cost when we sell more (Commission) %
A107: Difference between recurring Profit/Loss vs Total P/L | H107: =H57-H99 -> 169385.24 | J107: =J57-J99 -> 279942.87 | L107: =L57-L99 -> 162921.32 | N107: =N57-N99 -> 128196 | P107: =P57-P99 -> 25816 | R107: =R57-R99 -> 59587 | T107: =T57-T99 -> 217638 | V107: =V57-V99 -> 137557 | X107: =X57-X99 -> 114632 | Z107: =Z57-Z99 -> 1295676.5 | AA107: *This section needs works - doesn't add up on Product Sales only $658k
A108: Project Services | H108: =H13 -> 60454.51 | J108: =J13 -> 64037.92 | L108: =L13 -> 43186.08 | N108: =N13 -> 27190 | P108: =P13 -> 43417 | R108: =R13 -> 53573 | T108: =T13 -> 98569 | V108: =V13 -> 139411 | X108: =X13 -> 106978 | Z108: =Z13 -> 636816.8 | AA108: *This is profit made from Project Engineers
A109: Difference between P&L gap and project | H109: =H107-H108 -> 108930.73 | J109: =J107-J108 -> 215904.95 | L109: =L107-L108 -> 119735.24 | N109: =N107-N108 -> 101006 | P109: =P107-P108 -> -17601 | R109: =R107-R108 -> 6014 | T109: =T107-T108 -> 119069 | V109: =V107-V108 -> -1854 | X109: =X107-X108 -> 7654 | Z109: =Z107-Z108 -> 658859.7 | AA109: *This is profit made from Product Sales Only
A111: Selling Expenses broken out
A114: To Do's
A115: Dennis to give daily payroll calculations
A119: Profit Goals | B119: Monthly | D119: Annual
A120: California | B120: 250000 | D120: =B120*12 -> 3000000
A121: Ohio | B121: 75000 | D121: =B121*12 -> 900000
B122: =SUM(B120:B121) -> 325000 | C122: =SUM(C120:C121) -> 0 | D122: =SUM(D120:D121) -> 3900000
F125: 481 | H125: -375 | J125: =F125+H125 -> 106

Sheet Fresno

Sheet Ohio - old format
B1: Month 1 ($) | C1: Month 1 (%) | D1: Month 2 ($) | E1: Month 2 (%) | F1: Month 3 ($) | G1: Month 3 (%) | H1: Month 4 ($) | I1: Month 4 (%) | J1: Month 5 ($) | K1: Month 5 (%) | L1: Month 6 ($) | M1: Month 6 (%) | N1: Month 7 ($) | O1: Month 7 (%) | P1: Month 8 ($) | Q1: Month 8 (%) | R1: Month 9 ($) | S1: Month 9 (%) | T1: Month 10 ($) | U1: Month 10 (%) | V1: Month 11 ($) | W1: Month 11 (%) | X1: Month 12 ($) | Y1: Month 12 (%) | Z1: 9 Month Totals | AA1: 9 Month Average | AC1: 9 Month Sparkline | AD1: Last 3 Months Average | AE1: Last 3 Months Sparkline | AF1: Target $ | AG1: Target % | AH1: Annual Budget Q1 * 4 | AI1: Monthly Budget
A2: Location | B2: All Locations | D2: All Locations | F2: All Locations | H2: All Locations | J2: All Locations | L2: All Locations | N2: All Locations | P2: All Locations | R2: All Locations | T2: All Locations | V2: All Locations | X2: All Locations
A3: Month | H3: 07/31/2022 | J3: 08/31/2022 | L3: 09/30/2022 | N3: 10/31/2022 | P3: 11/30/2022 | R3: 12/31/2022 | T3: 01/31/2023 | V3: 02/28/2023 | X3: 03/31/2023
A4: Days in Month | H4: 31 | J4: 31 | L4: 30 | N4: 31 | P4: 30 | R4: 31 | T4: 31 | V4: 28 | X4: 31
A5: Quarter | H5: 3 | J5: 3 | L5: 3 | N5: 4 | P5: 4 | R5: 4 | T5: 1 | V5: 1 | X5: 1
A6: Year | H6: 2022 | J6: 2022 | L6: 2022 | N6: 2022 | P6: 2022 | R6: 2022 | T6: 2023 | V6: 2023 | X6: 2023
A8: Revenue
A9: Subcontracted Services | I9: =H9/H$16 -> 0 | K9: =J9/J$16 -> 0 | L9: 0 | M9: =L9/L$16 -> 0 | N9: 0 | O9: =N9/N$16 -> 0 | P9: 0 | Q9: =P9/#REF! -> #REF! | R9: 38 | S9: =R9/#REF! -> #REF! | T9: 0 | U9: =T9/#REF! -> #REF! | V9: 1592 | W9: =V9/#REF! -> #REF! | X9: 145 | Y9: =X9/X$16 -> 0.00036998574 | Z9: =B9+D9+F9+H9+J9+L9+N9+P9+R9+T9+V9+X9 -> 1775 | AA9: =IFERROR(AVERAGE(B9,D9,F9,H9,J9,L9,N9,P9,R9,T9,V9,X9),0) -> 253.57143 | AD9: =IFERROR(AVERAGE(T9:X9),0) -> 0 | AH9: =(T9+V9+X9)*4 -> 6948 | AI9: =AH9/12 -> 579
A10: Product Sales | H10: 150185.67 | I10: =H10/H$16 -> 0.5037856 | J10: 717329.98 | K10: =J10/J$16 -> 0.81870829 | L10: 244195.99 | M10: =L10/L$16 -> 0.62562321 | N10: 478815 | O10: =N10/N$16 -> 0.74824781 | P10: 0 | Q10: =P10/#REF! -> #REF! | R10: 142302 | S10: =R10/#REF! -> #REF! | T10: 81066 | U10: =T10/#REF! -> #REF! | V10: 442457 | W10: =V10/#REF! -> #REF! | X10: 153161 | Y10: =X10/X$16 -> 0.39080955 | Z10: =B10+D10+F10+H10+J10+L10+N10+P10+R10+T10+V10+X10 -> 2409512.6 | AA10: =IFERROR(AVERAGE(B10,D10,F10,H10,J10,L10,N10,P10,R10,T10,V10,X10),0) -> 267723.63 | AD10: =IFERROR(AVERAGE(T10:X10),0) -> 0 | AH10: =(T10+V10+X10)*4 -> 2706736 | AI10: =AH10/12 -> 225561.33
A11: Commissions | H11: 3022.7 | I11: =H11/H$16 -> 0.010139401 | J11: 14518.66 | K11: =J11/J$16 -> 0.016570543 | L11: 2020.05 | M11: =L11/L$16 -> 0.0051753109 | N11: 974 | O11: =N11/N$16 -> 0.0015220772 | P11: 0 | Q11: =P11/#REF! -> #REF! | R11: 4410 | S11: =R11/#REF! -> #REF! | T11: 0 | U11: =T11/#REF! -> #REF! | V11: 0 | W11: =V11/#REF! -> #REF! | X11: 0 | Y11: =X11/X$16 -> 0 | Z11: =B11+D11+F11+H11+J11+L11+N11+P11+R11+T11+V11+X11 -> 24945.41 | AA11: =IFERROR(AVERAGE(B11,D11,F11,H11,J11,L11,N11,P11,R11,T11,V11,X11),0) -> 2771.7122 | AD11: =IFERROR(AVERAGE(T11:X11),0) -> 0 | AH11: =(T11+V11+X11)*4 -> 0 | AI11: =AH11/12 -> 0
A12: Cloud | I12: =H12/H$16 -> 0 | J12: 124424.64 | K12: =J12/J$16 -> 0.14200924 | L12: 140620.16 | M12: =L12/L$16 -> 0.36026486 | N12: 699 | O12: =N12/N$16 -> 0.0010923326 | P12: 136857 | Q12: =P12/#REF! -> #REF! | R12: 0 | S12: =R12/#REF! -> #REF! | T12: 43961 | U12: =T12/#REF! -> #REF! | V12: 7683 | W12: =V12/#REF! -> #REF! | X12: 31895 | Y12: =X12/X$16 -> 0.081384104 | Z12: =B12+D12+F12+H12+J12+L12+N12+P12+R12+T12+V12+X12 -> 486139.8 | AA12: =IFERROR(AVERAGE(B12,D12,F12,H12,J12,L12,N12,P12,R12,T12,V12,X12),0) -> 60767.475 | AD12: =IFERROR(AVERAGE(T12:X12),0) -> 0 | AH12: =(T12+V12+X12)*4 -> 334156 | AI12: =AH12/12 -> 27846.333
A13: Project Services | H13: 2440 | I13: =H13/H$16 -> 0.0081847812 | J13: 20326.59 | K13: =J13/J$16 -> 0.023199292 | L13: 2812 | M13: =L13/L$16 -> 0.0072042643 | N13: 21691 | O13: =N13/N$16 -> 0.033896689 | P13: 5050 | Q13: =P13/#REF! -> #REF! | R13: 1270 | S13: =R13/#REF! -> #REF! | T13: 59765 | U13: =T13/#REF! -> #REF! | V13: 113090 | W13: =V13/#REF! -> #REF! | X13: 72796 | Y13: =X13/X$16 -> 0.18574815 | Z13: =B13+D13+F13+H13+J13+L13+N13+P13+R13+T13+V13+X13 -> 299240.59 | AA13: =IFERROR(AVERAGE(B13,D13,F13,H13,J13,L13,N13,P13,R13,T13,V13,X13),0) -> 33248.954 | AD13: =IFERROR(AVERAGE(T13:X13),0) -> 0 | AH13: =(T13+V13+X13)*4 -> 982604 | AI13: =AH13/12 -> 81883.667
A14: Managed IT Services | H14: 142465.89 | I14: =H14/H$16 -> 0.47789022 | J14: -427.01 | K14: =J14/J$16 -> -0.00048735817 | L14: 676.18 | M14: =L14/L$16 -> 0.001732354 | N14: 137736 | O14: =N14/N$16 -> 0.21524109 | P14: 0 | Q14: =P14/#REF! -> #REF! | R14: 250758 | S14: =R14/#REF! -> #REF! | T14: 102223 | U14: =T14/#REF! -> #REF! | V14: 101637 | W14: =V14/#REF! -> #REF! | X14: 133979 | Y14: =X14/X$16 -> 0.34186427 | Z14: =B14+D14+F14+H14+J14+L14+N14+P14+R14+T14+V14+X14 -> 869048.06 | AA14: =IFERROR(AVERAGE(B14,D14,F14,H14,J14,L14,N14,P14,R14,T14,V14,X14),0) -> 96560.896 | AD14: =IFERROR(AVERAGE(T14:X14),0) -> 0 | AH14: =(T14+V14+X14)*4 -> 1351356 | AI14: =AH14/12 -> 112613
