Workbook
Name NB_Monthly_Recurring_Private_Cloud_CA: #REF!
Name NB_Monthly_Recurring_Private_Cloud_OH: #REF!
Name NB_Monthly_Recurring_Resale_CA: #REF!
Name NB_Monthly_Recurring_Resale_OH: #REF!
Name NB_Monthly_Recurring_Services_CA: #REF!
Name NB_Monthly_Recurring_Services_OH: #REF!
Name WA_Monthly_Recurring_Private_Cloud_CA: #REF!
Name WA_Monthly_Recurring_Resale_CA: #REF!
Name WA_Monthly_Recurring_Resale_OH: #REF!
Name WA_Monthly_Recurring_Services_CA: #REF!
Name WA_Monthly_Recurring_Services_OH: #REF!

Sheet 2024 Bdg vs Actual All
I1: Budget Vs Actual | M1: Variance | N1: (Red) | O1: Over budget | Q1: Budget Vs Actual
I2: Income Statement - All | N2: Black | O2: Under budget | Q2: Income Statement - All
I3: 2024 | Q3: 2024
AB4: x
F7: Budget
F8: Year 1* | H8: January | L8: February | P8: March | T8: April | X8: May | AB8: June | AF8: July | AJ8: August | AN8: September | AR8: October | AV8: November | AZ8: December | BG8: YTD
A9: Year Ending | F9: 45657 | H9: Budget | I9: Actual | J9: Var | L9: Budget | M9: Actual | N9: Variance | O9: Notes | P9: Budget | Q9: Actual | R9: Variance | S9: Notes | T9: Budget | U9: Actual | V9: Variance | W9: Notes | X9: Budget | Y9: Actual | Z9: Variance | AA9: Notes | AB9: Budget | AC9: Actual | AD9: Variance | AE9: Notes | AF9: Budget | AG9: Actual | AH9: Variance | AI9: Notes | AJ9: Budget | AK9: Actual | AL9: Variance | AM9: Notes | AN9: Budget | AO9: Actual | AP9: Variance | AQ9: Notes | AR9: Budget | AS9: Actual | AT9: Variance | AU9: Notes | AV9: Budget | AW9: Actual | AX9: Variance | AY9: Notes | AZ9: Budget | BA9: Actual | BB9: Variance | BC9: Notes | BE9: Questions | BG9: Budget | BH9: Actual | BI9: Variance
N10: (Red) over budget
A11: **Gross Sales** | F11: =H11+L11+P11+T11+X11+AB11+AF11+AJ11+AN11+AR11+AV11+AZ11 -> 27189475 | H11: =SUM(H14:H23) -> 2263097.8 | I11: =SUM(I14:I23) -> 1375722.6 | J11: =+I11-H11 -> -887375.27 | L11: =SUM(L14:L23) -> 2193476.8 | M11: =SUM(M14:M23) -> 1708668 | N11: =+M11-L11 -> -484808.83 | P11: =SUM(P14:P23) -> 2167400 | Q11: =SUM(Q14:Q23) -> 1256746 | R11: =+Q11-P11 -> -910654 | T11: =SUM(T14:T23) -> 2193700 | U11: =SUM(U14:U23) -> 1740436 | V11: =+U11-T11 -> -453264 | X11: =SUM(X14:X23) -> 2215400 | Y11: =SUM(Y14:Y23) -> 1510467 | Z11: =+Y11-X11 -> -704933 | AB11: =SUM(AB14:AB23) -> 2258900 | AC11: =SUM(AC14:AC23) -> 2578281 | AD11: =+AC11-AB11 -> 319381 | AF11: =SUM(AF14:AF23) -> 2278300 | AG11: =SUM(AG14:AG23) -> 2399002 | AH11: =+AG11-AF11 -> 120702 | AJ11: =SUM(AJ14:AJ23) -> 2289100 | AK11: =SUM(AK14:AK23) -> 2786533 | AL11: =+AK11-AJ11 -> 497433 | AN11: =SUM(AN14:AN23) -> 2304800 | AO11: =SUM(AO14:AO23) -> 1407338 | AP11: =+AO11-AN11 -> -897462 | AR11: =SUM(AR14:AR23) -> 2324400 | AS11: =SUM(AS14:AS23) -> 1520174 | AT11: =+AS11-AR11 -> -804226 | AV11: =SUM(AV14:AV23) -> 2340800 | AW11: =SUM(AW14:AW23) -> 1802062 | AX11: =+AW11-AV11 -> -538738 | AZ11: =SUM(AZ14:AZ23) -> 2360100 | BA11: =SUM(BA14:BA23) -> 1196916 | BB11: =+BA11-AZ11 -> -1163184 | BG11: =+P11+L11+H11+T11+X11+AB11+AF11+AJ11+AN11+AR11+AV11+AZ11 -> 27189475 | BH11: =+Q11+M11+I11+U11+Y11+AC11+AG11+AK11+AO11+AS11+AW11+BA11 -> 21282346 | BI11: =+BH11-BG11 -> -5907129.1
A13: Services
A14: Monthly Recurring Services | F14: =H14+L14+P14+T14+X14+AB14+AF14+AJ14+AN14+AR14+AV14+AZ14 -> 7002838 | H14: =+'2024 Bdg vs Actual-CA'!O14+'2024 Bdg vs Actual -OH'!O14 -> 607265.97 | I14: 519442 | J14: =+I14-H14 -> -87823.971 | K14: How is recurring services so much less? It should be a repeat of December and IR was modeled out? | L14: =+'2024 Bdg vs Actual-CA'!S14+'2024 Bdg vs Actual -OH'!S14 -> 519372 | M14: 533709 | N14: =+M14-L14 -> 14337 | O14: Budget for February is updated based on actual MRR from last meeting D | P14: =ROUND(+'2024 Bdg vs Actual-CA'!W14+'2024 Bdg vs Actual -OH'!W14,-2) -> 516400 | Q14: 522308 | R14: =+Q14-P14 -> 5908 | S14: Budget for March is updated based on actual MRR from last meeting D | T14: =ROUND(+'2024 Bdg vs Actual-CA'!AA14+'2024 Bdg vs Actual -OH'!AA14,-2) -> 534200 | U14: 514855 | V14: =+U14-T14 -> -19345 | X14: =ROUND(+'2024 Bdg vs Actual-CA'!AE14+'2024 Bdg vs Actual -OH'!AE14,-2) -> 546000 | Y14: 444256 | Z14: =+Y14-X14 -> -101744 | AA14: See location for notes | AB14: =ROUND(+'2024 Bdg vs Actual-CA'!AI14+'2024 Bdg vs Actual -OH'!AI14,-2) -> 575100 | AC14: 513444 | AD14: =+AC14-AB14 -> -61656 | AE14: See location for notes | AF14: =ROUND(+'2024 Bdg vs Actual-CA'!AM14+'2024 Bdg vs Actual -OH'!AM14,-2) -> 590000 | AG14: 505165 | AH14: =+AG14-AF14 -> -84835 | AI14: See location for notes | AJ14: =ROUND(+'2024 Bdg vs Actual-CA'!AQ14+'2024 Bdg vs Actual -OH'!AQ14,-2) -> 596300 | AK14: 534210 | AL14: =+AK14-AJ14 -> -62090 | AM14: See location for notes | AN14: =ROUND(+'2024 Bdg vs Actual-CA'!AU14+'2024 Bdg vs Actual -OH'!AU14,-2) -> 608000 | AO14: 521714 | AP14: =+AO14-AN14 -> -86286 | AQ14: See location for notes | AR14: =ROUND(+'2024 Bdg vs Actual-CA'!AY14+'2024 Bdg vs Actual -OH'!AY14,-2) -> 623400 | AS14: 507617 | AT14: =+AS14-AR14 -> -115783 | AU14: See location for notes | AV14: =ROUND(+'2024 Bdg vs Actual-CA'!BC14+'2024 Bdg vs Actual -OH'!BC14,-2) -> 636300 | AW14: 551943 | AX14: =+AW14-AV14 -> -84357 | AZ14: =ROUND(+'2024 Bdg vs Actual-CA'!BG14+'2024 Bdg vs Actual -OH'!BG14,-2) -> 650500 | BA14: 577780 | BB14: =+BA14-AZ14 -> -72720 | BC14: See location for notes | BG14: =+P14+L14+H14+T14+X14+AB14+AF14+AJ14+AN14+AR14+AV14+AZ14 -> 7002838 | BH14: =+Q14+M14+I14+U14+Y14+AC14+AG14+AK14+AO14+AS14+AW14+BA14 -> 6246443 | BI14: =+BH14-BG14 -> -756394.97
A15: Monthly Recurring Private Cloud | F15: =H15+L15+P15+T15+X15+AB15+AF15+AJ15+AN15+AR15+AV15+AZ15 -> 255753.84 | H15: =+'2024 Bdg vs Actual-CA'!O15+'2024 Bdg vs Actual -OH'!O15 -> 26611.835 | I15: 21937 | J15: =+I15-H15 -> -4674.835 | L15: =+'2024 Bdg vs Actual-CA'!S15+'2024 Bdg vs Actual -OH'!S15 -> 18042 | M15: 24564 | N15: =+M15-L15 -> 6522 | P15: =ROUND(+'2024 Bdg vs Actual-CA'!W15+'2024 Bdg vs Actual -OH'!W15,-2) -> 18000 | Q15: 18807 | R15: =+Q15-P15 -> 807 | T15: =ROUND(+'2024 Bdg vs Actual-CA'!AA15+'2024 Bdg vs Actual -OH'!AA15,-2) -> 18500 | U15: 20511 | V15: =+U15-T15 -> 2011 | X15: =ROUND(+'2024 Bdg vs Actual-CA'!AE15+'2024 Bdg vs Actual -OH'!AE15,-2) -> 18000 | Y15: 20275 | Z15: =+Y15-X15 -> 2275 | AB15: =ROUND(+'2024 Bdg vs Actual-CA'!AI15+'2024 Bdg vs Actual -OH'!AI15,-2) -> 20900 | AC15: 18128 | AD15: =+AC15-AB15 -> -2772 | AF15: =ROUND(+'2024 Bdg vs Actual-CA'!AM15+'2024 Bdg vs Actual -OH'!AM15,-2) -> 21400 | AG15: 18272 | AH15: =+AG15-AF15 -> -3128 | AJ15: =ROUND(+'2024 Bdg vs Actual-CA'!AQ15+'2024 Bdg vs Actual -OH'!AQ15,-2) -> 21800 | AK15: 18250 | AL15: =+AK15-AJ15 -> -3550 | AN15: =ROUND(+'2024 Bdg vs Actual-CA'!AU15+'2024 Bdg vs Actual -OH'!AU15,-2) -> 22300 | AO15: 22059 | AP15: =+AO15-AN15 -> -241 | AR15: =ROUND(+'2024 Bdg vs Actual-CA'!AY15+'2024 Bdg vs Actual -OH'!AY15,-2) -> 22700 | AS15: 26554 | AT15: =+AS15-AR15 -> 3854 | AV15: =ROUND(+'2024 Bdg vs Actual-CA'!BC15+'2024 Bdg vs Actual -OH'!BC15,-2) -> 23200 | AW15: 17924 | AX15: =+AW15-AV15 -> -5276 | AZ15: =ROUND(+'2024 Bdg vs Actual-CA'!BG15+'2024 Bdg vs Actual -OH'!BG15,-2) -> 24300 | BA15: 21850 | BB15: =+BA15-AZ15 -> -2450 | BG15: =+P15+L15+H15+T15+X15+AB15+AF15+AJ15+AN15+AR15+AV15+AZ15 -> 255753.84 | BH15: =+Q15+M15+I15+U15+Y15+AC15+AG15+AK15+AO15+AS15+AW15+BA15 -> 249131 | BI15: =+BH15-BG15 -> -6622.835
A16: Monthly Recurring Resale | F16: =H16+L16+P16+T16+X16+AB16+AF16+AJ16+AN16+AR16+AV16+AZ16 -> 2768443.7 | H16: =+'2024 Bdg vs Actual-CA'!O16+'2024 Bdg vs Actual -OH'!O16 -> 199886.7 | I16: 226368 | J16: =+I16-H16 -> 26481.298 | L16: =+'2024 Bdg vs Actual-CA'!S16+'2024 Bdg vs Actual -OH'!S16 -> 216957 | M16: 220002 | N16: =+M16-L16 -> 3045 | P16: =ROUND(+'2024 Bdg vs Actual-CA'!W16+'2024 Bdg vs Actual -OH'!W16,-2) -> 203600 | Q16: 206276 | R16: =+Q16-P16 -> 2676 | T16: =ROUND(+'2024 Bdg vs Actual-CA'!AA16+'2024 Bdg vs Actual -OH'!AA16,-2) -> 211600 | U16: 218674 | V16: =+U16-T16 -> 7074 | X16: =ROUND(+'2024 Bdg vs Actual-CA'!AE16+'2024 Bdg vs Actual -OH'!AE16,-2) -> 222000 | Y16: 216193 | Z16: =+Y16-X16 -> -5807 | AB16: =ROUND(+'2024 Bdg vs Actual-CA'!AI16+'2024 Bdg vs Actual -OH'!AI16,-2) -> 233500 | AC16: 221605 | AD16: =+AC16-AB16 -> -11895 | AF16: =ROUND(+'2024 Bdg vs Actual-CA'!AM16+'2024 Bdg vs Actual -OH'!AM16,-2) -> 237500 | AG16: 221399 | AH16: =+AG16-AF16 -> -16101 | AJ16: =ROUND(+'2024 Bdg vs Actual-CA'!AQ16+'2024 Bdg vs Actual -OH'!AQ16,-2) -> 241600 | AK16: 219968 | AL16: =+AK16-AJ16 -> -21632 | AN16: =ROUND(+'2024 Bdg vs Actual-CA'!AU16+'2024 Bdg vs Actual -OH'!AU16,-2) -> 245100 | AO16: 225338 | AP16: =+AO16-AN16 -> -19762 | AR16: =ROUND(+'2024 Bdg vs Actual-CA'!AY16+'2024 Bdg vs Actual -OH'!AY16,-2) -> 248900 | AS16: 234350 | AT16: =+AS16-AR16 -> -14550 | AV16: =ROUND(+'2024 Bdg vs Actual-CA'!BC16+'2024 Bdg vs Actual -OH'!BC16,-2) -> 251900 | AW16: 238967 | AX16: =+AW16-AV16 -> -12933 | AZ16: =ROUND(+'2024 Bdg vs Actual-CA'!BG16+'2024 Bdg vs Actual -OH'!BG16,-2) -> 255900 | BA16: 241544 | BB16: =+BA16-AZ16 -> -14356 | BG16: =+P16+L16+H16+T16+X16+AB16+AF16+AJ16+AN16+AR16+AV16+AZ16 -> 2768443.7 | BH16: =+Q16+M16+I16+U16+Y16+AC16+AG16+AK16+AO16+AS16+AW16+BA16 -> 2690684 | BI16: =+BH16-BG16 -> -77759.702
A17: IT Project Services | F17: =H17+L17+P17+T17+X17+AB17+AF17+AJ17+AN17+AR17+AV17+AZ17 -> 1447392.5 | H17: =+'2024 Bdg vs Actual-CA'!O17+'2024 Bdg vs Actual -OH'!O17 -> 120784.5 | I17: 47765.57 | J17: =+I17-H17 -> -73018.93 | L17: =+'2024 Bdg vs Actual-CA'!S17+'2024 Bdg vs Actual -OH'!S17 -> 118608 | M17: 91984 | N17: =+M17-L17 -> -26624 | O17: No changes to project forecast | P17: =ROUND(+'2024 Bdg vs Actual-CA'!W17+'2024 Bdg vs Actual -OH'!W17,-2) -> 120800 | Q17: 85429 | R17: =+Q17-P17 -> -35371 | S17: No changes to project forecast | T17: =ROUND(+'2024 Bdg vs Actual-CA'!AA17+'2024 Bdg vs Actual -OH'!AA17,-2) -> 120800 | U17: 185976 | V17: =+U17-T17 -> 65176 | X17: =ROUND(+'2024 Bdg vs Actual-CA'!AE17+'2024 Bdg vs Actual -OH'!AE17,-2) -> 120800 | Y17: 173843 | Z17: =+Y17-X17 -> 53043 | AB17: =ROUND(+'2024 Bdg vs Actual-CA'!AI17+'2024 Bdg vs Actual -OH'!AI17,-2) -> 120800 | AC17: 148908 | AD17: =+AC17-AB17 -> 28108 | AF17: =ROUND(+'2024 Bdg vs Actual-CA'!AM17+'2024 Bdg vs Actual -OH'!AM17,-2) -> 120800 | AG17: 190189 | AH17: =+AG17-AF17 -> 69389 | AJ17: =ROUND(+'2024 Bdg vs Actual-CA'!AQ17+'2024 Bdg vs Actual -OH'!AQ17,-2) -> 120800 | AK17: 344196 | AL17: =+AK17-AJ17 -> 223396 | AN17: =ROUND(+'2024 Bdg vs Actual-CA'!AU17+'2024 Bdg vs Actual -OH'!AU17,-2) -> 120800 | AO17: 100536 | AP17: =+AO17-AN17 -> -20264 | AR17: =ROUND(+'2024 Bdg vs Actual-CA'!AY17+'2024 Bdg vs Actual -OH'!AY17,-2) -> 120800 | AS17: 90248 | AT17: =+AS17-AR17 -> -30552 | AV17: =ROUND(+'2024 Bdg vs Actual-CA'!BC17+'2024 Bdg vs Actual -OH'!BC17,-2) -> 120800 | AW17: 46132 | AX17: =+AW17-AV17 -> -74668 | AZ17: =ROUND(+'2024 Bdg vs Actual-CA'!BG17+'2024 Bdg vs Actual -OH'!BG17,-2) -> 120800 | BA17: 39163 | BB17: =+BA17-AZ17 -> -81637 | BG17: =+P17+L17+H17+T17+X17+AB17+AF17+AJ17+AN17+AR17+AV17+AZ17 -> 1447392.5 | BH17: =+Q17+M17+I17+U17+Y17+AC17+AG17+AK17+AO17+AS17+AW17+BA17 -> 1544369.6 | BI17: =+BH17-BG17 -> 96977.07
A18: Subcontracted Services | F18: =H18+L18+P18+T18+X18+AB18+AF18+AJ18+AN18+AR18+AV18+AZ18 -> 696225 | H18: =+'2024 Bdg vs Actual-CA'!O18+'2024 Bdg vs Actual -OH'!O18 -> 56763 | I18: 5809 | J18: =+I18-H18 -> -50954 | L18: =+'2024 Bdg vs Actual-CA'!S18+'2024 Bdg vs Actual -OH'!S18 -> 71462 | M18: 74654 | N18: =+M18-L18 -> 3192 | P18: =ROUND(+'2024 Bdg vs Actual-CA'!W18+'2024 Bdg vs Actual -OH'!W18,-2) -> 56800 | Q18: 16220 | R18: =+Q18-P18 -> -40580 | T18: =ROUND(+'2024 Bdg vs Actual-CA'!AA18+'2024 Bdg vs Actual -OH'!AA18,-2) -> 56800 | U18: 10805 | V18: =+U18-T18 -> -45995 | X18: =ROUND(+'2024 Bdg vs Actual-CA'!AE18+'2024 Bdg vs Actual -OH'!AE18,-2) -> 56800 | Y18: 14230 | Z18: =+Y18-X18 -> -42570 | AB18: =ROUND(+'2024 Bdg vs Actual-CA'!AI18+'2024 Bdg vs Actual -OH'!AI18,-2) -> 56800 | AC18: 19715 | AD18: =+AC18-AB18 -> -37085 | AF18: =ROUND(+'2024 Bdg vs Actual-CA'!AM18+'2024 Bdg vs Actual -OH'!AM18,-2) -> 56800 | AG18: 295714 | AH18: =+AG18-AF18 -> 238914 | AJ18: =ROUND(+'2024 Bdg vs Actual-CA'!AQ18+'2024 Bdg vs Actual -OH'!AQ18,-2) -> 56800 | AK18: 132645 | AL18: =+AK18-AJ18 -> 75845 | AN18: =ROUND(+'2024 Bdg vs Actual-CA'!AU18+'2024 Bdg vs Actual -OH'!AU18,-2) -> 56800 | AO18: 24969 | AP18: =+AO18-AN18 -> -31831 | AR18: =ROUND(+'2024 Bdg vs Actual-CA'!AY18+'2024 Bdg vs Actual -OH'!AY18,-2) -> 56800 | AS18: 32496 | AT18: =+AS18-AR18 -> -24304 | AV18: =ROUND(+'2024 Bdg vs Actual-CA'!BC18+'2024 Bdg vs Actual -OH'!BC18,-2) -> 56800 | AW18: 12751 | AX18: =+AW18-AV18 -> -44049 | AZ18: =ROUND(+'2024 Bdg vs Actual-CA'!BG18+'2024 Bdg vs Actual -OH'!BG18,-2) -> 56800 | BA18: 25687 | BB18: =+BA18-AZ18 -> -31113 | BG18: =+P18+L18+H18+T18+X18+AB18+AF18+AJ18+AN18+AR18+AV18+AZ18 -> 696225 | BH18: =+Q18+M18+I18+U18+Y18+AC18+AG18+AK18+AO18+AS18+AW18+BA18 -> 665695 | BI18: =+BH18-BG18 -> -30530
A21: Product Sales
A22: Product Resale | F22: =H22+L22+P22+T22+X22+AB22+AF22+AJ22+AN22+AR22+AV22+AZ22 -> 14789905 | H22: =+'2024 Bdg vs Actual-CA'!O22+'2024 Bdg vs Actual -OH'!O22 -> 1232452.5 | I22: 542234 | J22: =+I22-H22 -> -690218.5 | L22: =+'2024 Bdg vs Actual-CA'!S22+'2024 Bdg vs Actual -OH'!S22 -> 1232452.5 | M22: 756837 | N22: =+M22-L22 -> -475615.5 | O22: No changes yet to product forecast | P22: =ROUND(+'2024 Bdg vs Actual-CA'!W22+'2024 Bdg vs Actual -OH'!W22,-2) -> 1232500 | Q22: 392152 | R22: =+Q22-P22 -> -840348 | S22: No changes yet to product forecast | T22: =ROUND(+'2024 Bdg vs Actual-CA'!AA22+'2024 Bdg vs Actual -OH'!AA22,-2) -> 1232500 | U22: 784945 | V22: =+U22-T22 -> -447555 | X22: =ROUND(+'2024 Bdg vs Actual-CA'!AE22+'2024 Bdg vs Actual -OH'!AE22,-2) -> 1232500 | Y22: 629848 | Z22: =+Y22-X22 -> -602652 | AB22: =ROUND(+'2024 Bdg vs Actual-CA'!AI22+'2024 Bdg vs Actual -OH'!AI22,-2) -> 1232500 | AC22: 1645749 | AD22: =+AC22-AB22 -> 413249 | AF22: =ROUND(+'2024 Bdg vs Actual-CA'!AM22+'2024 Bdg vs Actual -OH'!AM22,-2) -> 1232500 | AG22: 1162232 | AH22: =+AG22-AF22 -> -70268 | AJ22: =ROUND(+'2024 Bdg vs Actual-CA'!AQ22+'2024 Bdg vs Actual -OH'!AQ22,-2) -> 1232500 | AK22: 1529705 | AL22: =+AK22-AJ22 -> 297205 | AN22: =ROUND(+'2024 Bdg vs Actual-CA'!AU22+'2024 Bdg vs Actual -OH'!AU22,-2) -> 1232500 | AO22: 494557 | AP22: =+AO22-AN22 -> -737943 | AR22: =ROUND(+'2024 Bdg vs Actual-CA'!AY22+'2024 Bdg vs Actual -OH'!AY22,-2) -> 1232500 | AS22: 621149 | AT22: =+AS22-AR22 -> -611351 | AV22: =ROUND(+'2024 Bdg vs Actual-CA'!BC22+'2024 Bdg vs Actual -OH'!BC22,-2) -> 1232500 | AW22: 927230 | AX22: =+AW22-AV22 -> -305270 | AZ22: =ROUND(+'2024 Bdg vs Actual-CA'!BG22+'2024 Bdg vs Actual -OH'!BG22,-2) -> 1232500 | BA22: 263714 | BB22: =+BA22-AZ22 -> -968786 | BG22: =+P22+L22+H22+T22+X22+AB22+AF22+AJ22+AN22+AR22+AV22+AZ22 -> 14789905 | BH22: =+Q22+M22+I22+U22+Y22+AC22+AG22+AK22+AO22+AS22+AW22+BA22 -> 9750352 | BI22: =+BH22-BG22 -> -5039553
A23: Other Revenue | F23: =H23+L23+P23+T23+X23+AB23+AF23+AJ23+AN23+AR23+AV23+AZ23 -> 228916.67 | H23: =+'2024 Bdg vs Actual-CA'!O23+'2024 Bdg vs Actual -OH'!O23 -> 19333.333 | I23: 12167 | J23: =+I23-H23 -> -7166.3333 | L23: =+'2024 Bdg vs Actual-CA'!S23+'2024 Bdg vs Actual -OH'!S23 -> 16583.333 | M23: 6918 | N23: =+M23-L23 -> -9665.3333 | P23: =ROUND(+'2024 Bdg vs Actual-CA'!W23+'2024 Bdg vs Actual -OH'!W23,-2) -> 19300 | Q23: 15554 | R23: =+Q23-P23 -> -3746 | T23: =ROUND(+'2024 Bdg vs Actual-CA'!AA23+'2024 Bdg vs Actual -OH'!AA23,-2) -> 19300 | U23: 4670 | V23: =+U23-T23 -> -14630 | X23: =ROUND(+'2024 Bdg vs Actual-CA'!AE23+'2024 Bdg vs Actual -OH'!AE23,-2) -> 19300 | Y23: =102670-90848 -> 11822 | Z23: =+Y23-X23 -> -7478 | AB23: =ROUND(+'2024 Bdg vs Actual-CA'!AI23+'2024 Bdg vs Actual -OH'!AI23,-2) -> 19300 | AC23: 10732 | AD23: =+AC23-AB23 -> -8568 | AF23: =ROUND(+'2024 Bdg vs Actual-CA'!AM23+'2024 Bdg vs Actual -OH'!AM23,-2) -> 19300 | AG23: 6031 | AH23: =+AG23-AF23 -> -13269 | AJ23: =ROUND(+'2024 Bdg vs Actual-CA'!AQ23+'2024 Bdg vs Actual -OH'!AQ23,-2) -> 19300 | AK23: 7559 | AL23: =+AK23-AJ23 -> -11741 | AN23: =ROUND(+'2024 Bdg vs Actual-CA'!AU23+'2024 Bdg vs Actual -OH'!AU23,-2) -> 19300 | AO23: 18165 | AP23: =+AO23-AN23 -> -1135 | AR23: =ROUND(+'2024 Bdg vs Actual-CA'!AY23+'2024 Bdg vs Actual -OH'!AY23,-2) -> 19300 | AS23: 7760 | AT23: =+AS23-AR23 -> -11540 | AV23: =ROUND(+'2024 Bdg vs Actual-CA'!BC23+'2024 Bdg vs Actual -OH'!BC23,-2) -> 19300 | AW23: 7115 | AX23: =+AW23-AV23 -> -12185 | AZ23: =ROUND(+'2024 Bdg vs Actual-CA'!BG23+'2024 Bdg vs Actual -OH'!BG23,-2) -> 19300 | BA23: 27178 | BB23: =+BA23-AZ23 -> 7878 | BG23: =+P23+L23+H23+T23+X23+AB23+AF23+AJ23+AN23+AR23+AV23+AZ23 -> 228916.67 | BH23: =+Q23+M23+I23+U23+Y23+AC23+AG23+AK23+AO23+AS23+AW23+BA23 -> 135671 | BI23: =+BH23-BG23 -> -93245.667
A25: Cost of Services- **
A26: Costs of Monthly Recurring Services | F26: =H26+L26+P26+T26+X26+AB26+AF26+AJ26+AN26+AR26+AV26+AZ26 -> 231439.78 | H26: =H14*0.033 -> 20039.777 | I26: 18726 | J26: =H26-I26 -> 1313.777 | L26: =+'2024 Bdg vs Actual-CA'!S26+'2024 Bdg vs Actual -OH'!S26 -> 17400 | M26: 21728 | N26: =L26-M26 -> -4328 | P26: =ROUND(+'2024 Bdg vs Actual-CA'!W26+'2024 Bdg vs Actual -OH'!W26,-2) -> 17200 | Q26: 23839 | R26: =P26-Q26 -> -6639 | T26: =ROUND('2024 Bdg vs Actual-CA'!AA26+'2024 Bdg vs Actual -OH'!AA26,-2) -> 17600 | U26: 31075 | V26: =T26-U26 -> -13475 | X26: =ROUND('2024 Bdg vs Actual-CA'!AE26+'2024 Bdg vs Actual -OH'!AE26,-2) -> 18000 | Y26: 21136 | Z26: =X26-Y26 -> -3136 | AB26: =ROUND('2024 Bdg vs Actual-CA'!AI26+'2024 Bdg vs Actual -OH'!AI26,-2) -> 19000 | AC26: 21363 | AD26: =AB26-AC26 -> -2363 | AF26: =ROUND('2024 Bdg vs Actual-CA'!AM26+'2024 Bdg vs Actual -OH'!AM26,-2) -> 19500 | AG26: 22325 | AH26: =AF26-AG26 -> -2825 | AJ26: =ROUND('2024 Bdg vs Actual-CA'!AQ26+'2024 Bdg vs Actual -OH'!AQ26,-2) -> 19700 | AK26: 16009 | AL26: =AJ26-AK26 -> 3691 | AN26: =ROUND('2024 Bdg vs Actual-CA'!AU26+'2024 Bdg vs Actual -OH'!AU26,-2) -> 20000 | AO26: 17427 | AP26: =AN26-AO26 -> 2573 | AR26: =ROUND('2024 Bdg vs Actual-CA'!AY26+'2024 Bdg vs Actual -OH'!AY26,-2) -> 20600 | AS26: 13618 | AT26: =AR26-AS26 -> 6982 | AV26: =ROUND('2024 Bdg vs Actual-CA'!BC26+'2024 Bdg vs Actual -OH'!BC26,-2) -> 21000 | AW26: 20756 | AX26: =AV26-AW26 -> 244 | AZ26: =ROUND('2024 Bdg vs Actual-CA'!BG26+'2024 Bdg vs Actual -OH'!BG26,-2) -> 21400 | BA26: 16438 | BB26: =AZ26-BA26 -> 4962 | BG26: =+P26+L26+H26+T26+X26+AB26+AF26+AJ26+AN26+AR26+AV26+AZ26 -> 231439.78 | BH26: =+Q26+M26+I26+U26+Y26+AC26+AG26+AK26+AO26+AS26+AW26+BA26 -> 244440 | BI26: =BG26-BH26 -> -13000.223
A27: Costs of Recur Private Cloud | F27: =H27+L27+P27+T27+X27+AB27+AF27+AJ27+AN27+AR27+AV27+AZ27 -> 185593.58 | H27: =H15*0.725 -> 19293.58 | I27: 13334 | J27: =H27-I27 -> 5959.5804 | L27: =+'2024 Bdg vs Actual-CA'!S27+'2024 Bdg vs Actual -OH'!S27 -> 13100 | M27: 12968 | N27: =L27-M27 -> 132 | P27: =ROUND(+'2024 Bdg vs Actual-CA'!W27+'2024 Bdg vs Actual -OH'!W27,-2) -> 13100 | Q27: 8745 | R27: =P27-Q27 -> 4355 | T27: =ROUND('2024 Bdg vs Actual-CA'!AA27+'2024 Bdg vs Actual -OH'!AA27,-2) -> 13400 | U27: 5436 | V27: =T27-U27 -> 7964 | X27: =ROUND('2024 Bdg vs Actual-CA'!AE27+'2024 Bdg vs Actual -OH'!AE27,-2) -> 13100 | Y27: 9138 | Z27: =X27-Y27 -> 3962 | AB27: =ROUND('2024 Bdg vs Actual-CA'!AI27+'2024 Bdg vs Actual -OH'!AI27,-2) -> 15200 | AC27: 7867 | AD27: =AB27-AC27 -> 7333 | AF27: =ROUND('2024 Bdg vs Actual-CA'!AM27+'2024 Bdg vs Actual -OH'!AM27,-2) -> 15500 | AG27: 8470 | AH27: =AF27-AG27 -> 7030 | AJ27: =ROUND('2024 Bdg vs Actual-CA'!AQ27+'2024 Bdg vs Actual -OH'!AQ27,-2) -> 15800 | AK27: 7841 | AL27: =AJ27-AK27 -> 7959 | AN27: =ROUND('2024 Bdg vs Actual-CA'!AU27+'2024 Bdg vs Actual -OH'!AU27,-2) -> 16200 | AO27: 9617 | AP27: =AN27-AO27 -> 6583 | AR27: =ROUND('2024 Bdg vs Actual-CA'!AY27+'2024 Bdg vs Actual -OH'!AY27,-2) -> 16500 | AS27: 10737 | AT27: =AR27-AS27 -> 5763 | AV27: =ROUND('2024 Bdg vs Actual-CA'!BC27+'2024 Bdg vs Actual -OH'!BC27,-2) -> 16800 | AW27: 7273 | AX27: =AV27-AW27 -> 9527 | AZ27: =ROUND('2024 Bdg vs Actual-CA'!BG27+'2024 Bdg vs Actual -OH'!BG27,-2) -> 17600 | BA27: 9786 | BB27: =AZ27-BA27 -> 7814 | BG27: =+P27+L27+H27+T27+X27+AB27+AF27+AJ27+AN27+AR27+AV27+AZ27 -> 185593.58 | BH27: =+Q27+M27+I27+U27+Y27+AC27+AG27+AK27+AO27+AS27+AW27+BA27 -> 111212 | BI27: =BG27-BH27 -> 74381.58
A28: Costs of Monthly Recurring Resale | F28: =H28+L28+P28+T28+X28+AB28+AF28+AJ28+AN28+AR28+AV28+AZ28 -> 1788426.7 | H28: =H16*0.647 -> 129326.7 | I28: 151839 | J28: =H28-I28 -> -22512.304 | L28: =+'2024 Bdg vs Actual-CA'!S28+'2024 Bdg vs Actual -OH'!S28 -> 139800 | M28: 162704 | N28: =L28-M28 -> -22904 | P28: =ROUND(+'2024 Bdg vs Actual-CA'!W28+'2024 Bdg vs Actual -OH'!W28,-2) -> 129600 | Q28: 153411 | R28: =P28-Q28 -> -23811 | T28: =ROUND('2024 Bdg vs Actual-CA'!AA28+'2024 Bdg vs Actual -OH'!AA28,-2) -> 136900 | U28: 150078 | V28: =T28-U28 -> -13178 | X28: =ROUND('2024 Bdg vs Actual-CA'!AE28+'2024 Bdg vs Actual -OH'!AE28,-2) -> 143600 | Y28: 150744 | Z28: =X28-Y28 -> -7144 | AB28: =ROUND('2024 Bdg vs Actual-CA'!AI28+'2024 Bdg vs Actual -OH'!AI28,-2) -> 151100 | AC28: 147044 | AD28: =AB28-AC28 -> 4056 | AF28: =ROUND('2024 Bdg vs Actual-CA'!AM28+'2024 Bdg vs Actual -OH'!AM28,-2) -> 153700 | AG28: 143293 | AH28: =AF28-AG28 -> 10407 | AJ28: =ROUND('2024 Bdg vs Actual-CA'!AQ28+'2024 Bdg vs Actual -OH'!AQ28,-2) -> 156300 | AK28: 145211 | AL28: =AJ28-AK28 -> 11089 | AN28: =ROUND('2024 Bdg vs Actual-CA'!AU28+'2024 Bdg vs Actual -OH'!AU28,-2) -> 158600 | AO28: 156493 | AP28: =AN28-AO28 -> 2107 | AR28: =ROUND('2024 Bdg vs Actual-CA'!AY28+'2024 Bdg vs Actual -OH'!AY28,-2) -> 161000 | AS28: 155761 | AT28: =AR28-AS28 -> 5239 | AV28: =ROUND('2024 Bdg vs Actual-CA'!BC28+'2024 Bdg vs Actual -OH'!BC28,-2) -> 163000 | AW28: 165048 | AX28: =AV28-AW28 -> -2048 | AZ28: =ROUND('2024 Bdg vs Actual-CA'!BG28+'2024 Bdg vs Actual -OH'!BG28,-2) -> 165500 | BA28: 166833 | BB28: =AZ28-BA28 -> -1333 | BG28: =+P28+L28+H28+T28+X28+AB28+AF28+AJ28+AN28+AR28+AV28+AZ28 -> 1788426.7 | BH28: =+Q28+M28+I28+U28+Y28+AC28+AG28+AK28+AO28+AS28+AW28+BA28 -> 1848459 | BI28: =BG28-BH28 -> -60032.304
A29: Costs of IT Project Services | F29: =H29+L29+P29+T29+X29+AB29+AF29+AJ29+AN29+AR29+AV29+AZ29 -> 16944.414 | H29: =H17*0.012 -> 1449.414 | I29: 2444 | J29: =H29-I29 -> -994.586 | L29: =+'2024 Bdg vs Actual-CA'!S29+'2024 Bdg vs Actual -OH'!S29 -> 1495 | M29: 371 | N29: =L29-M29 -> 1124 | P29: =ROUND(+'2024 Bdg vs Actual-CA'!W29+'2024 Bdg vs Actual -OH'!W29,-2) -> 1400 | Q29: 270 | R29: =P29-Q29 -> 1130 | T29: =ROUND('2024 Bdg vs Actual-CA'!AA29+'2024 Bdg vs Actual -OH'!AA29,-2) -> 1400 | U29: 3310 | V29: =T29-U29 -> -1910 | X29: =ROUND('2024 Bdg vs Actual-CA'!AE29+'2024 Bdg vs Actual -OH'!AE29,-2) -> 1400 | Y29: 367 | Z29: =X29-Y29 -> 1033 | AB29: =ROUND('2024 Bdg vs Actual-CA'!AI29+'2024 Bdg vs Actual -OH'!AI29,-2) -> 1400 | AC29: 19990 | AD29: =AB29-AC29 -> -18590 | AF29: =ROUND('2024 Bdg vs Actual-CA'!AM29+'2024 Bdg vs Actual -OH'!AM29,-2) -> 1400 | AG29: 794 | AH29: =AF29-AG29 -> 606 | AJ29: =ROUND('2024 Bdg vs Actual-CA'!AQ29+'2024 Bdg vs Actual -OH'!AQ29,-2) -> 1400 | AK29: 245 | AL29: =AJ29-AK29 -> 1155 | AN29: =ROUND('2024 Bdg vs Actual-CA'!AU29+'2024 Bdg vs Actual -OH'!AU29,-2) -> 1400 | AO29: 0 | AP29: =AN29-AO29 -> 1400 | AR29: =ROUND('2024 Bdg vs Actual-CA'!AY29+'2024 Bdg vs Actual -OH'!AY29,-2) -> 1400 | AS29: 0 | AT29: =AR29-AS29 -> 1400 | AV29: =ROUND('2024 Bdg vs Actual-CA'!BC29+'2024 Bdg vs Actual -OH'!BC29,-2) -> 1400 | AW29: 562 | AX29: =AV29-AW29 -> 838 | AZ29: =ROUND('2024 Bdg vs Actual-CA'!BG29+'2024 Bdg vs Actual -OH'!BG29,-2) -> 1400 | BA29: 0 | BB29: =AZ29-BA29 -> 1400 | BG29: =+P29+L29+H29+T29+X29+AB29+AF29+AJ29+AN29+AR29+AV29+AZ29 -> 16944.414 | BH29: =+Q29+M29+I29+U29+Y29+AC29+AG29+AK29+AO29+AS29+AW29+BA29 -> 28353 | BI29: =BG29-BH29 -> -11408.586
A30: Costs of Subcontracted Services | F30: =H30+L30+P30+T30+X30+AB30+AF30+AJ30+AN30+AR30+AV30+AZ30 -> 621646.12 | H30: =H18*0.894 -> 50746.122 | I30: 4581 | J30: =H30-I30 -> 46165.122 | L30: =+'2024 Bdg vs Actual-CA'!S30+'2024 Bdg vs Actual -OH'!S30 -> 63900 | M30: 62562 | N30: =L30-M30 -> 1338 | P30: =ROUND(+'2024 Bdg vs Actual-CA'!W30+'2024 Bdg vs Actual -OH'!W30,-2) -> 50700 | Q30: 13434 | R30: =P30-Q30 -> 37266 | T30: =ROUND('2024 Bdg vs Actual-CA'!AA30+'2024 Bdg vs Actual -OH'!AA30,-2) -> 50700 | U30: 9004 | V30: =T30-U30 -> 41696 | X30: =ROUND('2024 Bdg vs Actual-CA'!AE30+'2024 Bdg vs Actual -OH'!AE30,-2) -> 50700 | Y30: 11858 | Z30: =X30-Y30 -> 38842 | AB30: =ROUND('2024 Bdg vs Actual-CA'!AI30+'2024 Bdg vs Actual -OH'!AI30,-2) -> 50700 | AC30: 13738 | AD30: =AB30-AC30 -> 36962 | AF30: =ROUND('2024 Bdg vs Actual-CA'!AM30+'2024 Bdg vs Actual -OH'!AM30,-2) -> 50700 | AG30: 246428 | AH30: =AF30-AG30 -> -195728 | AJ30: =ROUND('2024 Bdg vs Actual-CA'!AQ30+'2024 Bdg vs Actual -OH'!AQ30,-2) -> 50700 | AK30: 111796 | AL30: =AJ30-AK30 -> -61096 | AN30: =ROUND('2024 Bdg vs Actual-CA'!AU30+'2024 Bdg vs Actual -OH'!AU30,-2) -> 50700 | AO30: 22771 | AP30: =AN30-AO30 -> 27929 | AR30: =ROUND('2024 Bdg vs Actual-CA'!AY30+'2024 Bdg vs Actual -OH'!AY30,-2) -> 50700 | AS30: 27250 | AT30: =AR30-AS30 -> 23450 | AV30: =ROUND('2024 Bdg vs Actual-CA'!BC30+'2024 Bdg vs Actual -OH'!BC30,-2) -> 50700 | AW30: 10575 | AX30: =AV30-AW30 -> 40125 | AZ30: =ROUND('2024 Bdg vs Actual-CA'!BG30+'2024 Bdg vs Actual -OH'!BG30,-2) -> 50700 | BA30: 22708 | BB30: =AZ30-BA30 -> 27992 | BG30: =+P30+L30+H30+T30+X30+AB30+AF30+AJ30+AN30+AR30+AV30+AZ30 -> 621646.12 | BH30: =+Q30+M30+I30+U30+Y30+AC30+AG30+AK30+AO30+AS30+AW30+BA30 -> 556705 | BI30: =BG30-BH30 -> 64941.122
A31: Costs of Product Resale | F31: =H31+L31+P31+T31+X31+AB31+AF31+AJ31+AN31+AR31+AV31+AZ31 -> 12571185 | H31: =H22*0.85 -> 1047584.6 | I31: 454504 | J31: =H31-I31 -> 593080.62 | L31: =+'2024 Bdg vs Actual-CA'!S31+'2024 Bdg vs Actual -OH'!S31 -> 1047600 | M31: 619534 | N31: =L31-M31 -> 428066 | P31: =ROUND(+'2024 Bdg vs Actual-CA'!W31+'2024 Bdg vs Actual -OH'!W31,-2) -> 1047600 | Q31: 322796 | R31: =P31-Q31 -> 724804 | T31: =ROUND('2024 Bdg vs Actual-CA'!AA31+'2024 Bdg vs Actual -OH'!AA31,-2) -> 1047600 | U31: 633077 | V31: =T31-U31 -> 414523 | X31: =ROUND('2024 Bdg vs Actual-CA'!AE31+'2024 Bdg vs Actual -OH'!AE31,-2) -> 1047600 | Y31: 529476 | Z31: =X31-Y31 -> 518124 | AB31: =ROUND('2024 Bdg vs Actual-CA'!AI31+'2024 Bdg vs Actual -OH'!AI31,-2) -> 1047600 | AC31: 1363102 | AD31: =AB31-AC31 -> -315502 | AF31: =ROUND('2024 Bdg vs Actual-CA'!AM31+'2024 Bdg vs Actual -OH'!AM31,-2) -> 1047600 | AG31: 980082 | AH31: =AF31-AG31 -> 67518 | AJ31: =ROUND('2024 Bdg vs Actual-CA'!AQ31+'2024 Bdg vs Actual -OH'!AQ31,-2) -> 1047600 | AK31: 1197545 | AL31: =AJ31-AK31 -> -149945 | AN31: =ROUND('2024 Bdg vs Actual-CA'!AU31+'2024 Bdg vs Actual -OH'!AU31,-2) -> 1047600 | AO31: 413028 | AP31: =AN31-AO31 -> 634572 | AR31: =ROUND('2024 Bdg vs Actual-CA'!AY31+'2024 Bdg vs Actual -OH'!AY31,-2) -> 1047600 | AS31: 521483 | AT31: =AR31-AS31 -> 526117 | AV31: =ROUND('2024 Bdg vs Actual-CA'!BC31+'2024 Bdg vs Actual -OH'!BC31,-2) -> 1047600 | AW31: 768618 | AX31: =AV31-AW31 -> 278982 | AZ31: =ROUND('2024 Bdg vs Actual-CA'!BG31+'2024 Bdg vs Actual -OH'!BG31,-2) -> 1047600 | BA31: 218840 | BB31: =AZ31-BA31 -> 828760 | BG31: =+P31+L31+H31+T31+X31+AB31+AF31+AJ31+AN31+AR31+AV31+AZ31 -> 12571185 | BH31: =+Q31+M31+I31+U31+Y31+AC31+AG31+AK31+AO31+AS31+AW31+BA31 -> 8022085 | BI31: =BG31-BH31 -> 4549099.6
A33: Direct Labor-Fully loaded(Support/Engineers) | F33: =H33+L33+P33+T33+X33+AB33+AF33+AJ33+AN33+AR33+AV33+AZ33 -> 4169565.2 | H33: ='2024 Bdg vs Actual-CA'!O33+'2024 Bdg vs Actual -OH'!O33 -> 361700 | I33: =313241+15170+3640+21873 -> 353924 | J33: =H33-I33 -> 7776 | L33: =+'2024 Bdg vs Actual-CA'!S33+'2024 Bdg vs Actual -OH'!S33 -> 348865.19 | M33: 333332 | N33: =L33-M33 -> 15533.193 | O33: Update budgetpayroll based on onboarding and off boardings notified of | P33: =ROUND(+'2024 Bdg vs Actual-CA'!W33+'2024 Bdg vs Actual -OH'!W33,-2) -> 345200 | Q33: 333234 | R33: =P33-Q33 -> 11966 | T33: =ROUND('2024 Bdg vs Actual-CA'!AA33+'2024 Bdg vs Actual -OH'!AA33,-2) -> 341000 | U33: 345633 | V33: =T33-U33 -> -4633 | X33: =ROUND('2024 Bdg vs Actual-CA'!AE33+'2024 Bdg vs Actual -OH'!AE33,-2) -> 346600 | Y33: 357329 | Z33: =X33-Y33 -> -10729 | AB33: =ROUND('2024 Bdg vs Actual-CA'!AI33+'2024 Bdg vs Actual -OH'!AI33,-2) -> 346600 | AC33: 346405 | AD33: =AB33-AC33 -> 195 | AF33: =ROUND('2024 Bdg vs Actual-CA'!AM33+'2024 Bdg vs Actual -OH'!AM33,-2) -> 346600 | AG33: 340442 | AH33: =AF33-AG33 -> 6158 | AJ33: =ROUND('2024 Bdg vs Actual-CA'!AQ33+'2024 Bdg vs Actual -OH'!AQ33,-2) -> 346600 | AK33: 349505 | AL33: =AJ33-AK33 -> -2905 | AN33: =ROUND('2024 Bdg vs Actual-CA'!AU33+'2024 Bdg vs Actual -OH'!AU33,-2) -> 346600 | AO33: 325154 | AP33: =AN33-AO33 -> 21446 | AR33: =ROUND('2024 Bdg vs Actual-CA'!AY33+'2024 Bdg vs Actual -OH'!AY33,-2) -> 346600 | AS33: 333772 | AT33: =AR33-AS33 -> 12828 | AV33: =ROUND('2024 Bdg vs Actual-CA'!BC33+'2024 Bdg vs Actual -OH'!BC33,-2) -> 346600 | AW33: 359057 | AX33: =AV33-AW33 -> -12457 | AZ33: =ROUND('2024 Bdg vs Actual-CA'!BG33+'2024 Bdg vs Actual -OH'!BG33,-2) -> 346600 | BA33: 333778 | BB33: =AZ33-BA33 -> 12822 | BG33: =+P33+L33+H33+T33+X33+AB33+AF33+AJ33+AN33+AR33+AV33+AZ33 -> 4169565.2 | BH33: =+Q33+M33+I33+U33+Y33+AC33+AG33+AK33+AO33+AS33+AW33+BA33 -> 4111565 | BI33: =BG33-BH33 -> 58000.192
A34: Total Cost of Good Sold** | F34: =H34+L34+P34+T34+X34+AB34+AF34+AJ34+AN34+AR34+AV34+AZ34 -> 19584800 | H34: =SUM(H26:H33) -> 1630140.2 | I34: =SUM(I26:I33) -> 999352 | J34: =H34-I34 -> 630788.21 | L34: =SUM(L26:L33) -> 1632160.2 | M34: =SUM(M26:M33) -> 1213199 | N34: =L34-M34 -> 418961.19 | P34: =SUM(P26:P33) -> 1604800 | Q34: =SUM(Q26:Q33) -> 855729 | R34: =P34-Q34 -> 749071 | T34: =SUM(T26:T33) -> 1608600 | U34: =SUM(U26:U33) -> 1177613 | V34: =T34-U34 -> 430987 | X34: =SUM(X26:X33) -> 1621000 | Y34: =SUM(Y26:Y33) -> 1080048 | Z34: =X34-Y34 -> 540952 | AB34: =SUM(AB26:AB33) -> 1631600 | AC34: =SUM(AC26:AC33) -> 1919509 | AD34: =AB34-AC34 -> -287909 | AF34: =SUM(AF26:AF33) -> 1635000 | AG34: =SUM(AG26:AG33) -> 1741834 | AH34: =AF34-AG34 -> -106834 | AJ34: =SUM(AJ26:AJ33) -> 1638100 | AK34: =SUM(AK26:AK33) -> 1828152 | AL34: =AJ34-AK34 -> -190052 | AN34: =SUM(AN26:AN33) -> 1641100 | AO34: =SUM(AO26:AO33) -> 944490 | AP34: =AN34-AO34 -> 696610 | AR34: =SUM(AR26:AR33) -> 1644400 | AS34: =SUM(AS26:AS33) -> 1062621 | AT34: =AR34-AS34 -> 581779 | AV34: =SUM(AV26:AV33) -> 1647100 | AW34: =SUM(AW26:AW33) -> 1331889 | AX34: =AV34-AW34 -> 315211 | AZ34: =SUM(AZ26:AZ33) -> 1650800 | BA34: =SUM(BA26:BA33) -> 768383 | BB34: =AZ34-BA34 -> 882417 | BG34: =+P34+L34+H34+T34+X34+AB34+AF34+AJ34+AN34+AR34+AV34+AZ34 -> 19584800 | BH34: =+Q34+M34+I34+U34+Y34+AC34+AG34+AK34+AO34+AS34+AW34+BA34 -> 14922819 | BI34: =BG34-BH34 -> 4661981.4
A35: Total Gross Margin | F35: =F11-F34 -> 7604674.3 | H35: =H11-H34 -> 632957.63 | I35: =I11-I34 -> 376370.57 | J35: =I35-H35 -> -256587.06 | L35: =L11-L34 -> 561316.64 | M35: =M11-M34 -> 495469 | N35: =M35-L35 -> -65847.641 | P35: =P11-P34 -> 562600 | Q35: =Q11-Q34 -> 401017 | R35: =Q35-P35 -> -161583 | T35: =T11-T34 -> 585100 | U35: =U11-U34 -> 562823 | V35: =U35-T35 -> -22277 | X35: =X11-X34 -> 594400 | Y35: =Y11-Y34 -> 430419 | Z35: =Y35-X35 -> -163981 | AB35: =AB11-AB34 -> 627300 | AC35: =AC11-AC34 -> 658772 | AD35: =AC35-AB35 -> 31472 | AF35: =AF11-AF34 -> 643300 | AG35: =AG11-AG34 -> 657168 | AH35: =AG35-AF35 -> 13868 | AJ35: =AJ11-AJ34 -> 651000 | AK35: =AK11-AK34 -> 958381 | AL35: =AK35-AJ35 -> 307381 | AN35: =AN11-AN34 -> 663700 | AO35: =AO11-AO34 -> 462848 | AP35: =AO35-AN35 -> -200852 | AR35: =AR11-AR34 -> 680000 | AS35: =AS11-AS34 -> 457553 | AT35: =AS35-AR35 -> -222447 | AV35: =AV11-AV34 -> 693700 | AW35: =AW11-AW34 -> 470173 | AX35: =AW35-AV35 -> -223527 | AZ35: =AZ11-AZ34 -> 709300 | BA35: =BA11-BA34 -> 428533 | BB35: =BA35-AZ35 -> -280767 | BG35: =BG11-BG34 -> 7604674.3 | BH35: =BH11-BH34 -> 6359526.6 | BI35: =BH35-BG35 -> -1245147.7
A37: Direct Selling Costs
A39: Commissions | F39: =H39+L39+P39+T39+X39+AB39+AF39+AJ39+AN39+AR39+AV39+AZ39 -> 603000 | H39: =+'2024 Bdg vs Actual-CA'!O39+'2024 Bdg vs Actual -OH'!O39 -> 66600 | I39: 2772 | J39: =H39-I39 -> 63828 | L39: =+'2024 Bdg vs Actual-CA'!S39+'2024 Bdg vs Actual -OH'!S39 -> 19300 | M39: 30348 | N39: =L39-M39 -> -11048 | O39: Paid out commissions from 4Q2024 | P39: =ROUND(+'2024 Bdg vs Actual-CA'!W39+'2024 Bdg vs Actual -OH'!W39,-2) -> 28900 | Q39: 0 | R39: =P39-Q39 -> 28900 | T39: =+'2024 Bdg vs Actual-CA'!AA39+'2024 Bdg vs Actual -OH'!AA39 -> 51700 | U39: 26145 | V39: =T39-U39 -> 25555 | X39: =+'2024 Bdg vs Actual-CA'!AE39+'2024 Bdg vs Actual -OH'!AE39 -> 51700 | Y39: 15741.92 | Z39: =X39-Y39 -> 35958.08 | AB39: =+'2024 Bdg vs Actual-CA'!AI39+'2024 Bdg vs Actual -OH'!AI39 -> 101600 | AC39: 31323 | AD39: =AB39-AC39 -> 70277 | AF39: =+'2024 Bdg vs Actual-CA'!AM39+'2024 Bdg vs Actual -OH'!AM39 -> 47200 | AG39: 22987 | AH39: =AF39-AG39 -> 24213 | AJ39: =+'2024 Bdg vs Actual-CA'!AQ39+'2024 Bdg vs Actual -OH'!AQ39 -> 47200 | AK39: =31335 -> 31335 | AL39: =AJ39-AK39 -> 15865 | AN39: =+'2024 Bdg vs Actual-CA'!AU39+'2024 Bdg vs Actual -OH'!AU39 -> 47200 | AO39: 29868 | AP39: =AN39-AO39 -> 17332 | AR39: =+'2024 Bdg vs Actual-CA'!AY39+'2024 Bdg vs Actual -OH'!AY39 -> 47200 | AS39: 41573 | AT39: =AR39-AS39 -> 5627 | AV39: =+'2024 Bdg vs Actual-CA'!BC39+'2024 Bdg vs Actual -OH'!BC39 -> 47200 | AW39: 22190 | AX39: =AV39-AW39 -> 25010 | AZ39: =+'2024 Bdg vs Actual-CA'!BG39+'2024 Bdg vs Actual -OH'!BG39 -> 47200 | BA39: 26793 | BB39: =AZ39-BA39 -> 20407 | BG39: =+P39+L39+H39+T39+X39+AB39+AF39+AJ39+AN39+AR39+AV39+AZ39 -> 603000 | BH39: =+Q39+M39+I39+U39+Y39+AC39+AG39+AK39+AO39+AS39+AW39+BA39 -> 281075.92 | BI39: =BG39-BH39 -> 321924.08
A40: Labor Selling - Loaded | F40: =H40+L40+P40+T40+X40+AB40+AF40+AJ40+AN40+AR40+AV40+AZ40 -> 1414731.5 | H40: ='2024 Bdg vs Actual-CA'!O40+'2024 Bdg vs Actual -OH'!O40 -> 110400 | I40: 118582 | J40: =H40-I40 -> -8182 | K40: I'm assuming these commissions are from December/prior, because they should be much less than budgeted with sales so low | L40: =+'2024 Bdg vs Actual-CA'!S40+'2024 Bdg vs Actual -OH'!S40 -> 130631.49 | M40: 127279 | N40: =L40-M40 -> 3352.49 | O40: Update budgetpayroll based on onboarding and off boardings notified of | P40: =ROUND(+'2024 Bdg vs Actual-CA'!W40+'2024 Bdg vs Actual -OH'!W40,-2) -> 130600 | Q40: 132452 | R40: =P40-Q40 -> -1852 | T40: =ROUND('2024 Bdg vs Actual-CA'!AA40+'2024 Bdg vs Actual -OH'!AA40,-2) -> 120700 | U40: =157259-26145 -> 131114 | V40: =T40-U40 -> -10414 | X40: =ROUND('2024 Bdg vs Actual-CA'!AE40+'2024 Bdg vs Actual -OH'!AE40,-2) -> 115300 | Y40: 147392 | Z40: =X40-Y40 -> -32092 | AB40: =ROUND('2024 Bdg vs Actual-CA'!AI40+'2024 Bdg vs Actual -OH'!AI40,-2) -> 115300 | AC40: =141685-31323 -> 110362 | AD40: =AB40-AC40 -> 4938 | AF40: =ROUND('2024 Bdg vs Actual-CA'!AM40+'2024 Bdg vs Actual -OH'!AM40,-2) -> 115300 | AG40: =108853+10617+2430+4607 -> 126507 | AH40: =AF40-AG40 -> -11207 | AJ40: =ROUND('2024 Bdg vs Actual-CA'!AQ40+'2024 Bdg vs Actual -OH'!AQ40,-2) -> 115300 | AK40: =130111-31335 -> 98776 | AL40: =AJ40-AK40 -> 16524 | AN40: =ROUND('2024 Bdg vs Actual-CA'!AU40+'2024 Bdg vs Actual -OH'!AU40,-2) -> 115300 | AO40: =119660-AO39 -> 89792 | AP40: =AN40-AO40 -> 25508 | AR40: =ROUND('2024 Bdg vs Actual-CA'!AY40+'2024 Bdg vs Actual -OH'!AY40,-2) -> 115300 | AS40: =115290+12667+1692+4023+6460 -> 140132 | AT40: =AR40-AS40 -> -24832 | AV40: =ROUND('2024 Bdg vs Actual-CA'!BC40+'2024 Bdg vs Actual -OH'!BC40,-2) -> 115300 | AW40: =84308+7906+1531+3339+6007 -> 103091 | AX40: =AV40-AW40 -> 12209 | AZ40: =ROUND('2024 Bdg vs Actual-CA'!BG40+'2024 Bdg vs Actual -OH'!BG40,-2) -> 115300 | BA40: =126880.26-26793 -> 100087.26 | BB40: =AZ40-BA40 -> 15212.74 | BG40: =+P40+L40+H40+T40+X40+AB40+AF40+AJ40+AN40+AR40+AV40+AZ40 -> 1414731.5 | BH40: =+Q40+M40+I40+U40+Y40+AC40+AG40+AK40+AO40+AS40+AW40+BA40 -> 1425566.3 | BI40: =BG40-BH40 -> -10834.77
A41: Contribution Margin | F41: =F35-F39-F40 -> 5586942.8 | H41: =H35-H39-H40 -> 455957.63 | I41: =I35-I39-I40 -> 255016.57 | J41: =I41-H41 -> -200941.06 | K41: *We need to have a way to project commissions and timing | L41: =L35-L39-L40 -> 411385.15 | M41: =M35-M39-M40 -> 337842 | N41: =M41-L41 -> -73543.151 | P41: =P35-P39-P40 -> 403100 | Q41: =Q35-Q39-Q40 -> 268565 | R41: =Q41-P41 -> -134535 | T41: =T35-T39-T40 -> 412700 | U41: =U35-U39-U40 -> 405564 | V41: =U41-T41 -> -7136 | X41: =X35-X39-X40 -> 427400 | Y41: =Y35-Y39-Y40 -> 267285.08 | Z41: =Y41-X41 -> -160114.92 | AB41: =AB35-AB39-AB40 -> 410400 | AC41: =AC35-AC39-AC40 -> 517087 | AD41: =AC41-AB41 -> 106687 | AF41: =AF35-AF39-AF40 -> 480800 | AG41: =AG35-AG39-AG40 -> 507674 | AH41: =AG41-AF41 -> 26874 | AJ41: =AJ35-AJ39-AJ40 -> 488500 | AK41: =AK35-AK39-AK40 -> 828270 | AL41: =AK41-AJ41 -> 339770 | AN41: =AN35-AN39-AN40 -> 501200 | AO41: =AO35-AO39-AO40 -> 343188 | AP41: =AO41-AN41 -> -158012 | AR41: =AR35-AR39-AR40 -> 517500 | AS41: =AS35-AS39-AS40 -> 275848 | AT41: =AS41-AR41 -> -241652 | AV41: =AV35-AV39-AV40 -> 531200 | AW41: =AW35-AW39-AW40 -> 344892 | AX41: =AW41-AV41 -> -186308 | AZ41: =AZ35-AZ39-AZ40 -> 546800 | BA41: =BA35-BA39-BA40 -> 301652.74 | BB41: =BA41-AZ41 -> -245147.26 | BG41: =BG35-BG39-BG40 -> 5586942.8 | BH41: =BH35-BH39-BH40 -> 4652884.4 | BI41: =BH41-BG41 -> -934058.39
A43: **Expenses**
A45: Payroll ***
A46: Exec/ Mgmnt/Admin- Fully Loaded | F46: =H46+L46+P46+T46+X46+AB46+AF46+AJ46+AN46+AR46+AV46+AZ46 -> 1395000 | H46: ='2024 Bdg vs Actual-CA'!O46+'2024 Bdg vs Actual -OH'!O46 -> 109100 | I46: 132611 | J46: =H46-I46 -> -23511 | L46: =+'2024 Bdg vs Actual-CA'!S46+'2024 Bdg vs Actual -OH'!S46 -> 109100 | M46: 111986 | N46: =L46-M46 -> -2886 | O46: Update budgetpayroll based on onboarding and off boardings notified of | P46: =ROUND(+'2024 Bdg vs Actual-CA'!W46+'2024 Bdg vs Actual -OH'!W46,-2) -> 110300 | Q46: 115934 | R46: =P46-Q46 -> -5634 | T46: =ROUND('2024 Bdg vs Actual-CA'!AA46+'2024 Bdg vs Actual -OH'!AA46,-2) -> 118500 | U46: 130035 | V46: =T46-U46 -> -11535 | X46: =ROUND('2024 Bdg vs Actual-CA'!AE46+'2024 Bdg vs Actual -OH'!AE46,-2) -> 118500 | Y46: 132946 | Z46: =X46-Y46 -> -14446 | AB46: =ROUND('2024 Bdg vs Actual-CA'!AI46+'2024 Bdg vs Actual -OH'!AI46,-2) -> 118500 | AC46: 110799 | AD46: =AB46-AC46 -> 7701 | AF46: =ROUND('2024 Bdg vs Actual-CA'!AM46+'2024 Bdg vs Actual -OH'!AM46,-2) -> 118500 | AG46: 104268 | AH46: =AF46-AG46 -> 14232 | AJ46: =ROUND('2024 Bdg vs Actual-CA'!AQ46+'2024 Bdg vs Actual -OH'!AQ46,-2) -> 118500 | AK46: 110147 | AL46: =AJ46-AK46 -> 8353 | AN46: =ROUND('2024 Bdg vs Actual-CA'!AU46+'2024 Bdg vs Actual -OH'!AU46,-2) -> 118500 | AO46: 105538 | AP46: =AN46-AO46 -> 12962 | AR46: =ROUND('2024 Bdg vs Actual-CA'!AY46+'2024 Bdg vs Actual -OH'!AY46,-2) -> 118500 | AS46: 117800 | AT46: =AR46-AS46 -> 700 | AV46: =ROUND('2024 Bdg vs Actual-CA'!BC46+'2024 Bdg vs Actual -OH'!BC46,-2) -> 118500 | AW46: 109515 | AX46: =AV46-AW46 -> 8985 | AZ46: =ROUND('2024 Bdg vs Actual-CA'!BG46+'2024 Bdg vs Actual -OH'!BG46,-2) -> 118500 | BA46: 149557 | BB46: =AZ46-BA46 -> -31057 | BG46: =+P46+L46+H46+T46+X46+AB46+AF46+AJ46+AN46+AR46+AV46+AZ46 -> 1395000 | BH46: =+Q46+M46+I46+U46+Y46+AC46+AG46+AK46+AO46+AS46+AW46+BA46 -> 1431136 | BI46: =BG46-BH46 -> -36136
A47: Workers Comp | F47: =H47+L47+P47+T47+X47+AB47+AF47+AJ47+AN47+AR47+AV47+AZ47 -> 9000 | H47: ='2024 Bdg vs Actual-CA'!O47+'2024 Bdg vs Actual -OH'!O47 -> 0 | I47: 0 | J47: =H47-I47 -> 0 | L47: ='2024 Bdg vs Actual-CA'!S47+'2024 Bdg vs Actual -OH'!S47 -> 0 | M47: 0 | N47: =L47-M47 -> 0 | P47: =ROUND(+'2024 Bdg vs Actual-CA'!W47+'2024 Bdg vs Actual -OH'!W47,-2) -> 3000 | Q47: 0 | R47: =P47-Q47 -> 3000 | T47: ='2024 Bdg vs Actual-CA'!AA47+'2024 Bdg vs Actual -OH'!AA47 -> 0 | V47: =T47-U47 -> 0 | X47: ='2024 Bdg vs Actual-CA'!AE47+'2024 Bdg vs Actual -OH'!AE47 -> 0 | Z47: =X47-Y47 -> 0 | AB47: ='2024 Bdg vs Actual-CA'!AI47+'2024 Bdg vs Actual -OH'!AI47 -> 3000 | AD47: =AB47-AC47 -> 3000 | AF47: ='2024 Bdg vs Actual-CA'!AM47+'2024 Bdg vs Actual -OH'!AM47 -> 0 | AH47: =AF47-AG47 -> 0 | AJ47: ='2024 Bdg vs Actual-CA'!AQ47+'2024 Bdg vs Actual -OH'!AQ47 -> 0 | AL47: =AJ47-AK47 -> 0 | AN47: ='2024 Bdg vs Actual-CA'!AU47+'2024 Bdg vs Actual -OH'!AU47 -> 0 | AP47: =AN47-AO47 -> 0 | AR47: ='2024 Bdg vs Actual-CA'!AY47+'2024 Bdg vs Actual -OH'!AY47 -> 3000 | AS47: 0 | AT47: =AR47-AS47 -> 3000 | AV47: ='2024 Bdg vs Actual-CA'!BC47+'2024 Bdg vs Actual -OH'!BC47 -> 0 | AX47: =AV47-AW47 -> 0 | AZ47: ='2024 Bdg vs Actual-CA'!BG47+'2024 Bdg vs Actual -OH'!BG47 -> 0 | BB47: =AZ47-BA47 -> 0 | BG47: =+P47+L47+H47+T47+X47+AB47+AF47+AJ47+AN47+AR47+AV47+AZ47 -> 9000 | BH47: =+Q47+M47+I47+U47+Y47+AC47+AG47+AK47+AO47+AS47+AW47+BA47 -> 0 | BI47: =BG47-BH47 -> 9000
A48: Total Payroll | F48: =SUM(H48:AZ48) -> 2689500 | H48: =H46+H47 -> 109100 | I48: =I46+I47 -> 132611 | J48: =H48-I48 -> -23511 | L48: =L46+L47 -> 109100 | M48: =M46+M47 -> 111986 | N48: =L48-M48 -> -2886 | P48: =P46+P47 -> 113300 | Q48: =Q46+Q47 -> 115934 | R48: =P48-Q48 -> -2634 | T48: =T46+T47 -> 118500 | U48: =U46+U47 -> 130035 | V48: =T48-U48 -> -11535 | X48: =X46+X47 -> 118500 | Y48: =Y46+Y47 -> 132946 | Z48: =X48-Y48 -> -14446 | AB48: =AB46+AB47 -> 121500 | AC48: =AC46+AC47 -> 110799 | AD48: =AB48-AC48 -> 10701 | AF48: =AF46+AF47 -> 118500 | AG48: =AG46+AG47 -> 104268 | AH48: =AF48-AG48 -> 14232 | AJ48: =AJ46+AJ47 -> 118500 | AK48: =AK46+AK47 -> 110147 | AL48: =AJ48-AK48 -> 8353 | AN48: =AN46+AN47 -> 118500 | AO48: =AO46+AO47 -> 105538 | AP48: =AN48-AO48 -> 12962 | AR48: =AR46+AR47 -> 121500 | AS48: =AS46+AS47 -> 117800 | AT48: =AR48-AS48 -> 3700 | AV48: =AV46+AV47 -> 118500 | AW48: =AW46+AW47 -> 109515 | AX48: =AV48-AW48 -> 8985 | AZ48: =AZ46+AZ47 -> 118500 | BA48: =BA46+BA47 -> 149557 | BB48: =AZ48-BA48 -> -31057 | BG48: =BG46+BG47 -> 1404000 | BH48: =BH46+BH47 -> 1431136 | BI48: =BG48-BH48 -> -27136
A51: Office Expenses****
A52: Office Lease | F52: =H52+L52+P52+T52+X52+AB52+AF52+AJ52+AN52+AR52+AV52+AZ52 -> 321500 | H52: ='2024 Bdg vs Actual-CA'!O52+'2024 Bdg vs Actual -OH'!O52 -> 26200 | I52: =27952-1700 -> 26252 | J52: =H52-I52 -> -52 | L52: =+'2024 Bdg vs Actual-CA'!S52+'2024 Bdg vs Actual -OH'!S52 -> 26200 | M52: 27157 | N52: =L52-M52 -> -957 | P52: =ROUND(+'2024 Bdg vs Actual-CA'!W52+'2024 Bdg vs Actual -OH'!W52,-2) -> 26600 | Q52: 31350 | R52: =P52-Q52 -> -4750 | T52: =+'2024 Bdg vs Actual-CA'!AA52+'2024 Bdg vs Actual -OH'!AA52 -> 26600 | U52: 26358 | V52: =T52-U52 -> 242 | X52: =+'2024 Bdg vs Actual-CA'!AE52+'2024 Bdg vs Actual -OH'!AE52 -> 26600 | Y52: 25407 | Z52: =X52-Y52 -> 1193 | AB52: =+'2024 Bdg vs Actual-CA'!AI52+'2024 Bdg vs Actual -OH'!AI52 -> 26600 | AC52: 25212 | AD52: =AB52-AC52 -> 1388 | AF52: =+'2024 Bdg vs Actual-CA'!AM52+'2024 Bdg vs Actual -OH'!AM52 -> 26700 | AG52: 27192 | AH52: =AF52-AG52 -> -492 | AJ52: =+'2024 Bdg vs Actual-CA'!AQ52+'2024 Bdg vs Actual -OH'!AQ52 -> 27200 | AK52: 26310 | AL52: =AJ52-AK52 -> 890 | AN52: =+'2024 Bdg vs Actual-CA'!AU52+'2024 Bdg vs Actual -OH'!AU52 -> 27200 | AO52: 28017 | AP52: =AN52-AO52 -> -817 | AR52: =+'2024 Bdg vs Actual-CA'!AY52+'2024 Bdg vs Actual -OH'!AY52 -> 27200 | AS52: 27465 | AT52: =AR52-AS52 -> -265 | AV52: =+'2024 Bdg vs Actual-CA'!BC52+'2024 Bdg vs Actual -OH'!BC52 -> 27200 | AW52: 26216 | AX52: =AV52-AW52 -> 984 | AZ52: =+'2024 Bdg vs Actual-CA'!BG52+'2024 Bdg vs Actual -OH'!BG52 -> 27200 | BA52: 26216 | BB52: =AZ52-BA52 -> 984 | BG52: =+P52+L52+H52+T52+X52+AB52+AF52+AJ52+AN52+AR52+AV52+AZ52 -> 321500 | BH52: =+Q52+M52+I52+U52+Y52+AC52+AG52+AK52+AO52+AS52+AW52+BA52 -> 323152 | BI52: =BG52-BH52 -> -1652
A53: Insurance | F53: =H53+L53+P53+T53+X53+AB53+AF53+AJ53+AN53+AR53+AV53+AZ53 -> 120000 | H53: ='2024 Bdg vs Actual-CA'!O53+'2024 Bdg vs Actual -OH'!O53 -> 9000 | I53: 7175 | J53: =H53-I53 -> 1825 | L53: =+'2024 Bdg vs Actual-CA'!S53+'2024 Bdg vs Actual -OH'!S53 -> 10000 | M53: =-32456+40000 -> 7544 | N53: =L53-M53 -> 2456 | P53: =ROUND(+'2024 Bdg vs Actual-CA'!W53+'2024 Bdg vs Actual -OH'!W53,-2) -> 10000 | Q53: 8116 | R53: =P53-Q53 -> 1884 | T53: =+'2024 Bdg vs Actual-CA'!AA53+'2024 Bdg vs Actual -OH'!AA53 -> 10000 | U53: 4860 | V53: =T53-U53 -> 5140 | X53: =+'2024 Bdg vs Actual-CA'!AE53+'2024 Bdg vs Actual -OH'!AE53 -> 10000 | Y53: 5589 | Z53: =X53-Y53 -> 4411 | AB53: =+'2024 Bdg vs Actual-CA'!AI53+'2024 Bdg vs Actual -OH'!AI53 -> 10000 | AC53: 7749 | AD53: =AB53-AC53 -> 2251 | AF53: =+'2024 Bdg vs Actual-CA'!AM53+'2024 Bdg vs Actual -OH'!AM53 -> 10000 | AG53: 5678 | AH53: =AF53-AG53 -> 4322 | AJ53: =+'2024 Bdg vs Actual-CA'!AQ53+'2024 Bdg vs Actual -OH'!AQ53 -> 10200 | AK53: 5936 | AL53: =AJ53-AK53 -> 4264 | AN53: =+'2024 Bdg vs Actual-CA'!AU53+'2024 Bdg vs Actual -OH'!AU53 -> 10200 | AO53: 5581 | AP53: =AN53-AO53 -> 4619 | AR53: =+'2024 Bdg vs Actual-CA'!AY53+'2024 Bdg vs Actual -OH'!AY53 -> 10200 | AS53: 7074 | AT53: =AR53-AS53 -> 3126 | AV53: =+'2024 Bdg vs Actual-CA'!BC53+'2024 Bdg vs Actual -OH'!BC53 -> 10200 | AW53: 6275 | AX53: =AV53-AW53 -> 3925 | AZ53: =+'2024 Bdg vs Actual-CA'!BG53+'2024 Bdg vs Actual -OH'!BG53 -> 10200 | BA53: 6513 | BB53: =AZ53-BA53 -> 3687 | BG53: =+P53+L53+H53+T53+X53+AB53+AF53+AJ53+AN53+AR53+AV53+AZ53 -> 120000 | BH53: =+Q53+M53+I53+U53+Y53+AC53+AG53+AK53+AO53+AS53+AW53+BA53 -> 78090 | BI53: =BG53-BH53 -> 41910
A54: Utilities - Internet-Phones | F54: =H54+L54+P54+T54+X54+AB54+AF54+AJ54+AN54+AR54+AV54+AZ54 -> 150000 | H54: ='2024 Bdg vs Actual-CA'!O54+'2024 Bdg vs Actual -OH'!O54 -> 12500 | I54: 6687 | J54: =H54-I54 -> 5813 | L54: =+'2024 Bdg vs Actual-CA'!S54+'2024 Bdg vs Actual -OH'!S54 -> 12500 | M54: 15238 | N54: =L54-M54 -> -2738 | P54: =ROUND(+'2024 Bdg vs Actual-CA'!W54+'2024 Bdg vs Actual -OH'!W54,-2) -> 12500 | Q54: 11351 | R54: =P54-Q54 -> 1149 | T54: =+'2024 Bdg vs Actual-CA'!AA54+'2024 Bdg vs Actual -OH'!AA54 -> 12500 | U54: 12240 | V54: =T54-U54 -> 260 | X54: =+'2024 Bdg vs Actual-CA'!AE54+'2024 Bdg vs Actual -OH'!AE54 -> 12500 | Y54: 11655 | Z54: =X54-Y54 -> 845 | AB54: =+'2024 Bdg vs Actual-CA'!AI54+'2024 Bdg vs Actual -OH'!AI54 -> 12500 | AC54: 11543 | AD54: =AB54-AC54 -> 957 | AF54: =+'2024 Bdg vs Actual-CA'!AM54+'2024 Bdg vs Actual -OH'!AM54 -> 12500 | AG54: 10863 | AH54: =AF54-AG54 -> 1637 | AJ54: =+'2024 Bdg vs Actual-CA'!AQ54+'2024 Bdg vs Actual -OH'!AQ54 -> 12500 | AK54: 13779 | AL54: =AJ54-AK54 -> -1279 | AN54: =+'2024 Bdg vs Actual-CA'!AU54+'2024 Bdg vs Actual -OH'!AU54 -> 12500 | AO54: 15797 | AP54: =AN54-AO54 -> -3297 | AR54: =+'2024 Bdg vs Actual-CA'!AY54+'2024 Bdg vs Actual -OH'!AY54 -> 12500 | AS54: 11708 | AT54: =AR54-AS54 -> 792 | AV54: =+'2024 Bdg vs Actual-CA'!BC54+'2024 Bdg vs Actual -OH'!BC54 -> 12500 | AW54: 12706 | AX54: =AV54-AW54 -> -206 | AZ54: =+'2024 Bdg vs Actual-CA'!BG54+'2024 Bdg vs Actual -OH'!BG54 -> 12500 | BA54: 12272 | BB54: =AZ54-BA54 -> 228 | BG54: =+P54+L54+H54+T54+X54+AB54+AF54+AJ54+AN54+AR54+AV54+AZ54 -> 150000 | BH54: =+Q54+M54+I54+U54+Y54+AC54+AG54+AK54+AO54+AS54+AW54+BA54 -> 145839 | BI54: =BG54-BH54 -> 4161
A55: Repairs & Maintenance | F55: =H55+L55+P55+T55+X55+AB55+AF55+AJ55+AN55+AR55+AV55+AZ55 -> 18000 | H55: ='2024 Bdg vs Actual-CA'!O55+'2024 Bdg vs Actual -OH'!O55 -> 1500 | I55: 8164 | J55: =H55-I55 -> -6664 | L55: =+'2024 Bdg vs Actual-CA'!S55+'2024 Bdg vs Actual -OH'!S55 -> 1500 | M55: 839 | N55: =L55-M55 -> 661 | P55: =ROUND(+'2024 Bdg vs Actual-CA'!W55+'2024 Bdg vs Actual -OH'!W55,-2) -> 1500 | Q55: 300 | R55: =P55-Q55 -> 1200 | T55: =+'2024 Bdg vs Actual-CA'!AA55+'2024 Bdg vs Actual -OH'!AA55 -> 1500 | U55: 324 | V55: =T55-U55 -> 1176 | X55: =+'2024 Bdg vs Actual-CA'!AE55+'2024 Bdg vs Actual -OH'!AE55 -> 1500 | Y55: 1004 | Z55: =X55-Y55 -> 496 | AB55: =+'2024 Bdg vs Actual-CA'!AI55+'2024 Bdg vs Actual -OH'!AI55 -> 1500 | AC55: 100 | AD55: =AB55-AC55 -> 1400 | AF55: =+'2024 Bdg vs Actual-CA'!AM55+'2024 Bdg vs Actual -OH'!AM55 -> 1500 | AG55: 200 | AH55: =AF55-AG55 -> 1300 | AJ55: =+'2024 Bdg vs Actual-CA'!AQ55+'2024 Bdg vs Actual -OH'!AQ55 -> 1500 | AK55: 225 | AL55: =AJ55-AK55 -> 1275 | AN55: =+'2024 Bdg vs Actual-CA'!AU55+'2024 Bdg vs Actual -OH'!AU55 -> 1500 | AO55: 3123 | AP55: =AN55-AO55 -> -1623 | AR55: =+'2024 Bdg vs Actual-CA'!AY55+'2024 Bdg vs Actual -OH'!AY55 -> 1500 | AS55: 3960 | AT55: =AR55-AS55 -> -2460 | AV55: =+'2024 Bdg vs Actual-CA'!BC55+'2024 Bdg vs Actual -OH'!BC55 -> 1500 | AW55: 2053 | AX55: =AV55-AW55 -> -553 | AZ55: =+'2024 Bdg vs Actual-CA'!BG55+'2024 Bdg vs Actual -OH'!BG55 -> 1500 | BA55: 0 | BB55: =AZ55-BA55 -> 1500 | BG55: =+P55+L55+H55+T55+X55+AB55+AF55+AJ55+AN55+AR55+AV55+AZ55 -> 18000 | BH55: =+Q55+M55+I55+U55+Y55+AC55+AG55+AK55+AO55+AS55+AW55+BA55 -> 20292 | BI55: =BG55-BH55 -> -2292
A56: Software | F56: =H56+L56+P56+T56+X56+AB56+AF56+AJ56+AN56+AR56+AV56+AZ56 -> 233000 | H56: ='2024 Bdg vs Actual-CA'!O56+'2024 Bdg vs Actual -OH'!O56 -> 15500 | I56: 18816 | J56: =H56-I56 -> -3316 | L56: ='2024 Bdg vs Actual-CA'!S56+'2024 Bdg vs Actual -OH'!S56 -> 15500 | M56: 25015 | N56: =L56-M56 -> -9515 | P56: =ROUND(+'2024 Bdg vs Actual-CA'!W56+'2024 Bdg vs Actual -OH'!W56,-2) -> 16600 | Q56: 26440 | R56: =P56-Q56 -> -9840 | T56: ='2024 Bdg vs Actual-CA'!AA56+'2024 Bdg vs Actual -OH'!AA56 -> 20600 | U56: 23064 | V56: =T56-U56 -> -2464 | X56: ='2024 Bdg vs Actual-CA'!AE56+'2024 Bdg vs Actual -OH'!AE56 -> 20600 | Y56: 27635 | Z56: =X56-Y56 -> -7035 | AB56: ='2024 Bdg vs Actual-CA'!AI56+'2024 Bdg vs Actual -OH'!AI56 -> 20600 | AC56: 21565 | AD56: =AB56-AC56 -> -965 | AF56: ='2024 Bdg vs Actual-CA'!AM56+'2024 Bdg vs Actual -OH'!AM56 -> 20600 | AG56: 25718 | AH56: =AF56-AG56 -> -5118 | AJ56: ='2024 Bdg vs Actual-CA'!AQ56+'2024 Bdg vs Actual -OH'!AQ56 -> 20600 | AK56: 27694 | AL56: =AJ56-AK56 -> -7094 | AN56: ='2024 Bdg vs Actual-CA'!AU56+'2024 Bdg vs Actual -OH'!AU56 -> 20600 | AO56: 25409 | AP56: =AN56-AO56 -> -4809 | AR56: ='2024 Bdg vs Actual-CA'!AY56+'2024 Bdg vs Actual -OH'!AY56 -> 20600 | AS56: 19695 | AT56: =AR56-AS56 -> 905 | AV56: ='2024 Bdg vs Actual-CA'!BC56+'2024 Bdg vs Actual -OH'!BC56 -> 20600 | AW56: 29417 | AX56: =AV56-AW56 -> -8817 | AZ56: ='2024 Bdg vs Actual-CA'!BG56+'2024 Bdg vs Actual -OH'!BG56 -> 20600 | BA56: 30329 | BB56: =AZ56-BA56 -> -9729 | BG56: =+P56+L56+H56+T56+X56+AB56+AF56+AJ56+AN56+AR56+AV56+AZ56 -> 233000 | BH56: =+Q56+M56+I56+U56+Y56+AC56+AG56+AK56+AO56+AS56+AW56+BA56 -> 300797 | BI56: =BG56-BH56 -> -67797
A57: Supplies | F57: =H57+L57+P57+T57+X57+AB57+AF57+AJ57+AN57+AR57+AV57+AZ57 -> 126100 | H57: ='2024 Bdg vs Actual-CA'!O57+'2024 Bdg vs Actual -OH'!O57 -> 12300 | I57: 6387 | J57: =H57-I57 -> 5913 | L57: =+'2024 Bdg vs Actual-CA'!S57+'2024 Bdg vs Actual -OH'!S57 -> 12300 | M57: 7131 | N57: =L57-M57 -> 5169 | P57: =ROUND(+'2024 Bdg vs Actual-CA'!W57+'2024 Bdg vs Actual -OH'!W57,-2) -> 10000 | Q57: 5421 | R57: =P57-Q57 -> 4579 | T57: =+'2024 Bdg vs Actual-CA'!AA57+'2024 Bdg vs Actual -OH'!AA57 -> 10000 | U57: 7310 | V57: =T57-U57 -> 2690 | X57: =+'2024 Bdg vs Actual-CA'!AE57+'2024 Bdg vs Actual -OH'!AE57 -> 10000 | Y57: 7708 | Z57: =X57-Y57 -> 2292 | AB57: =+'2024 Bdg vs Actual-CA'!AI57+'2024 Bdg vs Actual -OH'!AI57 -> 10500 | AC57: 8439 | AD57: =AB57-AC57 -> 2061 | AF57: =+'2024 Bdg vs Actual-CA'!AM57+'2024 Bdg vs Actual -OH'!AM57 -> 10500 | AG57: 6835 | AH57: =AF57-AG57 -> 3665 | AJ57: =+'2024 Bdg vs Actual-CA'!AQ57+'2024 Bdg vs Actual -OH'!AQ57 -> 10500 | AK57: 10690 | AL57: =AJ57-AK57 -> -190 | AN57: =+'2024 Bdg vs Actual-CA'!AU57+'2024 Bdg vs Actual -OH'!AU57 -> 10000 | AO57: 12177 | AP57: =AN57-AO57 -> -2177 | AR57: =+'2024 Bdg vs Actual-CA'!AY57+'2024 Bdg vs Actual -OH'!AY57 -> 10000 | AS57: 9305 | AT57: =AR57-AS57 -> 695 | AV57: =+'2024 Bdg vs Actual-CA'!BC57+'2024 Bdg vs Actual -OH'!BC57 -> 10000 | AW57: 4929 | AX57: =AV57-AW57 -> 5071 | AZ57: =+'2024 Bdg vs Actual-CA'!BG57+'2024 Bdg vs Actual -OH'!BG57 -> 10000 | BA57: 6232 | BB57: =AZ57-BA57 -> 3768 | BG57: =+P57+L57+H57+T57+X57+AB57+AF57+AJ57+AN57+AR57+AV57+AZ57 -> 126100 | BH57: =+Q57+M57+I57+U57+Y57+AC57+AG57+AK57+AO57+AS57+AW57+BA57 -> 92564 | BI57: =BG57-BH57 -> 33536
A58: Total Office Expenses | F58: =SUM(F52:F57) -> 968600 | H58: =SUM(H52:H57) -> 77000 | I58: =SUM(I52:I57) -> 73481 | J58: =H58-I58 -> 3519 | L58: =SUM(L52:L57) -> 78000 | M58: =SUM(M52:M57) -> 82924 | N58: =L58-M58 -> -4924 | P58: =SUM(P52:P57) -> 77200 | Q58: =SUM(Q52:Q57) -> 82978 | R58: =P58-Q58 -> -5778 | T58: =SUM(T52:T57) -> 81200 | U58: =SUM(U52:U57) -> 74156 | V58: =T58-U58 -> 7044 | X58: =SUM(X52:X57) -> 81200 | Y58: =SUM(Y52:Y57) -> 78998 | Z58: =X58-Y58 -> 2202 | AB58: =SUM(AB52:AB57) -> 81700 | AC58: =SUM(AC52:AC57) -> 74608 | AD58: =AB58-AC58 -> 7092 | AF58: =SUM(AF52:AF57) -> 81800 | AG58: =SUM(AG52:AG57) -> 76486 | AH58: =AF58-AG58 -> 5314 | AJ58: =SUM(AJ52:AJ57) -> 82500 | AK58: =SUM(AK52:AK57) -> 84634 | AL58: =AJ58-AK58 -> -2134 | AN58: =SUM(AN52:AN57) -> 82000 | AO58: =SUM(AO52:AO57) -> 90104 | AP58: =AN58-AO58 -> -8104 | AR58: =SUM(AR52:AR57) -> 82000 | AS58: =SUM(AS52:AS57) -> 79207 | AT58: =AR58-AS58 -> 2793 | AV58: =SUM(AV52:AV57) -> 82000 | AW58: =SUM(AW52:AW57) -> 81596 | AX58: =AV58-AW58 -> 404 | AZ58: =SUM(AZ52:AZ57) -> 82000 | BA58: =SUM(BA52:BA57) -> 81562 | BB58: =AZ58-BA58 -> 438 | BG58: =SUM(BG52:BG57) -> 968600 | BH58: =SUM(BH52:BH57) -> 960734 | BI58: =BG58-BH58 -> 7866
A61: Professional Services*****
A62: Consulting / Legal | F62: =H62+L62+P62+T62+X62+AB62+AF62+AJ62+AN62+AR62+AV62+AZ62 -> 254800 | H62: ='2024 Bdg vs Actual-CA'!O62+'2024 Bdg vs Actual -OH'!O62 -> 23400 | I62: =15147-525-525-27-25-350 -> 13695 | J62: =H62-I62 -> 9705 | L62: ='2024 Bdg vs Actual-CA'!S62+'2024 Bdg vs Actual -OH'!S62 -> 23400 | M62: 3458 | N62: =L62-M62 -> 19942 | O62: Scott paid 2X in December | P62: =ROUND(+'2024 Bdg vs Actual-CA'!W62+'2024 Bdg vs Actual -OH'!W62,-2) -> 20800 | Q62: 25620 | R62: =P62-Q62 -> -4820 | T62: ='2024 Bdg vs Actual-CA'!AA62+'2024 Bdg vs Actual -OH'!AA62 -> 20800 | U62: =18193.41+18960 -> 37153.41 | V62: =T62-U62 -> -16353.41 | X62: ='2024 Bdg vs Actual-CA'!AE62+'2024 Bdg vs Actual -OH'!AE62 -> 20800 | Y62: 12614.34 | Z62: =X62-Y62 -> 8185.66 | AB62: ='2024 Bdg vs Actual-CA'!AI62+'2024 Bdg vs Actual -OH'!AI62 -> 20800 | AC62: =21985-350-2531 -> 19104 | AD62: =AB62-AC62 -> 1696 | AF62: ='2024 Bdg vs Actual-CA'!AM62+'2024 Bdg vs Actual -OH'!AM62 -> 20800 | AG62: 30131 | AH62: =AF62-AG62 -> -9331 | AJ62: ='2024 Bdg vs Actual-CA'!AQ62+'2024 Bdg vs Actual -OH'!AQ62 -> 20800 | AK62: =39581-350-860 -> 38371 | AL62: =AJ62-AK62 -> -17571 | AN62: ='2024 Bdg vs Actual-CA'!AU62+'2024 Bdg vs Actual -OH'!AU62 -> 20800 | AO62: 30771 | AP62: =AN62-AO62 -> -9971 | AR62: ='2024 Bdg vs Actual-CA'!AY62+'2024 Bdg vs Actual -OH'!AY62 -> 20800 | AS62: 52423.78 | AT62: =AR62-AS62 -> -31623.78 | AV62: ='2024 Bdg vs Actual-CA'!BC62+'2024 Bdg vs Actual -OH'!BC62 -> 20800 | AW62: 44520.06 | AX62: =AV62-AW62 -> -23720.06 | AZ62: ='2024 Bdg vs Actual-CA'!BG62+'2024 Bdg vs Actual -OH'!BG62 -> 20800 | BA62: =15870.27+25000 -> 40870.27 | BB62: =AZ62-BA62 -> -20070.27 | BG62: =+P62+L62+H62+T62+X62+AB62+AF62+AJ62+AN62+AR62+AV62+AZ62 -> 254800 | BH62: =+Q62+M62+I62+U62+Y62+AC62+AG62+AK62+AO62+AS62+AW62+BA62 -> 348731.86 | BI62: =BG62-BH62 -> -93931.86
A63: Accounting / CPA | F63: =H63+L63+P63+T63+X63+AB63+AF63+AJ63+AN63+AR63+AV63+AZ63 -> 13100 | H63: ='2024 Bdg vs Actual-CA'!O63+'2024 Bdg vs Actual -OH'!O63 -> 0 | I63: 350 | J63: =H63-I63 -> -350 | L63: ='2024 Bdg vs Actual-CA'!S63+'2024 Bdg vs Actual -OH'!S63 -> 0 | N63: =L63-M63 -> 0 | P63: =ROUND(+'2024 Bdg vs Actual-CA'!W63+'2024 Bdg vs Actual -OH'!W63,-2) -> 6800 | R63: =P63-Q63 -> 6800 | T63: ='2024 Bdg vs Actual-CA'!AA63+'2024 Bdg vs Actual -OH'!AA63 -> 6300 | U63: 23069 | V63: =T63-U63 -> -16769 | X63: ='2024 Bdg vs Actual-CA'!AE63+'2024 Bdg vs Actual -OH'!AE63 -> 0 | Y63: 350 | Z63: =X63-Y63 -> -350 | AB63: ='2024 Bdg vs Actual-CA'!AI63+'2024 Bdg vs Actual -OH'!AI63 -> 0 | AC63: 350 | AD63: =AB63-AC63 -> -350 | AF63: ='2024 Bdg vs Actual-CA'!AM63+'2024 Bdg vs Actual -OH'!AM63 -> 0 | AG63: 350 | AH63: =AF63-AG63 -> -350 | AJ63: ='2024 Bdg vs Actual-CA'!AQ63+'2024 Bdg vs Actual -OH'!AQ63 -> 0 | AK63: 350 | AL63: =AJ63-AK63 -> -350 | AN63: ='2024 Bdg vs Actual-CA'!AU63+'2024 Bdg vs Actual -OH'!AU63 -> 0 | AO63: 350 | AP63: =AN63-AO63 -> -350 | AR63: ='2024 Bdg vs Actual-CA'!AY63+'2024 Bdg vs Actual -OH'!AY63 -> 0 | AS63: 400 | AT63: =AR63-AS63 -> -400 | AV63: ='2024 Bdg vs Actual-CA'!BC63+'2024 Bdg vs Actual -OH'!BC63 -> 0 | AW63: 400 | AX63: =AV63-AW63 -> -400 | AZ63: ='2024 Bdg vs Actual-CA'!BG63+'2024 Bdg vs Actual -OH'!BG63 -> 0 | BA63: 400 | BB63: =AZ63-BA63 -> -400 | BG63: =+P63+L63+H63+T63+X63+AB63+AF63+AJ63+AN63+AR63+AV63+AZ63 -> 13100 | BH63: =+Q63+M63+I63+U63+Y63+AC63+AG63+AK63+AO63+AS63+AW63+BA63 -> 26369 | BI63: =BG63-BH63 -> -13269
A64: HR Recruitment + Consulting | F64: =H64+L64+P64+T64+X64+AB64+AF64+AJ64+AN64+AR64+AV64+AZ64 -> 8500 | H64: ='2024 Bdg vs Actual-CA'!O64+'2024 Bdg vs Actual -OH'!O64 -> 700 | I64: =525+525+25+27 -> 1102 | J64: =H64-I64 -> -402 | L64: ='2024 Bdg vs Actual-CA'!S64+'2024 Bdg vs Actual -OH'!S64 -> 0 | N64: =L64-M64 -> 0 | P64: =ROUND(+'2024 Bdg vs Actual-CA'!W64+'2024 Bdg vs Actual -OH'!W64,-2) -> 1400 | R64: =P64-Q64 -> 1400 | T64: ='2024 Bdg vs Actual-CA'!AA64+'2024 Bdg vs Actual -OH'!AA64 -> 0 | U64: 110.18 | V64: =T64-U64 -> -110.18 | X64: ='2024 Bdg vs Actual-CA'!AE64+'2024 Bdg vs Actual -OH'!AE64 -> 900 | Y64: 671.89 | Z64: =X64-Y64 -> 228.11 | AB64: ='2024 Bdg vs Actual-CA'!AI64+'2024 Bdg vs Actual -OH'!AI64 -> 900 | AC64: 2531.23 | AD64: =AB64-AC64 -> -1631.23 | AF64: ='2024 Bdg vs Actual-CA'!AM64+'2024 Bdg vs Actual -OH'!AM64 -> 0 | AG64: 2275 | AH64: =AF64-AG64 -> -2275 | AJ64: ='2024 Bdg vs Actual-CA'!AQ64+'2024 Bdg vs Actual -OH'!AQ64 -> 1900 | AK64: 860 | AL64: =AJ64-AK64 -> 1040 | AN64: ='2024 Bdg vs Actual-CA'!AU64+'2024 Bdg vs Actual -OH'!AU64 -> 0 | AO64: 1643.5 | AP64: =AN64-AO64 -> -1643.5 | AR64: ='2024 Bdg vs Actual-CA'!AY64+'2024 Bdg vs Actual -OH'!AY64 -> 900 | AS64: 20 | AT64: =AR64-AS64 -> 880 | AV64: ='2024 Bdg vs Actual-CA'!BC64+'2024 Bdg vs Actual -OH'!BC64 -> 900 | AW64: 1102.62 | AX64: =AV64-AW64 -> -202.62 | AZ64: ='2024 Bdg vs Actual-CA'!BG64+'2024 Bdg vs Actual -OH'!BG64 -> 900 | BA64: 1140 | BB64: =AZ64-BA64 -> -240 | BG64: =+P64+L64+H64+T64+X64+AB64+AF64+AJ64+AN64+AR64+AV64+AZ64 -> 8500 | BH64: =+Q64+M64+I64+U64+Y64+AC64+AG64+AK64+AO64+AS64+AW64+BA64 -> 11456.42 | BI64: =BG64-BH64 -> -2956.42
A65: Financial Review / Audit | F65: =H65+L65+P65+T65+X65+AB65+AF65+AJ65+AN65+AR65+AV65+AZ65 -> 33000 | H65: ='2024 Bdg vs Actual-CA'!O65+'2024 Bdg vs Actual -OH'!O65 -> 0 | J65: =H65-I65 -> 0 | L65: ='2024 Bdg vs Actual-CA'!S65+'2024 Bdg vs Actual -OH'!S65 -> 0 | N65: =L65-M65 -> 0 | P65: =ROUND(+'2024 Bdg vs Actual-CA'!W65+'2024 Bdg vs Actual -OH'!W65,-2) -> 0 | R65: =P65-Q65 -> 0 | T65: ='2024 Bdg vs Actual-CA'!AA65+'2024 Bdg vs Actual -OH'!AA65 -> 0 | U65: 7500 | V65: =T65-U65 -> -7500 | X65: ='2024 Bdg vs Actual-CA'!AE65+'2024 Bdg vs Actual -OH'!AE65 -> 0 | Z65: =X65-Y65 -> 0 | AB65: ='2024 Bdg vs Actual-CA'!AI65+'2024 Bdg vs Actual -OH'!AI65 -> 0 | AF65: ='2024 Bdg vs Actual-CA'!AM65+'2024 Bdg vs Actual -OH'!AM65 -> 0 | AJ65: ='2024 Bdg vs Actual-CA'!AQ65+'2024 Bdg vs Actual -OH'!AQ65 -> 0 | AN65: ='2024 Bdg vs Actual-CA'!AU65+'2024 Bdg vs Actual -OH'!AU65 -> 33000 | AR65: ='2024 Bdg vs Actual-CA'!AY65+'2024 Bdg vs Actual -OH'!AY65 -> 0 | AV65: ='2024 Bdg vs Actual-CA'!BC65+'2024 Bdg vs Actual -OH'!BC65 -> 0 | AX65: =AV65-AW65 -> 0 | AZ65: ='2024 Bdg vs Actual-CA'!BG65+'2024 Bdg vs Actual -OH'!BG65 -> 0 | BB65: =AZ65-BA65 -> 0 | BG65: =+P65+L65+H65+T65+X65+AB65+AF65+AJ65+AN65+AR65+AV65+AZ65 -> 33000 | BH65: =+Q65+M65+I65+U65+Y65+AC65+AG65+AK65+AO65+AS65+AW65+BA65 -> 7500 | BI65: =BG65-BH65 -> 25500
A66: Professional Services Total | F66: =SUM(F62:F65) -> 309400 | H66: =SUM(H62:H65) -> 24100 | I66: =SUM(I62:I65) -> 15147 | J66: =H66-I66 -> 8953 | L66: =SUM(L62:L65) -> 23400 | M66: =SUM(M62:M65) -> 3458 | N66: =L66-M66 -> 19942 | P66: =SUM(P62:P65) -> 29000 | Q66: =SUM(Q62:Q65) -> 25620 | R66: =P66-Q66 -> 3380 | T66: =SUM(T62:T65) -> 27100 | U66: =SUM(U62:U65) -> 67832.59 | V66: =T66-U66 -> -40732.59 | X66: =SUM(X62:X65) -> 21700 | Y66: =SUM(Y62:Y65) -> 13636.23 | Z66: =X66-Y66 -> 8063.77 | AB66: =SUM(AB62:AB65) -> 21700 | AC66: =SUM(AC62:AC65) -> 21985.23 | AD66: =AB66-AC66 -> -285.23 | AF66: =SUM(AF62:AF65) -> 20800 | AG66: =SUM(AG62:AG65) -> 32756 | AH66: =AF66-AG66 -> -11956 | AJ66: =SUM(AJ62:AJ65) -> 22700 | AK66: =SUM(AK62:AK65) -> 39581 | AL66: =AJ66-AK66 -> -16881 | AN66: =SUM(AN62:AN65) -> 53800 | AO66: =SUM(AO62:AO65) -> 32764.5 | AP66: =AN66-AO66 -> 21035.5 | AR66: =SUM(AR62:AR65) -> 21700 | AS66: =SUM(AS62:AS65) -> 52843.78 | AT66: =AR66-AS66 -> -31143.78 | AV66: =SUM(AV62:AV65) -> 21700 | AW66: =SUM(AW62:AW65) -> 46022.68 | AX66: =AV66-AW66 -> -24322.68 | AZ66: =SUM(AZ62:AZ65) -> 21700 | BA66: =SUM(BA62:BA65) -> 42410.27 | BB66: =AZ66-BA66 -> -20710.27 | BG66: =SUM(BG62:BG65) -> 309400 | BH66: =SUM(BH62:BH65) -> 394057.28 | BI66: =BG66-BH66 -> -84657.28
A68: General & Admin Expenses
A69: Charitable Contributions | F69: =H69+L69+P69+T69+X69+AB69+AF69+AJ69+AN69+AR69+AV69+AZ69 -> 35100 | H69: ='2024 Bdg vs Actual-CA'!O69+'2024 Bdg vs Actual -OH'!O69 -> 1000 | I69: 1000 | J69: =H69-I69 -> 0 | L69: ='2024 Bdg vs Actual-CA'!S69+'2024 Bdg vs Actual -OH'!S69 -> 1500 | M69: 1250 | N69: =L69-M69 -> 250 | P69: =ROUND(+'2024 Bdg vs Actual-CA'!W69+'2024 Bdg vs Actual -OH'!W69,-2) -> 2300 | Q69: 6181 | R69: =P69-Q69 -> -3881 | T69: ='2024 Bdg vs Actual-CA'!AA69+'2024 Bdg vs Actual -OH'!AA69 -> 5100 | U69: 1250 | V69: =T69-U69 -> 3850 | X69: ='2024 Bdg vs Actual-CA'!AE69+'2024 Bdg vs Actual -OH'!AE69 -> 3000 | Y69: 3613 | Z69: =X69-Y69 -> -613 | AB69: ='2024 Bdg vs Actual-CA'!AI69+'2024 Bdg vs Actual -OH'!AI69 -> 5100 | AC69: 1000 | AD69: =AB69-AC69 -> 4100 | AF69: ='2024 Bdg vs Actual-CA'!AM69+'2024 Bdg vs Actual -OH'!AM69 -> 2000 | AG69: 11000 | AH69: =AF69-AG69 -> -9000 | AJ69: ='2024 Bdg vs Actual-CA'!AQ69+'2024 Bdg vs Actual -OH'!AQ69 -> 2000 | AK69: 6098 | AL69: =AJ69-AK69 -> -4098 | AN69: ='2024 Bdg vs Actual-CA'!AU69+'2024 Bdg vs Actual -OH'!AU69 -> 2000 | AO69: 3700 | AP69: =AN69-AO69 -> -1700 | AR69: ='2024 Bdg vs Actual-CA'!AY69+'2024 Bdg vs Actual -OH'!AY69 -> 4000 | AS69: 1180 | AT69: =AR69-AS69 -> 2820 | AV69: ='2024 Bdg vs Actual-CA'!BC69+'2024 Bdg vs Actual -OH'!BC69 -> 2000 | AW69: 1000 | AX69: =AV69-AW69 -> 1000 | AZ69: ='2024 Bdg vs Actual-CA'!BG69+'2024 Bdg vs Actual -OH'!BG69 -> 5100 | BA69: 1100 | BB69: =AZ69-BA69 -> 4000 | BG69: =+P69+L69+H69+T69+X69+AB69+AF69+AJ69+AN69+AR69+AV69+AZ69 -> 35100 | BH69: =+Q69+M69+I69+U69+Y69+AC69+AG69+AK69+AO69+AS69+AW69+BA69 -> 38372 | BI69: =BG69-BH69 -> -3272
A70: Marketing & Advertising | F70: =H70+L70+P70+T70+X70+AB70+AF70+AJ70+AN70+AR70+AV70+AZ70 -> 97411.9 | H70: ='2024 Bdg vs Actual-CA'!O70+'2024 Bdg vs Actual -OH'!O70 -> 7200 | I70: 9098 | J70: =H70-I70 -> -1898 | L70: 7211.9 | M70: 10745 | N70: =L70-M70 -> -3533.1 | O70: $4K for logo shirts, mugs, and backpacks | P70: =ROUND(+'2024 Bdg vs Actual-CA'!W70+'2024 Bdg vs Actual -OH'!W70,-2) -> 8300 | Q70: 8518 | R70: =P70-Q70 -> -218 | T70: ='2024 Bdg vs Actual-CA'!AA70+'2024 Bdg vs Actual -OH'!AA70 -> 8300 | U70: 6314 | V70: =T70-U70 -> 1986 | X70: ='2024 Bdg vs Actual-CA'!AE70+'2024 Bdg vs Actual -OH'!AE70 -> 8300 | Y70: 15860 | Z70: =X70-Y70 -> -7560 | AB70: ='2024 Bdg vs Actual-CA'!AI70+'2024 Bdg vs Actual -OH'!AI70 -> 8300 | AC70: 8253 | AD70: =AB70-AC70 -> 47 | AF70: ='2024 Bdg vs Actual-CA'!AM70+'2024 Bdg vs Actual -OH'!AM70 -> 8300 | AG70: 7388 | AH70: =AF70-AG70 -> 912 | AJ70: ='2024 Bdg vs Actual-CA'!AQ70+'2024 Bdg vs Actual -OH'!AQ70 -> 8300 | AK70: 9686 | AL70: =AJ70-AK70 -> -1386 | AN70: ='2024 Bdg vs Actual-CA'!AU70+'2024 Bdg vs Actual -OH'!AU70 -> 8300 | AO70: 12243 | AP70: =AN70-AO70 -> -3943 | AR70: ='2024 Bdg vs Actual-CA'!AY70+'2024 Bdg vs Actual -OH'!AY70 -> 8300 | AS70: 17257 | AT70: =AR70-AS70 -> -8957 | AV70: ='2024 Bdg vs Actual-CA'!BC70+'2024 Bdg vs Actual -OH'!BC70 -> 8300 | AW70: 13742 | AX70: =AV70-AW70 -> -5442 | AZ70: ='2024 Bdg vs Actual-CA'!BG70+'2024 Bdg vs Actual -OH'!BG70 -> 8300 | BA70: 13146 | BB70: =AZ70-BA70 -> -4846 | BG70: =+P70+L70+H70+T70+X70+AB70+AF70+AJ70+AN70+AR70+AV70+AZ70 -> 97411.9 | BH70: =+Q70+M70+I70+U70+Y70+AC70+AG70+AK70+AO70+AS70+AW70+BA70 -> 132250 | BI70: =BG70-BH70 -> -34838.1
A71: Education & Staff Development | F71: =H71+L71+P71+T71+X71+AB71+AF71+AJ71+AN71+AR71+AV71+AZ71 -> 16200 | H71: ='2024 Bdg vs Actual-CA'!O71+'2024 Bdg vs Actual -OH'!O71 -> 1000 | I71: 1072 | J71: =H71-I71 -> -72 | L71: 1500 | M71: 1304 | N71: =L71-M71 -> 196 | P71: =ROUND(+'2024 Bdg vs Actual-CA'!W71+'2024 Bdg vs Actual -OH'!W71,-2) -> 1300 | Q71: 340 | R71: =P71-Q71 -> 960 | T71: ='2024 Bdg vs Actual-CA'!AA71+'2024 Bdg vs Actual -OH'!AA71 -> 1500 | U71: 342 | V71: =T71-U71 -> 1158 | X71: ='2024 Bdg vs Actual-CA'!AE71+'2024 Bdg vs Actual -OH'!AE71 -> 1300 | Y71: 1846 | Z71: =X71-Y71 -> -546 | AB71: ='2024 Bdg vs Actual-CA'!AI71+'2024 Bdg vs Actual -OH'!AI71 -> 1500 | AC71: 880 | AD71: =AB71-AC71 -> 620 | AF71: ='2024 Bdg vs Actual-CA'!AM71+'2024 Bdg vs Actual -OH'!AM71 -> 1300 | AG71: 310 | AH71: =AF71-AG71 -> 990 | AJ71: ='2024 Bdg vs Actual-CA'!AQ71+'2024 Bdg vs Actual -OH'!AQ71 -> 1500 | AK71: 2291 | AL71: =AJ71-AK71 -> -791 | AN71: ='2024 Bdg vs Actual-CA'!AU71+'2024 Bdg vs Actual -OH'!AU71 -> 1300 | AO71: 644 | AP71: =AN71-AO71 -> 656 | AR71: ='2024 Bdg vs Actual-CA'!AY71+'2024 Bdg vs Actual -OH'!AY71 -> 1500 | AS71: 156 | AT71: =AR71-AS71 -> 1344 | AV71: ='2024 Bdg vs Actual-CA'!BC71+'2024 Bdg vs Actual -OH'!BC71 -> 1000 | AW71: 45 | AX71: =AV71-AW71 -> 955 | AZ71: ='2024 Bdg vs Actual-CA'!BG71+'2024 Bdg vs Actual -OH'!BG71 -> 1500 | BA71: 273 | BB71: =AZ71-BA71 -> 1227 | BG71: =+P71+L71+H71+T71+X71+AB71+AF71+AJ71+AN71+AR71+AV71+AZ71 -> 16200 | BH71: =+Q71+M71+I71+U71+Y71+AC71+AG71+AK71+AO71+AS71+AW71+BA71 -> 9503 | BI71: =BG71-BH71 -> 6697
A72: General & Admin Total | F72: =SUM(F69:F71) -> 148711.9 | H72: =SUM(H69:H71) -> 9200 | I72: =SUM(I69:I71) -> 11170 | J72: =H72-I72 -> -1970 | L72: =SUM(L69:L71) -> 10211.9 | M72: =SUM(M69:M71) -> 13299 | N72: =L72-M72 -> -3087.1 | P72: =SUM(P69:P71) -> 11900 | Q72: =SUM(Q69:Q71) -> 15039 | R72: =P72-Q72 -> -3139 | T72: =SUM(T69:T71) -> 14900 | U72: =SUM(U69:U71) -> 7906 | V72: =T72-U72 -> 6994 | X72: =SUM(X69:X71) -> 12600 | Y72: =SUM(Y69:Y71) -> 21319 | Z72: =X72-Y72 -> -8719 | AB72: =SUM(AB69:AB71) -> 14900 | AC72: =SUM(AC69:AC71) -> 10133 | AD72: =AB72-AC72 -> 4767 | AF72: =SUM(AF69:AF71) -> 11600 | AG72: =SUM(AG69:AG71) -> 18698 | AH72: =AF72-AG72 -> -7098 | AJ72: =SUM(AJ69:AJ71) -> 11800 | AK72: =SUM(AK69:AK71) -> 18075 | AL72: =AJ72-AK72 -> -6275 | AN72: =SUM(AN69:AN71) -> 11600 | AO72: =SUM(AO69:AO71) -> 16587 | AP72: =AN72-AO72 -> -4987 | AR72: =SUM(AR69:AR71) -> 13800 | AS72: =SUM(AS69:AS71) -> 18593 | AT72: =AR72-AS72 -> -4793 | AV72: =SUM(AV69:AV71) -> 11300 | AW72: =SUM(AW69:AW71) -> 14787 | AX72: =AV72-AW72 -> -3487 | AZ72: =SUM(AZ69:AZ71) -> 14900 | BA72: =SUM(BA69:BA71) -> 14519 | BB72: =AZ72-BA72 -> 381 | BG72: =SUM(BG69:BG71) -> 148711.9 | BH72: =SUM(BH69:BH71) -> 180125 | BI72: =BG72-BH72 -> -31413.1
A74: Other Expenses
A75: Vehicles/ Gasoline | F75: =H75+L75+P75+T75+X75+AB75+AF75+AJ75+AN75+AR75+AV75+AZ75 -> 209600 | H75: ='2024 Bdg vs Actual-CA'!O75+'2024 Bdg vs Actual -OH'!O75 -> 18300 | I75: 16872 | J75: =H75-I75 -> 1428 | L75: ='2024 Bdg vs Actual-CA'!S75+'2024 Bdg vs Actual -OH'!S75 -> 18300 | M75: 13450 | N75: =L75-M75 -> 4850 | P75: =ROUND(+'2024 Bdg vs Actual-CA'!W75+'2024 Bdg vs Actual -OH'!W75,-2) -> 17300 | Q75: 13237 | R75: =P75-Q75 -> 4063 | T75: ='2024 Bdg vs Actual-CA'!AA75+'2024 Bdg vs Actual -OH'!AA75 -> 17300 | U75: 14195 | V75: =T75-U75 -> 3105 | X75: ='2024 Bdg vs Actual-CA'!AE75+'2024 Bdg vs Actual -OH'!AE75 -> 17300 | Y75: 14233 | Z75: =X75-Y75 -> 3067 | AB75: ='2024 Bdg vs Actual-CA'!AI75+'2024 Bdg vs Actual -OH'!AI75 -> 17300 | AC75: 16055 | AD75: =AB75-AC75 -> 1245 | AF75: ='2024 Bdg vs Actual-CA'!AM75+'2024 Bdg vs Actual -OH'!AM75 -> 17300 | AG75: 18327 | AH75: =AF75-AG75 -> -1027 | AJ75: ='2024 Bdg vs Actual-CA'!AQ75+'2024 Bdg vs Actual -OH'!AQ75 -> 17300 | AK75: 16513 | AL75: =AJ75-AK75 -> 787 | AN75: ='2024 Bdg vs Actual-CA'!AU75+'2024 Bdg vs Actual -OH'!AU75 -> 17300 | AO75: 14728 | AP75: =AN75-AO75 -> 2572 | AR75: ='2024 Bdg vs Actual-CA'!AY75+'2024 Bdg vs Actual -OH'!AY75 -> 17300 | AS75: 10429 | AT75: =AR75-AS75 -> 6871 | AV75: ='2024 Bdg vs Actual-CA'!BC75+'2024 Bdg vs Actual -OH'!BC75 -> 17300 | AW75: 7015 | AX75: =AV75-AW75 -> 10285 | AZ75: ='2024 Bdg vs Actual-CA'!BG75+'2024 Bdg vs Actual -OH'!BG75 -> 17300 | BA75: 6104 | BB75: =AZ75-BA75 -> 11196 | BG75: =+P75+L75+H75+T75+X75+AB75+AF75+AJ75+AN75+AR75+AV75+AZ75 -> 209600 | BH75: =+Q75+M75+I75+U75+Y75+AC75+AG75+AK75+AO75+AS75+AW75+BA75 -> 161158 | BI75: =BG75-BH75 -> 48442
A76: Travel / Meals | F76: =H76+L76+P76+T76+X76+AB76+AF76+AJ76+AN76+AR76+AV76+AZ76 -> 171600 | H76: ='2024 Bdg vs Actual-CA'!O76+'2024 Bdg vs Actual -OH'!O76 -> 14300 | I76: 12398 | J76: =H76-I76 -> 1902 | L76: ='2024 Bdg vs Actual-CA'!S76+'2024 Bdg vs Actual -OH'!S76 -> 14300 | M76: 31751 | N76: =L76-M76 -> -17451 | O76: See breakdown on location tabs | P76: =ROUND(+'2024 Bdg vs Actual-CA'!W76+'2024 Bdg vs Actual -OH'!W76,-2) -> 14300 | Q76: 20716 | R76: =P76-Q76 -> -6416 | T76: ='2024 Bdg vs Actual-CA'!AA76+'2024 Bdg vs Actual -OH'!AA76 -> 14300 | U76: 14774 | V76: =T76-U76 -> -474 | X76: ='2024 Bdg vs Actual-CA'!AE76+'2024 Bdg vs Actual -OH'!AE76 -> 14300 | Y76: 16372 | Z76: =X76-Y76 -> -2072 | AB76: ='2024 Bdg vs Actual-CA'!AI76+'2024 Bdg vs Actual -OH'!AI76 -> 14300 | AC76: =40277+2689 -> 42966 | AD76: =AB76-AC76 -> -28666 | AF76: ='2024 Bdg vs Actual-CA'!AM76+'2024 Bdg vs Actual -OH'!AM76 -> 14300 | AG76: 7590 | AH76: =AF76-AG76 -> 6710 | AJ76: ='2024 Bdg vs Actual-CA'!AQ76+'2024 Bdg vs Actual -OH'!AQ76 -> 14300 | AK76: 13797 | AL76: =AJ76-AK76 -> 503 | AN76: ='2024 Bdg vs Actual-CA'!AU76+'2024 Bdg vs Actual -OH'!AU76 -> 14300 | AO76: 6220 | AP76: =AN76-AO76 -> 8080 | AR76: ='2024 Bdg vs Actual-CA'!AY76+'2024 Bdg vs Actual -OH'!AY76 -> 14300 | AS76: =12724+2570 -> 15294 | AT76: =AR76-AS76 -> -994 | AV76: ='2024 Bdg vs Actual-CA'!BC76+'2024 Bdg vs Actual -OH'!BC76 -> 14300 | AW76: 18897 | AX76: =AV76-AW76 -> -4597 | AZ76: ='2024 Bdg vs Actual-CA'!BG76+'2024 Bdg vs Actual -OH'!BG76 -> 14300 | BA76: 22743 | BB76: =AZ76-BA76 -> -8443 | BG76: =+P76+L76+H76+T76+X76+AB76+AF76+AJ76+AN76+AR76+AV76+AZ76 -> 171600 | BH76: =+Q76+M76+I76+U76+Y76+AC76+AG76+AK76+AO76+AS76+AW76+BA76 -> 223518 | BI76: =BG76-BH76 -> -51918
A77: Property Taxes | F77: =H77+L77+P77+T77+X77+AB77+AF77+AJ77+AN77+AR77+AV77+AZ77 -> 60300 | H77: ='2024 Bdg vs Actual-CA'!O77+'2024 Bdg vs Actual -OH'!O77 -> 7400 | I77: 0 | J77: =H77-I77 -> 7400 | L77: ='2024 Bdg vs Actual-CA'!S77+'2024 Bdg vs Actual -OH'!S77 -> 0 | M77: 0 | N77: =L77-M77 -> 0 | P77: =ROUND(+'2024 Bdg vs Actual-CA'!W77+'2024 Bdg vs Actual -OH'!W77,-2) -> 300 | Q77: 864 | R77: =P77-Q77 -> -564 | T77: ='2024 Bdg vs Actual-CA'!AA77+'2024 Bdg vs Actual -OH'!AA77 -> 0 | U77: 640 | V77: =T77-U77 -> -640 | X77: ='2024 Bdg vs Actual-CA'!AE77+'2024 Bdg vs Actual -OH'!AE77 -> 0 | Y77: 0 | Z77: =X77-Y77 -> 0 | AB77: ='2024 Bdg vs Actual-CA'!AI77+'2024 Bdg vs Actual -OH'!AI77 -> 0 | AC77: 0 | AD77: =AB77-AC77 -> 0 | AF77: ='2024 Bdg vs Actual-CA'!AM77+'2024 Bdg vs Actual -OH'!AM77 -> 8600 | AG77: 6263 | AH77: =AF77-AG77 -> 2337 | AJ77: ='2024 Bdg vs Actual-CA'!AQ77+'2024 Bdg vs Actual -OH'!AQ77 -> 0 | AK77: 298 | AL77: =AJ77-AK77 -> -298 | AN77: ='2024 Bdg vs Actual-CA'!AU77+'2024 Bdg vs Actual -OH'!AU77 -> 3800 | AO77: 129 | AP77: =AN77-AO77 -> 3671 | AR77: ='2024 Bdg vs Actual-CA'!AY77+'2024 Bdg vs Actual -OH'!AY77 -> 1000 | AS77: 0 | AT77: =AR77-AS77 -> 1000 | AV77: ='2024 Bdg vs Actual-CA'!BC77+'2024 Bdg vs Actual -OH'!BC77 -> 15500 | AW77: 0 | AX77: =AV77-AW77 -> 15500 | AZ77: ='2024 Bdg vs Actual-CA'!BG77+'2024 Bdg vs Actual -OH'!BG77 -> 23700 | BA77: 0 | BB77: =AZ77-BA77 -> 23700 | BG77: =+P77+L77+H77+T77+X77+AB77+AF77+AJ77+AN77+AR77+AV77+AZ77 -> 60300 | BH77: =+Q77+M77+I77+U77+Y77+AC77+AG77+AK77+AO77+AS77+AW77+BA77 -> 8194 | BI77: =BG77-BH77 -> 52106
A78: Finance Charges- Merchant and Bank Fees | F78: =H78+L78+P78+T78+X78+AB78+AF78+AJ78+AN78+AR78+AV78+AZ78 -> 91400 | H78: ='2024 Bdg vs Actual-CA'!O78+'2024 Bdg vs Actual -OH'!O78 -> 7700 | I78: 8055 | J78: =H78-I78 -> -355 | L78: ='2024 Bdg vs Actual-CA'!S78+'2024 Bdg vs Actual -OH'!S78 -> 12600 | M78: 5245 | N78: =L78-M78 -> 7355 | P78: =ROUND(+'2024 Bdg vs Actual-CA'!W78+'2024 Bdg vs Actual -OH'!W78,-2) -> 6600 | Q78: 4393 | R78: =P78-Q78 -> 2207 | T78: ='2024 Bdg vs Actual-CA'!AA78+'2024 Bdg vs Actual -OH'!AA78 -> 6900 | U78: 5004 | V78: =T78-U78 -> 1896 | X78: ='2024 Bdg vs Actual-CA'!AE78+'2024 Bdg vs Actual -OH'!AE78 -> 7000 | Y78: 4091 | Z78: =X78-Y78 -> 2909 | AB78: ='2024 Bdg vs Actual-CA'!AI78+'2024 Bdg vs Actual -OH'!AI78 -> 7000 | AC78: 4971 | AD78: =AB78-AC78 -> 2029 | AF78: ='2024 Bdg vs Actual-CA'!AM78+'2024 Bdg vs Actual -OH'!AM78 -> 8000 | AG78: 5373 | AH78: =AF78-AG78 -> 2627 | AJ78: ='2024 Bdg vs Actual-CA'!AQ78+'2024 Bdg vs Actual -OH'!AQ78 -> 7700 | AK78: 5321 | AL78: =AJ78-AK78 -> 2379 | AN78: ='2024 Bdg vs Actual-CA'!AU78+'2024 Bdg vs Actual -OH'!AU78 -> 5500 | AO78: 4803 | AP78: =AN78-AO78 -> 697 | AR78: ='2024 Bdg vs Actual-CA'!AY78+'2024 Bdg vs Actual -OH'!AY78 -> 5100 | AS78: =4953+249 -> 5202 | AT78: =AR78-AS78 -> -102 | AV78: ='2024 Bdg vs Actual-CA'!BC78+'2024 Bdg vs Actual -OH'!BC78 -> 7800 | AW78: 5353 | AX78: =AV78-AW78 -> 2447 | AZ78: ='2024 Bdg vs Actual-CA'!BG78+'2024 Bdg vs Actual -OH'!BG78 -> 9500 | BA78: 6945 | BB78: =AZ78-BA78 -> 2555 | BG78: =+P78+L78+H78+T78+X78+AB78+AF78+AJ78+AN78+AR78+AV78+AZ78 -> 91400 | BH78: =+Q78+M78+I78+U78+Y78+AC78+AG78+AK78+AO78+AS78+AW78+BA78 -> 64756 | BI78: =BG78-BH78 -> 26644
A79: Other Expenses Total | F79: =SUM(F75:F78) -> 532900 | H79: =SUM(H75:H78) -> 47700 | I79: =SUM(I75:I78) -> 37325 | J79: =H79-I79 -> 10375 | L79: =SUM(L75:L78) -> 45200 | M79: =SUM(M75:M78) -> 50446 | N79: =L79-M79 -> -5246 | P79: =SUM(P75:P78) -> 38500 | Q79: =SUM(Q75:Q78) -> 39210 | R79: =P79-Q79 -> -710 | T79: =SUM(T75:T78) -> 38500 | U79: =SUM(U75:U78) -> 34613 | V79: =T79-U79 -> 3887 | X79: =SUM(X75:X78) -> 38600 | Y79: =SUM(Y75:Y78) -> 34696 | Z79: =X79-Y79 -> 3904 | AB79: =SUM(AB75:AB78) -> 38600 | AC79: =SUM(AC75:AC78) -> 63992 | AD79: =AB79-AC79 -> -25392 | AF79: =SUM(AF75:AF78) -> 48200 | AG79: =SUM(AG75:AG78) -> 37553 | AH79: =AF79-AG79 -> 10647 | AJ79: =SUM(AJ75:AJ78) -> 39300 | AK79: =SUM(AK75:AK78) -> 35929 | AL79: =AJ79-AK79 -> 3371 | AN79: =SUM(AN75:AN78) -> 40900 | AO79: =SUM(AO75:AO78) -> 25880 | AP79: =AN79-AO79 -> 15020 | AR79: =SUM(AR75:AR78) -> 37700 | AS79: =SUM(AS75:AS78) -> 30925 | AT79: =AR79-AS79 -> 6775 | AV79: =SUM(AV75:AV78) -> 54900 | AW79: =SUM(AW75:AW78) -> 31265 | AX79: =AV79-AW79 -> 23635 | AZ79: =SUM(AZ75:AZ78) -> 64800 | BA79: =SUM(BA75:BA78) -> 35792 | BB79: =AZ79-BA79 -> 29008 | BG79: =SUM(BG75:BG78) -> 532900 | BH79: =SUM(BH75:BH78) -> 457626 | BI79: =BG79-BH79 -> 75274
A81: Total Operating Expenses | F81: =F48+F58+F66+F72+F79 -> 4649111.9 | H81: =H48+H58+H66+H72+H79 -> 267100 | I81: =I48+I58+I66+I72+I79 -> 269734 | J81: =H81-I81 -> -2634 | L81: =L48+L58+L66+L72+L79 -> 265911.9 | M81: =M48+M58+M66+M72+M79 -> 262113 | N81: =L81-M81 -> 3798.9 | P81: =ROUND(+'2024 Bdg vs Actual-CA'!W81+'2024 Bdg vs Actual -OH'!W81,-2) -> 269900 | Q81: =Q48+Q58+Q66+Q72+Q79 -> 278781 | R81: =P81-Q81 -> -8881 | T81: =T48+T58+T66+T72+T79 -> 280200 | U81: =U48+U58+U66+U72+U79 -> 314542.59 | V81: =T81-U81 -> -34342.59 | X81: =X48+X58+X66+X72+X79 -> 272600 | Y81: =Y48+Y58+Y66+Y72+Y79 -> 281595.23 | Z81: =X81-Y81 -> -8995.23 | AB81: =AB48+AB58+AB66+AB72+AB79 -> 278400 | AC81: =AC48+AC58+AC66+AC72+AC79 -> 281517.23 | AD81: =AB81-AC81 -> -3117.23 | AF81: =AF48+AF58+AF66+AF72+AF79 -> 280900 | AG81: =AG48+AG58+AG66+AG72+AG79 -> 269761 | AH81: =AF81-AG81 -> 11139 | AJ81: =AJ48+AJ58+AJ66+AJ72+AJ79 -> 274800 | AK81: =AK48+AK58+AK66+AK72+AK79 -> 288366 | AL81: =AJ81-AK81 -> -13566 | AN81: =AN48+AN58+AN66+AN72+AN79 -> 306800 | AO81: =AO48+AO58+AO66+AO72+AO79 -> 270873.5 | AP81: =AN81-AO81 -> 35926.5 | AR81: =AR48+AR58+AR66+AR72+AR79 -> 276700 | AS81: =AS48+AS58+AS66+AS72+AS79 -> 299368.78 | AT81: =AR81-AS81 -> -22668.78 | AV81: =AV48+AV58+AV66+AV72+AV79 -> 288400 | AW81: =AW48+AW58+AW66+AW72+AW79 -> 283185.68 | AX81: =AV81-AW81 -> 5214.32 | AZ81: =AZ48+AZ58+AZ66+AZ72+AZ79 -> 301900 | BA81: =BA48+BA58+BA66+BA72+BA79 -> 323840.27 | BB81: =AZ81-BA81 -> -21940.27 | BG81: =BG48+BG58+BG66+BG72+BG79 -> 3363611.9 | BH81: =+Q81+M81+I81+U81+Y81+AC81+AG81+AK81+AO81+AS81+AW81+BA81 -> 3423678.3 | BI81: =BG81-BH81 -> -60066.38
A83: EBITDA | F83: =F41-F81 -> 937830.88 | H83: =H41-H81 -> 188857.63 | I83: =I41-I81 -> -14717.43 | J83: =I83-H83 -> -203575.06 | L83: =L41-L81 -> 145473.25 | M83: =M41-M81 -> 75729 | N83: =M83-L83 -> -69744.251 | P83: =P41-P81 -> 133200 | Q83: =Q41-Q81 -> -10216 | R83: =Q83-P83 -> -143416 | T83: =T41-T81 -> 132500 | U83: =U41-U81 -> 91021.41 | V83: =U83-T83 -> -41478.59 | X83: =X41-X81 -> 154800 | Y83: =Y41-Y81 -> -14310.15 | Z83: =Y83-X83 -> -169110.15 | AB83: =AB41-AB81 -> 132000 | AC83: =AC41-AC81 -> 235569.77 | AD83: =AC83-AB83 -> 103569.77 | AF83: =AF41-AF81 -> 199900 | AG83: =AG41-AG81 -> 237913 | AH83: =AG83-AF83 -> 38013 | AJ83: =AJ41-AJ81 -> 213700 | AK83: =AK41-AK81 -> 539904 | AL83: =AK83-AJ83 -> 326204 | AN83: =AN41-AN81 -> 194400 | AO83: =AO41-AO81 -> 72314.5 | AP83: =AO83-AN83 -> -122085.5 | AR83: =AR41-AR81 -> 240800 | AS83: =AS41-AS81 -> -23520.78 | AT83: =AS83-AR83 -> -264320.78 | AV83: =AV41-AV81 -> 242800 | AW83: =AW41-AW81 -> 61706.32 | AX83: =AW83-AV83 -> -181093.68 | AZ83: =AZ41-AZ81 -> 244900 | BA83: =BA41-BA81 -> -22187.53 | BB83: =BA83-AZ83 -> -267087.53 | BG83: =BG41-BG81 -> 2223330.9 | BH83: =BH41-BH81 -> 1229206.1 | BI83: =BH83-BG83 -> -994124.77
A84: EBIDTA % of Gross Sales | F84: =F83/F11 -> 0.034492424 | H84: =H83/H11 -> 0.083450933 | I84: =I83/I11 -> -0.010697964 | L84: =L83/L11 -> 0.066320851 | M84: =M83/M11 -> 0.044320488 | P84: =P83/P11 -> 0.061456123 | Q84: =Q83/Q11 -> -0.0081289298 | T84: =T83/T11 -> 0.060400237 | U84: =U83/U11 -> 0.052298051 | X84: =X83/X11 -> 0.069874515 | Y84: =Y83/Y11 -> -0.0094739905 | AB84: =AB83/AB11 -> 0.058435522 | AC84: =AC83/AC11 -> 0.091366988 | AF84: =AF83/AF11 -> 0.087740859 | AG84: =AG83/AG11 -> 0.099171656 | AJ84: =AJ83/AJ11 -> 0.093355467 | AK84: =AK83/AK11 -> 0.19375475 | AO84: =AO83/AO11 -> 0.051383889 | AS84: =AS83/AS11 -> -0.015472426 | AW84: =AW83/AW11 -> 0.034242063 | BG84: =BG83/BG11 -> 0.081771748 | BH84: =BH83/BH11 -> 0.057757079
A86: Other Income- Non Budgeted
A87: Interest Income | I87: 1028 | P87: =ROUND(+'2024 Bdg vs Actual-CA'!W87+'2024 Bdg vs Actual -OH'!W87,-2) -> 0 | T87: 0 | V87: =U87-T87 -> 0 | X87: 0 | Y87: 0 | Z87: =Y87-X87 -> 0 | AO87: 1090 | AS87: 2411 | AW87: 1801 | BA87: 1994 | BG87: =+P87+L87+H87+T87+X87+AB87+AF87+AJ87+AN87+AR87 -> 0 | BH87: =+Q87+M87+I87+U87+Y87+AC87+AG87+AK87+AO87+AS87+AW87+BA87 -> 8324 | BI87: =+BH87-BG87 -> 8324
A88: Other Income- Non Budgeted | I88: 600000 | P88: =ROUND(+'2024 Bdg vs Actual-CA'!W88+'2024 Bdg vs Actual -OH'!W88,-2) -> 0 | Q88: 35 | T88: 0 | U88: 19789 | V88: =U88-T88 -> 19789 | X88: 0 | Y88: 90848 | Z88: =Y88-X88 -> 90848 | AA88: Thomanson Tractor Final Billing | AB88: 0 | AC88: 3246 | AD88: =AC88-AB88 -> 3246 | AF88: 0 | AG88: 0 | AH88: =AG88-AF88 -> 0 | AJ88: 0 | AK88: 0 | AL88: =AK88-AJ88 -> 0 | AN88: 0 | AO88: 0 | AP88: =AO88-AN88 -> 0 | AS88: 9520 | AT88: =AS88-AR88 -> 9520 | AX88: =AW88-AV88 -> 0 | BB88: =BA88-AZ88 -> 0 | BG88: =+P88+L88+H88+T88+X88+AB88+AF88+AJ88+AN88+AR88 -> 0 | BH88: =+Q88+M88+I88+U88+Y88+AC88+AG88+AK88+AO88+AS88+AW88+BA88 -> 723438 | BI88: =+BH88-BG88 -> 723438
A89: Total Other Income | I89: =I87+I88 -> 601028 | M89: =M87+M88 -> 0 | P89: =SUM(P87:P88) -> 0 | Q89: =SUM(Q87:Q88) -> 35 | R89: =Q89-P89 -> 35 | T89: =SUM(T87:T88) -> 0 | U89: =SUM(U87:U88) -> 19789 | V89: =U89-T89 -> 19789 | X89: =SUM(X87:X88) -> 0 | Y89: =SUM(Y87:Y88) -> 90848 | Z89: =Y89-X89 -> 90848 | AB89: =SUM(AB87:AB88) -> 0 | AC89: =SUM(AC87:AC88) -> 3246 | AD89: =AC89-AB89 -> 3246 | AF89: =SUM(AF87:AF88) -> 0 | AG89: =SUM(AG87:AG88) -> 0 | AH89: =AG89-AF89 -> 0 | AJ89: =SUM(AJ87:AJ88) -> 0 | AK89: =SUM(AK87:AK88) -> 0 | AL89: =AK89-AJ89 -> 0 | AN89: =SUM(AN87:AN88) -> 0 | AO89: =SUM(AO87:AO88) -> 1090 | AP89: =AO89-AN89 -> 1090 | AS89: =SUM(AS87:AS88) -> 11931 | AT89: =AS89-AR89 -> 11931 | AW89: =SUM(AW87:AW88) -> 1801 | AX89: =AW89-AV89 -> 1801 | BA89: =SUM(BA87:BA88) -> 1994 | BB89: =BA89-AZ89 -> 1994 | BG89: =SUM(BG87:BG88) -> 0 | BH89: =SUM(BH87:BH88) -> 731762 | BI89: =BH89-BG89 -> 731762
A90: Other Expenses-
A91: Interest Expense | F91: =H91+L91+P91+T91+X91+AB91+AF91+AJ91+AN91+AR91+AV91+AZ91 -> 92900 | H91: ='2024 Bdg vs Actual-CA'!O91+'2024 Bdg vs Actual -OH'!O91 -> 10800 | I91: 11201 | J91: =H91-I91 -> -401 | L91: ='2024 Bdg vs Actual-CA'!S92+'2024 Bdg vs Actual -OH'!S91 -> 8600 | M91: 10191 | N91: =L91-M91 -> -1591 | P91: =ROUND(+'2024 Bdg vs Actual-CA'!W91+'2024 Bdg vs Actual -OH'!W91,-2) -> 10600 | Q91: 10597 | R91: =P91-Q91 -> 3 | T91: ='2024 Bdg vs Actual-CA'!AA91+'2024 Bdg vs Actual -OH'!AA91 -> 9100 | U91: 9419 | V91: =T91-U91 -> -319 | X91: ='2024 Bdg vs Actual-CA'!AE92+'2024 Bdg vs Actual -OH'!AE91 -> 7200 | Y91: 9109 | Z91: =X91-Y91 -> -1909 | AB91: ='2024 Bdg vs Actual-CA'!AI92+'2024 Bdg vs Actual -OH'!AI91 -> 7100 | AC91: 8905 | AD91: =AB91-AC91 -> -1805 | AF91: ='2024 Bdg vs Actual-CA'!AM92+'2024 Bdg vs Actual -OH'!AM91 -> 6900 | AG91: 8816 | AH91: =AF91-AG91 -> -1916 | AJ91: ='2024 Bdg vs Actual-CA'!AQ92+'2024 Bdg vs Actual -OH'!AQ91 -> 6800 | AK91: 8753 | AL91: =AJ91-AK91 -> -1953 | AN91: ='2024 Bdg vs Actual-CA'!AU92+'2024 Bdg vs Actual -OH'!AU91 -> 6700 | AO91: 8541 | AP91: =AN91-AO91 -> -1841 | AR91: ='2024 Bdg vs Actual-CA'!AY92+'2024 Bdg vs Actual -OH'!AY91 -> 6500 | AS91: 8212 | AT91: =AR91-AS91 -> -1712 | AV91: ='2024 Bdg vs Actual-CA'!BC92+'2024 Bdg vs Actual -OH'!BC91 -> 6400 | AW91: 8053 | AX91: =AV91-AW91 -> -1653 | AZ91: ='2024 Bdg vs Actual-CA'!BG92+'2024 Bdg vs Actual -OH'!BG91 -> 6200 | BA91: 7787 | BB91: =AZ91-BA91 -> -1587 | BG91: =+P91+L91+H91+T91+X91+AB91+AF91+AJ91+AN91+AR91+AV91+AZ91 -> 92900 | BH91: =+Q91+M91+I91+U91+Y91+AC91+AG91+AK91+AO91+AS91+AW91+BA91 -> 109584 | BI91: =BG91-BH91 -> -16684
A92: State and Local Income Taxes | F92: 77300 | H92: 7400 | I92: 6327 | J92: =H92-I92 -> 1073 | L92: 0 | M92: 52 | N92: =L92-M92 -> -52 | P92: =ROUND(+'2024 Bdg vs Actual-CA'!W92+'2024 Bdg vs Actual -OH'!W92,-2) -> 17000 | Q92: 3171 | R92: =P92-Q92 -> 13829 | T92: =ROUND(+'2024 Bdg vs Actual-CA'!AA92+'2024 Bdg vs Actual -OH'!AA92,-2) -> 0 | U92: 9351 | V92: =T92-U92 -> -9351 | X92: 0 | Y92: 1257 | Z92: =X92-Y92 -> -1257 | AB92: 0 | AC92: 0 | AD92: =AB92-AC92 -> 0 | AF92: 8600 | AG92: 4450 | AH92: =AF92-AG92 -> 4150 | AJ92: 0 | AK92: 1538 | AL92: =AJ92-AK92 -> -1538 | AN92: 3800 | AO92: 4118 | AP92: =AN92-AO92 -> -318 | AR92: 1000 | AS92: 7291 | AT92: =AR92-AS92 -> -6291 | AV92: 15500 | AW92: 12733 | AX92: =AV92-AW92 -> 2767 | AZ92: 23700 | BA92: 4718 | BB92: =AZ92-BA92 -> 18982 | BG92: =+P92+L92+H92+T92+X92+AB92+AF92+AJ92+AN92+AR92+AV92+AZ92 -> 77000 | BH92: =+Q92+M92+I92+U92+Y92+AC92+AG92+AK92+AO92+AS92+AW92+BA92 -> 55006 | BI92: =BG92-BH92 -> 21994
A93: Partnership Expenses | I93: 27972 | J93: =H93-I93 -> -27972 | M93: 34196 | N93: =L93-M93 -> -34196 | O93: List out | P93: =ROUND(+'2024 Bdg vs Actual-CA'!W93+'2024 Bdg vs Actual -OH'!W93,-2) -> 0 | Q93: 43552 | R93: =P93-Q93 -> -43552 | T93: 0 | U93: 28488 | V93: =T93-U93 -> -28488 | X93: 0 | Y93: 13250 | Z93: =X93-Y93 -> -13250 | AB93: 0 | AC93: 28699 | AD93: =AB93-AC93 -> -28699 | AF93: 0 | AG93: 20831 | AH93: =AF93-AG93 -> -20831 | AJ93: 0 | AK93: 15612 | AL93: =AJ93-AK93 -> -15612 | AN93: 0 | AO93: 16576 | AP93: =AN93-AO93 -> -16576 | AR93: 0 | AS93: 15462 | AT93: =AR93-AS93 -> -15462 | AV93: 0 | AW93: 15308 | AX93: =AV93-AW93 -> -15308 | AZ93: 0 | BA93: 18050 | BB93: =AZ93-BA93 -> -18050 | BG93: =+P93+L93+H93+T93+X93+AB93+AF93+AJ93+AN93+AR93+AV93+AZ93 -> 0 | BH93: =+Q93+M93+I93+U93+Y93+AC93+AG93+AK93+AO93+AS93+AW93+BA93 -> 277996 | BI93: =BG93-BH93 -> -277996
A94: Total Other Expenses | F94: =SUM(F91:F93) -> 170200 | H94: =SUM(H91:H93) -> 18200 | I94: =SUM(I91:I93) -> 45500 | J94: =H94-I94 -> -27300 | L94: =SUM(L91:L93) -> 8600 | M94: =SUM(M91:M93) -> 44439 | N94: =L94-M94 -> -35839 | P94: =SUM(P91:P93) -> 27600 | Q94: =SUM(Q91:Q93) -> 57320 | R94: =P94-Q94 -> -29720 | T94: =SUM(T91:T93) -> 9100 | U94: =SUM(U91:U93) -> 47258 | V94: =T94-U94 -> -38158 | X94: =SUM(X91:X93) -> 7200 | Y94: =SUM(Y91:Y93) -> 23616 | Z94: =X94-Y94 -> -16416 | AB94: =SUM(AB91:AB93) -> 7100 | AC94: =SUM(AC91:AC93) -> 37604 | AD94: =AB94-AC94 -> -30504 | AF94: =SUM(AF91:AF93) -> 15500 | AG94: =SUM(AG91:AG93) -> 34097 | AH94: =AF94-AG94 -> -18597 | AJ94: =SUM(AJ91:AJ93) -> 6800 | AK94: =SUM(AK91:AK93) -> 25903 | AL94: =AJ94-AK94 -> -19103 | AN94: =SUM(AN91:AN93) -> 10500 | AO94: =SUM(AO91:AO93) -> 29235 | AP94: =AN94-AO94 -> -18735 | AR94: =SUM(AR91:AR93) -> 7500 | AS94: =SUM(AS91:AS93) -> 30965 | AT94: =AR94-AS94 -> -23465 | AV94: =SUM(AV91:AV93) -> 21900 | AW94: =SUM(AW91:AW93) -> 36094 | AX94: =AV94-AW94 -> -14194 | AZ94: =SUM(AZ91:AZ93) -> 29900 | BA94: =SUM(BA91:BA93) -> 30555 | BB94: =AZ94-BA94 -> -655 | BG94: =SUM(BG91:BG93) -> 169900 | BH94: =SUM(BH91:BH93) -> 442586 | BI94: =BG94-BH94 -> -272686
A96: Total Net Income | F96: =F83+F89-F94 -> 767630.88 | H96: =H83+H89-H94 -> 170657.63 | I96: =I83+I89-I94 -> 540810.57 | J96: =I96-H96 -> 370152.94 | L96: =L83+L89-L94 -> 136873.25 | M96: =M83+M89-M94 -> 31290 | N96: =M96-L96 -> -105583.25 | P96: =P83+P89-P94 -> 105600 | Q96: =Q83+Q89-Q94 -> -67501 | R96: =Q96-P96 -> -173101 | T96: =T83+T89-T94 -> 123400 | U96: =U83+U89-U94 -> 63552.41 | V96: =U96-T96 -> -59847.59 | X96: =X83+X89-X94 -> 147600 | Y96: =Y83+Y89-Y94 -> 52921.85 | Z96: =Y96-X96 -> -94678.15 | AB96: =AB83+AB89-AB94 -> 124900 | AC96: =AC83+AC89-AC94 -> 201211.77 | AD96: =AC96-AB96 -> 76311.77 | AF96: =AF83+AF89-AF94 -> 184400 | AG96: =AG83+AG89-AG94 -> 203816 | AH96: =AG96-AF96 -> 19416 | AJ96: =AJ83+AJ89-AJ94 -> 206900 | AK96: =AK83+AK89-AK94 -> 514001 | AL96: =AK96-AJ96 -> 307101 | AN96: =AN83+AN89-AN94 -> 183900 | AO96: =AO83+AO89-AO94 -> 44169.5 | AP96: =AO96-AN96 -> -139730.5 | AR96: =AR83+AR89-AR94 -> 233300 | AS96: =AS83+AS89-AS94 -> -42554.78 | AT96: =AS96-AR96 -> -275854.78 | AV96: =AV83+AV89-AV94 -> 220900 | AW96: =AW83+AW89-AW94 -> 27413.32 | AX96: =AW96-AV96 -> -193486.68 | AZ96: =AZ83+AZ89-AZ94 -> 215000 | BA96: =BA83+BA89-BA94 -> -50748.53 | BB96: =BA96-AZ96 -> -265748.53 | BG96: =BG83+BG89-BG94 -> 2053430.9 | BH96: =BH83+BH89-BH94 -> 1518382.1 | BI96: =BH96-BG96 -> -535048.77
I97: ='[1]2024 Bdg vs Actual All'!$I$96-I96 -> -1 | M97: ='[1]2024 Bdg vs Actual All'!$M$96-M96 -> 0
A98: Net Income % of Revenue | H98: =+H96/H11 -> 0.075408859 | I98: =+I96/I11 -> 0.3931102 | L98: =+L96/L11 -> 0.062400135 | M98: =+M96/M11 -> 0.01831251 | P98: =+P96/P11 -> 0.048721971 | Q98: =+Q96/Q11 -> -0.053710933 | T98: =+T96/T11 -> 0.056251994 | U98: =+U96/U11 -> 0.036515224 | X98: =+X96/X11 -> 0.066624537 | Y98: =+Y96/Y11 -> 0.035036747 | AB98: =+AB96/AB11 -> 0.055292399 | AC98: =+AC96/AC11 -> 0.078041055 | AF98: =+AF96/AF11 -> 0.080937541 | AG98: =+AG96/AG11 -> 0.084958662 | AJ98: =+AJ96/AJ11 -> 0.090384867 | AK98: =+AK96/AK11 -> 0.18445897 | AN98: =+AN96/AN11 -> 0.079790003 | AO98: =+AO96/AO11 -> 0.03138514 | AS98: =+AS96/AS11 -> -0.027993361 | AW98: =+AW96/AW11 -> 0.015212196 | BA98: =+BA96/BA11 -> -0.042399408 | BG98: =+BG96/BG11 -> 0.075523007 | BH98: =+BH96/BH11 -> 0.071344679
BG100: =AZ96+AV96+AR96+AN96+AJ96+AF96+AB96+X96+T96+P96+L96+H96 -> 2053430.9 | BI100: =BI96/BG96 -> -0.26056332

Sheet 2024  Bdg vs Actual-CA
M1: Financial Projections | P1: Budget Vs Actual | T1: Variance | U1: (Red) | V1: Over budget | X1: Budget Vs Actual
M2: Income Statement 2023-2028 | P2: Income Statement - California | U2: Black | V2: Under budget | X2: Income Statement - California
P3: 2024 | X3: 2024
E8: Year 1* | G8: Year 2 * | I8: Year 3* | K8: Year 4 * | M8: Year 5 * | O8: January | S8: Feburary | W8: March | AA8: April | AE8: May | AI8: June | AM8: July | AQ8: August | AU8: September | AY8: October | BC8: November | BG8: December | CG8: YTD
E9: 45657 | O9: Budget | P9: Actual | Q9: Var | R9: Notes | S9: Budget | T9: Actual | U9: Var | V9: Notes | W9: Budget | X9: Actual | Y9: Var $ | Z9: Notes | AA9: Budget | AB9: Actual | AC9: Variance | AD9: Notes | AE9: Budget | AF9: Actual | AG9: Variance | AH9: Notes | AI9: Budget | AJ9: Actual | AK9: Variance | AL9: Notes | AM9: Budget | AN9: Actual | AO9: Variance | AP9: Notes | AQ9: Budget | AR9: Actual | AS9: Variance | AT9: Notes | AU9: Budget | AV9: Actual | AW9: Variance | AX9: Notes | AY9: Budget | AZ9: Actual | BA9: Variance | BB9: Notes | BC9: Budget | BD9: Actual | BE9: Variance | BF9: Notes | BG9: Budget | BH9: Actual | BI9: Variance | BJ9: Notes | BK9: Variance | BL9: Notes | CG9: Budget | CH9: Actual | CI9: Variance
A11: **Gross Sales** | E11: =SUM(E14:E23) -> 18200700 | O11: =SUM(O14:O23) -> 1542999 | P11: =+'2024 Bdg vs Actual All'!I11-'2024 Bdg vs Actual -OH'!P11 -> 840269.57 | Q11: =+P11-O11 -> -702729.4 | S11: =SUM(S14:S23) -> 1478678.8 | T11: =+'2024 Bdg vs Actual All'!M11-'2024 Bdg vs Actual -OH'!T11 -> 1238032 | U11: =+T11-S11 -> -240646.83 | W11: =SUM(W14:W23) -> 1442217.2 | X11: =+'2024 Bdg vs Actual All'!Q11-'2024 Bdg vs Actual -OH'!X11 -> 837354 | Y11: =+X11-W11 -> -604863.23 | AA11: =SUM(AA14:AA23) -> 1455488.3 | AB11: =SUM(AB14:AB23) -> 947573 | AC11: =+AB11-AA11 -> -507915.33 | AE11: =SUM(AE14:AE23) -> 1469333.3 | AF11: =SUM(AF14:AF23) -> 851142 | AG11: =+AF11-AE11 -> -618191.33 | AI11: =SUM(AI14:AI23) -> 1519265 | AJ11: =SUM(AJ14:AJ23) -> 1863270 | AK11: =+AJ11-AI11 -> 344005.01 | AM11: =SUM(AM14:AM23) -> 1526715 | AN11: =SUM(AN14:AN23) -> 1324908 | AO11: =+AN11-AM11 -> -201806.99 | AQ11: =SUM(AQ14:AQ23) -> 1530165 | AR11: =SUM(AR14:AR23) -> 1360378 | AS11: =+AR11-AQ11 -> -169786.99 | AU11: =SUM(AU14:AU23) -> 1541615 | AV11: =SUM(AV14:AV23) -> 939557 | AW11: =+AV11-AU11 -> -602057.99 | AY11: =SUM(AY14:AY23) -> 1553065 | AZ11: =SUM(AZ14:AZ23) -> 914158 | BA11: =+AZ11-AY11 -> -638906.99 | BC11: =SUM(BC14:BC23) -> 1564515 | BD11: =SUM(BD14:BD23) -> 1324777 | BE11: =+BD11-BC11 -> -239737.99 | BG11: =SUM(BG14:BG23) -> 1576601.8 | BH11: =SUM(BH14:BH23) -> 839015 | BI11: =+BH11-BG11 -> -737586.83 | CG11: =+W11+S11+O11+AA11+AE11+AI11+AM11+AQ11+AU11+AY11+BC11+BG11 -> 18200658 | CH11: =+X11+T11+P11+AB11+AF11+AJ11+AN11+AR11+AV11+AZ11+BD11+BH11 -> 13280434 | CI11: =+CH11-CG11 -> -4920224.9
A13: Services | M13: Attrition
A14: Monthly Recurring Services | D14: New Business + Current Agreements | E14: =ROUND(O14+S14+W14+AA14+AE14+AI14+AM14+AQ14+AU14+AY14+BC14+BG14,-2) -> 5276000 | M14: 0.005 | O14: 484784.11 | P14: ='2024 Bdg vs Actual All'!I14-'2024 Bdg vs Actual -OH'!P14 -> 401933.48 | Q14: =P14-O14 -> -82850.635 | S14: 400334 | T14: ='2024 Bdg vs Actual All'!M14-'2024 Bdg vs Actual -OH'!T14 -> 404034 | U14: =T14-S14 -> 3700 | V14: Pinacle Minds new client that is not renewing | W14: 393866.89 | X14: ='2024 Bdg vs Actual All'!Q14-'2024 Bdg vs Actual -OH'!X14 -> 394718 | Y14: =X14-W14 -> 851.1092 | AA14: 400000 | AB14: ='2024 Bdg vs Actual All'!U14-'2024 Bdg vs Actual -OH'!AB14 -> 388414 | AC14: =AB14-AA14 -> -11586 | AD14: Credit of Agee double March invoice, new business budget is 7875 - actual new business is 1755 (TPC), Fabricated Extrusion credit for $1800 for overbilling for 2 months and reduced bill by 900 | AE14: 406000 | AF14: ='2024 Bdg vs Actual All'!Y14-'2024 Bdg vs Actual -OH'!AF14 -> 312110 | AG14: =AF14-AE14 -> -93890 | AH14: New Business was budgeted at 15,750 and new business was only 7,350. | AI14: 441000 | AJ14: ='2024 Bdg vs Actual All'!AC14-'2024 Bdg vs Actual -OH'!AJ14 -> 387467 | AK14: =AJ14-AI14 -> -53533 | AL14: New Business was budgeted at 50,575 and new business was only 9,210. Sunny Valley was 6k under, Thomason Tractor 7K under, (both cancelled) | AM14: 445000 | AN14: ='2024 Bdg vs Actual All'!AG14-'2024 Bdg vs Actual -OH'!AN14 -> 409430 | AO14: =AN14-AM14 -> -35570 | AP14: New Business was budgeted at 58K and new business was only 48K. (Clients that left- Lammersville, Thomas tractor, Chathom- (16.4k)) (Under budget Clients- Sunny Valley -(6.2K), Chathom (3.4k), Graceada (3K), River delta (2K), Project Hope Alliance had credit for overbilling Jan- June (3K), Sylvan USD was over budget by 5K. | AQ14: 445000 | AR14: ='2024 Bdg vs Actual All'!AK14-'2024 Bdg vs Actual -OH'!AR14 -> 383691 | AS14: =AR14-AQ14 -> -61309 | AT14: New Business is 36.5K under budget,Lost companies total 24K, Gratton Elementary $1K under budget (will be caught up in Sept) | AU14: 453000 | AV14: ='2024 Bdg vs Actual All'!AO14-'2024 Bdg vs Actual -OH'!AV14 -> 385274 | AW14: =AV14-AU14 -> -67726 | AX14: No New Business - See Agreement Revenue Comparison - Sept to Aug 2024 see supplemental report for breakdown | AY14: 461000 | AZ14: ='2024 Bdg vs Actual All'!AS14-'2024 Bdg vs Actual -OH'!AZ14 -> 386945 | BA14: =AZ14-AY14 -> -74055 | BB14: No New Business - See Agreement Revenue Comparison - Sept to Aug 2024 see supplemental report for breakdown | BC14: 469000 | BD14: ='2024 Bdg vs Actual All'!AW14-'2024 Bdg vs Actual -OH'!BD14 -> 414555 | BE14: =BD14-BC14 -> -54445 | BG14: 477000 | BH14: ='2024 Bdg vs Actual All'!BA14-'2024 Bdg vs Actual -OH'!BH14 -> 437673 | BI14: =BH14-BG14 -> -39327 | BJ14: see supplemental report for breakdown | CG14: =+W14+S14+O14+AA14+AE14+AI14+AM14+AQ14+AU14+AY14+BC14+BG14 -> 5275985 | CH14: =+X14+T14+P14+AB14+AF14+AJ14+AN14+AR14+AV14+AZ14+BD14+BH14 -> 4706244.5 | CI14: =CH14-CG14 -> -569740.53
A15: Monthly Recurring Private Cloud | D15: New Business + Current Agreements | E15: =ROUND(O15+S15+W15+AA15+AE15+AI15+AM15+AQ15+AU15+AY15+BC15+BG15,-2) -> 255800 | O15: 26611.835 | P15: ='2024 Bdg vs Actual All'!I15-'2024 Bdg vs Actual -OH'!P15 -> 21937 | Q15: =P15-O15 -> -4674.835 | S15: 18042 | T15: ='2024 Bdg vs Actual All'!M15-'2024 Bdg vs Actual -OH'!T15 -> 24564 | U15: =T15-S15 -> 6522 | V15: Pinacle Minds new client that is not renewing | W15: 18041.66 | X15: ='2024 Bdg vs Actual All'!Q15-'2024 Bdg vs Actual -OH'!X15 -> 18807 | Y15: =X15-W15 -> 765.34 | AA15: 18491.66 | AB15: ='2024 Bdg vs Actual All'!U15-'2024 Bdg vs Actual -OH'!AB15 -> 20511 | AC15: =AB15-AA15 -> 2019.34 | AE15: 18000 | AF15: ='2024 Bdg vs Actual All'!Y15-'2024 Bdg vs Actual -OH'!AF15 -> 20275 | AG15: =AF15-AE15 -> 2275 | AH15: New Business was budgeted at 900 we had 2,500 in new business | AI15: 20931.66 | AJ15: ='2024 Bdg vs Actual All'!AC15-'2024 Bdg vs Actual -OH'!AJ15 -> 18128 | AK15: =AJ15-AI15 -> -2803.66 | AL15: New Business was budgeted at 2,890- we had 2,500 in new business, Thomason Tractor 1.2k under SoCal addiction 236 under(cancelled), Capital Financial 500 under, Laguna tools 400 under | AM15: 21381.66 | AN15: ='2024 Bdg vs Actual All'!AG15-'2024 Bdg vs Actual -OH'!AN15 -> 18272 | AO15: =AN15-AM15 -> -3109.66 | AP15: New Business was budgeted at 3,340- we had 2,500 in new business, Thomason Tractor 1.2k under SoCal addiction 236 under(cancelled), Capital Financial 575 under, Laguna tools 400 under, City of Firbaigh 300 over | AQ15: 21831.66 | AR15: ='2024 Bdg vs Actual All'!AK15-'2024 Bdg vs Actual -OH'!AR15 -> 18250 | AS15: =AR15-AQ15 -> -3581.66 | AT15: New Business is 1.2K under budget, lost business 2.7K, | AU15: 22281.66 | AV15: ='2024 Bdg vs Actual All'!AO15-'2024 Bdg vs Actual -OH'!AV15 -> 22059 | AW15: =AV15-AU15 -> -222.66 | AY15: 22731.66 | AZ15: ='2024 Bdg vs Actual All'!AS15-'2024 Bdg vs Actual -OH'!AZ15 -> 26554 | BA15: =AZ15-AY15 -> 3822.34 | BC15: 23181.66 | BD15: ='2024 Bdg vs Actual All'!AW15-'2024 Bdg vs Actual -OH'!BD15 -> 17924 | BE15: =BD15-BC15 -> -5257.66 | BG15: 24268.5 | BH15: ='2024 Bdg vs Actual All'!BA15-'2024 Bdg vs Actual -OH'!BH15 -> 21850 | BI15: =BH15-BG15 -> -2418.5 | CG15: =+W15+S15+O15+AA15+AE15+AI15+AM15+AQ15+AU15+AY15+BC15+BG15 -> 255795.62 | CH15: =+X15+T15+P15+AB15+AF15+AJ15+AN15+AR15+AV15+AZ15+BD15+BH15 -> 249131 | CI15: =CH15-CG15 -> -6664.6151
A16: Monthly Recurring Resale | D16: New Business + Current Agreements | E16: =ROUND(O16+S16+W16+AA16+AE16+AI16+AM16+AQ16+AU16+AY16+BC16+BG16,-2) -> 2440300 | O16: 180269.69 | P16: ='2024 Bdg vs Actual All'!I16-'2024 Bdg vs Actual -OH'!P16 -> 199323.86 | Q16: =P16-O16 -> 19054.173 | S16: 196417 | T16: ='2024 Bdg vs Actual All'!M16-'2024 Bdg vs Actual -OH'!T16 -> 196648 | U16: =T16-S16 -> 231 | W16: 178975.34 | X16: ='2024 Bdg vs Actual All'!Q16-'2024 Bdg vs Actual -OH'!X16 -> 181582 | Y16: =X16-W16 -> 2606.6588 | Z16: Agee Construction up $1200- duplicate invoice- correction in April- New customer Carmel USD | AA16: 185663.34 | AB16: ='2024 Bdg vs Actual All'!U16-'2024 Bdg vs Actual -OH'!AB16 -> 195163 | AC16: =AB16-AA16 -> 9499.6588 | AD16: Lucia Mar New Business $4k, City of Selma new agreement increase 2.7K, Catch up billing Dehart, | AE16: 194000 | AF16: ='2024 Bdg vs Actual All'!Y16-'2024 Bdg vs Actual -OH'!AF16 -> 193173 | AG16: =AF16-AE16 -> -827 | AH16: New Business was budgeted at 5850.00 and we actually had 8,738 in new business- | AI16: 206000 | AJ16: ='2024 Bdg vs Actual All'!AC16-'2024 Bdg vs Actual -OH'!AJ16 -> 198029 | AK16: =AJ16-AI16 -> -7971 | AL16: New Business was budgeted at 18,785.00, new business was 2K, City of Selma 2.7K over budget, Dehart 1.7K over budget, Graceada 2K over budget, Lucia Mar 4.9K over budget, Trumark 2K over budget, John Potter 1K under budget, Thomaston 1.5K under budget, SunnyValley 1.9K under budget | AM16: 209000 | AN16: ='2024 Bdg vs Actual All'!AG16-'2024 Bdg vs Actual -OH'!AN16 -> 199828 | AO16: =AN16-AM16 -> -9172 | AP16: New Business was budgeted at 21,700.00, new business was 2.7K,(Over Budget -City of Selma 2.7Kt, Dehart 1.8K, Graceada 1.2K, Lucia Mar 6K, Trumark 1.5K,Cranbrook 750),- (Under budget- John Potter (1K), ThomasonTractor- left(1.5K), Learning Quest-left(1.1K), and Sylvan(875)). | AQ16: 212000 | AR16: ='2024 Bdg vs Actual All'!AK16-'2024 Bdg vs Actual -OH'!AR16 -> 197654 | AS16: =AR16-AQ16 -> -14346 | AT16: New Business is 24K under budget, lost business 4K, City of Selma 2.7K over budget, Dehart 1.7K over budget, Fabricated Extrusion 1K over budget, Lucia Mar 5K over budget | AU16: 215000 | AV16: ='2024 Bdg vs Actual All'!AO16-'2024 Bdg vs Actual -OH'!AV16 -> 205177 | AW16: =AV16-AU16 -> -9823 | AY16: 218000 | AZ16: ='2024 Bdg vs Actual All'!AS16-'2024 Bdg vs Actual -OH'!AZ16 -> 212080 | BA16: =AZ16-AY16 -> -5920 | BC16: 221000 | BD16: ='2024 Bdg vs Actual All'!AW16-'2024 Bdg vs Actual -OH'!BD16 -> 212141 | BE16: =BD16-BC16 -> -8859 | BG16: 224000 | BH16: ='2024 Bdg vs Actual All'!BA16-'2024 Bdg vs Actual -OH'!BH16 -> 217770 | BI16: =BH16-BG16 -> -6230 | CG16: =+W16+S16+O16+AA16+AE16+AI16+AM16+AQ16+AU16+AY16+BC16+BG16 -> 2440325.4 | CH16: =+X16+T16+P16+AB16+AF16+AJ16+AN16+AR16+AV16+AZ16+BD16+BH16 -> 2408568.9 | CI16: =CH16-CG16 -> -31756.509
A17: IT Project Services | D17: New Business | E17: =ROUND(O17+S17+W17+AA17+AE17+AI17+AM17+AQ17+AU17+AY17+BC17+BG17,-2) -> 618900 | O17: 51754.5 | P17: ='2024 Bdg vs Actual All'!I17-'2024 Bdg vs Actual -OH'!P17 -> 27228.23 | Q17: =P17-O17 -> -24526.27 | S17: 49608 | T17: ='2024 Bdg vs Actual All'!M17-'2024 Bdg vs Actual -OH'!T17 -> 49608 | U17: =T17-S17 -> 0 | W17: 51754.5 | X17: ='2024 Bdg vs Actual All'!Q17-'2024 Bdg vs Actual -OH'!X17 -> 44366 | Y17: =X17-W17 -> -7388.5 | AA17: 51754.5 | AB17: ='2024 Bdg vs Actual All'!U17-'2024 Bdg vs Actual -OH'!AB17 -> 131293 | AC17: =AB17-AA17 -> 79538.5 | AD17: Modesto City Project completed | AE17: 51754.5 | AF17: ='2024 Bdg vs Actual All'!Y17-'2024 Bdg vs Actual -OH'!AF17 -> 148275 | AG17: =AF17-AE17 -> 96520.5 | AH17: Empire USD $50K Final Billing | AI17: 51754.5 | AJ17: ='2024 Bdg vs Actual All'!AC17-'2024 Bdg vs Actual -OH'!AJ17 -> 71950 | AK17: =AJ17-AI17 -> 20195.5 | AM17: 51754.5 | AN17: ='2024 Bdg vs Actual All'!AG17-'2024 Bdg vs Actual -OH'!AN17 -> 23582 | AO17: =AN17-AM17 -> -28172.5 | AQ17: 51754.5 | AR17: ='2024 Bdg vs Actual All'!AK17-'2024 Bdg vs Actual -OH'!AR17 -> 171887 | AS17: =AR17-AQ17 -> 120132.5 | AT17: Lucia Mar 150K | AU17: 51754.5 | AV17: ='2024 Bdg vs Actual All'!AO17-'2024 Bdg vs Actual -OH'!AV17 -> 34501 | AW17: =AV17-AU17 -> -17253.5 | AX17: See Breakdown in Project and Product Sales Sept 2024 for details | AY17: 51754.5 | AZ17: ='2024 Bdg vs Actual All'!AS17-'2024 Bdg vs Actual -OH'!AZ17 -> 41200 | BA17: =AZ17-AY17 -> -10554.5 | BB17: See Breakdown in Project and Product Sales Sept 2024 for details | BC17: 51754.5 | BD17: ='2024 Bdg vs Actual All'!AW17-'2024 Bdg vs Actual -OH'!BD17 -> 30800 | BE17: =BD17-BC17 -> -20954.5 | BG17: 51754.5 | BH17: ='2024 Bdg vs Actual All'!BA17-'2024 Bdg vs Actual -OH'!BH17 -> 33100 | BI17: =BH17-BG17 -> -18654.5 | CG17: =+W17+S17+O17+AA17+AE17+AI17+AM17+AQ17+AU17+AY17+BC17+BG17 -> 618907.5 | CH17: =+X17+T17+P17+AB17+AF17+AJ17+AN17+AR17+AV17+AZ17+BD17+BH17 -> 807790.23 | CI17: =CH17-CG17 -> 188882.73
A18: Subcontracted Services | D18: New Business | E18: =ROUND(O18+S18+W18+AA18+AE18+AI18+AM18+AQ18+AU18+AY18+BC18+BG18,-2) -> 695900 | O18: 56763 | P18: ='2024 Bdg vs Actual All'!I18-'2024 Bdg vs Actual -OH'!P18 -> 5209 | Q18: =P18-O18 -> -51554 | S18: 71462 | T18: ='2024 Bdg vs Actual All'!M18-'2024 Bdg vs Actual -OH'!T18 -> 71462 | U18: =T18-S18 -> 0 | W18: 56763 | X18: ='2024 Bdg vs Actual All'!Q18-'2024 Bdg vs Actual -OH'!X18 -> 15971 | Y18: =X18-W18 -> -40792 | AA18: 56763 | AB18: ='2024 Bdg vs Actual All'!U18-'2024 Bdg vs Actual -OH'!AB18 -> 10805 | AC18: =AB18-AA18 -> -45958 | AE18: 56763 | AF18: ='2024 Bdg vs Actual All'!Y18-'2024 Bdg vs Actual -OH'!AF18 -> 14230 | AG18: =AF18-AE18 -> -42533 | AI18: 56763 | AJ18: ='2024 Bdg vs Actual All'!AC18-'2024 Bdg vs Actual -OH'!AJ18 -> 5640 | AK18: =AJ18-AI18 -> -51123 | AM18: 56763 | AN18: ='2024 Bdg vs Actual All'!AG18-'2024 Bdg vs Actual -OH'!AN18 -> 14851 | AO18: =AN18-AM18 -> -41912 | AQ18: 56763 | AR18: ='2024 Bdg vs Actual All'!AK18-'2024 Bdg vs Actual -OH'!AR18 -> 109670 | AS18: =AR18-AQ18 -> 52907 | AT18: Lucia Mar 102K | AU18: 56763 | AV18: ='2024 Bdg vs Actual All'!AO18-'2024 Bdg vs Actual -OH'!AV18 -> 24969 | AW18: =AV18-AU18 -> -31794 | AY18: 56763 | AZ18: ='2024 Bdg vs Actual All'!AS18-'2024 Bdg vs Actual -OH'!AZ18 -> 32496 | BA18: =AZ18-AY18 -> -24267 | BC18: 56763 | BD18: ='2024 Bdg vs Actual All'!AW18-'2024 Bdg vs Actual -OH'!BD18 -> 12751 | BE18: =BD18-BC18 -> -44012 | BG18: 56763 | BH18: ='2024 Bdg vs Actual All'!BA18-'2024 Bdg vs Actual -OH'!BH18 -> 25687 | BI18: =BH18-BG18 -> -31076 | CG18: =+W18+S18+O18+AA18+AE18+AI18+AM18+AQ18+AU18+AY18+BC18+BG18 -> 695855 | CH18: =+X18+T18+P18+AB18+AF18+AJ18+AN18+AR18+AV18+AZ18+BD18+BH18 -> 343741 | CI18: =CH18-CG18 -> -352114
A21: Product Sales
A22: Product Resale | D22: New Business | E22: =ROUND(O22+S22+W22+AA22+AE22+AI22+AM22+AQ22+AU22+AY22+BC22+BG22,-2) -> 8714800 | O22: 726232.5 | P22: ='2024 Bdg vs Actual All'!I22-'2024 Bdg vs Actual -OH'!P22 -> 172471 | Q22: =P22-O22 -> -553761.5 | S22: 726232.5 | T22: ='2024 Bdg vs Actual All'!M22-'2024 Bdg vs Actual -OH'!T22 -> 484798 | U22: =T22-S22 -> -241434.5 | V22: Lucia Mar Licenses $231K & MCS Switches $139K billed this month | W22: 726232.5 | X22: ='2024 Bdg vs Actual All'!Q22-'2024 Bdg vs Actual -OH'!X22 -> 166933 | Y22: =X22-W22 -> -559299.5 | AA22: 726232.5 | AB22: ='2024 Bdg vs Actual All'!U22-'2024 Bdg vs Actual -OH'!AB22 -> 196717 | AC22: =AB22-AA22 -> -529515.5 | AE22: 726232.5 | AF22: ='2024 Bdg vs Actual All'!Y22-'2024 Bdg vs Actual -OH'!AF22 -> 155736 | AG22: =AF22-AE22 -> -570496.5 | AI22: 726232.5 | AJ22: ='2024 Bdg vs Actual All'!AC22-'2024 Bdg vs Actual -OH'!AJ22 -> 1175975 | AK22: =AJ22-AI22 -> 449742.5 | AM22: 726232.5 | AN22: ='2024 Bdg vs Actual All'!AG22-'2024 Bdg vs Actual -OH'!AN22 -> 652914 | AO22: =AN22-AM22 -> -73318.5 | AQ22: 726232.5 | AR22: ='2024 Bdg vs Actual All'!AK22-'2024 Bdg vs Actual -OH'!AR22 -> 471667 | AS22: =AR22-AQ22 -> -254565.5 | AT22: Washington USD 127K, Newman Crows 94K, Stanislaus USD 76K, Stanislaus Food 20K | AU22: 726232.5 | AV22: ='2024 Bdg vs Actual All'!AO22-'2024 Bdg vs Actual -OH'!AV22 -> 249412 | AW22: =AV22-AU22 -> -476820.5 | AX22: See Breakdown in Project and Product Sales Sept 2024 for details | AY22: 726232.5 | AZ22: ='2024 Bdg vs Actual All'!AS22-'2024 Bdg vs Actual -OH'!AZ22 -> 207123 | BA22: =AZ22-AY22 -> -519109.5 | BB22: See Breakdown in Project and Product Sales Sept 2024 for details | BC22: 726232.5 | BD22: ='2024 Bdg vs Actual All'!AW22-'2024 Bdg vs Actual -OH'!BD22 -> 630352 | BE22: =BD22-BC22 -> -95880.5 | BF22: See Breakdown in Project and Product Sales Sept 2024 for details | BG22: 726232.5 | BH22: ='2024 Bdg vs Actual All'!BA22-'2024 Bdg vs Actual -OH'!BH22 -> 96681 | BI22: =BH22-BG22 -> -629551.5 | CG22: =+W22+S22+O22+AA22+AE22+AI22+AM22+AQ22+AU22+AY22+BC22+BG22 -> 8714790 | CH22: =+X22+T22+P22+AB22+AF22+AJ22+AN22+AR22+AV22+AZ22+BD22+BH22 -> 4660779 | CI22: =CH22-CG22 -> -4054011
A23: Other Revenue | E23: =ROUND(O23+S23+W23+AA23+AE23+AI23+AM23+AQ23+AU23+AY23+BC23+BG23,-2) -> 199000 | O23: 16583.333 | P23: ='2024 Bdg vs Actual All'!I23-'2024 Bdg vs Actual -OH'!P23 -> 12167 | Q23: =P23-O23 -> -4416.3333 | S23: 16583.333 | T23: ='2024 Bdg vs Actual All'!M23-'2024 Bdg vs Actual -OH'!T23 -> 6918 | U23: =T23-S23 -> -9665.3333 | W23: 16583.333 | X23: ='2024 Bdg vs Actual All'!Q23-'2024 Bdg vs Actual -OH'!X23 -> 14977 | Y23: =X23-W23 -> -1606.3333 | AA23: 16583.333 | AB23: ='2024 Bdg vs Actual All'!U23-'2024 Bdg vs Actual -OH'!AB23 -> 4670 | AC23: =AB23-AA23 -> -11913.333 | AE23: 16583.333 | AF23: ='2024 Bdg vs Actual All'!Y23-'2024 Bdg vs Actual -OH'!AF23 -> 7343 | AG23: =AF23-AE23 -> -9240.3333 | AI23: 16583.333 | AJ23: ='2024 Bdg vs Actual All'!AC23-'2024 Bdg vs Actual -OH'!AJ23 -> 6081 | AK23: =AJ23-AI23 -> -10502.333 | AM23: 16583.333 | AN23: ='2024 Bdg vs Actual All'!AG23-'2024 Bdg vs Actual -OH'!AN23 -> 6031 | AO23: =AN23-AM23 -> -10552.333 | AQ23: 16583.333 | AR23: ='2024 Bdg vs Actual All'!AK23-'2024 Bdg vs Actual -OH'!AR23 -> 7559 | AS23: =AR23-AQ23 -> -9024.3333 | AU23: 16583.333 | AV23: ='2024 Bdg vs Actual All'!AO23-'2024 Bdg vs Actual -OH'!AV23 -> 18165 | AW23: =AV23-AU23 -> 1581.6667 | AY23: 16583.333 | AZ23: ='2024 Bdg vs Actual All'!AS23-'2024 Bdg vs Actual -OH'!AZ23 -> 7760 | BA23: =AZ23-AY23 -> -8823.3333 | BC23: 16583.333 | BD23: ='2024 Bdg vs Actual All'!AW23-'2024 Bdg vs Actual -OH'!BD23 -> 6254 | BE23: =BD23-BC23 -> -10329.333 | BG23: 16583.333 | BH23: ='2024 Bdg vs Actual All'!BA23-'2024 Bdg vs Actual -OH'!BH23 -> 6254 | BI23: =BH23-BG23 -> -10329.333 | CG23: =+W23+S23+O23+AA23+AE23+AI23+AM23+AQ23+AU23+AY23+BC23+BG23 -> 199000 | CH23: =+X23+T23+P23+AB23+AF23+AJ23+AN23+AR23+AV23+AZ23+BD23+BH23 -> 104179 | CI23: =CH23-CG23 -> -94821
A25: Cost of Services- **
A26: Costs of Monthly Recurring Services | E26: =ROUND(O26+S26+W26+AA26+AE26+AI26+AM26+AQ26+AU26+AY26+BC26+BG26,-2) -> 174100 | O26: =ROUND(O14*0.033, -2) -> 16000 | P26: ='2024 Bdg vs Actual All'!I26-'2024 Bdg vs Actual -OH'!P26 -> 13219 | Q26: =O26-P26 -> 2781 | S26: =ROUND(S14*0.033, -2) -> 13200 | T26: ='2024 Bdg vs Actual All'!M26-'2024 Bdg vs Actual -OH'!T26 -> 15915 | U26: =S26-T26 -> -2715 | W26: =ROUND(W14*0.033, -2) -> 13000 | X26: ='2024 Bdg vs Actual All'!Q26-'2024 Bdg vs Actual -OH'!X26 -> 18585 | Y26: =W26-X26 -> -5585 | AA26: =ROUND(AA14*0.033, -2) -> 13200 | AB26: ='2024 Bdg vs Actual All'!U26-'2024 Bdg vs Actual -OH'!AB26 -> 25820 | AC26: =AA26-AB26 -> -12620 | AE26: =ROUND(AE14*0.033, -2) -> 13400 | AF26: ='2024 Bdg vs Actual All'!Y26-'2024 Bdg vs Actual -OH'!AF26 -> 15838 | AG26: =AE26-AF26 -> -2438 | AI26: =ROUND(AI14*0.033, -2) -> 14600 | AJ26: ='2024 Bdg vs Actual All'!AC26-'2024 Bdg vs Actual -OH'!AJ26 -> 15995 | AK26: =AI26-AJ26 -> -1395 | AM26: =ROUND(AM14*0.033, -2) -> 14700 | AN26: ='2024 Bdg vs Actual All'!AG26-'2024 Bdg vs Actual -OH'!AN26 -> 17768 | AO26: =AM26-AN26 -> -3068 | AQ26: =ROUND(AQ14*0.033, -2) -> 14700 | AR26: ='2024 Bdg vs Actual All'!AK26-'2024 Bdg vs Actual -OH'!AR26 -> 11472 | AS26: =AQ26-AR26 -> 3228 | AU26: =ROUND(AU14*0.033, -2) -> 14900 | AV26: ='2024 Bdg vs Actual All'!AO26-'2024 Bdg vs Actual -OH'!AV26 -> 11644 | AW26: =AU26-AV26 -> 3256 | AY26: =ROUND(AY14*0.033, -2) -> 15200 | AZ26: ='2024 Bdg vs Actual All'!AS26-'2024 Bdg vs Actual -OH'!AZ26 -> 11122 | BA26: =AY26-AZ26 -> 4078 | BC26: =ROUND(BC14*0.033, -2) -> 15500 | BD26: ='2024 Bdg vs Actual All'!AW26-'2024 Bdg vs Actual -OH'!BD26 -> 14702 | BE26: =BC26-BD26 -> 798 | BG26: =ROUND(BG14*0.033, -2) -> 15700 | BH26: ='2024 Bdg vs Actual All'!BA26-'2024 Bdg vs Actual -OH'!BH26 -> 10598 | BI26: =BG26-BH26 -> 5102 | CG26: =+W26+S26+O26+AA26+AE26+AI26+AM26+AQ26+AU26+AY26+BC26+BG26 -> 174100 | CH26: =+X26+T26+P26+AB26+AF26+AJ26+AN26+AR26+AV26+AZ26+BD26+BH26 -> 182678 | CI26: =CG26-CH26 -> -8578 | CJ26: =CH26/CH14 -> 0.038816088
A27: Costs of Recur Private Cloud | E27: =ROUND(O27+S27+W27+AA27+AE27+AI27+AM27+AQ27+AU27+AY27+BC27+BG27,-2) -> 185600 | O27: =ROUND(O15*0.725, -2) -> 19300 | P27: ='2024 Bdg vs Actual All'!I27-'2024 Bdg vs Actual -OH'!P27 -> 13334 | Q27: =O27-P27 -> 5966 | S27: =ROUND(S15*0.725, -2) -> 13100 | T27: ='2024 Bdg vs Actual All'!M27-'2024 Bdg vs Actual -OH'!T27 -> 12968 | U27: =S27-T27 -> 132 | W27: =ROUND(W15*0.725, -2) -> 13100 | X27: ='2024 Bdg vs Actual All'!Q27-'2024 Bdg vs Actual -OH'!X27 -> 8745 | Y27: =W27-X27 -> 4355 | AA27: =ROUND(AA15*0.725, -2) -> 13400 | AB27: ='2024 Bdg vs Actual All'!U27-'2024 Bdg vs Actual -OH'!AB27 -> 5436 | AC27: =AA27-AB27 -> 7964 | AE27: =ROUND(AE15*0.725, -2) -> 13100 | AF27: ='2024 Bdg vs Actual All'!Y27-'2024 Bdg vs Actual -OH'!AF27 -> 9138 | AG27: =AE27-AF27 -> 3962 | AI27: =ROUND(AI15*0.725, -2) -> 15200 | AJ27: ='2024 Bdg vs Actual All'!AC27-'2024 Bdg vs Actual -OH'!AJ27 -> 7867 | AK27: =AI27-AJ27 -> 7333 | AM27: =ROUND(AM15*0.725, -2) -> 15500 | AN27: ='2024 Bdg vs Actual All'!AG27-'2024 Bdg vs Actual -OH'!AN27 -> 8470 | AO27: =AM27-AN27 -> 7030 | AQ27: =ROUND(AQ15*0.725, -2) -> 15800 | AR27: ='2024 Bdg vs Actual All'!AK27-'2024 Bdg vs Actual -OH'!AR27 -> 7841 | AS27: =AQ27-AR27 -> 7959 | AU27: =ROUND(AU15*0.725, -2) -> 16200 | AV27: ='2024 Bdg vs Actual All'!AO27-'2024 Bdg vs Actual -OH'!AV27 -> 9617 | AW27: =AU27-AV27 -> 6583 | AY27: =ROUND(AY15*0.725, -2) -> 16500 | AZ27: ='2024 Bdg vs Actual All'!AS27-'2024 Bdg vs Actual -OH'!AZ27 -> 10737 | BA27: =AY27-AZ27 -> 5763 | BC27: =ROUND(BC15*0.725, -2) -> 16800 | BD27: ='2024 Bdg vs Actual All'!AW27-'2024 Bdg vs Actual -OH'!BD27 -> 7273 | BE27: =BC27-BD27 -> 9527 | BG27: =ROUND(BG15*0.725, -2) -> 17600 | BH27: ='2024 Bdg vs Actual All'!BA27-'2024 Bdg vs Actual -OH'!BH27 -> 9786 | BI27: =BG27-BH27 -> 7814 | CG27: =+W27+S27+O27+AA27+AE27+AI27+AM27+AQ27+AU27+AY27+BC27+BG27 -> 185600 | CH27: =+X27+T27+P27+AB27+AF27+AJ27+AN27+AR27+AV27+AZ27+BD27+BH27 -> 111212 | CI27: =CG27-CH27 -> 74388 | CJ27: =CH27/CH15 -> 0.44639969
A28: Costs of Monthly Recurring Resale | E28: =ROUND(O28+S28+W28+AA28+AE28+AI28+AM28+AQ28+AU28+AY28+BC28+BG28,-2) -> 1578800 | O28: =ROUND(O16*0.647, -2) -> 116600 | P28: ='2024 Bdg vs Actual All'!I28-'2024 Bdg vs Actual -OH'!P28 -> 136650 | Q28: =O28-P28 -> -20050 | S28: =ROUND(S16*0.647, -2) -> 127100 | T28: ='2024 Bdg vs Actual All'!M28-'2024 Bdg vs Actual -OH'!T28 -> 150388 | U28: =S28-T28 -> -23288 | W28: =ROUND(W16*0.647, -2) -> 115800 | X28: ='2024 Bdg vs Actual All'!Q28-'2024 Bdg vs Actual -OH'!X28 -> 139780 | Y28: =W28-X28 -> -23980 | AA28: =ROUND(AA16*0.647, -2) -> 120100 | AB28: ='2024 Bdg vs Actual All'!U28-'2024 Bdg vs Actual -OH'!AB28 -> 137295 | AC28: =AA28-AB28 -> -17195 | AE28: =ROUND(AE16*0.647, -2) -> 125500 | AF28: ='2024 Bdg vs Actual All'!Y28-'2024 Bdg vs Actual -OH'!AF28 -> 139422 | AG28: =AE28-AF28 -> -13922 | AI28: =ROUND(AI16*0.647, -2) -> 133300 | AJ28: ='2024 Bdg vs Actual All'!AC28-'2024 Bdg vs Actual -OH'!AJ28 -> 133576 | AK28: =AI28-AJ28 -> -276 | AM28: =ROUND(AM16*0.647, -2) -> 135200 | AN28: ='2024 Bdg vs Actual All'!AG28-'2024 Bdg vs Actual -OH'!AN28 -> 130556 | AO28: =AM28-AN28 -> 4644 | AQ28: =ROUND(AQ16*0.647, -2) -> 137200 | AR28: ='2024 Bdg vs Actual All'!AK28-'2024 Bdg vs Actual -OH'!AR28 -> 131785 | AS28: =AQ28-AR28 -> 5415 | AU28: =ROUND(AU16*0.647, -2) -> 139100 | AV28: ='2024 Bdg vs Actual All'!AO28-'2024 Bdg vs Actual -OH'!AV28 -> 146220 | AW28: =AU28-AV28 -> -7120 | AY28: =ROUND(AY16*0.647, -2) -> 141000 | AZ28: ='2024 Bdg vs Actual All'!AS28-'2024 Bdg vs Actual -OH'!AZ28 -> 145713 | BA28: =AY28-AZ28 -> -4713 | BC28: =ROUND(BC16*0.647, -2) -> 143000 | BD28: ='2024 Bdg vs Actual All'!AW28-'2024 Bdg vs Actual -OH'!BD28 -> 151204 | BE28: =BC28-BD28 -> -8204 | BG28: =ROUND(BG16*0.647, -2) -> 144900 | BH28: ='2024 Bdg vs Actual All'!BA28-'2024 Bdg vs Actual -OH'!BH28 -> 152553 | BI28: =BG28-BH28 -> -7653 | CG28: =+W28+S28+O28+AA28+AE28+AI28+AM28+AQ28+AU28+AY28+BC28+BG28 -> 1578800 | CH28: =+X28+T28+P28+AB28+AF28+AJ28+AN28+AR28+AV28+AZ28+BD28+BH28 -> 1695142 | CI28: =CG28-CH28 -> -116342 | CJ28: =CH28/CH16 -> 0.70379636
A29: Costs of IT Project Services | E29: =ROUND(O29+S29+W29+AA29+AE29+AI29+AM29+AQ29+AU29+AY29+BC29+BG29,-2) -> 7200 | O29: =ROUND(O17*0.012, -2) -> 600 | P29: ='2024 Bdg vs Actual All'!I29-'2024 Bdg vs Actual -OH'!P29 -> 567 | Q29: =O29-P29 -> 33 | S29: =ROUND(S17*0.012, -2) -> 600 | T29: ='2024 Bdg vs Actual All'!M29-'2024 Bdg vs Actual -OH'!T29 -> -76 | U29: =S29-T29 -> 676 | W29: =ROUND(W17*0.012, -2) -> 600 | X29: ='2024 Bdg vs Actual All'!Q29-'2024 Bdg vs Actual -OH'!X29 -> -1 | Y29: =W29-X29 -> 601 | AA29: =ROUND(AA17*0.012, -2) -> 600 | AB29: ='2024 Bdg vs Actual All'!U29-'2024 Bdg vs Actual -OH'!AB29 -> 1 | AC29: =AA29-AB29 -> 599 | AE29: =ROUND(AE17*0.012, -2) -> 600 | AF29: 0 | AG29: =AE29-AF29 -> 600 | AI29: =ROUND(AI17*0.012, -2) -> 600 | AJ29: ='2024 Bdg vs Actual All'!AC29-'2024 Bdg vs Actual -OH'!AJ29 -> 1 | AK29: =AI29-AJ29 -> 599 | AM29: =ROUND(AM17*0.012, -2) -> 600 | AN29: ='2024 Bdg vs Actual All'!AG29-'2024 Bdg vs Actual -OH'!AN29 -> 0 | AO29: =AM29-AN29 -> 600 | AQ29: =ROUND(AQ17*0.012, -2) -> 600 | AR29: ='2024 Bdg vs Actual All'!AK29-'2024 Bdg vs Actual -OH'!AR29 -> 0 | AS29: =AQ29-AR29 -> 600 | AU29: =ROUND(AU17*0.012, -2) -> 600 | AV29: ='2024 Bdg vs Actual All'!AO29-'2024 Bdg vs Actual -OH'!AV29 -> 0 | AW29: =AU29-AV29 -> 600 | AY29: =ROUND(AY17*0.012, -2) -> 600 | AZ29: ='2024 Bdg vs Actual All'!AS29-'2024 Bdg vs Actual -OH'!AZ29 -> 0 | BA29: =AY29-AZ29 -> 600 | BC29: =ROUND(BC17*0.012, -2) -> 600 | BD29: ='2024 Bdg vs Actual All'!AW29-'2024 Bdg vs Actual -OH'!BD29 -> 562 | BE29: =BC29-BD29 -> 38 | BG29: =ROUND(BG17*0.012, -2) -> 600 | BH29: ='2024 Bdg vs Actual All'!BA29-'2024 Bdg vs Actual -OH'!BH29 -> 0 | BI29: =BG29-BH29 -> 600 | CG29: =+W29+S29+O29+AA29+AE29+AI29+AM29+AQ29+AU29+AY29+BC29+BG29 -> 7200 | CH29: =+X29+T29+P29+AB29+AF29+AJ29+AN29+AR29+AV29+AZ29+BD29+BH29 -> 1054 | CI29: =CG29-CH29 -> 6146
A30: Costs of Subcontracted Services | E30: =ROUND(O30+S30+W30+AA30+AE30+AI30+AM30+AQ30+AU30+AY30+BC30+BG30,-2) -> 621600 | O30: =ROUND(O18*0.894, -2) -> 50700 | P30: ='2024 Bdg vs Actual All'!I30-'2024 Bdg vs Actual -OH'!P30 -> 4341 | Q30: =O30-P30 -> 46359 | S30: =ROUND(S18*0.894, -2) -> 63900 | T30: ='2024 Bdg vs Actual All'!M30-'2024 Bdg vs Actual -OH'!T30 -> 61066 | U30: =S30-T30 -> 2834 | W30: =ROUND(W18*0.894, -2) -> 50700 | X30: ='2024 Bdg vs Actual All'!Q30-'2024 Bdg vs Actual -OH'!X30 -> 13310 | Y30: =W30-X30 -> 37390 | AA30: =ROUND(AA18*0.894, -2) -> 50700 | AB30: ='2024 Bdg vs Actual All'!U30-'2024 Bdg vs Actual -OH'!AB30 -> 9004 | AC30: =AA30-AB30 -> 41696 | AE30: =ROUND(AE18*0.894, -2) -> 50700 | AF30: ='2024 Bdg vs Actual All'!Y30-'2024 Bdg vs Actual -OH'!AF30 -> 11858 | AG30: =AE30-AF30 -> 38842 | AI30: =ROUND(AI18*0.894, -2) -> 50700 | AJ30: ='2024 Bdg vs Actual All'!AC30-'2024 Bdg vs Actual -OH'!AJ30 -> 4701 | AK30: =AI30-AJ30 -> 45999 | AM30: =ROUND(AM18*0.894, -2) -> 50700 | AN30: ='2024 Bdg vs Actual All'!AG30-'2024 Bdg vs Actual -OH'!AN30 -> 12376 | AO30: =AM30-AN30 -> 38324 | AQ30: =ROUND(AQ18*0.894, -2) -> 50700 | AR30: ='2024 Bdg vs Actual All'!AK30-'2024 Bdg vs Actual -OH'!AR30 -> 108550 | AS30: =AQ30-AR30 -> -57850 | AU30: =ROUND(AU18*0.894, -2) -> 50700 | AV30: ='2024 Bdg vs Actual All'!AO30-'2024 Bdg vs Actual -OH'!AV30 -> 20808 | AW30: =AU30-AV30 -> 29892 | AY30: =ROUND(AY18*0.894, -2) -> 50700 | AZ30: ='2024 Bdg vs Actual All'!AS30-'2024 Bdg vs Actual -OH'!AZ30 -> 27250 | BA30: =AY30-AZ30 -> 23450 | BC30: =ROUND(BC18*0.894, -2) -> 50700 | BD30: ='2024 Bdg vs Actual All'!AW30-'2024 Bdg vs Actual -OH'!BD30 -> 10575 | BE30: =BC30-BD30 -> 40125 | BG30: =ROUND(BG18*0.894, -2) -> 50700 | BH30: ='2024 Bdg vs Actual All'!BA30-'2024 Bdg vs Actual -OH'!BH30 -> 22708 | BI30: =BG30-BH30 -> 27992 | CG30: =+W30+S30+O30+AA30+AE30+AI30+AM30+AQ30+AU30+AY30+BC30+BG30 -> 621600 | CH30: =+X30+T30+P30+AB30+AF30+AJ30+AN30+AR30+AV30+AZ30+BD30+BH30 -> 306547 | CI30: =CG30-CH30 -> 315053
A31: Costs of Product Resale | E31: =ROUND(O31+S31+W31+AA31+AE31+AI31+AM31+AQ31+AU31+AY31+BC31+BG31,-2) -> 7407600 | O31: =ROUND(O22*0.85, -2) -> 617300 | P31: ='2024 Bdg vs Actual All'!I31-'2024 Bdg vs Actual -OH'!P31 -> 148950 | Q31: =O31-P31 -> 468350 | S31: =ROUND(S22*0.85, -2) -> 617300 | T31: ='2024 Bdg vs Actual All'!M31-'2024 Bdg vs Actual -OH'!T31 -> 411509 | U31: =S31-T31 -> 205791 | W31: =ROUND(W22*0.85, -2) -> 617300 | X31: ='2024 Bdg vs Actual All'!Q31-'2024 Bdg vs Actual -OH'!X31 -> 139679 | Y31: =W31-X31 -> 477621 | AA31: =ROUND(AA22*0.85, -2) -> 617300 | AB31: ='2024 Bdg vs Actual All'!U31-'2024 Bdg vs Actual -OH'!AB31 -> 161107 | AC31: =AA31-AB31 -> 456193 | AE31: =ROUND(AE22*0.85, -2) -> 617300 | AF31: ='2024 Bdg vs Actual All'!Y31-'2024 Bdg vs Actual -OH'!AF31 -> 130716 | AG31: =AE31-AF31 -> 486584 | AI31: =ROUND(AI22*0.85, -2) -> 617300 | AJ31: ='2024 Bdg vs Actual All'!AC31-'2024 Bdg vs Actual -OH'!AJ31 -> 991300 | AK31: =AI31-AJ31 -> -374000 | AM31: =ROUND(AM22*0.85, -2) -> 617300 | AN31: ='2024 Bdg vs Actual All'!AG31-'2024 Bdg vs Actual -OH'!AN31 -> 542848 | AO31: =AM31-AN31 -> 74452 | AQ31: =ROUND(AQ22*0.85, -2) -> 617300 | AR31: ='2024 Bdg vs Actual All'!AK31-'2024 Bdg vs Actual -OH'!AR31 -> 384028 | AS31: =AQ31-AR31 -> 233272 | AU31: =ROUND(AU22*0.85, -2) -> 617300 | AV31: ='2024 Bdg vs Actual All'!AO31-'2024 Bdg vs Actual -OH'!AV31 -> 205407 | AW31: =AU31-AV31 -> 411893 | AY31: =ROUND(AY22*0.85, -2) -> 617300 | AZ31: ='2024 Bdg vs Actual All'!AS31-'2024 Bdg vs Actual -OH'!AZ31 -> 169673 | BA31: =AY31-AZ31 -> 447627 | BC31: =ROUND(BC22*0.85, -2) -> 617300 | BD31: ='2024 Bdg vs Actual All'!AW31-'2024 Bdg vs Actual -OH'!BD31 -> 528287 | BE31: =BC31-BD31 -> 89013 | BG31: =ROUND(BG22*0.85, -2) -> 617300 | BH31: ='2024 Bdg vs Actual All'!BA31-'2024 Bdg vs Actual -OH'!BH31 -> 81059 | BI31: =BG31-BH31 -> 536241 | CG31: =+W31+S31+O31+AA31+AE31+AI31+AM31+AQ31+AU31+AY31+BC31+BG31 -> 7407600 | CH31: =+X31+T31+P31+AB31+AF31+AJ31+AN31+AR31+AV31+AZ31+BD31+BH31 -> 3894563 | CI31: =CG31-CH31 -> 3513037
X32: =(X22-X31)/X22 -> 0.16326311 | Z32: =+AA33+AA40+AA46 -> 392566.5 | AB32: =(AB22-AB31)/AB22 -> 0.18102147 | AF32: =(AF22-AF31)/AF22 -> 0.1606565
A33: Direct Labor-Fully loaded(Support/Engineers) | E33: =ROUND(O33+S33+W33+AA33+AE33+AI33+AM33+AQ33+AU33+AY33+BC33+BG33,-2) -> 2643500 | O33: 230700 | P33: ='2024 Bdg vs Actual All'!I33-'2024 Bdg vs Actual -OH'!P33 -> 222614 | Q33: =O33-P33 -> 8086 | S33: 221417 | T33: ='2024 Bdg vs Actual All'!M33-'2024 Bdg vs Actual -OH'!T33 -> 207622 | U33: =S33-T33 -> 13795 | W33: 222958.14 | X33: ='2024 Bdg vs Actual All'!Q33-'2024 Bdg vs Actual -OH'!X33 -> 217505 | Y33: =W33-X33 -> 5453.14 | Z33: =+$AA$33/Z32 -> 0.55714 | AA33: 218714.5 | AB33: ='2024 Bdg vs Actual All'!U33-'2024 Bdg vs Actual -OH'!AB33 -> 230301 | AC33: =AA33-AB33 -> -11586.504 | AD33: UMR Health insurance overage, and off boardings | AE33: 218714.5 | AF33: ='2024 Bdg vs Actual All'!Y33-'2024 Bdg vs Actual -OH'!AF33 -> 227582 | AG33: =AE33-AF33 -> -8867.5043 | AI33: 218714.5 | AJ33: ='2024 Bdg vs Actual All'!AC33-'2024 Bdg vs Actual -OH'!AJ33 -> 218433 | AK33: =AI33-AJ33 -> 281.49569 | AM33: 218714.5 | AN33: ='2024 Bdg vs Actual All'!AG33-'2024 Bdg vs Actual -OH'!AN33 -> 217252 | AO33: =AM33-AN33 -> 1462.4957 | AQ33: 218714.5 | AR33: ='2024 Bdg vs Actual All'!AK33-'2024 Bdg vs Actual -OH'!AR33 -> 225229 | AS33: =AQ33-AR33 -> -6514.5043 | AU33: 218714.5 | AV33: ='2024 Bdg vs Actual All'!AO33-'2024 Bdg vs Actual -OH'!AV33 -> 196278 | AW33: =AU33-AV33 -> 22436.496 | AY33: 218714.5 | AZ33: ='2024 Bdg vs Actual All'!AS33-'2024 Bdg vs Actual -OH'!AZ33 -> 228050 | BA33: =AY33-AZ33 -> -9335.5043 | BC33: 218714.5 | BD33: ='2024 Bdg vs Actual All'!AW33-'2024 Bdg vs Actual -OH'!BD33 -> 224445 | BE33: =BC33-BD33 -> -5730.5043 | BG33: 218714.5 | BH33: ='2024 Bdg vs Actual All'!BA33-'2024 Bdg vs Actual -OH'!BH33 -> 213015 | BI33: =BG33-BH33 -> 5699.4957 | CG33: =+W33+S33+O33+AA33+AE33+AI33+AM33+AQ33+AU33+AY33+BC33+BG33 -> 2643505.6 | CH33: =+X33+T33+P33+AB33+AF33+AJ33+AN33+AR33+AV33+AZ33+BD33+BH33 -> 2628326 | CI33: =CG33-CH33 -> 15179.601
A34: Total Cost of Good Sold** | E34: =ROUND(O34+S34+W34+AA34+AE34+AI34+AM34+AQ34+AU34+AY34+BC34+BG34,-2) -> 12618400 | O34: =SUM(O26:O33) -> 1051200 | P34: =SUM(P26:P33) -> 539675 | Q34: =O34-P34 -> 511525 | S34: =SUM(S26:S33) -> 1056617 | T34: =SUM(T26:T33) -> 859392 | U34: =S34-T34 -> 197225 | W34: =SUM(W26:W33) -> 1033458.1 | X34: =SUM(X26:X33) -> 537603.16 | Y34: =W34-X34 -> 495854.98 | AA34: =SUM(AA26:AA33) -> 1034014.5 | AB34: =SUM(AB26:AB33) -> 568964.18 | AC34: =AA34-AB34 -> 465050.31 | AE34: =SUM(AE26:AE33) -> 1039314.5 | AF34: ='2024 Bdg vs Actual All'!Y34-'2024 Bdg vs Actual -OH'!AF34 -> 534553.84 | AG34: =AE34-AF34 -> 504760.65 | AI34: =SUM(AI26:AI33) -> 1050414.5 | AJ34: ='2024 Bdg vs Actual All'!AC34-'2024 Bdg vs Actual -OH'!AJ34 -> 1371872.8 | AK34: =AI34-AJ34 -> -321458.3 | AM34: =SUM(AM26:AM33) -> 1052714.5 | AN34: ='2024 Bdg vs Actual All'!AG34-'2024 Bdg vs Actual -OH'!AN34 -> 929269.86 | AO34: =AM34-AN34 -> 123444.64 | AQ34: =SUM(AQ26:AQ33) -> 1055014.5 | AR34: ='2024 Bdg vs Actual All'!AK34-'2024 Bdg vs Actual -OH'!AR34 -> 868904.77 | AS34: =AQ34-AR34 -> 186109.73 | AU34: =SUM(AU26:AU33) -> 1057514.5 | AV34: ='2024 Bdg vs Actual All'!AO34-'2024 Bdg vs Actual -OH'!AV34 -> 589973.85 | AW34: =AU34-AV34 -> 467540.65 | AY34: =SUM(AY26:AY33) -> 1060014.5 | AZ34: ='2024 Bdg vs Actual All'!AS34-'2024 Bdg vs Actual -OH'!AZ34 -> 592544.85 | BA34: =AY34-AZ34 -> 467469.65 | BC34: =SUM(BC26:BC33) -> 1062614.5 | BD34: ='2024 Bdg vs Actual All'!AW34-'2024 Bdg vs Actual -OH'!BD34 -> 937048 | BE34: =BC34-BD34 -> 125566.5 | BG34: =SUM(BG26:BG33) -> 1065514.5 | BH34: ='2024 Bdg vs Actual All'!BA34-'2024 Bdg vs Actual -OH'!BH34 -> 489719 | BI34: =BG34-BH34 -> 575795.5 | CG34: =+W34+S34+O34+AA34+AE34+AI34+AM34+AQ34+AU34+AY34+BC34+BG34 -> 12618406 | CH34: =+X34+T34+P34+AB34+AF34+AJ34+AN34+AR34+AV34+AZ34+BD34+BH34 -> 8819521.3 | CI34: =CG34-CH34 -> 3798884.3
A35: Total Gross Margin | E35: =E11-E34 -> 5582300 | O35: =O11-O34 -> 491798.97 | P35: =P11-P34 -> 300594.57 | Q35: =P35-O35 -> -191204.4 | S35: =S11-S34 -> 422061.83 | T35: =T11-T34 -> 378640 | U35: =T35-S35 -> -43421.833 | W35: =W11-W34 -> 408759.09 | X35: =X11-X34 -> 299750.84 | Y35: =X35-W35 -> -109008.25 | AA35: =AA11-AA34 -> 421473.84 | AB35: =AB11-AB34 -> 378608.82 | AC35: =AB35-AA35 -> -42865.02 | AE35: =AE11-AE34 -> 430018.84 | AF35: =AF11-AF34 -> 316588.16 | AG35: =AF35-AE35 -> -113430.68 | AI35: =AI11-AI34 -> 468850.5 | AJ35: =AJ11-AJ34 -> 491397.21 | AK35: =AJ35-AI35 -> 22546.711 | AM35: =AM11-AM34 -> 474000.5 | AN35: =AN11-AN34 -> 395638.14 | AO35: =AN35-AM35 -> -78362.356 | AQ35: =AQ11-AQ34 -> 475150.5 | AR35: =AR11-AR34 -> 491473.23 | AS35: =AR35-AQ35 -> 16322.733 | AU35: =AU11-AU34 -> 484100.5 | AV35: =AV11-AV34 -> 349583.15 | AW35: =AV35-AU35 -> -134517.34 | AY35: =AY11-AY34 -> 493050.5 | AZ35: =AZ11-AZ34 -> 321613.15 | BA35: =AZ35-AY35 -> -171437.35 | BC35: =BC11-BC34 -> 501900.5 | BD35: =BD11-BD34 -> 387729 | BE35: =BD35-BC35 -> -114171.5 | BG35: =BG11-BG34 -> 511087.34 | BH35: =BH11-BH34 -> 349296 | BI35: =BH35-BG35 -> -161791.34 | CG35: =CG11-CG34 -> 5582252.9 | CH35: =CH11-CH34 -> 4460912.3 | CI35: =CH35-CG35 -> -1121340.6
E36: =+E35/E11 -> 0.30670798 | S36: =(S22-S31)/S22 -> 0.14999673 | T36: =(T22-T31)/T22 -> 0.1511743 | W36: =(W22-W31)/W22 -> 0.14999673 | X36: =(X22-X31)/X22 -> 0.16326311 | AA36: =(AA22-AA31)/AA22 -> 0.14999673 | AB36: =(AB22-AB31)/AB22 -> 0.18102147
A37: Direct Selling Costs
A39: Commissions | E39: =ROUND(O39+S39+W39+AA39+AE39+AI39+AM39+AQ39+AU39+AY39+BC39+BG39,-2) -> 289400 | O39: 39100 | P39: ='2024 Bdg vs Actual All'!I39-'2024 Bdg vs Actual -OH'!P39 -> 2772 | Q39: =O39-P39 -> 36328 | S39: 0 | T39: ='2024 Bdg vs Actual All'!M39-'2024 Bdg vs Actual -OH'!T39 -> 252 | U39: =S39-T39 -> -252 | W39: 9600 | X39: ='2024 Bdg vs Actual All'!Q39-'2024 Bdg vs Actual -OH'!X39 -> 0 | Y39: =W39-X39 -> 9600 | AA39: 24200 | AB39: ='2024 Bdg vs Actual All'!U39-'2024 Bdg vs Actual -OH'!AB39 -> 3604 | AC39: =AA39-AB39 -> 20596 | AE39: 24200 | AF39: ='2024 Bdg vs Actual All'!Y39-'2024 Bdg vs Actual -OH'!AF39 -> 5758.92 | AG39: =AE39-AF39 -> 18441.08 | AI39: 74100 | AJ39: ='2024 Bdg vs Actual All'!AC39-'2024 Bdg vs Actual -OH'!AJ39 -> 14626 | AK39: =AI39-AJ39 -> 59474 | AM39: 19700 | AN39: ='2024 Bdg vs Actual All'!AG39-'2024 Bdg vs Actual -OH'!AN39 -> 2689 | AO39: =AM39-AN39 -> 17011 | AP39: New business did not meet budget so commissions are under budget | AQ39: 19700 | AR39: ='2024 Bdg vs Actual All'!AK39-'2024 Bdg vs Actual -OH'!AR39 -> 15036 | AS39: =AQ39-AR39 -> 4664 | AT39: New business did not meet budget so commissions are under budget | AU39: 19700 | AV39: ='2024 Bdg vs Actual All'!AO39-'2024 Bdg vs Actual -OH'!AV39 -> 9905 | AW39: =AU39-AV39 -> 9795 | AX39: New business did not meet budget so commissions are under budget | AY39: 19700 | AZ39: ='2024 Bdg vs Actual All'!AS39-'2024 Bdg vs Actual -OH'!AZ39 -> 8310 | BA39: =AY39-AZ39 -> 11390 | BC39: 19700 | BD39: ='2024 Bdg vs Actual All'!AW39-'2024 Bdg vs Actual -OH'!BD39 -> 4340 | BE39: =BC39-BD39 -> 15360 | BG39: 19700 | BH39: ='2024 Bdg vs Actual All'!BA39-'2024 Bdg vs Actual -OH'!BH39 -> 12997 | BI39: =BG39-BH39 -> 6703 | CG39: =+W39+S39+O39+AA39+AE39+AI39+AM39+AQ39+AU39+AY39+BC39+BG39 -> 289400 | CH39: =+X39+T39+P39+AB39+AF39+AJ39+AN39+AR39+AV39+AZ39+BD39+BH39 -> 80289.92 | CI39: =CG39-CH39 -> 209110.08
A40: Labor Selling - Loaded | E40: =ROUND(O40+S40+W40+AA40+AE40+AI40+AM40+AQ40+AU40+AY40+BC40+BG40,-2) -> 914800 | O40: =ROUND(896000/12,-2) -> 74700 | P40: ='2024 Bdg vs Actual All'!I40-'2024 Bdg vs Actual -OH'!P40 -> 83908 | Q40: =O40-P40 -> -9208 | S40: 88442 | T40: ='2024 Bdg vs Actual All'!M40-'2024 Bdg vs Actual -OH'!T40 -> 89853 | U40: =S40-T40 -> -1411 | W40: =80326.7158333333+8115 -> 88441.716 | X40: ='2024 Bdg vs Actual All'!Q40-'2024 Bdg vs Actual -OH'!X40 -> 91789 | Y40: =W40-X40 -> -3347.2842 | Z40: =+AA40/$Z$32 -> 0.20004764 | AA40: 78532 | AB40: ='2024 Bdg vs Actual All'!U40-'2024 Bdg vs Actual -OH'!AB40 -> 87972 | AC40: =AA40-AB40 -> -9440 | AD40: Health insurance overage | AE40: 73090 | AF40: ='2024 Bdg vs Actual All'!Y40-'2024 Bdg vs Actual -OH'!AF40 -> 102736 | AG40: =AE40-AF40 -> -29646 | AH40: Final Pays and Severance for Orion, Jason, and Frankie | AI40: 73090 | AJ40: ='2024 Bdg vs Actual All'!AC40-'2024 Bdg vs Actual -OH'!AJ40 -> 68723 | AK40: =AI40-AJ40 -> 4367 | AM40: 73090 | AN40: ='2024 Bdg vs Actual All'!AG40-'2024 Bdg vs Actual -OH'!AN40 -> 58967 | AO40: =AM40-AN40 -> 14123 | AQ40: 73090 | AR40: ='2024 Bdg vs Actual All'!AK40-'2024 Bdg vs Actual -OH'!AR40 -> 62770 | AS40: =AQ40-AR40 -> 10320 | AU40: 73090 | AV40: ='2024 Bdg vs Actual All'!AO40-'2024 Bdg vs Actual -OH'!AV40 -> 54139 | AW40: =AU40-AV40 -> 18951 | AY40: 73090 | AZ40: ='2024 Bdg vs Actual All'!AS40-'2024 Bdg vs Actual -OH'!AZ40 -> 60117 | BA40: =AY40-AZ40 -> 12973 | BC40: 73090 | BD40: ='2024 Bdg vs Actual All'!AW40-'2024 Bdg vs Actual -OH'!BD40 -> 61208 | BE40: =BC40-BD40 -> 11882 | BG40: 73090 | BH40: ='2024 Bdg vs Actual All'!BA40-'2024 Bdg vs Actual -OH'!BH40 -> 60072.26 | BI40: =BG40-BH40 -> 13017.74 | BK40: {=ROUND(O40:BG40, -2)} -> #VALUE! | CG40: =+W40+S40+O40+AA40+AE40+AI40+AM40+AQ40+AU40+AY40+BC40+BG40 -> 914835.72 | CH40: =+X40+T40+P40+AB40+AF40+AJ40+AN40+AR40+AV40+AZ40+BD40+BH40 -> 882254.26 | CI40: =CG40-CH40 -> 32581.456
A41: Contribution Margin | E41: =E35-E39-E40 -> 4378100 | O41: =O35-O39-O40 -> 377998.97 | P41: =P35-P39-P40 -> 213914.57 | Q41: =P41-O41 -> -164084.4 | S41: =S35-S39-S40 -> 333619.83 | T41: =T35-T39-T40 -> 288535 | U41: =T41-S41 -> -45084.833 | W41: =W35-W39-W40 -> 310717.37 | X41: =X35-X39-X40 -> 207961.84 | Y41: =X41-W41 -> -102755.53 | AA41: =AA35-AA39-AA40 -> 318741.84 | AB41: =AB35-AB39-AB40 -> 287032.82 | AC41: =AB41-AA41 -> -31709.02 | AE41: =AE35-AE39-AE40 -> 332728.84 | AF41: =AF35-AF39-AF40 -> 208093.24 | AG41: =AF41-AE41 -> -124635.6 | AI41: =AI35-AI39-AI40 -> 321660.5 | AJ41: =AJ35-AJ39-AJ40 -> 408048.21 | AK41: =AJ41-AI41 -> 86387.711 | AM41: =AM35-AM39-AM40 -> 381210.5 | AN41: =AN35-AN39-AN40 -> 333982.14 | AO41: =AN41-AM41 -> -47228.356 | AQ41: =AQ35-AQ39-AQ40 -> 382360.5 | AR41: =AR35-AR39-AR40 -> 413667.23 | AS41: =AR41-AQ41 -> 31306.733 | AU41: =AU35-AU39-AU40 -> 391310.5 | AV41: =AV35-AV39-AV40 -> 285539.15 | AW41: =AV41-AU41 -> -105771.34 | AY41: =AY35-AY39-AY40 -> 400260.5 | AZ41: =AZ35-AZ39-AZ40 -> 253186.15 | BA41: =AZ41-AY41 -> -147074.35 | BC41: =BC35-BC39-BC40 -> 409110.5 | BD41: =BD35-BD39-BD40 -> 322181 | BE41: =BD41-BC41 -> -86929.498 | BG41: =BG35-BG39-BG40 -> 418297.34 | BH41: =BH35-BH39-BH40 -> 276226.74 | BI41: =BH41-BG41 -> -142070.6 | BK41: {=ROUND(O41:BG41, -2)} -> #VALUE! | CG41: =CG35-CG39-CG40 -> 4378017.2 | CH41: =CH35-CH39-CH40 -> 3498368.1 | CI41: =CH41-CG41 -> -879649.08
E42: =+E41/E11 -> 0.24054569
A43: **Expenses**
A45: Payroll ***
A46: Executive / Management Loaded | E46: =ROUND(O46+S46+W46+AA46+AE46+AI46+AM46+AQ46+AU46+AY46+BC46+BG46,-2) -> 1115900 | O46: =1026000/12 -> 85500 | P46: ='2024 Bdg vs Actual All'!I46-'2024 Bdg vs Actual -OH'!P46 -> 101949 | Q46: =O46-P46 -> -16449 | S46: =1026000/12 -> 85500 | T46: ='2024 Bdg vs Actual All'!M46-'2024 Bdg vs Actual -OH'!T46 -> 89256 | U46: =S46-T46 -> -3756 | W46: 87030.907 | X46: ='2024 Bdg vs Actual All'!Q46-'2024 Bdg vs Actual -OH'!X46 -> 90173 | Y46: =W46-X46 -> -3142.0933 | Z46: =+AA46/$Z$32 -> 0.24281237 | AA46: 95320 | AB46: ='2024 Bdg vs Actual All'!U46-'2024 Bdg vs Actual -OH'!AB46 -> 100765 | AC46: =AA46-AB46 -> -5445 | AD46: health Insurance overage | AE46: 95320 | AF46: ='2024 Bdg vs Actual All'!Y46-'2024 Bdg vs Actual -OH'!AF46 -> 103272 | AG46: =AE46-AF46 -> -7952 | AH46: Dan Obrien Final Pay and Health ins overages | AI46: 95320 | AJ46: ='2024 Bdg vs Actual All'!AC46-'2024 Bdg vs Actual -OH'!AJ46 -> 84968 | AK46: =AI46-AJ46 -> 10352 | AM46: 95320 | AN46: ='2024 Bdg vs Actual All'!AG46-'2024 Bdg vs Actual -OH'!AN46 -> 84847 | AO46: =AM46-AN46 -> 10473 | AQ46: 95320 | AR46: ='2024 Bdg vs Actual All'!AK46-'2024 Bdg vs Actual -OH'!AR46 -> 94211 | AS46: =AQ46-AR46 -> 1109 | AU46: 95320 | AV46: ='2024 Bdg vs Actual All'!AO46-'2024 Bdg vs Actual -OH'!AV46 -> 85294 | AW46: =AU46-AV46 -> 10026 | AY46: 95320 | AZ46: ='2024 Bdg vs Actual All'!AS46-'2024 Bdg vs Actual -OH'!AZ46 -> 96675 | BA46: =AY46-AZ46 -> -1355 | BC46: 95320 | BD46: ='2024 Bdg vs Actual All'!AW46-'2024 Bdg vs Actual -OH'!BD46 -> 97457 | BE46: =BC46-BD46 -> -2137 | BG46: 95320 | BH46: ='2024 Bdg vs Actual All'!BA46-'2024 Bdg vs Actual -OH'!BH46 -> 129935 | BI46: =BG46-BH46 -> -34615 | BK46: {=ROUND(O46:BG46, -2)} -> #VALUE! | CG46: =+W46+S46+O46+AA46+AE46+AI46+AM46+AQ46+AU46+AY46+BC46+BG46 -> 1115910.9 | CH46: =+X46+T46+P46+AB46+AF46+AJ46+AN46+AR46+AV46+AZ46+BD46+BH46 -> 1158802 | CI46: =CG46-CH46 -> -42891.093
A47: Workers Comp | E47: =ROUND(O47+S47+W47+AA47+AE47+AI47+AM47+AQ47+AU47+AY47+BC47+BG47,-2) -> 6000 | Q47: =O47-P47 -> 0 | U47: =S47-T47 -> 0 | W47: 2000 | X47: ='2024 Bdg vs Actual All'!Q47-'2024 Bdg vs Actual -OH'!X47 -> 0 | Y47: =W47-X47 -> 2000 | AC47: =AA47-AB47 -> 0 | AI47: 2000 | AY47: 2000 | BK47: {=ROUND(O47:BG47, -2)} -> #VALUE! | CG47: =+W47+S47+O47+AA47+AE47+AI47+AM47+AQ47+AU47+AY47+BC47+BG47 -> 6000 | CH47: =+X47+T47+P47+AB47+AF47+AJ47+AN47+AR47+AV47+AZ47+BD47+BH47 -> 0 | CI47: =CG47-CH47 -> 6000
A48: Total Payroll | E48: =SUM(E45:E47) -> 1121900 | O48: =SUM(O45:O47) -> 85500 | P48: =SUM(P45:P47) -> 101949 | Q48: =O48-P48 -> -16449 | S48: =SUM(S45:S47) -> 85500 | T48: =SUM(T45:T47) -> 89256 | U48: =S48-T48 -> -3756 | W48: =SUM(W45:W47) -> 89030.907 | X48: =SUM(X45:X47) -> 90173 | Y48: =W48-X48 -> -1142.0933 | AA48: =SUM(AA45:AA47) -> 95320 | AB48: =SUM(AB45:AB47) -> 100765 | AC48: =AA48-AB48 -> -5445 | AE48: =SUM(AE45:AE47) -> 95320 | AF48: =SUM(AF45:AF47) -> 103272 | AG48: =AE48-AF48 -> -7952 | AI48: =SUM(AI45:AI47) -> 97320 | AJ48: =SUM(AJ45:AJ47) -> 84968 | AK48: =AI48-AJ48 -> 12352 | AM48: =SUM(AM45:AM47) -> 95320 | AN48: =SUM(AN45:AN47) -> 84847 | AO48: =AM48-AN48 -> 10473 | AQ48: =SUM(AQ45:AQ47) -> 95320 | AR48: =SUM(AR45:AR47) -> 94211 | AS48: =AQ48-AR48 -> 1109 | AU48: =SUM(AU45:AU47) -> 95320 | AV48: =SUM(AV45:AV47) -> 85294 | AW48: =AU48-AV48 -> 10026 | AY48: =SUM(AY45:AY47) -> 97320 | AZ48: =SUM(AZ45:AZ47) -> 96675 | BA48: =AY48-AZ48 -> 645 | BC48: =SUM(BC45:BC47) -> 95320 | BD48: =SUM(BD45:BD47) -> 97457 | BE48: =BC48-BD48 -> -2137 | BG48: =SUM(BG45:BG47) -> 95320 | BH48: =SUM(BH45:BH47) -> 129935 | BI48: =BG48-BH48 -> -34615 | BK48: {=ROUND(O48:BG48, -2)} -> #VALUE! | CG48: =SUM(CG45:CG47) -> 1121910.9 | CH48: =SUM(CH45:CH47) -> 1158802 | CI48: =CG48-CH48 -> -36891.093
A51: Office Expenses****
A52: Office Lease | E52: =ROUND(O52+S52+W52+AA52+AE52+AI52+AM52+AQ52+AU52+AY52+BC52+BG52,-2) -> 206400 | O52: 17200 | P52: ='2024 Bdg vs Actual All'!I52-'2024 Bdg vs Actual -OH'!P52 -> 17927 | Q52: =O52-P52 -> -727 | S52: 17200 | T52: ='2024 Bdg vs Actual All'!M52-'2024 Bdg vs Actual -OH'!T52 -> 18504 | U52: =S52-T52 -> -1304 | W52: 17200 | X52: ='2024 Bdg vs Actual All'!Q52-'2024 Bdg vs Actual -OH'!X52 -> 17536 | Y52: =W52-X52 -> -336 | AA52: 17200 | AB52: ='2024 Bdg vs Actual All'!U52-'2024 Bdg vs Actual -OH'!AB52 -> 16970 | AC52: =AA52-AB52 -> 230 | AE52: 17200 | AF52: ='2024 Bdg vs Actual All'!Y52-'2024 Bdg vs Actual -OH'!AF52 -> 16003 | AG52: =AE52-AF52 -> 1197 | AI52: 17200 | AJ52: ='2024 Bdg vs Actual All'!AC52-'2024 Bdg vs Actual -OH'!AJ52 -> 17254 | AK52: =AI52-AJ52 -> -54 | AM52: 17200 | AN52: ='2024 Bdg vs Actual All'!AG52-'2024 Bdg vs Actual -OH'!AN52 -> 17754 | AO52: =AM52-AN52 -> -554 | AP52: Clevel Office | AQ52: 17200 | AR52: ='2024 Bdg vs Actual All'!AK52-'2024 Bdg vs Actual -OH'!AR52 -> 16753 | AS52: =AQ52-AR52 -> 447 | AU52: 17200 | AV52: 18459 | AW52: =AU52-AV52 -> -1259 | AX52: Clevel Advising Office catch up billing | AY52: 17200 | AZ52: ='2024 Bdg vs Actual All'!AS52-'2024 Bdg vs Actual -OH'!AZ52 -> 17908 | BA52: =AY52-AZ52 -> -708 | BB52: Clevel Advising Office | BC52: 17200 | BD52: ='2024 Bdg vs Actual All'!AW52-'2024 Bdg vs Actual -OH'!BD52 -> 16659 | BE52: =BC52-BD52 -> 541 | BG52: 17200 | BH52: ='2024 Bdg vs Actual All'!BA52-'2024 Bdg vs Actual -OH'!BH52 -> 16659 | BI52: =BG52-BH52 -> 541 | BJ52: Clevel Advising Office | BK52: {=ROUND(O52:BG52, -2)} -> #VALUE! | CG52: =+W52+S52+O52+AA52+AE52+AI52+AM52+AQ52+AU52+AY52+BC52+BG52 -> 206400 | CH52: =+X52+T52+P52+AB52+AF52+AJ52+AN52+AR52+AV52+AZ52+BD52+BH52 -> 208386 | CI52: =CG52-CH52 -> -1986
A53: Insurance | E53: =ROUND(O53+S53+W53+AA53+AE53+AI53+AM53+AQ53+AU53+AY53+BC53+BG53,-2) -> 95000 | O53: 7000 | P53: ='2024 Bdg vs Actual All'!I53-'2024 Bdg vs Actual -OH'!P53 -> 5877 | Q53: =O53-P53 -> 1123 | S53: 8000 | T53: ='2024 Bdg vs Actual All'!M53-'2024 Bdg vs Actual -OH'!T53 -> 5520 | U53: =S53-T53 -> 2480 | W53: 8000 | X53: ='2024 Bdg vs Actual All'!Q53-'2024 Bdg vs Actual -OH'!X53 -> 6470 | Y53: =W53-X53 -> 1530 | AA53: 8000 | AB53: ='2024 Bdg vs Actual All'!U53-'2024 Bdg vs Actual -OH'!AB53 -> 3213 | AC53: =AA53-AB53 -> 4787 | AE53: 8000 | AF53: ='2024 Bdg vs Actual All'!Y53-'2024 Bdg vs Actual -OH'!AF53 -> 3941 | AG53: =AE53-AF53 -> 4059 | AI53: 8000 | AJ53: ='2024 Bdg vs Actual All'!AC53-'2024 Bdg vs Actual -OH'!AJ53 -> 6451 | AK53: =AI53-AJ53 -> 1549 | AM53: 8000 | AN53: ='2024 Bdg vs Actual All'!AG53-'2024 Bdg vs Actual -OH'!AN53 -> 3658 | AO53: =AM53-AN53 -> 4342 | AQ53: 8000 | AR53: ='2024 Bdg vs Actual All'!AK53-'2024 Bdg vs Actual -OH'!AR53 -> 4296 | AS53: =AQ53-AR53 -> 3704 | AU53: 8000 | AV53: ='2024 Bdg vs Actual All'!AO53-'2024 Bdg vs Actual -OH'!AV53 -> 4321 | AW53: =AU53-AV53 -> 3679 | AY53: 8000 | AZ53: ='2024 Bdg vs Actual All'!AS53-'2024 Bdg vs Actual -OH'!AZ53 -> 4333 | BA53: =AY53-AZ53 -> 3667 | BC53: 8000 | BD53: ='2024 Bdg vs Actual All'!AW53-'2024 Bdg vs Actual -OH'!BD53 -> 4333 | BE53: =BC53-BD53 -> 3667 | BG53: 8000 | BH53: ='2024 Bdg vs Actual All'!BA53-'2024 Bdg vs Actual -OH'!BH53 -> 4571 | BI53: =BG53-BH53 -> 3429 | BK53: {=ROUND(O53:BG53, -2)} -> #VALUE! | CG53: =+W53+S53+O53+AA53+AE53+AI53+AM53+AQ53+AU53+AY53+BC53+BG53 -> 95000 | CH53: =+X53+T53+P53+AB53+AF53+AJ53+AN53+AR53+AV53+AZ53+BD53+BH53 -> 56984 | CI53: =CG53-CH53 -> 38016
A54: Utilities - Internet-Phones | E54: =ROUND(O54+S54+W54+AA54+AE54+AI54+AM54+AQ54+AU54+AY54+BC54+BG54,-2) -> 105600 | O54: 8800 | P54: ='2024 Bdg vs Actual All'!I54-'2024 Bdg vs Actual -OH'!P54 -> 4641 | Q54: =O54-P54 -> 4159 | S54: 8800 | T54: ='2024 Bdg vs Actual All'!M54-'2024 Bdg vs Actual -OH'!T54 -> 12477 | U54: =S54-T54 -> -3677 | W54: 8800 | X54: ='2024 Bdg vs Actual All'!Q54-'2024 Bdg vs Actual -OH'!X54 -> 9225 | Y54: =W54-X54 -> -425 | AA54: 8800 | AB54: ='2024 Bdg vs Actual All'!U54-'2024 Bdg vs Actual -OH'!AB54 -> 8735 | AC54: =AA54-AB54 -> 65 | AE54: 8800 | AF54: ='2024 Bdg vs Actual All'!Y54-'2024 Bdg vs Actual -OH'!AF54 -> 8393 | AG54: =AE54-AF54 -> 407 | AI54: 8800 | AJ54: ='2024 Bdg vs Actual All'!AC54-'2024 Bdg vs Actual -OH'!AJ54 -> 9709.34 | AK54: =AI54-AJ54 -> -909.34 | AM54: 8800 | AN54: ='2024 Bdg vs Actual All'!AG54-'2024 Bdg vs Actual -OH'!AN54 -> 8697 | AO54: =AM54-AN54 -> 103 | AQ54: 8800 | AR54: ='2024 Bdg vs Actual All'!AK54-'2024 Bdg vs Actual -OH'!AR54 -> 11526 | AS54: =AQ54-AR54 -> -2726 | AT54: MID was 2870, Dialpad charges increased | AU54: 8800 | AV54: ='2024 Bdg vs Actual All'!AO54-'2024 Bdg vs Actual -OH'!AV54 -> 13285 | AW54: =AU54-AV54 -> -4485 | AX54: Comcast catch up invoice from August $1800 | AY54: 8800 | AZ54: ='2024 Bdg vs Actual All'!AS54-'2024 Bdg vs Actual -OH'!AZ54 -> 9016 | BA54: =AY54-AZ54 -> -216 | BC54: 8800 | BD54: ='2024 Bdg vs Actual All'!AW54-'2024 Bdg vs Actual -OH'!BD54 -> 10792 | BE54: =BC54-BD54 -> -1992 | BG54: 8800 | BH54: ='2024 Bdg vs Actual All'!BA54-'2024 Bdg vs Actual -OH'!BH54 -> 9890 | BI54: =BG54-BH54 -> -1090 | BK54: {=ROUND(O54:BG54, -2)} -> #VALUE! | CG54: =+W54+S54+O54+AA54+AE54+AI54+AM54+AQ54+AU54+AY54+BC54+BG54 -> 105600 | CH54: =+X54+T54+P54+AB54+AF54+AJ54+AN54+AR54+AV54+AZ54+BD54+BH54 -> 116386.34 | CI54: =CG54-CH54 -> -10786.34
A55: Repairs & Maintenance | E55: =ROUND(O55+S55+W55+AA55+AE55+AI55+AM55+AQ55+AU55+AY55+BC55+BG55,-2) -> 10800 | O55: 900 | P55: ='2024 Bdg vs Actual All'!I55-'2024 Bdg vs Actual -OH'!P55 -> 8164 | Q55: =O55-P55 -> -7264 | S55: 900 | T55: ='2024 Bdg vs Actual All'!M55-'2024 Bdg vs Actual -OH'!T55 -> 839 | U55: =S55-T55 -> 61 | W55: 900 | X55: ='2024 Bdg vs Actual All'!Q55-'2024 Bdg vs Actual -OH'!X55 -> 300 | Y55: =W55-X55 -> 600 | AA55: 900 | AB55: ='2024 Bdg vs Actual All'!U55-'2024 Bdg vs Actual -OH'!AB55 -> 324 | AC55: =AA55-AB55 -> 576 | AE55: 900 | AF55: ='2024 Bdg vs Actual All'!Y55-'2024 Bdg vs Actual -OH'!AF55 -> 1004 | AG55: =AE55-AF55 -> -104 | AI55: 900 | AJ55: ='2024 Bdg vs Actual All'!AC55-'2024 Bdg vs Actual -OH'!AJ55 -> 100 | AK55: =AI55-AJ55 -> 800 | AM55: 900 | AN55: ='2024 Bdg vs Actual All'!AG55-'2024 Bdg vs Actual -OH'!AN55 -> 200 | AO55: =AM55-AN55 -> 700 | AQ55: 900 | AR55: ='2024 Bdg vs Actual All'!AK55-'2024 Bdg vs Actual -OH'!AR55 -> 225 | AS55: =AQ55-AR55 -> 675 | AU55: 900 | AV55: ='2024 Bdg vs Actual All'!AO55-'2024 Bdg vs Actual -OH'!AV55 -> 711 | AW55: =AU55-AV55 -> 189 | AY55: 900 | AZ55: ='2024 Bdg vs Actual All'!AS55-'2024 Bdg vs Actual -OH'!AZ55 -> 100 | BA55: =AY55-AZ55 -> 800 | BC55: 900 | BD55: ='2024 Bdg vs Actual All'!AW55-'2024 Bdg vs Actual -OH'!BD55 -> 101 | BE55: =BC55-BD55 -> 799 | BG55: 900 | BH55: ='2024 Bdg vs Actual All'!BA55-'2024 Bdg vs Actual -OH'!BH55 -> 0 | BI55: =BG55-BH55 -> 900 | BK55: {=ROUND(O55:BG55, -2)} -> #VALUE! | CG55: =+W55+S55+O55+AA55+AE55+AI55+AM55+AQ55+AU55+AY55+BC55+BG55 -> 10800 | CH55: =+X55+T55+P55+AB55+AF55+AJ55+AN55+AR55+AV55+AZ55+BD55+BH55 -> 12068 | CI55: =CG55-CH55 -> -1268
A56: Software | E56: =ROUND(O56+S56+W56+AA56+AE56+AI56+AM56+AQ56+AU56+AY56+BC56+BG56,-2) -> 188000 | O56: 14000 | P56: ='2024 Bdg vs Actual All'!I56-'2024 Bdg vs Actual -OH'!P56 -> 15078 | Q56: =O56-P56 -> -1078 | S56: 14000 | T56: ='2024 Bdg vs Actual All'!M56-'2024 Bdg vs Actual -OH'!T56 -> 16845 | U56: =S56-T56 -> -2845 | W56: 14200 | X56: ='2024 Bdg vs Actual All'!Q56-'2024 Bdg vs Actual -OH'!X56 -> 16341 | Y56: =W56-X56 -> -2141 | AA56: 16200 | AB56: ='2024 Bdg vs Actual All'!U56-'2024 Bdg vs Actual -OH'!AB56 -> 15871 | AC56: =AA56-AB56 -> 329 | AE56: 16200 | AF56: ='2024 Bdg vs Actual All'!Y56-'2024 Bdg vs Actual -OH'!AF56 -> 19784 | AG56: =AE56-AF56 -> -3584 | AI56: 16200 | AJ56: ='2024 Bdg vs Actual All'!AC56-'2024 Bdg vs Actual -OH'!AJ56 -> 13034 | AK56: =AI56-AJ56 -> 3166 | AM56: 16200 | AN56: ='2024 Bdg vs Actual All'!AG56-'2024 Bdg vs Actual -OH'!AN56 -> 16935 | AO56: =AM56-AN56 -> -735 | AQ56: 16200 | AR56: ='2024 Bdg vs Actual All'!AK56-'2024 Bdg vs Actual -OH'!AR56 -> 19012 | AS56: =AQ56-AR56 -> -2812 | AT56: Avalara Aug & Sept hit the GL,Knowbe4 renewal | AU56: 16200 | AV56: ='2024 Bdg vs Actual All'!AO56-'2024 Bdg vs Actual -OH'!AV56 -> 18001 | AW56: =AU56-AV56 -> -1801 | AY56: 16200 | AZ56: ='2024 Bdg vs Actual All'!AS56-'2024 Bdg vs Actual -OH'!AZ56 -> 13564 | BA56: =AY56-AZ56 -> 2636 | BC56: 16200 | BD56: ='2024 Bdg vs Actual All'!AW56-'2024 Bdg vs Actual -OH'!BD56 -> 20496 | BE56: =BC56-BD56 -> -4296 | BG56: 16200 | BH56: ='2024 Bdg vs Actual All'!BA56-'2024 Bdg vs Actual -OH'!BH56 -> 21168 | BI56: =BG56-BH56 -> -4968 | BK56: {=ROUND(O56:BG56, -2)} -> #VALUE! | CG56: =+W56+S56+O56+AA56+AE56+AI56+AM56+AQ56+AU56+AY56+BC56+BG56 -> 188000 | CH56: =+X56+T56+P56+AB56+AF56+AJ56+AN56+AR56+AV56+AZ56+BD56+BH56 -> 206129 | CI56: =CG56-CH56 -> -18129
A57: Supplies | E57: =ROUND(O57+S57+W57+AA57+AE57+AI57+AM57+AQ57+AU57+AY57+BC57+BG57,-2) -> 94500 | O57: 9000 | P57: ='2024 Bdg vs Actual All'!I57-'2024 Bdg vs Actual -OH'!P57 -> 5243 | Q57: =O57-P57 -> 3757 | S57: 9000 | T57: ='2024 Bdg vs Actual All'!M57-'2024 Bdg vs Actual -OH'!T57 -> 5288 | U57: =S57-T57 -> 3712 | W57: 7500 | X57: ='2024 Bdg vs Actual All'!Q57-'2024 Bdg vs Actual -OH'!X57 -> 4665 | Y57: =W57-X57 -> 2835 | AA57: 7500 | AB57: ='2024 Bdg vs Actual All'!U57-'2024 Bdg vs Actual -OH'!AB57 -> 5026 | AC57: =AA57-AB57 -> 2474 | AE57: 7500 | AF57: ='2024 Bdg vs Actual All'!Y57-'2024 Bdg vs Actual -OH'!AF57 -> 5399 | AG57: =AE57-AF57 -> 2101 | AI57: 8000 | AJ57: ='2024 Bdg vs Actual All'!AC57-'2024 Bdg vs Actual -OH'!AJ57 -> 4875 | AK57: =AI57-AJ57 -> 3125 | AM57: 8000 | AN57: ='2024 Bdg vs Actual All'!AG57-'2024 Bdg vs Actual -OH'!AN57 -> 4600 | AO57: =AM57-AN57 -> 3400 | AQ57: 8000 | AR57: ='2024 Bdg vs Actual All'!AK57-'2024 Bdg vs Actual -OH'!AR57 -> 6953 | AS57: =AQ57-AR57 -> 1047 | AU57: 7500 | AV57: 10530 | AW57: =AU57-AV57 -> -3030 | AY57: 7500 | AZ57: ='2024 Bdg vs Actual All'!AS57-'2024 Bdg vs Actual -OH'!AZ57 -> 6932 | BA57: =AY57-AZ57 -> 568 | BC57: 7500 | BD57: ='2024 Bdg vs Actual All'!AW57-'2024 Bdg vs Actual -OH'!BD57 -> 4221 | BE57: =BC57-BD57 -> 3279 | BG57: 7500 | BH57: ='2024 Bdg vs Actual All'!BA57-'2024 Bdg vs Actual -OH'!BH57 -> 4210 | BI57: =BG57-BH57 -> 3290 | BK57: {=ROUND(O57:BG57, -2)} -> #VALUE! | CG57: =+W57+S57+O57+AA57+AE57+AI57+AM57+AQ57+AU57+AY57+BC57+BG57 -> 94500 | CH57: =+X57+T57+P57+AB57+AF57+AJ57+AN57+AR57+AV57+AZ57+BD57+BH57 -> 67942 | CI57: =CG57-CH57 -> 26558
A58: Total Office Expenses | E58: =SUM(E52:E57) -> 700300 | O58: =SUM(O52:O57) -> 56900 | P58: =SUM(P52:P57) -> 56930 | Q58: =O58-P58 -> -30 | S58: =SUM(S52:S57) -> 57900 | T58: =SUM(T52:T57) -> 59473 | U58: =S58-T58 -> -1573 | W58: =SUM(W52:W57) -> 56600 | X58: =SUM(X52:X57) -> 54537 | Y58: =W58-X58 -> 2063 | AA58: =SUM(AA52:AA57) -> 58600 | AB58: =SUM(AB52:AB57) -> 50139 | AC58: =AA58-AB58 -> 8461 | AE58: =SUM(AE52:AE57) -> 58600 | AF58: =SUM(AF52:AF57) -> 54524 | AG58: =AE58-AF58 -> 4076 | AI58: =SUM(AI52:AI57) -> 59100 | AJ58: =SUM(AJ52:AJ57) -> 51423.34 | AK58: =AI58-AJ58 -> 7676.66 | AM58: =SUM(AM52:AM57) -> 59100 | AN58: =SUM(AN52:AN57) -> 51844 | AO58: =AM58-AN58 -> 7256 | AQ58: =SUM(AQ52:AQ57) -> 59100 | AR58: =SUM(AR52:AR57) -> 58765 | AS58: =AQ58-AR58 -> 335 | AU58: =SUM(AU52:AU57) -> 58600 | AV58: =SUM(AV52:AV57) -> 65307 | AW58: =AU58-AV58 -> -6707 | AY58: =SUM(AY52:AY57) -> 58600 | AZ58: =SUM(AZ52:AZ57) -> 51853 | BA58: =AY58-AZ58 -> 6747 | BC58: =SUM(BC52:BC57) -> 58600 | BD58: =SUM(BD52:BD57) -> 56602 | BE58: =BC58-BD58 -> 1998 | BG58: =SUM(BG52:BG57) -> 58600 | BH58: =SUM(BH52:BH57) -> 56498 | BI58: =BG58-BH58 -> 2102 | BK58: {=ROUND(O58:BG58, -2)} -> #VALUE! | CG58: =SUM(CG52:CG57) -> 700300 | CH58: =SUM(CH52:CH57) -> 667895.34 | CI58: =CG58-CH58 -> 32404.66
A61: Professional Services*****
A62: Consulting / Legal | E62: =ROUND(O62+S62+W62+AA62+AE62+AI62+AM62+AQ62+AU62+AY62+BC62+BG62,-2) -> 238000 | O62: 22000 | P62: ='2024 Bdg vs Actual All'!I62-'2024 Bdg vs Actual -OH'!P62 -> 13695 | Q62: =O62-P62 -> 8305 | S62: 22000 | T62: ='2024 Bdg vs Actual All'!M62-'2024 Bdg vs Actual -OH'!T62 -> 3458 | U62: =S62-T62 -> 18542 | W62: 19400 | X62: ='2024 Bdg vs Actual All'!Q62-'2024 Bdg vs Actual -OH'!X62 -> 25620 | Y62: =W62-X62 -> -6220 | Z62: $6200 for AP Logic | AA62: 19400 | AB62: ='2024 Bdg vs Actual All'!U62-'2024 Bdg vs Actual -OH'!AB62 -> 37153.41 | AC62: =AA62-AB62 -> -17753.41 | AD62: $18K for SOC2 Audit | AE62: 19400 | AF62: ='2024 Bdg vs Actual All'!Y62-'2024 Bdg vs Actual -OH'!AF62 -> 10999.83 | AG62: =AE62-AF62 -> 8400.17 | AH62: Accured SOC Complaince over the year | AI62: 19400 | AJ62: ='2024 Bdg vs Actual All'!AC62-'2024 Bdg vs Actual -OH'!AJ62 -> 18342.5 | AK62: =AI62-AJ62 -> 1057.5 | AM62: 19400 | AN62: ='2024 Bdg vs Actual All'!AG62-'2024 Bdg vs Actual -OH'!AN62 -> 29369 | AO62: =AM62-AN62 -> -9969 | AP62: Clevel Advising increase | AQ62: 19400 | AR62: ='2024 Bdg vs Actual All'!AK62-'2024 Bdg vs Actual -OH'!AR62 -> 37609.5 | AS62: =AQ62-AR62 -> -18209.5 | AT62: Clevel Advising increase | AU62: 19400 | AV62: ='2024 Bdg vs Actual All'!AO62-'2024 Bdg vs Actual -OH'!AV62 -> 30010 | AW62: =AU62-AV62 -> -10610 | AX62: Clevel Advising increase | AY62: 19400 | AZ62: ='2024 Bdg vs Actual All'!AS62-'2024 Bdg vs Actual -OH'!AZ62 -> 51661.78 | BA62: =AY62-AZ62 -> -32261.78 | BB62: Clevel Advising and Phoenix Strategy | BC62: 19400 | BD62: ='2024 Bdg vs Actual All'!AW62-'2024 Bdg vs Actual -OH'!BD62 -> 43338.06 | BE62: =BC62-BD62 -> -23938.06 | BG62: 19400 | BH62: ='2024 Bdg vs Actual All'!BA62-'2024 Bdg vs Actual -OH'!BH62 -> 39687.44 | BI62: =BG62-BH62 -> -20287.44 | BJ62: Clevel Advising and Phoenix Strategy | CG62: =+W62+S62+O62+AA62+AE62+AI62+AM62+AQ62+AU62+AY62+BC62+BG62 -> 238000 | CH62: =+X62+T62+P62+AB62+AF62+AJ62+AN62+AR62+AV62+AZ62+BD62+BH62 -> 340944.52 | CI62: =CG62-CH62 -> -102944.52
A63: Accounting / CPA | E63: =ROUND(O63+S63+W63+AA63+AE63+AI63+AM63+AQ63+AU63+AY63+BC63+BG63,-2) -> 13100 | O63: 0 | P63: ='2024 Bdg vs Actual All'!I63-'2024 Bdg vs Actual -OH'!P63 -> 350 | Q63: =O63-P63 -> -350 | S63: 0 | T63: ='2024 Bdg vs Actual All'!M63-'2024 Bdg vs Actual -OH'!T63 -> 0 | U63: =S63-T63 -> 0 | W63: 6800 | X63: ='2024 Bdg vs Actual All'!Q63-'2024 Bdg vs Actual -OH'!X63 -> 0 | Y63: =W63-X63 -> 6800 | AA63: 6300 | AB63: ='2024 Bdg vs Actual All'!U63-'2024 Bdg vs Actual -OH'!AB63 -> 19769 | AC63: =AA63-AB63 -> -13469 | AD63: Tax returns | AE63: 0 | AF63: ='2024 Bdg vs Actual All'!Y63-'2024 Bdg vs Actual -OH'!AF63 -> 350 | AG63: =AE63-AF63 -> -350 | AI63: 0 | AJ63: ='2024 Bdg vs Actual All'!AC63-'2024 Bdg vs Actual -OH'!AJ63 -> 350 | AK63: =AI63-AJ63 -> -350 | AM63: 0 | AN63: ='2024 Bdg vs Actual All'!AG63-'2024 Bdg vs Actual -OH'!AN63 -> 350 | AO63: =AM63-AN63 -> -350 | AQ63: 0 | AR63: ='2024 Bdg vs Actual All'!AK63-'2024 Bdg vs Actual -OH'!AR63 -> 350 | AS63: =AQ63-AR63 -> -350 | AU63: 0 | AV63: ='2024 Bdg vs Actual All'!AO63-'2024 Bdg vs Actual -OH'!AV63 -> 350 | AW63: =AU63-AV63 -> -350 | AY63: 0 | AZ63: ='2024 Bdg vs Actual All'!AS63-'2024 Bdg vs Actual -OH'!AZ63 -> 400 | BA63: =AY63-AZ63 -> -400 | BC63: 0 | BD63: ='2024 Bdg vs Actual All'!AW63-'2024 Bdg vs Actual -OH'!BD63 -> 400 | BE63: =BC63-BD63 -> -400 | BG63: 0 | BH63: ='2024 Bdg vs Actual All'!BA63-'2024 Bdg vs Actual -OH'!BH63 -> 400 | BI63: =BG63-BH63 -> -400 | CG63: =+W63+S63+O63+AA63+AE63+AI63+AM63+AQ63+AU63+AY63+BC63+BG63 -> 13100 | CH63: =+X63+T63+P63+AB63+AF63+AJ63+AN63+AR63+AV63+AZ63+BD63+BH63 -> 23069 | CI63: =CG63-CH63 -> -9969
A64: HR Recruitment + Consulting | E64: =ROUND(O64+S64+W64+AA64+AE64+AI64+AM64+AQ64+AU64+AY64+BC64+BG64,-2) -> 8500 | O64: 700 | P64: ='2024 Bdg vs Actual All'!I64-'2024 Bdg vs Actual -OH'!P64 -> 1102 | Q64: =O64-P64 -> -402 | S64: 0 | T64: ='2024 Bdg vs Actual All'!M64-'2024 Bdg vs Actual -OH'!T64 -> 0 | U64: =S64-T64 -> 0 | W64: 1400 | X64: ='2024 Bdg vs Actual All'!Q64-'2024 Bdg vs Actual -OH'!X64 -> 0 | Y64: =W64-X64 -> 1400 | AA64: 0 | AB64: ='2024 Bdg vs Actual All'!U64-'2024 Bdg vs Actual -OH'!AB64 -> 92.59 | AC64: =AA64-AB64 -> -92.59 | AE64: 900 | AF64: ='2024 Bdg vs Actual All'!Y64-'2024 Bdg vs Actual -OH'!AF64 -> 569.09 | AG64: =AE64-AF64 -> 330.91 | AI64: 900 | AJ64: ='2024 Bdg vs Actual All'!AC64-'2024 Bdg vs Actual -OH'!AJ64 -> 2531.23 | AK64: =AI64-AJ64 -> -1631.23 | AM64: 0 | AN64: ='2024 Bdg vs Actual All'!AG64-'2024 Bdg vs Actual -OH'!AN64 -> 2275 | AO64: =AM64-AN64 -> -2275 | AQ64: 1900 | AR64: ='2024 Bdg vs Actual All'!AK64-'2024 Bdg vs Actual -OH'!AR64 -> 860 | AS64: =AQ64-AR64 -> 1040 | AU64: 0 | AV64: ='2024 Bdg vs Actual All'!AO64-'2024 Bdg vs Actual -OH'!AV64 -> 1643.5 | AW64: =AU64-AV64 -> -1643.5 | AY64: 900 | AZ64: ='2024 Bdg vs Actual All'!AS64-'2024 Bdg vs Actual -OH'!AZ64 -> 20 | BA64: =AY64-AZ64 -> 880 | BC64: 900 | BD64: ='2024 Bdg vs Actual All'!AW64-'2024 Bdg vs Actual -OH'!BD64 -> 295 | BE64: =BC64-BD64 -> 605 | BG64: 900 | BH64: ='2024 Bdg vs Actual All'!BA64-'2024 Bdg vs Actual -OH'!BH64 -> 997.5 | BI64: =BG64-BH64 -> -97.5 | CG64: =+W64+S64+O64+AA64+AE64+AI64+AM64+AQ64+AU64+AY64+BC64+BG64 -> 8500 | CH64: =+X64+T64+P64+AB64+AF64+AJ64+AN64+AR64+AV64+AZ64+BD64+BH64 -> 10385.91 | CI64: =CG64-CH64 -> -1885.91
A65: Financial Review / Audit | E65: =ROUND(O65+S65+W65+AA65+AE65+AI65+AM65+AQ65+AU65+AY65+BC65+BG65,-2) -> 33000 | O65: 0 | P65: ='2024 Bdg vs Actual All'!I65-'2024 Bdg vs Actual -OH'!P65 -> 0 | Q65: =O65-P65 -> 0 | S65: 0 | T65: ='2024 Bdg vs Actual All'!M65-'2024 Bdg vs Actual -OH'!T65 -> 0 | U65: =S65-T65 -> 0 | W65: 0 | X65: ='2024 Bdg vs Actual All'!Q65-'2024 Bdg vs Actual -OH'!X65 -> 0 | Y65: =W65-X65 -> 0 | AA65: 0 | AB65: ='2024 Bdg vs Actual All'!U65-'2024 Bdg vs Actual -OH'!AB65 -> 7500 | AC65: =AA65-AB65 -> -7500 | AE65: 0 | AF65: ='2024 Bdg vs Actual All'!Y65-'2024 Bdg vs Actual -OH'!AF65 -> 0 | AG65: =AE65-AF65 -> 0 | AI65: 0 | AJ65: ='2024 Bdg vs Actual All'!AC65-'2024 Bdg vs Actual -OH'!AJ65 -> 0 | AK65: =AI65-AJ65 -> 0 | AM65: 0 | AN65: ='2024 Bdg vs Actual All'!AG65-'2024 Bdg vs Actual -OH'!AN65 -> 0 | AO65: =AM65-AN65 -> 0 | AQ65: 0 | AR65: ='2024 Bdg vs Actual All'!AK65-'2024 Bdg vs Actual -OH'!AR65 -> 0 | AS65: =AQ65-AR65 -> 0 | AU65: 33000 | AV65: ='2024 Bdg vs Actual All'!AO65-'2024 Bdg vs Actual -OH'!AV65 -> 0 | AW65: =AU65-AV65 -> 33000 | AY65: 0 | AZ65: ='2024 Bdg vs Actual All'!AS65-'2024 Bdg vs Actual -OH'!AZ65 -> 0 | BA65: =AY65-AZ65 -> 0 | BC65: 0 | BD65: ='2024 Bdg vs Actual All'!AW65-'2024 Bdg vs Actual -OH'!BD65 -> 0 | BE65: =BC65-BD65 -> 0 | BG65: 0 | BH65: ='2024 Bdg vs Actual All'!BA65-'2024 Bdg vs Actual -OH'!BH65 -> 0 | BI65: =BG65-BH65 -> 0 | CG65: =+W65+S65+O65+AA65+AE65+AI65+AM65+AQ65+AU65+AY65+BC65+BG65 -> 33000 | CH65: =+X65+T65+P65+AB65+AF65+AJ65+AN65+AR65+AV65+AZ65+BD65+BH65 -> 7500 | CI65: =CG65-CH65 -> 25500
A66: Professional Services Total | E66: =SUM(E62:E65) -> 292600 | O66: =SUM(O62:O65) -> 22700 | P66: =SUM(P62:P65) -> 15147 | Q66: =O66-P66 -> 7553 | S66: =SUM(S62:S65) -> 22000 | T66: =SUM(T62:T65) -> 3458 | U66: =S66-T66 -> 18542 | W66: =SUM(W62:W65) -> 27600 | X66: =SUM(X62:X65) -> 25620 | Y66: =W66-X66 -> 1980 | AA66: =SUM(AA62:AA65) -> 25700 | AB66: =SUM(AB62:AB65) -> 64515 | AC66: =AA66-AB66 -> -38815 | AE66: =SUM(AE62:AE65) -> 20300 | AF66: =SUM(AF62:AF65) -> 11918.92 | AG66: =AE66-AF66 -> 8381.08 | AI66: =SUM(AI62:AI65) -> 20300 | AJ66: =SUM(AJ62:AJ65) -> 21223.73 | AK66: =AI66-AJ66 -> -923.73 | AM66: =SUM(AM62:AM65) -> 19400 | AN66: =SUM(AN62:AN65) -> 31994 | AO66: =AM66-AN66 -> -12594 | AQ66: =SUM(AQ62:AQ65) -> 21300 | AR66: =SUM(AR62:AR65) -> 38819.5 | AS66: =AQ66-AR66 -> -17519.5 | AU66: =SUM(AU62:AU65) -> 52400 | AV66: =SUM(AV62:AV65) -> 32003.5 | AW66: =AU66-AV66 -> 20396.5 | AY66: =SUM(AY62:AY65) -> 20300 | AZ66: =SUM(AZ62:AZ65) -> 52081.78 | BA66: =AY66-AZ66 -> -31781.78 | BC66: =SUM(BC62:BC65) -> 20300 | BD66: =SUM(BD62:BD65) -> 44033.06 | BE66: =BC66-BD66 -> -23733.06 | BG66: =SUM(BG62:BG65) -> 20300 | BH66: =SUM(BH62:BH65) -> 41084.94 | BI66: =BG66-BH66 -> -20784.94 | CG66: =SUM(CG62:CG65) -> 292600 | CH66: =SUM(CH62:CH65) -> 381899.43 | CI66: =CG66-CH66 -> -89299.43
A68: General & Admin Expenses
A69: Charitable Contributions | E69: =ROUND(O69+S69+W69+AA69+AE69+AI69+AM69+AQ69+AU69+AY69+BC69+BG69,-2) -> 35100 | O69: 1000 | P69: ='2024 Bdg vs Actual All'!I69-'2024 Bdg vs Actual -OH'!P69 -> 1000 | Q69: =O69-P69 -> 0 | S69: 1500 | T69: ='2024 Bdg vs Actual All'!M69-'2024 Bdg vs Actual -OH'!T69 -> 1250 | U69: =S69-T69 -> 250 | W69: 2300 | X69: ='2024 Bdg vs Actual All'!Q69-'2024 Bdg vs Actual -OH'!X69 -> 6181 | Y69: =W69-X69 -> -3881 | Z69: $5K for Aerial Recovery | AA69: 5100 | AB69: ='2024 Bdg vs Actual All'!U69-'2024 Bdg vs Actual -OH'!AB69 -> 1250 | AC69: =AA69-AB69 -> 3850 | AE69: 3000 | AF69: ='2024 Bdg vs Actual All'!Y69-'2024 Bdg vs Actual -OH'!AF69 -> 3613 | AG69: =AE69-AF69 -> -613 | AI69: 5100 | AJ69: ='2024 Bdg vs Actual All'!AC69-'2024 Bdg vs Actual -OH'!AJ69 -> 1000 | AK69: =AI69-AJ69 -> 4100 | AM69: 2000 | AN69: ='2024 Bdg vs Actual All'!AG69-'2024 Bdg vs Actual -OH'!AN69 -> 11000 | AO69: =AM69-AN69 -> -9000 | AP69: $10K for GG San Francisco Contribution | AQ69: 2000 | AR69: ='2024 Bdg vs Actual All'!AK69-'2024 Bdg vs Actual -OH'!AR69 -> 6098 | AS69: =AQ69-AR69 -> -4098 | AU69: 2000 | AV69: ='2024 Bdg vs Actual All'!AO69-'2024 Bdg vs Actual -OH'!AV69 -> 3700 | AW69: =AU69-AV69 -> -1700 | AY69: 4000 | AZ69: ='2024 Bdg vs Actual All'!AS69-'2024 Bdg vs Actual -OH'!AZ69 -> 1180 | BA69: =AY69-AZ69 -> 2820 | BC69: 2000 | BD69: ='2024 Bdg vs Actual All'!AW69-'2024 Bdg vs Actual -OH'!BD69 -> 1000 | BE69: =BC69-BD69 -> 1000 | BG69: 5100 | BH69: ='2024 Bdg vs Actual All'!BA69-'2024 Bdg vs Actual -OH'!BH69 -> 1100 | BI69: =BG69-BH69 -> 4000 | CG69: =+W69+S69+O69+AA69+AE69+AI69+AM69+AQ69+AU69+AY69+BC69+BG69 -> 35100 | CH69: =+X69+T69+P69+AB69+AF69+AJ69+AN69+AR69+AV69+AZ69+BD69+BH69 -> 38372 | CI69: =CG69-CH69 -> -3272
A70: Marketing & Advertising | E70: =ROUND(O70+S70+W70+AA70+AE70+AI70+AM70+AQ70+AU70+AY70+BC70+BG70,-2) -> 86600 | O70: 6800 | P70: ='2024 Bdg vs Actual All'!I70-'2024 Bdg vs Actual -OH'!P70 -> 8944 | Q70: =O70-P70 -> -2144 | S70: 6800 | T70: ='2024 Bdg vs Actual All'!M70-'2024 Bdg vs Actual -OH'!T70 -> 8802 | U70: =S70-T70 -> -2002 | W70: 7300 | X70: ='2024 Bdg vs Actual All'!Q70-'2024 Bdg vs Actual -OH'!X70 -> 8618 | Y70: =W70-X70 -> -1318 | AA70: 7300 | AB70: ='2024 Bdg vs Actual All'!U70-'2024 Bdg vs Actual -OH'!AB70 -> 5065 | AC70: =AA70-AB70 -> 2235 | AE70: 7300 | AF70: ='2024 Bdg vs Actual All'!Y70-'2024 Bdg vs Actual -OH'!AF70 -> 15188 | AG70: =AE70-AF70 -> -7888 | AI70: 7300 | AJ70: ='2024 Bdg vs Actual All'!AC70-'2024 Bdg vs Actual -OH'!AJ70 -> 6842 | AK70: =AI70-AJ70 -> 458 | AL70: CTE Confernce $4K | AM70: 7300 | AN70: ='2024 Bdg vs Actual All'!AG70-'2024 Bdg vs Actual -OH'!AN70 -> 7388 | AO70: =AM70-AN70 -> -88 | AQ70: 7300 | AR70: ='2024 Bdg vs Actual All'!AK70-'2024 Bdg vs Actual -OH'!AR70 -> 9556 | AS70: =AQ70-AR70 -> -2256 | AT70: Sweeplift - linked in advertising | AU70: 7300 | AV70: 12244 | AW70: =AU70-AV70 -> -4944 | AX70: Sweeplift $5K | AY70: 7300 | AZ70: ='2024 Bdg vs Actual All'!AS70-'2024 Bdg vs Actual -OH'!AZ70 -> 15806 | BA70: =AY70-AZ70 -> -8506 | BB70: Sweeplift $5K & 2.5K, Linked In Ads | BC70: 7300 | BD70: ='2024 Bdg vs Actual All'!AW70-'2024 Bdg vs Actual -OH'!BD70 -> 13702 | BE70: =BC70-BD70 -> -6402 | BG70: 7300 | BH70: ='2024 Bdg vs Actual All'!BA70-'2024 Bdg vs Actual -OH'!BH70 -> 11392 | BI70: =BG70-BH70 -> -4092 | CG70: =+W70+S70+O70+AA70+AE70+AI70+AM70+AQ70+AU70+AY70+BC70+BG70 -> 86600 | CH70: =+X70+T70+P70+AB70+AF70+AJ70+AN70+AR70+AV70+AZ70+BD70+BH70 -> 123547 | CI70: =CG70-CH70 -> -36947
A71: Education & Staff Development | E71: =ROUND(O71+S71+W71+AA71+AE71+AI71+AM71+AQ71+AU71+AY71+BC71+BG71,-2) -> 12800 | O71: 800 | P71: ='2024 Bdg vs Actual All'!I71-'2024 Bdg vs Actual -OH'!P71 -> 1009 | Q71: =O71-P71 -> -209 | S71: 1200 | T71: ='2024 Bdg vs Actual All'!M71-'2024 Bdg vs Actual -OH'!T71 -> 815 | U71: =S71-T71 -> 385 | W71: 1000 | X71: ='2024 Bdg vs Actual All'!Q71-'2024 Bdg vs Actual -OH'!X71 -> 277 | Y71: =W71-X71 -> 723 | AA71: 1200 | AB71: ='2024 Bdg vs Actual All'!U71-'2024 Bdg vs Actual -OH'!AB71 -> 78 | AC71: =AA71-AB71 -> 1122 | AE71: 1000 | AF71: ='2024 Bdg vs Actual All'!Y71-'2024 Bdg vs Actual -OH'!AF71 -> 1633 | AG71: =AE71-AF71 -> -633 | AI71: 1200 | AJ71: ='2024 Bdg vs Actual All'!AC71-'2024 Bdg vs Actual -OH'!AJ71 -> 880 | AK71: =AI71-AJ71 -> 320 | AM71: 1000 | AN71: ='2024 Bdg vs Actual All'!AG71-'2024 Bdg vs Actual -OH'!AN71 -> 310 | AO71: =AM71-AN71 -> 690 | AQ71: 1200 | AR71: ='2024 Bdg vs Actual All'!AK71-'2024 Bdg vs Actual -OH'!AR71 -> 1923 | AS71: =AQ71-AR71 -> -723 | AU71: 1000 | AV71: ='2024 Bdg vs Actual All'!AO71-'2024 Bdg vs Actual -OH'!AV71 -> 631 | AW71: =AU71-AV71 -> 369 | AY71: 1200 | AZ71: ='2024 Bdg vs Actual All'!AS71-'2024 Bdg vs Actual -OH'!AZ71 -> 156 | BA71: =AY71-AZ71 -> 1044 | BC71: 800 | BD71: ='2024 Bdg vs Actual All'!AW71-'2024 Bdg vs Actual -OH'!BD71 -> 45 | BE71: =BC71-BD71 -> 755 | BG71: 1200 | BH71: ='2024 Bdg vs Actual All'!BA71-'2024 Bdg vs Actual -OH'!BH71 -> 250 | BI71: =BG71-BH71 -> 950 | CG71: =+W71+S71+O71+AA71+AE71+AI71+AM71+AQ71+AU71+AY71+BC71+BG71 -> 12800 | CH71: =+X71+T71+P71+AB71+AF71+AJ71+AN71+AR71+AV71+AZ71+BD71+BH71 -> 8007 | CI71: =CG71-CH71 -> 4793
A72: General & Admin Total | E72: =SUM(E69:E71) -> 134500 | O72: =SUM(O69:O71) -> 8600 | P72: =SUM(P69:P71) -> 10953 | Q72: =O72-P72 -> -2353 | S72: =SUM(S69:S71) -> 9500 | T72: =SUM(T69:T71) -> 10867 | U72: =S72-T72 -> -1367 | W72: =SUM(W69:W71) -> 10600 | X72: =SUM(X69:X71) -> 15076 | Y72: =W72-X72 -> -4476 | AA72: =SUM(AA69:AA71) -> 13600 | AB72: =SUM(AB69:AB71) -> 6393 | AC72: =AA72-AB72 -> 7207 | AE72: =SUM(AE69:AE71) -> 11300 | AF72: =SUM(AF69:AF71) -> 20434 | AG72: =AE72-AF72 -> -9134 | AI72: =SUM(AI69:AI71) -> 13600 | AJ72: =SUM(AJ69:AJ71) -> 8722 | AK72: =AI72-AJ72 -> 4878 | AM72: =SUM(AM69:AM71) -> 10300 | AN72: =SUM(AN69:AN71) -> 18698 | AO72: =AM72-AN72 -> -8398 | AQ72: =SUM(AQ69:AQ71) -> 10500 | AR72: =SUM(AR69:AR71) -> 17577 | AS72: =AQ72-AR72 -> -7077 | AU72: =SUM(AU69:AU71) -> 10300 | AV72: =SUM(AV69:AV71) -> 16575 | AW72: =AU72-AV72 -> -6275 | AY72: =SUM(AY69:AY71) -> 12500 | AZ72: =SUM(AZ69:AZ71) -> 17142 | BA72: =AY72-AZ72 -> -4642 | BC72: =SUM(BC69:BC71) -> 10100 | BD72: =SUM(BD69:BD71) -> 14747 | BE72: =BC72-BD72 -> -4647 | BG72: =SUM(BG69:BG71) -> 13600 | BH72: =SUM(BH69:BH71) -> 12742 | BI72: =BG72-BH72 -> 858 | CG72: =SUM(CG69:CG71) -> 134500 | CH72: =SUM(CH69:CH71) -> 169926 | CI72: =CG72-CH72 -> -35426
A74: Other Expenses
A75: Vehicles/ Gasoline | E75: =ROUND(O75+S75+W75+AA75+AE75+AI75+AM75+AQ75+AU75+AY75+BC75+BG75,-2) -> 107600 | O75: 9800 | P75: ='2024 Bdg vs Actual All'!I75-'2024 Bdg vs Actual -OH'!P75 -> 8773 | Q75: =O75-P75 -> 1027 | S75: 9800 | T75: ='2024 Bdg vs Actual All'!M75-'2024 Bdg vs Actual -OH'!T75 -> 5491 | U75: =S75-T75 -> 4309 | W75: 8800 | X75: ='2024 Bdg vs Actual All'!Q75-'2024 Bdg vs Actual -OH'!X75 -> 5877 | Y75: =W75-X75 -> 2923 | AA75: 8800 | AB75: ='2024 Bdg vs Actual All'!U75-'2024 Bdg vs Actual -OH'!AB75 -> 7265 | AC75: =AA75-AB75 -> 1535 | AE75: 8800 | AF75: ='2024 Bdg vs Actual All'!Y75-'2024 Bdg vs Actual -OH'!AF75 -> 7112 | AG75: =AE75-AF75 -> 1688 | AI75: 8800 | AJ75: ='2024 Bdg vs Actual All'!AC75-'2024 Bdg vs Actual -OH'!AJ75 -> 7913 | AK75: =AI75-AJ75 -> 887 | AM75: 8800 | AN75: ='2024 Bdg vs Actual All'!AG75-'2024 Bdg vs Actual -OH'!AN75 -> 8046 | AO75: =AM75-AN75 -> 754 | AQ75: 8800 | AR75: ='2024 Bdg vs Actual All'!AK75-'2024 Bdg vs Actual -OH'!AR75 -> 8123 | AS75: =AQ75-AR75 -> 677 | AU75: 8800 | AV75: ='2024 Bdg vs Actual All'!AO75-'2024 Bdg vs Actual -OH'!AV75 -> 9366 | AW75: =AU75-AV75 -> -566 | AY75: 8800 | AZ75: ='2024 Bdg vs Actual All'!AS75-'2024 Bdg vs Actual -OH'!AZ75 -> 6711 | BA75: =AY75-AZ75 -> 2089 | BC75: 8800 | BD75: ='2024 Bdg vs Actual All'!AW75-'2024 Bdg vs Actual -OH'!BD75 -> 4607 | BE75: =BC75-BD75 -> 4193 | BG75: 8800 | BH75: ='2024 Bdg vs Actual All'!BA75-'2024 Bdg vs Actual -OH'!BH75 -> 4692 | BI75: =BG75-BH75 -> 4108 | CG75: =+W75+S75+O75+AA75+AE75+AI75+AM75+AQ75+AU75+AY75+BC75+BG75 -> 107600 | CH75: =+X75+T75+P75+AB75+AF75+AJ75+AN75+AR75+AV75+AZ75+BD75+BH75 -> 83976 | CI75: =CG75-CH75 -> 23624
A76: Travel / Meals | E76: =ROUND(O76+S76+W76+AA76+AE76+AI76+AM76+AQ76+AU76+AY76+BC76+BG76,-2) -> 147600 | O76: 12300 | P76: ='2024 Bdg vs Actual All'!I76-'2024 Bdg vs Actual -OH'!P76 -> 11956 | Q76: =O76-P76 -> 344 | S76: 12300 | T76: ='2024 Bdg vs Actual All'!M76-'2024 Bdg vs Actual -OH'!T76 -> 22497 | U76: =S76-T76 -> -10197 | V76: Brandon and Dan trips to Ohio, IETA conference (Orion & Jay) Boom Conference (Michael & Frankie) James travel 9.9K Dave travel 2.2K | W76: 12300 | X76: ='2024 Bdg vs Actual All'!Q76-'2024 Bdg vs Actual -OH'!X76 -> 18820 | Y76: =W76-X76 -> -6520 | Z76: Brandon trip to Ohio, Boom Conference (Michael & Frankie) James travel 4.9K Dave travel 4.7K | AA76: 12300 | AB76: ='2024 Bdg vs Actual All'!U76-'2024 Bdg vs Actual -OH'!AB76 -> 8807 | AC76: =AA76-AB76 -> 3493 | AD76: Dan S to Bahamas, Jay to Western Steel James travel 4.8K Dave travel 0.5K | AE76: 12300 | AF76: ='2024 Bdg vs Actual All'!Y76-'2024 Bdg vs Actual -OH'!AF76 -> 13503 | AG76: =AE76-AF76 -> -1203 | AI76: 12300 | AJ76: ='2024 Bdg vs Actual All'!AC76-'2024 Bdg vs Actual -OH'!AJ76 -> 42512 | AK76: =AI76-AJ76 -> -30212 | AL76: Lucai Mar $13K, James $12K | AM76: 12300 | AN76: ='2024 Bdg vs Actual All'!AG76-'2024 Bdg vs Actual -OH'!AN76 -> 5588 | AO76: =AM76-AN76 -> 6712 | AQ76: 12300 | AR76: ='2024 Bdg vs Actual All'!AK76-'2024 Bdg vs Actual -OH'!AR76 -> 13670 | AS76: =AQ76-AR76 -> -1370 | AT76: Dinyero $2.1K, David $3K, James$5.6K, | AU76: 12300 | AV76: ='2024 Bdg vs Actual All'!AO76-'2024 Bdg vs Actual -OH'!AV76 -> 4171 | AW76: =AU76-AV76 -> 8129 | AY76: 12300 | AZ76: ='2024 Bdg vs Actual All'!AS76-'2024 Bdg vs Actual -OH'!AZ76 -> 14816 | BA76: =AY76-AZ76 -> -2516 | BC76: 12300 | BD76: ='2024 Bdg vs Actual All'!AW76-'2024 Bdg vs Actual -OH'!BD76 -> 18774 | BE76: =BC76-BD76 -> -6474 | BG76: 12300 | BH76: ='2024 Bdg vs Actual All'!BA76-'2024 Bdg vs Actual -OH'!BH76 -> 16628 | BI76: =BG76-BH76 -> -4328 | BJ76: Peter to NYC $1.6K, James $7.2K, David $5.3K | CG76: =+W76+S76+O76+AA76+AE76+AI76+AM76+AQ76+AU76+AY76+BC76+BG76 -> 147600 | CH76: =+X76+T76+P76+AB76+AF76+AJ76+AN76+AR76+AV76+AZ76+BD76+BH76 -> 191742 | CI76: =CG76-CH76 -> -44142
A77: Property Taxes | E77: =ROUND(O77+S77+W77+AA77+AE77+AI77+AM77+AQ77+AU77+AY77+BC77+BG77,-2) -> 59400 | O77: 7300 | P77: ='2024 Bdg vs Actual All'!I77-'2024 Bdg vs Actual -OH'!P77 -> 0 | Q77: =O77-P77 -> 7300 | S77: 0 | T77: ='2024 Bdg vs Actual All'!M77-'2024 Bdg vs Actual -OH'!T77 -> 0 | U77: =S77-T77 -> 0 | W77: 100 | X77: ='2024 Bdg vs Actual All'!Q77-'2024 Bdg vs Actual -OH'!X77 -> 564 | Y77: =W77-X77 -> -464 | AA77: 0 | AB77: ='2024 Bdg vs Actual All'!U77-'2024 Bdg vs Actual -OH'!AB77 -> 640 | AC77: =AA77-AB77 -> -640 | AE77: 0 | AF77: ='2024 Bdg vs Actual All'!Y77-'2024 Bdg vs Actual -OH'!AF77 -> 0 | AG77: =AE77-AF77 -> 0 | AI77: 0 | AJ77: ='2024 Bdg vs Actual All'!AC77-'2024 Bdg vs Actual -OH'!AJ77 -> 0 | AK77: =AI77-AJ77 -> 0 | AM77: 8500 | AN77: ='2024 Bdg vs Actual All'!AG77-'2024 Bdg vs Actual -OH'!AN77 -> 6263 | AO77: =AM77-AN77 -> 2237 | AQ77: 0 | AR77: ='2024 Bdg vs Actual All'!AK77-'2024 Bdg vs Actual -OH'!AR77 -> 298 | AS77: =AQ77-AR77 -> -298 | AU77: 3800 | AV77: ='2024 Bdg vs Actual All'!AO77-'2024 Bdg vs Actual -OH'!AV77 -> 25 | AW77: =AU77-AV77 -> 3775 | AY77: 1000 | AZ77: ='2024 Bdg vs Actual All'!AS77-'2024 Bdg vs Actual -OH'!AZ77 -> 0 | BA77: =AY77-AZ77 -> 1000 | BC77: 15300 | BD77: ='2024 Bdg vs Actual All'!AW77-'2024 Bdg vs Actual -OH'!BD77 -> 0 | BE77: =BC77-BD77 -> 15300 | BG77: 23400 | BH77: ='2024 Bdg vs Actual All'!BA77-'2024 Bdg vs Actual -OH'!BH77 -> 0 | BI77: =BG77-BH77 -> 23400 | CG77: =+W77+S77+O77+AA77+AE77+AI77+AM77+AQ77+AU77+AY77+BC77+BG77 -> 59400 | CH77: =+X77+T77+P77+AB77+AF77+AJ77+AN77+AR77+AV77+AZ77+BD77+BH77 -> 7790 | CI77: =CG77-CH77 -> 51610
A78: Finance Charges- Merchant and Bank Fees | E78: =ROUND(O78+S78+W78+AA78+AE78+AI78+AM78+AQ78+AU78+AY78+BC78+BG78,-2) -> 85300 | O78: 7200 | P78: ='2024 Bdg vs Actual All'!I78-'2024 Bdg vs Actual -OH'!P78 -> 7764 | Q78: =O78-P78 -> -564 | S78: 11800 | T78: ='2024 Bdg vs Actual All'!M78-'2024 Bdg vs Actual -OH'!T78 -> 5245 | U78: =S78-T78 -> 6555 | W78: 6200 | X78: ='2024 Bdg vs Actual All'!Q78-'2024 Bdg vs Actual -OH'!X78 -> 4393 | Y78: =W78-X78 -> 1807 | AA78: 6500 | AB78: ='2024 Bdg vs Actual All'!U78-'2024 Bdg vs Actual -OH'!AB78 -> 5004 | AC78: =AA78-AB78 -> 1496 | AE78: 6600 | AF78: ='2024 Bdg vs Actual All'!Y78-'2024 Bdg vs Actual -OH'!AF78 -> 4091 | AG78: =AE78-AF78 -> 2509 | AI78: 6600 | AJ78: ='2024 Bdg vs Actual All'!AC78-'2024 Bdg vs Actual -OH'!AJ78 -> 4971 | AK78: =AI78-AJ78 -> 1629 | AM78: 7000 | AN78: ='2024 Bdg vs Actual All'!AG78-'2024 Bdg vs Actual -OH'!AN78 -> 5373 | AO78: =AM78-AN78 -> 1627 | AQ78: 7200 | AR78: ='2024 Bdg vs Actual All'!AK78-'2024 Bdg vs Actual -OH'!AR78 -> 5321 | AS78: =AQ78-AR78 -> 1879 | AU78: 5200 | AV78: ='2024 Bdg vs Actual All'!AO78-'2024 Bdg vs Actual -OH'!AV78 -> 4578 | AW78: =AU78-AV78 -> 622 | AY78: 4800 | AZ78: ='2024 Bdg vs Actual All'!AS78-'2024 Bdg vs Actual -OH'!AZ78 -> 5175 | BA78: =AY78-AZ78 -> -375 | BC78: 7300 | BD78: ='2024 Bdg vs Actual All'!AW78-'2024 Bdg vs Actual -OH'!BD78 -> 5352 | BE78: =BC78-BD78 -> 1948 | BG78: 8900 | BH78: ='2024 Bdg vs Actual All'!BA78-'2024 Bdg vs Actual -OH'!BH78 -> 6945 | BI78: =BG78-BH78 -> 1955 | CG78: =+W78+S78+O78+AA78+AE78+AI78+AM78+AQ78+AU78+AY78+BC78+BG78 -> 85300 | CH78: =+X78+T78+P78+AB78+AF78+AJ78+AN78+AR78+AV78+AZ78+BD78+BH78 -> 64212 | CI78: =CG78-CH78 -> 21088
A79: Other Expenses Total | E79: =SUM(E75:E78) -> 399900 | O79: =SUM(O75:O78) -> 36600 | P79: =SUM(P75:P78) -> 28493 | Q79: =O79-P79 -> 8107 | S79: =SUM(S75:S78) -> 33900 | T79: =SUM(T75:T78) -> 33233 | U79: =S79-T79 -> 667 | W79: =SUM(W75:W78) -> 27400 | X79: =SUM(X75:X78) -> 29654 | Y79: =W79-X79 -> -2254 | AA79: =SUM(AA75:AA78) -> 27600 | AB79: =SUM(AB75:AB78) -> 21716 | AC79: =AA79-AB79 -> 5884 | AE79: =SUM(AE75:AE78) -> 27700 | AF79: =SUM(AF75:AF78) -> 24706 | AG79: =AE79-AF79 -> 2994 | AI79: =SUM(AI75:AI78) -> 27700 | AJ79: =SUM(AJ75:AJ78) -> 55396 | AK79: =AI79-AJ79 -> -27696 | AM79: =SUM(AM75:AM78) -> 36600 | AN79: =SUM(AN75:AN78) -> 25270 | AO79: =AM79-AN79 -> 11330 | AQ79: =SUM(AQ75:AQ78) -> 28300 | AR79: =SUM(AR75:AR78) -> 27412 | AS79: =AQ79-AR79 -> 888 | AU79: =SUM(AU75:AU78) -> 30100 | AV79: =SUM(AV75:AV78) -> 18140 | AW79: =AU79-AV79 -> 11960 | AY79: =SUM(AY75:AY78) -> 26900 | AZ79: =SUM(AZ75:AZ78) -> 26702 | BA79: =AY79-AZ79 -> 198 | BC79: =SUM(BC75:BC78) -> 43700 | BD79: =SUM(BD75:BD78) -> 28733 | BE79: =BC79-BD79 -> 14967 | BG79: =SUM(BG75:BG78) -> 53400 | BH79: =SUM(BH75:BH78) -> 28265 | BI79: =BG79-BH79 -> 25135 | CG79: =SUM(CG75:CG78) -> 399900 | CH79: =SUM(CH75:CH78) -> 347720 | CI79: =CG79-CH79 -> 52180
A81: Total Operating Expenses | E81: =E48+E58+E66+E72+E79 -> 2649200 | O81: =O48+O58+O66+O72+O79 -> 210300 | P81: =P48+P58+P66+P72+P79 -> 213472 | Q81: =O81-P81 -> -3172 | S81: =S48+S58+S66+S72+S79 -> 208800 | T81: =T48+T58+T66+T72+T79 -> 196287 | U81: =S81-T81 -> 12513 | W81: =W48+W58+W66+W72+W79 -> 211230.91 | X81: =X48+X58+X66+X72+X79 -> 215060 | Y81: =W81-X81 -> -3829.0933 | AA81: =AA48+AA58+AA66+AA72+AA79 -> 220820 | AB81: =AB48+AB58+AB66+AB72+AB79 -> 243528 | AC81: =AA81-AB81 -> -22708 | AE81: =AE48+AE58+AE66+AE72+AE79 -> 213220 | AF81: ='2024 Bdg vs Actual All'!Y81-'2024 Bdg vs Actual -OH'!AF81 -> 214854.92 | AG81: =AE81-AF81 -> -1634.92 | AI81: =AI48+AI58+AI66+AI72+AI79 -> 218020 | AJ81: ='2024 Bdg vs Actual All'!AC81-'2024 Bdg vs Actual -OH'!AJ81 -> 221733.07 | AK81: =AI81-AJ81 -> -3713.07 | AM81: =AM48+AM58+AM66+AM72+AM79 -> 220720 | AN81: ='2024 Bdg vs Actual All'!AG81-'2024 Bdg vs Actual -OH'!AN81 -> 212653 | AO81: =AM81-AN81 -> 8067 | AQ81: =AQ48+AQ58+AQ66+AQ72+AQ79 -> 214520 | AR81: ='2024 Bdg vs Actual All'!AK81-'2024 Bdg vs Actual -OH'!AR81 -> 236784.5 | AS81: =AQ81-AR81 -> -22264.5 | AU81: =AU48+AU58+AU66+AU72+AU79 -> 246720 | AV81: ='2024 Bdg vs Actual All'!AO81-'2024 Bdg vs Actual -OH'!AV81 -> 217320.5 | AW81: =AU81-AV81 -> 29399.5 | AY81: =AY48+AY58+AY66+AY72+AY79 -> 215620 | AZ81: ='2024 Bdg vs Actual All'!AS81-'2024 Bdg vs Actual -OH'!AZ81 -> 244453.78 | BA81: =AY81-AZ81 -> -28833.78 | BC81: =BC48+BC58+BC66+BC72+BC79 -> 228020 | BD81: ='2024 Bdg vs Actual All'!AW81-'2024 Bdg vs Actual -OH'!BD81 -> 241572.06 | BE81: =BC81-BD81 -> -13552.06 | BG81: =BG48+BG58+BG66+BG72+BG79 -> 241220 | BH81: ='2024 Bdg vs Actual All'!BA81-'2024 Bdg vs Actual -OH'!BH81 -> 268524.94 | BI81: =BG81-BH81 -> -27304.94 | CG81: =CG48+CG58+CG66+CG72+CG79 -> 2649210.9 | CH81: =CH48+CH58+CH66+CH72+CH79 -> 2726242.8 | CI81: =CG81-CH81 -> -77031.863
A83: EBITDA | E83: =E41-E81 -> 1728900 | O83: =O41-O81 -> 167698.97 | P83: =P41-P81 -> 442.57 | Q83: =P83-O83 -> -167256.4 | S83: =S41-S81 -> 124819.83 | T83: =T41-T81 -> 92248 | U83: =T83-S83 -> -32571.833 | W83: =W41-W81 -> 99486.463 | X83: =X41-X81 -> -7098.1633 | Y83: =X83-W83 -> -106584.63 | AA83: =AA41-AA81 -> 97921.839 | AB83: =AB41-AB81 -> 43504.819 | AC83: =AB83-AA83 -> -54417.02 | AE83: =AE41-AE81 -> 119508.84 | AF83: =AF41-AF81 -> -6761.6811 | AG83: =AF83-AE83 -> -126270.52 | AI83: =AI41-AI81 -> 103640.5 | AJ83: =AJ41-AJ81 -> 186315.14 | AK83: =AJ83-AI83 -> 82674.641 | AM83: =AM41-AM81 -> 160490.5 | AN83: =AN41-AN81 -> 121329.14 | AO83: =AN83-AM83 -> -39161.356 | AQ83: =AQ41-AQ81 -> 167840.5 | AR83: =AR41-AR81 -> 176882.73 | AS83: =AR83-AQ83 -> 9042.2335 | AU83: =AU41-AU81 -> 144590.5 | AV83: =AV41-AV81 -> 68218.653 | AW83: =AV83-AU83 -> -76371.845 | AY83: =AY41-AY81 -> 184640.5 | AZ83: =AZ41-AZ81 -> 8732.3703 | BA83: =AZ83-AY83 -> -175908.13 | BC83: =BC41-BC81 -> 181090.5 | BD83: =BD41-BD81 -> 80608.94 | BE83: =BD83-BC83 -> -100481.56 | BG83: =BG41-BG81 -> 177077.34 | BH83: =BH41-BH81 -> 7701.8 | BI83: =BH83-BG83 -> -169375.54 | CG83: =CG41-CG81 -> 1728806.3 | CH83: =CH41-CH81 -> 772125.32 | CI83: =CH83-CG83 -> -956680.95
A84: EBIDTA % of Gross Sales | E84: =E83/E11 -> 0.094990852 | O84: =O83/O11 -> 0.10868379 | P84: =P83/P11 -> 0.00052670002 | S84: =S83/S11 -> 0.084413079 | T84: =T83/T11 -> 0.074511806 | W84: =W83/W11 -> 0.068981608 | X84: =X83/X11 -> -0.0084768966 | AA84: =AA83/AA11 -> 0.067277653 | AB84: =AB83/AB11 -> 0.045911839 | AE84: =AE83/AE11 -> 0.081335416 | AF84: =AF83/AF11 -> -0.0079442456 | AI84: =AI83/AI11 -> 0.068217525 | AJ84: =AJ83/AJ11 -> 0.099993634 | AM84: =AM83/AM11 -> 0.10512145 | AN84: =AN83/AN11 -> 0.091575522 | AQ84: =AQ83/AQ11 -> 0.10968784 | AR84: =AR83/AR11 -> 0.13002469 | AU84: =AU83/AU11 -> 0.093791575 | AV84: =AV83/AV11 -> 0.072607253 | AY84: =AY83/AY11 -> 0.11888781 | AZ84: =AZ83/AZ11 -> 0.0095523643 | BC84: =BC83/BC11 -> 0.11574865 | BD84: =BD83/BD11 -> 0.060847177 | BG84: =BG83/BG11 -> 0.11231583 | BH84: =BH83/BH11 -> 0.0091795737 | CG84: =CG83/CG11 -> 0.094985919 | CH84: =CH83/CH11 -> 0.058140069
T85: =+T41-T81 -> 92248
A86: Other Income- Non Budgeted
A87: Interest Income | P87: ='2024 Bdg vs Actual All'!I87-'2024 Bdg vs Actual -OH'!P87 -> 1028 | Q87: =P87-O87 -> 1028 | T87: ='2024 Bdg vs Actual All'!M87-'2024 Bdg vs Actual -OH'!T87 -> 0 | U87: =T87-S87 -> 0 | X87: ='2024 Bdg vs Actual All'!Q87-'2024 Bdg vs Actual -OH'!X87 -> 0 | Y87: =X87-W87 -> 0 | AB87: ='2024 Bdg vs Actual All'!U87-'2024 Bdg vs Actual -OH'!AB87 -> 0 | AC87: =AB87-AA87 -> 0 | AF87: ='2024 Bdg vs Actual All'!Y87-'2024 Bdg vs Actual -OH'!AF87 -> 0 | AG87: =AF87-AE87 -> 0 | AV87: ='2024 Bdg vs Actual All'!AO87-'2024 Bdg vs Actual -OH'!AV87 -> 1090 | AZ87: ='2024 Bdg vs Actual All'!AS87-'2024 Bdg vs Actual -OH'!AZ87 -> 2411 | BB87: Money Market | BD87: ='2024 Bdg vs Actual All'!AW87-'2024 Bdg vs Actual -OH'!BD87 -> 1801 | BH87: ='2024 Bdg vs Actual All'!BA87-'2024 Bdg vs Actual -OH'!BH87 -> 1994 | BJ87: Money Market | CG87: =+W87+S87+O87+AA87+AE87+AI87+AM87+AQ87+AU87+AY87+BC87+BG87 -> 0 | CH87: =+X87+T87+P87+AB87+AF87+AJ87+AN87+AR87+AV87+AZ87+BD87+BH87 -> 8324
A88: Other Income- Non Budgeted | P88: ='2024 Bdg vs Actual All'!I88-'2024 Bdg vs Actual -OH'!P88 -> 600000 | Q88: =P88-O88 -> 600000 | T88: ='2024 Bdg vs Actual All'!M88-'2024 Bdg vs Actual -OH'!T88 -> 0 | U88: =T88-S88 -> 0 | X88: ='2024 Bdg vs Actual All'!Q88-'2024 Bdg vs Actual -OH'!X88 -> 0 | Y88: =X88-W88 -> 0 | AB88: ='2024 Bdg vs Actual All'!U88-'2024 Bdg vs Actual -OH'!AB88 -> 15470 | AC88: =AB88-AA88 -> 15470 | AD88: RAMP Cash Back Rewards | AF88: ='2024 Bdg vs Actual All'!Y88-'2024 Bdg vs Actual -OH'!AF88 -> 90848 | AG88: =AF88-AE88 -> 90848 | AH88: Thomanson Tractor Final Billing | AJ88: ='2024 Bdg vs Actual All'!AC88-'2024 Bdg vs Actual -OH'!AJ88 -> 3246 | AK88: =AJ88-AI88 -> 3246 | AN88: ='2024 Bdg vs Actual All'!AG88-'2024 Bdg vs Actual -OH'!AN88 -> 0 | AO88: =AN88-AM88 -> 0 | AR88: ='2024 Bdg vs Actual All'!AK88-'2024 Bdg vs Actual -OH'!AR88 -> 0 | AS88: =AR88-AQ88 -> 0 | AV88: ='2024 Bdg vs Actual All'!AO88-'2024 Bdg vs Actual -OH'!AV88 -> 0 | AW88: =AV88-AU88 -> 0 | AZ88: ='2024 Bdg vs Actual All'!AS88-'2024 Bdg vs Actual -OH'!AZ88 -> 9520 | BA88: =AZ88-AY88 -> 9520 | BB88: Pinnacle settlement | BD88: ='2024 Bdg vs Actual All'!AW88-'2024 Bdg vs Actual -OH'!BD88 -> 0 | BE88: =BD88-BC88 -> 0 | BH88: ='2024 Bdg vs Actual All'!BA88-'2024 Bdg vs Actual -OH'!BH88 -> 0 | BI88: =BH88-BG88 -> 0 | CG88: =+W88+S88+O88+AA88+AE88+AI88+AM88+AQ88+AU88+AY88+BC88+BG88 -> 0 | CH88: =+X88+T88+P88+AB88+AF88+AJ88+AN88+AR88+AV88+AZ88+BD88+BH88 -> 719084 | CI88: =CH88-CG88 -> 719084
A89: Total Other Income | E89: =E87+E88 -> 0 | O89: =O87+O88 -> 0 | P89: =P87+P88 -> 601028 | Q89: =Q87+Q88 -> 601028 | T89: =T87+T88 -> 0 | U89: =U87+U88 -> 0 | X89: =X87+X88 -> 0 | AA89: =AA87+AA88 -> 0 | AB89: =AB87+AB88 -> 15470 | AC89: =AB89-AA89 -> 15470 | AE89: =AE87+AE88 -> 0 | AF89: =AF87+AF88 -> 90848 | AG89: =AF89-AE89 -> 90848 | AI89: =AI87+AI88 -> 0 | AJ89: =AJ87+AJ88 -> 3246 | AK89: =AJ89-AI89 -> 3246 | AM89: =AM87+AM88 -> 0 | AN89: =AN87+AN88 -> 0 | AO89: =AN89-AM89 -> 0 | AQ89: =AQ87+AQ88 -> 0 | AR89: =AR87+AR88 -> 0 | AS89: =AR89-AQ89 -> 0 | AU89: =AU87+AU88 -> 0 | AV89: =AV87+AV88 -> 1090 | AW89: =AV89-AU89 -> 1090 | AY89: =AY87+AY88 -> 0 | AZ89: =AZ87+AZ88 -> 11931 | BA89: =AZ89-AY89 -> 11931 | BC89: =BC87+BC88 -> 0 | BD89: =BD87+BD88 -> 1801 | BE89: =BD89-BC89 -> 1801 | BG89: =BG87+BG88 -> 0 | BH89: =BH87+BH88 -> 1994 | BI89: =BH89-BG89 -> 1994 | CG89: =CG87+CG88 -> 0 | CH89: =CH87+CH88 -> 727408
A90: Other Expenses-
A91: Interest Expense | E91: =ROUND(O91+S92+W92+AA92+AE92+AI92+AM92+AQ92+AU92+AY92+BC92+BG92,-2) -> 19100 | O91: 2100 | P91: ='2024 Bdg vs Actual All'!I91-'2024 Bdg vs Actual -OH'!P91 -> 2024 | Q91: =P91-O91 -> -76 | S91: 2000 | T91: ='2024 Bdg vs Actual All'!M91-'2024 Bdg vs Actual -OH'!T91 -> 1995 | U91: =S91-T91 -> 5 | W91: 2000 | X91: ='2024 Bdg vs Actual All'!Q91-'2024 Bdg vs Actual -OH'!X91 -> 1983 | Y91: =W91-X91 -> 17 | AA91: 1900 | AB91: ='2024 Bdg vs Actual All'!U91-'2024 Bdg vs Actual -OH'!AB91 -> 2211 | AC91: =AA91-AB91 -> -311 | AE91: 1800 | AF91: ='2024 Bdg vs Actual All'!Y91-'2024 Bdg vs Actual -OH'!AF91 -> 1900 | AG91: =AE91-AF91 -> -100 | AI91: 1800 | AJ91: ='2024 Bdg vs Actual All'!AC91-'2024 Bdg vs Actual -OH'!AJ91 -> 1697 | AK91: =AI91-AJ91 -> 103 | AM91: 1600 | AN91: ='2024 Bdg vs Actual All'!AG91-'2024 Bdg vs Actual -OH'!AN91 -> 1607 | AO91: =AM91-AN91 -> -7 | AQ91: 1500 | AR91: ='2024 Bdg vs Actual All'!AK91-'2024 Bdg vs Actual -OH'!AR91 -> 1544 | AS91: =AQ91-AR91 -> -44 | AU91: 1500 | AV91: ='2024 Bdg vs Actual All'!AO91-'2024 Bdg vs Actual -OH'!AV91 -> 1469 | AW91: =AU91-AV91 -> 31 | AY91: 1200 | AZ91: ='2024 Bdg vs Actual All'!AS91-'2024 Bdg vs Actual -OH'!AZ91 -> 1276 | BA91: =AY91-AZ91 -> -76 | BC91: 1100 | BD91: ='2024 Bdg vs Actual All'!AW91-'2024 Bdg vs Actual -OH'!BD91 -> 1246 | BE91: =BC91-BD91 -> -146 | BG91: 1100 | BH91: ='2024 Bdg vs Actual All'!BA91-'2024 Bdg vs Actual -OH'!BH91 -> 1126 | BI91: =BG91-BH91 -> -26 | CG91: =+W91+S91+O91+AA91+AE91+AI91+AM91+AQ91+AU91+AY91+BC91+BG91 -> 19600 | CH91: =+X91+T91+P91+AB91+AF91+AJ91+AN91+AR91+AV91+AZ91+BD91+BH91 -> 20078 | CI91: =CG91-CH91 -> -478
A92: State and Local Income Taxes | P92: ='2024 Bdg vs Actual All'!I92-'2024 Bdg vs Actual -OH'!P92 -> 6327 | Q92: =O92-P92 -> -6327 | T92: ='2024 Bdg vs Actual All'!M92-'2024 Bdg vs Actual -OH'!T92 -> 52 | U92: =S92-T92 -> -52 | W92: 17000 | X92: ='2024 Bdg vs Actual All'!Q92-'2024 Bdg vs Actual -OH'!X92 -> 4000 | Y92: =W92-X92 -> 13000 | AB92: ='2024 Bdg vs Actual All'!U92-'2024 Bdg vs Actual -OH'!AB92 -> 4579 | AC92: =AA92-AB92 -> -4579 | AF92: ='2024 Bdg vs Actual All'!Y92-'2024 Bdg vs Actual -OH'!AF92 -> 1257 | AG92: =AE92-AF92 -> -1257 | AJ92: ='2024 Bdg vs Actual All'!AC92-'2024 Bdg vs Actual -OH'!AJ92 -> 0 | AK92: =AI92-AJ92 -> 0 | AN92: ='2024 Bdg vs Actual All'!AG92-'2024 Bdg vs Actual -OH'!AN92 -> 4450 | AO92: =AM92-AN92 -> -4450 | AR92: ='2024 Bdg vs Actual All'!AK92-'2024 Bdg vs Actual -OH'!AR92 -> 1 | AS92: =AQ92-AR92 -> -1 | AV92: ='2024 Bdg vs Actual All'!AO92-'2024 Bdg vs Actual -OH'!AV92 -> 0 | AW92: =AU92-AV92 -> 0 | AZ92: ='2024 Bdg vs Actual All'!AS92-'2024 Bdg vs Actual -OH'!AZ92 -> 601 | BA92: =AY92-AZ92 -> -601 | BD92: ='2024 Bdg vs Actual All'!AW92-'2024 Bdg vs Actual -OH'!BD92 -> 6042 | BE92: =BC92-BD92 -> -6042 | BH92: ='2024 Bdg vs Actual All'!BA92-'2024 Bdg vs Actual -OH'!BH92 -> 600 | BI92: =BG92-BH92 -> -600 | CG92: =+W92+S92+O92+AA92+AE92+AI92+AM92+AQ92+AU92+AY92+BC92+BG92 -> 17000 | CH92: =+X92+T92+P92+AB92+AF92+AJ92+AN92+AR92+AV92+AZ92+BD92+BH92 -> 27909 | CI92: =CG92-CH92 -> -10909
A93: Partnership Expenses | P93: ='2024 Bdg vs Actual All'!I93-'2024 Bdg vs Actual -OH'!P93 -> 27972 | Q93: =O93-P93 -> -27972 | T93: ='2024 Bdg vs Actual All'!M93-'2024 Bdg vs Actual -OH'!T93 -> 34196 | U93: =S93-T93 -> -34196 | X93: ='2024 Bdg vs Actual All'!Q93-'2024 Bdg vs Actual -OH'!X93 -> 43552 | Y93: =W93-X93 -> -43552 | AB93: ='2024 Bdg vs Actual All'!U93-'2024 Bdg vs Actual -OH'!AB93 -> 28488 | AC93: =AA93-AB93 -> -28488 | AF93: ='2024 Bdg vs Actual All'!Y93-'2024 Bdg vs Actual -OH'!AF93 -> 13250 | AG93: =AE93-AF93 -> -13250 | AJ93: ='2024 Bdg vs Actual All'!AC93-'2024 Bdg vs Actual -OH'!AJ93 -> 28699 | AK93: =AI93-AJ93 -> -28699 | AN93: ='2024 Bdg vs Actual All'!AG93-'2024 Bdg vs Actual -OH'!AN93 -> 20831 | AO93: =AM93-AN93 -> -20831 | AR93: ='2024 Bdg vs Actual All'!AK93-'2024 Bdg vs Actual -OH'!AR93 -> 15612 | AS93: =AQ93-AR93 -> -15612 | AV93: ='2024 Bdg vs Actual All'!AO93-'2024 Bdg vs Actual -OH'!AV93 -> 16576 | AW93: =AU93-AV93 -> -16576 | AZ93: ='2024 Bdg vs Actual All'!AS93-'2024 Bdg vs Actual -OH'!AZ93 -> 15462 | BA93: =AY93-AZ93 -> -15462 | BD93: ='2024 Bdg vs Actual All'!AW93-'2024 Bdg vs Actual -OH'!BD93 -> 15308 | BE93: =BC93-BD93 -> -15308 | BH93: ='2024 Bdg vs Actual All'!BA93-'2024 Bdg vs Actual -OH'!BH93 -> 18050 | BI93: =BG93-BH93 -> -18050 | CG93: =+W93+S93+O93+AA93+AE93+AI93+AM93+AQ93+AU93+AY93+BC93+BG93 -> 0 | CH93: =+X93+T93+P93+AB93+AF93+AJ93+AN93+AR93+AV93+AZ93+BD93+BH93 -> 277996 | CI93: =CG93-CH93 -> -277996
A94: Total Other Expenses | E94: =SUM(E91:E93) -> 19100 | O94: =SUM(O91:O93) -> 2100 | P94: =SUM(P91:P93) -> 36323 | Q94: =SUM(Q91:Q93) -> -34375 | S94: =SUM(S91:S93) -> 2000 | T94: =SUM(T91:T93) -> 36243 | U94: =S94-T94 -> -34243 | W94: =SUM(W91:W93) -> 19000 | X94: =SUM(X91:X93) -> 49535 | Y94: =W94-X94 -> -30535 | AA94: =SUM(AA91:AA93) -> 1900 | AB94: =SUM(AB91:AB93) -> 35278 | AC94: =AA94-AB94 -> -33378 | AE94: =SUM(AE91:AE93) -> 1800 | AF94: =SUM(AF91:AF93) -> 16407 | AG94: =AE94-AF94 -> -14607 | AI94: =SUM(AI91:AI93) -> 1800 | AJ94: =SUM(AJ91:AJ93) -> 30396 | AK94: =AI94-AJ94 -> -28596 | AM94: =SUM(AM91:AM93) -> 1600 | AN94: =SUM(AN91:AN93) -> 26888 | AO94: =AM94-AN94 -> -25288 | AQ94: =SUM(AQ91:AQ93) -> 1500 | AR94: =SUM(AR91:AR93) -> 17157 | AS94: =AQ94-AR94 -> -15657 | AU94: =SUM(AU91:AU93) -> 1500 | AV94: =SUM(AV91:AV93) -> 18045 | AW94: =AU94-AV94 -> -16545 | AY94: =SUM(AY91:AY93) -> 1200 | AZ94: =SUM(AZ91:AZ93) -> 17339 | BA94: =AY94-AZ94 -> -16139 | BC94: =SUM(BC91:BC93) -> 1100 | BD94: =SUM(BD91:BD93) -> 22596 | BE94: =BC94-BD94 -> -21496 | BG94: =SUM(BG91:BG93) -> 1100 | BH94: =SUM(BH91:BH93) -> 19776 | BI94: =BG94-BH94 -> -18676 | CG94: =SUM(CG91:CG93) -> 36600 | CH94: =SUM(CH91:CH93) -> 325983 | CI94: =CG94-CH94 -> -289383
E95: =E89-E94 -> -19100
A96: Total Net Income | E96: =E83+E95 -> 1709800 | O96: =O83+O89-O94 -> 165598.97 | P96: =P83+P89-P94 -> 565147.57 | Q96: =P96-O96 -> 399548.6 | S96: =S83+S89-S94 -> 122819.83 | T96: =T83+T89-T94 -> 56005 | U96: =T96-S96 -> -66814.833 | W96: =W83+W89-W94 -> 80486.463 | X96: =X83+X89-X94 -> -56633.163 | Y96: =X96-W96 -> -137119.63 | AA96: =AA83+AA89-AA94 -> 96021.839 | AB96: =AB83+AB89-AB94 -> 23696.819 | AC96: =AB96-AA96 -> -72325.02 | AE96: =AE83+AE89-AE94 -> 117708.84 | AF96: =AF83+AF89-AF94 -> 67679.319 | AG96: =AF96-AE96 -> -50029.519 | AI96: =AI83+AI89-AI94 -> 101840.5 | AJ96: =AJ83+AJ89-AJ94 -> 159165.14 | AK96: =AJ96-AI96 -> 57324.641 | AM96: =AM83+AM89-AM94 -> 158890.5 | AN96: =AN83+AN89-AN94 -> 94441.142 | AO96: =AN96-AM96 -> -64449.356 | AQ96: =AQ83+AQ89-AQ94 -> 166340.5 | AR96: =AR83+AR89-AR94 -> 159725.73 | AS96: =AR96-AQ96 -> -6614.7665 | AU96: =AU83+AU89-AU94 -> 143090.5 | AV96: =AV83+AV89-AV94 -> 51263.653 | AW96: =AV96-AU96 -> -91826.845 | AY96: =AY83+AY89-AY94 -> 183440.5 | AZ96: =AZ83+AZ89-AZ94 -> 3324.3703 | BA96: =AZ96-AY96 -> -180116.13 | BC96: =BC83+BC89-BC94 -> 179990.5 | BD96: =BD83+BD89-BD94 -> 59813.94 | BE96: =BD96-BC96 -> -120176.56 | BG96: =BG83+BG89-BG94 -> 175977.34 | BH96: =BH83+BH89-BH94 -> -10080.2 | BI96: =BH96-BG96 -> -186057.54 | CG96: =CG83+CG89-CG94 -> 1692206.3 | CH96: =CH83+CH89-CH94 -> 1173550.3 | CI96: =CH96-CG96 -> -518655.95
AZ97: =+AZ96+AV96+AR96+AN96+AJ96+AF96+AB96+X96+T96+P96 -> 1123815.6 | BD97: =+BD96+AZ96+AV96+AR96+AN96+AJ96 -> 527733.97 | BH97: =+BH96+BD96+AZ96+AV96+AR96+AN96 -> 358488.64
A98: Net Income % of Revenue | E98: =E83/E11 -> 0.094990852 | G98: =G83/G11 -> #DIV/0! | I98: =I83/I11 -> #DIV/0! | K98: =K83/K11 -> #DIV/0! | M98: =M83/M11 -> #DIV/0! | O98: =+O96/O11 -> 0.1073228 | P98: =+P96/P11 -> 0.67257888 | S98: =+S96/S11 -> 0.08306052 | T98: =+T96/T11 -> 0.045237118 | W98: =+W96/W11 -> 0.055807448 | X98: =+X96/X11 -> -0.067633478 | AA98: =+AA96/AA11 -> 0.065972249 | AB98: =+AB96/AB11 -> 0.025007909 | AE98: =AE83/AE11 -> 0.081335416 | AF98: =+AF96/AF11 -> 0.079515896 | AI98: =AI83/AI11 -> 0.068217525 | AJ98: =+AJ96/AJ11 -> 0.085422477 | AM98: =AM83/AM11 -> 0.10512145 | AN98: =+AN96/AN11 -> 0.071281283 | AQ98: =AQ83/AQ11 -> 0.10968784 | AR98: =+AR96/AR11 -> 0.11741276 | AU98: =AU83/AU11 -> 0.093791575 | AV98: =+AV96/AV11 -> 0.054561515 | AY98: =AY83/AY11 -> 0.11888781 | BC98: =BC83/BC11 -> 0.11574865 | BG98: =BG83/BG11 -> 0.11231583 | CG98: =CG83/CG11 -> 0.094985919 | CH98: =+CH96/CH11 -> 0.088366868

Sheet 2024 Bdg vs Actual -OH
P1: Budget Vs Actual | T1: Variance | U1: (Red) | V1: Over budget | X1: Budget Vs Actual
P2: Income Statement - Ohio | U2: Black | V2: Under budget | X2: Income Statement - Ohio
P3: 2024 | X3: 2024
E8: Year 1* | G8: Year 2 * | I8: Year 3* | K8: Year 4 * | M8: Year 5 * | O8: January | S8: Feb | W8: March | AA8: April | AE8: May | AI8: June | AM8: July | AQ8: August | AU8: September | AY8: October | BC8: November | BF8: December | BG8: December | CH8: YTD
A9: Year Ending | E9: 45657 | G9: 46022 | I9: 46387 | K9: 46752 | M9: 47118 | O9: Budget | P9: Actual | Q9: Var | S9: Budget | T9: Actual | U9: Var | V9: Notes | W9: Budget | X9: Actual | Y9: Var $ | Z9: Notes | AA9: Budget | AB9: Actual | AC9: Variance | AD9: Notes | AE9: Budget | AF9: Actual | AG9: Variance | AH9: Notes | AI9: Budget | AJ9: Actual | AK9: Variance | AL9: Notes | AM9: Budget | AN9: Actual | AO9: Variance | AP9: Notes | AQ9: Budget | AR9: Actual | AS9: Variance | AT9: Notes | AU9: Budget | AV9: Actual | AW9: Variance | AX9: Notes | AY9: Budget | AZ9: Actual | BA9: Variance | BB9: Notes | BC9: Budget | BD9: Actual | BE9: Variance | BF9: Notes | BG9: Budget | BH9: Actual | BI9: Variance | BJ9: Notes | CH9: Budget | CI9: Actual | CJ9: Variance
A11: **Gross Sales** | E11: =SUM(E14:E23) -> 8987920.8 | G11: =SUM(G14:G23) -> 9886712.9 | I11: =SUM(I14:I23) -> 10875384 | K11: =SUM(K14:K23) -> 11962923 | M11: =SUM(M14:M23) -> 13159215 | O11: =SUM(O14:O23) -> 720098.87 | P11: =SUM(P14:P23) -> 535453 | Q11: =P11-O11 -> -184645.87 | S11: =SUM(S14:S23) -> 714798 | T11: =SUM(T14:T23) -> 470636 | U11: =T11-S11 -> -244162 | W11: =SUM(W14:W23) -> 725188.44 | X11: =SUM(X14:X23) -> 419392 | Y11: =X11-W11 -> -305796.44 | AA11: =SUM(AA14:AA23) -> 738053.51 | AB11: =SUM(AB14:AB23) -> 792863 | AC11: =AB11-AA11 -> 54809.488 | AE11: =SUM(AE14:AE23) -> 746000 | AF11: =SUM(AF14:AF23) -> 659325 | AG11: =AF11-AE11 -> -86675 | AI11: =SUM(AI14:AI23) -> 739576.88 | AJ11: =SUM(AJ14:AJ23) -> 715011 | AK11: =AJ11-AI11 -> -24565.88 | AM11: =SUM(AM14:AM23) -> 751486.05 | AN11: =SUM(AN14:AN23) -> 1074094 | AO11: =AN11-AM11 -> 322607.95 | AQ11: =SUM(AQ14:AQ23) -> 758847.84 | AR11: =SUM(AR14:AR23) -> 1426155 | AS11: =AR11-AQ11 -> 667307.16 | AU11: =SUM(AU14:AU23) -> 763090.39 | AV11: =SUM(AV14:AV23) -> 467781 | AW11: =AV11-AU11 -> -295309.39 | AY11: =SUM(AY14:AY23) -> 771306.45 | AZ11: =SUM(AZ14:AZ23) -> 606016 | BA11: =AZ11-AY11 -> -165290.45 | BC11: =SUM(BC14:BC23) -> 776109.14 | BD11: =SUM(BD14:BD23) -> 477285 | BE11: =BD11-BC11 -> -298824.14 | BG11: =SUM(BG14:BG23) -> 783365.26 | BH11: =SUM(BH14:BH23) -> 357901 | BI11: =BH11-BG11 -> -425464.26 | CH11: =+W11+S11+O11+AA11+AE11+AI11+AM11+AQ11+AU11+AY11+BC11+BG11 -> 8987920.8 | CI11: =+X11+T11+P11+AB11+AF11+AJ11+AN11+AR11+AV11+AZ11+BD11+BH11 -> 8001912 | CJ11: =CI11-CH11 -> -986008.83
A13: Services
A14: Monthly Recurring Services | D14: New Business + Current Agreements | E14: =O14+S14+W14+AA14+AE14+AI14+AM14+AQ14+AU14+AY14+BC14+BG14 -> 1726677.3 | G14: =E14*1.1 -> 1899345 | I14: =G14*1.1 -> 2089279.5 | K14: =I14*1.1 -> 2298207.5 | M14: =K14*1.1 -> 2528028.2 | O14: 122481.86 | P14: 117508.52 | Q14: =P14-O14 -> -4973.3361 | S14: =108547+10491 -> 119038 | T14: 129675 | U14: =T14-S14 -> 10637 | V14: Par Excellance $3K and St John Nottingham $10K Agreement catch up billing | W14: =125848.89625-2309.1-1000 -> 122539.8 | X14: 127590 | Y14: =X14-W14 -> 5050.2038 | Z14: St Sebstian and St John Nottingaham catch up billing for Feb | AA14: 134156.07 | AB14: 126441 | AC14: =AB14-AA14 -> -7715.0662 | AD14: 2 months credit Franklinton, Westwood Prep did not double as estimated, New Business budgeted at 6,450- only Ummah Center at 1,000 | AE14: 140000 | AF14: 132146 | AG14: =AF14-AE14 -> -7854 | AH14: New Business is budgeted at $12,900- The only new business is Ummah Center $1,000, Year End billing for USAC $4,600 over budget | AI14: 134108.81 | AJ14: 125977 | AK14: =AJ14-AI14 -> -8131.815 | AL14: New Business is budgeted at $19,350- The new business is only 1.5K,- Menlo Park over budget 4.6K(they cancelled 07/01 not 06/01), Imagine Great western 6.4K over budget(they did not cancel)Explorers 1.5 under budget | AM14: 144953.98 | AN14: 95735 | AO14: =AN14-AM14 -> -49218.985 | AP14: New Business is budgeted at $25,800- The new business is only 8.5K,-(Under Budget Imagine Schools -7K, Explorers -1.5, Columbus Prep -3K, Cristo Rey -4.7K, Focus North -3K, Invictus -3K, JWP -2K, River Gate-1.3K) | AQ14: 151265.77 | AR14: 150519 | AS14: =AR14-AQ14 -> -746.77495 | AT14: See additional Breakdown of MSP Billing | AU14: 155025.82 | AV14: 136440 | AW14: =AV14-AU14 -> -18585.825 | AX14: No New Business - See Agreement Revenue Comparison - Sept to Aug 2024 see supplemental report for breakdown | AY14: 162396.88 | AZ14: 120672 | BA14: =AZ14-AY14 -> -41724.885 | BB14: No New Business - See Agreement Revenue Comparison - Sept to Aug 2024 see supplemental report for breakdown | BC14: 167252.07 | BD14: 137388 | BE14: =BD14-BC14 -> -29864.075 | BF14: No New Business - See Agreement Revenue Comparison - Sept to Aug 2024 see supplemental report for breakdown | BG14: 173458.19 | BH14: 140107 | BI14: =BH14-BG14 -> -33351.195 | BJ14: No New Business - See Agreement Revenue Comparison - Sept to Aug 2024 see supplemental report for breakdown | BL14: {=ROUND(O14:BG14, -2)} -> #VALUE! | CH14: =+W14+S14+O14+AA14+AE14+AI14+AM14+AQ14+AU14+AY14+BC14+BG14 -> 1726677.3 | CI14: =+X14+T14+P14+AB14+AF14+AJ14+AN14+AR14+AV14+AZ14+BD14+BH14 -> 1540198.5 | CJ14: =CI14-CH14 -> -186478.75
A15: Monthly Recurring Private Cloud | D15: New Business + Current Agreements | E15: =O15+S15+W15+AA15+AE15+AI15+AM15+AQ15+AU15+AY15+BC15+BG15 -> 0 | G15: =E15*1.1 -> 0 | I15: =G15*1.1 -> 0 | K15: =I15*1.1 -> 0 | M15: =K15*1.1 -> 0 | O15: 0 | P15: 0 | Q15: =P15-O15 -> 0 | S15: 0 | U15: =T15-S15 -> 0 | W15: 0 | X15: 0 | Y15: =X15-W15 -> 0 | AA15: 0 | AB15: 0 | AC15: =AB15-AA15 -> 0 | AE15: 0 | AG15: =AF15-AE15 -> 0 | AI15: 0 | AJ15: 0 | AK15: =AJ15-AI15 -> 0 | AM15: 0 | AO15: =AN15-AM15 -> 0 | AQ15: 0 | AS15: =AR15-AQ15 -> 0 | AU15: 0 | AW15: =AV15-AU15 -> 0 | AY15: 0 | BA15: =AZ15-AY15 -> 0 | BC15: 0 | BD15: 0 | BE15: =BD15-BC15 -> 0 | BG15: 0 | BH15: 0 | BI15: =BH15-BG15 -> 0 | BL15: {=ROUND(O15:BG15, -2)} -> #VALUE! | CH15: =+W15+S15+O15+AA15+AE15+AI15+AM15+AQ15+AU15+AY15+BC15+BG15 -> 0 | CI15: =+X15+T15+P15+AB15+AF15+AJ15+AN15+AR15+AV15+AZ15+BD15+BH15 -> 0 | CJ15: =CI15-CH15 -> 0
A16: Monthly Recurring Resale | D16: New Business + Current Agreements | E16: =O16+S16+W16+AA16+AE16+AI16+AM16+AQ16+AU16+AY16+BC16+BG16 -> 328023.56 | G16: =E16*1.1 -> 360825.92 | I16: =G16*1.1 -> 396908.51 | K16: =I16*1.1 -> 436599.36 | M16: =K16*1.1 -> 480259.29 | O16: 19617.015 | P16: 27044.14 | Q16: =P16-O16 -> 7427.1251 | S16: 20540 | T16: 23354 | U16: =T16-S16 -> 2814 | V16: Par Excellence $3K and St John Nottingham $10K Agreement catch up billing | W16: =21339.6461+2309+1000 -> 24648.646 | X16: 24694 | Y16: =X16-W16 -> 45.3539 | Z16: updated budget for Sherer hospital & Par excellence | AA16: 25897.446 | AB16: 23511 | AC16: =AB16-AA16 -> -2386.4461 | AD16: New Business budgeted at $1050.00 no new business, East muskingum correction | AE16: 28000 | AF16: 23020 | AG16: =AF16-AE16 -> -4980 | AH16: New Business is Budgeted at $2,100- New business is only $220- Difference of $1,900, Imagine Schools $1K under budget, Westwood Prep $800 under budget, St Sebastions $600 under budget | AI16: 27468.065 | AJ16: 23576 | AK16: =AJ16-AI16 -> -3892.0646 | AL16: New Business is budgeted at 3.1K, New business is only $220, North Shore is 500 under, Westwood Prep 800 under | AM16: 28532.065 | AN16: 21571 | AO16: =AN16-AM16 -> -6961.0646 | AP16: New Business is budgeted at 4.2K, New business is only 2.4K,(Under Budget- Imagine Schools -3.1K, North Shore - 650, Westwood Prep -650) | AQ16: 29582.065 | AR16: 22314 | AS16: =AR16-AQ16 -> -7268.0646 | AT16: New Business is 6.6K under budget | AU16: 30064.565 | AV16: 20161 | AW16: =AV16-AU16 -> -9903.5646 | AY16: 30909.565 | AZ16: 22270 | BA16: =AZ16-AY16 -> -8639.5646 | BC16: 30857.065 | BD16: 26826 | BE16: =BD16-BC16 -> -4031.0646 | BG16: 31907.065 | BH16: 23774 | BI16: =BH16-BG16 -> -8133.0646 | BL16: {=ROUND(O16:BG16, -2)} -> #VALUE! | CH16: =+W16+S16+O16+AA16+AE16+AI16+AM16+AQ16+AU16+AY16+BC16+BG16 -> 328023.56 | CI16: =+X16+T16+P16+AB16+AF16+AJ16+AN16+AR16+AV16+AZ16+BD16+BH16 -> 282115.14 | CJ16: =CI16-CH16 -> -45908.419
A17: IT Project Services | D17: New Business | E17: =O17+S17+W17+AA17+AE17+AI17+AM17+AQ17+AU17+AY17+BC17+BG17 -> 828330 | G17: =E17*1.1 -> 911163 | I17: =G17*1.1 -> 1002279.3 | K17: =I17*1.1 -> 1102507.2 | M17: =K17*1.1 -> 1212758 | O17: 69030 | P17: 20537.34 | Q17: =P17-O17 -> -48492.66 | S17: 69000 | T17: 42376 | U17: =T17-S17 -> -26624 | W17: 69030 | X17: 41063 | Y17: =X17-W17 -> -27967 | AA17: 69030 | AB17: 54683 | AC17: =AB17-AA17 -> -14347 | AE17: 69030 | AF17: 25568 | AG17: =AF17-AE17 -> -43462 | AI17: 69030 | AJ17: 76958 | AK17: =AJ17-AI17 -> 7928 | AL17: West Liberty Project $39K | AM17: 69030 | AN17: 166607 | AO17: =AN17-AM17 -> 97577 | AP17: Marysville Project, Imagine Great Western | AQ17: 69030 | AR17: 172309 | AS17: =AR17-AQ17 -> 103279 | AT17: Marysville 25K, West Liberty 22K, Triad 17K, Imagine Great Western 12K, Tolles 12K | AU17: 69030 | AV17: 66035 | AW17: So | AX17: See Breakdown in Project and Product Sales Sept 2024 for details | AY17: 69030 | AZ17: 49048 | BA17: =AZ17-AY17 -> -19982 | BB17: See Breakdown in Project and Product Sales Sept 2024 for details | BC17: 69030 | BD17: 15332 | BE17: =BD17-BC17 -> -53698 | BF17: See Breakdown in Project and Product Sales Sept 2024 for details | BG17: 69030 | BH17: 6063 | BI17: =BH17-BG17 -> -62967 | BL17: {=ROUND(O17:BG17, -2)} -> #VALUE! | CH17: =+W17+S17+O17+AA17+AE17+AI17+AM17+AQ17+AU17+AY17+BC17+BG17 -> 828330 | CI17: =+X17+T17+P17+AB17+AF17+AJ17+AN17+AR17+AV17+AZ17+BD17+BH17 -> 736579.34 | CJ17: =CI17-CH17 -> -91750.66
A18: Subcontracted Services | D18: New Business | E18: =O18+S18+W18+AA18+AE18+AI18+AM18+AQ18+AU18+AY18+BC18+BG18 -> 0 | G18: =E18*1.1 -> 0 | I18: =G18*1.1 -> 0 | K18: =I18*1.1 -> 0 | M18: =K18*1.1 -> 0 | O18: 0 | P18: 600 | Q18: =P18-O18 -> 600 | S18: 0 | T18: 3192 | U18: =T18-S18 -> 3192 | W18: 0 | X18: 249 | Y18: =X18-W18 -> 249 | AA18: 0 | AC18: =AB18-AA18 -> 0 | AE18: 0 | AF18: 0 | AG18: =AF18-AE18 -> 0 | AI18: 0 | AJ18: 14075 | AK18: =AJ18-AI18 -> 14075 | AM18: 0 | AN18: 280863 | AO18: =AN18-AM18 -> 280863 | AP18: Marysville Project | AQ18: 0 | AR18: 22975 | AS18: =AR18-AQ18 -> 22975 | AT18: Imagine Great Western | AU18: 0 | AW18: =AV18-AU18 -> 0 | AY18: 0 | BA18: =AZ18-AY18 -> 0 | BC18: 0 | BD18: 0 | BE18: =BD18-BC18 -> 0 | BG18: 0 | BH18: 0 | BI18: =BH18-BG18 -> 0 | BL18: {=ROUND(O18:BG18, -2)} -> #VALUE! | CH18: =+W18+S18+O18+AA18+AE18+AI18+AM18+AQ18+AU18+AY18+BC18+BG18 -> 0 | CI18: =+X18+T18+P18+AB18+AF18+AJ18+AN18+AR18+AV18+AZ18+BD18+BH18 -> 321954 | CJ18: =CI18-CH18 -> 321954
A21: Product Sales
A22: Product Resale | D22: New Business | E22: =O22+S22+W22+AA22+AE22+AI22+AM22+AQ22+AU22+AY22+BC22+BG22 -> 6074640 | G22: =E22*1.1 -> 6682104 | I22: =G22*1.1 -> 7350314.4 | K22: =I22*1.1 -> 8085345.8 | M22: =K22*1.1 -> 8893880.4 | O22: 506220 | P22: 369763 | Q22: =P22-O22 -> -136457 | S22: 506220 | T22: 272039 | U22: =T22-S22 -> -234181 | W22: 506220 | X22: 225219 | Y22: =X22-W22 -> -281001 | AA22: 506220 | AB22: 588228 | AC22: =AB22-AA22 -> 82008 | AD22: Miami East chromebooks, Scheurer Hospital, VitalCare | AE22: 506220 | AF22: 474112 | AG22: =AF22-AE22 -> -32108 | AI22: 506220 | AJ22: 469774 | AK22: =AJ22-AI22 -> -36446 | AM22: 506220 | AN22: 509318 | AO22: =AN22-AM22 -> 3098 | AQ22: 506220 | AR22: 1058038 | AS22: =AR22-AQ22 -> 551818 | AT22: Triad 150K, Tolles 134K,East Guernsey 80K, Imagine Great Wester 61K, Mid-East55K, North Shore 50K, Arts & College Prep 48K | AU22: 506220 | AV22: 245145 | AW22: =AV22-AU22 -> -261075 | AX22: See Breakdown in Project and Product Sales Sept 2024 for details | AY22: 506220 | AZ22: 414026 | BA22: =AZ22-AY22 -> -92194 | BB22: See Breakdown in Project and Product Sales Sept 2024 for details | BC22: 506220 | BD22: 296878 | BE22: =BD22-BC22 -> -209342 | BF22: See Breakdown in Project and Product Sales Sept 2024 for details | BG22: 506220 | BH22: 167033 | BI22: =BH22-BG22 -> -339187 | BL22: {=ROUND(O22:BG22, -2)} -> #VALUE! | CH22: =+W22+S22+O22+AA22+AE22+AI22+AM22+AQ22+AU22+AY22+BC22+BG22 -> 6074640 | CI22: =+X22+T22+P22+AB22+AF22+AJ22+AN22+AR22+AV22+AZ22+BD22+BH22 -> 5089573 | CJ22: =CI22-CH22 -> -985067
A23: Other Revenue | E23: =O23+S23+W23+AA23+AE23+AI23+AM23+AQ23+AU23+AY23+BC23+BG23 -> 30250 | G23: =E23*1.1 -> 33275 | I23: =G23*1.1 -> 36602.5 | K23: =I23*1.1 -> 40262.75 | M23: =K23*1.1 -> 44289.025 | O23: =33000/12 -> 2750 | P23: 0 | Q23: =P23-O23 -> -2750 | S23: 0 | T23: 0 | U23: =T23-S23 -> 0 | W23: 2750 | X23: 577 | Y23: =X23-W23 -> -2173 | AA23: 2750 | AB23: 0 | AC23: =AB23-AA23 -> -2750 | AE23: 2750 | AF23: 4479 | AG23: =AF23-AE23 -> 1729 | AI23: 2750 | AJ23: 4651 | AK23: =AJ23-AI23 -> 1901 | AM23: 2750 | AN23: 0 | AO23: =AN23-AM23 -> -2750 | AQ23: 2750 | AR23: 0 | AS23: =AR23-AQ23 -> -2750 | AU23: 2750 | AV23: 0 | AW23: =AV23-AU23 -> -2750 | AY23: 2750 | AZ23: 0 | BA23: =AZ23-AY23 -> -2750 | BC23: 2750 | BD23: 861 | BE23: =BD23-BC23 -> -1889 | BG23: 2750 | BH23: 20924 | BI23: =BH23-BG23 -> 18174 | BL23: {=ROUND(O23:BG23, -2)} -> #VALUE! | CH23: =+W23+S23+O23+AA23+AE23+AI23+AM23+AQ23+AU23+AY23+BC23+BG23 -> 30250 | CI23: =+X23+T23+P23+AB23+AF23+AJ23+AN23+AR23+AV23+AZ23+BD23+BH23 -> 31492 | CJ23: =CI23-CH23 -> 1242
A25: Cost of Services- **
A26: Costs of Monthly Recurring Services | E26: =O26+S26+W26+AA26+AE26+AI26+AM26+AQ26+AU26+AY26+BC26+BG26 -> 57300 | G26: =G14*0.033 -> 62678.385 | I26: =I14*0.033 -> 68946.224 | K26: =K14*0.033 -> 75840.846 | M26: =M14*0.033 -> 83424.93 | O26: =ROUND(O14*0.033, -2) -> 4000 | P26: 5507 | Q26: =O26-P26 -> -1507 | S26: 4200 | T26: 5813 | U26: =S26-T26 -> -1613 | W26: 4200 | X26: 5254 | Y26: =W26-X26 -> -1054 | AA26: =ROUND(AA14*0.033, -2) -> 4400 | AB26: 5255 | AC26: =AA26-AB26 -> -855 | AE26: =ROUND(AE14*0.033, -2) -> 4600 | AF26: 5298 | AG26: =AE26-AF26 -> -698 | AI26: =ROUND(AI14*0.033, -2) -> 4400 | AJ26: 5368 | AK26: =AI26-AJ26 -> -968 | AM26: =ROUND(AM14*0.033, -2) -> 4800 | AN26: 4557 | AO26: =AM26-AN26 -> 243 | AQ26: =ROUND(AQ14*0.033, -2) -> 5000 | AR26: 4537 | AS26: =AQ26-AR26 -> 463 | AU26: =ROUND(AU14*0.033, -2) -> 5100 | AV26: 5783 | AW26: =AU26-AV26 -> -683 | AY26: =ROUND(AY14*0.033, -2) -> 5400 | AZ26: 2496 | BA26: =AY26-AZ26 -> 2904 | BC26: =ROUND(BC14*0.033, -2) -> 5500 | BD26: 6054 | BE26: =BC26-BD26 -> -554 | BG26: =ROUND(BG14*0.033, -2) -> 5700 | BH26: 5840 | BI26: =BG26-BH26 -> -140 | BL26: {=ROUND(O26:BG26, -2)} -> #VALUE! | CH26: =+W26+S26+O26+AA26+AE26+AI26+AM26+AQ26+AU26+AY26+BC26+BG26 -> 57300 | CI26: =+X26+T26+P26+AB26+AF26+AJ26+AN26+AR26+AV26+AZ26+BD26+BH26 -> 61762 | CJ26: =CH26-CI26 -> -4462
A27: Costs of Recur Private Cloud | E27: =O27+S27+W27+AA27+AE27+AI27+AM27+AQ27+AU27+AY27+BC27+BG27 -> 0 | G27: =G15*0.678 -> 0 | I27: =I15*0.678 -> 0 | K27: =K15*0.678 -> 0 | M27: =M15*0.678 -> 0 | P27: 0 | Q27: =O27-P27 -> 0 | S27: 0 | T27: 0 | U27: =S27-T27 -> 0 | X27: 0 | Y27: =W27-X27 -> 0 | AB27: 0 | AC27: =AA27-AB27 -> 0 | AF27: 0 | AG27: =AE27-AF27 -> 0 | AJ27: 0 | AK27: =AI27-AJ27 -> 0 | AO27: =AM27-AN27 -> 0 | AS27: =AQ27-AR27 -> 0 | AW27: =AU27-AV27 -> 0 | BA27: =AY27-AZ27 -> 0 | BD27: 0 | BE27: =BC27-BD27 -> 0 | BH27: 0 | BI27: =BG27-BH27 -> 0 | BL27: {=ROUND(O27:BG27, -2)} -> #VALUE! | CH27: =+W27+S27+O27+AA27+AE27+AI27+AM27+AQ27+AU27+AY27+BC27+BG27 -> 0 | CI27: =+X27+T27+P27+AB27+AF27+AJ27+AN27+AR27+AV27+AZ27+BD27+BH27 -> 0 | CJ27: =CH27-CI27 -> 0
