Workbook
Name NB_Monthly_Recurring_Private_Cloud_CA: #REF!
Name NB_Monthly_Recurring_Private_Cloud_OH: #REF!
Name NB_Monthly_Recurring_Resale_CA: #REF!
Name NB_Monthly_Recurring_Resale_OH: #REF!
Name NB_Monthly_Recurring_Services_CA: #REF!
Name NB_Monthly_Recurring_Services_OH: #REF!
Name WA_Monthly_Recurring_Private_Cloud_CA: #REF!
Name WA_Monthly_Recurring_Private_Cloud_CA: #REF!
Name WA_Monthly_Recurring_Resale_CA: #REF!
Name WA_Monthly_Recurring_Resale_CA: #REF!
Name WA_Monthly_Recurring_Resale_OH: #REF!
Name WA_Monthly_Recurring_Services_CA: #REF!
Name WA_Monthly_Recurring_Services_CA: #REF!
Name WA_Monthly_Recurring_Services_OH: #REF!

Sheet P&L MTD with Previous Month Com
A1: Datapath | I1: *Need to get figures in separate tabs
A2: P&L MTD with Previous Month Comparison
A3: Reporting Book: | C3: ACCRUAL
A4: As of Date: | C4: 10/31/2025
A5: Location group: | C5: Modesto Fresno Ohio
P6: Actual Billings/In Period Receipts Posted
C7: DP California | D7: DP California | F7: DP Ohio | G7: DP Ohio | I7: Data Path - All Locations | J7: Data Path - All Locations | L7: DP California | M7: DP Ohio | N7: Data Path - All Locations | P7: DP California | R7: DP Ohio
C8: Month Ending | D8: Month Ending | F8: Month Ending | G8: Month Ending | I8: Month Ending | J8: Month Ending | L8: Year To Date | M8: Year To Date | N8: Year To Date | P8: Month Ending | R8: Month Ending
C9: 10/31/2025 | D9: 09/30/2025 | F9: 10/31/2025 | G9: 09/30/2025 | I9: 10/31/2025 | J9: 09/30/2025 | L9: 10/31/2025 | M9: 10/31/2025 | N9: 10/31/2025 | P9: 10/31/2025 | Q9: vs. Accrual | R9: 10/31/2025 | S9: vs. Accrual | T9: Notes
D10: Actual | E10: Variance | F10: Actual | G10: Actual | H10: Variance | I10: Actual | J10: Actual | K10: Variance | L10: Actual | M10: Actual | N10: Actual
A11: Net Income- With DL above the line | B11: Net | U11: =I11
A12: Operating Net Income- DL above the line | B12: Operating | U12: =I12
A13: Gross Profit with Direct Labor | B13: Gross | U13: =I13
A14: Revenue | B14: Revenue | U14: =I14
A15: Monthly Recurring Services | B15: Monthly | U15: =I15
A16: 40000 - Managed IT Revenue | B16: 40000 | C16: 456302 | D16: 424153 | E16: 32149 | F16: 92188 | G16: 91841 | H16: 347 | I16: 548490 | J16: 515994 | K16: 32496 | L16: 4326264 | M16: 979344 | N16: 5305607 | O16: CA: Irvine pickup from Sept. (No reversal in August performed). This is for billings but not yet earned. | P16: =IFERROR(-VLOOKUP(B16,'Actual Billings'!$A$8:$C$26,3,FALSE),0) -> 458920.03 | Q16: =C16-P16 -> -2618.03 | R16: =IFERROR(-VLOOKUP(B16,'Actual Billings'!$H$8:$J$24,3,FALSE),0) -> 92188.25 | S16: =F16-R16 -> -0.25 | U16: 548490 | V16: =U16-I16 -> 0
A17: 40100 - Managed Security Revenue | B17: 40100 | C17: 4729 | D17: 5055 | E17: -326 | F17: 0 | G17: 0 | H17: 0 | I17: 4729 | J17: 5056 | K17: -326 | L17: 68993 | M17: 0 | N17: 68993 | P17: =IFERROR(-VLOOKUP(B17,'Actual Billings'!$A$8:$C$17,3,FALSE),0) -> 5055.45 | Q17: =C17-P17 -> -326.45 | R17: =IFERROR(-VLOOKUP(B17,'Actual Billings'!$H$8:$J$24,3,FALSE),0) -> 0 | S17: =F17-R17 -> 0 | U17: 4729 | V17: =U17-I17 -> 0
A18: 40200 - Managed Voice Revenue | B18: 40200 | C18: 2826 | D18: 2953 | E18: -126 | F18: 5580 | G18: 5581 | H18: 0 | I18: 8407 | J18: 8532 | K18: -126 | L18: 41808 | M18: 61056 | N18: 102865 | P18: =IFERROR(-VLOOKUP(B18,'Actual Billings'!$A$8:$C$17,3,FALSE),0) -> 2826.33 | Q18: =C18-P18 -> -0.33 | R18: =IFERROR(-VLOOKUP(B18,'Actual Billings'!$H$8:$J$24,3,FALSE),0) -> 5580.2 | S18: =F18-R18 -> -0.2 | U18: 8407 | V18: =U18-I18 -> 0
A19: 41320 - Managed Back up Revenue | B19: 41320 | C19: 8758 | D19: 8987 | E19: -230 | F19: 2800 | G19: 2734 | H19: 65 | I19: 11556 | J19: 11722 | K19: -165 | L19: 91653 | M19: 31748 | N19: 123401 | P19: =IFERROR(-VLOOKUP(B19,'Actual Billings'!$A$8:$C$17,3,FALSE),0) -> 8757.36 | Q19: =C19-P19 -> 0.64 | R19: =IFERROR(-VLOOKUP(B19,'Actual Billings'!$H$8:$J$24,3,FALSE),0) -> 2799.25 | S19: =F19-R19 -> 0.75 | U19: 11556 | V19: =U19-I19 -> 0
A20: 41925 - USAC ERATE BM Revenue | B20: 41925 | C20: 0 | D20: 0 | E20: 0 | F20: 5774 | G20: 5913 | H20: -140 | I20: 5774 | J20: 5913 | K20: -140 | L20: 0 | M20: 84373 | N20: 84373 | P20: =IFERROR(-VLOOKUP(B20,'Actual Billings'!$A$8:$C$17,3,FALSE),0) -> 0 | Q20: =C20-P20 -> 0 | R20: =IFERROR(-VLOOKUP(B20,'Actual Billings'!$H$8:$J$24,3,FALSE),0) -> 5773.93 | S20: =F20-R20 -> 0.07 | U20: 5774 | V20: =U20-I20 -> 0
A21: Monthly Recurring Services | B21: Monthly | C21: 472615 | D21: 441148 | E21: 31467 | F21: 106342 | G21: 106069 | H21: 272 | I21: 578956 | J21: 547217 | K21: 31739 | L21: 4528718 | M21: 1156521 | N21: 5685239 | U21: 578956 | V21: =U21-I21 -> 0
A22: Monthly Recurring Private Cloud | B22: Monthly | V22: =U22-I22 -> #VALUE!
A23: 41360 - Public Cloud Revenue | B23: 41360 | C23: 1144 | D23: 1144 | E23: 0 | F23: 0 | G23: 0 | H23: 0 | I23: 1144 | J23: 1144 | K23: 0 | L23: 11440 | M23: 0 | N23: 11440 | P23: =IFERROR(-VLOOKUP(B23,'Actual Billings'!$A$8:$C$26,3,FALSE),0) -> 1144 | Q23: =C23-P23 -> 0 | R23: =IFERROR(-VLOOKUP(B23,'Actual Billings'!$H$8:$J$24,3,FALSE),0) -> 0 | S23: =F23-R23 -> 0 | U23: 1144 | V23: =U23-I23 -> 0
A24: 41365 - Private Cloud Revenue | B24: 41365 | C24: 25853 | D24: 20457 | E24: 5396 | F24: 0 | G24: 0 | H24: 0 | I24: 25853 | J24: 20457 | K24: 5396 | L24: 227591 | M24: 0 | N24: 227591 | O24: CA: Irvine pickup from Sept. (No reversal in August performed). This is for billings but not yet earned. | P24: =IFERROR(-VLOOKUP(B24,'Actual Billings'!$A$8:$C$26,3,FALSE),0) -> 25853.05 | Q24: =C24-P24 -> -0.05 | R24: =IFERROR(-VLOOKUP(B24,'Actual Billings'!$H$8:$J$24,3,FALSE),0) -> 0 | S24: =F24-R24 -> 0 | U24: 25853 | V24: =U24-I24 -> 0
A25: Monthly Recurring Private Cloud | B25: Monthly | C25: 26997 | D25: 21601 | E25: 5396 | F25: 0 | G25: 0 | H25: 0 | I25: 26997 | J25: 21601 | K25: 5396 | L25: 239031 | M25: 0 | N25: 239031 | U25: 26997 | V25: =U25-I25 -> 0
A26: Monthly Recurring Resale | B26: Monthly | V26: =U26-I26 -> #VALUE!
A27: 41200 - HaaS Revenue | B27: 41200 | C27: 26074 | D27: 20854 | E27: 5220 | F27: 315 | G27: 0 | H27: 315 | I27: 26390 | J27: 20854 | K27: 5536 | L27: 247116 | M27: 315 | N27: 247431 | O27: CA: Irvine pickup from Sept. (No reversal in August performed). This is for billings but not yet earned. | P27: =IFERROR(-VLOOKUP(B27,'Actual Billings'!$A$8:$C$26,3,FALSE),0) -> 26310.81 | Q27: =C27-P27 -> -236.81 | R27: =IFERROR(-VLOOKUP(B27,'Actual Billings'!$H$8:$J$24,3,FALSE),0) -> 315 | S27: =F27-R27 -> 0 | T27: Delta of zero because recurring reversal amount = same for Sept, Oct. Sept = artificially low. | U27: 26390 | V27: =U27-I27 -> 0
A28: 41250 - Chromebook ADP Revenue | B28: 41250 | C28: 0 | D28: 0 | E28: 0 | F28: 562 | G28: 563 | H28: 0 | I28: 562 | J28: 563 | K28: 0 | L28: 0 | M28: 5625 | N28: 5625 | P28: =IFERROR(-VLOOKUP(B28,'Actual Billings'!$A$8:$C$26,3,FALSE),0) -> 0 | Q28: =C28-P28 -> 0 | R28: =IFERROR(-VLOOKUP(B28,'Actual Billings'!$H$8:$J$24,3,FALSE),0) -> 562.5 | S28: =F28-R28 -> -0.5 | U28: 562 | V28: =U28-I28 -> 0
A29: 41300 - Cloud SAAS Revenue | B29: 41300 | C29: 49508 | D29: 43551 | E29: 5957 | F29: 2011 | G29: 2065 | H29: -54 | I29: 51519 | J29: 45616 | K29: 5902 | L29: 414124 | M29: 29568 | N29: 443692 | O29: CA: Irvine pickup from Sept. (No reversal in August performed). This is for billings but not yet earned. | P29: =IFERROR(-VLOOKUP(B29,'Actual Billings'!$A$8:$C$26,3,FALSE),0) -> 49744.37 | Q29: =C29-P29 -> -236.37 | R29: =IFERROR(-VLOOKUP(B29,'Actual Billings'!$H$8:$J$24,3,FALSE),0) -> 2010.85 | S29: =F29-R29 -> 0.15 | U29: 51519 | V29: =U29-I29 -> 0
A30: 41350 - Managed Spam Filtering Revenue | B30: 41350 | C30: 899 | D30: 954 | E30: -56 | F30: 0 | G30: 0 | H30: 0 | I30: 899 | J30: 954 | K30: -55 | L30: 9128 | M30: 0 | N30: 9127 | P30: =IFERROR(-VLOOKUP(B30,'Actual Billings'!$A$8:$C$26,3,FALSE),0) -> 898.87 | Q30: =C30-P30 -> 0.13 | R30: =IFERROR(-VLOOKUP(B30,'Actual Billings'!$H$8:$J$24,3,FALSE),0) -> 0 | S30: =F30-R30 -> 0 | U30: 899 | V30: =U30-I30 -> 0
A31: 41450 - Microsoft 365 Revenue | B31: 41450 | C31: 121163 | D31: 80884 | E31: 40279 | F31: 1377 | G31: 1311 | H31: 67 | I31: 122540 | J31: 82195 | K31: 40345 | L31: 893072 | M31: 12306 | N31: 905379 | O31: CA: Increase is primarily the result of a new 365 agreement for 24 Hour Home Care, $31k, as well as $11k Irvine pickup from Sept. (No reversal in August performed). This is for billings but not yet earned. | P31: =IFERROR(-VLOOKUP(B31,'Actual Billings'!$A$8:$C$26,3,FALSE),0) -> 121329.87 | Q31: =C31-P31 -> -166.87 | R31: =IFERROR(-VLOOKUP(B31,'Actual Billings'!$H$8:$J$24,3,FALSE),0) -> 1377.37 | S31: =F31-R31 -> -0.37 | T31: 24 hour | U31: 122540 | V31: =U31-I31 -> 0
A32: 42100 - Security Resale Revenue | B32: 42100 | C32: 134500 | D32: 129956 | E32: 4544 | F32: 14214 | G32: 13409 | H32: 805 | I32: 148714 | J32: 143365 | K32: 5349 | L32: 1113719 | M32: 119114 | N32: 1232833 | O32: CA: Irvine pickup from Sept. (No reversal in August performed). This is for billings but not yet earned. | P32: =IFERROR(-VLOOKUP(B32,'Actual Billings'!$A$8:$C$26,3,FALSE),0) -> 135011.8 | Q32: =C32-P32 -> -511.8 | R32: =IFERROR(-VLOOKUP(B32,'Actual Billings'!$H$8:$J$24,3,FALSE),0) -> 14214.1 | S32: =F32-R32 -> -0.1 | T32: 149216 | U32: 148714 | V32: =U32-I32 -> 0
A33: 42200 - Tool Resale Revenue | B33: 42200 | C33: 1898 | D33: 1898 | E33: 0 | F33: 1719 | G33: 1718 | H33: 0 | I33: 3616 | J33: 3616 | K33: 0 | L33: 19291 | M33: 21465 | N33: 40756 | P33: =IFERROR(-VLOOKUP(B33,'Actual Billings'!$A$8:$C$26,3,FALSE),0) -> 1898.23 | Q33: =C33-P33 -> -0.23 | R33: =IFERROR(-VLOOKUP(B33,'Actual Billings'!$H$8:$J$24,3,FALSE),0) -> 1718.1 | S33: =F33-R33 -> 0.9 | T33: 3616 | U33: 3616 | V33: =U33-I33 -> 0
A34: 42300 - Voice Resale Revenue | B34: 42300 | C34: 1792 | D34: 1792 | E34: 0 | F34: 754 | G34: 754 | H34: 0 | I34: 2546 | J34: 2546 | K34: 0 | L34: 16127 | M34: 5468 | N34: 21594 | P34: =IFERROR(-VLOOKUP(B34,'Actual Billings'!$A$8:$C$26,3,FALSE),0) -> 1791.81 | Q34: =C34-P34 -> 0.19 | R34: =IFERROR(-VLOOKUP(B34,'Actual Billings'!$H$8:$J$24,3,FALSE),0) -> 754 | S34: =F34-R34 -> 0 | T34: 2546 | U34: 2546 | V34: =U34-I34 -> 0
A35: Monthly Recurring Resale | B35: Monthly | C35: 335834 | D35: 279889 | E35: 55944 | F35: 20952 | G35: 19820 | H35: 1133 | I35: 356786 | J35: 299709 | K35: 57077 | L35: 2712577 | M35: 193861 | N35: 2906437 | T35: 357732 | U35: 356786 | V35: =U35-I35 -> 0
A36: Project Services | B36: Project | V36: =U36-I36 -> #VALUE!
A37: 41500 - Project Service Revenue | B37: 41500 | C37: 51320 | D37: 24527 | E37: 26794 | F37: 16234 | G37: 21545 | H37: -5311 | I37: 67554 | J37: 46071 | K37: 21483 | L37: 511189 | M37: 277231 | N37: 788421 | O37: CA: Increase primarily driven by the following: $11.2k Sconsa Candy -Storage Refresh project in October, no projects in September $7.4k Graceada Ptnrs. -2 projects closed in October -Enforce 2FA and Password Management Solutions no projects in September $6.4k DiMare-Site Moved completed in October, no projects in September - put on hold couple times by customer $6.2k Oliveira Wealth-Workstation Configuration & Set up project in October, no projects in September $4k Cranbrook Group-Oakland Server Restoration & SharePoint Migration project in October, no projects in September Partially offset by: ($11k) decrease City of Firebaugh-Switching Refresh project in September , no projects in October OH: Decrease primarily driven by the following: $11k Vital Care, USAC, River Gate HS, partially offset by ($5.9k) Imagine Great Western-no October business. | P37: =IFERROR(-VLOOKUP(B37,'Actual Billings'!$A$8:$C$26,3,FALSE),0) -> 46520 | Q37: =C37-P37 -> 4800 | R37: =IFERROR(-VLOOKUP(B37,'Actual Billings'!$H$8:$J$24,3,FALSE),0) -> 22171 | S37: =F37-R37 -> -5937 | T37: Also bring in Customer level variance analysis tab | U37: 67554 | V37: =U37-I37 -> 0
A38: Revenue - Project Services | B38: Revenue | C38: 51320 | D38: 24527 | E38: 26794 | F38: 16234 | G38: 21545 | H38: -5311 | I38: 67554 | J38: 46071 | K38: 21483 | L38: 511189 | M38: 277231 | N38: 788421 | U38: 67554 | V38: =U38-I38 -> 0
A39: Subcontracted Services | B39: Subcontracted | V39: =U39-I39 -> #VALUE!
A40: 41700 - Subcontracted Service Revenue | B40: 41700 | C40: 10863 | D40: 7030 | E40: 3832 | F40: 9125 | G40: 7449 | H40: 1677 | I40: 19989 | J40: 14480 | K40: 5509 | L40: 251649 | M40: 50731 | N40: 302380 | O40: See tab 41700-50500 | P40: =IFERROR(-VLOOKUP(B40,'Actual Billings'!$A$8:$C$26,3,FALSE),0) -> 10863.16 | Q40: =C40-P40 -> -0.16 | R40: =IFERROR(-VLOOKUP(B40,'Actual Billings'!$H$8:$J$24,3,FALSE),0) -> 9125.8 | S40: =F40-R40 -> -0.8 | U40: 19989 | V40: =U40-I40 -> 0
A41: Subcontracted Services | B41: Subcontracted | C41: 10863 | D41: 7030 | E41: 3832 | F41: 9125 | G41: 7449 | H41: 1677 | I41: 19989 | J41: 14480 | K41: 5509 | L41: 251649 | M41: 50731 | N41: 302380 | U41: 19989 | V41: =U41-I41 -> 0
A42: Product Sales | B42: Product | V42: =U42-I42 -> #VALUE!
A43: 42000 - Product Sales Revenue | B43: 42000 | C43: 206648 | D43: 112605 | E43: 94044 | F43: 360317 | G43: 243695 | H43: 116621 | I43: 566965 | J43: 356300 | K43: 210665 | L43: 2089246 | M43: 3110896 | N43: 5200143 | O43: CA: Increase of $137k from Sept - October primarily the result of SO's closed in October for customers: River Delta, Valley Iron, Stewart & Jasper, Lucia Mar SD, City of Atwater, Stanislaus SD, partially offset by a reduction in product rev of ($51k) for Newman-Crows, and City of Clovis. OH: Increase of $257k from Sept - October primarily the result of Aug NRR reversal and SO's closed in October for Hopebridge Autism Therapy Centers, River Gate HS, St Johns Jesuit High School, North Shore High School, Imagine Klepinger Rd, Imagine Pediatrics, Millennium Comm School, partially offset by a reduction in product rev of ($38k) for Scheurer Health and St. John 23rd SD. | P43: =IFERROR(-VLOOKUP(B43,'Actual Billings'!$A$8:$C$26,3,FALSE),0) -> 193347.56 | Q43: =C43-P43 -> 13300.44 | R43: =IFERROR(-VLOOKUP(B43,'Actual Billings'!$H$8:$J$24,3,FALSE),0) -> 441630.42 | S43: =F43-R43 -> -81313.42 | U43: 566965 | V43: =U43-I43 -> 0
A44: 44000 - Freight and Shipping Revenue | B44: 44000 | C44: 512 | D44: 249 | E44: 263 | F44: 11336 | G44: 7520 | H44: 3815 | I44: 11848 | J44: 7770 | K44: 4078 | L44: 8365 | M44: 95844 | N44: 104209 | P44: =IFERROR(-VLOOKUP(B44,'Actual Billings'!$A$8:$C$26,3,FALSE),0) -> 551.15 | Q44: =C44-P44 -> -39.15 | R44: =IFERROR(-VLOOKUP(B44,'Actual Billings'!$H$8:$J$24,3,FALSE),0) -> 17123.75 | S44: =F44-R44 -> -5787.75 | U44: 11848 | V44: =U44-I44 -> 0
A45: Revenue - Product Sales | B45: Revenue | C45: 207160 | D45: 112854 | E45: 94307 | F45: 371653 | G45: 251215 | H45: 120436 | I45: 578813 | J45: 364070 | K45: 214743 | L45: 2097611 | M45: 3206740 | N45: 5304352 | U45: 578813 | V45: =U45-I45 -> 0
A46: Revenue - Other | B46: Revenue | V46: =U46-I46 -> #VALUE!
A47: 40800 - Revenue - Other | B47: 40800 | C47: 0 | D47: 0 | E47: 0 | F47: 0 | G47: 0 | H47: 0 | I47: 0 | J47: 0 | K47: 0 | L47: -59 | M47: 0 | N47: -59 | P47: =IFERROR(-VLOOKUP(B47,'Actual Billings'!$A$8:$C$26,3,FALSE),0) -> 0 | Q47: =C47-P47 -> 0 | R47: =IFERROR(-VLOOKUP(B47,'Actual Billings'!$H$8:$J$24,3,FALSE),0) -> 0 | S47: =F47-R47 -> 0 | U47: 0 | V47: =U47-I47 -> 0
A48: 41400 - Commission Revenue | B48: 41400 | C48: 7878 | D48: 5585 | E48: 2293 | F48: 1230 | G48: 721 | H48: 510 | I48: 9108 | J48: 6305 | K48: 2803 | L48: 64462 | M48: 11060 | N48: 75521 | P48: =IFERROR(-VLOOKUP(B48,'Actual Billings'!$A$8:$C$26,3,FALSE),0) -> 7877.69 | Q48: =C48-P48 -> 0.31 | R48: =IFERROR(-VLOOKUP(B48,'Actual Billings'!$H$8:$J$24,3,FALSE),0) -> 1230.41 | S48: =F48-R48 -> -0.41 | U48: 9108 | V48: =U48-I48 -> 0
A49: Total Revenue - Other | B49: Total | C49: 7878 | D49: 5585 | E49: 2293 | F49: 1230 | G49: 721 | H49: 510 | I49: 9108 | J49: 6305 | K49: 2803 | L49: 64403 | M49: 11060 | N49: 75462 | U49: 9108 | V49: =U49-I49 -> 0
A50: Total Revenue | B50: Total | C50: 1112667 | D50: 892634 | E50: 220033 | F50: 525536 | G50: 406819 | H50: 118717 | I50: 1638203 | J50: 1299453 | K50: 338750 | L50: 10405178 | M50: 4896144 | N50: 15301322 | U50: 1638203 | V50: =U50-I50 -> 0
A51: Cost of Rev with Direct and IT Project Labor | B51: Cost | V51: =U51-I51 -> #VALUE!
A52: Managed IT Service Costs | B52: Managed | V52: =U52-I52 -> #VALUE!
A53: 50000 - Managed IT Costs | B53: 50000 | C53: 30365 | D53: 17845 | E53: 12521 | F53: 7888 | G53: 12059 | H53: -4171 | I53: 38253 | J53: 29904 | K53: 8350 | L53: 190769 | M53: 72326 | N53: 263095 | O53: CA:$10.7k BigLeaf catch-up, ZoomInfo, VyOS Router charges hitting current month | U53: 38253 | V53: =U53-I53 -> 0
A54: Total Cost of Supports Revenue | B54: Total | C54: 30365 | D54: 17845 | E54: 12521 | F54: 7888 | G54: 12059 | H54: -4171 | I54: 38253 | J54: 29904 | K54: 8350 | L54: 190769 | M54: 72326 | N54: 263095 | U54: 38253 | V54: =U54-I54 -> 0
A55: Cost of Monthly Recurring Cloud | B55: Cost | V55: =U55-I55 -> #VALUE!
A56: 50090 - Public Cloud Costs | B56: 50090 | C56: 401 | D56: 401 | E56: 0 | F56: 0 | G56: 0 | H56: 0 | I56: 401 | J56: 401 | K56: 0 | L56: 4009 | M56: 0 | N56: 4009 | U56: 401 | V56: =U56-I56 -> 0
A57: 50095 - Private Cloud Costs | B57: 50095 | C57: 11002 | D57: 8612 | E57: 2389 | F57: 0 | G57: 0 | H57: 0 | I57: 11002 | J57: 8612 | K57: 2389 | L57: 103776 | M57: 0 | N57: 103776 | U57: 11002 | V57: =U57-I57 -> 0
A58: Cost of Monthly Recurring Cloud | B58: Cost | C58: 11403 | D58: 9013 | E58: 2389 | F58: 0 | G58: 0 | H58: 0 | I58: 11403 | J58: 9013 | K58: 2389 | L58: 107785 | M58: 0 | N58: 107785 | U58: 11403 | V58: =U58-I58 -> 0
A59: Cost of Monthly Recurring Resale | B59: Cost | V59: =U59-I59 -> #VALUE!
A60: 50050 - Managed Back up Costs | B60: 50050 | C60: 4802 | D60: 3610 | E60: 1194 | F60: 633 | G60: 619 | H60: 14 | I60: 5436 | J60: 4228 | K60: 1208 | L60: 60330 | M60: 7750 | N60: 68080 | U60: 5436 | V60: =U60-I60 -> 0
A61: 50080 - Managed Spam Filtering Costs | B61: 50080 | C61: 374 | D61: 390 | E61: -17 | F61: 0 | G61: 0 | H61: 0 | I61: 373 | J61: 391 | K61: -17 | L61: 3805 | M61: 0 | N61: 3804 | U61: 373 | V61: =U61-I61 -> 0
A62: 50100 - Domain Names Costs | B62: 50100 | C62: 527 | D62: 606 | E62: -80 | F62: 0 | G62: 0 | H62: 0 | I62: 527 | J62: 606 | K62: -79 | L62: 2436 | M62: 0 | N62: 2437 | U62: 527 | V62: =U62-I62 -> 0
A63: 50150 - Recurring Resale Cost - MSP (Cloud SaaS) | B63: 50150 | C63: 32853 | D63: 21925 | E63: 10928 | F63: 900 | G63: 1042 | H63: -143 | I63: 33753 | J63: 22968 | K63: 10784 | L63: 256991 | M63: 12164 | N63: 269155 | O63: See above | U63: 33753 | V63: =U63-I63 -> 0
A64: 50190 - Managed Voice Costs | B64: 50190 | C64: 2876 | D64: 0 | E64: 2876 | F64: 0 | G64: 0 | H64: 0 | I64: 2876 | J64: 0 | K64: 2876 | L64: 3261 | M64: 0 | N64: 3261 | U64: 2876 | V64: =U64-I64 -> 0
A65: 50400 - HaaS Costs | B65: 50400 | C65: 8551 | D65: 7310 | E65: 1242 | F65: 209 | G65: 0 | H65: 209 | I65: 8760 | J65: 7309 | K65: 1451 | L65: 89922 | M65: 209 | N65: 90131 | U65: 8760 | V65: =U65-I65 -> 0
A66: 51250 - Chromebook ADP Costs | B66: 51250 | C66: 6364 | D66: 5842 | E66: 522 | F66: 0 | G66: 0 | H66: 0 | I66: 6364 | J66: 5842 | K66: 522 | L66: 12206 | M66: 1450 | N66: 13656 | U66: 6364 | V66: =U66-I66 -> 0
A67: 51450 - Microsoft 365 Costs | B67: 51450 | C67: 98997 | D67: 65435 | E67: 33562 | F67: 1119 | G67: 1065 | H67: 55 | I67: 100116 | J67: 66500 | K67: 33617 | L67: 719088 | M67: 11024 | N67: 730112 | O67: See above | U67: 100116 | V67: =U67-I67 -> 0
A68: 52100 - Security Resale Costs | B68: 52100 | C68: 59207 | D68: 57719 | E68: 1487 | F68: 5168 | G68: 4927 | H68: 241 | I68: 64375 | J68: 62646 | K68: 1728 | L68: 482052 | M68: 44208 | N68: 526260 | U68: 64375 | V68: =U68-I68 -> 0
A69: 52300 - Voice Resale Costs | B69: 52300 | C69: 4652 | D69: 4647 | E69: 6 | F69: 358 | G69: 358 | H69: 0 | I69: 5011 | J69: 5005 | K69: 6 | L69: 26198 | M69: 6798 | N69: 32996 | U69: 5011 | V69: =U69-I69 -> 0
A70: 62500 - Managed Security Costs | B70: 62500 | C70: 1844 | D70: 1827 | E70: 16 | F70: 0 | G70: 0 | H70: 0 | I70: 1843 | J70: 1827 | K70: 16 | L70: 23597 | M70: 0 | N70: 23597 | U70: 1843 | V70: =U70-I70 -> 0
A71: Cost of Monthly Recurring Resale | B71: Cost | C71: 221047 | D71: 169311 | E71: 51736 | F71: 8387 | G71: 8011 | H71: 376 | I71: 229434 | J71: 177322 | K71: 52112 | L71: 1679886 | M71: 83603 | N71: 1763489 | U71: 229434 | V71: =U71-I71 -> 0
A72: Project Service Costs | B72: Project | V72: =U72-I72 -> #VALUE!
A73: 50200 - Project Service Costs | B73: 50200 | C73: 0 | D73: 0 | E73: 0 | F73: 0 | G73: 0 | H73: 0 | I73: 0 | J73: 0 | K73: 0 | L73: 2823 | M73: 76 | N73: 2899 | U73: 0 | V73: =U73-I73 -> 0
A74: Total Cost of Maintenances Revenue | B74: Total | C74: 0 | D74: 0 | E74: 0 | F74: 0 | G74: 0 | H74: 0 | I74: 0 | J74: 0 | K74: 0 | L74: 2823 | M74: 76 | N74: 2899 | U74: 0 | V74: =U74-I74 -> 0
A75: Subcontractor Service Costs | B75: Subcontractor | V75: =U75-I75 -> #VALUE!
A76: 50500 - Subcontracted Service Costs | B76: 50500 | C76: 10904 | D76: 6719 | E76: 4186 | F76: 12135 | G76: 6704 | H76: 5431 | I76: 23040 | J76: 13423 | K76: 9617 | L76: 215397 | M76: 49714 | N76: 265110 | O76: See tab 41700-50500 | U76: 23040 | V76: =U76-I76 -> 0
A77: Total Cost of Sales Revenue | B77: Total | C77: 10904 | D77: 6719 | E77: 4186 | F77: 12135 | G77: 6704 | H77: 5431 | I77: 23040 | J77: 13423 | K77: 9617 | L77: 215397 | M77: 49714 | N77: 265110 | U77: 23040 | V77: =U77-I77 -> 0
A78: Product Sales Cost | B78: Product | V78: =U78-I78 -> #VALUE!
A79: 50300 - Product Sales Costs | B79: 50300 | C79: 159773 | D79: 94509 | E79: 65263 | F79: 305291 | G79: 209536 | H79: 95755 | I79: 465063 | J79: 304045 | K79: 161018 | L79: 1753403 | M79: 2624736 | N79: 4378140 | O79: See above | U79: 465063 | V79: =U79-I79 -> 0
A80: 54000 - Freight Cost | B80: 54000 | C80: 10614 | D80: 9899 | E80: 715 | F80: 10329 | G80: 7210 | H80: 3118 | I80: 20943 | J80: 17109 | K80: 3834 | L80: 32407 | M80: 95967 | N80: 128373 | U80: 20943 | V80: =U80-I80 -> 0
A81: Total Cost of Products Revenue | B81: Total | C81: 170387 | D81: 104408 | E81: 65978 | F81: 315620 | G81: 216746 | H81: 98873 | I81: 486006 | J81: 321154 | K81: 164852 | L81: 1785810 | M81: 2720703 | N81: 4506513 | U81: 486006 | V81: =U81-I81 -> 0
A82: IT Project Labor | B82: IT | V82: =U82-I82 -> #VALUE!
A83: 50605 - Project Labor - Wages | B83: 50605 | C83: 47961 | D83: 45876 | E83: 2086 | F83: 0 | G83: 0 | H83: 0 | I83: 47961 | J83: 45877 | K83: 2085 | L83: 450576 | M83: 82377 | N83: 532953 | O83: CA: Accrual / more working days | U83: 47961 | V83: =U83-I83 -> 0
A84: 50705 - Payroll Taxes- Project Labor | B84: 50705 | C84: 3437 | D84: 3288 | E84: 149 | F84: 0 | G84: 0 | H84: 0 | I84: 3437 | J84: 3287 | K84: 150 | L84: 34537 | M84: 6542 | N84: 41080 | U84: 3437 | V84: =U84-I84 -> 0
A85: 50805 - Payroll Pension Match- Project Labor | B85: 50805 | C85: 1439 | D85: 1376 | E85: 63 | F85: 0 | G85: 0 | H85: 0 | I85: 1439 | J85: 1377 | K85: 62 | L85: 13517 | M85: 2471 | N85: 15989 | U85: 1439 | V85: =U85-I85 -> 0
A86: 60705 - Employee Benefits- Project Labor | B86: 60705 | C86: 5066 | D86: 4846 | E86: 220 | F86: 0 | G86: 0 | H86: 0 | I86: 5067 | J86: 4846 | K86: 220 | L86: 48811 | M86: 3444 | N86: 52254 | U86: 5067 | V86: =U86-I86 -> 0
A87: Total IT Project Labor | B87: Total | C87: 57903 | D87: 55386 | E87: 2518 | F87: 0 | G87: 0 | H87: 0 | I87: 57904 | J87: 55387 | K87: 2517 | L87: 547441 | M87: 94834 | N87: 642276 | U87: 57904 | V87: =U87-I87 -> 0
A88: Direct Labor Costs | B88: Direct | V88: =U88-I88 -> #VALUE!
A89: 50610 - Direct Labor Wages | B89: 50610 | C89: 108366 | D89: 118003 | E89: -9637 | F89: 64806 | G89: 57854 | H89: 6953 | I89: 173172 | J89: 175855 | K89: -2684 | L89: 1178677 | M89: 572860 | N89: 1751537 | O89: CA: Decrease the result of Thomas B and Luis H dismissed in Sept OH: Chirstopher Vouis costs incurred in Oct. | U89: 174852 | V89: =U89-I89 -> 1680
A90: 50710 - Payroll Taxes- Direct Labor | B90: 50710 | C90: 8181 | D90: 8729 | E90: -548 | F90: 4673 | G90: 4150 | H90: 523 | I90: 12853 | J90: 12880 | K90: -25 | L90: 95886 | M90: 43295 | N90: 139181 | U90: 12982 | V90: =U90-I90 -> 129
A91: 50811 - Payroll Pension Match- Direct Labor | B91: 50811 | C91: 997 | D91: 1363 | E91: -367 | F91: 928 | G91: 888 | H91: 40 | I91: 1924 | J91: 2251 | K91: -327 | L91: 13428 | M91: 8979 | N91: 22406 | U91: 1924 | V91: =U91-I91 -> 0
A92: 60710 - Employee Benefits- Direct Labor | B92: 60710 | C92: 8291 | D92: 9315 | E92: -1024 | F92: 6951 | G92: 6360 | H92: 591 | I92: 15243 | J92: 15675 | K92: -433 | L92: 93879 | M92: 68693 | N92: 162573 | O92: CA: Dismissed EE's benefits hitting Sept, not Oct. | U92: 15242 | V92: =U92-I92 -> -1
A93: 50660 - Contractor Wages - Direct Labor | B93: 50660 | C93: 3628 | D93: 4035 | E93: -406 | F93: 0 | G93: 0 | H93: 0 | I93: 3628 | J93: 4035 | K93: -406 | L93: 11377 | M93: 0 | N93: 11378 | U93: 3629 | V93: =U93-I93 -> 1
A94: Total Direct Labor Costs | B94: Total | C94: 129463 | D94: 141445 | E94: -11982 | F94: 77358 | G94: 69252 | H94: 8107 | I94: 206820 | J94: 210696 | K94: -3875 | L94: 1393247 | M94: 693827 | N94: 2087075 | U94: 208629 | V94: =U94-I94 -> 1809
A95: Total Cost of Rev with IT Project and Direct Labor | B95: Total | C95: 631472 | D95: 504127 | E95: 127346 | F95: 421388 | G95: 312772 | H95: 108616 | I95: 1052860 | J95: 816899 | K95: 235962 | L95: 5923158 | M95: 3715083 | N95: 9638242 | U95: 1054669 | V95: =U95-I95 -> 1809
A96: Total Gross Profit with Direct Labor | B96: Total | C96: 481195 | D96: 388507 | E96: 92688 | F96: 104148 | G96: 94047 | H96: 10101 | I96: 585343 | J96: 482554 | K96: 102789 | L96: 4482020 | M96: 1181061 | N96: 5663080 | U96: 583534 | V96: =U96-I96 -> -1809
A97: Sales Labor Costs | B97: Sales | V97: =U97-I97 -> #VALUE!
A98: 50620 - Sales Wages | B98: 50620 | C98: 60965 | D98: 64222 | E98: -3257 | F98: 19337 | G98: 14414 | H98: 4923 | I98: 80302 | J98: 78635 | K98: 1666 | L98: 612279 | M98: 278879 | N98: 891156 | O98: CA: Accrual / more working days Oct. | U98: 80301 | V98: =U98-I98 -> -1
A99: 50720 - Payroll Taxes- Sales | B99: 50720 | C99: 2979 | D99: 3838 | E99: -859 | F99: 2776 | G99: 3548 | H99: -772 | I99: 5755 | J99: 7387 | K99: -1631 | L99: 58830 | M99: 30689 | N99: 89521 | U99: 5756 | V99: =U99-I99 -> 1
A100: 50821 - Payroll Pension Match- Sales | B100: 50821 | C100: 1396 | D100: 1508 | E100: -113 | F100: 0 | G100: 90 | H100: -90 | I100: 1395 | J100: 1598 | K100: -203 | L100: 15008 | M100: 3100 | N100: 18107 | U100: 1395 | V100: =U100-I100 -> 0
...

Sheet Payroll Breakdown - October
A1: August Payroll Breakdown | F1: P&L | H1: Payoll Cost | I1: Differences | J1: Notes
F2: IT Project Labor | G2: 55387 | H2: =ROUND(+H13,0) -> 57904 | I2: =+G2-H2 -> -2517
F3: Direct Labor | G3: 210696 | H3: =ROUND(+H50,0) -> 208629 | I3: =+G3-H3 -> 2067
A4: Dismissed | F4: Sales (includes commissions) | G4: 147904 | H4: =ROUND(+H64,0) -> 131474 | I4: =+G4-H4 -> 16430 | J4: CC transactions
A5: New Hires | F5: Admin | G5: 75369 | H5: =ROUND(+H76,0) -> 72670 | I5: =+G5-H5 -> 2699 | J5: Stop loss
A7: Last Day | B7: New Hire First Day | C7: Last Name | D7: First Name | E7: Full Name | F7: Department | G7: Financial Statement category | H7: Payroll Cost | I7: One time Payouts | J7: After- Hours On Call and Overtime | K7: Monthly Base Cost | L7: September Monthly Base Estimated | M7: Diff | N7: Commissions Current Month | O7: Commissions Previous Month | P7: Difference | Q7: Notes
C8: Bruce | D8: James | E8: James Bruce | F8: West Coast - Engineering | G8: 1-IT Project Labor | H8: 10476.994 | K8: =+H8-I8-J8 -> 10476.994 | L8: 10021.473 | M8: =+K8-L8 -> 455.52138
C9: Lampe | D9: Matthew | E9: Matthew Lampe | F9: West Coast - Engineering | G9: 1-IT Project Labor | H9: 8861.7975 | K9: =+H9-I9-J9 -> 8861.7975 | L9: 8476.5067 | M9: =+K9-L9 -> 385.29085
C10: Newson | D10: Keith | E10: Keith Newson | F10: West Coast - Engineering | G10: 1-IT Project Labor | H10: 11954.575 | K10: =+H10-I10-J10 -> 11954.575 | L10: 11434.835 | M10: =+K10-L10 -> 519.74008
C11: Walski | D11: Stephen | E11: Stephen Walski | F11: West Coast - Service Delivery | G11: 1-IT Project Labor | H11: 14940.796 | K11: =+H11-I11-J11 -> 14940.796 | L11: 14291.239 | M11: =+K11-L11 -> 649.557
C12: Gilmore | D12: Christopher | E12: Christopher Gilmore | F12: West Cost-Fresno Engineering | G12: 1-IT Project Labor | H12: 11669.737 | K12: =+H12-I12-J12 -> 11669.737 | L12: 11162.338 | M12: =+K12-L12 -> 507.39915
G13: 1-IT Project Labor Total | H13: =SUM(H8:H12) -> 57903.9 | I13: =SUM(I8:I12) -> 0 | J13: =SUM(J8:J12) -> 0 | K13: =SUM(K8:K12) -> 57903.9 | L13: =+SUM(L8:L12) -> 55386.392 | M13: =+K13-L13 -> 2517.5085 | Q13: =+M13/K13 -> 0.043477355
C14: Annabel | D14: Peter | E14: Peter Annabel | F14: Cloud Services | G14: 2-Direct Labor | H14: 12204.655 | K14: =+J14+I14+H14 -> 12204.655 | L14: 11674.037 | M14: =+K14-L14 -> 530.61846
C15: Barr | D15: Kevin | E15: Kevin Barr | F15: East Coast - Installation Services | G15: 2-Direct Labor | H15: 5566.2061 | K15: =+J15+I15+H15 -> 5566.2061 | L15: 5324.1974 | M15: =+K15-L15 -> 242.00869
C16: Bates | D16: Colin | E16: Colin Bates | F16: West Coast - Service Delivery | G16: 2-Direct Labor | H16: 2794.836 | K16: =+J16+I16+H16 -> 2794.836 | L16: 1908.104 | M16: =+K16-L16 -> 886.732 | Q16: Lower number of hours each payroll
C17: Blair | D17: Joshua | E17: Joshua Blair | F17: West Coast - Service Delivery | G17: 2-Direct Labor | H17: 1344.78 | K17: =+J17+I17+H17 -> 1344.78 | L17: 4379.028 | M17: =+K17-L17 -> -3034.248
A18: 45925 | C18: Brennan | D18: Thomas | E18: Thomas Brennan | F18: West Coast - Service Delivery | G18: 2-Direct Labor | H18: 2669.72 | K18: =+J18+I18+H18 -> 2669.72 | L18: 5498.33 | M18: =+K18-L18 -> -2828.61
C19: Brinovec | D19: Matthew | E19: Matthew Brinovec | F19: East Coast - Service Desk | G19: 2-Direct Labor | H19: 7755.0722 | K19: =+J19+I19+H19 -> 7755.0722 | L19: 7417.8848 | M19: =+K19-L19 -> 337.18738
C20: Chavez Soto | D20: Cristina | E20: Cristina Chavez Soto | F20: West Coast - Service Delivery | G20: 2-Direct Labor | H20: 5678.355 | K20: =+J20+I20+H20 -> 5678.355 | L20: 5115.1 | M20: =+K20-L20 -> 563.255
C21: Conkle | D21: Kerr | E21: Kerr Conkle | F21: East Coast - Service Desk | G21: 2-Direct Labor | H21: 8651.9532 | K21: =+J21+I21+H21 -> 8651.9532 | L21: 8275.7572 | M21: =+K21-L21 -> 376.19608
C22: Contreras | D22: Angela | E22: Angela Contreras | F22: West Coast - Service Delivery | G22: 2-Direct Labor | H22: 8122.963 | K22: =+J22+I22+H22 -> 8122.963 | L22: 7565.472 | M22: =+K22-L22 -> 557.491
C23: Contreras | D23: Oscar | E23: Oscar Contreras | F23: West Coast - Service Delivery | G23: 2-Direct Labor | H23: 4454.091 | K23: =+J23+I23+H23 -> 4454.091 | L23: 6111.799 | M23: =+K23-L23 -> -1657.708
B24: 45922 | C24: Darmstandler | D24: Hudson | E24: Hudson Darmstandler | F24: West Coast - Service Delivery | G24: 2-Direct Labor | H24: 3397.9 | K24: =+J24+I24+H24 -> 3397.9
C25: Dean | D25: Sam | E25: Sam Dean | F25: East Coast - Service Desk | G25: 2-Direct Labor | H25: 6809.689 | K25: =+J25+I25+H25 -> 6809.689 | L25: 6684.366 | M25: =+K25-L25 -> 125.323
C26: Dimson | D26: Hoover | E26: Hoover Dimson | F26: West Coast - Service Delivery | G26: 2-Direct Labor | H26: 1265.44 | K26: =+J26+I26+H26 -> 1265.44 | L26: 1218.71 | M26: =+K26-L26 -> 46.73
C27: Doyle | D27: William | E27: William Doyle | F27: West Coast - Service Delivery | G27: 2-Direct Labor | H27: 8698.385 | K27: =+J27+I27+H27 -> 8698.385 | L27: 6935.78 | M27: =+K27-L27 -> 1762.605
C28: Dupray | D28: Nathaniel | E28: Nathaniel Dupray | F28: East Coast - Service Desk | G28: 2-Direct Labor | H28: 5696.815 | K28: =+J28+I28+H28 -> 5696.815 | L28: 5564.28 | M28: =+K28-L28 -> 132.535
C29: Espinoza | D29: Gabriel | E29: Gabriel Espinoza | F29: West Coast - Service Delivery | G29: 2-Direct Labor | H29: 9442.185 | K29: =+J29+I29+H29 -> 9442.185 | L29: 6603.77 | M29: =+K29-L29 -> 2838.415
C30: Fajardo | D30: Franz Aram | E30: Franz Aram Fajardo | F30: West Coast - Service Delivery | G30: 2-Direct Labor | H30: 1039.8 | K30: =+J30+I30+H30 -> 1039.8 | L30: 1665.3 | M30: =+K30-L30 -> -625.5
C31: Hughes | D31: Michael | E31: Michael Hughes | F31: West Coast - Service Delivery | G31: 2-Direct Labor | H31: 6626.784 | K31: =+J31+I31+H31 -> 6626.784 | L31: 6092.471 | M31: =+K31-L31 -> 534.313
A32: 45926 | C32: Huizar | D32: Luis | E32: Luis Huizar | F32: West Coast - Service Delivery | G32: 2-Direct Labor | H32: -2083.957 | K32: =+J32+I32+H32 -> -2083.957 | L32: 8272.229 | M32: =+K32-L32 -> -10356.186
C33: Hulsey-Cedeno | D33: Brandon | E33: Brandon Hulsey-Cedeno | F33: West Coast - Service Delivery | G33: 2-Direct Labor | H33: 6006.198 | K33: =+J33+I33+H33 -> 6006.198 | L33: 4800.202 | M33: =+K33-L33 -> 1205.996
C34: Johnson | D34: Brandon | E34: Brandon Johnson | F34: West Coast - Service Delivery | G34: 2-Direct Labor | H34: 11503.135 | K34: =+J34+I34+H34 -> 11503.135 | L34: 11002.965 | M34: =+K34-L34 -> 500.16992
C35: Keim | D35: Colton | E35: Colton Keim | F35: East Coast - Service Desk | G35: 2-Direct Labor | H35: 6853.913 | K35: =+J35+I35+H35 -> 6853.913 | L35: 5542.592 | M35: =+K35-L35 -> 1311.321
C36: Lanning | D36: Nathan | E36: Nathan Lanning | F36: East Coast - Field Engineering | G36: 2-Direct Labor | H36: 9312.9098 | K36: =+J36+I36+H36 -> 9312.9098 | L36: 8908.0198 | M36: =+K36-L36 -> 404.88992
C37: Magcalayo | D37: Jenny Rose | E37: Jenny Rose Magcalayo | F37: West Coast - Service Delivery | G37: 2-Direct Labor | H37: 1322.96 | K37: =+J37+I37+H37 -> 1322.96
C38: Matuszynski | D38: Cole | E38: Cole Matuszynski | F38: East Coast - Service Desk | G38: 2-Direct Labor | H38: 2327.989 | K38: =+J38+I38+H38 -> 2327.989 | L38: 3738.606 | M38: =+K38-L38 -> -1410.617
C39: Mercer | D39: Mark | E39: Mark Mercer | F39: West Coast-Fresno Service | G39: 2-Direct Labor | H39: 7335.503 | K39: =+J39+I39+H39 -> 7335.503 | L39: 6633.957 | M39: =+K39-L39 -> 701.546
C40: Morozov | D40: Steve | E40: Steve Morozov | F40: West Coast - Service Delivery | G40: 2-Direct Labor | H40: 5527.16 | K40: =+J40+I40+H40 -> 5527.16 | L40: 4939.66 | M40: =+K40-L40 -> 587.5
C41: Pena | D41: Luis | E41: Luis Pena | F41: West Coast - Service Delivery | G41: 2-Direct Labor | H41: 8710.102 | K41: =+J41+I41+H41 -> 8710.102 | L41: 6475.793 | M41: =+K41-L41 -> 2234.309
C42: Schilber | D42: Michael | E42: Michael Schilber | F42: Cyber Security | G42: 2-Direct Labor | H42: 8818.7392 | K42: =+J42+I42+H42 -> 8818.7392 | L42: 8435.3062 | M42: =+K42-L42 -> 383.43308
C43: Stewart | D43: Timothy | E43: Timothy Stewart | F43: West Coast - Service Delivery | G43: 2-Direct Labor | H43: 9093.931 | K43: =+J43+I43+H43 -> 9093.931 | L43: 8326.744 | M43: =+K43-L43 -> 767.187
C44: Strassell | D44: Cory | E44: Cory Strassell | F44: East Coast - Field Engineering | G44: 2-Direct Labor | H44: 7784.074 | K44: =+J44+I44+H44 -> 7784.074 | L44: 7445.646 | M44: =+K44-L44 -> 338.428
A45: 45919 | C45: Terrell | D45: Duncan | E45: Duncan Terrell | F45: East Coast - Installation Services | G45: 2-Direct Labor | H45: 1808.52 | K45: =+J45+I45+H45 -> 1808.52 | L45: 3093.175 | M45: =+K45-L45 -> -1284.655
C46: Trude | D46: Michael | E46: Michael Trude | F46: East Coast - Field Engineering | G46: 2-Direct Labor | H46: 8431.3608 | K46: =+J46+I46+H46 -> 8431.3608 | L46: 8176.8988 | M46: =+K46-L46 -> 254.46192
B47: 45943 | C47: Vega | D47: Arnold | E47: Arnold Vega | F47: West Coast - Service Delivery | G47: 2-Direct Labor | H47: 3553.84 | K47: =+J47+I47+H47 -> 3553.84
B48: 45922 | C48: Vouis | D48: Christopher | E48: Christopher Vouis | F48: East Coast - Service Desk | G48: 2-Direct Labor | H48: 4551.05 | K48: =+J48+I48+H48 -> 4551.05
C49: Wijaya | D49: Tommy | E49: Tommy Wijaya | F49: West Coast - Service Delivery | G49: 2-Direct Labor | H49: 5551.966 | K49: =+J49+I49+H49 -> 5551.966 | L49: 5185.739 | M49: =+K49-L49 -> 366.227
G50: Direct Labor Total | H50: =SUM(H14:H49) -> 208629.02 | I50: =SUM(I14:I49) -> 0 | J50: =SUM(J14:J49) -> 0 | K50: =SUM(K14:K49) -> 208629.02 | L50: =SUM(L14:L49) -> 199011.92 | M50: =+K50-L50 -> 9617.1045 | Q50: =+M50/K50 -> 0.046096676
C51: De Guzman | D51: Edwin | E51: Edwin De Guzman | F51: Contract Wages | G51: 3-Sales Labor Costs | H51: 2021.61 | K51: =+H51+I51+J51 -> 2021.61 | L51: 1938.95 | M51: =+K51-L51 -> 82.66 | P51: =+N51-O51 -> 0
C52: Martinez Duran | D52: Julissa | E52: Julissa Martinez Duran | F52: Contract Wages | G52: 3-Sales Labor Costs | H52: 2091.24 | K52: =+H52+I52+J52 -> 2091.24 | L52: 2123.08 | M52: =+K52-L52 -> -31.84 | P52: =+N52-O52 -> 0
C53: Martinez | D53: Maria | E53: Maria Martinez | F53: Contract Wages | G53: 3-Sales Labor Costs | H53: 2272.98 | K53: =+H53+I53+J53 -> 2272.98 | L53: 2307.7 | M53: =+K53-L53 -> -34.72 | P53: =+N53-O53 -> 0
C54: Villanueva | D54: Myca | E54: Myca Villanueva | F54: Contract Wages | G54: 3-Sales Labor Costs | H54: 2081.91 | K54: =+H54+I54+J54 -> 2081.91 | L54: 2052.3 | M54: =+K54-L54 -> 29.61 | P54: =+N54-O54 -> 0
C55: Walker | D55: Joel | E55: Joel Walker | F55: East Coast - Sales and Marketing | G55: 3-Sales Labor Costs | H55: 26370.343 | K55: =+H55+I55+J55 -> 26370.343 | L55: 34807.88 | M55: =+K55-L55 -> -8437.5369 | N55: 25140.59 | O55: 16975.66 | P55: =+N55-O55 -> 8164.93
A56: 45922 | C56: Baker | D56: Matthew | E56: Matthew Baker | F56: East Coast - Sales and Marketing | G56: 3-Sales Labor Costs | H56: 6055.31 | K56: =+H56+I56+J56 -> 6055.31 | L56: 13421.303 | M56: =+K56-L56 -> -7365.9931 | N56: 7592.05 | O56: 0 | P56: =+N56-O56 -> 7592.05
C57: Wallace | D57: Mark | E57: Mark Wallace | F57: East Coast - Sales and Marketing | G57: 3-Sales Labor Costs | H57: 8696.6886 | K57: =+H57+I57+J57 -> 8696.6886 | L57: 7487.2391 | M57: =+K57-L57 -> 1209.4495 | O57: 810.64 | P57: =+N57-O57 -> -810.64
C58: Chadwell | D58: Daniel | E58: Daniel Chadwell | F58: Procurement and Sales Engineering | G58: 3-Sales Labor Costs | H58: 9354.9949 | K58: =+H58+I58+J58 -> 9354.9949 | L58: 8948.2516 | M58: =+K58-L58 -> 406.74331 | P58: =+N58-O58 -> 0
C59: Johnson | D59: DinYero | E59: DinYero Johnson | F59: Procurement and Sales Engineering | G59: 3-Sales Labor Costs | H59: 17461.36 | K59: =+H59+I59+J59 -> 17461.36 | L59: 17256.721 | M59: =+K59-L59 -> 204.63823 | P59: =+N59-O59 -> 0 | AH59: =2080/8 -> 260
C60: Maestas | D60: Ricky | E60: Ricky Maestas | F60: West Coast - Education | G60: 3-Sales Labor Costs | H60: 10064.356 | K60: =+H60+I60+J60 -> 10064.356 | L60: 9428.759 | M60: =+K60-L60 -> 635.597 | N60: 1530.46 | O60: 1792.36 | P60: =+N60-O60 -> -261.9
C61: Sturdivant | D61: Daniel | E61: Daniel Sturdivant | F61: West Coast - Sales + Marketing | G61: 3-Sales Labor Costs | H61: 23386.56 | K61: =+H61+I61+J61 -> 23386.56 | L61: 22290.93 | M61: =+K61-L61 -> 1095.6301 | N61: 7415.12 | O61: 7716.2 | P61: =+N61-O61 -> -301.08
C62: Harvey | D62: Jay | E62: Jay Harvey | F62: West Coast - Sales + Marketing | G62: 3-Sales Labor Costs | H62: 11257.667 | K62: =+H62+I62+J62 -> 11257.667 | L62: 12710.618 | M62: =+K62-L62 -> -1452.9512 | N62: 2471.91 | O62: 749.01 | P62: =+N62-O62 -> 1722.9
C63: La Fleche | D63: Nathan | E63: Nathan La Fleche | F63: West Coast - Sales + Marketing | G63: 3-Sales Labor Costs | H63: 10359.109 | K63: =+H63+I63+J63 -> 10359.109 | L63: 9658.925 | M63: =+K63-L63 -> 700.18385 | N63: 1227.22 | O63: 1525.58 | P63: =+N63-O63 -> -298.36
G64: Sales Labor Total | H64: =SUM(H51:H63) -> 131474.13 | I64: =SUM(I51:I63) -> 0 | J64: =SUM(J51:J63) -> 0 | K64: =SUMIFS(K8:K75,G8:G75,"3-Sales Labor Costs") -> 131474.13 | L64: 126930.66 | M64: =+K64-L64 -> 4543.4717 | N64: =SUM(N51:N63) -> 45377.35 | O64: =SUM(O51:O63) -> 29569.45 | P64: =SUM(P51:P63) -> 15807.9 | Q64: =+M64/K64 -> 0.034557915
A65: 45919 | C65: Vicencio | D65: P. Dennis | E65: P. Dennis Vicencio | F65: Admin + Finance + HR | G65: 4-Admin | H65: 10351.62 | K65: =+H65+I65+J65 -> 10351.62 | L65: 8417.5038 | M65: =+K65-L65 -> 1934.1162
C66: Hennington | D66: Melinda | E66: Melinda Hennington | F66: Admin Finance-Fresno | G66: 4-Admin | H66: 8874.8402 | K66: =+H66+I66+J66 -> 8874.8402 | L66: 8488.9768 | M66: =+K66-L66 -> 385.86338
C67: Peterson | D67: Devin | E67: Devin Peterson | F67: Central Services & Internal IT | G67: 4-Admin | H67: 9155.4269 | K67: =+H67+I67+J67 -> 9155.4269 | L67: 8757.3646 | M67: =+K67-L67 -> 398.06231
C68: Rownd | D68: Marshall | E68: Marshall Rownd | F68: Central Services & Internal IT | G68: 4-Admin | H68: 12289.946 | K68: =+H68+I68+J68 -> 12289.946 | L68: 11755.591 | M68: =+K68-L68 -> 534.35546
C69: Terrones | D69: Genelyn | E69: Genelyn Terrones | F69: Contract Wages | G69: 4-Admin | H69: 1469.83 | K69: =+H69+I69+J69 -> 1469.83 | L69: 1470 | M69: =+K69-L69 -> -0.17
C70: David | D70: Carrlyn | E70: Carrlyn David | F70: Procurement | G70: 4-Admin | H70: 1127.92 | K70: =+H70+I70+J70 -> 1127.92
C71: Esteras | D71: Lyza | E71: Lyza Esteras | F71: Contract Wages | G71: 4-Admin | H71: 2094.2 | K71: =+H71+I71+J71 -> 2094.2 | L71: 1974 | M71: =+K71-L71 -> 120.2
C72: Dizon | D72: Jaquelene | E72: Jaquelene Dizon | F72: Contract Wages | G72: 4-Admin | H72: 1898.26 | K72: =+H72+I72+J72 -> 1898.26 | L72: 1819.3 | M72: =+K72-L72 -> 78.96
C73: Bates | D73: James | E73: James Bates | F73: Owner | G73: 4-Admin | H73: 7496.512 | K73: =+H73+I73+J73 -> 7496.512 | L73: 7170.558 | M73: =+K73-L73 -> 325.954
C74: Darmstandler | D74: David | E74: David Darmstandler | F74: Owner | G74: 4-Admin | H74: 9254.251 | K74: =+H74+I74+J74 -> 9254.251 | L74: 8863.964 | M74: =+K74-L74 -> 390.287
C75: Craig | D75: David | E75: David Craig | F75: Procurement | G75: 4-Admin | H75: 8656.7486 | K75: =+H75+I75+J75 -> 8656.7486 | L75: 8280.3541 | M75: =+K75-L75 -> 376.39454
G76: Admin Total Costs | H76: =SUM(H65:H75) -> 72669.555 | I76: =SUM(I65:I75) -> 0 | J76: =SUM(J65:J75) -> 0 | K76: =SUM(K65:K75) -> 72669.555 | L76: =SUM(L65:L75) -> 66997.612 | M76: =+K76-L76 -> 5671.9428 | Q76: =+M76/K76 -> 0.078051157
G78: Total Labor Costs | H78: =H76+H64+H50+H13 -> 470676.61 | I78: =+I76+I64+I50+I13 -> 0 | J78: =+J76+J64+J50+J13 -> 0 | K78: =K76+K64+K50+K13 -> 470676.61 | L78: =+L76+L64+L50+L13 -> 448326.58 | M78: =+K78-L78 -> 22350.028 | N78: =+N64 -> 45377.35 | O78: =+O64 -> 29569.45 | P78: =+N78-O78 -> 15807.9 | Q78: =+M78/K78 -> 0.047484891
A79: New Hires - September
B80: 45902 | C80: Magcalayo | D80: Jenny Rose | E80: Jenny Rose Magcalayo | F80: West Coast - Service Delivery | G80: 2-Direct Labor
B81: 45917 | C81: David | D81: Carrlyn | E81: Carrlyn David
G83: Est April Totals
G84: IT Project Labor Costs | K84: =SUMIFS(K8:K83,G8:G83,"1-IT Project Labor") -> 57903.9
G85: Direct Labor Costs | K85: =SUMIFS(K8:K82,G8:G82,"2-Direct Labor") -> 208629.02
G86: Sales Labor Costs | K86: =SUMIFS(K8:K82,G8:G82,"3-Sales Labor Costs") -> 131474.13
G87: Admin Labor Costs | K87: =SUMIFS(K8:K82,G8:G82,"4-Admin ") -> 72669.555
G88: Total Labor Costs | K88: =SUM(K84:K87) -> 470676.61

Sheet Oct Agreement Compare OH
A1: Location | B1: Customer | C1: Agreement Type | D1: Agreement Name | E1: Invoice Number | F1: Invoice Date | G1: October Financials | H1: October Revenue | I1: September Clawback | J1: September Financials | K1: Difference October - September | L1: % Change | M1: Notes
B2: Albert Einstein Academy of Ohio | C2: Recurring Resale - MSP | D2: Recurring Resale - MSP 25/26 | E2: 180446OH | F2: 45931 | G2: 112.5 | H2: =+G2 -> 112.5 | J2: =SUMIFS('[1]Sept-August Comp OH'!$G$2:$G$154,'[1]Sept-August Comp OH'!$B$2:$B$154,'Oct Agreement Compare OH'!B2,'[1]Sept-August Comp OH'!$C$2:$C$154,'Oct Agreement Compare OH'!C2,'[1]Sept-August Comp OH'!$D$2:$D$154,'Oct Agreement Compare OH'!D2) -> 112.5 | K2: =+G2-J2 -> 0 | L2: =IFERROR(K2/J2,1) -> 0
B3: Albert Einstein Academy of Ohio | C3: T-Services-MSP | D3: T-Services-MSP | E3: 180446OH | F3: 45931 | G3: 2842.2 | H3: =+G3 -> 2842.2 | J3: =SUMIFS('[1]Sept-August Comp OH'!$G$2:$G$154,'[1]Sept-August Comp OH'!$B$2:$B$154,'Oct Agreement Compare OH'!B3,'[1]Sept-August Comp OH'!$C$2:$C$154,'Oct Agreement Compare OH'!C3,'[1]Sept-August Comp OH'!$D$2:$D$154,'Oct Agreement Compare OH'!D3) -> 2842.2 | K3: =+G3-J3 -> 0 | L3: =IFERROR(K3/J3,1) -> 0
B4: Albert Einstein Academy of Ohio Total | G4: =SUBTOTAL(9,G2:G3) -> 2954.7 | H4: =SUBTOTAL(9,H2:H3) -> 2954.7 | I4: =SUBTOTAL(9,I2:I3) -> 0 | J4: =SUBTOTAL(9,J2:J3) -> 2954.7
B5: Arcanum Butler Local School District | C5: T-Services-MSP | D5: T-Services-MSP | E5: 180447OH | F5: 45931 | G5: 1161 | H5: =+G5 -> 1161 | J5: =SUMIFS('[1]Sept-August Comp OH'!$G$2:$G$154,'[1]Sept-August Comp OH'!$B$2:$B$154,'Oct Agreement Compare OH'!B5,'[1]Sept-August Comp OH'!$C$2:$C$154,'Oct Agreement Compare OH'!C5,'[1]Sept-August Comp OH'!$D$2:$D$154,'Oct Agreement Compare OH'!D5) -> 1161 | K5: =+G5-J5 -> 0 | L5: =IFERROR(K5/J5,1) -> 0
B6: Arcanum Butler Local School District Total | G6: =SUBTOTAL(9,G5:G5) -> 1161 | H6: =SUBTOTAL(9,H5:H5) -> 1161 | I6: =SUBTOTAL(9,I5:I5) -> 0 | J6: =SUBTOTAL(9,J5:J5) -> 1161
B7: Arts and College Preparatory Academy | C7: Erate-MIBS-School Percentage | D7: Erate-MIBS-School Percentage 25/26 | E7: 180448OH | F7: 45931 | G7: 111.5 | H7: =+G7 -> 111.5 | J7: =SUMIFS('[1]Sept-August Comp OH'!$G$2:$G$154,'[1]Sept-August Comp OH'!$B$2:$B$154,'Oct Agreement Compare OH'!B7,'[1]Sept-August Comp OH'!$C$2:$C$154,'Oct Agreement Compare OH'!C7,'[1]Sept-August Comp OH'!$D$2:$D$154,'Oct Agreement Compare OH'!D7) -> 111.5 | K7: =+G7-J7 -> 0 | L7: =IFERROR(K7/J7,1) -> 0
B8: Arts and College Preparatory Academy | C8: Recurring Resale - MSP | D8: Recurring Resale - MSP 2025 | E8: 180449OH | F8: 45931 | G8: 280 | H8: =+G8 -> 280 | J8: =SUMIFS('[1]Sept-August Comp OH'!$G$2:$G$154,'[1]Sept-August Comp OH'!$B$2:$B$154,'Oct Agreement Compare OH'!B8,'[1]Sept-August Comp OH'!$C$2:$C$154,'Oct Agreement Compare OH'!C8,'[1]Sept-August Comp OH'!$D$2:$D$154,'Oct Agreement Compare OH'!D8) -> 280 | K8: =+G8-J8 -> 0 | L8: =IFERROR(K8/J8,1) -> 0
B9: Arts and College Preparatory Academy | C9: Recurring Resale - Security | D9: Recurring Resale - Security 2025 | E9: 180449OH | F9: 45931 | G9: 35 | H9: =+G9 -> 35 | J9: =SUMIFS('[1]Sept-August Comp OH'!$G$2:$G$154,'[1]Sept-August Comp OH'!$B$2:$B$154,'Oct Agreement Compare OH'!B9,'[1]Sept-August Comp OH'!$C$2:$C$154,'Oct Agreement Compare OH'!C9,'[1]Sept-August Comp OH'!$D$2:$D$154,'Oct Agreement Compare OH'!D9) -> 35 | K9: =+G9-J9 -> 0 | L9: =IFERROR(K9/J9,1) -> 0
B10: Arts and College Preparatory Academy | C10: T-Erate-MIBS-USAC Percentage | D10: T-Erate-MIBS-USAC Percentage 25/26 | E10: 180426OH | F10: 45932 | G10: 446 | H10: =+G10 -> 446 | J10: =SUMIFS('[1]Sept-August Comp OH'!$G$2:$G$154,'[1]Sept-August Comp OH'!$B$2:$B$154,'Oct Agreement Compare OH'!B10,'[1]Sept-August Comp OH'!$C$2:$C$154,'Oct Agreement Compare OH'!C10,'[1]Sept-August Comp OH'!$D$2:$D$154,'Oct Agreement Compare OH'!D10) -> 446 | K10: =+G10-J10 -> 0 | L10: =IFERROR(K10/J10,1) -> 0
B11: Arts and College Preparatory Academy | C11: T-Services-MSP | D11: T-Services-MSP 2025-Evergreen | E11: 180449OH | F11: 45931 | G11: 2658 | H11: =+G11 -> 2658 | J11: =SUMIFS('[1]Sept-August Comp OH'!$G$2:$G$154,'[1]Sept-August Comp OH'!$B$2:$B$154,'Oct Agreement Compare OH'!B11,'[1]Sept-August Comp OH'!$C$2:$C$154,'Oct Agreement Compare OH'!C11,'[1]Sept-August Comp OH'!$D$2:$D$154,'Oct Agreement Compare OH'!D11) -> 2658 | K11: =+G11-J11 -> 0 | L11: =IFERROR(K11/J11,1) -> 0
B12: Arts and College Preparatory Academy Total | G12: =SUBTOTAL(9,G7:G11) -> 3530.5 | H12: =SUBTOTAL(9,H7:H11) -> 3530.5 | I12: =SUBTOTAL(9,I7:I11) -> 0 | J12: =SUBTOTAL(9,J7:J11) -> 3530.5
B13: Caldwell Exempted Village | C13: Erate-MIBS-School Percentage | D13: Erate-MIBS-School Percentage | E13: 180450OH | F13: 45931 | G13: 288.6 | H13: =+G13 -> 288.6 | J13: =SUMIFS('[1]Sept-August Comp OH'!$G$2:$G$154,'[1]Sept-August Comp OH'!$B$2:$B$154,'Oct Agreement Compare OH'!B13,'[1]Sept-August Comp OH'!$C$2:$C$154,'Oct Agreement Compare OH'!C13,'[1]Sept-August Comp OH'!$D$2:$D$154,'Oct Agreement Compare OH'!D13) -> 288.6 | K13: =+G13-J13 -> 0 | L13: =IFERROR(K13/J13,1) -> 0
B14: Caldwell Exempted Village | C14: T-Erate-MIBS-USAC Percentage | D14: T-Erate-MIBS-USAC Percentage 25/26 | E14: 180427OH | F14: 45932 | G14: 673.4 | H14: =+G14 -> 673.4 | J14: =SUMIFS('[1]Sept-August Comp OH'!$G$2:$G$154,'[1]Sept-August Comp OH'!$B$2:$B$154,'Oct Agreement Compare OH'!B14,'[1]Sept-August Comp OH'!$C$2:$C$154,'Oct Agreement Compare OH'!C14,'[1]Sept-August Comp OH'!$D$2:$D$154,'Oct Agreement Compare OH'!D14) -> 673.4 | K14: =+G14-J14 -> 0 | L14: =IFERROR(K14/J14,1) -> 0
B15: Caldwell Exempted Village | C15: T-Services-MSP | D15: T-Services-MSP 2025 Camera | E15: 180451OH | F15: 45931 | G15: 1058 | H15: =+G15 -> 1058 | J15: =SUMIFS('[1]Sept-August Comp OH'!$G$2:$G$154,'[1]Sept-August Comp OH'!$B$2:$B$154,'Oct Agreement Compare OH'!B15,'[1]Sept-August Comp OH'!$C$2:$C$154,'Oct Agreement Compare OH'!C15,'[1]Sept-August Comp OH'!$D$2:$D$154,'Oct Agreement Compare OH'!D15) -> 1058 | K15: =+G15-J15 -> 0 | L15: =IFERROR(K15/J15,1) -> 0
B16: Caldwell Exempted Village | C16: T-Services-MSP | D16: T-Services-MSP VoIP | E16: 180452OH | F16: 45931 | G16: 530 | H16: =+G16 -> 530 | J16: =SUMIFS('[1]Sept-August Comp OH'!$G$2:$G$154,'[1]Sept-August Comp OH'!$B$2:$B$154,'Oct Agreement Compare OH'!B16,'[1]Sept-August Comp OH'!$C$2:$C$154,'Oct Agreement Compare OH'!C16,'[1]Sept-August Comp OH'!$D$2:$D$154,'Oct Agreement Compare OH'!D16) -> 530 | K16: =+G16-J16 -> 0 | L16: =IFERROR(K16/J16,1) -> 0
B17: Caldwell Exempted Village Total | G17: =SUBTOTAL(9,G13:G16) -> 2550 | H17: =SUBTOTAL(9,H13:H16) -> 2550 | I17: =SUBTOTAL(9,I13:I16) -> 0 | J17: =SUBTOTAL(9,J13:J16) -> 2550
B18: City Day Community School | C18: Erate-MIBS-School Percentage | D18: Erate-MIBS-School Percentage 25/26 | E18: 180454OH | F18: 45931 | G18: 40.1 | H18: =+G18 -> 40.1 | J18: =SUMIFS('[1]Sept-August Comp OH'!$G$2:$G$154,'[1]Sept-August Comp OH'!$B$2:$B$154,'Oct Agreement Compare OH'!B18,'[1]Sept-August Comp OH'!$C$2:$C$154,'Oct Agreement Compare OH'!C18,'[1]Sept-August Comp OH'!$D$2:$D$154,'Oct Agreement Compare OH'!D18) -> 40.1 | K18: =+G18-J18 -> 0 | L18: =IFERROR(K18/J18,1) -> 0
B19: City Day Community School | C19: Recurring Resale - MSP | D19: Recurring Resale - MSP 2024/27 | E19: 180453OH | F19: 45931 | G19: 272.44 | H19: =+G19 -> 272.44 | J19: =SUMIFS('[1]Sept-August Comp OH'!$G$2:$G$154,'[1]Sept-August Comp OH'!$B$2:$B$154,'Oct Agreement Compare OH'!B19,'[1]Sept-August Comp OH'!$C$2:$C$154,'Oct Agreement Compare OH'!C19,'[1]Sept-August Comp OH'!$D$2:$D$154,'Oct Agreement Compare OH'!D19) -> 272.44 | K19: =+G19-J19 -> 0 | L19: =IFERROR(K19/J19,1) -> 0
B20: City Day Community School | C20: Recurring Resale - Security | D20: Recurring Resale - Security 2024/27 | E20: 180453OH | F20: 45931 | G20: 217 | H20: =+G20 -> 217 | J20: =SUMIFS('[1]Sept-August Comp OH'!$G$2:$G$154,'[1]Sept-August Comp OH'!$B$2:$B$154,'Oct Agreement Compare OH'!B20,'[1]Sept-August Comp OH'!$C$2:$C$154,'Oct Agreement Compare OH'!C20,'[1]Sept-August Comp OH'!$D$2:$D$154,'Oct Agreement Compare OH'!D20) -> 217 | K20: =+G20-J20 -> 0 | L20: =IFERROR(K20/J20,1) -> 0
B21: City Day Community School | C21: T-Erate-MIBS-USAC Percentage | D21: T-Erate-MIBS-USAC Percentage 25/26 | E21: 180428OH | F21: 45932 | G21: 227.23 | H21: =+G21 -> 227.23 | J21: =SUMIFS('[1]Sept-August Comp OH'!$G$2:$G$154,'[1]Sept-August Comp OH'!$B$2:$B$154,'Oct Agreement Compare OH'!B21,'[1]Sept-August Comp OH'!$C$2:$C$154,'Oct Agreement Compare OH'!C21,'[1]Sept-August Comp OH'!$D$2:$D$154,'Oct Agreement Compare OH'!D21) -> 227.23 | K21: =+G21-J21 -> 0 | L21: =IFERROR(K21/J21,1) -> 0
B22: City Day Community School | C22: T-Services-MSP | D22: Managed Services 2024/27 | E22: 180453OH | F22: 45931 | G22: 2240.53 | H22: =+G22 -> 2240.53 | J22: =SUMIFS('[1]Sept-August Comp OH'!$G$2:$G$154,'[1]Sept-August Comp OH'!$B$2:$B$154,'Oct Agreement Compare OH'!B22,'[1]Sept-August Comp OH'!$C$2:$C$154,'Oct Agreement Compare OH'!C22,'[1]Sept-August Comp OH'!$D$2:$D$154,'Oct Agreement Compare OH'!D22) -> 2240.53 | K22: =+G22-J22 -> 0 | L22: =IFERROR(K22/J22,1) -> 0
B23: City Day Community School Total | G23: =SUBTOTAL(9,G18:G22) -> 2997.3 | H23: =SUBTOTAL(9,H18:H22) -> 2997.3 | I23: =SUBTOTAL(9,I18:I22) -> 0 | J23: =SUBTOTAL(9,J18:J22) -> 2997.3
B24: Columbus Preparatory Academy | C24: Recurring Resale - Microsoft 365 NCE | D24: Microsoft 365 | E24: 180455OH | F24: 45931 | G24: 67.1 | H24: =+G24 -> 67.1 | J24: =SUMIFS('[1]Sept-August Comp OH'!$G$2:$G$154,'[1]Sept-August Comp OH'!$B$2:$B$154,'Oct Agreement Compare OH'!B24,'[1]Sept-August Comp OH'!$C$2:$C$154,'Oct Agreement Compare OH'!C24,'[1]Sept-August Comp OH'!$D$2:$D$154,'Oct Agreement Compare OH'!D24) -> 67.1 | K24: =+G24-J24 -> 0 | L24: =IFERROR(K24/J24,1) -> 0
B25: Columbus Preparatory Academy Total | G25: =SUBTOTAL(9,G24:G24) -> 67.1 | H25: =SUBTOTAL(9,H24:H24) -> 67.1 | I25: =SUBTOTAL(9,I24:I24) -> 0 | J25: =SUBTOTAL(9,J24:J24) -> 67.1
B26: Cristo Rey High School | C26: Erate-MIBS-School Percentage | D26: Erate-MIBS-School Percentage 25/26 | E26: 180456OH | F26: 45931 | G26: 39.79 | H26: =+G26 -> 39.79 | J26: =SUMIFS('[1]Sept-August Comp OH'!$G$2:$G$154,'[1]Sept-August Comp OH'!$B$2:$B$154,'Oct Agreement Compare OH'!B26,'[1]Sept-August Comp OH'!$C$2:$C$154,'Oct Agreement Compare OH'!C26,'[1]Sept-August Comp OH'!$D$2:$D$154,'Oct Agreement Compare OH'!D26) -> 39.79 | K26: =+G26-J26 -> 0 | L26: =IFERROR(K26/J26,1) -> 0
B27: Cristo Rey High School | C27: Recurring Resale - MSP | D27: Recurring Resale - MSP 25/26 | E27: 180459OH | F27: 45931 | G27: 116.14 | H27: =+G27 -> 116.14 | J27: =SUMIFS('[1]Sept-August Comp OH'!$G$2:$G$154,'[1]Sept-August Comp OH'!$B$2:$B$154,'Oct Agreement Compare OH'!B27,'[1]Sept-August Comp OH'!$C$2:$C$154,'Oct Agreement Compare OH'!C27,'[1]Sept-August Comp OH'!$D$2:$D$154,'Oct Agreement Compare OH'!D27) -> 116.14 | K27: =+G27-J27 -> 0 | L27: =IFERROR(K27/J27,1) -> 0
B28: Cristo Rey High School | C28: Recurring Resale - Security | D28: Recurring Resale - Security 25/26 | E28: 180459OH | F28: 45931 | G28: 3489 | H28: =+G28 -> 3489 | J28: =SUMIFS('[1]Sept-August Comp OH'!$G$2:$G$154,'[1]Sept-August Comp OH'!$B$2:$B$154,'Oct Agreement Compare OH'!B28,'[1]Sept-August Comp OH'!$C$2:$C$154,'Oct Agreement Compare OH'!C28,'[1]Sept-August Comp OH'!$D$2:$D$154,'Oct Agreement Compare OH'!D28) -> 2968 | K28: =+G28-J28 -> 521 | L28: =IFERROR(K28/J28,1) -> 0.17553908
B29: Cristo Rey High School | C29: T-Erate-MIBS-USAC Percentage | D29: T-Erate-MIBS-USAC Percentage 25/26 | E29: 180429OH | F29: 45932 | G29: 225.41 | H29: =+G29 -> 225.41 | J29: =SUMIFS('[1]Sept-August Comp OH'!$G$2:$G$154,'[1]Sept-August Comp OH'!$B$2:$B$154,'Oct Agreement Compare OH'!B29,'[1]Sept-August Comp OH'!$C$2:$C$154,'Oct Agreement Compare OH'!C29,'[1]Sept-August Comp OH'!$D$2:$D$154,'Oct Agreement Compare OH'!D29) -> 225.41 | K29: =+G29-J29 -> 0 | L29: =IFERROR(K29/J29,1) -> 0
B30: Cristo Rey High School | C30: T-Services-MSP | D30: 2018/2026 VOIP | E30: 180457OH | F30: 45931 | G30: 379.5 | H30: =+G30 -> 379.5 | J30: =SUMIFS('[1]Sept-August Comp OH'!$G$2:$G$154,'[1]Sept-August Comp OH'!$B$2:$B$154,'Oct Agreement Compare OH'!B30,'[1]Sept-August Comp OH'!$C$2:$C$154,'Oct Agreement Compare OH'!C30,'[1]Sept-August Comp OH'!$D$2:$D$154,'Oct Agreement Compare OH'!D30) -> 379.5 | K30: =+G30-J30 -> 0 | L30: =IFERROR(K30/J30,1) -> 0
B31: Cristo Rey High School | C31: T-Services-MSP | D31: T-Services-MSP - Student Device Support 25/26 | E31: 180458OH | F31: 45931 | G31: 4416.67 | H31: =+G31 -> 4416.67 | J31: =SUMIFS('[1]Sept-August Comp OH'!$G$2:$G$154,'[1]Sept-August Comp OH'!$B$2:$B$154,'Oct Agreement Compare OH'!B31,'[1]Sept-August Comp OH'!$C$2:$C$154,'Oct Agreement Compare OH'!C31,'[1]Sept-August Comp OH'!$D$2:$D$154,'Oct Agreement Compare OH'!D31) -> 4416.67 | K31: =+G31-J31 -> 0 | L31: =IFERROR(K31/J31,1) -> 0
B32: Cristo Rey High School | C32: T-Services-MSP | D32: T-Services-MSP 25/26 | E32: 180459OH | F32: 45931 | G32: 4533.7 | H32: =+G32 -> 4533.7 | J32: =SUMIFS('[1]Sept-August Comp OH'!$G$2:$G$154,'[1]Sept-August Comp OH'!$B$2:$B$154,'Oct Agreement Compare OH'!B32,'[1]Sept-August Comp OH'!$C$2:$C$154,'Oct Agreement Compare OH'!C32,'[1]Sept-August Comp OH'!$D$2:$D$154,'Oct Agreement Compare OH'!D32) -> 4533.7 | K32: =+G32-J32 -> 0 | L32: =IFERROR(K32/J32,1) -> 0
B33: Cristo Rey High School Total | G33: =SUBTOTAL(9,G26:G32) -> 13200.21 | H33: =SUBTOTAL(9,H26:H32) -> 13200.21 | I33: =SUBTOTAL(9,I26:I32) -> 0 | J33: =SUBTOTAL(9,J26:J32) -> 12679.21
B34: Dayton SMART Elementary | C34: Recurring Resale - Security | D34: Recurring Resale - Security 25/26 | E34: 180460OH | F34: 45931 | G34: 105 | H34: =+G34 -> 105 | J34: =SUMIFS('[1]Sept-August Comp OH'!$G$2:$G$154,'[1]Sept-August Comp OH'!$B$2:$B$154,'Oct Agreement Compare OH'!B34,'[1]Sept-August Comp OH'!$C$2:$C$154,'Oct Agreement Compare OH'!C34,'[1]Sept-August Comp OH'!$D$2:$D$154,'Oct Agreement Compare OH'!D34) -> 91 | K34: =+G34-J34 -> 14 | L34: =IFERROR(K34/J34,1) -> 0.15384615
B35: Dayton SMART Elementary | C35: T-Services-MSP | D35: T-Services-MSP 25/26 | E35: 180460OH | F35: 45931 | G35: 1608 | H35: =+G35 -> 1608 | J35: =SUMIFS('[1]Sept-August Comp OH'!$G$2:$G$154,'[1]Sept-August Comp OH'!$B$2:$B$154,'Oct Agreement Compare OH'!B35,'[1]Sept-August Comp OH'!$C$2:$C$154,'Oct Agreement Compare OH'!C35,'[1]Sept-August Comp OH'!$D$2:$D$154,'Oct Agreement Compare OH'!D35) -> 1608 | K35: =+G35-J35 -> 0 | L35: =IFERROR(K35/J35,1) -> 0
B36: Dayton SMART Elementary Total | G36: =SUBTOTAL(9,G34:G35) -> 1713 | H36: =SUBTOTAL(9,H34:H35) -> 1713 | I36: =SUBTOTAL(9,I34:I35) -> 0 | J36: =SUBTOTAL(9,J34:J35) -> 1699
B37: East Muskingum School District | C37: Recurring Resale - MSP | D37: MSP -Recurring Resale | E37: 180462OH | F37: 45931 | G37: 173.5 | H37: =+G37 -> 173.5 | J37: =SUMIFS('[1]Sept-August Comp OH'!$G$2:$G$154,'[1]Sept-August Comp OH'!$B$2:$B$154,'Oct Agreement Compare OH'!B37,'[1]Sept-August Comp OH'!$C$2:$C$154,'Oct Agreement Compare OH'!C37,'[1]Sept-August Comp OH'!$D$2:$D$154,'Oct Agreement Compare OH'!D37) -> 178.5 | K37: =+G37-J37 -> -5 | L37: =IFERROR(K37/J37,1) -> -0.028011204
B38: East Muskingum School District | C38: T-Services-MSP | D38: T-Services-MSP | E38: 180461OH | F38: 45931 | G38: 1260 | H38: =+G38 -> 1260 | J38: =SUMIFS('[1]Sept-August Comp OH'!$G$2:$G$154,'[1]Sept-August Comp OH'!$B$2:$B$154,'Oct Agreement Compare OH'!B38,'[1]Sept-August Comp OH'!$C$2:$C$154,'Oct Agreement Compare OH'!C38,'[1]Sept-August Comp OH'!$D$2:$D$154,'Oct Agreement Compare OH'!D38) -> 1260 | K38: =+G38-J38 -> 0 | L38: =IFERROR(K38/J38,1) -> 0
B39: East Muskingum School District Total | G39: =SUBTOTAL(9,G37:G38) -> 1433.5 | H39: =SUBTOTAL(9,H37:H38) -> 1433.5 | I39: =SUBTOTAL(9,I37:I38) -> 0 | J39: =SUBTOTAL(9,J37:J38) -> 1438.5
B40: Energility LLC | C40: Recurring Resale - Security | D40: Recurring Resale - Security | E40: 180463OH | F40: 45931 | G40: 35 | H40: =+G40 -> 35 | J40: =SUMIFS('[1]Sept-August Comp OH'!$G$2:$G$154,'[1]Sept-August Comp OH'!$B$2:$B$154,'Oct Agreement Compare OH'!B40,'[1]Sept-August Comp OH'!$C$2:$C$154,'Oct Agreement Compare OH'!C40,'[1]Sept-August Comp OH'!$D$2:$D$154,'Oct Agreement Compare OH'!D40) -> 35 | K40: =+G40-J40 -> 0 | L40: =IFERROR(K40/J40,1) -> 0
B41: Energility LLC | C41: T-Services-MSP | D41: 2021/23 MSC | E41: 180463OH | F41: 45931 | G41: 231.66 | H41: =+G41 -> 231.66 | J41: =SUMIFS('[1]Sept-August Comp OH'!$G$2:$G$154,'[1]Sept-August Comp OH'!$B$2:$B$154,'Oct Agreement Compare OH'!B41,'[1]Sept-August Comp OH'!$C$2:$C$154,'Oct Agreement Compare OH'!C41,'[1]Sept-August Comp OH'!$D$2:$D$154,'Oct Agreement Compare OH'!D41) -> 231.66 | K41: =+G41-J41 -> 0 | L41: =IFERROR(K41/J41,1) -> 0
B42: Energility LLC Total | G42: =SUBTOTAL(9,G40:G41) -> 266.66 | H42: =SUBTOTAL(9,H40:H41) -> 266.66 | I42: =SUBTOTAL(9,I40:I41) -> 0 | J42: =SUBTOTAL(9,J40:J41) -> 266.66
B43: Explorers Academy of Science and Tech | C43: T-Services-MSP | D43: Voice Services 2024/25 | E43: 180464OH | F43: 45931 | G43: 362.56 | H43: =+G43 -> 362.56 | J43: =SUMIFS('[1]Sept-August Comp OH'!$G$2:$G$154,'[1]Sept-August Comp OH'!$B$2:$B$154,'Oct Agreement Compare OH'!B43,'[1]Sept-August Comp OH'!$C$2:$C$154,'Oct Agreement Compare OH'!C43,'[1]Sept-August Comp OH'!$D$2:$D$154,'Oct Agreement Compare OH'!D43) -> 362.56 | K43: =+G43-J43 -> 0 | L43: =IFERROR(K43/J43,1) -> 0
B44: Explorers Academy of Science and Tech Total | G44: =SUBTOTAL(9,G43:G43) -> 362.56 | H44: =SUBTOTAL(9,H43:H43) -> 362.56 | I44: =SUBTOTAL(9,I43:I43) -> 0 | J44: =SUBTOTAL(9,J43:J43) -> 362.56
B45: Focus Learning Academy North | C45: Recurring Resale - MSP | D45: 24/27 Recurring Resale - MSP | E45: 180465OH | F45: 45931 | G45: 813.12 | H45: =+G45 -> 813.12 | J45: =SUMIFS('[1]Sept-August Comp OH'!$G$2:$G$154,'[1]Sept-August Comp OH'!$B$2:$B$154,'Oct Agreement Compare OH'!B45,'[1]Sept-August Comp OH'!$C$2:$C$154,'Oct Agreement Compare OH'!C45,'[1]Sept-August Comp OH'!$D$2:$D$154,'Oct Agreement Compare OH'!D45) -> 813.12 | K45: =+G45-J45 -> 0 | L45: =IFERROR(K45/J45,1) -> 0
B46: Focus Learning Academy North | C46: Recurring Resale - Security | D46: 24/27 Recurring Resale - Security | E46: 180465OH | F46: 45931 | G46: 604.5 | H46: =+G46 -> 604.5 | J46: =SUMIFS('[1]Sept-August Comp OH'!$G$2:$G$154,'[1]Sept-August Comp OH'!$B$2:$B$154,'Oct Agreement Compare OH'!B46,'[1]Sept-August Comp OH'!$C$2:$C$154,'Oct Agreement Compare OH'!C46,'[1]Sept-August Comp OH'!$D$2:$D$154,'Oct Agreement Compare OH'!D46) -> 598 | K46: =+G46-J46 -> 6.5 | L46: =IFERROR(K46/J46,1) -> 0.010869565
B47: Focus Learning Academy North | C47: T-Services-MSP | D47: 24/27 T-Services-MSP | E47: 180465OH | F47: 45931 | G47: 3415 | H47: =+G47 -> 3415 | J47: =SUMIFS('[1]Sept-August Comp OH'!$G$2:$G$154,'[1]Sept-August Comp OH'!$B$2:$B$154,'Oct Agreement Compare OH'!B47,'[1]Sept-August Comp OH'!$C$2:$C$154,'Oct Agreement Compare OH'!C47,'[1]Sept-August Comp OH'!$D$2:$D$154,'Oct Agreement Compare OH'!D47) -> 3415 | K47: =+G47-J47 -> 0 | L47: =IFERROR(K47/J47,1) -> 0
B48: Focus Learning Academy North Total | G48: =SUBTOTAL(9,G45:G47) -> 4832.62 | H48: =SUBTOTAL(9,H45:H47) -> 4832.62 | I48: =SUBTOTAL(9,I45:I47) -> 0 | J48: =SUBTOTAL(9,J45:J47) -> 4826.12
B49: Focus Learning Academy of Central Col | C49: Erate-MIBS-School Percentage | D49: Erate-MIBS-School Percentage 25/26 | E49: 180466OH | F49: 45931 | G49: 18 | H49: =+G49 -> 18 | J49: =SUMIFS('[1]Sept-August Comp OH'!$G$2:$G$154,'[1]Sept-August Comp OH'!$B$2:$B$154,'Oct Agreement Compare OH'!B49,'[1]Sept-August Comp OH'!$C$2:$C$154,'Oct Agreement Compare OH'!C49,'[1]Sept-August Comp OH'!$D$2:$D$154,'Oct Agreement Compare OH'!D49) -> 18 | K49: =+G49-J49 -> 0 | L49: =IFERROR(K49/J49,1) -> 0
B50: Focus Learning Academy of Central Col | C50: T-Erate-MIBS-USAC Percentage | D50: T-Erate-MIBS-USAC Percentage 25/26 | E50: 180430OH | F50: 45932 | G50: 96.46 | H50: =+G50 -> 96.46 | J50: =SUMIFS('[1]Sept-August Comp OH'!$G$2:$G$154,'[1]Sept-August Comp OH'!$B$2:$B$154,'Oct Agreement Compare OH'!B50,'[1]Sept-August Comp OH'!$C$2:$C$154,'Oct Agreement Compare OH'!C50,'[1]Sept-August Comp OH'!$D$2:$D$154,'Oct Agreement Compare OH'!D50) -> 96.46 | K50: =+G50-J50 -> 0 | L50: =IFERROR(K50/J50,1) -> 0
B51: Focus Learning Academy of Central Col Total | G51: =SUBTOTAL(9,G49:G50) -> 114.46 | H51: =SUBTOTAL(9,H49:H50) -> 114.46 | I51: =SUBTOTAL(9,I49:I50) -> 0 | J51: =SUBTOTAL(9,J49:J50) -> 114.46
B52: Global Ambassadors Language Academy | C52: Erate-MIBS-School Percentage | D52: Erate-MIBS-School Percentage 25/26 | E52: 180467OH | F52: 45931 | G52: 72.65 | H52: =+G52 -> 72.65 | J52: =SUMIFS('[1]Sept-August Comp OH'!$G$2:$G$154,'[1]Sept-August Comp OH'!$B$2:$B$154,'Oct Agreement Compare OH'!B52,'[1]Sept-August Comp OH'!$C$2:$C$154,'Oct Agreement Compare OH'!C52,'[1]Sept-August Comp OH'!$D$2:$D$154,'Oct Agreement Compare OH'!D52) -> 72.65 | K52: =+G52-J52 -> 0 | L52: =IFERROR(K52/J52,1) -> 0
B53: Global Ambassadors Language Academy | C53: Recurring Resale - MSP | D53: Recurring Resale - MSP 25/27 | E53: 180468OH | F53: 45931 | G53: 389 | H53: =+G53 -> 389 | J53: =SUMIFS('[1]Sept-August Comp OH'!$G$2:$G$154,'[1]Sept-August Comp OH'!$B$2:$B$154,'Oct Agreement Compare OH'!B53,'[1]Sept-August Comp OH'!$C$2:$C$154,'Oct Agreement Compare OH'!C53,'[1]Sept-August Comp OH'!$D$2:$D$154,'Oct Agreement Compare OH'!D53) -> 346.5 | K53: =+G53-J53 -> 42.5 | L53: =IFERROR(K53/J53,1) -> 0.12265512
B54: Global Ambassadors Language Academy | C54: Recurring Resale - Security | D54: Recurring Resale - Security 25/27 | E54: 180468OH | F54: 45931 | G54: 469.5 | H54: =+G54 -> 469.5 | J54: =SUMIFS('[1]Sept-August Comp OH'!$G$2:$G$154,'[1]Sept-August Comp OH'!$B$2:$B$154,'Oct Agreement Compare OH'!B54,'[1]Sept-August Comp OH'!$C$2:$C$154,'Oct Agreement Compare OH'!C54,'[1]Sept-August Comp OH'!$D$2:$D$154,'Oct Agreement Compare OH'!D54) -> 462 | K54: =+G54-J54 -> 7.5 | L54: =IFERROR(K54/J54,1) -> 0.016233766
B55: Global Ambassadors Language Academy | C55: T-Erate-MIBS-USAC Percentage | D55: T-Erate-MIBS-USAC Percentage 25/26 | E55: 180431OH | F55: 45932 | G55: 290.58 | H55: =+G55 -> 290.58 | J55: =SUMIFS('[1]Sept-August Comp OH'!$G$2:$G$154,'[1]Sept-August Comp OH'!$B$2:$B$154,'Oct Agreement Compare OH'!B55,'[1]Sept-August Comp OH'!$C$2:$C$154,'Oct Agreement Compare OH'!C55,'[1]Sept-August Comp OH'!$D$2:$D$154,'Oct Agreement Compare OH'!D55) -> 290.58 | K55: =+G55-J55 -> 0 | L55: =IFERROR(K55/J55,1) -> 0
B56: Global Ambassadors Language Academy | C56: T-Services-MSP | D56: T-Services-MSP 25/27 | E56: 180468OH | F56: 45931 | G56: 2133.7 | H56: =+G56 -> 2133.7 | J56: =SUMIFS('[1]Sept-August Comp OH'!$G$2:$G$154,'[1]Sept-August Comp OH'!$B$2:$B$154,'Oct Agreement Compare OH'!B56,'[1]Sept-August Comp OH'!$C$2:$C$154,'Oct Agreement Compare OH'!C56,'[1]Sept-August Comp OH'!$D$2:$D$154,'Oct Agreement Compare OH'!D56) -> 2133.7 | K56: =+G56-J56 -> 0 | L56: =IFERROR(K56/J56,1) -> 0
B57: Global Ambassadors Language Academy Total | G57: =SUBTOTAL(9,G52:G56) -> 3355.43 | H57: =SUBTOTAL(9,H52:H56) -> 3355.43 | I57: =SUBTOTAL(9,I52:I56) -> 0 | J57: =SUBTOTAL(9,J52:J56) -> 3305.43
B58: Holowicki Enterprises | C58: T-Services-MSP | D58: Managed Security - Britton Store #35696 | E58: 180469OH | F58: 45931 | G58: 225 | H58: =+G58 -> 225 | J58: =SUMIFS('[1]Sept-August Comp OH'!$G$2:$G$154,'[1]Sept-August Comp OH'!$B$2:$B$154,'Oct Agreement Compare OH'!B58,'[1]Sept-August Comp OH'!$C$2:$C$154,'Oct Agreement Compare OH'!C58,'[1]Sept-August Comp OH'!$D$2:$D$154,'Oct Agreement Compare OH'!D58) -> 225 | K58: =+G58-J58 -> 0 | L58: =IFERROR(K58/J58,1) -> 0
B59: Holowicki Enterprises | C59: T-Services-MSP | D59: Managed Security - Renner Store #11490 | E59: 180470OH | F59: 45931 | G59: 222.5 | H59: =+G59 -> 222.5 | J59: =SUMIFS('[1]Sept-August Comp OH'!$G$2:$G$154,'[1]Sept-August Comp OH'!$B$2:$B$154,'Oct Agreement Compare OH'!B59,'[1]Sept-August Comp OH'!$C$2:$C$154,'Oct Agreement Compare OH'!C59,'[1]Sept-August Comp OH'!$D$2:$D$154,'Oct Agreement Compare OH'!D59) -> 222.5 | K59: =+G59-J59 -> 0 | L59: =IFERROR(K59/J59,1) -> 0
B60: Holowicki Enterprises | C60: T-Services-MSP | D60: Managed Security Avery Store #15746 | E60: 180472OH | F60: 45931 | G60: 20 | H60: =+G60 -> 20 | J60: =SUMIFS('[1]Sept-August Comp OH'!$G$2:$G$154,'[1]Sept-August Comp OH'!$B$2:$B$154,'Oct Agreement Compare OH'!B60,'[1]Sept-August Comp OH'!$C$2:$C$154,'Oct Agreement Compare OH'!C60,'[1]Sept-August Comp OH'!$D$2:$D$154,'Oct Agreement Compare OH'!D60) -> 20 | K60: =+G60-J60 -> 0 | L60: =IFERROR(K60/J60,1) -> 0
B61: Holowicki Enterprises | C61: T-Services-MSP | D61: Managed Security Hillard #2466 | E61: 180473OH | F61: 45931 | G61: 227.5 | H61: =+G61 -> 227.5 | J61: =SUMIFS('[1]Sept-August Comp OH'!$G$2:$G$154,'[1]Sept-August Comp OH'!$B$2:$B$154,'Oct Agreement Compare OH'!B61,'[1]Sept-August Comp OH'!$C$2:$C$154,'Oct Agreement Compare OH'!C61,'[1]Sept-August Comp OH'!$D$2:$D$154,'Oct Agreement Compare OH'!D61) -> 227.5 | K61: =+G61-J61 -> 0 | L61: =IFERROR(K61/J61,1) -> 0
B62: Holowicki Enterprises | C62: T-Services-MSP | D62: Managed Security Marysville #28775 | E62: 180474OH | F62: 45931 | G62: 230 | H62: =+G62 -> 230 | J62: =SUMIFS('[1]Sept-August Comp OH'!$G$2:$G$154,'[1]Sept-August Comp OH'!$B$2:$B$154,'Oct Agreement Compare OH'!B62,'[1]Sept-August Comp OH'!$C$2:$C$154,'Oct Agreement Compare OH'!C62,'[1]Sept-August Comp OH'!$D$2:$D$154,'Oct Agreement Compare OH'!D62) -> 230 | K62: =+G62-J62 -> 0 | L62: =IFERROR(K62/J62,1) -> 0
B63: Holowicki Enterprises | C63: T-Services-MSP | D63: Managed Security West Jefferson Store #22386 | E63: 180471OH | F63: 45931 | G63: 190 | H63: =+G63 -> 190 | J63: =SUMIFS('[1]Sept-August Comp OH'!$G$2:$G$154,'[1]Sept-August Comp OH'!$B$2:$B$154,'Oct Agreement Compare OH'!B63,'[1]Sept-August Comp OH'!$C$2:$C$154,'Oct Agreement Compare OH'!C63,'[1]Sept-August Comp OH'!$D$2:$D$154,'Oct Agreement Compare OH'!D63) -> 190 | K63: =+G63-J63 -> 0 | L63: =IFERROR(K63/J63,1) -> 0
B64: Holowicki Enterprises Total | G64: =SUBTOTAL(9,G58:G63) -> 1115 | H64: =SUBTOTAL(9,H58:H63) -> 1115 | I64: =SUBTOTAL(9,I58:I63) -> 0 | J64: =SUBTOTAL(9,J58:J63) -> 1115
B65: Imagine Akron Academy | C65: Erate-MIBS-School Percentage | D65: Erate-MIBS-School Percentage 25/26 | E65: 180475OH | F65: 45931 | G65: 21.78 | H65: =+G65 -> 21.78 | J65: =SUMIFS('[1]Sept-August Comp OH'!$G$2:$G$154,'[1]Sept-August Comp OH'!$B$2:$B$154,'Oct Agreement Compare OH'!B65,'[1]Sept-August Comp OH'!$C$2:$C$154,'Oct Agreement Compare OH'!C65,'[1]Sept-August Comp OH'!$D$2:$D$154,'Oct Agreement Compare OH'!D65) -> 21.78 | K65: =+G65-J65 -> 0 | L65: =IFERROR(K65/J65,1) -> 0
B66: Imagine Akron Academy | C66: T-Erate-MIBS-USAC Percentage | D66: T-Erate-MIBS-USAC Percentage 25/26 | E66: 180432OH | F66: 45932 | G66: 123.46 | H66: =+G66 -> 123.46 | J66: =SUMIFS('[1]Sept-August Comp OH'!$G$2:$G$154,'[1]Sept-August Comp OH'!$B$2:$B$154,'Oct Agreement Compare OH'!B66,'[1]Sept-August Comp OH'!$C$2:$C$154,'Oct Agreement Compare OH'!C66,'[1]Sept-August Comp OH'!$D$2:$D$154,'Oct Agreement Compare OH'!D66) -> 123.46 | K66: =+G66-J66 -> 0 | L66: =IFERROR(K66/J66,1) -> 0
B67: Imagine Akron Academy Total | G67: =SUBTOTAL(9,G65:G66) -> 145.24 | H67: =SUBTOTAL(9,H65:H66) -> 145.24 | I67: =SUBTOTAL(9,I65:I66) -> 0 | J67: =SUBTOTAL(9,J65:J66) -> 145.24
B68: Imagine Bella Academy of Excellence | C68: Erate-MIBS-School Percentage | D68: Erate-MIBS-School Percentage 25/26 | E68: 180476OH | F68: 45931 | G68: 18.05 | H68: =+G68 -> 18.05 | J68: =SUMIFS('[1]Sept-August Comp OH'!$G$2:$G$154,'[1]Sept-August Comp OH'!$B$2:$B$154,'Oct Agreement Compare OH'!B68,'[1]Sept-August Comp OH'!$C$2:$C$154,'Oct Agreement Compare OH'!C68,'[1]Sept-August Comp OH'!$D$2:$D$154,'Oct Agreement Compare OH'!D68) -> 18.05 | K68: =+G68-J68 -> 0 | L68: =IFERROR(K68/J68,1) -> 0
B69: Imagine Bella Academy of Excellence | C69: Recurring Resale - Security | D69: Recurring Resale - Security 2024/25 | E69: 180477OH | F69: 45931 | G69: 210 | H69: =+G69 -> 210 | J69: =SUMIFS('[1]Sept-August Comp OH'!$G$2:$G$154,'[1]Sept-August Comp OH'!$B$2:$B$154,'Oct Agreement Compare OH'!B69,'[1]Sept-August Comp OH'!$C$2:$C$154,'Oct Agreement Compare OH'!C69,'[1]Sept-August Comp OH'!$D$2:$D$154,'Oct Agreement Compare OH'!D69) -> 210 | K69: =+G69-J69 -> 0 | L69: =IFERROR(K69/J69,1) -> 0
B70: Imagine Bella Academy of Excellence | C70: T-Erate-MIBS-USAC Percentage | D70: T-Erate-MIBS-USAC Percentage 25/26 | E70: 180433OH | F70: 45932 | G70: 102.28 | H70: =+G70 -> 102.28 | J70: =SUMIFS('[1]Sept-August Comp OH'!$G$2:$G$154,'[1]Sept-August Comp OH'!$B$2:$B$154,'Oct Agreement Compare OH'!B70,'[1]Sept-August Comp OH'!$C$2:$C$154,'Oct Agreement Compare OH'!C70,'[1]Sept-August Comp OH'!$D$2:$D$154,'Oct Agreement Compare OH'!D70) -> 102.28 | K70: =+G70-J70 -> 0 | L70: =IFERROR(K70/J70,1) -> 0
B71: Imagine Bella Academy of Excellence | C71: T-Services-MSP | D71: T-Services-MSP 2024/2025 | E71: 180477OH | F71: 45931 | G71: 2294.86 | H71: =+G71 -> 2294.86 | J71: =SUMIFS('[1]Sept-August Comp OH'!$G$2:$G$154,'[1]Sept-August Comp OH'!$B$2:$B$154,'Oct Agreement Compare OH'!B71,'[1]Sept-August Comp OH'!$C$2:$C$154,'Oct Agreement Compare OH'!C71,'[1]Sept-August Comp OH'!$D$2:$D$154,'Oct Agreement Compare OH'!D71) -> 2293.41 | K71: =+G71-J71 -> 1.45 | L71: =IFERROR(K71/J71,1) -> 0.00063224631
B72: Imagine Bella Academy of Excellence Total | G72: =SUBTOTAL(9,G68:G71) -> 2625.19 | H72: =SUBTOTAL(9,H68:H71) -> 2625.19 | I72: =SUBTOTAL(9,I68:I71) -> 0 | J72: =SUBTOTAL(9,J68:J71) -> 2623.74
B73: Imagine Columbus Primary Academy | C73: Erate-MIBS-School Percentage | D73: Erate-MIBS-School Percentage 25/26 | E73: 180479OH | F73: 45931 | G73: 29.91 | H73: =+G73 -> 29.91 | J73: =SUMIFS('[1]Sept-August Comp OH'!$G$2:$G$154,'[1]Sept-August Comp OH'!$B$2:$B$154,'Oct Agreement Compare OH'!B73,'[1]Sept-August Comp OH'!$C$2:$C$154,'Oct Agreement Compare OH'!C73,'[1]Sept-August Comp OH'!$D$2:$D$154,'Oct Agreement Compare OH'!D73) -> 29.91 | K73: =+G73-J73 -> 0 | L73: =IFERROR(K73/J73,1) -> 0
B74: Imagine Columbus Primary Academy | C74: Recurring Resale - MSP | D74: Recurring Resale - MSP 25/26 | E74: 180478OH | F74: 45931 | G74: 249.8 | H74: =+G74 -> 249.8 | J74: =SUMIFS('[1]Sept-August Comp OH'!$G$2:$G$154,'[1]Sept-August Comp OH'!$B$2:$B$154,'Oct Agreement Compare OH'!B74,'[1]Sept-August Comp OH'!$C$2:$C$154,'Oct Agreement Compare OH'!C74,'[1]Sept-August Comp OH'!$D$2:$D$154,'Oct Agreement Compare OH'!D74) -> 249.8 | K74: =+G74-J74 -> 0 | L74: =IFERROR(K74/J74,1) -> 0
B75: Imagine Columbus Primary Academy | C75: Recurring Resale - Security | D75: Recurring Resale - Security 25/26 | E75: 180478OH | F75: 45931 | G75: 287 | H75: =+G75 -> 287 | J75: =SUMIFS('[1]Sept-August Comp OH'!$G$2:$G$154,'[1]Sept-August Comp OH'!$B$2:$B$154,'Oct Agreement Compare OH'!B75,'[1]Sept-August Comp OH'!$C$2:$C$154,'Oct Agreement Compare OH'!C75,'[1]Sept-August Comp OH'!$D$2:$D$154,'Oct Agreement Compare OH'!D75) -> 294 | K75: =+G75-J75 -> -7 | L75: =IFERROR(K75/J75,1) -> -0.023809524
B76: Imagine Columbus Primary Academy | C76: T-Erate-MIBS-USAC Percentage | D76: T-Erate-MIBS-USAC Percentage 25/26 | E76: 180434OH | F76: 45932 | G76: 169.5 | H76: =+G76 -> 169.5 | J76: =SUMIFS('[1]Sept-August Comp OH'!$G$2:$G$154,'[1]Sept-August Comp OH'!$B$2:$B$154,'Oct Agreement Compare OH'!B76,'[1]Sept-August Comp OH'!$C$2:$C$154,'Oct Agreement Compare OH'!C76,'[1]Sept-August Comp OH'!$D$2:$D$154,'Oct Agreement Compare OH'!D76) -> 169.5 | K76: =+G76-J76 -> 0 | L76: =IFERROR(K76/J76,1) -> 0
B77: Imagine Columbus Primary Academy | C77: T-Services-MSP | D77: T-Services-MSP 25/26 | E77: 180478OH | F77: 45931 | G77: 2305 | H77: =+G77 -> 2305 | J77: =SUMIFS('[1]Sept-August Comp OH'!$G$2:$G$154,'[1]Sept-August Comp OH'!$B$2:$B$154,'Oct Agreement Compare OH'!B77,'[1]Sept-August Comp OH'!$C$2:$C$154,'Oct Agreement Compare OH'!C77,'[1]Sept-August Comp OH'!$D$2:$D$154,'Oct Agreement Compare OH'!D77) -> 2305 | K77: =+G77-J77 -> 0 | L77: =IFERROR(K77/J77,1) -> 0
B78: Imagine Columbus Primary Academy Total | G78: =SUBTOTAL(9,G73:G77) -> 3041.21 | H78: =SUBTOTAL(9,H73:H77) -> 3041.21 | I78: =SUBTOTAL(9,I73:I77) -> 0 | J78: =SUBTOTAL(9,J73:J77) -> 3048.21
B79: Imagine Great Western Academy | C79: Erate-MIBS-School Percentage | D79: Erate-MIBS-School Percentage 25/26 | E79: 180480OH | F79: 45931 | G79: 101.59 | H79: =+G79 -> 101.59 | J79: =SUMIFS('[1]Sept-August Comp OH'!$G$2:$G$154,'[1]Sept-August Comp OH'!$B$2:$B$154,'Oct Agreement Compare OH'!B79,'[1]Sept-August Comp OH'!$C$2:$C$154,'Oct Agreement Compare OH'!C79,'[1]Sept-August Comp OH'!$D$2:$D$154,'Oct Agreement Compare OH'!D79) -> 101.59 | K79: =+G79-J79 -> 0 | L79: =IFERROR(K79/J79,1) -> 0
B80: Imagine Great Western Academy | C80: Recurring Resale - MSP | D80: Recurring Resale - MSP 25/26 | E80: 180482OH | F80: 45931 | G80: 49.8 | H80: =+G80 -> 49.8 | J80: =SUMIFS('[1]Sept-August Comp OH'!$G$2:$G$154,'[1]Sept-August Comp OH'!$B$2:$B$154,'Oct Agreement Compare OH'!B80,'[1]Sept-August Comp OH'!$C$2:$C$154,'Oct Agreement Compare OH'!C80,'[1]Sept-August Comp OH'!$D$2:$D$154,'Oct Agreement Compare OH'!D80) -> 49.8 | K80: =+G80-J80 -> 0 | L80: =IFERROR(K80/J80,1) -> 0
B81: Imagine Great Western Academy | C81: Recurring Resale - MSP | D81: Recurring Resale - MSP 25/26B | E81: 180481OH | F81: 45931 | G81: 28.77 | H81: =+G81 -> 28.77 | J81: =SUMIFS('[1]Sept-August Comp OH'!$G$2:$G$154,'[1]Sept-August Comp OH'!$B$2:$B$154,'Oct Agreement Compare OH'!B81,'[1]Sept-August Comp OH'!$C$2:$C$154,'Oct Agreement Compare OH'!C81,'[1]Sept-August Comp OH'!$D$2:$D$154,'Oct Agreement Compare OH'!D81) -> 28.77 | K81: =+G81-J81 -> 0 | L81: =IFERROR(K81/J81,1) -> 0
B82: Imagine Great Western Academy | C82: T-Erate-MIBS-USAC Percentage | D82: T-Erate-MIBS-USAC Percentage 25/26 | E82: 180435OH | F82: 45932 | G82: 575.66 | H82: =+G82 -> 575.66 | J82: =SUMIFS('[1]Sept-August Comp OH'!$G$2:$G$154,'[1]Sept-August Comp OH'!$B$2:$B$154,'Oct Agreement Compare OH'!B82,'[1]Sept-August Comp OH'!$C$2:$C$154,'Oct Agreement Compare OH'!C82,'[1]Sept-August Comp OH'!$D$2:$D$154,'Oct Agreement Compare OH'!D82) -> 575.66 | K82: =+G82-J82 -> 0 | L82: =IFERROR(K82/J82,1) -> 0
B83: Imagine Great Western Academy | C83: T-Services-MSP | D83: 2021/2023 MSC | E83: 180482OH | F83: 45931 | G83: 6204.11 | H83: =+G83 -> 6204.11 | J83: =SUMIFS('[1]Sept-August Comp OH'!$G$2:$G$154,'[1]Sept-August Comp OH'!$B$2:$B$154,'Oct Agreement Compare OH'!B83,'[1]Sept-August Comp OH'!$C$2:$C$154,'Oct Agreement Compare OH'!C83,'[1]Sept-August Comp OH'!$D$2:$D$154,'Oct Agreement Compare OH'!D83) -> 6204.11 | K83: =+G83-J83 -> 0 | L83: =IFERROR(K83/J83,1) -> 0
B84: Imagine Great Western Academy Total | G84: =SUBTOTAL(9,G79:G83) -> 6959.93 | H84: =SUBTOTAL(9,H79:H83) -> 6959.93 | I84: =SUBTOTAL(9,I79:I83) -> 0 | J84: =SUBTOTAL(9,J79:J83) -> 6959.93
B85: Imagine Groveport Community School | C85: Erate-MIBS-School Percentage | D85: Erate-MIBS-School Percentage 25/26 | E85: 180484OH | F85: 45931 | G85: 111.6 | H85: =+G85 -> 111.6 | J85: =SUMIFS('[1]Sept-August Comp OH'!$G$2:$G$154,'[1]Sept-August Comp OH'!$B$2:$B$154,'Oct Agreement Compare OH'!B85,'[1]Sept-August Comp OH'!$C$2:$C$154,'Oct Agreement Compare OH'!C85,'[1]Sept-August Comp OH'!$D$2:$D$154,'Oct Agreement Compare OH'!D85) -> 111.6 | K85: =+G85-J85 -> 0 | L85: =IFERROR(K85/J85,1) -> 0
B86: Imagine Groveport Community School | C86: Recurring Resale - Security | D86: Recurring Resale - Security | E86: 180483OH | F86: 45931 | G86: 1050 | H86: =+G86 -> 1050 | J86: =SUMIFS('[1]Sept-August Comp OH'!$G$2:$G$154,'[1]Sept-August Comp OH'!$B$2:$B$154,'Oct Agreement Compare OH'!B86,'[1]Sept-August Comp OH'!$C$2:$C$154,'Oct Agreement Compare OH'!C86,'[1]Sept-August Comp OH'!$D$2:$D$154,'Oct Agreement Compare OH'!D86) -> 1020.5 | K86: =+G86-J86 -> 29.5 | L86: =IFERROR(K86/J86,1) -> 0.028907398
B87: Imagine Groveport Community School | C87: T-Erate-MIBS-USAC Percentage | D87: T-Erate-MIBS-USAC Percentage 25/26 | E87: 180436OH | F87: 45932 | G87: 632.4 | H87: =+G87 -> 632.4 | J87: =SUMIFS('[1]Sept-August Comp OH'!$G$2:$G$154,'[1]Sept-August Comp OH'!$B$2:$B$154,'Oct Agreement Compare OH'!B87,'[1]Sept-August Comp OH'!$C$2:$C$154,'Oct Agreement Compare OH'!C87,'[1]Sept-August Comp OH'!$D$2:$D$154,'Oct Agreement Compare OH'!D87) -> 632.4 | K87: =+G87-J87 -> 0 | L87: =IFERROR(K87/J87,1) -> 0
B88: Imagine Groveport Community School | C88: T-Services-MSP | D88: 2021/2023 MSC | E88: 180483OH | F88: 45931 | G88: 6462.96 | H88: =+G88 -> 6462.96 | J88: =SUMIFS('[1]Sept-August Comp OH'!$G$2:$G$154,'[1]Sept-August Comp OH'!$B$2:$B$154,'Oct Agreement Compare OH'!B88,'[1]Sept-August Comp OH'!$C$2:$C$154,'Oct Agreement Compare OH'!C88,'[1]Sept-August Comp OH'!$D$2:$D$154,'Oct Agreement Compare OH'!D88) -> 6462.96 | K88: =+G88-J88 -> 0 | L88: =IFERROR(K88/J88,1) -> 0
B89: Imagine Groveport Community School Total | G89: =SUBTOTAL(9,G85:G88) -> 8256.96 | H89: =SUBTOTAL(9,H85:H88) -> 8256.96 | I89: =SUBTOTAL(9,I85:I88) -> 0 | J89: =SUBTOTAL(9,J85:J88) -> 8227.46
B90: Imagine Klepinger Rd | C90: Recurring Resale - MSP | D90: Recurring Resale - MSP 25/26 | E90: 180485OH | F90: 45931 | G90: 475.7922 | H90: =+G90 -> 475.7922 | J90: =SUMIFS('[1]Sept-August Comp OH'!$G$2:$G$154,'[1]Sept-August Comp OH'!$B$2:$B$154,'Oct Agreement Compare OH'!B90,'[1]Sept-August Comp OH'!$C$2:$C$154,'Oct Agreement Compare OH'!C90,'[1]Sept-August Comp OH'!$D$2:$D$154,'Oct Agreement Compare OH'!D90) -> 475.7922 | K90: =+G90-J90 -> 0 | L90: =IFERROR(K90/J90,1) -> 0
B91: Imagine Klepinger Rd | C91: Recurring Resale - Security | D91: Recurring Resale - Security 25/26 | E91: 180485OH | F91: 45931 | G91: 308 | H91: =+G91 -> 308 | J91: =SUMIFS('[1]Sept-August Comp OH'!$G$2:$G$154,'[1]Sept-August Comp OH'!$B$2:$B$154,'Oct Agreement Compare OH'!B91,'[1]Sept-August Comp OH'!$C$2:$C$154,'Oct Agreement Compare OH'!C91,'[1]Sept-August Comp OH'!$D$2:$D$154,'Oct Agreement Compare OH'!D91) -> 308 | K91: =+G91-J91 -> 0 | L91: =IFERROR(K91/J91,1) -> 0
B92: Imagine Klepinger Rd | C92: T-Services-MSP | D92: T-Services-MSP 25/26 | E92: 180485OH | F92: 45931 | G92: 3825.75 | H92: =+G92 -> 3825.75 | J92: =SUMIFS('[1]Sept-August Comp OH'!$G$2:$G$154,'[1]Sept-August Comp OH'!$B$2:$B$154,'Oct Agreement Compare OH'!B92,'[1]Sept-August Comp OH'!$C$2:$C$154,'Oct Agreement Compare OH'!C92,'[1]Sept-August Comp OH'!$D$2:$D$154,'Oct Agreement Compare OH'!D92) -> 3825.75 | K92: =+G92-J92 -> 0 | L92: =IFERROR(K92/J92,1) -> 0
B93: Imagine Klepinger Rd Total | G93: =SUBTOTAL(9,G90:G92) -> 4609.5422 | H93: =SUBTOTAL(9,H90:H92) -> 4609.5422 | I93: =SUBTOTAL(9,I90:I92) -> 0 | J93: =SUBTOTAL(9,J90:J92) -> 4609.5422
B94: Imagine Leadership Academy | C94: Erate-MIBS-School Percentage | D94: Erate-MIBS-School Percentage 25/26 | E94: 180487OH | F94: 45931 | G94: 2.83 | H94: =+G94 -> 2.83 | J94: =SUMIFS('[1]Sept-August Comp OH'!$G$2:$G$154,'[1]Sept-August Comp OH'!$B$2:$B$154,'Oct Agreement Compare OH'!B94,'[1]Sept-August Comp OH'!$C$2:$C$154,'Oct Agreement Compare OH'!C94,'[1]Sept-August Comp OH'!$D$2:$D$154,'Oct Agreement Compare OH'!D94) -> 2.83 | K94: =+G94-J94 -> 0 | L94: =IFERROR(K94/J94,1) -> 0
B95: Imagine Leadership Academy | C95: Recurring Resale - MSP | D95: 24/25 Recurring Resale - MSP | E95: 180486OH | F95: 45931 | G95: 126.1718 | H95: =+G95 -> 126.1718 | J95: =SUMIFS('[1]Sept-August Comp OH'!$G$2:$G$154,'[1]Sept-August Comp OH'!$B$2:$B$154,'Oct Agreement Compare OH'!B95,'[1]Sept-August Comp OH'!$C$2:$C$154,'Oct Agreement Compare OH'!C95,'[1]Sept-August Comp OH'!$D$2:$D$154,'Oct Agreement Compare OH'!D95) -> 62.8026 | K95: =+G95-J95 -> 63.3692 | L95: =IFERROR(K95/J95,1) -> 1.0090219
B96: Imagine Leadership Academy | C96: Recurring Resale - Security | D96: 24/25 Recurring Resale - Security | E96: 180486OH | F96: 45931 | G96: 147 | H96: =+G96 -> 147 | J96: =SUMIFS('[1]Sept-August Comp OH'!$G$2:$G$154,'[1]Sept-August Comp OH'!$B$2:$B$154,'Oct Agreement Compare OH'!B96,'[1]Sept-August Comp OH'!$C$2:$C$154,'Oct Agreement Compare OH'!C96,'[1]Sept-August Comp OH'!$D$2:$D$154,'Oct Agreement Compare OH'!D96) -> 126 | K96: =+G96-J96 -> 21 | L96: =IFERROR(K96/J96,1) -> 0.16666667
B97: Imagine Leadership Academy | C97: T-Erate-MIBS-USAC Percentage | D97: T-Erate-MIBS-USAC Percentage 25/26 | E97: 180437OH | F97: 45932 | G97: 16.25 | H97: =+G97 -> 16.25 | J97: =SUMIFS('[1]Sept-August Comp OH'!$G$2:$G$154,'[1]Sept-August Comp OH'!$B$2:$B$154,'Oct Agreement Compare OH'!B97,'[1]Sept-August Comp OH'!$C$2:$C$154,'Oct Agreement Compare OH'!C97,'[1]Sept-August Comp OH'!$D$2:$D$154,'Oct Agreement Compare OH'!D97) -> 16.25 | K97: =+G97-J97 -> 0 | L97: =IFERROR(K97/J97,1) -> 0
B98: Imagine Leadership Academy | C98: T-Services-MSP | D98: 24/25 T-Services-MSP | E98: 180486OH | F98: 45931 | G98: 2143.53 | H98: =+G98 -> 2143.53 | J98: =SUMIFS('[1]Sept-August Comp OH'!$G$2:$G$154,'[1]Sept-August Comp OH'!$B$2:$B$154,'Oct Agreement Compare OH'!B98,'[1]Sept-August Comp OH'!$C$2:$C$154,'Oct Agreement Compare OH'!C98,'[1]Sept-August Comp OH'!$D$2:$D$154,'Oct Agreement Compare OH'!D98) -> 2143.53 | K98: =+G98-J98 -> 0 | L98: =IFERROR(K98/J98,1) -> 0
B99: Imagine Leadership Academy Total | G99: =SUBTOTAL(9,G94:G98) -> 2435.7818 | H99: =SUBTOTAL(9,H94:H98) -> 2435.7818 | I99: =SUBTOTAL(9,I94:I98) -> 0 | J99: =SUBTOTAL(9,J94:J98) -> 2351.4126
B100: Imagine Madison Ave | C100: Erate-MIBS-School Percentage | D100: Erate-MIBS-School Percentage 25/26 | E100: 180489OH | F100: 45931 | G100: 20.29 | H100: =+G100 -> 20.29 | J100: =SUMIFS('[1]Sept-August Comp OH'!$G$2:$G$154,'[1]Sept-August Comp OH'!$B$2:$B$154,'Oct Agreement Compare OH'!B100,'[1]Sept-August Comp OH'!$C$2:$C$154,'Oct Agreement Compare OH'!C100,'[1]Sept-August Comp OH'!$D$2:$D$154,'Oct Agreement Compare OH'!D100) -> 20.29 | K100: =+G100-J100 -> 0 | L100: =IFERROR(K100/J100,1) -> 0
...

Sheet Oct Agreement Compare CA
A1: Location | B1: Customer | C1: Agreement Type | D1: Agreement Name | E1: Invoice Number | F1: Invoice Date | G1: October Financials | H1: October Revenue | I1: September Clawback | J1: September Financials | K1: Difference October - September | L1: % Change | M1: Notes
B2: 24 Hour Home Care | C2: Recurring Resale - Microsoft 365 NCE | D2: Recurring Resale - Microsoft 365 NCE | E2: 180325 | F2: 45931 | G2: 31614.3 | H2: =+G2 -> 31614.3 | J2: =SUMIFS('[2]Sep-Aug Comp CA'!$G$1:$G$498,'[2]Sep-Aug Comp CA'!$B$1:$B$498,'Oct Agreement Compare CA'!B2,'[2]Sep-Aug Comp CA'!$C$1:$C$498,'Oct Agreement Compare CA'!C2,'[2]Sep-Aug Comp CA'!$D$1:$D$498,'Oct Agreement Compare CA'!D2) -> 0 | K2: =+G2-J2 -> 31614.3 | L2: =+K2/J2 -> #DIV/0!
B3: 24 Hour Home Care | C3: Recurring Resale - MSP | D3: Recurring Resale - MSP 2024/27 | E3: 180324 | F3: 45931 | G3: 1003.0806 | H3: =+G3 -> 1003.0806 | J3: =SUMIFS('[2]Sep-Aug Comp CA'!$G$1:$G$498,'[2]Sep-Aug Comp CA'!$B$1:$B$498,'Oct Agreement Compare CA'!B3,'[2]Sep-Aug Comp CA'!$C$1:$C$498,'Oct Agreement Compare CA'!C3,'[2]Sep-Aug Comp CA'!$D$1:$D$498,'Oct Agreement Compare CA'!D3) -> 989.6244 | K3: =+G3-J3 -> 13.4562 | L3: =+K3/J3 -> 0.01359728
B4: 24 Hour Home Care | C4: Recurring Resale - Security | D4: Recurring Resale - Security | E4: 180324 | F4: 45931 | G4: 11764 | H4: =+G4 -> 11764 | J4: =SUMIFS('[2]Sep-Aug Comp CA'!$G$1:$G$498,'[2]Sep-Aug Comp CA'!$B$1:$B$498,'Oct Agreement Compare CA'!B4,'[2]Sep-Aug Comp CA'!$C$1:$C$498,'Oct Agreement Compare CA'!C4,'[2]Sep-Aug Comp CA'!$D$1:$D$498,'Oct Agreement Compare CA'!D4) -> 11618 | K4: =+G4-J4 -> 146 | L4: =+K4/J4 -> 0.012566707
B5: 24 Hour Home Care | C5: T-Services-MSP | D5: T-Services-MSP | E5: 180324 | F5: 45931 | G5: 28950 | H5: =+G5 -> 28950 | J5: =SUMIFS('[2]Sep-Aug Comp CA'!$G$1:$G$498,'[2]Sep-Aug Comp CA'!$B$1:$B$498,'Oct Agreement Compare CA'!B5,'[2]Sep-Aug Comp CA'!$C$1:$C$498,'Oct Agreement Compare CA'!C5,'[2]Sep-Aug Comp CA'!$D$1:$D$498,'Oct Agreement Compare CA'!D5) -> 28675 | K5: =+G5-J5 -> 275 | L5: =+K5/J5 -> 0.0095902354
B6: 24 Hour Home Care Total | G6: =SUBTOTAL(9,G2:G5) -> 73331.381 | H6: =SUBTOTAL(9,H2:H5) -> 73331.381 | I6: =SUBTOTAL(9,I2:I5) -> 0 | J6: =SUBTOTAL(9,J2:J5) -> 41282.624 | K6: =+G6-J6 -> 32048.756 | L6: =+K6/J6 -> 0.77632555
B7: 7C Escrow | C7: Cloud - Private | D7: Cloud - Private | E7: 180748 | F7: 45945 | G7: 954.1 | H7: =+G7 -> 954.1 | J7: =SUMIFS('[2]Sep-Aug Comp CA'!$G$1:$G$498,'[2]Sep-Aug Comp CA'!$B$1:$B$498,'Oct Agreement Compare CA'!B7,'[2]Sep-Aug Comp CA'!$C$1:$C$498,'Oct Agreement Compare CA'!C7,'[2]Sep-Aug Comp CA'!$D$1:$D$498,'Oct Agreement Compare CA'!D7) -> 954.1 | K7: =+G7-J7 -> 0 | L7: =+K7/J7 -> 0
B8: 7C Escrow | C8: Recurring Resale - MSP | D8: Recurring Resale - MSP | E8: 180748 | F8: 45945 | G8: 28.38 | H8: =+G8 -> 28.38 | J8: =SUMIFS('[2]Sep-Aug Comp CA'!$G$1:$G$498,'[2]Sep-Aug Comp CA'!$B$1:$B$498,'Oct Agreement Compare CA'!B8,'[2]Sep-Aug Comp CA'!$C$1:$C$498,'Oct Agreement Compare CA'!C8,'[2]Sep-Aug Comp CA'!$D$1:$D$498,'Oct Agreement Compare CA'!D8) -> 28.38 | K8: =+G8-J8 -> 0 | L8: =+K8/J8 -> 0
B9: 7C Escrow | C9: Recurring Resale - Security | D9: Recurring Resale - Security | E9: 180748 | F9: 45945 | G9: 330.5 | H9: =+G9 -> 330.5 | J9: =SUMIFS('[2]Sep-Aug Comp CA'!$G$1:$G$498,'[2]Sep-Aug Comp CA'!$B$1:$B$498,'Oct Agreement Compare CA'!B9,'[2]Sep-Aug Comp CA'!$C$1:$C$498,'Oct Agreement Compare CA'!C9,'[2]Sep-Aug Comp CA'!$D$1:$D$498,'Oct Agreement Compare CA'!D9) -> 330.5 | K9: =+G9-J9 -> 0 | L9: =+K9/J9 -> 0
B10: 7C Escrow | C10: T-Services-MSP | D10: T-Services-MSP | E10: 180748 | F10: 45945 | G10: 351.5 | H10: =+G10 -> 351.5 | J10: =SUMIFS('[2]Sep-Aug Comp CA'!$G$1:$G$498,'[2]Sep-Aug Comp CA'!$B$1:$B$498,'Oct Agreement Compare CA'!B10,'[2]Sep-Aug Comp CA'!$C$1:$C$498,'Oct Agreement Compare CA'!C10,'[2]Sep-Aug Comp CA'!$D$1:$D$498,'Oct Agreement Compare CA'!D10) -> 351.5 | K10: =+G10-J10 -> 0 | L10: =+K10/J10 -> 0
B11: 7C Escrow Total | G11: =SUBTOTAL(9,G7:G10) -> 1664.48 | H11: =SUBTOTAL(9,H7:H10) -> 1664.48 | I11: =SUBTOTAL(9,I7:I10) -> 0 | J11: =SUBTOTAL(9,J7:J10) -> 1664.48 | K11: =+G11-J11 -> 0 | L11: =+K11/J11 -> 0
B12: Abest Professional Health Care | C12: Recurring Resale - Microsoft 365 NCE | D12: Recurring Resale - Microsoft 365 NCE | E12: 180326 | F12: 45931 | G12: 484 | H12: =+G12 -> 484 | J12: =SUMIFS('[2]Sep-Aug Comp CA'!$G$1:$G$498,'[2]Sep-Aug Comp CA'!$B$1:$B$498,'Oct Agreement Compare CA'!B12,'[2]Sep-Aug Comp CA'!$C$1:$C$498,'Oct Agreement Compare CA'!C12,'[2]Sep-Aug Comp CA'!$D$1:$D$498,'Oct Agreement Compare CA'!D12) -> 484 | K12: =+G12-J12 -> 0 | L12: =+K12/J12 -> 0
B13: Abest Professional Health Care | C13: Recurring Resale - MSP | D13: Recurring Resale - MSP 2025/27 | E13: 180326 | F13: 45931 | G13: 158 | H13: =+G13 -> 158 | J13: =SUMIFS('[2]Sep-Aug Comp CA'!$G$1:$G$498,'[2]Sep-Aug Comp CA'!$B$1:$B$498,'Oct Agreement Compare CA'!B13,'[2]Sep-Aug Comp CA'!$C$1:$C$498,'Oct Agreement Compare CA'!C13,'[2]Sep-Aug Comp CA'!$D$1:$D$498,'Oct Agreement Compare CA'!D13) -> 158 | K13: =+G13-J13 -> 0 | L13: =+K13/J13 -> 0
B14: Abest Professional Health Care | C14: Recurring Resale - MSP | D14: Temp Backups Agreement | E14: 180326 | F14: 45931 | G14: 289.356 | H14: =+G14 -> 289.356 | J14: =SUMIFS('[2]Sep-Aug Comp CA'!$G$1:$G$498,'[2]Sep-Aug Comp CA'!$B$1:$B$498,'Oct Agreement Compare CA'!B14,'[2]Sep-Aug Comp CA'!$C$1:$C$498,'Oct Agreement Compare CA'!C14,'[2]Sep-Aug Comp CA'!$D$1:$D$498,'Oct Agreement Compare CA'!D14) -> 292.7244 | K14: =+G14-J14 -> -3.3684 | L14: =+K14/J14 -> -0.011507069
B15: Abest Professional Health Care | C15: Recurring Resale - Security | D15: Recurring Resale - Security 2025/27 | E15: 180326 | F15: 45931 | G15: 117 | H15: =+G15 -> 117 | J15: =SUMIFS('[2]Sep-Aug Comp CA'!$G$1:$G$498,'[2]Sep-Aug Comp CA'!$B$1:$B$498,'Oct Agreement Compare CA'!B15,'[2]Sep-Aug Comp CA'!$C$1:$C$498,'Oct Agreement Compare CA'!C15,'[2]Sep-Aug Comp CA'!$D$1:$D$498,'Oct Agreement Compare CA'!D15) -> 133 | K15: =+G15-J15 -> -16 | L15: =+K15/J15 -> -0.12030075
B16: Abest Professional Health Care | C16: T-Services-MSP | D16: T-Services-MSP 2024/27 | E16: 180326 | F16: 45931 | G16: 615.004 | H16: =+G16 -> 615.004 | J16: =SUMIFS('[2]Sep-Aug Comp CA'!$G$1:$G$498,'[2]Sep-Aug Comp CA'!$B$1:$B$498,'Oct Agreement Compare CA'!B16,'[2]Sep-Aug Comp CA'!$C$1:$C$498,'Oct Agreement Compare CA'!C16,'[2]Sep-Aug Comp CA'!$D$1:$D$498,'Oct Agreement Compare CA'!D16) -> 560 | K16: =+G16-J16 -> 55.004 | L16: =+K16/J16 -> 0.098221429
B17: Abest Professional Health Care Total | G17: =SUBTOTAL(9,G12:G16) -> 1663.36 | H17: =SUBTOTAL(9,H12:H16) -> 1663.36 | I17: =SUBTOTAL(9,I12:I16) -> 0 | J17: =SUBTOTAL(9,J12:J16) -> 1627.7244 | K17: =+G17-J17 -> 35.6356 | L17: =+K17/J17 -> 0.021892895
B18: ABI Healthcare | C18: Recurring Resale - Microsoft 365 NCE | D18: Recurring Resale - Microsoft 365 NCE | E18: 180327 | F18: 45931 | G18: 3358.53 | H18: =+G18 -> 3358.53 | J18: =SUMIFS('[2]Sep-Aug Comp CA'!$G$1:$G$498,'[2]Sep-Aug Comp CA'!$B$1:$B$498,'Oct Agreement Compare CA'!B18,'[2]Sep-Aug Comp CA'!$C$1:$C$498,'Oct Agreement Compare CA'!C18,'[2]Sep-Aug Comp CA'!$D$1:$D$498,'Oct Agreement Compare CA'!D18) -> 3358.53 | K18: =+G18-J18 -> 0 | L18: =+K18/J18 -> 0
B19: ABI Healthcare | C19: Recurring Resale - MSP | D19: MSP -Recurring Resale | E19: 180327 | F19: 45931 | G19: 10.5 | H19: =+G19 -> 10.5 | J19: =SUMIFS('[2]Sep-Aug Comp CA'!$G$1:$G$498,'[2]Sep-Aug Comp CA'!$B$1:$B$498,'Oct Agreement Compare CA'!B19,'[2]Sep-Aug Comp CA'!$C$1:$C$498,'Oct Agreement Compare CA'!C19,'[2]Sep-Aug Comp CA'!$D$1:$D$498,'Oct Agreement Compare CA'!D19) -> 10.5 | K19: =+G19-J19 -> 0 | L19: =+K19/J19 -> 0
B20: ABI Healthcare | C20: Recurring Resale - Security | D20: Recurring Resale - Security | E20: 180327 | F20: 45931 | G20: 5357 | H20: =+G20 -> 5357 | J20: =SUMIFS('[2]Sep-Aug Comp CA'!$G$1:$G$498,'[2]Sep-Aug Comp CA'!$B$1:$B$498,'Oct Agreement Compare CA'!B20,'[2]Sep-Aug Comp CA'!$C$1:$C$498,'Oct Agreement Compare CA'!C20,'[2]Sep-Aug Comp CA'!$D$1:$D$498,'Oct Agreement Compare CA'!D20) -> 5390 | K20: =+G20-J20 -> -33 | L20: =+K20/J20 -> -0.006122449
B21: ABI Healthcare | C21: T-Services-MSP | D21: T-Services-MSP | E21: 180327 | F21: 45931 | G21: 9032 | H21: =+G21 -> 9032 | J21: =SUMIFS('[2]Sep-Aug Comp CA'!$G$1:$G$498,'[2]Sep-Aug Comp CA'!$B$1:$B$498,'Oct Agreement Compare CA'!B21,'[2]Sep-Aug Comp CA'!$C$1:$C$498,'Oct Agreement Compare CA'!C21,'[2]Sep-Aug Comp CA'!$D$1:$D$498,'Oct Agreement Compare CA'!D21) -> 9286 | K21: =+G21-J21 -> -254 | L21: =+K21/J21 -> -0.027353005
B22: ABI Healthcare Total | G22: =SUBTOTAL(9,G18:G21) -> 17758.03 | H22: =SUBTOTAL(9,H18:H21) -> 17758.03 | I22: =SUBTOTAL(9,I18:I21) -> 0 | J22: =SUBTOTAL(9,J18:J21) -> 18045.03 | K22: =+G22-J22 -> -287 | L22: =+K22/J22 -> -0.015904656
B23: ABIFI Professional Health Care | C23: Recurring Resale - Microsoft 365 NCE | D23: Recurring Resale - Microsoft 365 NCE | E23: 180328 | F23: 45931 | G23: 1219.2 | H23: =+G23 -> 1219.2 | J23: =SUMIFS('[2]Sep-Aug Comp CA'!$G$1:$G$498,'[2]Sep-Aug Comp CA'!$B$1:$B$498,'Oct Agreement Compare CA'!B23,'[2]Sep-Aug Comp CA'!$C$1:$C$498,'Oct Agreement Compare CA'!C23,'[2]Sep-Aug Comp CA'!$D$1:$D$498,'Oct Agreement Compare CA'!D23) -> 1598.4 | K23: =+G23-J23 -> -379.2 | L23: =+K23/J23 -> -0.23723724
B24: ABIFI Professional Health Care | C24: Recurring Resale - MSP | D24: Recurring Resale - MSP 2024/27 | E24: 180328 | F24: 45931 | G24: 380.4734 | H24: =+G24 -> 380.4734 | J24: =SUMIFS('[2]Sep-Aug Comp CA'!$G$1:$G$498,'[2]Sep-Aug Comp CA'!$B$1:$B$498,'Oct Agreement Compare CA'!B24,'[2]Sep-Aug Comp CA'!$C$1:$C$498,'Oct Agreement Compare CA'!C24,'[2]Sep-Aug Comp CA'!$D$1:$D$498,'Oct Agreement Compare CA'!D24) -> 370.0562 | K24: =+G24-J24 -> 10.4172 | L24: =+K24/J24 -> 0.028150319
B25: ABIFI Professional Health Care | C25: Recurring Resale - Security | D25: Recurring Resale - Security 2024/27 | E25: 180328 | F25: 45931 | G25: 1006 | H25: =+G25 -> 1006 | J25: =SUMIFS('[2]Sep-Aug Comp CA'!$G$1:$G$498,'[2]Sep-Aug Comp CA'!$B$1:$B$498,'Oct Agreement Compare CA'!B25,'[2]Sep-Aug Comp CA'!$C$1:$C$498,'Oct Agreement Compare CA'!C25,'[2]Sep-Aug Comp CA'!$D$1:$D$498,'Oct Agreement Compare CA'!D25) -> 1020 | K25: =+G25-J25 -> -14 | L25: =+K25/J25 -> -0.01372549
B26: ABIFI Professional Health Care | C26: T-Services-MSP | D26: T-Services-MSP | E26: 180328 | F26: 45931 | G26: 820 | H26: =+G26 -> 820 | J26: =SUMIFS('[2]Sep-Aug Comp CA'!$G$1:$G$498,'[2]Sep-Aug Comp CA'!$B$1:$B$498,'Oct Agreement Compare CA'!B26,'[2]Sep-Aug Comp CA'!$C$1:$C$498,'Oct Agreement Compare CA'!C26,'[2]Sep-Aug Comp CA'!$D$1:$D$498,'Oct Agreement Compare CA'!D26) -> 967.0038 | K26: =+G26-J26 -> -147.0038 | L26: =+K26/J26 -> -0.15201988
B27: ABIFI Professional Health Care Total | G27: =SUBTOTAL(9,G23:G26) -> 3425.6734 | H27: =SUBTOTAL(9,H23:H26) -> 3425.6734 | I27: =SUBTOTAL(9,I23:I26) -> 0 | J27: =SUBTOTAL(9,J23:J26) -> 3955.46 | K27: =+G27-J27 -> -529.7866 | L27: =+K27/J27 -> -0.13393805
B28: Ability Ambeck Mortgage | C28: Recurring Resale - Microsoft 365 NCE | D28: Ability Microsoft 365 | E28: 180330 | F28: 45931 | G28: 1016 | H28: =+G28 -> 1016 | J28: =SUMIFS('[2]Sep-Aug Comp CA'!$G$1:$G$498,'[2]Sep-Aug Comp CA'!$B$1:$B$498,'Oct Agreement Compare CA'!B28,'[2]Sep-Aug Comp CA'!$C$1:$C$498,'Oct Agreement Compare CA'!C28,'[2]Sep-Aug Comp CA'!$D$1:$D$498,'Oct Agreement Compare CA'!D28) -> 994 | K28: =+G28-J28 -> 22 | L28: =+K28/J28 -> 0.022132797
B29: Ability Ambeck Mortgage | C29: Recurring Resale - MSP | D29: Recurring Resale - MSP | E29: 180330 | F29: 45931 | G29: 625.51 | H29: =+G29 -> 625.51 | J29: =SUMIFS('[2]Sep-Aug Comp CA'!$G$1:$G$498,'[2]Sep-Aug Comp CA'!$B$1:$B$498,'Oct Agreement Compare CA'!B29,'[2]Sep-Aug Comp CA'!$C$1:$C$498,'Oct Agreement Compare CA'!C29,'[2]Sep-Aug Comp CA'!$D$1:$D$498,'Oct Agreement Compare CA'!D29) -> 625.51 | K29: =+G29-J29 -> 0 | L29: =+K29/J29 -> 0
B30: Ability Ambeck Mortgage | C30: Recurring Resale - MSP | D30: Recurring Resale - MSP 25/26 | E30: 180329 | F30: 45931 | G30: 7.4 | H30: =+G30 -> 7.4 | J30: =SUMIFS('[2]Sep-Aug Comp CA'!$G$1:$G$498,'[2]Sep-Aug Comp CA'!$B$1:$B$498,'Oct Agreement Compare CA'!B30,'[2]Sep-Aug Comp CA'!$C$1:$C$498,'Oct Agreement Compare CA'!C30,'[2]Sep-Aug Comp CA'!$D$1:$D$498,'Oct Agreement Compare CA'!D30) -> 7.4 | K30: =+G30-J30 -> 0 | L30: =+K30/J30 -> 0
B31: Ability Ambeck Mortgage | C31: Recurring Resale - Security | D31: Ability - Recurring Resale - Security | E31: 180330 | F31: 45931 | G31: 838 | H31: =+G31 -> 838 | J31: =SUMIFS('[2]Sep-Aug Comp CA'!$G$1:$G$498,'[2]Sep-Aug Comp CA'!$B$1:$B$498,'Oct Agreement Compare CA'!B31,'[2]Sep-Aug Comp CA'!$C$1:$C$498,'Oct Agreement Compare CA'!C31,'[2]Sep-Aug Comp CA'!$D$1:$D$498,'Oct Agreement Compare CA'!D31) -> 850 | K31: =+G31-J31 -> -12 | L31: =+K31/J31 -> -0.014117647
B32: Ability Ambeck Mortgage | C32: T-Services-MSP | D32: Ability-Managed | E32: 180330 | F32: 45931 | G32: 855.2 | H32: =+G32 -> 855.2 | J32: =SUMIFS('[2]Sep-Aug Comp CA'!$G$1:$G$498,'[2]Sep-Aug Comp CA'!$B$1:$B$498,'Oct Agreement Compare CA'!B32,'[2]Sep-Aug Comp CA'!$C$1:$C$498,'Oct Agreement Compare CA'!C32,'[2]Sep-Aug Comp CA'!$D$1:$D$498,'Oct Agreement Compare CA'!D32) -> 855.2 | K32: =+G32-J32 -> 0 | L32: =+K32/J32 -> 0
B33: Ability Ambeck Mortgage Total | G33: =SUBTOTAL(9,G28:G32) -> 3342.11 | H33: =SUBTOTAL(9,H28:H32) -> 3342.11 | I33: =SUBTOTAL(9,I28:I32) -> 0 | J33: =SUBTOTAL(9,J28:J32) -> 3332.11 | K33: =+G33-J33 -> 10 | L33: =+K33/J33 -> 0.0030011014
B34: Advantage Home Care | C34: Recurring Resale - Security | D34: Recurring Resale - Security | E34: 180331 | F34: 45931 | G34: 5298 | H34: =+G34 -> 5298 | J34: =SUMIFS('[2]Sep-Aug Comp CA'!$G$1:$G$498,'[2]Sep-Aug Comp CA'!$B$1:$B$498,'Oct Agreement Compare CA'!B34,'[2]Sep-Aug Comp CA'!$C$1:$C$498,'Oct Agreement Compare CA'!C34,'[2]Sep-Aug Comp CA'!$D$1:$D$498,'Oct Agreement Compare CA'!D34) -> 5312 | K34: =+G34-J34 -> -14 | L34: =+K34/J34 -> -0.0026355422
B35: Advantage Home Care | C35: T-Services-MSP | D35: T-Services-MSP | E35: 180331 | F35: 45931 | G35: 7176 | H35: =+G35 -> 7176 | J35: =SUMIFS('[2]Sep-Aug Comp CA'!$G$1:$G$498,'[2]Sep-Aug Comp CA'!$B$1:$B$498,'Oct Agreement Compare CA'!B35,'[2]Sep-Aug Comp CA'!$C$1:$C$498,'Oct Agreement Compare CA'!C35,'[2]Sep-Aug Comp CA'!$D$1:$D$498,'Oct Agreement Compare CA'!D35) -> 6600 | K35: =+G35-J35 -> 576 | L35: =+K35/J35 -> 0.087272727
B36: Advantage Home Care Total | G36: =SUBTOTAL(9,G34:G35) -> 12474 | H36: =SUBTOTAL(9,H34:H35) -> 12474 | I36: =SUBTOTAL(9,I34:I35) -> 0 | J36: =SUBTOTAL(9,J34:J35) -> 11912 | K36: =+G36-J36 -> 562 | L36: =+K36/J36 -> 0.047179315
B37: Agape Corporation WEB Du | C37: Recurring Resale - MSP | D37: Recurring Resale - MSP | E37: 180292 | F37: 45931 | G37: 250 | H37: =+G37 -> 250 | J37: =SUMIFS('[2]Sep-Aug Comp CA'!$G$1:$G$498,'[2]Sep-Aug Comp CA'!$B$1:$B$498,'Oct Agreement Compare CA'!B37,'[2]Sep-Aug Comp CA'!$C$1:$C$498,'Oct Agreement Compare CA'!C37,'[2]Sep-Aug Comp CA'!$D$1:$D$498,'Oct Agreement Compare CA'!D37) -> 250 | K37: =+G37-J37 -> 0 | L37: =+K37/J37 -> 0
B38: Agape Corporation WEB Du | C38: Recurring Resale - Security | D38: Recurring Resale - Security | E38: 180292 | F38: 45931 | G38: 1600 | H38: =+G38 -> 1600 | J38: =SUMIFS('[2]Sep-Aug Comp CA'!$G$1:$G$498,'[2]Sep-Aug Comp CA'!$B$1:$B$498,'Oct Agreement Compare CA'!B38,'[2]Sep-Aug Comp CA'!$C$1:$C$498,'Oct Agreement Compare CA'!C38,'[2]Sep-Aug Comp CA'!$D$1:$D$498,'Oct Agreement Compare CA'!D38) -> 1600 | K38: =+G38-J38 -> 0 | L38: =+K38/J38 -> 0
B39: Agape Corporation WEB Du | C39: T-Services-MSP | D39: T-Services-MSP | E39: 180292 | F39: 45931 | G39: 3288.79 | H39: =+G39 -> 3288.79 | J39: =SUMIFS('[2]Sep-Aug Comp CA'!$G$1:$G$498,'[2]Sep-Aug Comp CA'!$B$1:$B$498,'Oct Agreement Compare CA'!B39,'[2]Sep-Aug Comp CA'!$C$1:$C$498,'Oct Agreement Compare CA'!C39,'[2]Sep-Aug Comp CA'!$D$1:$D$498,'Oct Agreement Compare CA'!D39) -> 3288.79 | K39: =+G39-J39 -> 0 | L39: =+K39/J39 -> 0
B40: Agape Corporation WEB Du Total | G40: =SUBTOTAL(9,G37:G39) -> 5138.79 | H40: =SUBTOTAL(9,H37:H39) -> 5138.79 | I40: =SUBTOTAL(9,I37:I39) -> 0 | J40: =SUBTOTAL(9,J37:J39) -> 5138.79 | K40: =+G40-J40 -> 0 | L40: =+K40/J40 -> 0
B41: Agee Construction | C41: Cloud - Private | D41: Cloud - Private | E41: 180293 | F41: 45931 | G41: 75 | H41: =+G41 -> 75 | J41: =SUMIFS('[2]Sep-Aug Comp CA'!$G$1:$G$498,'[2]Sep-Aug Comp CA'!$B$1:$B$498,'Oct Agreement Compare CA'!B41,'[2]Sep-Aug Comp CA'!$C$1:$C$498,'Oct Agreement Compare CA'!C41,'[2]Sep-Aug Comp CA'!$D$1:$D$498,'Oct Agreement Compare CA'!D41) -> 75 | K41: =+G41-J41 -> 0 | L41: =+K41/J41 -> 0
B42: Agee Construction | C42: Recurring Resale - Microsoft 365 NCE | D42: Agee Microsoft 365 | E42: 180293 | F42: 45931 | G42: 400 | H42: =+G42 -> 400 | J42: =SUMIFS('[2]Sep-Aug Comp CA'!$G$1:$G$498,'[2]Sep-Aug Comp CA'!$B$1:$B$498,'Oct Agreement Compare CA'!B42,'[2]Sep-Aug Comp CA'!$C$1:$C$498,'Oct Agreement Compare CA'!C42,'[2]Sep-Aug Comp CA'!$D$1:$D$498,'Oct Agreement Compare CA'!D42) -> 400 | K42: =+G42-J42 -> 0 | L42: =+K42/J42 -> 0
B43: Agee Construction | C43: Recurring Resale - MSP | D43: Recurring Resale - MSP | E43: 180293 | F43: 45931 | G43: 697.8872 | H43: =+G43 -> 697.8872 | J43: =SUMIFS('[2]Sep-Aug Comp CA'!$G$1:$G$498,'[2]Sep-Aug Comp CA'!$B$1:$B$498,'Oct Agreement Compare CA'!B43,'[2]Sep-Aug Comp CA'!$C$1:$C$498,'Oct Agreement Compare CA'!C43,'[2]Sep-Aug Comp CA'!$D$1:$D$498,'Oct Agreement Compare CA'!D43) -> 685.5542 | K43: =+G43-J43 -> 12.333 | L43: =+K43/J43 -> 0.017989825
B44: Agee Construction | C44: Recurring Resale - Security | D44: Recurring Resale - Security | E44: 180293 | F44: 45931 | G44: 668.5 | H44: =+G44 -> 668.5 | J44: =SUMIFS('[2]Sep-Aug Comp CA'!$G$1:$G$498,'[2]Sep-Aug Comp CA'!$B$1:$B$498,'Oct Agreement Compare CA'!B44,'[2]Sep-Aug Comp CA'!$C$1:$C$498,'Oct Agreement Compare CA'!C44,'[2]Sep-Aug Comp CA'!$D$1:$D$498,'Oct Agreement Compare CA'!D44) -> 661.5 | K44: =+G44-J44 -> 7 | L44: =+K44/J44 -> 0.010582011
B45: Agee Construction | C45: T-Services-MSP | D45: T-Services-MSP | E45: 180293 | F45: 45931 | G45: 1758.0928 | H45: =+G45 -> 1758.0928 | J45: =SUMIFS('[2]Sep-Aug Comp CA'!$G$1:$G$498,'[2]Sep-Aug Comp CA'!$B$1:$B$498,'Oct Agreement Compare CA'!B45,'[2]Sep-Aug Comp CA'!$C$1:$C$498,'Oct Agreement Compare CA'!C45,'[2]Sep-Aug Comp CA'!$D$1:$D$498,'Oct Agreement Compare CA'!D45) -> 1758.09 | K45: =+G45-J45 -> 0.0028 | L45: =+K45/J45 -> 1.5926375e-06
B46: Agee Construction Total | G46: =SUBTOTAL(9,G41:G45) -> 3599.48 | H46: =SUBTOTAL(9,H41:H45) -> 3599.48 | I46: =SUBTOTAL(9,I41:I45) -> 0 | J46: =SUBTOTAL(9,J41:J45) -> 3580.1442 | K46: =+G46-J46 -> 19.3358 | L46: =+K46/J46 -> 0.0054008439
B47: Alliance Services | C47: Recurring Resale - Microsoft 365 NCE | D47: Recurring Resale - Microsoft 365 NCE | E47: 180332 | F47: 45931 | G47: 662 | H47: =+G47 -> 662 | J47: =SUMIFS('[2]Sep-Aug Comp CA'!$G$1:$G$498,'[2]Sep-Aug Comp CA'!$B$1:$B$498,'Oct Agreement Compare CA'!B47,'[2]Sep-Aug Comp CA'!$C$1:$C$498,'Oct Agreement Compare CA'!C47,'[2]Sep-Aug Comp CA'!$D$1:$D$498,'Oct Agreement Compare CA'!D47) -> 640 | K47: =+G47-J47 -> 22 | L47: =+K47/J47 -> 0.034375
B48: Alliance Services | C48: Recurring Resale - MSP | D48: Recurring Resale - MSP | E48: 180332 | F48: 45931 | G48: 154 | H48: =+G48 -> 154 | J48: =SUMIFS('[2]Sep-Aug Comp CA'!$G$1:$G$498,'[2]Sep-Aug Comp CA'!$B$1:$B$498,'Oct Agreement Compare CA'!B48,'[2]Sep-Aug Comp CA'!$C$1:$C$498,'Oct Agreement Compare CA'!C48,'[2]Sep-Aug Comp CA'!$D$1:$D$498,'Oct Agreement Compare CA'!D48) -> 150 | K48: =+G48-J48 -> 4 | L48: =+K48/J48 -> 0.026666667
B49: Alliance Services | C49: Recurring Resale - Security | D49: Recurring Resale - Security | E49: 180332 | F49: 45931 | G49: 1054 | H49: =+G49 -> 1054 | J49: =SUMIFS('[2]Sep-Aug Comp CA'!$G$1:$G$498,'[2]Sep-Aug Comp CA'!$B$1:$B$498,'Oct Agreement Compare CA'!B49,'[2]Sep-Aug Comp CA'!$C$1:$C$498,'Oct Agreement Compare CA'!C49,'[2]Sep-Aug Comp CA'!$D$1:$D$498,'Oct Agreement Compare CA'!D49) -> 1060 | K49: =+G49-J49 -> -6 | L49: =+K49/J49 -> -0.0056603774
B50: Alliance Services | C50: T-Services-MSP | D50: T-Services-MSP | E50: 180332 | F50: 45931 | G50: 1994.3 | H50: =+G50 -> 1994.3 | J50: =SUMIFS('[2]Sep-Aug Comp CA'!$G$1:$G$498,'[2]Sep-Aug Comp CA'!$B$1:$B$498,'Oct Agreement Compare CA'!B50,'[2]Sep-Aug Comp CA'!$C$1:$C$498,'Oct Agreement Compare CA'!C50,'[2]Sep-Aug Comp CA'!$D$1:$D$498,'Oct Agreement Compare CA'!D50) -> 1927.65 | K50: =+G50-J50 -> 66.65 | L50: =+K50/J50 -> 0.034575779
B51: Alliance Services Total | G51: =SUBTOTAL(9,G47:G50) -> 3864.3 | H51: =SUBTOTAL(9,H47:H50) -> 3864.3 | I51: =SUBTOTAL(9,I47:I50) -> 0 | J51: =SUBTOTAL(9,J47:J50) -> 3777.65 | K51: =+G51-J51 -> 86.65 | L51: =+K51/J51 -> 0.022937541
B52: Ameribest | C52: Cloud - Private | D52: Cloud - Private | E52: 180333 | F52: 45931 | G52: 335 | H52: =+G52 -> 335 | J52: =SUMIFS('[2]Sep-Aug Comp CA'!$G$1:$G$498,'[2]Sep-Aug Comp CA'!$B$1:$B$498,'Oct Agreement Compare CA'!B52,'[2]Sep-Aug Comp CA'!$C$1:$C$498,'Oct Agreement Compare CA'!C52,'[2]Sep-Aug Comp CA'!$D$1:$D$498,'Oct Agreement Compare CA'!D52) -> 335 | K52: =+G52-J52 -> 0 | L52: =+K52/J52 -> 0
B53: Ameribest | C53: Recurring Resale - MSP | D53: Recurring Resale - MSP | E53: 180333 | F53: 45931 | G53: 3891.9012 | H53: =+G53 -> 3891.9012 | J53: =SUMIFS('[2]Sep-Aug Comp CA'!$G$1:$G$498,'[2]Sep-Aug Comp CA'!$B$1:$B$498,'Oct Agreement Compare CA'!B53,'[2]Sep-Aug Comp CA'!$C$1:$C$498,'Oct Agreement Compare CA'!C53,'[2]Sep-Aug Comp CA'!$D$1:$D$498,'Oct Agreement Compare CA'!D53) -> 3740.4614 | K53: =+G53-J53 -> 151.4398 | L53: =+K53/J53 -> 0.04048693
B54: Ameribest | C54: Recurring Resale - Security | D54: Recurring Resale - Security | E54: 180333 | F54: 45931 | G54: 3989 | H54: =+G54 -> 3989 | J54: =SUMIFS('[2]Sep-Aug Comp CA'!$G$1:$G$498,'[2]Sep-Aug Comp CA'!$B$1:$B$498,'Oct Agreement Compare CA'!B54,'[2]Sep-Aug Comp CA'!$C$1:$C$498,'Oct Agreement Compare CA'!C54,'[2]Sep-Aug Comp CA'!$D$1:$D$498,'Oct Agreement Compare CA'!D54) -> 3868 | K54: =+G54-J54 -> 121 | L54: =+K54/J54 -> 0.031282316
B55: Ameribest | C55: T-Services-MSP | D55: T-Services-MSP | E55: 180333 | F55: 45931 | G55: 9775 | H55: =+G55 -> 9775 | J55: =SUMIFS('[2]Sep-Aug Comp CA'!$G$1:$G$498,'[2]Sep-Aug Comp CA'!$B$1:$B$498,'Oct Agreement Compare CA'!B55,'[2]Sep-Aug Comp CA'!$C$1:$C$498,'Oct Agreement Compare CA'!C55,'[2]Sep-Aug Comp CA'!$D$1:$D$498,'Oct Agreement Compare CA'!D55) -> 9170 | K55: =+G55-J55 -> 605 | L55: =+K55/J55 -> 0.065976009
B56: Ameribest Total | G56: =SUBTOTAL(9,G52:G55) -> 17990.901 | H56: =SUBTOTAL(9,H52:H55) -> 17990.901 | I56: =SUBTOTAL(9,I52:I55) -> 0 | J56: =SUBTOTAL(9,J52:J55) -> 17113.461 | K56: =+G56-J56 -> 877.4398 | L56: =+K56/J56 -> 0.051271907
B57: American Institute of Science and Technology | C57: Recurring Resale - MSP | D57: Recurring Resale - MSP | E57: 180334 | F57: 45931 | G57: 395.2 | H57: =+G57 -> 395.2 | J57: =SUMIFS('[2]Sep-Aug Comp CA'!$G$1:$G$498,'[2]Sep-Aug Comp CA'!$B$1:$B$498,'Oct Agreement Compare CA'!B57,'[2]Sep-Aug Comp CA'!$C$1:$C$498,'Oct Agreement Compare CA'!C57,'[2]Sep-Aug Comp CA'!$D$1:$D$498,'Oct Agreement Compare CA'!D57) -> 395.2 | K57: =+G57-J57 -> 0 | L57: =+K57/J57 -> 0
B58: American Institute of Science and Technology | C58: Recurring Resale - Security | D58: Recurring Resale - Security | E58: 180334 | F58: 45931 | G58: 404 | H58: =+G58 -> 404 | J58: =SUMIFS('[2]Sep-Aug Comp CA'!$G$1:$G$498,'[2]Sep-Aug Comp CA'!$B$1:$B$498,'Oct Agreement Compare CA'!B58,'[2]Sep-Aug Comp CA'!$C$1:$C$498,'Oct Agreement Compare CA'!C58,'[2]Sep-Aug Comp CA'!$D$1:$D$498,'Oct Agreement Compare CA'!D58) -> 400 | K58: =+G58-J58 -> 4 | L58: =+K58/J58 -> 0.01
B59: American Institute of Science and Technology | C59: T-Services-MSP | D59: T-Services-MSP 24/27 | E59: 180334 | F59: 45931 | G59: 982 | H59: =+G59 -> 982 | J59: =SUMIFS('[2]Sep-Aug Comp CA'!$G$1:$G$498,'[2]Sep-Aug Comp CA'!$B$1:$B$498,'Oct Agreement Compare CA'!B59,'[2]Sep-Aug Comp CA'!$C$1:$C$498,'Oct Agreement Compare CA'!C59,'[2]Sep-Aug Comp CA'!$D$1:$D$498,'Oct Agreement Compare CA'!D59) -> 982 | K59: =+G59-J59 -> 0 | L59: =+K59/J59 -> 0
B60: American Institute of Science and Technology Total | G60: =SUBTOTAL(9,G57:G59) -> 1781.2 | H60: =SUBTOTAL(9,H57:H59) -> 1781.2 | I60: =SUBTOTAL(9,I57:I59) -> 0 | J60: =SUBTOTAL(9,J57:J59) -> 1777.2 | K60: =+G60-J60 -> 4 | L60: =+K60/J60 -> 0.0022507315
B61: Anonymous LLC | C61: Cloud - Private | D61: Anonymous Cloud Services | E61: 180749 | F61: 45945 | G61: 484.62 | H61: =+G61 -> 484.62 | J61: =SUMIFS('[2]Sep-Aug Comp CA'!$G$1:$G$498,'[2]Sep-Aug Comp CA'!$B$1:$B$498,'Oct Agreement Compare CA'!B61,'[2]Sep-Aug Comp CA'!$C$1:$C$498,'Oct Agreement Compare CA'!C61,'[2]Sep-Aug Comp CA'!$D$1:$D$498,'Oct Agreement Compare CA'!D61) -> 484.62 | K61: =+G61-J61 -> 0 | L61: =+K61/J61 -> 0
B62: Anonymous LLC | C62: Recurring Resale - MSP | D62: Recurring Resale - MSP | E62: 180749 | F62: 45945 | G62: 1540 | H62: =+G62 -> 1540 | J62: =SUMIFS('[2]Sep-Aug Comp CA'!$G$1:$G$498,'[2]Sep-Aug Comp CA'!$B$1:$B$498,'Oct Agreement Compare CA'!B62,'[2]Sep-Aug Comp CA'!$C$1:$C$498,'Oct Agreement Compare CA'!C62,'[2]Sep-Aug Comp CA'!$D$1:$D$498,'Oct Agreement Compare CA'!D62) -> 1540 | K62: =+G62-J62 -> 0 | L62: =+K62/J62 -> 0
B63: Anonymous LLC | C63: Recurring Resale - Security | D63: Recurring Resale - Security | E63: 180749 | F63: 45945 | G63: 250 | H63: =+G63 -> 250 | J63: =SUMIFS('[2]Sep-Aug Comp CA'!$G$1:$G$498,'[2]Sep-Aug Comp CA'!$B$1:$B$498,'Oct Agreement Compare CA'!B63,'[2]Sep-Aug Comp CA'!$C$1:$C$498,'Oct Agreement Compare CA'!C63,'[2]Sep-Aug Comp CA'!$D$1:$D$498,'Oct Agreement Compare CA'!D63) -> 250 | K63: =+G63-J63 -> 0 | L63: =+K63/J63 -> 0
B64: Anonymous LLC | C64: T-Services-MSP | D64: T-Services-MSP | E64: 180749 | F64: 45945 | G64: 2595.6 | H64: =+G64 -> 2595.6 | J64: =SUMIFS('[2]Sep-Aug Comp CA'!$G$1:$G$498,'[2]Sep-Aug Comp CA'!$B$1:$B$498,'Oct Agreement Compare CA'!B64,'[2]Sep-Aug Comp CA'!$C$1:$C$498,'Oct Agreement Compare CA'!C64,'[2]Sep-Aug Comp CA'!$D$1:$D$498,'Oct Agreement Compare CA'!D64) -> 2595.6 | K64: =+G64-J64 -> 0 | L64: =+K64/J64 -> 0
B65: Anonymous LLC Total | G65: =SUBTOTAL(9,G61:G64) -> 4870.22 | H65: =SUBTOTAL(9,H61:H64) -> 4870.22 | I65: =SUBTOTAL(9,I61:I64) -> 0 | J65: =SUBTOTAL(9,J61:J64) -> 4870.22 | K65: =+G65-J65 -> 0 | L65: =+K65/J65 -> 0
B66: Applegate Teeples Drilling | C66: Cloud - Private | D66: Cloud - Private | E66: 180335 | F66: 45931 | G66: 500 | H66: =+G66 -> 500 | J66: =SUMIFS('[2]Sep-Aug Comp CA'!$G$1:$G$498,'[2]Sep-Aug Comp CA'!$B$1:$B$498,'Oct Agreement Compare CA'!B66,'[2]Sep-Aug Comp CA'!$C$1:$C$498,'Oct Agreement Compare CA'!C66,'[2]Sep-Aug Comp CA'!$D$1:$D$498,'Oct Agreement Compare CA'!D66) -> 500 | K66: =+G66-J66 -> 0 | L66: =+K66/J66 -> 0
B67: Applegate Teeples Drilling | C67: Recurring Resale - Microsoft 365 NCE | D67: Recurring Resale - Microsoft 365 NCE | E67: 180335 | F67: 45931 | G67: 664.8 | H67: =+G67 -> 664.8 | J67: =SUMIFS('[2]Sep-Aug Comp CA'!$G$1:$G$498,'[2]Sep-Aug Comp CA'!$B$1:$B$498,'Oct Agreement Compare CA'!B67,'[2]Sep-Aug Comp CA'!$C$1:$C$498,'Oct Agreement Compare CA'!C67,'[2]Sep-Aug Comp CA'!$D$1:$D$498,'Oct Agreement Compare CA'!D67) -> 664.8 | K67: =+G67-J67 -> 0 | L67: =+K67/J67 -> 0
B68: Applegate Teeples Drilling | C68: Recurring Resale - MSP | D68: Recurring Resale - MSP | E68: 180335 | F68: 45931 | G68: 95.5 | H68: =+G68 -> 95.5 | J68: =SUMIFS('[2]Sep-Aug Comp CA'!$G$1:$G$498,'[2]Sep-Aug Comp CA'!$B$1:$B$498,'Oct Agreement Compare CA'!B68,'[2]Sep-Aug Comp CA'!$C$1:$C$498,'Oct Agreement Compare CA'!C68,'[2]Sep-Aug Comp CA'!$D$1:$D$498,'Oct Agreement Compare CA'!D68) -> 95.5 | K68: =+G68-J68 -> 0 | L68: =+K68/J68 -> 0
B69: Applegate Teeples Drilling | C69: Recurring Resale - Security | D69: Recurring Resale - Security | E69: 180335 | F69: 45931 | G69: 1147 | H69: =+G69 -> 1147 | J69: =SUMIFS('[2]Sep-Aug Comp CA'!$G$1:$G$498,'[2]Sep-Aug Comp CA'!$B$1:$B$498,'Oct Agreement Compare CA'!B69,'[2]Sep-Aug Comp CA'!$C$1:$C$498,'Oct Agreement Compare CA'!C69,'[2]Sep-Aug Comp CA'!$D$1:$D$498,'Oct Agreement Compare CA'!D69) -> 1156 | K69: =+G69-J69 -> -9 | L69: =+K69/J69 -> -0.0077854671
B70: Applegate Teeples Drilling | C70: T-Services-MSP | D70: T-Services-MSP | E70: 180335 | F70: 45931 | G70: 1706.79 | H70: =+G70 -> 1706.79 | J70: =SUMIFS('[2]Sep-Aug Comp CA'!$G$1:$G$498,'[2]Sep-Aug Comp CA'!$B$1:$B$498,'Oct Agreement Compare CA'!B70,'[2]Sep-Aug Comp CA'!$C$1:$C$498,'Oct Agreement Compare CA'!C70,'[2]Sep-Aug Comp CA'!$D$1:$D$498,'Oct Agreement Compare CA'!D70) -> 1672.37 | K70: =+G70-J70 -> 34.42 | L70: =+K70/J70 -> 0.02058157
B71: Applegate Teeples Drilling Total | G71: =SUBTOTAL(9,G66:G70) -> 4114.09 | H71: =SUBTOTAL(9,H66:H70) -> 4114.09 | I71: =SUBTOTAL(9,I66:I70) -> 0 | J71: =SUBTOTAL(9,J66:J70) -> 4088.67 | K71: =+G71-J71 -> 25.42 | L71: =+K71/J71 -> 0.0062171806
B72: ATD Home Health Agency, INC | C72: Recurring Resale - Security | D72: Recurring Resale - Security 24/27 | E72: 180336 | F72: 45931 | G72: 784 | H72: =+G72 -> 784 | J72: =SUMIFS('[2]Sep-Aug Comp CA'!$G$1:$G$498,'[2]Sep-Aug Comp CA'!$B$1:$B$498,'Oct Agreement Compare CA'!B72,'[2]Sep-Aug Comp CA'!$C$1:$C$498,'Oct Agreement Compare CA'!C72,'[2]Sep-Aug Comp CA'!$D$1:$D$498,'Oct Agreement Compare CA'!D72) -> 789 | K72: =+G72-J72 -> -5 | L72: =+K72/J72 -> -0.0063371356
B73: ATD Home Health Agency, INC | C73: T-Services-MSP | D73: T-Services-MSP 24/27 | E73: 180336 | F73: 45931 | G73: 2795 | H73: =+G73 -> 2795 | J73: =SUMIFS('[2]Sep-Aug Comp CA'!$G$1:$G$498,'[2]Sep-Aug Comp CA'!$B$1:$B$498,'Oct Agreement Compare CA'!B73,'[2]Sep-Aug Comp CA'!$C$1:$C$498,'Oct Agreement Compare CA'!C73,'[2]Sep-Aug Comp CA'!$D$1:$D$498,'Oct Agreement Compare CA'!D73) -> 2690 | K73: =+G73-J73 -> 105 | L73: =+K73/J73 -> 0.039033457
B74: ATD Home Health Agency, INC Total | G74: =SUBTOTAL(9,G72:G73) -> 3579 | H74: =SUBTOTAL(9,H72:H73) -> 3579 | I74: =SUBTOTAL(9,I72:I73) -> 0 | J74: =SUBTOTAL(9,J72:J73) -> 3479 | K74: =+G74-J74 -> 100 | L74: =+K74/J74 -> 0.028743892
B75: Aweta - Americas | C75: Recurring Resale - Microsoft 365 NCE | D75: Recurring Resale - Microsoft 365 NCE | E75: 180294 | F75: 45931 | G75: 1026 | H75: =+G75 -> 1026 | J75: =SUMIFS('[2]Sep-Aug Comp CA'!$G$1:$G$498,'[2]Sep-Aug Comp CA'!$B$1:$B$498,'Oct Agreement Compare CA'!B75,'[2]Sep-Aug Comp CA'!$C$1:$C$498,'Oct Agreement Compare CA'!C75,'[2]Sep-Aug Comp CA'!$D$1:$D$498,'Oct Agreement Compare CA'!D75) -> 1026 | K75: =+G75-J75 -> 0 | L75: =+K75/J75 -> 0
B76: Aweta - Americas | C76: Recurring Resale - MSP | D76: Recurring Resale - MSP | E76: 180294 | F76: 45931 | G76: 778.9052 | H76: =+G76 -> 778.9052 | J76: =SUMIFS('[2]Sep-Aug Comp CA'!$G$1:$G$498,'[2]Sep-Aug Comp CA'!$B$1:$B$498,'Oct Agreement Compare CA'!B76,'[2]Sep-Aug Comp CA'!$C$1:$C$498,'Oct Agreement Compare CA'!C76,'[2]Sep-Aug Comp CA'!$D$1:$D$498,'Oct Agreement Compare CA'!D76) -> 774.6446 | K76: =+G76-J76 -> 4.2606 | L76: =+K76/J76 -> 0.0055000706
B77: Aweta - Americas | C77: Recurring Resale - Security | D77: Recurring Resale - Security | E77: 180294 | F77: 45931 | G77: 733 | H77: =+G77 -> 733 | J77: =SUMIFS('[2]Sep-Aug Comp CA'!$G$1:$G$498,'[2]Sep-Aug Comp CA'!$B$1:$B$498,'Oct Agreement Compare CA'!B77,'[2]Sep-Aug Comp CA'!$C$1:$C$498,'Oct Agreement Compare CA'!C77,'[2]Sep-Aug Comp CA'!$D$1:$D$498,'Oct Agreement Compare CA'!D77) -> 733 | K77: =+G77-J77 -> 0 | L77: =+K77/J77 -> 0
B78: Aweta - Americas | C78: T-Services-MSP | D78: T-Services-MSP | E78: 180294 | F78: 45931 | G78: 2708.9448 | H78: =+G78 -> 2708.9448 | J78: =SUMIFS('[2]Sep-Aug Comp CA'!$G$1:$G$498,'[2]Sep-Aug Comp CA'!$B$1:$B$498,'Oct Agreement Compare CA'!B78,'[2]Sep-Aug Comp CA'!$C$1:$C$498,'Oct Agreement Compare CA'!C78,'[2]Sep-Aug Comp CA'!$D$1:$D$498,'Oct Agreement Compare CA'!D78) -> 2708.94 | K78: =+G78-J78 -> 0.0048 | L78: =+K78/J78 -> 1.7719108e-06
B79: Aweta - Americas | C79: T-Services-Security | D79: T-Services-Security | E79: 180294 | F79: 45931 | G79: 55 | H79: =+G79 -> 55 | J79: =SUMIFS('[2]Sep-Aug Comp CA'!$G$1:$G$498,'[2]Sep-Aug Comp CA'!$B$1:$B$498,'Oct Agreement Compare CA'!B79,'[2]Sep-Aug Comp CA'!$C$1:$C$498,'Oct Agreement Compare CA'!C79,'[2]Sep-Aug Comp CA'!$D$1:$D$498,'Oct Agreement Compare CA'!D79) -> 55 | K79: =+G79-J79 -> 0 | L79: =+K79/J79 -> 0
B80: Aweta - Americas Total | G80: =SUBTOTAL(9,G75:G79) -> 5301.85 | H80: =SUBTOTAL(9,H75:H79) -> 5301.85 | I80: =SUBTOTAL(9,I75:I79) -> 0 | J80: =SUBTOTAL(9,J75:J79) -> 5297.5846 | K80: =+G80-J80 -> 4.2654 | L80: =+K80/J80 -> 0.00080515939
B81: Big Valley Grace Community Church | C81: Recurring Resale - Microsoft 365 NCE | D81: Recurring Resale - Microsoft 365 NCE | E81: 180337 | F81: 45931 | G81: 27 | H81: =+G81 -> 27 | J81: =SUMIFS('[2]Sep-Aug Comp CA'!$G$1:$G$498,'[2]Sep-Aug Comp CA'!$B$1:$B$498,'Oct Agreement Compare CA'!B81,'[2]Sep-Aug Comp CA'!$C$1:$C$498,'Oct Agreement Compare CA'!C81,'[2]Sep-Aug Comp CA'!$D$1:$D$498,'Oct Agreement Compare CA'!D81) -> 27 | K81: =+G81-J81 -> 0 | L81: =+K81/J81 -> 0
B82: Big Valley Grace Community Church | C82: Recurring Resale - MSP | D82: Recurring Resale - MSP | E82: 180337 | F82: 45931 | G82: 552.7744 | H82: =+G82 -> 552.7744 | J82: =SUMIFS('[2]Sep-Aug Comp CA'!$G$1:$G$498,'[2]Sep-Aug Comp CA'!$B$1:$B$498,'Oct Agreement Compare CA'!B82,'[2]Sep-Aug Comp CA'!$C$1:$C$498,'Oct Agreement Compare CA'!C82,'[2]Sep-Aug Comp CA'!$D$1:$D$498,'Oct Agreement Compare CA'!D82) -> 560.8188 | K82: =+G82-J82 -> -8.0444 | L82: =+K82/J82 -> -0.014344027
B83: Big Valley Grace Community Church | C83: Recurring Resale - Security | D83: Recurring Resale - Security | E83: 180337 | F83: 45931 | G83: 960 | H83: =+G83 -> 960 | J83: =SUMIFS('[2]Sep-Aug Comp CA'!$G$1:$G$498,'[2]Sep-Aug Comp CA'!$B$1:$B$498,'Oct Agreement Compare CA'!B83,'[2]Sep-Aug Comp CA'!$C$1:$C$498,'Oct Agreement Compare CA'!C83,'[2]Sep-Aug Comp CA'!$D$1:$D$498,'Oct Agreement Compare CA'!D83) -> 925 | K83: =+G83-J83 -> 35 | L83: =+K83/J83 -> 0.037837838
B84: Big Valley Grace Community Church | C84: T-Services-MSP | D84: T-Services-MSP | E84: 180337 | F84: 45931 | G84: 7435.58 | H84: =+G84 -> 7435.58 | J84: =SUMIFS('[2]Sep-Aug Comp CA'!$G$1:$G$498,'[2]Sep-Aug Comp CA'!$B$1:$B$498,'Oct Agreement Compare CA'!B84,'[2]Sep-Aug Comp CA'!$C$1:$C$498,'Oct Agreement Compare CA'!C84,'[2]Sep-Aug Comp CA'!$D$1:$D$498,'Oct Agreement Compare CA'!D84) -> 7435.5812 | K84: =+G84-J84 -> -0.0012 | L84: =+K84/J84 -> -1.6138617e-07
B85: Big Valley Grace Community Church Total | G85: =SUBTOTAL(9,G81:G84) -> 8975.3544 | H85: =SUBTOTAL(9,H81:H84) -> 8975.3544 | I85: =SUBTOTAL(9,I81:I84) -> 0 | J85: =SUBTOTAL(9,J81:J84) -> 8948.4 | K85: =+G85-J85 -> 26.9544 | L85: =+K85/J85 -> 0.0030122033
B86: Borba Farms Partners | C86: Recurring Resale - Microsoft 365 NCE | D86: Recurring Resale - Microsoft 365 NCE | E86: 180295 | F86: 45931 | G86: 388 | H86: =+G86 -> 388 | J86: =SUMIFS('[2]Sep-Aug Comp CA'!$G$1:$G$498,'[2]Sep-Aug Comp CA'!$B$1:$B$498,'Oct Agreement Compare CA'!B86,'[2]Sep-Aug Comp CA'!$C$1:$C$498,'Oct Agreement Compare CA'!C86,'[2]Sep-Aug Comp CA'!$D$1:$D$498,'Oct Agreement Compare CA'!D86) -> 388 | K86: =+G86-J86 -> 0 | L86: =+K86/J86 -> 0
B87: Borba Farms Partners | C87: Recurring Resale - MSP | D87: Recurring Resale - MSP | E87: 180295 | F87: 45931 | G87: 398.7066 | H87: =+G87 -> 398.7066 | J87: =SUMIFS('[2]Sep-Aug Comp CA'!$G$1:$G$498,'[2]Sep-Aug Comp CA'!$B$1:$B$498,'Oct Agreement Compare CA'!B87,'[2]Sep-Aug Comp CA'!$C$1:$C$498,'Oct Agreement Compare CA'!C87,'[2]Sep-Aug Comp CA'!$D$1:$D$498,'Oct Agreement Compare CA'!D87) -> 397.2234 | K87: =+G87-J87 -> 1.4832 | L87: =+K87/J87 -> 0.003733919
B88: Borba Farms Partners | C88: Recurring Resale - Security | D88: Recurring Resale - Security | E88: 180295 | F88: 45931 | G88: 126 | H88: =+G88 -> 126 | J88: =SUMIFS('[2]Sep-Aug Comp CA'!$G$1:$G$498,'[2]Sep-Aug Comp CA'!$B$1:$B$498,'Oct Agreement Compare CA'!B88,'[2]Sep-Aug Comp CA'!$C$1:$C$498,'Oct Agreement Compare CA'!C88,'[2]Sep-Aug Comp CA'!$D$1:$D$498,'Oct Agreement Compare CA'!D88) -> 119 | K88: =+G88-J88 -> 7 | L88: =+K88/J88 -> 0.058823529
B89: Borba Farms Partners | C89: T-Services-MSP | D89: T-Services-MSP | E89: 180295 | F89: 45931 | G89: 1451.4734 | H89: =+G89 -> 1451.4734 | J89: =SUMIFS('[2]Sep-Aug Comp CA'!$G$1:$G$498,'[2]Sep-Aug Comp CA'!$B$1:$B$498,'Oct Agreement Compare CA'!B89,'[2]Sep-Aug Comp CA'!$C$1:$C$498,'Oct Agreement Compare CA'!C89,'[2]Sep-Aug Comp CA'!$D$1:$D$498,'Oct Agreement Compare CA'!D89) -> 1451.47 | K89: =+G89-J89 -> 0.0034 | L89: =+K89/J89 -> 2.3424528e-06
B90: Borba Farms Partners Total | G90: =SUBTOTAL(9,G86:G89) -> 2364.18 | H90: =SUBTOTAL(9,H86:H89) -> 2364.18 | I90: =SUBTOTAL(9,I86:I89) -> 0 | J90: =SUBTOTAL(9,J86:J89) -> 2355.6934 | K90: =+G90-J90 -> 8.4866 | L90: =+K90/J90 -> 0.0036025911
B91: Caloy Company LLC | C91: Cloud - Private | D91: Cloud - Private | E91: 180338 | F91: 45931 | G91: 501.79 | H91: =+G91 -> 501.79 | J91: =SUMIFS('[2]Sep-Aug Comp CA'!$G$1:$G$498,'[2]Sep-Aug Comp CA'!$B$1:$B$498,'Oct Agreement Compare CA'!B91,'[2]Sep-Aug Comp CA'!$C$1:$C$498,'Oct Agreement Compare CA'!C91,'[2]Sep-Aug Comp CA'!$D$1:$D$498,'Oct Agreement Compare CA'!D91) -> 501.79 | K91: =+G91-J91 -> 0 | L91: =+K91/J91 -> 0
B92: Caloy Company LLC | C92: Recurring Resale - Microsoft 365 NCE | D92: Caloy Microsoft 365 | E92: 180338 | F92: 45931 | G92: 352 | H92: =+G92 -> 352 | J92: =SUMIFS('[2]Sep-Aug Comp CA'!$G$1:$G$498,'[2]Sep-Aug Comp CA'!$B$1:$B$498,'Oct Agreement Compare CA'!B92,'[2]Sep-Aug Comp CA'!$C$1:$C$498,'Oct Agreement Compare CA'!C92,'[2]Sep-Aug Comp CA'!$D$1:$D$498,'Oct Agreement Compare CA'!D92) -> 352 | K92: =+G92-J92 -> 0 | L92: =+K92/J92 -> 0
B93: Caloy Company LLC | C93: Recurring Resale - MSP | D93: Recurring Resale - MSP | E93: 180338 | F93: 45931 | G93: 119.5 | H93: =+G93 -> 119.5 | J93: =SUMIFS('[2]Sep-Aug Comp CA'!$G$1:$G$498,'[2]Sep-Aug Comp CA'!$B$1:$B$498,'Oct Agreement Compare CA'!B93,'[2]Sep-Aug Comp CA'!$C$1:$C$498,'Oct Agreement Compare CA'!C93,'[2]Sep-Aug Comp CA'!$D$1:$D$498,'Oct Agreement Compare CA'!D93) -> 119.5 | K93: =+G93-J93 -> 0 | L93: =+K93/J93 -> 0
B94: Caloy Company LLC | C94: Recurring Resale - Security | D94: Recurring Resale - Security | E94: 180338 | F94: 45931 | G94: 355 | H94: =+G94 -> 355 | J94: =SUMIFS('[2]Sep-Aug Comp CA'!$G$1:$G$498,'[2]Sep-Aug Comp CA'!$B$1:$B$498,'Oct Agreement Compare CA'!B94,'[2]Sep-Aug Comp CA'!$C$1:$C$498,'Oct Agreement Compare CA'!C94,'[2]Sep-Aug Comp CA'!$D$1:$D$498,'Oct Agreement Compare CA'!D94) -> 355 | K94: =+G94-J94 -> 0 | L94: =+K94/J94 -> 0
B95: Caloy Company LLC | C95: T-Services-MSP | D95: Caloy-Managed | E95: 180338 | F95: 45931 | G95: 4522.21 | H95: =+G95 -> 4522.21 | J95: =SUMIFS('[2]Sep-Aug Comp CA'!$G$1:$G$498,'[2]Sep-Aug Comp CA'!$B$1:$B$498,'Oct Agreement Compare CA'!B95,'[2]Sep-Aug Comp CA'!$C$1:$C$498,'Oct Agreement Compare CA'!C95,'[2]Sep-Aug Comp CA'!$D$1:$D$498,'Oct Agreement Compare CA'!D95) -> 4522.21 | K95: =+G95-J95 -> 0 | L95: =+K95/J95 -> 0
B96: Caloy Company LLC Total | G96: =SUBTOTAL(9,G91:G95) -> 5850.5 | H96: =SUBTOTAL(9,H91:H95) -> 5850.5 | I96: =SUBTOTAL(9,I91:I95) -> 0 | J96: =SUBTOTAL(9,J91:J95) -> 5850.5 | K96: =+G96-J96 -> 0 | L96: =+K96/J96 -> 0
B97: Capital Financial Consultants Group | C97: Cloud - Private | D97: Capital Financial Cloud Services | E97: 180750 | F97: 45945 | G97: 334.75 | H97: =+G97 -> 334.75 | J97: =SUMIFS('[2]Sep-Aug Comp CA'!$G$1:$G$498,'[2]Sep-Aug Comp CA'!$B$1:$B$498,'Oct Agreement Compare CA'!B97,'[2]Sep-Aug Comp CA'!$C$1:$C$498,'Oct Agreement Compare CA'!C97,'[2]Sep-Aug Comp CA'!$D$1:$D$498,'Oct Agreement Compare CA'!D97) -> 334.75 | K97: =+G97-J97 -> 0 | L97: =+K97/J97 -> 0
B98: Capital Financial Consultants Group | C98: Recurring Resale - MSP | D98: Recurring Resale - MSP | E98: 180750 | F98: 45945 | G98: 0 | H98: =+G98 -> 0 | J98: =SUMIFS('[2]Sep-Aug Comp CA'!$G$1:$G$498,'[2]Sep-Aug Comp CA'!$B$1:$B$498,'Oct Agreement Compare CA'!B98,'[2]Sep-Aug Comp CA'!$C$1:$C$498,'Oct Agreement Compare CA'!C98,'[2]Sep-Aug Comp CA'!$D$1:$D$498,'Oct Agreement Compare CA'!D98) -> 0 | K98: =+G98-J98 -> 0 | L98: =+K98/J98 -> #DIV/0!
B99: Capital Financial Consultants Group | C99: Recurring Resale - MSP | D99: Recurring Resale - MSP 25/26 | E99: 180751 | F99: 45945 | G99: 4.165 | H99: =+G99 -> 4.165 | J99: =SUMIFS('[2]Sep-Aug Comp CA'!$G$1:$G$498,'[2]Sep-Aug Comp CA'!$B$1:$B$498,'Oct Agreement Compare CA'!B99,'[2]Sep-Aug Comp CA'!$C$1:$C$498,'Oct Agreement Compare CA'!C99,'[2]Sep-Aug Comp CA'!$D$1:$D$498,'Oct Agreement Compare CA'!D99) -> 4.165 | K99: =+G99-J99 -> 0 | L99: =+K99/J99 -> 0
B100: Capital Financial Consultants Group | C100: Recurring Resale - Security | D100: Recurring Resale - Security | E100: 180750 | F100: 45945 | G100: 299 | H100: =+G100 -> 299 | J100: =SUMIFS('[2]Sep-Aug Comp CA'!$G$1:$G$498,'[2]Sep-Aug Comp CA'!$B$1:$B$498,'Oct Agreement Compare CA'!B100,'[2]Sep-Aug Comp CA'!$C$1:$C$498,'Oct Agreement Compare CA'!C100,'[2]Sep-Aug Comp CA'!$D$1:$D$498,'Oct Agreement Compare CA'!D100) -> 299 | K100: =+G100-J100 -> 0 | L100: =+K100/J100 -> 0
...

Sheet Actual Billings
A1: Location name | B1: (Multiple Items) | H1: Location name | I1: (Multiple Items)
A2: Billing | B2: x | H2: Billing | I2: x
A4: Sum of Balance | B4: Column Labels | H4: Sum of Balance | I4: Column Labels
B5: Sep | C5: Oct | D5: Grand Total | I5: Sep | J5: Oct | K5: Grand Total
A7: Row Labels | H7: Row Labels
A8: 40000 | B8: -458333.46 | C8: -458920.03 | D8: -917253.49 | H8: 40000 | I8: -91841.37 | J8: -92188.25 | K8: -184029.62
A9: 40100 | B9: -5055.45 | C9: -5055.45 | D9: -10110.9 | H9: 40200 | I9: -5580.2 | J9: -5580.2 | K9: -11160.4
A10: 40200 | B10: -3141.33 | C10: -2826.33 | D10: -5967.66 | H10: 41200 | J10: -315 | K10: -315
A11: 41200 | B11: -26560.81 | C11: -26310.81 | D11: -52871.62 | H11: 41250 | I11: -562.5 | J11: -562.5 | K11: -1125
A12: 41300 | B12: -48266.91 | C12: -49744.37 | D12: -98011.28 | H12: 41300 | I12: -2064.91 | J12: -2010.85 | K12: -4075.76
A13: 41320 | B13: -8987.36 | C13: -8757.36 | D13: -17744.72 | H13: 41320 | I13: -2734.25 | J13: -2799.25 | K13: -5533.5
A14: 41350 | B14: -954.1 | C14: -898.87 | D14: -1852.97 | H14: 41400 | I14: -720.95 | J14: -1230.41 | K14: -1951.36
A15: 41360 | B15: -1144 | C15: -1144 | D15: -2288 | H15: 41450 | I15: -1310.97 | J15: -1377.37 | K15: -2688.34
A16: 41365 | B16: -25835.05 | C16: -25853.05 | D16: -51688.1 | H16: 42100 | I16: -13408.7 | J16: -14214.1 | K16: -27622.8
A17: 41400 | B17: -5584.21 | C17: -7877.69 | D17: -13461.9 | H17: 41500 | I17: -58058 | J17: -22171 | K17: -80229
A18: 41450 | B18: -92497.27 | C18: -121329.87 | D18: -213827.14 | H18: 42000 | I18: -228854.89 | J18: -441630.42 | K18: -670485.31
A19: 42100 | B19: -133948.08 | C19: -135011.8 | D19: -268959.88 | H19: 42300 | I19: -754 | J19: -754 | K19: -1508
A20: 41500 | B20: -24526.25 | C20: -46520 | D20: -71046.25 | H20: 44000 | I20: -1587.29 | J20: -17123.75 | K20: -18711.04
A21: 42000 | B21: -101632.12 | C21: -193347.56 | D21: -294979.68 | H21: 41700 | I21: -7449 | J21: -9125.8 | K21: -16574.8
A22: 42300 | B22: -1791.81 | C22: -1791.81 | D22: -3583.62 | H22: 42200 | I22: -1718.1 | J22: -1718.1 | K22: -3436.2
A23: 44000 | B23: -211.17 | C23: -551.15 | D23: -762.32 | H23: 41925 | I23: -5913.61 | J23: -5773.93 | K23: -11687.54
A24: 41700 | B24: -7030.76 | C24: -10863.16 | D24: -17893.92 | H24: Grand Total | I24: -422558.74 | J24: -618574.93 | K24: -1041133.7
A25: 42200 | B25: -1898.23 | C25: -1898.23 | D25: -3796.46
A26: Grand Total | B26: -947398.37 | C26: -1098701.5 | D26: -2046099.9

Sheet General Ledger report
A1: GL | B1: Posted dt. | C1: Doc dt. | D1: Doc | E1: Memo/Description | F1: Department | G1: Department name | H1: Vendor name | I1: Location name | J1: Item | K1: Customer name | L1: Item name | M1: Customer | N1: Product Type | O1: Txn No | P1: JNL | Q1: Debit | R1: Credit | S1: Balance | T1: Billing
A2: 40000 | B2: 45961 | C2: 45961 | E2: Accrual for Irvine Invoices- Oct REV Sept 2025 INV | I2: Irvine | K2: 7C Escrow | M2: C00002 | O2: 24186 | P2: ARJ | Q2: 351.5 | S2: 351.5
A3: 40000 | B3: 45961 | C3: 45961 | E3: Accrual for Irvine Invoices- Oct REV Sept 2025 INV | I3: Irvine | K3: Peak Real Estate Management LLC | M3: C00302 | O3: 24186 | P3: ARJ | Q3: 368.58 | S3: 368.58
A4: 40000 | B4: 45961 | C4: 45961 | E4: Accrual for Irvine Invoices- Oct REV Sept 2025 INV | I4: Irvine | K4: Your Escrow Company | M4: C-10008 | O4: 24186 | P4: ARJ | Q4: 449.4 | S4: 449.4
A5: 40000 | B5: 45961 | C5: 45961 | E5: Accrual for Irvine Invoices- Oct REV Sept 2025 INV | I5: Irvine | K5: Kaplan & Trombi | M5: C00165 | O5: 24186 | P5: ARJ | Q5: 614.25 | S5: 614.25
A6: 40000 | B6: 45961 | C6: 45961 | E6: Accrual for Irvine Invoices- Oct REV Sept 2025 INV | I6: Irvine | K6: Primetime Escrow | M6: C00215 | O6: 24186 | P6: ARJ | Q6: 653.38 | S6: 653.38
A7: 40000 | B7: 45961 | C7: 45961 | E7: Accrual for Irvine Invoices- Oct REV Sept 2025 INV | I7: Irvine | K7: Modiv | M7: C00224 | O7: 24186 | P7: ARJ | Q7: 843.6 | S7: 843.6
A8: 40000 | B8: 45961 | C8: 45961 | E8: Accrual for Irvine Invoices- Oct REV Sept 2025 INV | I8: Irvine | K8: Capital Financial Consultants Group | M8: C00060 | O8: 24186 | P8: ARJ | Q8: 1125.3 | S8: 1125.3
A9: 40000 | B9: 45961 | C9: 45961 | E9: Accrual for Irvine Invoices- Oct REV Sept 2025 INV | I9: Irvine | K9: Linwood Engineering Associates | M9: C00178 | O9: 24186 | P9: ARJ | Q9: 1378.95 | S9: 1378.95
A10: 40000 | B10: 45961 | C10: 45961 | E10: Accrual for Irvine Invoices- Oct REV Sept 2025 INV | I10: Irvine | K10: Project Hope Alliance | M10: C00216 | O10: 24186 | P10: ARJ | Q10: 1492.52 | S10: 1492.52
A11: 40000 | B11: 45961 | C11: 45961 | E11: Accrual for Irvine Invoices- Oct REV Sept 2025 INV | I11: Irvine | K11: Anonymous LLC | M11: C00020 | O11: 24186 | P11: ARJ | Q11: 2595.6 | S11: 2595.6
A12: 40000 | B12: 45961 | C12: 45961 | E12: Accrual for Irvine Invoices- Oct REV Sept 2025 INV | I12: Irvine | K12: Groundswell | M12: C00204 | O12: 24186 | P12: ARJ | Q12: 2648 | S12: 2648
A13: 40000 | B13: 45961 | C13: 45961 | E13: Accrual for Irvine Invoices- Oct REV Sept 2025 INV | I13: Irvine | K13: Free Wheelchair Mission | M13: C00116 | O13: 24186 | P13: ARJ | Q13: 2666.1 | S13: 2666.1
... A135: 42100 | B135: 45930 | C135: 45930 | E135: Accrual for Irvine Invoices- Sept REV Aug 2025 INV | I135: Irvine | K135: Hercules OEM Group | M135: C00139 | O135: 24080 | P135: ARJ | Q135: 1055 | S135: 1055
A136: 41500 | B136: 45925 | C136: 45925 | D136: 180271 | E136: Invoice - 24 Hour Home Care | F136: D-004 | G136: Projects | I136: Modesto | K136: 24 Hour Home Care | M136: 24hrcares | O136: 23658 | P136: ARJ | R136: 800 | S136: -800 | T136: x
A137: 42100 | B137: 45901 | C137: 45901 | D137: 179772 | E137: Invoice - 24 Hour Home Care: 24x7 Gateway Security Monitoring | F137: D-005 | G137: Security | I137: Modesto | J137: DPM-FWM-SM | K137: 24 Hour Home Care | L137: 24x7 Gateway Security Monitoring Small | M137: 24hrcares | O137: 23534 | P137: ARJ | R137: 1225 | S137: -1225 | T137: x
A138: 42100 | B138: 45931 | C138: 45931 | D138: 180324 | E138: Invoice - 24 Hour Home Care: 24x7 Gateway Security Monitoring | F138: D-005 | G138: Security | I138: Modesto | J138: DPM-FWM-SM | K138: 24 Hour Home Care | L138: 24x7 Gateway Security Monitoring Small | M138: 24hrcares | O138: 23749 | P138: ARJ | R138: 1225 | S138: -1225 | T138: x
A139: 42100 | B139: 45901 | C139: 45901 | D139: 179772 | E139: Invoice - 24 Hour Home Care: AI Powered Email Filtering and Phishing Protection | F139: D-005 | G139: Security | I139: Modesto | J139: IS-ESP-1 | K139: 24 Hour Home Care | L139: Email Security | M139: 24hrcares | O139: 23534 | P139: ARJ | R139: 2502 | S139: -2502 | T139: x
A140: 42100 | B140: 45931 | C140: 45931 | D140: 180324 | E140: Invoice - 24 Hour Home Care: AI Powered Email Filtering and Phishing Protection | F140: D-005 | G140: Security | I140: Modesto | J140: IS-ESP-1 | K140: 24 Hour Home Care | L140: Email Security | M140: 24hrcares | O140: 23749 | P140: ARJ | R140: 2502 | S140: -2502 | T140: x
A141: 42100 | B141: 45901 | C141: 45901 | D141: 179772 | E141: Invoice - 24 Hour Home Care: Dark Web Monitoring Service - 1 Domain | F141: D-005 | G141: Security | I141: Modesto | J141: SecureID | K141: 24 Hour Home Care | L141: Dark Web Monitoring | M141: 24hrcares | O141: 23534 | P141: ARJ | R141: 100 | S141: -100 | T141: x
A142: 42100 | B142: 45931 | C142: 45931 | D142: 180324 | E142: Invoice - 24 Hour Home Care: Dark Web Monitoring Service - 1 Domain | F142: D-005 | G142: Security | I142: Modesto | J142: SecureID | K142: 24 Hour Home Care | L142: Dark Web Monitoring | M142: 24hrcares | O142: 23749 | P142: ARJ | R142: 100 | S142: -100 | T142: x
A143: 41300 | B143: 45901 | C143: 45901 | D143: 179772 | E143: Invoice - 24 Hour Home Care: Datapath Managed Office 365 Backup - 1 User - 1 month | F143: D-005 | G143: Security | I143: Modesto | J143: DPMB-O365 | K143: 24 Hour Home Care | L143: Datapath Managed Office 365 Backup - 1 User - 1 mo | M143: 24hrcares | O143: 23534 | P143: ARJ | R143: 1764 | S143: -1764 | T143: x
A144: 41300 | B144: 45931 | C144: 45931 | D144: 180324 | E144: Invoice - 24 Hour Home Care: Datapath Managed Office 365 Backup - 1 User - 1 month | F144: D-005 | G144: Security | I144: Modesto | J144: DPMB-O365 | K144: 24 Hour Home Care | L144: Datapath Managed Office 365 Backup - 1 User - 1 mo | M144: 24hrcares | O144: 23749 | P144: ARJ | R144: 1784 | S144: -1784 | T144: x
A145: 42100 | B145: 45901 | C145: 45901 | D145: 179772 | E145: Invoice - 24 Hour Home Care: Endpoint Advanced Threat Protection - EDR 24x7 Monitoring - Per Endpoint | F145: D-005 | G145: Security | I145: Modesto | J145: DPM-Huntress | K145: 24 Hour Home Care | L145: Huntress Advanced Threat Protection | M145: 24hrcares | O145: 23534 | P145: ARJ | R145: 2890 | S145: -2890 | T145: x
A146: 42100 | B146: 45931 | C146: 45931 | D146: 180324 | E146: Invoice - 24 Hour Home Care: Endpoint Advanced Threat Protection - EDR 24x7 Monitoring - Per Endpoint | F146: D-005 | G146: Security | I146: Modesto | J146: DPM-Huntress | K146: 24 Hour Home Care | L146: Huntress Advanced Threat Protection | M146: 24hrcares | O146: 23749 | P146: ARJ | R146: 3000 | S146: -3000 | T146: x
A147: 41320 | B147: 45901 | C147: 45901 | D147: 179772 | E147: Invoice - 24 Hour Home Care: Managed Backup - Virtual Server | F147: D-003 | G147: MSP | I147: Modesto | J147: CB Prot Vir Mac | K147: 24 Hour Home Care | L147: MTS Cyber Protect Virtual Machines | M147: 24hrcares | O147: 23534 | P147: ARJ | R147: 120 | S147: -120 | T147: x
A148: 41320 | B148: 45931 | C148: 45931 | D148: 180324 | E148: Invoice - 24 Hour Home Care: Managed Backup - Virtual Server | F148: D-003 | G148: MSP | I148: Modesto | J148: CB Prot Vir Mac | K148: 24 Hour Home Care | L148: MTS Cyber Protect Virtual Machines | M148: 24hrcares | O148: 23749 | P148: ARJ | R148: 120 | S148: -120 | T148: x
... A319: 40000 | B319: 45931 | C319: 45931 | D319: 180331 | E319: Invoice - Advantage Home Care: Managed Services-User | F319: D-003 | G319: MSP | I319: Modesto | J319: T-Managed Services-User | K319: Advantage Home Care | L319: Managed Services-User | M319: C-10370 | O319: 23756 | P319: ARJ | R319: 2010 | S319: -2010 | T319: x
A320: 41500 | B320: 45961 | C320: 45961 | D320: 181164 | E320: Invoice - Agape Corporation WEB Du | F320: D-004 | G320: Projects | I320: Modesto | K320: Agape Corporation WEB Du | M320: C00004 | O320: 24210 | P320: ARJ | R320: 1900 | S320: -1900 | T320: x
A321: 41320 | B321: 45901 | C321: 45901 | D321: 179740 | E321: Invoice - Agape Corporation WEB Du: Managed Backup - Virtual Server | F321: D-003 | G321: MSP | I321: Fresno | J321: CB Prot Vir Mac | K321: Agape Corporation WEB Du | L321: MTS Cyber Protect Virtual Machines | M321: C00004 | O321: 23299 | P321: ARJ | R321: 250 | S321: -250 | T321: x
A322: 41320 | B322: 45931 | C322: 45931 | D322: 180292 | E322: Invoice - Agape Corporation WEB Du: Managed Backup - Virtual Server | F322: D-003 | G322: MSP | I322: Fresno | J322: CB Prot Vir Mac | K322: Agape Corporation WEB Du | L322: MTS Cyber Protect Virtual Machines | M322: C00004 | O322: 23716 | P322: ARJ | R322: 250 | S322: -250 | T322: x
A323: 40000 | B323: 45901 | C323: 45901 | D323: 179740 | E323: Invoice - Agape Corporation WEB Du: Managed Service | F323: D-003 | G323: MSP | I323: Fresno | J323: Hybrid Managed Service | K323: Agape Corporation WEB Du | L323: Hybrid Managed Service | M323: C00004 | O323: 23299 | P323: ARJ | R323: 3288.79 | S323: -3288.79 | T323: x
A324: 40000 | B324: 45931 | C324: 45931 | D324: 180292 | E324: Invoice - Agape Corporation WEB Du: Managed Service | F324: D-003 | G324: MSP | I324: Fresno | J324: Hybrid Managed Service | K324: Agape Corporation WEB Du | L324: Hybrid Managed Service | M324: C00004 | O324: 23716 | P324: ARJ | R324: 3288.79 | S324: -3288.79 | T324: x
A325: 41200 | B325: 45901 | C325: 45901 | D325: 179740 | E325: Invoice - Agape Corporation WEB Du: Palo Alto Networks Firewall Service 460 | F325: D-005 | G325: Security | I325: Fresno | J325: PAN-460-HAAS | K325: Agape Corporation WEB Du | L325: Palo Alto Networks Firewall Service 440 | M325: C00004 | O325: 23299 | P325: ARJ | R325: 1600 | S325: -1600 | T325: x
A326: 41200 | B326: 45931 | C326: 45931 | D326: 180292 | E326: Invoice - Agape Corporation WEB Du: Palo Alto Networks Firewall Service 460 | F326: D-005 | G326: Security | I326: Fresno | J326: PAN-460-HAAS | K326: Agape Corporation WEB Du | L326: Palo Alto Networks Firewall Service 440 | M326: C00004 | O326: 23716 | P326: ARJ | R326: 1600 | S326: -1600 | T326: x
A327: 42100 | B327: 45901 | C327: 45901 | D327: 179741 | E327: Invoice - Agee Construction: Duo MFA - 2 Factor Authentication - 1 User - 1 Month | F327: D-005 | G327: Security | I327: Fresno | J327: DuoMFA | K327: Agee Construction | L327: Duo MFA - 1 User | M327: C00005 | O327: 23300 | P327: ARJ | R327: 126 | S327: -126 | T327: x
A328: 42100 | B328: 45931 | C328: 45931 | D328: 180293 | E328: Invoice - Agee Construction: Duo MFA - 2 Factor Authentication - 1 User - 1 Month | F328: D-005 | G328: Security | I328: Fresno | J328: DuoMFA | K328: Agee Construction | L328: Duo MFA - 1 User | M328: C00005 | O328: 23717 | P328: ARJ | R328: 126 | S328: -126 | T328: x
A329: 42100 | B329: 45901 | C329: 45901 | D329: 179741 | E329: Invoice - Agee Construction: Endpoint Advanced Threat Protection - EDR 24x7 Monitoring - Per Endpoint | F329: D-005 | G329: Security | I329: Fresno | J329: DPM-Huntress | K329: Agee Construction | L329: Huntress Advanced Threat Protection | M329: C00005 | O329: 23300 | P329: ARJ | R329: 273 | S329: -273 | T329: x
A330: 42100 | B330: 45931 | C330: 45931 | D330: 180293 | E330: Invoice - Agee Construction: Endpoint Advanced Threat Protection - EDR 24x7 Monitoring - Per Endpoint | F330: D-005 | G330: Security | I330: Fresno | J330: DPM-Huntress | K330: Agee Construction | L330: Huntress Advanced Threat Protection | M330: C00005 | O330: 23717 | P330: ARJ | R330: 280 | S330: -280 | T330: x
A331: 41450 | B331: 45901 | C331: 45901 | D331: 179741 | E331: Invoice - Agee Construction: Exchange Online (Plan 1) - Annual Commitment, Monthly Billing - 1 User | F331: D-003 | G331: MSP | I331: Fresno | J331: C0LH16-0001-1Y1M | K331: Agee Construction | L331: Exchange Online (Plan 1) Annual Paid Monthly | M331: C00005 | O331: 23300 | P331: ARJ | R331: 112 | S331: -112 | T331: x
A332: 41450 | B332: 45931 | C332: 45931 | D332: 180293 | E332: Invoice - Agee Construction: Exchange Online (Plan 1) - Annual Commitment, Monthly Billing - 1 User | F332: D-003 | G332: MSP | I332: Fresno | J332: C0LH16-0001-1Y1M | K332: Agee Construction | L332: Exchange Online (Plan 1) Annual Paid Monthly | M332: C00005 | O332: 23717 | P332: ARJ | R332: 112 | S332: -112 | T332: x
... A352: 41200 | B352: 45931 | C352: 45931 | D352: 180293 | E352: Invoice - Agee Construction: Palo Alto Networks Firewall Service 440 | F352: D-005 | G352: Security | I352: Fresno | J352: PAN-440-HAAS | K352: Agee Construction | L352: Palo Alto Networks Firewall Service 440 | M352: C00005 | O352: 23717 | P352: ARJ | R352: 262.5 | S352: -262.5 | T352: x
A353: 41500 | B353: 45922 | C353: 45922 | D353: 180248OH | E353: Invoice - Albert Einstein Academy of Ohio | F353: D-028 | G353: Installation Team | I353: Ohio | K353: Albert Einstein Academy of Ohio | M353: C-10311 | O353: 23672 | P353: ARJ | R353: 4150 | S353: -4150 | T353: x
A354: 42000 | B354: 45922 | C354: 45922 | D354: 180248OH | E354: Invoice - Albert Einstein Academy of Ohio: Annual Hosting by 3CX | F354: D-001 | G354: Sales | I354: Ohio | J354: Hosted By 3CX | K354: Albert Einstein Academy of Ohio | L354: Annual Hosting by 3CX | M354: C-10311 | O354: 23672 | P354: ARJ | R354: 1145 | S354: -1145 | T354: x
A355: 40000 | B355: 45901 | C355: 45901 | D355: 180089OH | E355: Invoice - Albert Einstein Academy of Ohio: Classroom Support | F355: D-003 | G355: MSP | I355: Ohio | J355: MSC_CS | K355: Albert Einstein Academy of Ohio | L355: Classroom Support | M355: C-10311 | O355: 23331 | P355: ARJ | R355: 463.5 | S355: -463.5 | T355: x
A356: 40000 | B356: 45931 | C356: 45931 | D356: 180446OH | E356: Invoice - Albert Einstein Academy of Ohio: Classroom Support | F356: D-003 | G356: MSP | I356: Ohio | J356: MSC_CS | K356: Albert Einstein Academy of Ohio | L356: Classroom Support | M356: C-10311 | O356: 23865 | P356: ARJ | R356: 463.5 | S356: -463.5 | T356: x
A357: 41300 | B357: 45922 | C357: 45922 | D357: 180248OH | E357: Invoice - Albert Einstein Academy of Ohio: Grandstream VoIP Gateway - 2 x RJ-45 - 1 x FXS - 1 x FXO - Fast Ethernet | F357: D-001 | G357: Sales | I357: Ohio | J357: HT813 | K357: Albert Einstein Academy of Ohio | L357: Grandstream VoIP Gateway | M357: C-10311 | O357: 23672 | P357: ARJ | R357: 76.44 | S357: -76.44 | T357: x
A358: 40000 | B358: 45901 | C358: 45901 | D358: 180089OH | E358: Invoice - Albert Einstein Academy of Ohio: Location Technology Support | F358: D-003 | G358: MSP | I358: Ohio | J358: MSC_LTS | K358: Albert Einstein Academy of Ohio | L358: Location Technology Support | M358: C-10311 | O358: 23331 | P358: ARJ | R358: 41.2 | S358: -41.2 | T358: x
A359: 40000 | B359: 45931 | C359: 45931 | D359: 180446OH | E359: Invoice - Albert Einstein Academy of Ohio: Location Technology Support | F359: D-003 | G359: MSP | I359: Ohio | J359: MSC_LTS | K359: Albert Einstein Academy of Ohio | L359: Location Technology Support | M359: C-10311 | O359: 23865 | P359: ARJ | R359: 41.2 | S359: -41.2 | T359: x
A360: 42300 | B360: 45901 | C360: 45901 | D360: 180089OH | E360: Invoice - Albert Einstein Academy of Ohio: MobileTek Per Seat Phone License | F360: D-003 | G360: MSP | I360: Ohio | J360: m3cx-41to50 Seat | K360: Albert Einstein Academy of Ohio | L360: MobileTek Per Seat Phone License | M360: C-10311 | O360: 23331 | P360: ARJ | R360: 112.5 | S360: -112.5 | T360: x
A361: 42300 | B361: 45931 | C361: 45931 | D361: 180446OH | E361: Invoice - Albert Einstein Academy of Ohio: MobileTek Per Seat Phone License | F361: D-003 | G361: MSP | I361: Ohio | J361: m3cx-41to50 Seat | K361: Albert Einstein Academy of Ohio | L361: MobileTek Per Seat Phone License | M361: C-10311 | O361: 23865 | P361: ARJ | R361: 112.5 | S361: -112.5 | T361: x
A362: 40000 | B362: 45901 | C362: 45901 | D362: 180089OH | E362: Invoice - Albert Einstein Academy of Ohio: Staff Support | F362: D-003 | G362: MSP | I362: Ohio | J362: MSC_SS | K362: Albert Einstein Academy of Ohio | L362: Staff Support | M362: C-10311 | O362: 23331 | P362: ARJ | R362: 1699.5 | S362: -1699.5 | T362: x
A363: 40000 | B363: 45931 | C363: 45931 | D363: 180446OH | E363: Invoice - Albert Einstein Academy of Ohio: Staff Support | F363: D-003 | G363: MSP | I363: Ohio | J363: MSC_SS | K363: Albert Einstein Academy of Ohio | L363: Staff Support | M363: C-10311 | O363: 23865 | P363: ARJ | R363: 1699.5 | S363: -1699.5 | T363: x
A364: 40000 | B364: 45901 | C364: 45901 | D364: 180089OH | E364: Invoice - Albert Einstein Academy of Ohio: Student Device Management | F364: D-003 | G364: MSP | I364: Ohio | J364: MSC_SDM | K364: Albert Einstein Academy of Ohio | L364: Student Device Management | M364: C-10311 | O364: 23331 | P364: ARJ | R364: 638 | S364: -638 | T364: x
A365: 40000 | B365: 45931 | C365: 45931 | D365: 180446OH | E365: Invoice - Albert Einstein Academy of Ohio: Student Device Management | F365: D-003 | G365: MSP | I365: Ohio | J365: MSC_SDM | K365: Albert Einstein Academy of Ohio | L365: Student Device Management | M365: C-10311 | O365: 23865 | P365: ARJ | R365: 638 | S365: -638 | T365: x
A366: 42000 | B366: 45922 | C366: 45922 | D366: 180248OH | E366: Invoice - Albert Einstein Academy of Ohio: Yealink T44U IP Phone - Corded - Corded - Wall Mountable - 2.8â€ Color LCD - 12 x Total Line - VoIP LCD - 2 x Network (RJ-45) - PoE Ports | F366: D-001 | G366: Sales | I366: Ohio | J366: SIP-T44U | K366: Albert Einstein Academy of Ohio | L366: Yealink IP Phone - Corded - Corded/Cordless - Wi- | M366: C-10311 | O366: 23672 | P366: ARJ | R366: 1728 | S366: -1728 | T366: x
A367: 42100 | B367: 45901 | C367: 45901 | D367: 179779 | E367: Invoice - Alliance Services: 24x7 Gateway Security Monitoring | F367: D-005 | G367: Security | I367: Modesto | J367: DPM-FWM-SM | K367: Alliance Services | L367: 24x7 Gateway Security Monitoring Small | M367: C-10369 | O367: 23479 | P367: ARJ | R367: 175 | S367: -175 | T367: x
A368: 42100 | B368: 45931 | C368: 45931 | D368: 180332 | E368: Invoice - Alliance Services: 24x7 Gateway Security Monitoring | F368: D-005 | G368: Security | I368: Modesto | J368: DPM-FWM-SM | K368: Alliance Services | L368: 24x7 Gateway Security Monitoring Small | M368: C-10369 | O368: 23757 | P368: ARJ | R368: 175 | S368: -175 | T368: x
A369: 42100 | B369: 45901 | C369: 45901 | D369: 179779 | E369: Invoice - Alliance Services: AI Powered Email Filtering and Phishing Protection | F369: D-005 | G369: Security | I369: Modesto | J369: IS-ESP-1 | K369: Alliance Services | L369: Email Security | M369: C-10369 | O369: 23479 | P369: ARJ | R369: 168 | S369: -168 | T369: x
A370: 42100 | B370: 45931 | C370: 45931 | D370: 180332 | E370: Invoice - Alliance Services: AI Powered Email Filtering and Phishing Protection | F370: D-005 | G370: Security | I370: Modesto | J370: IS-ESP-1 | K370: Alliance Services | L370: Email Security | M370: C-10369 | O370: 23757 | P370: ARJ | R370: 168 | S370: -168 | T370: x
A371: 42100 | B371: 45901 | C371: 45901 | D371: 179779 | E371: Invoice - Alliance Services: Dark Web Monitoring Service - 1 Domain | F371: D-005 | G371: Security | I371: Modesto | J371: SecureID | K371: Alliance Services | L371: Dark Web Monitoring | M371: C-10369 | O371: 23479 | P371: ARJ | R371: 100 | S371: -100 | T371: x
A372: 42100 | B372: 45931 | C372: 45931 | D372: 180332 | E372: Invoice - Alliance Services: Dark Web Monitoring Service - 1 Domain | F372: D-005 | G372: Security | I372: Modesto | J372: SecureID | K372: Alliance Services | L372: Dark Web Monitoring | M372: C-10369 | O372: 23757 | P372: ARJ | R372: 100 | S372: -100 | T372: x
A373: 42100 | B373: 45901 | C373: 45901 | D373: 179779 | E373: Invoice - Alliance Services: Endpoint Advanced Threat Protection - EDR 24x7 Monitoring - Per Endpoint | F373: D-005 | G373: Security | I373: Modesto | J373: DPM-Huntress | K373: Alliance Services | L373: Huntress Advanced Threat Protection | M373: C-10369 | O373: 23479 | P373: ARJ | R373: 130 | S373: -130 | T373: x
A374: 42100 | B374: 45931 | C374: 45931 | D374: 180332 | E374: Invoice - Alliance Services: Endpoint Advanced Threat Protection - EDR 24x7 Monitoring - Per Endpoint | F374: D-005 | G374: Security | I374: Modesto | J374: DPM-Huntress | K374: Alliance Services | L374: Huntress Advanced Threat Protection | M374: C-10369 | O374: 23757 | P374: ARJ | R374: 120 | S374: -120 | T374: x
A375: 41450 | B375: 45901 | C375: 45901 | D375: 179779 | E375: Invoice - Alliance Services: Exchange Online (Plan 1) - Annual Commitment, Monthly Billing - 1 User | F375: D-003 | G375: MSP | I375: Modesto | J375: C0LH16-0001-1Y1M | K375: Alliance Services | L375: Exchange Online (Plan 1) Annual Paid Monthly | M375: C-10369 | O375: 23479 | P375: ARJ | R375: 8 | S375: -8 | T375: x
A376: 41450 | B376: 45931 | C376: 45931 | D376: 180332 | E376: Invoice - Alliance Services: Exchange Online (Plan 1) - Annual Commitment, Monthly Billing - 1 User | F376: D-003 | G376: MSP | I376: Modesto | J376: C0LH16-0001-1Y1M | K376: Alliance Services | L376: Exchange Online (Plan 1) Annual Paid Monthly | M376: C-10369 | O376: 23757 | P376: ARJ | R376: 8 | S376: -8 | T376: x
A377: 41320 | B377: 45901 | C377: 45901 | D377: 179779 | E377: Invoice - Alliance Services: Managed Backup - Server | F377: D-003 | G377: MSP | I377: Modesto | J377: mMTS CyberPS | K377: Alliance Services | L377: MTS Cyber Protect Servers | M377: C-10369 | O377: 23479 | P377: ARJ | R377: 50 | S377: -50 | T377: x
A378: 41320 | B378: 45931 | C378: 45931 | D378: 180332 | E378: Invoice - Alliance Services: Managed Backup - Server | F378: D-003 | G378: MSP | I378: Modesto | J378: mMTS CyberPS | K378: Alliance Services | L378: MTS Cyber Protect Servers | M378: C-10369 | O378: 23757 | P378: ARJ | R378: 50 | S378: -50 | T378: x
... A520: 41450 | B520: 45931 | C520: 45931 | D520: 180335 | E520: Invoice - Applegate Teeples Drilling: Project Plan 3 - Annual Commitment, Monthly Billing - 1 User | F520: D-003 | G520: MSP | I520: Modesto | J520: C0HDB0-0002-1Y1M | K520: Applegate Teeples Drilling | L520: Project Plan 3 Annual Paid Monthly | M520: C00022 | O520: 23760 | P520: ARJ | R520: 60 | S520: -60 | T520: x
A521: 40000 | B521: 45901 | C521: 45901 | D521: 179984OH | E521: Invoice - Arcanum Butler Local School District: Basic AD/DNS/DHCP Windows Server Patching and Support - Physical Box | F521: D-003 | G521: MSP | I521: Ohio | J521: MSCS-Windows Server Non-Virtua | K521: Arcanum Butler Local School District | L521: Basic AD/DNS/DHCP Windows Server Patching and Support | M521: C-10200 | O521: 23332 | P521: ARJ | R521: 555 | S521: -555 | T521: x
A522: 40000 | B522: 45931 | C522: 45931 | D522: 180447OH | E522: Invoice - Arcanum Butler Local School District: Basic AD/DNS/DHCP Windows Server Patching and Support - Physical Box | F522: D-003 | G522: MSP | I522: Ohio | J522: MSCS-Windows Server Non-Virtua | K522: Arcanum Butler Local School District | L522: Basic AD/DNS/DHCP Windows Server Patching and Support | M522: C-10200 | O522: 23866 | P522: ARJ | R522: 555 | S522: -555 | T522: x
A523: 40000 | B523: 45901 | C523: 45901 | D523: 179984OH | E523: Invoice - Arcanum Butler Local School District: E-Rate MIBS Support for E-Rate Eligible Equipment | F523: D-003 | G523: MSP | I523: Ohio | J523: T-Managed | K523: Arcanum Butler Local School District | L523: E-Rate MIBS Support | M523: C-10200 | O523: 23332 | P523: ARJ | R523: 252 | S523: -252 | T523: x
A524: 40000 | B524: 45931 | C524: 45931 | D524: 180447OH | E524: Invoice - Arcanum Butler Local School District: E-Rate MIBS Support for E-Rate Eligible Equipment | F524: D-003 | G524: MSP | I524: Ohio | J524: T-Managed | K524: Arcanum Butler Local School District | L524: E-Rate MIBS Support | M524: C-10200 | O524: 23866 | P524: ARJ | R524: 252 | S524: -252 | T524: x
A525: 40000 | B525: 45901 | C525: 45901 | D525: 179984OH | E525: Invoice - Arcanum Butler Local School District: Extreme Networks X440-G2-48p-10GE4 | F525: D-003 | G525: MSP | I525: Ohio | J525: mMIBSx440G248 | K525: Arcanum Butler Local School District | L525: Extreme Networks X440-G2-48p-10GE4 | M525: C-10200 | O525: 23332 | P525: ARJ | R525: 322 | S525: -322 | T525: x
A526: 40000 | B526: 45931 | C526: 45931 | D526: 180447OH | E526: Invoice - Arcanum Butler Local School District: Extreme Networks X440-G2-48p-10GE4 | F526: D-003 | G526: MSP | I526: Ohio | J526: mMIBSx440G248 | K526: Arcanum Butler Local School District | L526: Extreme Networks X440-G2-48p-10GE4 | M526: C-10200 | O526: 23866 | P526: ARJ | R526: 322 | S526: -322 | T526: x
A527: 40000 | B527: 45901 | C527: 45901 | D527: 179984OH | E527: Invoice - Arcanum Butler Local School District: Extreme Networks X460-G2-48p-10GE4 | F527: D-003 | G527: MSP | I527: Ohio | J527: mMIBS ExnX460G248P | K527: Arcanum Butler Local School District | L527: Extreme Networks X460-G2-48p-10GE4 | M527: C-10200 | O527: 23332 | P527: ARJ | R527: 32 | S527: -32 | T527: x
A528: 40000 | B528: 45931 | C528: 45931 | D528: 180447OH | E528: Invoice - Arcanum Butler Local School District: Extreme Networks X460-G2-48p-10GE4 | F528: D-003 | G528: MSP | I528: Ohio | J528: mMIBS ExnX460G248P | K528: Arcanum Butler Local School District | L528: Extreme Networks X460-G2-48p-10GE4 | M528: C-10200 | O528: 23866 | P528: ARJ | R528: 32 | S528: -32 | T528: x
A529: 40000 | B529: 45901 | C529: 45901 | D529: 179971OH | E529: Invoice - Arts and College Preparatory Academy: Classroom Support | F529: D-003 | G529: MSP | I529: Ohio | J529: MSC_CS | K529: Arts and College Preparatory Academy | L529: Classroom Support | M529: C-10062 | O529: 23334 | P529: ARJ | R529: 220 | S529: -220 | T529: x
A530: 40000 | B530: 45931 | C530: 45931 | D530: 180449OH | E530: Invoice - Arts and College Preparatory Academy: Classroom Support | F530: D-003 | G530: MSP | I530: Ohio | J530: MSC_CS | K530: Arts and College Preparatory Academy | L530: Classroom Support | M530: C-10062 | O530: 23868 | P530: ARJ | R530: 220 | S530: -220 | T530: x
A531: 40000 | B531: 45901 | C531: 45901 | D531: 179971OH | E531: Invoice - Arts and College Preparatory Academy: Cloud Managed Printing | F531: D-003 | G531: MSP | I531: Ohio | J531: MSC_PS | K531: Arts and College Preparatory Academy | L531: Cloud Managed Printing Support | M531: C-10062 | O531: 23334 | P531: ARJ | R531: 75 | S531: -75 | T531: x
A532: 40000 | B532: 45931 | C532: 45931 | D532: 180449OH | E532: Invoice - Arts and College Preparatory Academy: Cloud Managed Printing | F532: D-003 | G532: MSP | I532: Ohio | J532: MSC_PS | K532: Arts and College Preparatory Academy | L532: Cloud Managed Printing Support | M532: C-10062 | O532: 23868 | P532: ARJ | R532: 75 | S532: -75 | T532: x
... A555: 40000 | B555: 45931 | C555: 45931 | D555: 180449OH | E555: Invoice - Arts and College Preparatory Academy: Student Device Management | F555: D-003 | G555: MSP | I555: Ohio | J555: MSC_SDM | K555: Arts and College Preparatory Academy | L555: Student Device Management | M555: C-10062 | O555: 23868 | P555: ARJ | R555: 952 | S555: -952 | T555: x
A556: 42100 | B556: 45901 | C556: 45901 | D556: 179783 | E556: Invoice - ATD Home Health Agency, INC: AI Powered Email Filtering and Phishing Protection | F556: D-005 | G556: Security | I556: Modesto | J556: IS-ESP-1 | K556: ATD Home Health Agency, INC | L556: Email Security | M556: C-10393 | O556: 23478 | P556: ARJ | R556: 234 | S556: -234 | T556: x
A557: 42100 | B557: 45931 | C557: 45931 | D557: 180336 | E557: Invoice - ATD Home Health Agency, INC: AI Powered Email Filtering and Phishing Protection | F557: D-005 | G557: Security | I557: Modesto | J557: IS-ESP-1 | K557: ATD Home Health Agency, INC | L557: Email Security | M557: C-10393 | O557: 23761 | P557: ARJ | R557: 234 | S557: -234 | T557: x
A558: 42100 | B558: 45901 | C558: 45901 | D558: 179783 | E558: Invoice - ATD Home Health Agency, INC: Dark Web Monitoring Service - 1 Domain | F558: D-005 | G558: Security | I558: Modesto | J558: SecureID | K558: ATD Home Health Agency, INC | L558: Dark Web Monitoring | M558: C-10393 | O558: 23478 | P558: ARJ | R558: 100 | S558: -100 | T558: x
A559: 42100 | B559: 45931 | C559: 45931 | D559: 180336 | E559: Invoice - ATD Home Health Agency, INC: Dark Web Monitoring Service - 1 Domain | F559: D-005 | G559: Security | I559: Modesto | J559: SecureID | K559: ATD Home Health Agency, INC | L559: Dark Web Monitoring | M559: C-10393 | O559: 23761 | P559: ARJ | R559: 100 | S559: -100 | T559: x
A560: 42100 | B560: 45901 | C560: 45901 | D560: 179783 | E560: Invoice - ATD Home Health Agency, INC: Endpoint Advanced Threat Protection - EDR 24x7 Monitoring - Per Endpoint | F560: D-005 | G560: Security | I560: Modesto | J560: DPM-Huntress | K560: ATD Home Health Agency, INC | L560: Huntress Advanced Threat Protection | M560: C-10393 | O560: 23478 | P560: ARJ | R560: 195 | S560: -195 | T560: x
A561: 42100 | B561: 45931 | C561: 45931 | D561: 180336 | E561: Invoice - ATD Home Health Agency, INC: Endpoint Advanced Threat Protection - EDR 24x7 Monitoring - Per Endpoint | F561: D-005 | G561: Security | I561: Modesto | J561: DPM-Huntress | K561: ATD Home Health Agency, INC | L561: Huntress Advanced Threat Protection | M561: C-10393 | O561: 23761 | P561: ARJ | R561: 190 | S561: -190 | T561: x
A562: 40000 | B562: 45901 | C562: 45901 | D562: 179783 | E562: Invoice - ATD Home Health Agency, INC: Managed Endpoint Services | F562: D-003 | G562: MSP | I562: Modesto | J562: T-Managed Endpoint | K562: ATD Home Health Agency, INC | L562: Managed Endpoint Services | M562: C-10393 | O562: 23478 | P562: ARJ | R562: 245 | S562: -245 | T562: x
A563: 40000 | B563: 45931 | C563: 45931 | D563: 180336 | E563: Invoice - ATD Home Health Agency, INC: Managed Endpoint Services | F563: D-003 | G563: MSP | I563: Modesto | J563: T-Managed Endpoint | K563: ATD Home Health Agency, INC | L563: Managed Endpoint Services | M563: C-10393 | O563: 23761 | P563: ARJ | R563: 350 | S563: -350 | T563: x
A564: 42100 | B564: 45901 | C564: 45901 | D564: 179783 | E564: Invoice - ATD Home Health Agency, INC: Managed Security Awareness Training Program | F564: D-005 | G564: Security | I564: Modesto | J564: DPMSAT | K564: ATD Home Health Agency, INC | L564: Security Awareness Program | M564: C-10393 | O564: 23478 | P564: ARJ | R564: 200 | S564: -200 | T564: x
A565: 42100 | B565: 45931 | C565: 45931 | D565: 180336 | E565: Invoice - ATD Home Health Agency, INC: Managed Security Awareness Training Program | F565: D-005 | G565: Security | I565: Modesto | J565: DPMSAT | K565: ATD Home Health Agency, INC | L565: Security Awareness Program | M565: C-10393 | O565: 23761 | P565: ARJ | R565: 200 | S565: -200 | T565: x
A566: 40000 | B566: 45901 | C566: 45901 | D566: 179783 | E566: Invoice - ATD Home Health Agency, INC: Managed Services-Site | F566: D-003 | G566: MSP | I566: Modesto | J566: T-Managed Services Site | K566: ATD Home Health Agency, INC | L566: Managed Services-Site | M566: C-10393 | O566: 23478 | P566: ARJ | R566: 190 | S566: -190 | T566: x
A567: 40000 | B567: 45931 | C567: 45931 | D567: 180336 | E567: Invoice - ATD Home Health Agency, INC: Managed Services-Site | F567: D-003 | G567: MSP | I567: Modesto | J567: T-Managed Services Site | K567: ATD Home Health Agency, INC | L567: Managed Services-Site | M567: C-10393 | O567: 23761 | P567: ARJ | R567: 190 | S567: -190 | T567: x
... A643: 44000 | B643: 45922 | C643: 45922 | D643: 180231 | E643: Invoice - Borba Farms Partners: Shipping | F643: D-009 | G643: Admin | I643: Fresno | J643: QWShipping | K643: Borba Farms Partners | L643: Shipping | M643: C00045 | O643: 23663 | P643: ARJ | R643: 50.4 | S643: -50.4 | T643: x
A644: 41500 | B644: 45959 | C644: 45959 | D644: 181140OH | E644: Invoice - Caldwell Exempted Village | F644: D-028 | G644: Installation Team | I644: Ohio | K644: Caldwell Exempted Village | M644: C-10063 | O644: 24196 | P644: ARJ | R644: 1800 | S644: -1800 | T644: x
A645: 42000 | B645: 45931 | C645: 45931 | D645: 180572OH | E645: Invoice - Caldwell Exempted Village: 3CX 16PRO Annual License | F645: D-009 | G645: Admin | I645: Ohio | J645: VOIP_3CXLIC3 | K645: Caldwell Exempted Village | L645: 3CX 16PRO Annual License | M645: C-10063 | O645: 23946 | P645: ARJ | R645: 720 | S645: -720 | T645: x
A646: 42000 | B646: 45908 | C646: 45908 | D646: 180159OH | E646: Invoice - Caldwell Exempted Village: Bump Armor Ninja Shell for Lenovo 300e, 300w, 500e and 500w | F646: D-001 | G646: Sales | I646: Ohio | J646: LV-NS300E-G3-CS-FR | K646: Caldwell Exempted Village | L646: Ninja Shell for Lenovo 300e, 300w, 500e and 500w | M646: C-10063 | O646: 23582 | P646: ARJ | R646: 1620 | S646: -1620 | T646: x
A647: 42000 | B647: 45908 | C647: 45908 | D647: 180159OH | E647: Invoice - Caldwell Exempted Village: Chrome OS Mgmt Console Lic, EDU | F647: D-001 | G647: Sales | I647: Ohio | J647: CROSSWDISEDUNEW | K647: Caldwell Exempted Village | L647: Chrome OS Mgmt Console Lic, EDU | M647: C-10063 | O647: 23582 | P647: ARJ | R647: 2040 | S647: -2040 | T647: x
A648: 40000 | B648: 45901 | C648: 45901 | D648: 179935OH | E648: Invoice - Caldwell Exempted Village: E-Rate MIBS Support for E-Rate Eligible Equipment | F648: D-003 | G648: MSP | I648: Ohio | J648: T-Managed | K648: Caldwell Exempted Village | L648: E-Rate MIBS Support | M648: C-10063 | O648: 23335 | P648: ARJ | R648: 288.6 | S648: -288.6 | T648: x
...

Sheet 41700-50500
A1: OH | G1: CA
A2: Location name | B2: (Multiple Items) | G2: Location name | H2: (Multiple Items)
A3: GL | B3: 50500 | G3: GL | H3: 50500
A5: Sum of Balance | B5: Column Labels | G5: Sum of Balance | H5: Column Labels
B6: Sep | C6: Oct | D6: Grand Total | H6: Sep | I6: Oct | J6: Grand Total
A8: Row Labels | E8: =C8-B8 -> 0 | G8: Row Labels
A9: Caldwell Exempted Village | C9: 3230 | D9: 3230 | E9: =C9-B9 -> 3230 | G9: City of Atwater | H9: 3468.97 | I9: 35 | J9: 3503.97 | K9: =I9-H9 -> -3433.97
A10: Imagine Great Western Academy | B10: 400 | D10: 400 | E10: =C10-B10 -> -400 | G10: City of Firebaugh | H10: 1530 | J10: 1530 | K10: =I10-H10 -> -1530
A11: Imagine Klepinger Rd | C11: 1610 | D11: 1610 | E11: =C11-B11 -> 1610 | G11: Constellation Brands | H11: 860 | I11: 1875.55 | J11: 2735.55 | K11: =I11-H11 -> 1015.55
A12: Imagine Madison Ave | B12: 200 | D12: 200 | E12: =C12-B12 -> -200 | G12: Graceada Partners | I12: 5748.75 | J12: 5748.75 | K12: =I12-H12 -> 5748.75
A13: Imagine Pediatrics | C13: 273 | D13: 273 | E13: =C13-B13 -> 273 | G13: Nexus IT | I13: 1370 | J13: 1370 | K13: =I13-H13 -> 1370
A14: Imagine Sullivant | B14: 2000 | C14: 975 | D14: 2975 | E14: =C14-B14 -> -1025 | G14: (blank) | H14: 860 | I14: 1875.55 | J14: 2735.55 | K14: =I14-H14 -> 1015.55
A15: Invictus HS | C15: 513 | D15: 513 | E15: =C15-B15 -> 513 | G15: Grand Total | H15: 6718.97 | I15: 10904.85 | J15: 17623.82 | K15: =I15-H15 -> 4185.88
A16: River Gate HS | C16: 324 | D16: 324 | E16: =C16-B16 -> 324
A17: St Johns Jesuit High School | C17: 2549 | D17: 2549 | E17: =C17-B17 -> 2549
A18: Sunbridge Schools | C18: 486 | D18: 486 | E18: =C18-B18 -> 486
A19: The Richland School of Academic Arts | B19: 400 | C19: 300 | D19: 700 | E19: =C19-B19 -> -100
A20: Thyssenkrupp Automotive Technology | B20: 3000 | D20: 3000 | E20: =C20-B20 -> -3000 | G20: Location name | H20: (Multiple Items)
A21: USAC | B21: 579 | C21: 1875 | D21: 2454 | E21: =C21-B21 -> 1296 | G21: GL | H21: 41700
A22: Youthbuild Columbus Community | B22: 125 | D22: 125 | E22: =C22-B22 -> -125
A23: Grand Total | B23: 6704 | C23: 12135 | D23: 18839 | G23: Sum of Balance | H23: Column Labels
H24: Sep | I24: Oct | J24: Grand Total
G26: Row Labels
A27: Location name | B27: (Multiple Items) | G27: City of Atwater | H27: -4162.76 | I27: -70 | J27: -4232.76
A28: GL | B28: 41700 | G28: City of Firebaugh | H28: -1836 | J28: -1836
G29: Constellation Brands | H29: -1032 | I29: -2250.66 | J29: -3282.66
A30: Sum of Balance | B30: Column Labels | G30: Graceada Partners | I30: -6898.5 | J30: -6898.5
B31: Sep | C31: Oct | D31: Grand Total | G31: Nexus IT | I31: -1644 | J31: -1644
G32: Grand Total | H32: -7030.76 | I32: -10863.16 | J32: -17893.92
A33: Row Labels
A34: Caldwell Exempted Village | C34: -815 | D34: -815
A35: Imagine Great Western Academy | B35: -480 | D35: -480
A36: Imagine Klepinger Rd | C36: -1932 | D36: -1932
A37: Imagine Madison Ave | B37: -240 | D37: -240
A38: Imagine Pediatrics | C38: -312 | D38: -312
A39: Imagine Sullivant | B39: -2400 | C39: -1170 | D39: -3570
A40: Invictus HS | C40: -538.8 | D40: -538.8
A41: River Gate HS | C41: -400 | D41: -400
A42: St Johns Jesuit High School | C42: -3058 | D42: -3058
A43: Sunbridge Schools | C43: -550 | D43: -550
A44: The Richland School of Academic Arts | C44: -350 | D44: -350
A45: Thyssenkrupp Automotive Technology | B45: -3600 | D45: -3600
A46: USAC | B46: -579 | D46: -579
A47: Youthbuild Columbus Community | B47: -150 | D47: -150
A48: Grand Total | B48: -7449 | C48: -9125.8 | D48: -16574.8

Sheet COGS
A1: GL | B1: Posted dt. | C1: Doc dt. | D1: Doc | E1: Memo/Description | F1: Department | G1: Department name | H1: Vendor name | I1: Location name | J1: Item | K1: Customer name | L1: Item name | M1: Customer | N1: Product Type | O1: Txn No | P1: JNL | Q1: Debit | R1: Credit | S1: Balance | T1: Billing
A2: 50000 | B2: 45901 | C2: 45901 | D2: a1f25859-9c72-4f7c-9a51-8fd5397dbf22 | E2: Charge Card Transaction - Ramp: David Craig - G Suite Monthly | I2: Datapath, Inc. | O2: 4251 | P2: APJ | Q2: 1393.8 | S2: =Q2-R2 -> 1393.8
A3: 50000 | B3: 45901 | C3: 45901 | D3: c86ed39b-7d62-4177-b023-f4520db4e449 | E3: Charge Card Transaction - Ramp: Marshall Rownd - CWM Slack Integration | F3: D-006 | G3: Central Services | I3: Datapath, Inc. | O3: 4251 | P3: APJ | Q3: 1110 | S3: =Q3-R3 -> 1110
A4: 50000 | B4: 45901 | C4: 45901 | D4: COGS - 179740 | E4: COGS - 179740 | F4: D-003 | G4: MSP | I4: Fresno | J4: Tools-NMM-Total-Bill | K4: Agape Corporation WEB Du | L4: Tools-NMM-Total-Bill | M4: C00004 | O4: 10674 | P4: COG | Q4: 126 | S4: =Q4-R4 -> 126
A5: 50000 | B5: 45901 | C5: 45901 | D5: COGS - 179741 | E5: COGS - 179741 | F5: D-003 | G5: MSP | I5: Fresno | J5: Tools-NMM-Total-Bill | K5: Agee Construction | L5: Tools-NMM-Total-Bill | M5: C00005 | O5: 10675 | P5: COG | Q5: 27 | S5: =Q5-R5 -> 27
A6: 50000 | B6: 45901 | C6: 45901 | D6: COGS - 179742 | E6: COGS - 179742 | F6: D-003 | G6: MSP | I6: Fresno | J6: Tools-NMM-Total-Bill | K6: Aweta - Americas | L6: Tools-NMM-Total-Bill | M6: C00032 | O6: 10676 | P6: COG | Q6: 13.5 | S6: =Q6-R6 -> 13.5
A7: 50000 | B7: 45901 | C7: 45901 | D7: COGS - 179743 | E7: COGS - 179743 | F7: D-003 | G7: MSP | I7: Fresno | J7: Tools-NMM-Total-Bill | K7: Borba Farms Partners | L7: Tools-NMM-Total-Bill | M7: C00045 | O7: 10677 | P7: COG | Q7: 13.5 | S7: =Q7-R7 -> 13.5
A8: 50000 | B8: 45901 | C8: 45901 | D8: COGS - 179744 | E8: COGS - 179744 | F8: D-003 | G8: MSP | I8: Fresno | J8: Tools-NMM-Total-Bill | K8: City of Firebaugh | L8: Tools-NMM-Total-Bill | M8: C00073 | O8: 10678 | P8: COG | Q8: 4.5 | S8: =Q8-R8 -> 4.5
A9: 50000 | B9: 45901 | C9: 45901 | D9: COGS - 179746 | E9: COGS - 179746 | F9: D-003 | G9: MSP | I9: Fresno | J9: Tools-NMM-Total-Bill | K9: City of Selma | L9: Tools-NMM-Total-Bill | M9: C00077 | O9: 10680 | P9: COG | Q9: 81 | S9: =Q9-R9 -> 81
A10: 50000 | B10: 45901 | C10: 45901 | D10: COGS - 179747 | E10: COGS - 179747 | F10: D-003 | G10: MSP | I10: Fresno | J10: Tools-NMM-Total-Bill | K10: Collectibles Management Resources | L10: Tools-NMM-Total-Bill | M10: C00081 | O10: 10681 | P10: COG | Q10: 9 | S10: =Q10-R10 -> 9
A11: 50000 | B11: 45901 | C11: 45901 | D11: COGS - 179748 | E11: COGS - 179748 | F11: D-003 | G11: MSP | I11: Fresno | J11: Tools-NMM-Total-Bill | K11: Community Action Partnership of Madera Co | L11: Tools-NMM-Total-Bill | M11: C00082 | O11: 10682 | P11: COG | Q11: 171 | S11: =Q11-R11 -> 171
A12: 50000 | B12: 45901 | C12: 45901 | D12: COGS - 179753 | E12: COGS - 179753 | F12: D-003 | G12: MSP | I12: Fresno | J12: Tools-NMM-Total-Bill | K12: Daniel, Towle and Warkentine CPA | L12: Tools-NMM-Total-Bill | M12: C00088 | O12: 10687 | P12: COG | Q12: 9 | S12: =Q12-R12 -> 9
A13: 50000 | B13: 45901 | C13: 45901 | D13: COGS - 179755 | E13: COGS - 179755 | F13: D-003 | G13: MSP | I13: Fresno | J13: Tools-NMM-Total-Bill | K13: Fortune-Ratliff General Contractors, Inc. | L13: Tools-NMM-Total-Bill | M13: C00115 | O13: 10689 | P13: COG | Q13: 4.5 | S13: =Q13-R13 -> 4.5
A14: 50000 | B14: 45901 | C14: 45901 | D14: COGS - 179762 | E14: COGS - 179762 | F14: D-003 | G14: MSP | I14: Fresno | J14: Tools-NMM-Total-Bill | K14: JEM Management Corporation | L14: Tools-NMM-Total-Bill | M14: C00158 | O14: 10694 | P14: COG | Q14: 13.5 | S14: =Q14-R14 -> 13.5
A15: 50000 | B15: 45901 | C15: 45901 | D15: COGS - 179763 | E15: COGS - 179763 | F15: D-003 | G15: MSP | I15: Fresno | J15: Tools-NMM-Total-Bill | K15: Madera County Transportation Commission | L15: Tools-NMM-Total-Bill | M15: C00181 | O15: 10695 | P15: COG | Q15: 9 | S15: =Q15-R15 -> 9
... A61: 50000 | B61: 45901 | C61: 45901 | D61: COGS - 180071 | E61: COGS - 180071 | F61: D-003 | G61: MSP | I61: Modesto | J61: Tools-NMM-Total-Bill | K61: United Way of Stanislaus County | L61: Tools-NMM-Total-Bill | M61: C-10005 | O61: 10773 | P61: COG | Q61: 22.5 | S61: =Q61-R61 -> 22.5
A62: 50000 | B62: 45902 | C62: 45902 | D62: 3f5b85c0-e513-4057-9aef-ee6728cb11e1 | E62: Charge Card Transaction - Ramp: Genelyn Terrones - PO# 25709 | F62: D-014-E | G62: Procurement - East | I62: Data Path OHIO LLC | O62: 4255 | P62: APJ | Q62: 281.96 | S62: =Q62-R62 -> 281.96
A63: 50000 | B63: 45902 | C63: 45902 | D63: 6122768903 - Sept 2025 | E63: Bill - Verizon Wireless: Cradle Points | F63: D-002 | G63: Administration | H63: Verizon Wireless | I63: Datapath, Inc. | O63: 4230 | P63: APJ | Q63: 227.73 | S63: =Q63-R63 -> 227.73
A64: 50000 | B64: 45903 | C64: 45903 | D64: afea811f-267c-44d4-82d2-a9690947ff03 | E64: Charge Card Transaction - Ramp: David Craig | I64: Datapath, Inc. | O64: 4256 | P64: APJ | Q64: 41 | S64: =Q64-R64 -> 41
A65: 50000 | B65: 45904 | C65: 45904 | D65: 1c372ff1-0ee9-4fa6-ae9a-fc86bddcce77 | E65: Charge Card Transaction - Ramp: David Craig - Monthly Auvik Invoice | I65: Datapath, Inc. | O65: 4275 | P65: APJ | Q65: 7041.29 | S65: =Q65-R65 -> 7041.29
A66: 50000 | B66: 45904 | C66: 45904 | D66: b68caeeb-0ac4-490e-b79e-4e92f78d9d6b | E66: Charge Card Transaction - Ramp: David Craig - printer logic - Ohio | I66: Datapath, Inc. | O66: 4275 | P66: APJ | Q66: 931.13 | S66: =Q66-R66 -> 931.13
A67: 50000 | B67: 45905 | C67: 45905 | D67: 22354f9d-42d4-4a44-a472-56c52cfc0863 | E67: Charge Card Transaction - Ramp: Genelyn Terrones - PO# 25725 | F67: D-014-E | G67: Procurement - East | H67: Amazon | I67: Data Path OHIO LLC | O67: 4277 | P67: APJ | Q67: 89.99 | S67: =Q67-R67 -> 89.99
A68: 50000 | B68: 45905 | C68: 45905 | D68: 97882d45-f3bd-4b57-9975-bc0d3089c02c | E68: Charge Card Transaction - Ramp: Genelyn Terrones - PO#25716 | F68: D-014-E | G68: Procurement - East | H68: B&H Photo | I68: Data Path OHIO LLC | O68: 4277 | P68: APJ | Q68: 53.5 | S68: =Q68-R68 -> 53.5
A69: 50000 | B69: 45909 | C69: 45909 | D69: 0196ef93-43a0-497b-a665-105ce781474e | E69: Charge Card Transaction - Ramp: David Craig - Purchase for Brian Jump - One Time Virtual. | H69: Ingram Micro | I69: Datapath, Inc. | O69: 4273 | P69: APJ | Q69: 664.29 | S69: =Q69-R69 -> 664.29
A70: 50000 | B70: 45909 | C70: 45909 | D70: 82831d6c-d822-4168-8238-86d7a30dabae | E70: Charge Card Transaction - Ramp: David Craig | I70: Datapath, Inc. | O70: 4273 | P70: APJ | Q70: 25 | S70: =Q70-R70 -> 25
A71: 50000 | B71: 45911 | C71: 45911 | D71: 98a7b18c-e5d3-4aed-98e4-a30aa0869b3f | E71: Charge Card Transaction - Ramp: Marshall Rownd - Recurring CWA plug-in | F71: D-006 | G71: Central Services | I71: Datapath, Inc. | O71: 4271 | P71: APJ | Q71: 9.95 | S71: =Q71-R71 -> 9.95
A72: 50000 | B72: 45914 | C72: 45914 | D72: 2c4a26f6-0591-49c7-983c-17e95edfcb4c | E72: Charge Card Transaction - Ramp: David Craig - Monthly recurring expense for Brian Jump. | H72: FastSpring | I72: Datapath, Inc. | O72: 4276 | P72: APJ | Q72: 75 | S72: =Q72-R72 -> 75
A73: 50000 | B73: 45915 | C73: 45915 | D73: 5a9aac9a-a4b5-4c7d-840a-817f32709a35 | E73: Charge Card Transaction - Ramp: David Craig - Monthly Huntresss MSP | H73: Huntress Labs | I73: Datapath, Inc. | O73: 4274 | P73: APJ | Q73: 34829.11 | S73: =Q73-R73 -> 34829.11
A74: 50000 | B74: 45916 | C74: 45916 | D74: fe13d952-c534-4804-919b-979ecf949e82 | E74: Charge Card Transaction - Ramp: David Craig | H74: US Internet | I74: Datapath, Inc. | O74: 4280 | P74: APJ | Q74: 313.6 | S74: =Q74-R74 -> 313.6
A75: 50000 | B75: 45917 | C75: 45917 | D75: c1808e5e-6abb-4319-ace2-5f4ab67cfc90 | E75: Charge Card Transaction - Ramp: Marshall Rownd - CWA Plug-in | F75: D-006 | G75: Central Services | I75: Datapath, Inc. | O75: 4302 | P75: APJ | Q75: 299 | S75: =Q75-R75 -> 299
A76: 50000 | B76: 45918 | C76: 45918 | D76: 53ab07a5-6964-47dd-b1e3-009eb57f7dd5 | E76: Charge Card Transaction - Ramp: Genelyn Terrones - PO# 25828 | F76: D-014-E | G76: Procurement - East | H76: B&H Photo | I76: Data Path OHIO LLC | O76: 4296 | P76: APJ | Q76: 411.74 | S76: =Q76-R76 -> 411.74
A77: 50000 | B77: 45920 | C77: 45920 | D77: 06523e2a-ae20-4733-b41a-243ad7c81a13 | E77: Charge Card Transaction - Ramp: Dinyero Johnson - Hamina Wireless purchase for operational needs. | F77: D-015-W | G77: Engineering - West | I77: Datapath, Inc. | O77: 4303 | P77: APJ | Q77: 590 | S77: =Q77-R77 -> 590
A78: 50000 | B78: 45921 | C78: 45921 | D78: 3907184f-1253-4d83-a482-43a562e0b11e | E78: Charge Card Transaction - Ramp: Kerr Conkle - Re-occuring subscription for ClickUp service management tool. | F78: D-003-E | G78: MSP - East | H78: ClickUp | I78: Data Path OHIO LLC | O78: 4301 | P78: APJ | Q78: 60 | S78: =Q78-R78 -> 60
A79: 50000 | B79: 45925 | C79: 45925 | D79: 368c73a1-3808-4ceb-8613-92ec1adbc7b9 | E79: Charge Card Transaction - Ramp: Timothy Stewart - 3D-Printer Filament for Items for Specific team members Excellent Service Team Performance. Discussed with and Approved with Brandon Johnson | H79: Bambu Lab | I79: Modesto | O79: 4304 | P79: APJ | Q79: 75.15 | S79: =Q79-R79 -> 75.15
A80: 50000 | B80: 45925 | C80: 45925 | D80: 456e2c9f-a051-4105-8817-610a26f958c6 | E80: Charge Card Transaction - Ramp: Genelyn Terrones - PO# 25873 | F80: D-014-E | G80: Procurement - East | I80: Data Path OHIO LLC | O80: 4304 | P80: APJ | Q80: 5342.27 | S80: =Q80-R80 -> 5342.27
A81: 50000 | B81: 45925 | C81: 45925 | D81: c2f388f5-72d0-4ead-a950-447f27830023 | E81: Charge Card Transaction - Ramp: David Craig - 25866 | I81: Datapath, Inc. | O81: 4304 | P81: APJ | Q81: 6513.15 | S81: =Q81-R81 -> 6513.15
A82: 50000 | B82: 45927 | C82: 45927 | D82: 04753898-c04b-45d3-9326-7d19ed4ad300 | E82: Charge Card Transaction - Ramp: David Craig - 25869 | H82: Amazon | I82: Datapath, Inc. | O82: 4327 | P82: APJ | Q82: 1392.84 | S82: =Q82-R82 -> 1392.84
A83: 50000 | B83: 45927 | C83: 45927 | D83: ce2a6f9c-44c2-4994-9c29-77f07eeec1e5 | E83: Charge Card Transaction - Ramp: David Craig - Monthly C360 Payment - Internal | H83: Cognition360 | I83: Datapath, Inc. | O83: 4327 | P83: APJ | Q83: 1297 | S83: =Q83-R83 -> 1297
A84: 50000 | B84: 45927 | C84: 45927 | D84: fbd18ee5-8f96-4306-83b5-74b220e41e64 | E84: Charge Card Transaction - Ramp: Marshall Rownd - Recurring CWA plug-in for internal use. | F84: D-006 | G84: Central Services | I84: Datapath, Inc. | O84: 4327 | P84: APJ | Q84: 39.95 | S84: =Q84-R84 -> 39.95
A85: 50000 | B85: 45929 | C85: 45929 | D85: 6bf492d0-ae1e-4f3d-800e-dfd34950b736 | E85: Charge Card Transaction - Ramp: David Craig - Monthly Bitwarden subscription for security services. | I85: Datapath, Inc. | O85: 4320 | P85: APJ | Q85: 56.88 | S85: =Q85-R85 -> 56.88
A86: 50000 | B86: 45930 | C86: 45930 | E86: Pager Duty Annual Subscription | I86: Datapath, Inc. | O86: 2489 | P86: GJ | Q86: 1393.88 | S86: =Q86-R86 -> 1393.88
A87: 50000 | B87: 45930 | C87: 45930 | E87: Adjust monthly Huntress bill | H87: Huntress Labs | I87: Datapath, Inc. | O87: 2522 | P87: GJ | R87: 34829.11 | S87: =Q87-R87 -> -34829.11
A88: 50000 | B88: 45930 | C88: 45930 | E88: To reverse miscoded Sept Ramp card transactions | I88: Datapath, Inc. | O88: 2529 | P88: GJ | R88: 14546.22 | S88: =Q88-R88 -> -14546.22
A89: 50000 | B89: 45930 | C89: 45930 | D89: 09f21cef-5ba6-44de-969e-2018ff2dbf50 | E89: Charge Card Transaction - Ramp: David Craig - 25897 | H89: Amazon | I89: Datapath, Inc. | O89: 4321 | P89: APJ | Q89: 415.03 | S89: =Q89-R89 -> 415.03
A90: 50000 | B90: 45930 | C90: 45930 | D90: INV01475212 | E90: Bill - ConnectWise: ConnectWise PSA User StreamlineIT | H90: ConnectWise | I90: Datapath, Inc. | O90: 4311 | P90: APJ | Q90: 1540 | S90: =Q90-R90 -> 1540
A91: 50000 | B91: 45930 | C91: 45930 | D91: INV01475212 | E91: Bill - ConnectWise: Automate Standard Subscription | H91: ConnectWise | I91: Datapath, Inc. | O91: 4311 | P91: APJ | Q91: 3894.25 | S91: =Q91-R91 -> 3894.25
A92: 50000 | B92: 45930 | C92: 45930 | D92: INV01475212 | E92: Bill - ConnectWise: ConnectWise PSA User StreamlineIT | H92: ConnectWise | I92: Data Path OHIO LLC | O92: 4311 | P92: APJ | Q92: 1540 | S92: =Q92-R92 -> 1540
A93: 50000 | B93: 45930 | C93: 45930 | D93: INV01475212 | E93: Bill - ConnectWise: Automate Standard Subscription | H93: ConnectWise | I93: Data Path OHIO LLC | O93: 4311 | P93: APJ | Q93: 3894.25 | S93: =Q93-R93 -> 3894.25
A94: 50000 | B94: 45930 | C94: 45930 | D94: e2180ad8-6b9f-4956-8fed-f7a168185879 | E94: Charge Card Transaction - Ramp: Genelyn Terrones - PO# 25900 | F94: D-014-E | G94: Procurement - East | I94: Data Path OHIO LLC | O94: 4321 | P94: APJ | Q94: 20.9 | S94: =Q94-R94 -> 20.9
A95: 50000 | B95: 45931 | C95: 45931 | D95: 61778c98-dcad-475c-8a93-53f40b45b479 | E95: Charge Card Transaction - Ramp: David Craig - G Suite for brightbear.net | I95: Datapath, Inc. | O95: 4318 | P95: APJ | Q95: 50.4 | S95: =Q95-R95 -> 50.4
A96: 50000 | B96: 45931 | C96: 45931 | D96: 6d449aa4-a77b-4b40-92fa-6b1538b4cef6 | E96: Charge Card Transaction - Ramp: Marshall Rownd - CWM Slack Integration | F96: D-006 | G96: Central Services | I96: Datapath, Inc. | O96: 4318 | P96: APJ | Q96: 1110 | S96: =Q96-R96 -> 1110
A97: 50000 | B97: 45931 | C97: 45931 | D97: 76284061-246c-485d-b9ac-8371a6b8bb3f | E97: Charge Card Transaction - Ramp: Genelyn Terrones - PO# 25903 | F97: D-014-E | G97: Procurement - East | I97: Data Path OHIO LLC | O97: 4318 | P97: APJ | Q97: 1510.5 | S97: =Q97-R97 -> 1510.5
A98: 50000 | B98: 45931 | C98: 45931 | D98: COGS - 180292 | E98: COGS - 180292 | F98: D-003 | G98: MSP | I98: Fresno | J98: Tools-NMM-Total-Bill | K98: Agape Corporation WEB Du | L98: Tools-NMM-Total-Bill | M98: C00004 | O98: 10982 | P98: COG | Q98: 126 | S98: =Q98-R98 -> 126
A99: 50000 | B99: 45931 | C99: 45931 | D99: COGS - 180293 | E99: COGS - 180293 | F99: D-003 | G99: MSP | I99: Fresno | J99: Tools-NMM-Total-Bill | K99: Agee Construction | L99: Tools-NMM-Total-Bill | M99: C00005 | O99: 10983 | P99: COG | Q99: 27 | S99: =Q99-R99 -> 27
A100: 50000 | B100: 45931 | C100: 45931 | D100: COGS - 180294 | E100: COGS - 180294 | F100: D-003 | G100: MSP | I100: Fresno | J100: Tools-NMM-Total-Bill | K100: Aweta - Americas | L100: Tools-NMM-Total-Bill | M100: C00032 | O100: 10984 | P100: COG | Q100: 13.5 | S100: =Q100-R100 -> 13.5
A101: 50000 | B101: 45931 | C101: 45931 | D101: COGS - 180295 | E101: COGS - 180295 | F101: D-003 | G101: MSP | I101: Fresno | J101: Tools-NMM-Total-Bill | K101: Borba Farms Partners | L101: Tools-NMM-Total-Bill | M101: C00045 | O101: 10985 | P101: COG | Q101: 13.5 | S101: =Q101-R101 -> 13.5
A102: 50000 | B102: 45931 | C102: 45931 | D102: COGS - 180296 | E102: COGS - 180296 | F102: D-003 | G102: MSP | I102: Fresno | J102: Tools-NMM-Total-Bill | K102: City of Firebaugh | L102: Tools-NMM-Total-Bill | M102: C00073 | O102: 10986 | P102: COG | Q102: 4.5 | S102: =Q102-R102 -> 4.5
A103: 50000 | B103: 45931 | C103: 45931 | D103: COGS - 180298 | E103: COGS - 180298 | F103: D-003 | G103: MSP | I103: Fresno | J103: Tools-NMM-Total-Bill | K103: City of Selma | L103: Tools-NMM-Total-Bill | M103: C00077 | O103: 10988 | P103: COG | Q103: 81 | S103: =Q103-R103 -> 81
A104: 50000 | B104: 45931 | C104: 45931 | D104: COGS - 180299 | E104: COGS - 180299 | F104: D-003 | G104: MSP | I104: Fresno | J104: Tools-NMM-Total-Bill | K104: Collectibles Management Resources | L104: Tools-NMM-Total-Bill | M104: C00081 | O104: 10989 | P104: COG | Q104: 9 | S104: =Q104-R104 -> 9
A105: 50000 | B105: 45931 | C105: 45931 | D105: COGS - 180300 | E105: COGS - 180300 | F105: D-003 | G105: MSP | I105: Fresno | J105: Tools-NMM-Total-Bill | K105: Community Action Partnership of Madera Co | L105: Tools-NMM-Total-Bill | M105: C00082 | O105: 10990 | P105: COG | Q105: 171 | S105: =Q105-R105 -> 171
A106: 50000 | B106: 45931 | C106: 45931 | D106: COGS - 180305 | E106: COGS - 180305 | F106: D-003 | G106: MSP | I106: Fresno | J106: Tools-NMM-Total-Bill | K106: Daniel, Towle and Warkentine CPA | L106: Tools-NMM-Total-Bill | M106: C00088 | O106: 10995 | P106: COG | Q106: 9 | S106: =Q106-R106 -> 9
A107: 50000 | B107: 45931 | C107: 45931 | D107: COGS - 180307 | E107: COGS - 180307 | F107: D-003 | G107: MSP | I107: Fresno | J107: Tools-NMM-Total-Bill | K107: Fortune-Ratliff General Contractors, Inc. | L107: Tools-NMM-Total-Bill | M107: C00115 | O107: 10997 | P107: COG | Q107: 4.5 | S107: =Q107-R107 -> 4.5
A108: 50000 | B108: 45931 | C108: 45931 | D108: COGS - 180314 | E108: COGS - 180314 | F108: D-003 | G108: MSP | I108: Fresno | J108: Tools-NMM-Total-Bill | K108: JEM Management Corporation | L108: Tools-NMM-Total-Bill | M108: C00158 | O108: 11002 | P108: COG | Q108: 13.5 | S108: =Q108-R108 -> 13.5
A109: 50000 | B109: 45931 | C109: 45931 | D109: COGS - 180315 | E109: COGS - 180315 | F109: D-003 | G109: MSP | I109: Fresno | J109: Tools-NMM-Total-Bill | K109: Madera County Transportation Commission | L109: Tools-NMM-Total-Bill | M109: C00181 | O109: 11003 | P109: COG | Q109: 9 | S109: =Q109-R109 -> 9
... A135: 50000 | B135: 45931 | C135: 45931 | D135: COGS - 180400 | E135: COGS - 180400 | F135: D-003 | G135: MSP | I135: Modesto | J135: Tools-NMM-Total-Bill | K135: Sargent & Bryan, Inc | L135: Tools-NMM-Total-Bill | M135: C00237 | O135: 11086 | P135: COG | Q135: 9 | S135: =Q135-R135 -> 9
A136: 50000 | B136: 45931 | C136: 45931 | D136: COGS - 180401 | E136: COGS - 180401 | F136: D-003 | G136: MSP | I136: Modesto | J136: Tools-NMM-Total-Bill | K136: Satake USA | L136: Tools-NMM-Total-Bill | M136: C00238 | O136: 11087 | P136: COG | Q136: 13.5 | S136: =Q136-R136 -> 13.5 | T136: x
A137: 50000 | B137: 45931 | C137: 45931 | D137: COGS - 180402 | E137: COGS - 180402 | F137: D-003 | G137: MSP | I137: Modesto | J137: Tools-NMM-Total-Bill | K137: Sconza Candy Company | L137: Tools-NMM-Total-Bill | M137: C00240 | O137: 11088 | P137: COG | Q137: 157.5 | S137: =Q137-R137 -> 157.5 | T137: x
A138: 50000 | B138: 45931 | C138: 45931 | D138: COGS - 180403 | E138: COGS - 180403 | F138: D-003 | G138: MSP | I138: Modesto | J138: Tools-NMM-Total-Bill | K138: Shiloh Elementary School District | L138: Tools-NMM-Total-Bill | M138: C00241 | O138: 11089 | P138: COG | Q138: 18 | S138: =Q138-R138 -> 18 | T138: x
A139: 50000 | B139: 45931 | C139: 45931 | D139: COGS - 180404 | E139: COGS - 180404 | F139: D-003 | G139: MSP | I139: Modesto | J139: Tools-NMM-Total-Bill | K139: Spring Creek Golf & Country Club | L139: Tools-NMM-Total-Bill | M139: C00246 | O139: 11090 | P139: COG | Q139: 22.5 | S139: =Q139-R139 -> 22.5 | T139: x
A140: 50000 | B140: 45931 | C140: 45931 | D140: COGS - 180405 | E140: COGS - 180405 | F140: D-003 | G140: MSP | I140: Modesto | J140: Tools-NMM-Total-Bill | K140: St Lukes Family Practice | L140: Tools-NMM-Total-Bill | M140: C00248 | O140: 11091 | P140: COG | Q140: 9 | S140: =Q140-R140 -> 9 | T140: x
A141: 50000 | B141: 45931 | C141: 45931 | D141: COGS - 180410 | E141: COGS - 180410 | F141: D-003 | G141: MSP | I141: Modesto | J141: Tools-NMM-Total-Bill | K141: Stewart & Jasper | L141: Tools-NMM-Total-Bill | M141: C-10006 | O141: 11095 | P141: COG | Q141: 112.5 | S141: =Q141-R141 -> 112.5 | T141: x
A142: 50000 | B142: 45931 | C142: 45931 | D142: COGS - 180413 | E142: COGS - 180413 | F142: D-003 | G142: MSP | I142: Modesto | J142: Tools-NMM-Total-Bill | K142: Sylvan Union School District | L142: Tools-NMM-Total-Bill | M142: C00258 | O142: 11097 | P142: COG | Q142: 1012.5 | S142: =Q142-R142 -> 1012.5 | T142: x
A143: 50000 | B143: 45931 | C143: 45931 | D143: COGS - 180417 | E143: COGS - 180417 | F143: D-009 | G143: Admin | I143: Modesto | J143: Tools-NMM-Total-Bill | K143: TCB Industrial | L143: Tools-NMM-Total-Bill | M143: C-10333 | O143: 11101 | P143: COG | Q143: 31.5 | S143: =Q143-R143 -> 31.5 | T143: x
A144: 50000 | B144: 45931 | C144: 45931 | D144: COGS - 180419 | E144: COGS - 180419 | F144: D-003 | G144: MSP | I144: Modesto | J144: Tools-NMM-Total-Bill | K144: United Way of Stanislaus County | L144: Tools-NMM-Total-Bill | M144: C-10005 | O144: 11102 | P144: COG | Q144: 22.5 | S144: =Q144-R144 -> 22.5 | T144: x
A145: 50000 | B145: 45931 | C145: 45931 | D145: COGS - 180421 | E145: COGS - 180421 | F145: D-003 | G145: MSP | I145: Modesto | J145: Tools-NMM-Total-Bill | K145: Warden's | L145: Tools-NMM-Total-Bill | M145: C00293 | O145: 11104 | P145: COG | Q145: 18 | S145: =Q145-R145 -> 18 | T145: x
A146: 50000 | B146: 45931 | C146: 45931 | D146: COGS - 180422 | E146: COGS - 180422 | F146: D-003 | G146: MSP | I146: Modesto | J146: Tools-NMM-Total-Bill | K146: Western Steel Buildings | L146: Tools-NMM-Total-Bill | M146: C-10335 | O146: 11105 | P146: COG | Q146: 4.5 | S146: =Q146-R146 -> 4.5 | T146: x
A147: 50000 | B147: 45931 | C147: 45931 | D147: COGS - 180424 | E147: COGS - 180424 | F147: D-003 | G147: MSP | I147: Modesto | J147: Tools-NMM-Total-Bill | K147: Winton-Ireland, Strom & Green | L147: Tools-NMM-Total-Bill | M147: C00300 | O147: 11106 | P147: COG | Q147: 49.5 | S147: =Q147-R147 -> 49.5 | T147: x
... A153: 50000 | B153: 45931 | C153: 45931 | D153: COGS - 180514OH | E153: COGS - 180514OH | F153: D-003 | G153: MSP | I153: Ohio | J153: Tools-NMM-Total-Bill | K153: The Richland School of Academic Arts | L153: Tools-NMM-Total-Bill | M153: C-10104 | O153: 11154 | P153: COG | Q153: 40.5 | S153: =Q153-R153 -> 40.5 | T153: x
A154: 50000 | B154: 45931 | C154: 45931 | D154: d5cb8de2-7665-433d-b637-864e30ea76ad | E154: Charge Card Transaction - Ramp: David Craig - Monthly AWS | H154: Amazon Web Services | I154: Datapath, Inc. | O154: 4318 | P154: APJ | Q154: 902.31 | S154: =Q154-R154 -> 902.31 | T154: x
A155: 50000 | B155: 45931 | C155: 45931 | D155: 25412 - S2505061 | E155: Bill - Cal Coast Telecom: 00 - HealthyU, 2 x WAPs & Cabling | H155: Cal Coast Telecom | I155: Datapath, Inc. | O155: 4268 | P155: APJ | Q155: 1370 | S155: =Q155-R155 -> 1370 | T155: x
A156: 50000 | B156: 45931 | C156: 45931 | D156: ed9c76c0-ef9f-46f6-9cd8-37d77683387e | E156: Charge Card Transaction - Ramp: David Craig - Auto recharge for Twilio account - mis of internal and client use | H156: Twilio | I156: Datapath, Inc. | O156: 4318 | P156: APJ | Q156: 190.01 | S156: =Q156-R156 -> 190.01 | T156: x
A157: 50000 | B157: 45931 | C157: 45931 | D157: I/VC2025/0079/DATC/1 | E157: Bill - VyOS: Production Support Subscription for VyOS Router | H157: VyOS | I157: Datapath, Inc. | O157: 4268 | P157: APJ | Q157: 3000 | S157: =Q157-R157 -> 3000 | T157: x
A158: 50000 | B158: 45931 | C158: 45931 | D158: 17874444 | E158: Bill - Field Nation: UPS and Switch rack and mount 2832 | H158: Field Nation | I158: Data Path OHIO LLC | O158: 4268 | P158: APJ | Q158: 354.2 | S158: =Q158-R158 -> 354.2 | T158: x
A159: 50000 | B159: 45932 | C159: 45932 | D159: 6122768903 - Oct 2025 | E159: Bill - Verizon Wireless: Cradle Points | F159: D-002 | G159: Administration | H159: Verizon Wireless | I159: Datapath, Inc. | O159: 4312 | P159: APJ | Q159: 228.6 | S159: =Q159-R159 -> 228.6 | T159: x
A160: 50000 | B160: 45932 | C160: 45932 | D160: 9c0e9805-8e18-4eb0-898b-0fc530a5bf3c | E160: Charge Card Transaction - Ramp: David Craig - 25934 | H160: Amazon | I160: Datapath, Inc. | O160: 4322 | P160: APJ | Q160: 57.7 | S160: =Q160-R160 -> 57.7 | T160: x
A161: 50000 | B161: 45933 | C161: 45933 | D161: 1cb1ce73-7d71-446a-8c7e-ac11c7878139 | E161: Charge Card Transaction - Ramp: David Craig - Monthly Auvik Invoice | I161: Datapath, Inc. | O161: 4323 | P161: APJ | Q161: 6941.01 | S161: =Q161-R161 -> 6941.01 | T161: x
A162: 50000 | B162: 45933 | C162: 45933 | D162: a847f2f3-147f-44b9-8292-420329c3f1f3 | E162: Charge Card Transaction - Ramp: David Craig - printer logic - Ohio | I162: Datapath, Inc. | O162: 4323 | P162: APJ | Q162: 953.15 | S162: =Q162-R162 -> 953.15 | T162: x
A163: 50000 | B163: 45938 | C163: 45938 | D163: 38e7a7cd-8c41-4e19-9bb3-0b60b543f10b | E163: Charge Card Transaction - Ramp: Jaquelene Dizon - Monthly subscription for ZoomInfo services. | I163: Datapath, Inc. | O163: 4339 | P163: APJ | Q163: 3850.01 | S163: =Q163-R163 -> 3850.01 | T163: x
A164: 50000 | B164: 45941 | C164: 45941 | D164: 941e89f0-6ae5-4bb2-83bd-bd5ad6f54b95 | E164: Charge Card Transaction - Ramp: Marshall Rownd - Recurring CWA plug-in for internal use. | F164: D-006 | G164: Central Services | I164: Datapath, Inc. | O164: 4336 | P164: APJ | Q164: 9.95 | S164: =Q164-R164 -> 9.95 | T164: x
A165: 50000 | B165: 45943 | C165: 45943 | D165: 056aac0d-2083-49de-b629-b70a0414b2ac | E165: Charge Card Transaction - Ramp: Jaquelene Dizon - Monthly bills payment for managed IT services. | I165: Datapath, Inc. | O165: 4345 | P165: APJ | Q165: 528.94 | S165: =Q165-R165 -> 528.94 | T165: x
A166: 50000 | B166: 45943 | C166: 45943 | D166: 81f6b164-d0fc-4663-8c7f-8c63713e8d13 | E166: Charge Card Transaction - Ramp: Jaquelene Dizon - Monthly bills payment for managed IT services. | I166: Datapath, Inc. | O166: 4345 | P166: APJ | Q166: 528.94 | S166: =Q166-R166 -> 528.94 | T166: x
A167: 50000 | B167: 45943 | C167: 45943 | D167: aca2a3ec-1f78-42bb-be87-9fab7bc01f84 | E167: Charge Card Transaction - Ramp: Jaquelene Dizon - Monthly bills payment for managed IT services. | I167: Datapath, Inc. | O167: 4345 | P167: APJ | Q167: 528.94 | S167: =Q167-R167 -> 528.94 | T167: x
A168: 50000 | B168: 45943 | C168: 45943 | D168: b80ec5c5-3493-4c3e-9660-f7b9957bd687 | E168: Charge Card Transaction - Ramp: Jaquelene Dizon - Monthly bills payment for IT services. | I168: Datapath, Inc. | O168: 4345 | P168: APJ | Q168: 229 | S168: =Q168-R168 -> 229 | T168: x
A169: 50000 | B169: 45943 | C169: 45943 | D169: deb78c01-6b86-4210-b3b4-80e163c2e518 | E169: Charge Card Transaction - Ramp: Jaquelene Dizon - Monthly bills payment for managed IT services. | I169: Datapath, Inc. | O169: 4345 | P169: APJ | Q169: 528.94 | S169: =Q169-R169 -> 528.94 | T169: x
A170: 50000 | B170: 45944 | C170: 45944 | D170: 0185a008-f746-4d60-bcac-13f00e39637f | E170: Charge Card Transaction - Ramp: Jaquelene Dizon - Monthly bills payment for IT services. | I170: Datapath, Inc. | O170: 4358 | P170: APJ | Q170: 528.94 | S170: =Q170-R170 -> 528.94 | T170: x
A171: 50000 | B171: 45944 | C171: 45944 | D171: 1f3f66a5-924f-401d-987e-a9633acd3ce9 | E171: Charge Card Transaction - Ramp: David Craig - Monthly Microsoft Store subscription for Brian Jump. | I171: Datapath, Inc. | O171: 4358 | P171: APJ | Q171: 8 | S171: =Q171-R171 -> 8 | T171: x
A172: 50000 | B172: 45944 | C172: 45944 | D172: 2c103793-4a0e-4205-879e-3a8e75ac9d56 | E172: Charge Card Transaction - Ramp: David Craig - Monthly recurring expense for Brian Jump. | H172: FastSpring | I172: Datapath, Inc. | O172: 4358 | P172: APJ | Q172: 75 | S172: =Q172-R172 -> 75 | T172: x
A173: 50000 | B173: 45944 | C173: 45944 | D173: 428aa34b-dd5f-4b35-af64-df2db385f95f | E173: Charge Card Transaction - Ramp: David Craig - Monthly Microsoft Store subscription for October. | I173: Datapath, Inc. | O173: 4358 | P173: APJ | Q173: 45 | S173: =Q173-R173 -> 45 | T173: x
A174: 50000 | B174: 45944 | C174: 45944 | D174: 59335d1d-2996-47d2-a1a7-7d9b4ad9b216 | E174: Charge Card Transaction - Ramp: David Craig - Monthly Microsoft Store subscription for Brian Jump. | I174: Datapath, Inc. | O174: 4358 | P174: APJ | Q174: 319.68 | S174: =Q174-R174 -> 319.68 | T174: x
A175: 50000 | B175: 45946 | C175: 45946 | D175: 2cf8b007-3526-415d-b938-c14637220438 | E175: Charge Card Transaction - Ramp: Jaquelene Dizon - Monthly bills payment for managed IT services. | I175: Datapath, Inc. | O175: 4362 | P175: APJ | Q175: 1815.82 | S175: =Q175-R175 -> 1815.82 | T175: x
...
