Workbook

Sheet 2023 to 2025 P&L
A1: Datapath
A2: P&L MTD with Previous Month Comparison
A3: Reporting Book:
A4: As of Date:
B6: Data Path - All Locations | C6: Data Path - All Locations | D6: Data Path - All Locations
B7: Year To Date | C7: Year To Date | D7: Year To Date
B8: 46022 | C8: 12/31/2024 | D8: 12/31/2023
B9: Actual | C9: Actual | D9: Actual
A10: Net Income- With DL above the line
A11: Operating Net Income- DL above the line
A12: Gross Profit with Direct Labor
A13: Revenue
A14: Monthly Recurring Services | B14: 6854056 | C14: 6936443 | D14: 8102462
A15: Monthly Recurring Private Cloud | B15: 293246 | C15: 249130 | D15: 501696
A16: Monthly Recurring Resale | B16: 3552126 | C16: 2690685 | D16: 3860762
A17: Revenue - Project Services | B17: 897286 | C17: 1636389 | D17: 1243556
A18: Subcontracted Services | B18: 320191 | C18: 665693 | D18: 578727
A19: Revenue - Product Sales | B19: 5748162 | C19: 9750353 | D19: 13238613
A20: Revenue - Other | B20: 89645 | C20: 135672 | D20: 215473
B21: 0 | C21: 0 | D21: 69
A22: Total Revenue | B22: 17754712 | C22: 22064365 | D22: 27741220
A23: Cost of Rev with Direct and IT Project Labor
A24: Managed IT Service Costs | B24: 308646 | C24: 244439 | D24: 384241
A25: Cost of Monthly Recurring Cloud | B25: 130837 | C25: 111211 | D25: 362537
A26: Cost of Monthly Recurring Resale | B26: 2209537 | C26: 1848460 | D26: 2081794
A27: Project Service Costs | B27: 2899 | C27: 28353 | D27: 10903
A28: Subcontractor Service Costs | B28: 290943 | C28: 556704 | D28: 491468
A29: Product Sales Cost | B29: 4849109 | C29: 8022086 | D29: 11092919
A30: IT Project Labor | B30: 692147 | C30: 0 | D30: 0
A31: Direct Labor Costs | B31: 2587557 | C31: 4111567 | D31: 0
A32: Total Cost of Rev with IT Project and Direct Labor | B32: 11071675 | C32: 14922820 | D32: 14423862
A33: Total Gross Profit with Direct Labor | B33: 6683037 | C33: 7141545 | D33: 13317358
A34: Sales Labor Costs | B34: 1661111 | C34: 1706643 | D34: 0
A35: Operating Expense- no Direct or Sales Labor
A36: Payroll and Related Expenses no Direct or Sales Labor | B36: 960566 | C36: 1417800 | D36: 7319360
A37: Utilities and Facilities | B37: 494644 | C37: 485563 | D37: 443737
A38: Operating and Maintenance Expenses | B38: 1453007 | C38: 857972 | D38: 769383
A39: Marketing and Advertising Expenses | B39: 118962 | C39: 132250 | D39: 75785
A40: General and Administrative Expenses | B40: 269759 | C40: 389429 | D40: 399339
A41: Taxes and Insurance | B41: 228578 | C41: 78090 | D41: 105668
A42: Research and Development | C42: 665 | D42: 447
A43: Total Operating Expense- no Direct or Sales Labor | B43: 3525516 | C43: 3361769 | D43: 9113719
A44: Total Operating Net Income- DL above the line | B44: 1496410 | C44: 2073133 | D44: 4203639
A45: Other Income (Expense)
A46: Other Income | B46: 64546 | C46: 444375 | D46: 461995
A47: Other Expense | B47: -264914 | C47: -1328753 | D47: -1221564
A48: Total Other Income (Expense) | B48: -200368 | C48: -884378 | D48: -759569
A49: Income Taxes | B49: 38650 | C49: 61005 | D49: 40566
A50: Net Income | B50: 1257392 | C50: 1127750 | D50: 3403504
A53: Created on : 03/24/2026 3:43 AM PDT

Sheet Condensed P&L by Month
A1: Datapath
A2: P&L MTD with Previous Month Comparison
A3: Reporting Book:
A4: As of Date:
B6: Data Path - All Locations | F6: Data Path - All Locations | G6: Data Path - All Locations | H6: Data Path - All Locations | I6: Data Path - All Locations | J6: Data Path - All Locations | K6: Data Path - All Locations | L6: Data Path - All Locations | M6: Data Path - All Locations | N6: Data Path - All Locations | O6: Data Path - All Locations | P6: Data Path - All Locations | Q6: Data Path - All Locations
B7: Month Ending | D7: Unadjusted | F7: Month Ending | G7: Month Ending | H7: Month Ending | I7: Month Ending | J7: Month Ending | K7: Month Ending | L7: Month Ending | M7: Month Ending | N7: Month Ending | O7: Month Ending | P7: Month Ending | Q7: Month Ending
B8: 12/31/2025 | C8: YE Clean up | D8: 12/31/2025 | F8: 11/30/2025 | G8: 10/31/2025 | H8: 09/30/2025 | I8: 08/31/2025 | J8: 07/31/2025 | K8: 06/30/2025 | L8: 05/31/2025 | M8: 04/30/2025 | N8: 03/31/2025 | O8: 02/28/2025 | P8: 01/31/2025 | Q8: Total
A10: Net Income- With DL above the line
A11: Operating Net Income- DL above the line
A12: Gross Profit with Direct Labor
A13: Revenue
A14: Monthly Recurring Services | B14: =SUMIF('P&L by Month Detail'!$A:$A,'Condensed P&L by Month'!$A14,'P&L by Month Detail'!C:C) -> 586949 | C14: =SUMIF('P&L by Month Detail'!$A:$A,'Condensed P&L by Month'!$A14,'P&L by Month Detail'!D:D) -> 0 | D14: =+B14+C14 -> 586949 | F14: =SUMIF('P&L by Month Detail'!$A:$A,'Condensed P&L by Month'!$A14,'P&L by Month Detail'!G:G) -> 581869 | G14: =SUMIF('P&L by Month Detail'!$A:$A,'Condensed P&L by Month'!$A14,'P&L by Month Detail'!H:H) -> 578956 | H14: =SUMIF('P&L by Month Detail'!$A:$A,'Condensed P&L by Month'!$A14,'P&L by Month Detail'!I:I) -> 547217 | I14: =SUMIF('P&L by Month Detail'!$A:$A,'Condensed P&L by Month'!$A14,'P&L by Month Detail'!J:J) -> 587835 | J14: =SUMIF('P&L by Month Detail'!$A:$A,'Condensed P&L by Month'!$A14,'P&L by Month Detail'!K:K) -> 573925 | K14: =SUMIF('P&L by Month Detail'!$A:$A,'Condensed P&L by Month'!$A14,'P&L by Month Detail'!L:L) -> 595438 | L14: =SUMIF('P&L by Month Detail'!$A:$A,'Condensed P&L by Month'!$A14,'P&L by Month Detail'!M:M) -> 584502 | M14: =SUMIF('P&L by Month Detail'!$A:$A,'Condensed P&L by Month'!$A14,'P&L by Month Detail'!N:N) -> 587391 | N14: =SUMIF('P&L by Month Detail'!$A:$A,'Condensed P&L by Month'!$A14,'P&L by Month Detail'!O:O) -> 550648 | O14: =SUMIF('P&L by Month Detail'!$A:$A,'Condensed P&L by Month'!$A14,'P&L by Month Detail'!P:P) -> 541962 | P14: =SUMIF('P&L by Month Detail'!$A:$A,'Condensed P&L by Month'!$A14,'P&L by Month Detail'!Q:Q) -> 537364 | Q14: =+SUM(F14:P14)+B14 -> 6854056
A15: Monthly Recurring Private Cloud | B15: =SUMIF('P&L by Month Detail'!$A:$A,'Condensed P&L by Month'!$A15,'P&L by Month Detail'!C:C) -> 27201 | C15: =SUMIF('P&L by Month Detail'!$A:$A,'Condensed P&L by Month'!$A15,'P&L by Month Detail'!D:D) -> 0 | D15: =+B15+C15 -> 27201 | F15: =SUMIF('P&L by Month Detail'!$A:$A,'Condensed P&L by Month'!$A15,'P&L by Month Detail'!G:G) -> 27015 | G15: =SUMIF('P&L by Month Detail'!$A:$A,'Condensed P&L by Month'!$A15,'P&L by Month Detail'!H:H) -> 26997 | H15: =SUMIF('P&L by Month Detail'!$A:$A,'Condensed P&L by Month'!$A15,'P&L by Month Detail'!I:I) -> 21601 | I15: =SUMIF('P&L by Month Detail'!$A:$A,'Condensed P&L by Month'!$A15,'P&L by Month Detail'!J:J) -> 26424 | J15: =SUMIF('P&L by Month Detail'!$A:$A,'Condensed P&L by Month'!$A15,'P&L by Month Detail'!K:K) -> 26261 | K15: =SUMIF('P&L by Month Detail'!$A:$A,'Condensed P&L by Month'!$A15,'P&L by Month Detail'!L:L) -> 24486 | L15: =SUMIF('P&L by Month Detail'!$A:$A,'Condensed P&L by Month'!$A15,'P&L by Month Detail'!M:M) -> 24468 | M15: =SUMIF('P&L by Month Detail'!$A:$A,'Condensed P&L by Month'!$A15,'P&L by Month Detail'!N:N) -> 23204 | N15: =SUMIF('P&L by Month Detail'!$A:$A,'Condensed P&L by Month'!$A15,'P&L by Month Detail'!O:O) -> 22726 | O15: =SUMIF('P&L by Month Detail'!$A:$A,'Condensed P&L by Month'!$A15,'P&L by Month Detail'!P:P) -> 22726 | P15: =SUMIF('P&L by Month Detail'!$A:$A,'Condensed P&L by Month'!$A15,'P&L by Month Detail'!Q:Q) -> 20137 | Q15: =+SUM(F15:P15)+B15 -> 293246
A16: Monthly Recurring Resale | B16: =SUMIF('P&L by Month Detail'!$A:$A,'Condensed P&L by Month'!$A16,'P&L by Month Detail'!C:C) -> 293462 | C16: =SUMIF('P&L by Month Detail'!$A:$A,'Condensed P&L by Month'!$A16,'P&L by Month Detail'!D:D) -> -60357 | D16: =+B16+C16 -> 233105 | E16: 1 | F16: =SUMIF('P&L by Month Detail'!$A:$A,'Condensed P&L by Month'!$A16,'P&L by Month Detail'!G:G) -> 352224 | G16: =SUMIF('P&L by Month Detail'!$A:$A,'Condensed P&L by Month'!$A16,'P&L by Month Detail'!H:H) -> 356786 | H16: =SUMIF('P&L by Month Detail'!$A:$A,'Condensed P&L by Month'!$A16,'P&L by Month Detail'!I:I) -> 299709 | I16: =SUMIF('P&L by Month Detail'!$A:$A,'Condensed P&L by Month'!$A16,'P&L by Month Detail'!J:J) -> 308346 | J16: =SUMIF('P&L by Month Detail'!$A:$A,'Condensed P&L by Month'!$A16,'P&L by Month Detail'!K:K) -> 307801 | K16: =SUMIF('P&L by Month Detail'!$A:$A,'Condensed P&L by Month'!$A16,'P&L by Month Detail'!L:L) -> 301279 | L16: =SUMIF('P&L by Month Detail'!$A:$A,'Condensed P&L by Month'!$A16,'P&L by Month Detail'!M:M) -> 309155 | M16: =SUMIF('P&L by Month Detail'!$A:$A,'Condensed P&L by Month'!$A16,'P&L by Month Detail'!N:N) -> 271511 | N16: =SUMIF('P&L by Month Detail'!$A:$A,'Condensed P&L by Month'!$A16,'P&L by Month Detail'!O:O) -> 265320 | O16: =SUMIF('P&L by Month Detail'!$A:$A,'Condensed P&L by Month'!$A16,'P&L by Month Detail'!P:P) -> 247561 | P16: =SUMIF('P&L by Month Detail'!$A:$A,'Condensed P&L by Month'!$A16,'P&L by Month Detail'!Q:Q) -> 238972 | Q16: =+SUM(F16:P16)+B16 -> 3552126
A17: Revenue - Project Services | B17: =SUMIF('P&L by Month Detail'!$A:$A,'Condensed P&L by Month'!$A17,'P&L by Month Detail'!C:C) -> 61485 | C17: =SUMIF('P&L by Month Detail'!$A:$A,'Condensed P&L by Month'!$A17,'P&L by Month Detail'!D:D) -> 43058.14 | D17: =+B17+C17 -> 104543.14 | E17: 2 | F17: =SUMIF('P&L by Month Detail'!$A:$A,'Condensed P&L by Month'!$A17,'P&L by Month Detail'!G:G) -> 47381 | G17: =SUMIF('P&L by Month Detail'!$A:$A,'Condensed P&L by Month'!$A17,'P&L by Month Detail'!H:H) -> 67554 | H17: =SUMIF('P&L by Month Detail'!$A:$A,'Condensed P&L by Month'!$A17,'P&L by Month Detail'!I:I) -> 46071 | I17: =SUMIF('P&L by Month Detail'!$A:$A,'Condensed P&L by Month'!$A17,'P&L by Month Detail'!J:J) -> 104693 | J17: =SUMIF('P&L by Month Detail'!$A:$A,'Condensed P&L by Month'!$A17,'P&L by Month Detail'!K:K) -> 53462 | K17: =SUMIF('P&L by Month Detail'!$A:$A,'Condensed P&L by Month'!$A17,'P&L by Month Detail'!L:L) -> 120765 | L17: =SUMIF('P&L by Month Detail'!$A:$A,'Condensed P&L by Month'!$A17,'P&L by Month Detail'!M:M) -> 47201 | M17: =SUMIF('P&L by Month Detail'!$A:$A,'Condensed P&L by Month'!$A17,'P&L by Month Detail'!N:N) -> 99226 | N17: =SUMIF('P&L by Month Detail'!$A:$A,'Condensed P&L by Month'!$A17,'P&L by Month Detail'!O:O) -> 105235 | O17: =SUMIF('P&L by Month Detail'!$A:$A,'Condensed P&L by Month'!$A17,'P&L by Month Detail'!P:P) -> 92496 | P17: =SUMIF('P&L by Month Detail'!$A:$A,'Condensed P&L by Month'!$A17,'P&L by Month Detail'!Q:Q) -> 51717 | Q17: =+SUM(F17:P17)+B17 -> 897286
A18: Subcontracted Services | B18: =SUMIF('P&L by Month Detail'!$A:$A,'Condensed P&L by Month'!$A18,'P&L by Month Detail'!C:C) -> 4614 | C18: =SUMIF('P&L by Month Detail'!$A:$A,'Condensed P&L by Month'!$A18,'P&L by Month Detail'!D:D) -> 0 | D18: =+B18+C18 -> 4614 | F18: =SUMIF('P&L by Month Detail'!$A:$A,'Condensed P&L by Month'!$A18,'P&L by Month Detail'!G:G) -> 13197 | G18: =SUMIF('P&L by Month Detail'!$A:$A,'Condensed P&L by Month'!$A18,'P&L by Month Detail'!H:H) -> 19989 | H18: =SUMIF('P&L by Month Detail'!$A:$A,'Condensed P&L by Month'!$A18,'P&L by Month Detail'!I:I) -> 14480 | I18: =SUMIF('P&L by Month Detail'!$A:$A,'Condensed P&L by Month'!$A18,'P&L by Month Detail'!J:J) -> 36139 | J18: =SUMIF('P&L by Month Detail'!$A:$A,'Condensed P&L by Month'!$A18,'P&L by Month Detail'!K:K) -> 12686 | K18: =SUMIF('P&L by Month Detail'!$A:$A,'Condensed P&L by Month'!$A18,'P&L by Month Detail'!L:L) -> 8539 | L18: =SUMIF('P&L by Month Detail'!$A:$A,'Condensed P&L by Month'!$A18,'P&L by Month Detail'!M:M) -> 16341 | M18: =SUMIF('P&L by Month Detail'!$A:$A,'Condensed P&L by Month'!$A18,'P&L by Month Detail'!N:N) -> 14387 | N18: =SUMIF('P&L by Month Detail'!$A:$A,'Condensed P&L by Month'!$A18,'P&L by Month Detail'!O:O) -> 35020 | O18: =SUMIF('P&L by Month Detail'!$A:$A,'Condensed P&L by Month'!$A18,'P&L by Month Detail'!P:P) -> 58116 | P18: =SUMIF('P&L by Month Detail'!$A:$A,'Condensed P&L by Month'!$A18,'P&L by Month Detail'!Q:Q) -> 86683 | Q18: =+SUM(F18:P18)+B18 -> 320191
A19: Revenue - Product Sales | B19: =SUMIF('P&L by Month Detail'!$A:$A,'Condensed P&L by Month'!$A19,'P&L by Month Detail'!C:C) -> 157725 | C19: =SUMIF('P&L by Month Detail'!$A:$A,'Condensed P&L by Month'!$A19,'P&L by Month Detail'!D:D) -> 0 | D19: =+B19+C19 -> 157725 | F19: =SUMIF('P&L by Month Detail'!$A:$A,'Condensed P&L by Month'!$A19,'P&L by Month Detail'!G:G) -> 286085 | G19: =SUMIF('P&L by Month Detail'!$A:$A,'Condensed P&L by Month'!$A19,'P&L by Month Detail'!H:H) -> 578813 | H19: =SUMIF('P&L by Month Detail'!$A:$A,'Condensed P&L by Month'!$A19,'P&L by Month Detail'!I:I) -> 364070 | I19: =SUMIF('P&L by Month Detail'!$A:$A,'Condensed P&L by Month'!$A19,'P&L by Month Detail'!J:J) -> 667670 | J19: =SUMIF('P&L by Month Detail'!$A:$A,'Condensed P&L by Month'!$A19,'P&L by Month Detail'!K:K) -> 803455 | K19: =SUMIF('P&L by Month Detail'!$A:$A,'Condensed P&L by Month'!$A19,'P&L by Month Detail'!L:L) -> 598232 | L19: =SUMIF('P&L by Month Detail'!$A:$A,'Condensed P&L by Month'!$A19,'P&L by Month Detail'!M:M) -> 500988 | M19: =SUMIF('P&L by Month Detail'!$A:$A,'Condensed P&L by Month'!$A19,'P&L by Month Detail'!N:N) -> 584904 | N19: =SUMIF('P&L by Month Detail'!$A:$A,'Condensed P&L by Month'!$A19,'P&L by Month Detail'!O:O) -> 440383 | O19: =SUMIF('P&L by Month Detail'!$A:$A,'Condensed P&L by Month'!$A19,'P&L by Month Detail'!P:P) -> 554032 | P19: =SUMIF('P&L by Month Detail'!$A:$A,'Condensed P&L by Month'!$A19,'P&L by Month Detail'!Q:Q) -> 211805 | Q19: =+SUM(F19:P19)+B19 -> 5748162
A20: Revenue - Other | B20: =SUMIF('P&L by Month Detail'!$A:$A,'Condensed P&L by Month'!$A20,'P&L by Month Detail'!C:C) -> 4906 | C20: =SUMIF('P&L by Month Detail'!$A:$A,'Condensed P&L by Month'!$A20,'P&L by Month Detail'!D:D) -> 0 | D20: =+B20+C20 -> 4906 | F20: =SUMIF('P&L by Month Detail'!$A:$A,'Condensed P&L by Month'!$A20,'P&L by Month Detail'!G:G) -> 9277 | G20: =SUMIF('P&L by Month Detail'!$A:$A,'Condensed P&L by Month'!$A20,'P&L by Month Detail'!H:H) -> 9108 | H20: =SUMIF('P&L by Month Detail'!$A:$A,'Condensed P&L by Month'!$A20,'P&L by Month Detail'!I:I) -> 6305 | I20: =SUMIF('P&L by Month Detail'!$A:$A,'Condensed P&L by Month'!$A20,'P&L by Month Detail'!J:J) -> 6386 | J20: =SUMIF('P&L by Month Detail'!$A:$A,'Condensed P&L by Month'!$A20,'P&L by Month Detail'!K:K) -> 7049 | K20: =SUMIF('P&L by Month Detail'!$A:$A,'Condensed P&L by Month'!$A20,'P&L by Month Detail'!L:L) -> 3891 | L20: =SUMIF('P&L by Month Detail'!$A:$A,'Condensed P&L by Month'!$A20,'P&L by Month Detail'!M:M) -> 7133 | M20: =SUMIF('P&L by Month Detail'!$A:$A,'Condensed P&L by Month'!$A20,'P&L by Month Detail'!N:N) -> 11171 | N20: =SUMIF('P&L by Month Detail'!$A:$A,'Condensed P&L by Month'!$A20,'P&L by Month Detail'!O:O) -> 11139 | O20: =SUMIF('P&L by Month Detail'!$A:$A,'Condensed P&L by Month'!$A20,'P&L by Month Detail'!P:P) -> 7690 | P20: =SUMIF('P&L by Month Detail'!$A:$A,'Condensed P&L by Month'!$A20,'P&L by Month Detail'!Q:Q) -> 5590 | Q20: =+SUM(F20:P20)+B20 -> 89645
A21: Total Revenue | B21: =SUM(B14:B20) -> 1136342 | C21: =SUM(C14:C20) -> -17298.86 | D21: =SUM(D14:D20) -> 1119043.1 | F21: =SUM(F14:F20) -> 1317048 | G21: =SUM(G14:G20) -> 1638203 | H21: =SUM(H14:H20) -> 1299453 | I21: =SUM(I14:I20) -> 1737493 | J21: =SUM(J14:J20) -> 1784639 | K21: =SUM(K14:K20) -> 1652630 | L21: =SUM(L14:L20) -> 1489788 | M21: =SUM(M14:M20) -> 1591794 | ... Q21: =SUM(Q14:Q20) -> 17754712
A22: Cost of Rev with Direct and IT Project Labor
A23: Managed IT Service Costs | B23: =SUMIF('P&L by Month Detail'!$A:$A,'Condensed P&L by Month'!$A23,'P&L by Month Detail'!C:C) -> 28797 | C23: =SUMIF('P&L by Month Detail'!$A:$A,'Condensed P&L by Month'!$A23,'P&L by Month Detail'!D:D) -> 0 | D23: =+B23+C23 -> 28797 | F23: =SUMIF('P&L by Month Detail'!$A:$A,'Condensed P&L by Month'!$A23,'P&L by Month Detail'!G:G) -> 16754 | G23: =SUMIF('P&L by Month Detail'!$A:$A,'Condensed P&L by Month'!$A23,'P&L by Month Detail'!H:H) -> 38253 | H23: =SUMIF('P&L by Month Detail'!$A:$A,'Condensed P&L by Month'!$A23,'P&L by Month Detail'!I:I) -> 29904 | I23: =SUMIF('P&L by Month Detail'!$A:$A,'Condensed P&L by Month'!$A23,'P&L by Month Detail'!J:J) -> 28443 | J23: =SUMIF('P&L by Month Detail'!$A:$A,'Condensed P&L by Month'!$A23,'P&L by Month Detail'!K:K) -> 24465 | K23: =SUMIF('P&L by Month Detail'!$A:$A,'Condensed P&L by Month'!$A23,'P&L by Month Detail'!L:L) -> 22966 | L23: =SUMIF('P&L by Month Detail'!$A:$A,'Condensed P&L by Month'!$A23,'P&L by Month Detail'!M:M) -> 26243 | M23: =SUMIF('P&L by Month Detail'!$A:$A,'Condensed P&L by Month'!$A23,'P&L by Month Detail'!N:N) -> 23445 | N23: =SUMIF('P&L by Month Detail'!$A:$A,'Condensed P&L by Month'!$A23,'P&L by Month Detail'!O:O) -> 22148 | O23: =SUMIF('P&L by Month Detail'!$A:$A,'Condensed P&L by Month'!$A23,'P&L by Month Detail'!P:P) -> 24343 | P23: =SUMIF('P&L by Month Detail'!$A:$A,'Condensed P&L by Month'!$A23,'P&L by Month Detail'!Q:Q) -> 22885 | Q23: =+SUM(F23:P23)+B23 -> 308646
A24: Cost of Monthly Recurring Cloud | B24: =SUMIF('P&L by Month Detail'!$A:$A,'Condensed P&L by Month'!$A24,'P&L by Month Detail'!C:C) -> 11313 | C24: =SUMIF('P&L by Month Detail'!$A:$A,'Condensed P&L by Month'!$A24,'P&L by Month Detail'!D:D) -> 0 | D24: =+B24+C24 -> 11313 | F24: =SUMIF('P&L by Month Detail'!$A:$A,'Condensed P&L by Month'!$A24,'P&L by Month Detail'!G:G) -> 11740 | G24: =SUMIF('P&L by Month Detail'!$A:$A,'Condensed P&L by Month'!$A24,'P&L by Month Detail'!H:H) -> 11403 | H24: =SUMIF('P&L by Month Detail'!$A:$A,'Condensed P&L by Month'!$A24,'P&L by Month Detail'!I:I) -> 9013 | I24: =SUMIF('P&L by Month Detail'!$A:$A,'Condensed P&L by Month'!$A24,'P&L by Month Detail'!J:J) -> 11283 | J24: =SUMIF('P&L by Month Detail'!$A:$A,'Condensed P&L by Month'!$A24,'P&L by Month Detail'!K:K) -> 11187 | K24: =SUMIF('P&L by Month Detail'!$A:$A,'Condensed P&L by Month'!$A24,'P&L by Month Detail'!L:L) -> 11665 | L24: =SUMIF('P&L by Month Detail'!$A:$A,'Condensed P&L by Month'!$A24,'P&L by Month Detail'!M:M) -> 13395 | M24: =SUMIF('P&L by Month Detail'!$A:$A,'Condensed P&L by Month'!$A24,'P&L by Month Detail'!N:N) -> 10285 | N24: =SUMIF('P&L by Month Detail'!$A:$A,'Condensed P&L by Month'!$A24,'P&L by Month Detail'!O:O) -> 10286 | O24: =SUMIF('P&L by Month Detail'!$A:$A,'Condensed P&L by Month'!$A24,'P&L by Month Detail'!P:P) -> 10352 | P24: =SUMIF('P&L by Month Detail'!$A:$A,'Condensed P&L by Month'!$A24,'P&L by Month Detail'!Q:Q) -> 8915 | Q24: =+SUM(F24:P24)+B24 -> 130837
A25: Cost of Monthly Recurring Resale | B25: =SUMIF('P&L by Month Detail'!$A:$A,'Condensed P&L by Month'!$A25,'P&L by Month Detail'!C:C) -> 221137 | C25: =SUMIF('P&L by Month Detail'!$A:$A,'Condensed P&L by Month'!$A25,'P&L by Month Detail'!D:D) -> 0 | D25: =+B25+C25 -> 221137 | F25: =SUMIF('P&L by Month Detail'!$A:$A,'Condensed P&L by Month'!$A25,'P&L by Month Detail'!G:G) -> 224909 | G25: =SUMIF('P&L by Month Detail'!$A:$A,'Condensed P&L by Month'!$A25,'P&L by Month Detail'!H:H) -> 229434 | H25: =SUMIF('P&L by Month Detail'!$A:$A,'Condensed P&L by Month'!$A25,'P&L by Month Detail'!I:I) -> 177322 | I25: =SUMIF('P&L by Month Detail'!$A:$A,'Condensed P&L by Month'!$A25,'P&L by Month Detail'!J:J) -> 178977 | J25: =SUMIF('P&L by Month Detail'!$A:$A,'Condensed P&L by Month'!$A25,'P&L by Month Detail'!K:K) -> 177862 | K25: =SUMIF('P&L by Month Detail'!$A:$A,'Condensed P&L by Month'!$A25,'P&L by Month Detail'!L:L) -> 173126 | L25: =SUMIF('P&L by Month Detail'!$A:$A,'Condensed P&L by Month'!$A25,'P&L by Month Detail'!M:M) -> 166534 | M25: =SUMIF('P&L by Month Detail'!$A:$A,'Condensed P&L by Month'!$A25,'P&L by Month Detail'!N:N) -> 172048 | N25: =SUMIF('P&L by Month Detail'!$A:$A,'Condensed P&L by Month'!$A25,'P&L by Month Detail'!O:O) -> 171015 | O25: =SUMIF('P&L by Month Detail'!$A:$A,'Condensed P&L by Month'!$A25,'P&L by Month Detail'!P:P) -> 159224 | P25: =SUMIF('P&L by Month Detail'!$A:$A,'Condensed P&L by Month'!$A25,'P&L by Month Detail'!Q:Q) -> 157949 | Q25: =+SUM(F25:P25)+B25 -> 2209537
A26: Project Service Costs | B26: =SUMIF('P&L by Month Detail'!$A:$A,'Condensed P&L by Month'!$A26,'P&L by Month Detail'!C:C) -> 0 | C26: =SUMIF('P&L by Month Detail'!$A:$A,'Condensed P&L by Month'!$A26,'P&L by Month Detail'!D:D) -> 0 | D26: =+B26+C26 -> 0 | F26: =SUMIF('P&L by Month Detail'!$A:$A,'Condensed P&L by Month'!$A26,'P&L by Month Detail'!G:G) -> 0 | G26: =SUMIF('P&L by Month Detail'!$A:$A,'Condensed P&L by Month'!$A26,'P&L by Month Detail'!H:H) -> 0 | H26: =SUMIF('P&L by Month Detail'!$A:$A,'Condensed P&L by Month'!$A26,'P&L by Month Detail'!I:I) -> 0 | I26: =SUMIF('P&L by Month Detail'!$A:$A,'Condensed P&L by Month'!$A26,'P&L by Month Detail'!J:J) -> 0 | J26: =SUMIF('P&L by Month Detail'!$A:$A,'Condensed P&L by Month'!$A26,'P&L by Month Detail'!K:K) -> 1028 | K26: =SUMIF('P&L by Month Detail'!$A:$A,'Condensed P&L by Month'!$A26,'P&L by Month Detail'!L:L) -> 1215 | L26: =SUMIF('P&L by Month Detail'!$A:$A,'Condensed P&L by Month'!$A26,'P&L by Month Detail'!M:M) -> 632 | M26: =SUMIF('P&L by Month Detail'!$A:$A,'Condensed P&L by Month'!$A26,'P&L by Month Detail'!N:N) -> 0 | N26: =SUMIF('P&L by Month Detail'!$A:$A,'Condensed P&L by Month'!$A26,'P&L by Month Detail'!O:O) -> 24 | O26: =SUMIF('P&L by Month Detail'!$A:$A,'Condensed P&L by Month'!$A26,'P&L by Month Detail'!P:P) -> 0 | P26: =SUMIF('P&L by Month Detail'!$A:$A,'Condensed P&L by Month'!$A26,'P&L by Month Detail'!Q:Q) -> 0 | Q26: =+SUM(F26:P26)+B26 -> 2899
A27: Subcontractor Service Costs | B27: =SUMIF('P&L by Month Detail'!$A:$A,'Condensed P&L by Month'!$A27,'P&L by Month Detail'!C:C) -> 2305 | C27: =SUMIF('P&L by Month Detail'!$A:$A,'Condensed P&L by Month'!$A27,'P&L by Month Detail'!D:D) -> 0 | D27: =+B27+C27 -> 2305 | F27: =SUMIF('P&L by Month Detail'!$A:$A,'Condensed P&L by Month'!$A27,'P&L by Month Detail'!G:G) -> 23527 | G27: =SUMIF('P&L by Month Detail'!$A:$A,'Condensed P&L by Month'!$A27,'P&L by Month Detail'!H:H) -> 23040 | H27: =SUMIF('P&L by Month Detail'!$A:$A,'Condensed P&L by Month'!$A27,'P&L by Month Detail'!I:I) -> 13423 | I27: =SUMIF('P&L by Month Detail'!$A:$A,'Condensed P&L by Month'!$A27,'P&L by Month Detail'!J:J) -> 31339 | J27: =SUMIF('P&L by Month Detail'!$A:$A,'Condensed P&L by Month'!$A27,'P&L by Month Detail'!K:K) -> 11923 | K27: =SUMIF('P&L by Month Detail'!$A:$A,'Condensed P&L by Month'!$A27,'P&L by Month Detail'!L:L) -> 6946 | L27: =SUMIF('P&L by Month Detail'!$A:$A,'Condensed P&L by Month'!$A27,'P&L by Month Detail'!M:M) -> 13493 | M27: =SUMIF('P&L by Month Detail'!$A:$A,'Condensed P&L by Month'!$A27,'P&L by Month Detail'!N:N) -> 14836 | N27: =SUMIF('P&L by Month Detail'!$A:$A,'Condensed P&L by Month'!$A27,'P&L by Month Detail'!O:O) -> 29319 | O27: =SUMIF('P&L by Month Detail'!$A:$A,'Condensed P&L by Month'!$A27,'P&L by Month Detail'!P:P) -> 48356 | P27: =SUMIF('P&L by Month Detail'!$A:$A,'Condensed P&L by Month'!$A27,'P&L by Month Detail'!Q:Q) -> 72436 | Q27: =+SUM(F27:P27)+B27 -> 290943
A28: Product Sales Cost | B28: =SUMIF('P&L by Month Detail'!$A:$A,'Condensed P&L by Month'!$A28,'P&L by Month Detail'!C:C) -> 102255 | C28: =SUMIF('P&L by Month Detail'!$A:$A,'Condensed P&L by Month'!$A28,'P&L by Month Detail'!D:D) -> 42625.69 | D28: =+B28+C28 -> 144880.69 | E28: 3 | F28: =SUMIF('P&L by Month Detail'!$A:$A,'Condensed P&L by Month'!$A28,'P&L by Month Detail'!G:G) -> 240342 | G28: =SUMIF('P&L by Month Detail'!$A:$A,'Condensed P&L by Month'!$A28,'P&L by Month Detail'!H:H) -> 486006 | H28: =SUMIF('P&L by Month Detail'!$A:$A,'Condensed P&L by Month'!$A28,'P&L by Month Detail'!I:I) -> 321154 | I28: =SUMIF('P&L by Month Detail'!$A:$A,'Condensed P&L by Month'!$A28,'P&L by Month Detail'!J:J) -> 569431 | J28: =SUMIF('P&L by Month Detail'!$A:$A,'Condensed P&L by Month'!$A28,'P&L by Month Detail'!K:K) -> 694977 | K28: =SUMIF('P&L by Month Detail'!$A:$A,'Condensed P&L by Month'!$A28,'P&L by Month Detail'!L:L) -> 506712 | L28: =SUMIF('P&L by Month Detail'!$A:$A,'Condensed P&L by Month'!$A28,'P&L by Month Detail'!M:M) -> 409890 | M28: =SUMIF('P&L by Month Detail'!$A:$A,'Condensed P&L by Month'!$A28,'P&L by Month Detail'!N:N) -> 495271 | N28: =SUMIF('P&L by Month Detail'!$A:$A,'Condensed P&L by Month'!$A28,'P&L by Month Detail'!O:O) -> 370688 | O28: =SUMIF('P&L by Month Detail'!$A:$A,'Condensed P&L by Month'!$A28,'P&L by Month Detail'!P:P) -> 471991 | P28: =SUMIF('P&L by Month Detail'!$A:$A,'Condensed P&L by Month'!$A28,'P&L by Month Detail'!Q:Q) -> 180392 | Q28: =+SUM(F28:P28)+B28 -> 4849109
A29: IT Project Labor | B29: =SUMIF('P&L by Month Detail'!$A:$A,'Condensed P&L by Month'!$A29,'P&L by Month Detail'!C:C) -> -2116 | C29: =SUMIF('P&L by Month Detail'!$A:$A,'Condensed P&L by Month'!$A29,'P&L by Month Detail'!D:D) -> 68871.5 | D29: =+B29+C29 -> 66755.5 | E29: 5 | F29: =SUMIF('P&L by Month Detail'!$A:$A,'Condensed P&L by Month'!$A29,'P&L by Month Detail'!G:G) -> 51988 | G29: =SUMIF('P&L by Month Detail'!$A:$A,'Condensed P&L by Month'!$A29,'P&L by Month Detail'!H:H) -> 57904 | H29: =SUMIF('P&L by Month Detail'!$A:$A,'Condensed P&L by Month'!$A29,'P&L by Month Detail'!I:I) -> 55387 | I29: =SUMIF('P&L by Month Detail'!$A:$A,'Condensed P&L by Month'!$A29,'P&L by Month Detail'!J:J) -> 64553 | J29: =SUMIF('P&L by Month Detail'!$A:$A,'Condensed P&L by Month'!$A29,'P&L by Month Detail'!K:K) -> 65070 | K29: =SUMIF('P&L by Month Detail'!$A:$A,'Condensed P&L by Month'!$A29,'P&L by Month Detail'!L:L) -> 61677 | L29: =SUMIF('P&L by Month Detail'!$A:$A,'Condensed P&L by Month'!$A29,'P&L by Month Detail'!M:M) -> 64595 | M29: =SUMIF('P&L by Month Detail'!$A:$A,'Condensed P&L by Month'!$A29,'P&L by Month Detail'!N:N) -> 67481 | N29: =SUMIF('P&L by Month Detail'!$A:$A,'Condensed P&L by Month'!$A29,'P&L by Month Detail'!O:O) -> 71122 | O29: =SUMIF('P&L by Month Detail'!$A:$A,'Condensed P&L by Month'!$A29,'P&L by Month Detail'!P:P) -> 64602 | P29: =SUMIF('P&L by Month Detail'!$A:$A,'Condensed P&L by Month'!$A29,'P&L by Month Detail'!Q:Q) -> 69884 | Q29: =+SUM(F29:P29)+B29 -> 692147
A30: Direct Labor Costs | B30: =SUMIF('P&L by Month Detail'!$A:$A,'Condensed P&L by Month'!$A30,'P&L by Month Detail'!C:C) -> 325620 | C30: =SUMIF('P&L by Month Detail'!$A:$A,'Condensed P&L by Month'!$A30,'P&L by Month Detail'!D:D) -> -91087.33 | D30: =+B30+C30 -> 234532.67 | E30: 5 & 6 | F30: =SUMIF('P&L by Month Detail'!$A:$A,'Condensed P&L by Month'!$A30,'P&L by Month Detail'!G:G) -> 174861 | G30: =SUMIF('P&L by Month Detail'!$A:$A,'Condensed P&L by Month'!$A30,'P&L by Month Detail'!H:H) -> 206820 | H30: =SUMIF('P&L by Month Detail'!$A:$A,'Condensed P&L by Month'!$A30,'P&L by Month Detail'!I:I) -> 210696 | I30: =SUMIF('P&L by Month Detail'!$A:$A,'Condensed P&L by Month'!$A30,'P&L by Month Detail'!J:J) -> 189126 | J30: =SUMIF('P&L by Month Detail'!$A:$A,'Condensed P&L by Month'!$A30,'P&L by Month Detail'!K:K) -> 218508 | K30: =SUMIF('P&L by Month Detail'!$A:$A,'Condensed P&L by Month'!$A30,'P&L by Month Detail'!L:L) -> 205476 | L30: =SUMIF('P&L by Month Detail'!$A:$A,'Condensed P&L by Month'!$A30,'P&L by Month Detail'!M:M) -> 203541 | M30: =SUMIF('P&L by Month Detail'!$A:$A,'Condensed P&L by Month'!$A30,'P&L by Month Detail'!N:N) -> 194932 | N30: =SUMIF('P&L by Month Detail'!$A:$A,'Condensed P&L by Month'!$A30,'P&L by Month Detail'!O:O) -> 227117 | O30: =SUMIF('P&L by Month Detail'!$A:$A,'Condensed P&L by Month'!$A30,'P&L by Month Detail'!P:P) -> 203182 | P30: =SUMIF('P&L by Month Detail'!$A:$A,'Condensed P&L by Month'!$A30,'P&L by Month Detail'!Q:Q) -> 227678 | Q30: =+SUM(F30:P30)+B30 -> 2587557
A31: Total Cost of Rev with IT Project and Direct Labor | B31: =SUM(B23:B30) -> 689311 | C31: =SUM(C23:C30) -> 20409.86 | D31: =SUM(D23:D30) -> 709720.86 | F31: =SUM(F23:F30) -> 744121 | G31: =SUM(G23:G30) -> 1052860 | H31: =SUM(H23:H30) -> 816899 | I31: =SUM(I23:I30) -> 1073152 | J31: =SUM(J23:J30) -> 1205020 | K31: =SUM(K23:K30) -> 989783 | L31: =SUM(L23:L30) -> 898323 | M31: =SUM(M23:M30) -> 978298 | ... Q31: =SUM(Q23:Q30) -> 11071675
A32: Total Gross Profit with Direct Labor | B32: =SUMIF('P&L by Month Detail'!$A:$A,'Condensed P&L by Month'!$A32,'P&L by Month Detail'!C:C) -> 447031 | C32: =SUMIF('P&L by Month Detail'!$A:$A,'Condensed P&L by Month'!$A32,'P&L by Month Detail'!D:D) -> -37708.72 | D32: =+B32+C32 -> 409322.28 | F32: =SUMIF('P&L by Month Detail'!$A:$A,'Condensed P&L by Month'!$A32,'P&L by Month Detail'!G:G) -> 572927 | G32: =SUMIF('P&L by Month Detail'!$A:$A,'Condensed P&L by Month'!$A32,'P&L by Month Detail'!H:H) -> 585343 | H32: =SUMIF('P&L by Month Detail'!$A:$A,'Condensed P&L by Month'!$A32,'P&L by Month Detail'!I:I) -> 482554 | I32: =SUMIF('P&L by Month Detail'!$A:$A,'Condensed P&L by Month'!$A32,'P&L by Month Detail'!J:J) -> 664341 | J32: =SUMIF('P&L by Month Detail'!$A:$A,'Condensed P&L by Month'!$A32,'P&L by Month Detail'!K:K) -> 579619 | K32: =SUMIF('P&L by Month Detail'!$A:$A,'Condensed P&L by Month'!$A32,'P&L by Month Detail'!L:L) -> 662847 | L32: =SUMIF('P&L by Month Detail'!$A:$A,'Condensed P&L by Month'!$A32,'P&L by Month Detail'!M:M) -> 591465 | M32: =SUMIF('P&L by Month Detail'!$A:$A,'Condensed P&L by Month'!$A32,'P&L by Month Detail'!N:N) -> 613496 | N32: =SUMIF('P&L by Month Detail'!$A:$A,'Condensed P&L by Month'!$A32,'P&L by Month Detail'!O:O) -> 528752 | O32: =SUMIF('P&L by Month Detail'!$A:$A,'Condensed P&L by Month'!$A32,'P&L by Month Detail'!P:P) -> 542533 | P32: =SUMIF('P&L by Month Detail'!$A:$A,'Condensed P&L by Month'!$A32,'P&L by Month Detail'!Q:Q) -> 412129 | Q32: =+SUM(F32:P32)+B32 -> 6683037
A33: Sales Labor Costs | B33: =SUMIF('P&L by Month Detail'!$A:$A,'Condensed P&L by Month'!$A33,'P&L by Month Detail'!C:C) -> 31075 | C33: =SUMIF('P&L by Month Detail'!$A:$A,'Condensed P&L by Month'!$A33,'P&L by Month Detail'!D:D) -> 95959.63 | D33: =+B33+C33 -> 127034.63 | E33: 5 | F33: =SUMIF('P&L by Month Detail'!$A:$A,'Condensed P&L by Month'!$A33,'P&L by Month Detail'!G:G) -> 111629 | G33: =SUMIF('P&L by Month Detail'!$A:$A,'Condensed P&L by Month'!$A33,'P&L by Month Detail'!H:H) -> 197590 | H33: =SUMIF('P&L by Month Detail'!$A:$A,'Condensed P&L by Month'!$A33,'P&L by Month Detail'!I:I) -> 147595 | I33: =SUMIF('P&L by Month Detail'!$A:$A,'Condensed P&L by Month'!$A33,'P&L by Month Detail'!J:J) -> 145868 | J33: =SUMIF('P&L by Month Detail'!$A:$A,'Condensed P&L by Month'!$A33,'P&L by Month Detail'!K:K) -> 147139 | K33: =SUMIF('P&L by Month Detail'!$A:$A,'Condensed P&L by Month'!$A33,'P&L by Month Detail'!L:L) -> 129570 | L33: =SUMIF('P&L by Month Detail'!$A:$A,'Condensed P&L by Month'!$A33,'P&L by Month Detail'!M:M) -> 136510 | M33: =SUMIF('P&L by Month Detail'!$A:$A,'Condensed P&L by Month'!$A33,'P&L by Month Detail'!N:N) -> 128044 | N33: =SUMIF('P&L by Month Detail'!$A:$A,'Condensed P&L by Month'!$A33,'P&L by Month Detail'!O:O) -> 145044 | O33: =SUMIF('P&L by Month Detail'!$A:$A,'Condensed P&L by Month'!$A33,'P&L by Month Detail'!P:P) -> 166242 | P33: =SUMIF('P&L by Month Detail'!$A:$A,'Condensed P&L by Month'!$A33,'P&L by Month Detail'!Q:Q) -> 174805 | Q33: =+SUM(F33:P33)+B33 -> 1661111
A34: Operating Expense- no Direct or Sales Labor
A35: Payroll and Related Expenses no Direct or Sales Labor | B35: =SUMIF('P&L by Month Detail'!$A:$A,'Condensed P&L by Month'!$A35,'P&L by Month Detail'!C:C) -> 71324 | C35: =SUMIF('P&L by Month Detail'!$A:$A,'Condensed P&L by Month'!$A35,'P&L by Month Detail'!D:D) -> 14288.61 | D35: =+B35+C35 -> 85612.61 | E35: 5 | F35: =SUMIF('P&L by Month Detail'!$A:$A,'Condensed P&L by Month'!$A35,'P&L by Month Detail'!G:G) -> 54724 | G35: =SUMIF('P&L by Month Detail'!$A:$A,'Condensed P&L by Month'!$A35,'P&L by Month Detail'!H:H) -> 66012 | H35: =SUMIF('P&L by Month Detail'!$A:$A,'Condensed P&L by Month'!$A35,'P&L by Month Detail'!I:I) -> 75368 | I35: =SUMIF('P&L by Month Detail'!$A:$A,'Condensed P&L by Month'!$A35,'P&L by Month Detail'!J:J) -> 76247 | J35: =SUMIF('P&L by Month Detail'!$A:$A,'Condensed P&L by Month'!$A35,'P&L by Month Detail'!K:K) -> 88854 | K35: =SUMIF('P&L by Month Detail'!$A:$A,'Condensed P&L by Month'!$A35,'P&L by Month Detail'!L:L) -> 83226 | L35: =SUMIF('P&L by Month Detail'!$A:$A,'Condensed P&L by Month'!$A35,'P&L by Month Detail'!M:M) -> 85672 | M35: =SUMIF('P&L by Month Detail'!$A:$A,'Condensed P&L by Month'!$A35,'P&L by Month Detail'!N:N) -> 76476 | N35: =SUMIF('P&L by Month Detail'!$A:$A,'Condensed P&L by Month'!$A35,'P&L by Month Detail'!O:O) -> 86712 | O35: =SUMIF('P&L by Month Detail'!$A:$A,'Condensed P&L by Month'!$A35,'P&L by Month Detail'!P:P) -> 107567 | P35: =SUMIF('P&L by Month Detail'!$A:$A,'Condensed P&L by Month'!$A35,'P&L by Month Detail'!Q:Q) -> 88384 | Q35: =+SUM(F35:P35)+B35 -> 960566
A36: Utilities and Facilities | B36: =SUMIF('P&L by Month Detail'!$A:$A,'Condensed P&L by Month'!$A36,'P&L by Month Detail'!C:C) -> 46712 | C36: =SUMIF('P&L by Month Detail'!$A:$A,'Condensed P&L by Month'!$A36,'P&L by Month Detail'!D:D) -> 2773.88 | D36: =+B36+C36 -> 49485.88 | E36: 7 | F36: =SUMIF('P&L by Month Detail'!$A:$A,'Condensed P&L by Month'!$A36,'P&L by Month Detail'!G:G) -> 44444 | G36: =SUMIF('P&L by Month Detail'!$A:$A,'Condensed P&L by Month'!$A36,'P&L by Month Detail'!H:H) -> 32939 | H36: =SUMIF('P&L by Month Detail'!$A:$A,'Condensed P&L by Month'!$A36,'P&L by Month Detail'!I:I) -> 32562 | I36: =SUMIF('P&L by Month Detail'!$A:$A,'Condensed P&L by Month'!$A36,'P&L by Month Detail'!J:J) -> 43353 | J36: =SUMIF('P&L by Month Detail'!$A:$A,'Condensed P&L by Month'!$A36,'P&L by Month Detail'!K:K) -> 39315 | K36: =SUMIF('P&L by Month Detail'!$A:$A,'Condensed P&L by Month'!$A36,'P&L by Month Detail'!L:L) -> 38662 | L36: =SUMIF('P&L by Month Detail'!$A:$A,'Condensed P&L by Month'!$A36,'P&L by Month Detail'!M:M) -> 38240 | M36: =SUMIF('P&L by Month Detail'!$A:$A,'Condensed P&L by Month'!$A36,'P&L by Month Detail'!N:N) -> 39645 | N36: =SUMIF('P&L by Month Detail'!$A:$A,'Condensed P&L by Month'!$A36,'P&L by Month Detail'!O:O) -> 58379 | O36: =SUMIF('P&L by Month Detail'!$A:$A,'Condensed P&L by Month'!$A36,'P&L by Month Detail'!P:P) -> 40343 | P36: =SUMIF('P&L by Month Detail'!$A:$A,'Condensed P&L by Month'!$A36,'P&L by Month Detail'!Q:Q) -> 40050 | Q36: =+SUM(F36:P36)+B36 -> 494644
A37: Operating and Maintenance Expenses | B37: =SUMIF('P&L by Month Detail'!$A:$A,'Condensed P&L by Month'!$A37,'P&L by Month Detail'!C:C) -> 301681 | C37: =SUMIF('P&L by Month Detail'!$A:$A,'Condensed P&L by Month'!$A37,'P&L by Month Detail'!D:D) -> -245482.78 | D37: =+B37+C37 -> 56198.22 | E37: 8, 9 & 10 | F37: =SUMIF('P&L by Month Detail'!$A:$A,'Condensed P&L by Month'!$A37,'P&L by Month Detail'!G:G) -> 125361 | G37: =SUMIF('P&L by Month Detail'!$A:$A,'Condensed P&L by Month'!$A37,'P&L by Month Detail'!H:H) -> 93219 | H37: =SUMIF('P&L by Month Detail'!$A:$A,'Condensed P&L by Month'!$A37,'P&L by Month Detail'!I:I) -> 124862 | I37: =SUMIF('P&L by Month Detail'!$A:$A,'Condensed P&L by Month'!$A37,'P&L by Month Detail'!J:J) -> 127923 | J37: =SUMIF('P&L by Month Detail'!$A:$A,'Condensed P&L by Month'!$A37,'P&L by Month Detail'!K:K) -> 102371 | K37: =SUMIF('P&L by Month Detail'!$A:$A,'Condensed P&L by Month'!$A37,'P&L by Month Detail'!L:L) -> 97951 | L37: =SUMIF('P&L by Month Detail'!$A:$A,'Condensed P&L by Month'!$A37,'P&L by Month Detail'!M:M) -> 106192 | M37: =SUMIF('P&L by Month Detail'!$A:$A,'Condensed P&L by Month'!$A37,'P&L by Month Detail'!N:N) -> 94847 | N37: =SUMIF('P&L by Month Detail'!$A:$A,'Condensed P&L by Month'!$A37,'P&L by Month Detail'!O:O) -> 79928 | O37: =SUMIF('P&L by Month Detail'!$A:$A,'Condensed P&L by Month'!$A37,'P&L by Month Detail'!P:P) -> 109242 | P37: =SUMIF('P&L by Month Detail'!$A:$A,'Condensed P&L by Month'!$A37,'P&L by Month Detail'!Q:Q) -> 89430 | Q37: =+SUM(F37:P37)+B37 -> 1453007
A38: Marketing and Advertising Expenses | B38: =SUMIF('P&L by Month Detail'!$A:$A,'Condensed P&L by Month'!$A38,'P&L by Month Detail'!C:C) -> 13014 | C38: =SUMIF('P&L by Month Detail'!$A:$A,'Condensed P&L by Month'!$A38,'P&L by Month Detail'!D:D) -> -4000 | D38: =+B38+C38 -> 9014 | E38: 4 | F38: =SUMIF('P&L by Month Detail'!$A:$A,'Condensed P&L by Month'!$A38,'P&L by Month Detail'!G:G) -> 15176 | G38: =SUMIF('P&L by Month Detail'!$A:$A,'Condensed P&L by Month'!$A38,'P&L by Month Detail'!H:H) -> 14957 | H38: =SUMIF('P&L by Month Detail'!$A:$A,'Condensed P&L by Month'!$A38,'P&L by Month Detail'!I:I) -> 14315 | I38: =SUMIF('P&L by Month Detail'!$A:$A,'Condensed P&L by Month'!$A38,'P&L by Month Detail'!J:J) -> 9048 | J38: =SUMIF('P&L by Month Detail'!$A:$A,'Condensed P&L by Month'!$A38,'P&L by Month Detail'!K:K) -> 10887 | K38: =SUMIF('P&L by Month Detail'!$A:$A,'Condensed P&L by Month'!$A38,'P&L by Month Detail'!L:L) -> 10481 | L38: =SUMIF('P&L by Month Detail'!$A:$A,'Condensed P&L by Month'!$A38,'P&L by Month Detail'!M:M) -> 7303 | M38: =SUMIF('P&L by Month Detail'!$A:$A,'Condensed P&L by Month'!$A38,'P&L by Month Detail'!N:N) -> 8153 | N38: =SUMIF('P&L by Month Detail'!$A:$A,'Condensed P&L by Month'!$A38,'P&L by Month Detail'!O:O) -> 7987 | O38: =SUMIF('P&L by Month Detail'!$A:$A,'Condensed P&L by Month'!$A38,'P&L by Month Detail'!P:P) -> 3121 | P38: =SUMIF('P&L by Month Detail'!$A:$A,'Condensed P&L by Month'!$A38,'P&L by Month Detail'!Q:Q) -> 4520 | Q38: =+SUM(F38:P38)+B38 -> 118962
A39: General and Administrative Expenses | B39: =SUMIF('P&L by Month Detail'!$A:$A,'Condensed P&L by Month'!$A39,'P&L by Month Detail'!C:C) -> 33590 | C39: =SUMIF('P&L by Month Detail'!$A:$A,'Condensed P&L by Month'!$A39,'P&L by Month Detail'!D:D) -> 0 | D39: =+B39+C39 -> 33590 | F39: =SUMIF('P&L by Month Detail'!$A:$A,'Condensed P&L by Month'!$A39,'P&L by Month Detail'!G:G) -> 33809 | G39: =SUMIF('P&L by Month Detail'!$A:$A,'Condensed P&L by Month'!$A39,'P&L by Month Detail'!H:H) -> 25910 | H39: =SUMIF('P&L by Month Detail'!$A:$A,'Condensed P&L by Month'!$A39,'P&L by Month Detail'!I:I) -> 22849 | I39: =SUMIF('P&L by Month Detail'!$A:$A,'Condensed P&L by Month'!$A39,'P&L by Month Detail'!J:J) -> 16742 | J39: =SUMIF('P&L by Month Detail'!$A:$A,'Condensed P&L by Month'!$A39,'P&L by Month Detail'!K:K) -> 23977 | K39: =SUMIF('P&L by Month Detail'!$A:$A,'Condensed P&L by Month'!$A39,'P&L by Month Detail'!L:L) -> 17197 | L39: =SUMIF('P&L by Month Detail'!$A:$A,'Condensed P&L by Month'!$A39,'P&L by Month Detail'!M:M) -> 18050 | M39: =SUMIF('P&L by Month Detail'!$A:$A,'Condensed P&L by Month'!$A39,'P&L by Month Detail'!N:N) -> 15130 | N39: =SUMIF('P&L by Month Detail'!$A:$A,'Condensed P&L by Month'!$A39,'P&L by Month Detail'!O:O) -> 18959 | O39: =SUMIF('P&L by Month Detail'!$A:$A,'Condensed P&L by Month'!$A39,'P&L by Month Detail'!P:P) -> 23341 | P39: =SUMIF('P&L by Month Detail'!$A:$A,'Condensed P&L by Month'!$A39,'P&L by Month Detail'!Q:Q) -> 20205 | Q39: =+SUM(F39:P39)+B39 -> 269759
A40: Taxes and Insurance | B40: =SUMIF('P&L by Month Detail'!$A:$A,'Condensed P&L by Month'!$A40,'P&L by Month Detail'!C:C) -> 143390 | C40: =SUMIF('P&L by Month Detail'!$A:$A,'Condensed P&L by Month'!$A40,'P&L by Month Detail'!D:D) -> 0 | D40: =+B40+C40 -> 143390 | F40: =SUMIF('P&L by Month Detail'!$A:$A,'Condensed P&L by Month'!$A40,'P&L by Month Detail'!G:G) -> 7787 | G40: =SUMIF('P&L by Month Detail'!$A:$A,'Condensed P&L by Month'!$A40,'P&L by Month Detail'!H:H) -> 9950 | H40: =SUMIF('P&L by Month Detail'!$A:$A,'Condensed P&L by Month'!$A40,'P&L by Month Detail'!I:I) -> 14268 | I40: =SUMIF('P&L by Month Detail'!$A:$A,'Condensed P&L by Month'!$A40,'P&L by Month Detail'!J:J) -> 6091 | J40: =SUMIF('P&L by Month Detail'!$A:$A,'Condensed P&L by Month'!$A40,'P&L by Month Detail'!K:K) -> 6081 | K40: =SUMIF('P&L by Month Detail'!$A:$A,'Condensed P&L by Month'!$A40,'P&L by Month Detail'!L:L) -> 6826 | L40: =SUMIF('P&L by Month Detail'!$A:$A,'Condensed P&L by Month'!$A40,'P&L by Month Detail'!M:M) -> 5501 | M40: =SUMIF('P&L by Month Detail'!$A:$A,'Condensed P&L by Month'!$A40,'P&L by Month Detail'!N:N) -> 6410 | N40: =SUMIF('P&L by Month Detail'!$A:$A,'Condensed P&L by Month'!$A40,'P&L by Month Detail'!O:O) -> 7430 | O40: =SUMIF('P&L by Month Detail'!$A:$A,'Condensed P&L by Month'!$A40,'P&L by Month Detail'!P:P) -> 7419 | P40: =SUMIF('P&L by Month Detail'!$A:$A,'Condensed P&L by Month'!$A40,'P&L by Month Detail'!Q:Q) -> 7425 | Q40: =+SUM(F40:P40)+B40 -> 228578
A41: Total Operating Expense- no Direct or Sales Labor | B41: =SUM(B35:B40) -> 609711 | C41: =SUM(C35:C40) -> -232420.29 | D41: =SUM(D35:D40) -> 377290.71 | F41: =SUM(F35:F40) -> 281301 | G41: =SUM(G35:G40) -> 242987 | H41: =SUM(H35:H40) -> 284224 | I41: =SUM(I35:I40) -> 279404 | J41: =SUM(J35:J40) -> 271485 | K41: =SUM(K35:K40) -> 254343 | L41: =SUM(L35:L40) -> 260958 | M41: =SUM(M35:M40) -> 240661 | ... Q41: =SUM(Q35:Q40) -> 3525516
A42: Total Operating Net Income- DL above the line | B42: =+B32-B33-B41 -> -193755 | C42: =+C32-C33-C41 -> 98751.94 | D42: =+D32-D33-D41 -> -95003.06 | F42: =+F32-F33-F41 -> 179997 | G42: =+G32-G33-G41 -> 144766 | H42: =+H32-H33-H41 -> 50735 | I42: =+I32-I33-I41 -> 239069 | J42: =+J32-J33-J41 -> 160995 | K42: =+K32-K33-K41 -> 278934 | L42: =+L32-L33-L41 -> 193997 | M42: =+M32-M33-M41 -> 244791 | ... Q42: =+Q32-Q33-Q41 -> 1496410
A43: Other Income (Expense)
A44: Other Income | B44: =SUMIF('P&L by Month Detail'!$A:$A,'Condensed P&L by Month'!$A44,'P&L by Month Detail'!C:C) -> 4203 | C44: =SUMIF('P&L by Month Detail'!$A:$A,'Condensed P&L by Month'!$A44,'P&L by Month Detail'!D:D) -> 3246.98 | D44: =+B44+C44 -> 7449.98 | E44: 12 | F44: =SUMIF('P&L by Month Detail'!$A:$A,'Condensed P&L by Month'!$A44,'P&L by Month Detail'!G:G) -> 13 | G44: =SUMIF('P&L by Month Detail'!$A:$A,'Condensed P&L by Month'!$A44,'P&L by Month Detail'!H:H) -> 15 | H44: =SUMIF('P&L by Month Detail'!$A:$A,'Condensed P&L by Month'!$A44,'P&L by Month Detail'!I:I) -> 12009 | I44: =SUMIF('P&L by Month Detail'!$A:$A,'Condensed P&L by Month'!$A44,'P&L by Month Detail'!J:J) -> 9783 | J44: =SUMIF('P&L by Month Detail'!$A:$A,'Condensed P&L by Month'!$A44,'P&L by Month Detail'!K:K) -> 5604 | K44: =SUMIF('P&L by Month Detail'!$A:$A,'Condensed P&L by Month'!$A44,'P&L by Month Detail'!L:L) -> 9359 | L44: =SUMIF('P&L by Month Detail'!$A:$A,'Condensed P&L by Month'!$A44,'P&L by Month Detail'!M:M) -> 256 | M44: =SUMIF('P&L by Month Detail'!$A:$A,'Condensed P&L by Month'!$A44,'P&L by Month Detail'!N:N) -> 2809 | N44: =SUMIF('P&L by Month Detail'!$A:$A,'Condensed P&L by Month'!$A44,'P&L by Month Detail'!O:O) -> 1632 | O44: =SUMIF('P&L by Month Detail'!$A:$A,'Condensed P&L by Month'!$A44,'P&L by Month Detail'!P:P) -> 1250 | P44: =SUMIF('P&L by Month Detail'!$A:$A,'Condensed P&L by Month'!$A44,'P&L by Month Detail'!Q:Q) -> 17613 | Q44: =+SUM(F44:P44)+B44 -> 64546
A45: Other Expense | B45: =SUMIF('P&L by Month Detail'!$A:$A,'Condensed P&L by Month'!$A45,'P&L by Month Detail'!C:C) -> 189591 | C45: =SUMIF('P&L by Month Detail'!$A:$A,'Condensed P&L by Month'!$A45,'P&L by Month Detail'!D:D) -> -287253.95 | D45: =+B45+C45 -> -97662.95 | E45: 7, 12, 13 & 14 | F45: =SUMIF('P&L by Month Detail'!$A:$A,'Condensed P&L by Month'!$A45,'P&L by Month Detail'!G:G) -> -21719 | G45: =SUMIF('P&L by Month Detail'!$A:$A,'Condensed P&L by Month'!$A45,'P&L by Month Detail'!H:H) -> -66627 | H45: =SUMIF('P&L by Month Detail'!$A:$A,'Condensed P&L by Month'!$A45,'P&L by Month Detail'!I:I) -> -28869 | I45: =SUMIF('P&L by Month Detail'!$A:$A,'Condensed P&L by Month'!$A45,'P&L by Month Detail'!J:J) -> -62648 | J45: =SUMIF('P&L by Month Detail'!$A:$A,'Condensed P&L by Month'!$A45,'P&L by Month Detail'!K:K) -> -36001 | K45: =SUMIF('P&L by Month Detail'!$A:$A,'Condensed P&L by Month'!$A45,'P&L by Month Detail'!L:L) -> -52417 | L45: =SUMIF('P&L by Month Detail'!$A:$A,'Condensed P&L by Month'!$A45,'P&L by Month Detail'!M:M) -> -37641 | M45: =SUMIF('P&L by Month Detail'!$A:$A,'Condensed P&L by Month'!$A45,'P&L by Month Detail'!N:N) -> -29315 | N45: =SUMIF('P&L by Month Detail'!$A:$A,'Condensed P&L by Month'!$A45,'P&L by Month Detail'!O:O) -> -26987 | O45: =SUMIF('P&L by Month Detail'!$A:$A,'Condensed P&L by Month'!$A45,'P&L by Month Detail'!P:P) -> -57537 | P45: =SUMIF('P&L by Month Detail'!$A:$A,'Condensed P&L by Month'!$A45,'P&L by Month Detail'!Q:Q) -> -34744 | Q45: =+SUM(F45:P45)+B45 -> -264914
A46: Total Other Income (Expense) | B46: =+B44+B45 -> 193794 | C46: =+C44+C45 -> -284006.97 | D46: =+D44+D45 -> -90212.97 | F46: =+F44+F45 -> -21706 | G46: =+G44+G45 -> -66612 | H46: =+H44+H45 -> -16860 | I46: =+I44+I45 -> -52865 | J46: =+J44+J45 -> -30397 | K46: =+K44+K45 -> -43058 | L46: =+L44+L45 -> -37385 | M46: =+M44+M45 -> -26506 | ... Q46: =+Q44+Q45 -> -200368
A47: Income Taxes | B47: =SUMIF('P&L by Month Detail'!$A:$A,'Condensed P&L by Month'!$A47,'P&L by Month Detail'!C:C) -> 6023 | C47: =SUMIF('P&L by Month Detail'!$A:$A,'Condensed P&L by Month'!$A47,'P&L by Month Detail'!D:D) -> -2397.31 | D47: =+B47+C47 -> 3625.69 | F47: =SUMIF('P&L by Month Detail'!$A:$A,'Condensed P&L by Month'!$A47,'P&L by Month Detail'!G:G) -> 0 | G47: =SUMIF('P&L by Month Detail'!$A:$A,'Condensed P&L by Month'!$A47,'P&L by Month Detail'!H:H) -> 0 | H47: =SUMIF('P&L by Month Detail'!$A:$A,'Condensed P&L by Month'!$A47,'P&L by Month Detail'!I:I) -> 5382 | I47: =SUMIF('P&L by Month Detail'!$A:$A,'Condensed P&L by Month'!$A47,'P&L by Month Detail'!J:J) -> 1470 | J47: =SUMIF('P&L by Month Detail'!$A:$A,'Condensed P&L by Month'!$A47,'P&L by Month Detail'!K:K) -> 1048 | K47: =SUMIF('P&L by Month Detail'!$A:$A,'Condensed P&L by Month'!$A47,'P&L by Month Detail'!L:L) -> 2047 | L47: =SUMIF('P&L by Month Detail'!$A:$A,'Condensed P&L by Month'!$A47,'P&L by Month Detail'!M:M) -> 1202 | M47: =SUMIF('P&L by Month Detail'!$A:$A,'Condensed P&L by Month'!$A47,'P&L by Month Detail'!N:N) -> 0 | N47: =SUMIF('P&L by Month Detail'!$A:$A,'Condensed P&L by Month'!$A47,'P&L by Month Detail'!O:O) -> 15867 | O47: =SUMIF('P&L by Month Detail'!$A:$A,'Condensed P&L by Month'!$A47,'P&L by Month Detail'!P:P) -> 2691 | P47: =SUMIF('P&L by Month Detail'!$A:$A,'Condensed P&L by Month'!$A47,'P&L by Month Detail'!Q:Q) -> 2920 | Q47: =+SUM(F47:P47)+B47 -> 38650
A48: Net Income | B48: =+B42+B46-B47 -> -5984 | C48: =+C42+C46-C47 -> -182857.72 | D48: =+D42+D46-D47 -> -188841.72 | F48: =+F42+F46-F47 -> 158291 | G48: =+G42+G46-G47 -> 78154 | H48: =+H42+H46-H47 -> 28493 | I48: =+I42+I46-I47 -> 184734 | J48: =+J42+J46-J47 -> 129550 | K48: =+K42+K46-K47 -> 233829 | L48: =+L42+L46-L47 -> 155410 | M48: =+M42+M46-M47 -> 218285 | ... Q48: =+Q42+Q46-Q47 -> 1257392
A51: Created on : 03/24/2026 3:43 AM PDT

Sheet P&L by Month Detail
A1: Datapath
A2: P&L MTD with Previous Month Comparison
A3: Reporting Book:
A4: As of Date:
C6: Data Path - All Locations | G6: Data Path - All Locations | H6: Data Path - All Locations | I6: Data Path - All Locations | J6: Data Path - All Locations | K6: Data Path - All Locations | L6: Data Path - All Locations | M6: Data Path - All Locations | N6: Data Path - All Locations | O6: Data Path - All Locations | P6: Data Path - All Locations | Q6: Data Path - All Locations | R6: Data Path - All Locations
C7: Month Ending | E7: Unadjusted | G7: Month Ending | H7: Month Ending | I7: Month Ending | J7: Month Ending | K7: Month Ending | L7: Month Ending | M7: Month Ending | N7: Month Ending | O7: Month Ending | P7: Month Ending | Q7: Month Ending | R7: Month Ending
C8: 12/31/2025 | D8: YE Clean up | E8: 12/31/2025 | G8: 11/30/2025 | H8: 10/31/2025 | I8: 09/30/2025 | J8: 08/31/2025 | K8: 07/31/2025 | L8: 06/30/2025 | M8: 05/31/2025 | N8: 04/30/2025 | O8: 03/31/2025 | P8: 02/28/2025 | Q8: 01/31/2025 | R8: Total
C9: Actual | G9: Actual | H9: Actual | I9: Actual | J9: Actual | K9: Actual | L9: Actual | M9: Actual | N9: Actual | O9: Actual | P9: Actual | Q9: Actual | R9: Actual
A10: Net Income- With DL above the line
A11: Operating Net Income- DL above the line
A12: Gross Profit with Direct Labor
A13: Revenue
A14: Monthly Recurring Services
A15: 40000 - Managed IT Revenue | B15: 40000 | C15: 558277 | D15: =-SUMIF(Sheet1!A:A,B15,Sheet1!Z:Z) -> 0 | E15: =+C15+D15 -> 558277 | G15: 551140 | H15: 548490 | I15: 515994 | J15: 556309 | K15: 540665 | L15: 553888 | M15: 542770 | N15: 546505 | O15: 508811 | P15: 500073 | Q15: 492103 | R15: =SUM(G15:Q15)+C15 -> 6415025
A16: 40100 - Managed Security Revenue | B16: 40100 | C16: 5055 | D16: =-SUMIF(Sheet1!A:A,B16,Sheet1!Z:Z) -> 0 | E16: =+C16+D16 -> 5055 | G16: 5055 | H16: 4729 | I16: 5056 | J16: 5162 | K16: 5162 | L16: 7797 | M16: 7797 | N16: 7797 | O16: 7797 | P16: 7797 | Q16: 9897 | R16: =SUM(G16:Q16)+C16 -> 79101
A17: 40200 - Managed Voice Revenue | B17: 40200 | C17: 8406 | D17: =-SUMIF(Sheet1!A:A,B17,Sheet1!Z:Z) -> 0 | E17: =+C17+D17 -> 8406 | G17: 8407 | H17: 8407 | I17: 8532 | J17: 8807 | K17: 9888 | L17: 10629 | M17: 10629 | N17: 10210 | O17: 11050 | P17: 11462 | Q17: 13253 | R17: =SUM(G17:Q17)+C17 -> 119680
A18: 41320 - Managed Back up Revenue | B18: 41320 | C18: 10531 | D18: =-SUMIF(Sheet1!A:A,B18,Sheet1!Z:Z) -> 0 | E18: =+C18+D18 -> 10531 | G18: 11493 | H18: 11556 | I18: 11722 | J18: 11417 | K18: 12099 | L18: 13052 | M18: 13234 | N18: 12807 | O18: 12918 | P18: 12558 | Q18: 12039 | R18: =SUM(G18:Q18)+C18 -> 145426
A19: 41925 - USAC ERATE BM Revenue | B19: 41925 | C19: 4680 | D19: =-SUMIF(Sheet1!A:A,B19,Sheet1!Z:Z) -> 0 | E19: =+C19+D19 -> 4680 | G19: 5774 | H19: 5774 | I19: 5913 | J19: 6140 | K19: 6111 | L19: 10072 | M19: 10072 | N19: 10072 | O19: 10072 | P19: 10072 | Q19: 10072 | R19: =SUM(G19:Q19)+C19 -> 94824
A20: Monthly Recurring Services | C20: =SUM(C15:C19) -> 586949 | D20: =SUM(D15:D19) -> 0 | E20: =SUM(E15:E19) -> 586949 | G20: =SUM(G15:G19) -> 581869 | H20: =SUM(H15:H19) -> 578956 | I20: =SUM(I15:I19) -> 547217 | J20: =SUM(J15:J19) -> 587835 | K20: =SUM(K15:K19) -> 573925 | L20: =SUM(L15:L19) -> 595438 | M20: =SUM(M15:M19) -> 584502 | N20: =SUM(N15:N19) -> 587391 | ... Q20: =SUM(Q15:Q19) -> 537364 | R20: =SUM(G20:Q20)+C20 -> 6854056
A21: Monthly Recurring Private Cloud
A22: 41360 - Public Cloud Revenue | B22: 41360 | C22: 1144 | D22: =-SUMIF(Sheet1!A:A,B22,Sheet1!Z:Z) -> 0 | E22: =+C22+D22 -> 1144 | G22: 1144 | H22: 1144 | I22: 1144 | J22: 1144 | K22: 1144 | L22: 1144 | M22: 1144 | N22: 1144 | O22: 1144 | P22: 1144 | Q22: 1144 | R22: =SUM(G22:Q22)+C22 -> 13728
A23: 41365 - Private Cloud Revenue | B23: 41365 | C23: 26057 | D23: =-SUMIF(Sheet1!A:A,B23,Sheet1!Z:Z) -> 0 | E23: =+C23+D23 -> 26057 | G23: 25871 | H23: 25853 | I23: 20457 | J23: 25280 | K23: 25117 | L23: 23342 | M23: 23324 | N23: 22060 | O23: 21582 | P23: 21582 | Q23: 18993 | R23: =SUM(G23:Q23)+C23 -> 279518
A24: Monthly Recurring Private Cloud | C24: =SUM(C22:C23) -> 27201 | D24: =SUM(D22:D23) -> 0 | E24: =SUM(E22:E23) -> 27201 | G24: =SUM(G22:G23) -> 27015 | H24: =SUM(H22:H23) -> 26997 | I24: =SUM(I22:I23) -> 21601 | J24: =SUM(J22:J23) -> 26424 | K24: =SUM(K22:K23) -> 26261 | L24: =SUM(L22:L23) -> 24486 | M24: =SUM(M22:M23) -> 24468 | N24: =SUM(N22:N23) -> 23204 | ... Q24: =SUM(Q22:Q23) -> 20137 | R24: =SUM(G24:Q24)+C24 -> 293246
A25: Monthly Recurring Resale
A26: 41200 - HaaS Revenue | B26: 41200 | C26: 27131 | D26: =-SUMIF(Sheet1!A:A,B26,Sheet1!Z:Z) -> 0 | E26: =+C26+D26 -> 27131 | G26: 26941 | H26: 26390 | I26: 20854 | J26: 22102 | K26: 26229 | L26: 26479 | M26: 26155 | N26: 24655 | O26: 24654 | P26: 24795 | Q26: 25121 | R26: =SUM(G26:Q26)+C26 -> 301506
A27: 41250 - Chromebook ADP Revenue | B27: 41250 | C27: 562 | D27: =-SUMIF(Sheet1!A:A,B27,Sheet1!Z:Z) -> 0 | E27: =+C27+D27 -> 562 | G27: 563 | H27: 562 | I27: 563 | J27: 563 | K27: 562 | L27: 563 | M27: 562 | N27: 562 | O27: 563 | P27: 562 | Q27: 562 | R27: =SUM(G27:Q27)+C27 -> 6749
A28: 41300 - Cloud SAAS Revenue | B28: 41300 | C28: -15338 | D28: =-SUMIF(Sheet1!A:A,B28,Sheet1!Z:Z) -> -60357 | E28: =+C28+D28 -> -75695 | F28: 1 | G28: 46534 | H28: 51519 | I28: 45616 | J28: 50092 | K28: 50221 | L28: 49375 | M28: 49594 | N28: 39052 | O28: 38905 | P28: 38181 | Q28: 31136 | R28: =SUM(G28:Q28)+C28 -> 474887
A29: 41350 - Managed Spam Filtering Revenue | B29: 41350 | C29: 896 | D29: =-SUMIF(Sheet1!A:A,B29,Sheet1!Z:Z) -> 0 | E29: =+C29+D29 -> 896 | G29: 902 | H29: 899 | I29: 954 | J29: 952 | K29: 949 | L29: 952 | M29: 949 | N29: 756 | O29: 770 | P29: 974 | Q29: 974 | R29: =SUM(G29:Q29)+C29 -> 10927
A30: 41450 - Microsoft 365 Revenue | B30: 41450 | C30: 126918 | D30: =-SUMIF(Sheet1!A:A,B30,Sheet1!Z:Z) -> 0 | E30: =+C30+D30 -> 126918 | G30: 124569 | H30: 122540 | I30: 82195 | J30: 89934 | K30: 87546 | L30: 84100 | M30: 95660 | N30: 93187 | O30: 88758 | P30: 80232 | Q30: 81227 | R30: =SUM(G30:Q30)+C30 -> 1156866
A31: 42100 - Security Resale Revenue | B31: 42100 | C31: 147131 | D31: =-SUMIF(Sheet1!A:A,B31,Sheet1!Z:Z) -> 0 | E31: =+C31+D31 -> 147131 | G31: 146553 | H31: 148714 | I31: 143365 | J31: 138622 | K31: 136209 | L31: 133413 | M31: 129838 | N31: 106277 | O31: 104647 | P31: 96967 | Q31: 94782 | R31: =SUM(G31:Q31)+C31 -> 1526518
A32: 42200 - Tool Resale Revenue | B32: 42200 | C32: 3617 | D32: =-SUMIF(Sheet1!A:A,B32,Sheet1!Z:Z) -> 0 | E32: =+C32+D32 -> 3617 | G32: 3616 | H32: 3616 | I32: 3616 | J32: 3647 | K32: 3652 | L32: 3963 | M32: 3963 | N32: 4589 | O32: 4589 | P32: 4589 | Q32: 4529 | R32: =SUM(G32:Q32)+C32 -> 47986
A33: 42300 - Voice Resale Revenue | B33: 42300 | C33: 2545 | D33: =-SUMIF(Sheet1!A:A,B33,Sheet1!Z:Z) -> 0 | E33: =+C33+D33 -> 2545 | G33: 2546 | H33: 2546 | I33: 2546 | J33: 2434 | K33: 2433 | L33: 2434 | M33: 2434 | N33: 2433 | O33: 2434 | P33: 1261 | Q33: 641 | R33: =SUM(G33:Q33)+C33 -> 26687
A34: Monthly Recurring Resale | C34: =SUM(C26:C33) -> 293462 | D34: =SUM(D26:D33) -> -60357 | E34: =SUM(E26:E33) -> 233105 | G34: =SUM(G26:G33) -> 352224 | H34: =SUM(H26:H33) -> 356786 | I34: =SUM(I26:I33) -> 299709 | J34: =SUM(J26:J33) -> 308346 | K34: =SUM(K26:K33) -> 307801 | L34: =SUM(L26:L33) -> 301279 | M34: =SUM(M26:M33) -> 309155 | N34: =SUM(N26:N33) -> 271511 | ... Q34: =SUM(Q26:Q33) -> 238972 | R34: =SUM(G34:Q34)+C34 -> 3552126
A35: Project Services
A36: 41500 - Project Service Revenue | B36: 41500 | C36: 61485 | D36: =-SUMIF(Sheet1!A:A,B36,Sheet1!Z:Z) -> 43058.14 | E36: =+C36+D36 -> 104543.14 | F36: 2 | G36: 47381 | H36: 67554 | I36: 46071 | J36: 104693 | K36: 53462 | L36: 120765 | M36: 47201 | N36: 99226 | O36: 105235 | P36: 92496 | Q36: 51717 | R36: =SUM(G36:Q36)+C36 -> 897286
A37: Revenue - Project Services | C37: =+C36 -> 61485 | D37: =+D36 -> 43058.14 | E37: =+E36 -> 104543.14 | G37: =+G36 -> 47381 | H37: =+H36 -> 67554 | I37: =+I36 -> 46071 | J37: =+J36 -> 104693 | K37: =+K36 -> 53462 | L37: =+L36 -> 120765 | M37: =+M36 -> 47201 | N37: =+N36 -> 99226 | ... Q37: =+Q36 -> 51717 | R37: =SUM(G37:Q37)+C37 -> 897286
A38: Subcontracted Services
A39: 41700 - Subcontracted Service Revenue | B39: 41700 | C39: 4614 | D39: =-SUMIF(Sheet1!A:A,B39,Sheet1!Z:Z) -> 0 | E39: =+C39+D39 -> 4614 | G39: 13197 | H39: 19989 | I39: 14480 | J39: 36139 | K39: 12686 | L39: 8539 | M39: 16341 | N39: 14387 | O39: 35020 | P39: 58116 | Q39: 86683 | R39: =SUM(G39:Q39)+C39 -> 320191
A40: Subcontracted Services | C40: =+C39 -> 4614 | D40: =+D39 -> 0 | E40: =+E39 -> 4614 | G40: =+G39 -> 13197 | H40: =+H39 -> 19989 | I40: =+I39 -> 14480 | J40: =+J39 -> 36139 | K40: =+K39 -> 12686 | L40: =+L39 -> 8539 | M40: =+M39 -> 16341 | N40: =+N39 -> 14387 | ... Q40: =+Q39 -> 86683 | R40: =SUM(G40:Q40)+C40 -> 320191
A41: Product Sales
A42: 42000 - Product Sales Revenue | B42: 42000 | C42: 151701 | D42: =-SUMIF(Sheet1!A:A,B42,Sheet1!Z:Z) -> 0 | E42: =+C42+D42 -> 151701 | G42: 277939 | H42: 566965 | I42: 356300 | J42: 649034 | K42: 796750 | L42: 589564 | M42: 493958 | N42: 571435 | O42: 428136 | P42: 544906 | Q42: 203096 | R42: =SUM(G42:Q42)+C42 -> 5629784
A43: 44000 - Freight and Shipping Revenue | B43: 44000 | C43: 6024 | D43: =-SUMIF(Sheet1!A:A,B43,Sheet1!Z:Z) -> 0 | E43: =+C43+D43 -> 6024 | G43: 8146 | H43: 11848 | I43: 7770 | J43: 18636 | K43: 6705 | L43: 8668 | M43: 7030 | N43: 13469 | O43: 12247 | P43: 9126 | Q43: 8709 | R43: =SUM(G43:Q43)+C43 -> 118378
A44: Revenue - Product Sales | C44: =+C42+C43 -> 157725 | D44: =+D42+D43 -> 0 | E44: =+E42+E43 -> 157725 | G44: =+G42+G43 -> 286085 | H44: =+H42+H43 -> 578813 | I44: =+I42+I43 -> 364070 | J44: =+J42+J43 -> 667670 | K44: =+K42+K43 -> 803455 | L44: =+L42+L43 -> 598232 | M44: =+M42+M43 -> 500988 | N44: =+N42+N43 -> 584904 | ... Q44: =+Q42+Q43 -> 211805 | R44: =SUM(G44:Q44)+C44 -> 5748162
A45: Revenue - Other
A46: 40800 - Revenue - Other | B46: 40800 | C46: 0 | D46: =-SUMIF(Sheet1!A:A,B46,Sheet1!Z:Z) -> 0 | E46: =+C46+D46 -> 0 | G46: 0 | H46: 0 | I46: 0 | J46: -59 | K46: 0 | R46: =SUM(G46:Q46)+C46 -> -59
A47: 41400 - Commission Revenue | B47: 41400 | C47: 4906 | D47: =-SUMIF(Sheet1!A:A,B47,Sheet1!Z:Z) -> 0 | E47: =+C47+D47 -> 4906 | G47: 9277 | H47: 9108 | I47: 6305 | J47: 6445 | K47: 7049 | L47: 3891 | M47: 7133 | N47: 11171 | O47: 11139 | P47: 7690 | Q47: 5590 | R47: =SUM(G47:Q47)+C47 -> 89704
A48: Revenue - Other | C48: =+C46+C47 -> 4906 | D48: =+D46+D47 -> 0 | E48: =+E46+E47 -> 4906 | G48: =+G46+G47 -> 9277 | H48: =+H46+H47 -> 9108 | I48: =+I46+I47 -> 6305 | J48: =+J46+J47 -> 6386 | K48: =+K46+K47 -> 7049 | L48: =+L46+L47 -> 3891 | M48: =+M46+M47 -> 7133 | N48: =+N46+N47 -> 11171 | ... Q48: =+Q46+Q47 -> 5590 | R48: =SUM(G48:Q48)+C48 -> 89645
A49: Total Revenue | C49: =+C48+C44+C40+C37+C34+C24+C20 -> 1136342 | D49: =+D48+D44+D40+D37+D34+D24+D20 -> -17298.86 | E49: =+E48+E44+E40+E37+E34+E24+E20 -> 1119043.1 | G49: =+G48+G44+G40+G37+G34+G24+G20 -> 1317048 | H49: =+H48+H44+H40+H37+H34+H24+H20 -> 1638203 | I49: =+I48+I44+I40+I37+I34+I24+I20 -> 1299453 | J49: =+J48+J44+J40+J37+J34+J24+J20 -> 1737493 | K49: =+K48+K44+K40+K37+K34+K24+K20 -> 1784639 | L49: =+L48+L44+L40+L37+L34+L24+L20 -> 1652630 | M49: =+M48+M44+M40+M37+M34+M24+M20 -> 1489788 | N49: =+N48+N44+N40+N37+N34+N24+N20 -> 1591794 | ... Q49: =+Q48+Q44+Q40+Q37+Q34+Q24+Q20 -> 1152268 | R49: =SUM(G49:Q49)+C49 -> 17754712
A50: Cost of Rev with Direct and IT Project Labor
A51: Managed IT Service Costs
A52: 50000 - Managed IT Costs | B52: 50000 | C52: 28797 | D52: =-SUMIF(Sheet1!A:A,B52,Sheet1!Z:Z) -> 0 | E52: =+C52+D52 -> 28797 | G52: 16754 | H52: 38253 | I52: 29904 | J52: 28443 | K52: 24465 | L52: 22966 | M52: 26243 | N52: 23445 | O52: 22148 | P52: 24343 | Q52: 22885 | R52: =SUM(G52:Q52)+C52 -> 308646
A53: Managed IT Service Costs | C53: =+C52 -> 28797 | D53: =+D52 -> 0 | E53: =+E52 -> 28797 | G53: =+G52 -> 16754 | H53: =+H52 -> 38253 | I53: =+I52 -> 29904 | J53: =+J52 -> 28443 | K53: =+K52 -> 24465 | L53: =+L52 -> 22966 | M53: =+M52 -> 26243 | N53: =+N52 -> 23445 | ... Q53: =+Q52 -> 22885 | R53: =SUM(G53:Q53)+C53 -> 308646
A54: Cost of Monthly Recurring Cloud
A55: 50090 - Public Cloud Costs | B55: 50090 | C55: 401 | D55: =-SUMIF(Sheet1!A:A,B55,Sheet1!Z:Z) -> 0 | E55: =+C55+D55 -> 401 | G55: 400 | H55: 401 | I55: 401 | J55: 401 | K55: 401 | L55: 401 | M55: 401 | N55: 401 | O55: 401 | P55: 401 | Q55: 401 | R55: =SUM(G55:Q55)+C55 -> 4811
A56: 50095 - Private Cloud Costs | B56: 50095 | C56: 10912 | D56: =-SUMIF(Sheet1!A:A,B56,Sheet1!Z:Z) -> 0 | E56: =+C56+D56 -> 10912 | G56: 11340 | H56: 11002 | I56: 8612 | J56: 10882 | K56: 10786 | L56: 11264 | M56: 12994 | N56: 9884 | O56: 9885 | P56: 9951 | Q56: 8514 | R56: =SUM(G56:Q56)+C56 -> 126026
A57: Cost of Monthly Recurring Cloud | C57: =+C55+C56 -> 11313 | D57: =+D55+D56 -> 0 | E57: =+E55+E56 -> 11313 | G57: =+G55+G56 -> 11740 | H57: =+H55+H56 -> 11403 | I57: =+I55+I56 -> 9013 | J57: =+J55+J56 -> 11283 | K57: =+K55+K56 -> 11187 | L57: =+L55+L56 -> 11665 | M57: =+M55+M56 -> 13395 | N57: =+N55+N56 -> 10285 | ... Q57: =+Q55+Q56 -> 8915 | R57: =SUM(G57:Q57)+C57 -> 130837
A58: Cost of Monthly Recurring Resale
A59: 50050 - Managed Back up Costs | B59: 50050 | C59: 4940 | D59: =-SUMIF(Sheet1!A:A,B59,Sheet1!Z:Z) -> 0 | E59: =+C59+D59 -> 4940 | G59: 5454 | H59: 5436 | I59: 4228 | J59: 5608 | K59: 5772 | L59: 9489 | M59: 9771 | N59: 9840 | O59: 6097 | P59: 6016 | Q59: 5823 | R59: =SUM(G59:Q59)+C59 -> 78474
A60: 50080 - Managed Spam Filtering Costs | B60: 50080 | C60: 373 | D60: =-SUMIF(Sheet1!A:A,B60,Sheet1!Z:Z) -> 0 | E60: =+C60+D60 -> 373 | G60: 375 | H60: 373 | I60: 391 | J60: 390 | K60: 389 | L60: 421 | M60: 391 | N60: 311 | O60: 379 | P60: 381 | Q60: 381 | R60: =SUM(G60:Q60)+C60 -> 4555
A61: 50100 - Domain Names Costs | B61: 50100 | C61: 238 | D61: =-SUMIF(Sheet1!A:A,B61,Sheet1!Z:Z) -> 0 | E61: =+C61+D61 -> 238 | G61: 375 | H61: 527 | I61: 606 | J61: 0 | K61: 142 | L61: 166 | M61: 72 | N61: 229 | O61: 182 | P61: 110 | Q61: 401 | R61: =SUM(G61:Q61)+C61 -> 3048
A62: 50150 - Recurring Resale Cost - MSP (Cloud SaaS) | B62: 50150 | C62: 29470 | D62: =-SUMIF(Sheet1!A:A,B62,Sheet1!Z:Z) -> 0 | E62: =+C62+D62 -> 29470 | G62: 35438 | H62: 33753 | I62: 22968 | J62: 30137 | K62: 28969 | L62: 30612 | M62: 29174 | N62: 24171 | O62: 24046 | P62: 23728 | Q62: 21596 | R62: =SUM(G62:Q62)+C62 -> 334062
A63: 50190 - Managed Voice Costs | B63: 50190 | C63: 1160 | D63: =-SUMIF(Sheet1!A:A,B63,Sheet1!Z:Z) -> 0 | E63: =+C63+D63 -> 1160 | G63: 1116 | H63: 2876 | I63: 0 | J63: 0 | K63: 0 | L63: 190 | M63: 0 | N63: 0 | O63: 195 | R63: =SUM(G63:Q63)+C63 -> 5537
A64: 50400 - HaaS Costs | B64: 50400 | C64: 8507 | D64: =-SUMIF(Sheet1!A:A,B64,Sheet1!Z:Z) -> 0 | E64: =+C64+D64 -> 8507 | G64: 8773 | H64: 8760 | I64: 7309 | J64: 7540 | K64: 9140 | L64: 9544 | M64: 9633 | N64: 9758 | O64: 9633 | P64: 9437 | Q64: 9379 | R64: =SUM(G64:Q64)+C64 -> 107413
A65: 51250 - Chromebook ADP Costs | B65: 51250 | C65: 3336 | D65: =-SUMIF(Sheet1!A:A,B65,Sheet1!Z:Z) -> 0 | E65: =+C65+D65 -> 3336 | G65: 0 | H65: 6364 | I65: 5842 | J65: 0 | K65: 0 | L65: 0 | M65: 0 | N65: 0 | O65: 0 | P65: 0 | Q65: 1450 | R65: =SUM(G65:Q65)+C65 -> 16992
A66: 51450 - Microsoft 365 Costs | B66: 51450 | C66: 101283 | D66: =-SUMIF(Sheet1!A:A,B66,Sheet1!Z:Z) -> 0 | E66: =+C66+D66 -> 101283 | G66: 101870 | H66: 100116 | I66: 66500 | J66: 72819 | K66: 71087 | L66: 68586 | M66: 69373 | N66: 77062 | O66: 72524 | P66: 65422 | Q66: 66621 | R66: =SUM(G66:Q66)+C66 -> 933263
A67: 52100 - Security Resale Costs | B67: 52100 | C67: 64890 | D67: =-SUMIF(Sheet1!A:A,B67,Sheet1!Z:Z) -> 0 | E67: =+C67+D67 -> 64890 | G67: 64616 | H67: 64375 | I67: 62646 | J67: 58554 | K67: 57719 | L67: 47974 | M67: 42039 | N67: 44660 | O67: 51889 | P67: 48873 | Q67: 47532 | R67: =SUM(G67:Q67)+C67 -> 655767
A68: 52300 - Voice Resale Costs | B68: 52300 | C68: 5043 | D68: =-SUMIF(Sheet1!A:A,B68,Sheet1!Z:Z) -> 0 | E68: =+C68+D68 -> 5043 | G68: 5019 | H68: 5011 | I68: 5005 | J68: 3152 | K68: 3153 | L68: 3222 | M68: 3162 | N68: 3162 | O68: 3162 | P68: 2306 | Q68: 1661 | R68: =SUM(G68:Q68)+C68 -> 43058
A69: 62500 - Managed Security Costs | B69: 62500 | C69: 1897 | D69: =-SUMIF(Sheet1!A:A,B69,Sheet1!Z:Z) -> 0 | E69: =+C69+D69 -> 1897 | G69: 1873 | H69: 1843 | I69: 1827 | J69: 777 | K69: 1491 | L69: 2922 | M69: 2919 | N69: 2855 | O69: 2908 | P69: 2951 | Q69: 3105 | R69: =SUM(G69:Q69)+C69 -> 27368
A70: Cost of Monthly Recurring Resale | C70: =SUM(C59:C69) -> 221137 | D70: =SUM(D59:D69) -> 0 | E70: =SUM(E59:E69) -> 221137 | G70: =SUM(G59:G69) -> 224909 | H70: =SUM(H59:H69) -> 229434 | I70: =SUM(I59:I69) -> 177322 | J70: =SUM(J59:J69) -> 178977 | K70: =SUM(K59:K69) -> 177862 | L70: =SUM(L59:L69) -> 173126 | M70: =SUM(M59:M69) -> 166534 | N70: =SUM(N59:N69) -> 172048 | ... Q70: =SUM(Q59:Q69) -> 157949 | R70: =SUM(G70:Q70)+C70 -> 2209537
A71: Project Service Costs
A72: 50200 - Project Service Costs | B72: 50200 | C72: 0 | D72: =-SUMIF(Sheet1!A:A,B72,Sheet1!Z:Z) -> 0 | E72: =+C72+D72 -> 0 | G72: 0 | H72: 0 | I72: 0 | J72: 0 | K72: 1028 | L72: 1215 | M72: 632 | N72: 0 | O72: 24 | R72: =SUM(G72:Q72)+C72 -> 2899
A73: Project Service Costs | C73: =+C72 -> 0 | D73: =+D72 -> 0 | E73: =+E72 -> 0 | G73: =+G72 -> 0 | H73: =+H72 -> 0 | I73: =+I72 -> 0 | J73: =+J72 -> 0 | K73: =+K72 -> 1028 | L73: =+L72 -> 1215 | M73: =+M72 -> 632 | N73: =+N72 -> 0 | ... Q73: =+Q72 -> 0 | R73: =SUM(G73:Q73)+C73 -> 2899
A74: Subcontractor Service Costs
A75: 50500 - Subcontracted Service Costs | B75: 50500 | C75: 2305 | D75: =-SUMIF(Sheet1!A:A,B75,Sheet1!Z:Z) -> 0 | E75: =+C75+D75 -> 2305 | G75: 23527 | H75: 23040 | I75: 13423 | J75: 31339 | K75: 11923 | L75: 6946 | M75: 13493 | N75: 14836 | O75: 29319 | P75: 48356 | Q75: 72436 | R75: =SUM(G75:Q75)+C75 -> 290943
A76: Subcontractor Service Costs | C76: =+C75 -> 2305 | D76: =+D75 -> 0 | E76: =+E75 -> 2305 | G76: =+G75 -> 23527 | H76: =+H75 -> 23040 | I76: =+I75 -> 13423 | J76: =+J75 -> 31339 | K76: =+K75 -> 11923 | L76: =+L75 -> 6946 | M76: =+M75 -> 13493 | N76: =+N75 -> 14836 | ... Q76: =+Q75 -> 72436 | R76: =SUM(G76:Q76)+C76 -> 290943
A77: Product Sales Cost
A78: 50300 - Product Sales Costs | B78: 50300 | C78: 135295 | D78: =-SUMIF(Sheet1!A:A,B78,Sheet1!Z:Z) -> 0 | E78: =+C78+D78 -> 135295 | G78: 224835 | H78: 465063 | I78: 304045 | J78: 543762 | K78: 687967 | L78: 495522 | M78: 402630 | N78: 483514 | O78: 360592 | P78: 463290 | Q78: 171753 | R78: =SUM(G78:Q78)+C78 -> 4738268
A79: 54000 - Freight Cost | B79: 54000 | C79: -33040 | D79: =-SUMIF(Sheet1!A:A,B79,Sheet1!Z:Z) -> 42625.69 | E79: =+C79+D79 -> 9585.69 | F79: 3 | G79: 15507 | H79: 20943 | I79: 17109 | J79: 25669 | K79: 7010 | L79: 11190 | M79: 7260 | N79: 11757 | O79: 10096 | P79: 8701 | Q79: 8639 | R79: =SUM(G79:Q79)+C79 -> 110841
A80: Product Sales Cost | C80: =+C78+C79 -> 102255 | D80: =+D78+D79 -> 42625.69 | E80: =+E78+E79 -> 144880.69 | G80: =+G78+G79 -> 240342 | H80: =+H78+H79 -> 486006 | I80: =+I78+I79 -> 321154 | J80: =+J78+J79 -> 569431 | K80: =+K78+K79 -> 694977 | L80: =+L78+L79 -> 506712 | M80: =+M78+M79 -> 409890 | N80: =+N78+N79 -> 495271 | ... Q80: =+Q78+Q79 -> 180392 | R80: =SUM(G80:Q80)+C80 -> 4849109
A81: IT Project Labor
A82: 50605 - Project Labor - Wages | B82: 50605 | C82: -15249 | D82: =-SUMIF(Sheet1!A:A,B82,Sheet1!Z:Z) -> 64345.44 | E82: =+C82+D82 -> 49096.44 | F82: 5 | G82: 43185 | H82: 47961 | I82: 45877 | J82: 54236 | K82: 55059 | L82: 50284 | M82: 52671 | N82: 56279 | O82: 59815 | P82: 53539 | Q82: 57233 | R82: =SUM(G82:Q82)+C82 -> 560890
A83: 50705 - Payroll Taxes- Project Labor | B83: 50705 | C83: 932 | D83: =-SUMIF(Sheet1!A:A,B83,Sheet1!Z:Z) -> 2591.19 | E83: =+C83+D83 -> 3523.19 | F83: 5 | G83: 3102 | H83: 3437 | I83: 3287 | J83: 3935 | K83: 3447 | L83: 4160 | M83: 4358 | N83: 4315 | O83: 4463 | P83: 4095 | Q83: 5579 | R83: =SUM(G83:Q83)+C83 -> 45110
A84: 50805 - Payroll Pension Match- Project Labor | B84: 50805 | C84: -462 | D84: =-SUMIF(Sheet1!A:A,B84,Sheet1!Z:Z) -> 1934.87 | E84: =+C84+D84 -> 1472.87 | F84: 5 | G84: 1296 | H84: 1439 | I84: 1377 | J84: 1627 | K84: 1532 | L84: 1629 | M84: 1706 | N84: 1696 | O84: 1661 | P84: 1608 | Q84: 1716 | R84: =SUM(G84:Q84)+C84 -> 16825
A85: 60705 - Employee Benefits- Project Labor | B85: 60705 | C85: 12663 | D85: =-SUMIF(Sheet1!A:A,B85,Sheet1!Z:Z) -> 0 | E85: =+C85+D85 -> 12663 | G85: 4405 | H85: 5067 | I85: 4846 | J85: 4755 | K85: 5032 | L85: 5604 | M85: 5860 | N85: 5191 | O85: 5183 | P85: 5360 | Q85: 5356 | R85: =SUM(G85:Q85)+C85 -> 69322
A86: IT Project Labor | C86: =SUM(C82:C85) -> -2116 | D86: =SUM(D82:D85) -> 68871.5 | E86: =SUM(E82:E85) -> 66755.5 | G86: =SUM(G82:G85) -> 51988 | H86: =SUM(H82:H85) -> 57904 | I86: =SUM(I82:I85) -> 55387 | J86: =SUM(J82:J85) -> 64553 | K86: =SUM(K82:K85) -> 65070 | L86: =SUM(L82:L85) -> 61677 | M86: =SUM(M82:M85) -> 64595 | N86: =SUM(N82:N85) -> 67481 | ... Q86: =SUM(Q82:Q85) -> 69884 | R86: =SUM(G86:Q86)+C86 -> 692147
A87: Direct Labor Costs
A88: 50610 - Direct Labor Wages | B88: 50610 | C88: 338221 | D88: =-SUMIF(Sheet1!A:A,B88,Sheet1!Z:Z) -> -160688.6 | E88: =+C88+D88 -> 177532.4 | F88: 5 | G88: 145574 | H88: 173172 | I88: 175855 | J88: 157909 | K88: 185925 | L88: 172692 | M88: 169888 | N88: 163384 | O88: 193857 | P88: 172172 | Q88: 186685 | R88: =SUM(G88:Q88)+C88 -> 2235334
A89: 50710 - Payroll Taxes- Direct Labor | B89: 50710 | C89: 32170 | D89: =-SUMIF(Sheet1!A:A,B89,Sheet1!Z:Z) -> -19212.45 | E89: =+C89+D89 -> 12957.55 | F89: 5 | G89: 11260 | H89: 12853 | I89: 12880 | J89: 11615 | K89: 13657 | L89: 13180 | M89: 14048 | N89: 12786 | O89: 14313 | P89: 13183 | Q89: 20664 | R89: =SUM(G89:Q89)+C89 -> 182609
A90: 50811 - Payroll Pension Match- Direct Labor | B90: 50811 | C90: 3790 | D90: =-SUMIF(Sheet1!A:A,B90,Sheet1!Z:Z) -> -1834.42 | E90: =+C90+D90 -> 1955.58 | F90: 5 | G90: 1671 | H90: 1924 | I90: 2251 | J90: 2088 | K90: 2016 | L90: 2367 | M90: 2592 | N90: 2142 | O90: 2173 | P90: 2380 | Q90: 2475 | R90: =SUM(G90:Q90)+C90 -> 27869
A91: 60710 - Employee Benefits- Direct Labor | B91: 60710 | C91: 38623 | D91: =-SUMIF(Sheet1!A:A,B91,Sheet1!Z:Z) -> 0 | E91: =+C91+D91 -> 38623 | G91: 13391 | H91: 15243 | I91: 15675 | J91: 15237 | K91: 15471 | L91: 17237 | M91: 17013 | N91: 16620 | O91: 16774 | P91: 15447 | Q91: 17854 | R91: =SUM(G91:Q91)+C91 -> 214585
A92: 50660 - Contractor Wages - Direct Labor | B92: 50660 | C92: 3464 | D92: =-SUMIF(Sheet1!A:A,B92,Sheet1!Z:Z) -> 0 | E92: =+C92+D92 -> 3464 | G92: 2965 | H92: 3628 | I92: 4035 | J92: 2277 | K92: 1439 | R92: =SUM(G92:Q92)+C92 -> 17808
A93: 50661 - Payroll Expenses - Capitalized | B93: 50661 | C93: -90648 | D93: =-SUMIF(Sheet1!A:A,B93,Sheet1!Z:Z) -> 90648.14 | E93: =+C93+D93 -> 0.14 | F93: 6 | G93: 0 | R93: =SUM(G93:Q93)+C93 -> -90648
A94: Direct Labor Costs | C94: =SUM(C88:C93) -> 325620 | D94: =SUM(D88:D93) -> -91087.33 | E94: =SUM(E88:E93) -> 234532.67 | G94: =SUM(G88:G93) -> 174861 | H94: =SUM(H88:H93) -> 206820 | I94: =SUM(I88:I93) -> 210696 | J94: =SUM(J88:J93) -> 189126 | K94: =SUM(K88:K93) -> 218508 | L94: =SUM(L88:L93) -> 205476 | M94: =SUM(M88:M93) -> 203541 | N94: =SUM(N88:N93) -> 194932 | ... Q94: =SUM(Q88:Q93) -> 227678 | R94: =SUM(G94:Q94)+C94 -> 2587557
A95: Total Cost of Rev with IT Project and Direct Labor | C95: =+C94+C86+C80+C76+C73+C70+C57+C53 -> 689311 | D95: =+D94+D86+D80+D76+D73+D70+D57+D53 -> 20409.86 | E95: =+E94+E86+E80+E76+E73+E70+E57+E53 -> 709720.86 | G95: =+G94+G86+G80+G76+G73+G70+G57+G53 -> 744121 | H95: =+H94+H86+H80+H76+H73+H70+H57+H53 -> 1052860 | I95: =+I94+I86+I80+I76+I73+I70+I57+I53 -> 816899 | J95: =+J94+J86+J80+J76+J73+J70+J57+J53 -> 1073152 | K95: =+K94+K86+K80+K76+K73+K70+K57+K53 -> 1205020 | L95: =+L94+L86+L80+L76+L73+L70+L57+L53 -> 989783 | M95: =+M94+M86+M80+M76+M73+M70+M57+M53 -> 898323 | N95: =+N94+N86+N80+N76+N73+N70+N57+N53 -> 978298 | ... Q95: =+Q94+Q86+Q80+Q76+Q73+Q70+Q57+Q53 -> 740139 | R95: =SUM(G95:Q95)+C95 -> 11071675
A96: Total Gross Profit with Direct Labor | C96: =+C49-C95 -> 447031 | D96: =+D49-D95 -> -37708.72 | E96: =+E49-E95 -> 409322.28 | G96: =+G49-G95 -> 572927 | H96: =+H49-H95 -> 585343 | I96: =+I49-I95 -> 482554 | J96: =+J49-J95 -> 664341 | K96: =+K49-K95 -> 579619 | L96: =+L49-L95 -> 662847 | M96: =+M49-M95 -> 591465 | N96: =+N49-N95 -> 613496 | ... Q96: =+Q49-Q95 -> 412129 | R96: =SUM(G96:Q96)+C96 -> 6683037
A97: Sales Labor Costs
A98: 50620 - Sales Wages | B98: 50620 | C98: 94062 | D98: =-SUMIF(Sheet1!A:A,B98,Sheet1!Z:Z) -> -19385.56 | E98: =+C98+D98 -> 74676.44 | F98: 5 | G98: 64936 | H98: 80302 | I98: 78635 | J98: 82923 | K98: 85888 | L98: 84183 | M98: 89318 | N98: 87426 | O98: 105843 | P98: 93422 | Q98: 103218 | R98: =SUM(G98:Q98)+C98 -> 1050156
A99: 50720 - Payroll Taxes- Sales | B99: 50720 | C99: 7276 | D99: =-SUMIF(Sheet1!A:A,B99,Sheet1!Z:Z) -> -3123.99 | E99: =+C99+D99 -> 4152.01 | F99: 5 | G99: 3179 | H99: 5755 | I99: 7387 | J99: 9047 | K99: 8355 | L99: 8615 | M99: 9087 | N99: 7821 | O99: 9377 | P99: 10722 | Q99: 13354 | R99: =SUM(G99:Q99)+C99 -> 99975
A100: 50821 - Payroll Pension Match- Sales | B100: 50821 | C100: 2726 | D100: =-SUMIF(Sheet1!A:A,B100,Sheet1!Z:Z) -> -1350.25 | E100: =+C100+D100 -> 1375.75 | F100: 5 | G100: 992 | H100: 1395 | I100: 1598 | J100: 1702 | K100: 2310 | L100: 1642 | M100: 1720 | N100: 1411 | O100: 1542 | P100: 2748 | Q100: 2039 | R100: =SUM(G100:Q100)+C100 -> 21825
A101: 60720 - Employee Benefits- Sales | B101: 60720 | C101: 14610 | D101: =-SUMIF(Sheet1!A:A,B101,Sheet1!Z:Z) -> 0 | E101: =+C101+D101 -> 14610 | G101: 5205 | H101: 5985 | I101: 6485 | J101: 6018 | K101: 5287 | L101: 5889 | M101: 6170 | N101: 5504 | O101: 5485 | P101: 5550 | Q101: 6527 | R101: =SUM(G101:Q101)+C101 -> 78715
...

Sheet Sheet1
A1: GL Code | B1: Posted dt. | C1: Doc dt. | D1: Doc | E1: Memo/Description | F1: Department | G1: Location | H1: Department name | I1: Location name | J1: Customer name | K1: Customer | L1: Vendor name | M1: Vendor | N1: Item name | O1: Item | P1: Class name | Q1: Class | R1: Product Type | S1: Revenue Type | T1: Employee name | U1: Employee | V1: Txn No | W1: JNL | X1: Debit | Y1: Credit | Z1: Balance
A2: 41300 | B2: 46022 | C2: 46022 | E2: HHHC Overbilling correction | G2: DP | I2: Datapath, Inc. | V2: 2677 | W2: GJ | X2: 60357 | Z2: 60357
A3: 41500 | B3: 46022 | C3: 46022 | E3: Reverse WIP booking for 2024 | G3: DP | I3: Datapath, Inc. | V3: 2646 | W3: GJ | Y3: 1745.14 | Z3: -1745.14
A4: 41500 | B4: 46022 | C4: 46022 | E4: WIP Accrual 2025 | G4: DP | I4: Datapath, Inc. | V4: 2668 | W4: GJ | Y4: 13000 | Z4: -13000
A5: 41500 | B5: 46022 | C5: 46022 | E5: WIP Accrual 2025 | G5: DP | I5: Datapath, Inc. | V5: 2668 | W5: GJ | Y5: 15900 | Z5: -15900
A6: 41500 | B6: 46022 | C6: 46022 | E6: WIP Accrual 2025 | G6: DP | I6: Datapath, Inc. | V6: 2668 | W6: GJ | Y6: 18913.5 | Z6: -18913.5
A7: 41500 | B7: 46022 | C7: 46022 | E7: Reverse WIP booking for 2024 | G7: OHIO | I7: Data Path OHIO LLC | V7: 2646 | W7: GJ | X7: 6500.5 | Z7: 6500.5
A8: 50600 | B8: 46022 | C8: 46022 | E8: To correct payroll and accruals | G8: DP | I8: Datapath, Inc. | V8: 2681 | W8: GJ | Y8: 56839.74 | Z8: -56839.74
A9: 50600 | B9: 46022 | C9: 46022 | E9: To correct payroll and accruals | G9: DPF | I9: Datapath Fresno, LC | V9: 2681 | W9: GJ | Y9: 268.24 | Z9: -268.24
A10: 50600 | B10: 46022 | C10: 46022 | E10: To correct payroll and accruals | G10: OHIO | I10: Data Path OHIO LLC | V10: 2681 | W10: GJ | X10: 4679.26 | Z10: 4679.26
A11: 50605 | B11: 46022 | C11: 46022 | E11: To correct payroll and accruals | F11: D-002 | G11: DP | H11: Administration | I11: Datapath, Inc. | V11: 2681 | W11: GJ | X11: 14434.6 | Z11: 14434.6
A12: 50605 | B12: 46022 | C12: 46022 | E12: To correct payroll and accruals | F12: D-002 | G12: DPF | H12: Administration | I12: Datapath Fresno, LC | V12: 2681 | W12: GJ | X12: 3596.96 | Z12: 3596.96
A13: 50605 | B13: 46022 | C13: 46022 | E13: To correct payroll and accruals | F13: D-002 | G13: OHIO | H13: Administration | I13: Data Path OHIO LLC | V13: 2681 | W13: GJ | Y13: 82377 | Z13: -82377
A14: 50610 | B14: 46022 | C14: 46022 | E14: To correct payroll and accruals | F14: D-002 | G14: DP | H14: Administration | I14: Datapath, Inc. | V14: 2681 | W14: GJ | X14: 71686 | Z14: 71686
A15: 50610 | B15: 46022 | C15: 46022 | E15: To correct payroll and accruals | F15: D-002 | G15: DPF | H15: Administration | I15: Datapath Fresno, LC | V15: 2681 | W15: GJ | X15: 6868.02 | Z15: 6868.02
A16: 50610 | B16: 46022 | C16: 46022 | E16: To correct payroll and accruals | F16: D-002 | G16: OHIO | H16: Administration | I16: Data Path OHIO LLC | V16: 2681 | W16: GJ | X16: 82134.58 | Z16: 82134.58
A17: 50620 | B17: 46022 | C17: 46022 | E17: To correct payroll and accruals | F17: D-002 | G17: DP | H17: Administration | I17: Datapath, Inc. | V17: 2681 | W17: GJ | X17: 14922.8 | Z17: 14922.8
A18: 50620 | B18: 46022 | C18: 46022 | E18: To correct payroll and accruals | F18: D-002 | G18: OHIO | H18: Administration | I18: Data Path OHIO LLC | V18: 2681 | W18: GJ | X18: 4462.76 | Z18: 4462.76
A19: 50625 | B19: 46022 | C19: 46022 | E19: To correct payroll and accruals | F19: D-002 | G19: DP | H19: Administration | I19: Datapath, Inc. | V19: 2681 | W19: GJ | Y19: 135262.26 | Z19: -135262.26
A20: 50625 | B20: 46022 | C20: 46022 | E20: To correct payroll and accruals | F20: D-002 | G20: OHIO | H20: Administration | I20: Data Path OHIO LLC | V20: 2681 | W20: GJ | X20: 15442.83 | Z20: 15442.83
A21: 50661 | B21: 46022 | C21: 46022 | E21: To post internal use software. | G21: DP | I21: Datapath, Inc. | V21: 2721 | W21: GJ | Y21: 90648.14 | Z21: -90648.14
A22: 50700 | B22: 46022 | C22: 46022 | E22: To correct payroll and accruals | G22: DP | I22: Datapath, Inc. | V22: 2681 | W22: GJ | Y22: 15331.32 | Z22: -15331.32
A23: 50700 | B23: 46022 | C23: 46022 | E23: To correct payroll and accruals | G23: DPF | I23: Datapath Fresno, LC | V23: 2681 | W23: GJ | X23: 399.41 | Z23: 399.41
A24: 50700 | B24: 46022 | C24: 46022 | E24: To correct payroll and accruals | G24: OHIO | I24: Data Path OHIO LLC | V24: 2681 | W24: GJ | X24: 357.08 | Z24: 357.08
A25: 50705 | B25: 46022 | C25: 46022 | E25: To correct payroll and accruals | F25: D-002 | G25: DP | H25: Administration | I25: Datapath, Inc. | V25: 2681 | W25: GJ | X25: 3029.84 | Z25: 3029.84
A26: 50705 | B26: 46022 | C26: 46022 | E26: To correct payroll and accruals | F26: D-002 | G26: DPF | H26: Administration | I26: Datapath Fresno, LC | V26: 2681 | W26: GJ | X26: 920.97 | Z26: 920.97
A27: 50705 | B27: 46022 | C27: 46022 | E27: To correct payroll and accruals | F27: D-002 | G27: OHIO | H27: Administration | I27: Data Path OHIO LLC | V27: 2681 | W27: GJ | Y27: 6542 | Z27: -6542
A28: 50710 | B28: 46022 | C28: 46022 | E28: To correct payroll and accruals | F28: D-002 | G28: DP | H28: Administration | I28: Datapath, Inc. | V28: 2681 | W28: GJ | X28: 10631.43 | Z28: 10631.43
A29: 50710 | B29: 46022 | C29: 46022 | E29: To correct payroll and accruals | F29: D-002 | G29: DPF | H29: Administration | I29: Datapath Fresno, LC | V29: 2681 | W29: GJ | X29: 1178.99 | Z29: 1178.99
A30: 50710 | B30: 46022 | C30: 46022 | E30: To correct payroll and accruals | F30: D-002 | G30: OHIO | H30: Administration | I30: Data Path OHIO LLC | V30: 2681 | W30: GJ | X30: 7402.03 | Z30: 7402.03
A31: 50720 | B31: 46022 | C31: 46022 | E31: To correct payroll and accruals | F31: D-002 | G31: DP | H31: Administration | I31: Datapath, Inc. | V31: 2681 | W31: GJ | Y31: 758.42 | Z31: -758.42
A32: 50720 | B32: 46022 | C32: 46022 | E32: To correct payroll and accruals | F32: D-002 | G32: OHIO | H32: Administration | I32: Data Path OHIO LLC | V32: 2681 | W32: GJ | X32: 3882.41 | Z32: 3882.41
A33: 50801 | B33: 46022 | C33: 46022 | E33: To correct payroll and accruals | G33: DP | I33: Datapath, Inc. | V33: 2681 | W33: GJ | Y33: 1189.39 | Z33: -1189.39
A34: 50801 | B34: 46022 | C34: 46022 | E34: To correct payroll and accruals | G34: DPF | I34: Datapath Fresno, LC | V34: 2681 | W34: GJ | Y34: 9.43 | Z34: -9.43
A35: 50805 | B35: 46022 | C35: 46022 | E35: To correct payroll and accruals | F35: D-002 | G35: DP | H35: Administration | I35: Datapath, Inc. | V35: 2681 | W35: GJ | X35: 428.63 | Z35: 428.63
A36: 50805 | B36: 46022 | C36: 46022 | E36: To correct payroll and accruals | F36: D-002 | G36: DPF | H36: Administration | I36: Datapath Fresno, LC | V36: 2681 | W36: GJ | X36: 107.5 | Z36: 107.5
A37: 50805 | B37: 46022 | C37: 46022 | E37: To correct payroll and accruals | F37: D-002 | G37: OHIO | H37: Administration | I37: Data Path OHIO LLC | V37: 2681 | W37: GJ | Y37: 2471 | Z37: -2471
A38: 50811 | B38: 46022 | C38: 46022 | E38: To correct payroll and accruals | F38: D-002 | G38: DP | H38: Administration | I38: Datapath, Inc. | V38: 2681 | W38: GJ | Y38: 820.77 | Z38: -820.77
A39: 50811 | B39: 46022 | C39: 46022 | E39: To correct payroll and accruals | F39: D-002 | G39: DPF | H39: Administration | I39: Datapath Fresno, LC | V39: 2681 | W39: GJ | X39: 169.16 | Z39: 169.16
A40: 50811 | B40: 46022 | C40: 46022 | E40: To correct payroll and accruals | F40: D-002 | G40: OHIO | H40: Administration | I40: Data Path OHIO LLC | V40: 2681 | W40: GJ | X40: 2486.03 | Z40: 2486.03
A41: 50821 | B41: 46022 | C41: 46022 | E41: To correct payroll and accruals | F41: D-002 | G41: DP | H41: Administration | I41: Datapath, Inc. | V41: 2681 | W41: GJ | X41: 1170.38 | Z41: 1170.38
A42: 50821 | B42: 46022 | C42: 46022 | E42: To correct payroll and accruals | F42: D-002 | G42: OHIO | H42: Administration | I42: Data Path OHIO LLC | V42: 2681 | W42: GJ | X42: 179.87 | Z42: 179.87
A43: 50850 | B43: 46022 | C43: 46022 | E43: To correct payroll and accruals | F43: D-002 | G43: DP | H43: Administration | I43: Datapath, Inc. | V43: 2681 | W43: GJ | Y43: 1300 | Z43: -1300
A44: 50850 | B44: 46022 | C44: 46022 | E44: To correct payroll and accruals | F44: D-002 | G44: OHIO | H44: Administration | I44: Data Path OHIO LLC | V44: 2681 | W44: GJ | X44: 70 | Z44: 70
A45: 54000 | B45: 46022 | C45: 46022 | E45: Adjustment for Fright out getting relieved from Inventory when should be hitting P&L. | G45: DP | I45: Datapath, Inc. | V45: 2678 | W45: GJ | Y45: 3112.98 | Z45: -3112.98
A46: 54000 | B46: 46022 | C46: 46022 | E46: Adjustment for Fright out getting relieved from Inventory when should be hitting P&L. | G46: OHIO | I46: Data Path OHIO LLC | V46: 2679 | W46: GJ | Y46: 39512.71 | Z46: -39512.71
A47: 60100 | B47: 46022 | C47: 46022 | E47: To post internal use software. | G47: DP | I47: Datapath, Inc. | V47: 2721 | W47: GJ | X47: 3747.96 | Z47: 3747.96
A48: 60100 | B48: 46022 | C48: 46022 | D48: AJE241231-018 | E48: To book Depreciation and Amortization - Data Path Inc | G48: DP | I48: Datapath, Inc. | V48: 2159 | W48: GJ | X48: 142422 | Z48: 142422
A49: 60110 | B49: 46022 | C49: 46022 | E49: Finance Lease Entries 2025 | G49: DP | I49: Datapath, Inc. | V49: 2662 | W49: GJ | X49: 67887.92 | Z49: 67887.92
A50: 60190 | B50: 46022 | C50: 46022 | E50: To correct payroll and accruals | G50: DP | I50: Datapath, Inc. | V50: 2681 | W50: GJ | Y50: 2146 | Z50: -2146
A51: 60500 | B51: 46022 | C51: 46022 | D51: AJE241231-018 | E51: To book Depreciation and Amortization - Data Path Inc | G51: DP | I51: Datapath, Inc. | V51: 2159 | W51: GJ | X51: 1688 | Z51: 1688
A52: 60500 | B52: 46022 | C52: 46022 | D52: AJE241231-018 | E52: To book Depreciation and Amortization - Data Path Inc | G52: DP | I52: Datapath, Inc. | V52: 2159 | W52: GJ | X52: 8683 | Z52: 8683
A53: 60500 | B53: 46022 | C53: 46022 | D53: AJE241231-018 | E53: To book Depreciation and Amortization - Data Path Inc | G53: DP | I53: Datapath, Inc. | V53: 2159 | W53: GJ | X53: 16058 | Z53: 16058
A54: 60500 | B54: 46022 | C54: 46022 | D54: AJE241231-018 | E54: To book Depreciation and Amortization - Data Path Inc | G54: DP | I54: Datapath, Inc. | V54: 2159 | W54: GJ | X54: 18574 | Z54: 18574
A55: 60500 | B55: 46022 | C55: 46022 | D55: AJE241231-018 | E55: To book Depreciation and Amortization - Data Path Inc | G55: DP | I55: Datapath, Inc. | V55: 2159 | W55: GJ | X55: 56835 | Z55: 56835
A56: 60900 | B56: 46022 | C56: 46022 | E56: Finance Lease Entries 2025 | G56: DP | I56: Datapath, Inc. | V56: 2662 | W56: GJ | X56: 1099.72 | Z56: 1099.72
A57: 60900 | B57: 46022 | C57: 46022 | E57: To write off remaining balance on FF loan | G57: DP | I57: Datapath, Inc. | V57: 2744 | W57: GJ | Y57: 2243.24 | Z57: -2243.24
A58: 60900 | B58: 46022 | C58: 46022 | D58: Reversed - INV-10652 | E58: Bill - Chrysler Capital: Ohio Van- Chrysler Capital | F58: D-002 | G58: L-020 | H58: Administration | I58: Ohio | L58: Chrysler Capital | M58: V-10979 | V58: 4570 | W58: APJ | Y58: 184.18 | Z58: -184.18
A59: 60900 | B59: 46022 | C59: 46022 | D59: Reversed - INV-10662 | E59: Bill - Chrysler Capital: Ohio Van- Chrysler Capital | F59: D-002 | G59: L-020 | H59: Administration | I59: Ohio | L59: Chrysler Capital | M59: V-10979 | V59: 4570 | W59: APJ | Y59: 184.18 | Z59: -184.18
A60: 60900 | B60: 46022 | C60: 46022 | D60: Reversed - INV-10672 | E60: Bill - Chrysler Capital: Ohio Van- Chrysler Capital | F60: D-002 | G60: L-020 | H60: Administration | I60: Ohio | L60: Chrysler Capital | M60: V-10979 | V60: 4570 | W60: APJ | Y60: 184.18 | Z60: -184.18
A61: 61000 | B61: 46022 | C61: 46022 | E61: Balance sheet cleanup - prepaid insurance | F61: D-009 | G61: DP | H61: Admin | I61: Datapath, Inc. | V61: 2675 | W61: GJ | X61: 135253.48 | Z61: 135253.48
A62: 61100 | B62: 46022 | C62: 46022 | E62: Accrue Haskell Dec development | G62: DP | I62: Datapath, Inc. | L62: Haskell Macarcig | M62: V-11170 | V62: 2670 | W62: GJ | X62: 4000 | Z62: 4000
A63: 61250 | B63: 46022 | C63: 46022 | E63: Balance sheet cleanup - prepaid license | F63: D-009 | G63: DP | H63: Admin | I63: Datapath, Inc. | V63: 2673 | W63: GJ | X63: 2773.85 | Z63: 2773.85
A64: 61250 | B64: 46022 | C64: 46022 | E64: Balance sheet cleanup - prepaid tools | F64: D-009 | G64: DP | H64: Admin | I64: Datapath, Inc. | V64: 2674 | W64: GJ | X64: 4679.83 | Z64: 4679.83
A65: 61250 | B65: 46022 | C65: 46022 | E65: To expense items posted to fixed assets below threshold | G65: DP | I65: Datapath, Inc. | V65: 2719 | W65: GJ | X65: 6656.18 | Z65: 6656.18
A66: 61250 | B66: 46022 | C66: 46022 | E66: To expense items posted to fixed assets below threshold | G66: OHIO | I66: Data Path OHIO LLC | V66: 2719 | W66: GJ | X66: 682.95 | Z66: 682.95
A67: 61300 | B67: 45659 | C67: 45659 | E67: Charge Card Transaction - Southwest Visa: Professional Services | G67: L-010 | I67: Modesto | L67: Kiln | M67: V-10212 | V67: 2746 | W67: CDJ | X67: 303.56 | Z67: 303.56
A68: 61300 | B68: 46022 | C68: 46022 | E68: Operating Lease Entries 2025-DP Ohio | G68: OHIO | I68: Data Path OHIO LLC | V68: 2664 | W68: GJ | Y68: 3077.44 | Z68: -3077.44
A69: 61350 | B69: 46022 | C69: 46022 | E69: To correct payroll and accruals | G69: DP | I69: Datapath, Inc. | V69: 2681 | W69: GJ | X69: 57289.76 | Z69: 57289.76
A70: 61600 | B70: 46022 | C70: 46022 | E70: Adj to Avalara Accrual | G70: DP | I70: Datapath, Inc. | V70: 2655 | W70: GJ | X70: 3728.16 | Z70: 3728.16
A71: 61600 | B71: 46022 | C71: 46022 | E71: Adj to Avalara Accrual | G71: L-009 | I71: Fresno | V71: 2656 | W71: GJ | X71: 0.83 | Z71: 0.83
A72: 61600 | B72: 46022 | C72: 46022 | E72: Adj to Avalara Accrual | G72: OHIO | I72: Data Path OHIO LLC | V72: 2657 | W72: GJ | Y72: 1331.68 | Z72: -1331.68
A73: 61700 | B73: 46022 | C73: 46022 | E73: Property tax bill for fiscal year 2025-2026 | G73: DP | I73: Datapath, Inc. | V73: 2666 | W73: GJ | X73: 5983.31 | Z73: 5983.31
A74: 62100 | B74: 46022 | C74: 46022 | E74: Accrual for PAGA Class Action Suit, California | F74: D-002 | G74: DP | H74: Administration | I74: Datapath, Inc. | V74: 2649 | W74: GJ | X74: 5900 | Z74: 5900
A75: 62100 | B75: 46022 | C75: 46022 | E75: Move Citrin Cooperman fees to expense | F75: D-002 | G75: DP | H75: Administration | I75: Datapath, Inc. | V75: 2658 | W75: GJ | X75: 57500 | Z75: 57500
A76: 62100 | B76: 46022 | C76: 46022 | E76: Balance sheet cleanup - prepaid license | F76: D-009 | G76: DP | H76: Admin | I76: Datapath, Inc. | V76: 2673 | W76: GJ | X76: 5600 | Z76: 5600
A77: 62100 | B77: 46022 | C77: 46022 | E77: Accrue estimated settlement costs for CA Class action lawsuit (inclusive of 25k legal) | G77: DP | I77: Datapath, Inc. | V77: 2676 | W77: GJ | X77: 125000 | Z77: 125000
A78: 62100 | B78: 46022 | C78: 46022 | E78: To post PAGA Class Action Accrual | G78: DP | I78: Datapath, Inc. | V78: 2682 | W78: GJ | X78: 5900 | Z78: 5900
A79: 62100 | B79: 46022 | C79: 46022 | E79: To clean up prepaid Citrin balance | G79: DP | I79: Datapath, Inc. | V79: 2746 | W79: GJ | X79: 30906.25 | Z79: 30906.25
A80: 80000 | B80: 46022 | C80: 46022 | E80: Accrue remainder due to MSA for 2022/2023 R&D study | G80: DP | I80: Datapath, Inc. | L80: MSA Corporate Strategies LLC | M80: RMP_84 | V80: 2644 | W80: GJ | X80: 43139.71 | Z80: 43139.71
A81: 80000 | B81: 46022 | C81: 46022 | E81: Acct Cleanup-Unknown balance for services paid in advance | G81: DP | I81: Datapath, Inc. | V81: 2647 | W81: GJ | Y81: 3910.61 | Z81: -3910.61
A82: 80000 | B82: 46022 | C82: 46022 | E82: To correct payroll and accruals | G82: DP | I82: Datapath, Inc. | V82: 2681 | W82: GJ | Y82: 145807.95 | Z82: -145807.95
A83: 80000 | B83: 46022 | C83: 46022 | E83: Reverse DLL Finance Free Flooring | G83: DP | I83: Datapath, Inc. | V83: 2685 | W83: GJ | Y83: 216315.27 | Z83: -216315.27
A84: 80000 | B84: 46022 | C84: 46022 | E84: To write off remaining balance on Rav4 | G84: DP | I84: Datapath, Inc. | V84: 2717 | W84: GJ | X84: 0.09 | Z84: 0.09
A85: 80000 | B85: 46022 | C85: 46022 | E85: Write off remaining balance on Valley Network | G85: DP | I85: Datapath, Inc. | V85: 2718 | W85: GJ | X85: 0.3 | Z85: 0.3
A86: 80000 | B86: 46022 | C86: 46022 | E86: Payroll Accrual Correction | G86: DP | I86: Datapath, Inc. | V86: 2747 | W86: GJ | Y86: 35829.77 | Z86: -35829.77
A87: 80000 | B87: 46022 | C87: 46022 | E87: Acct Cleanup-Unknown balance for services paid in advance | G87: DPF | I87: Datapath Fresno, LC | V87: 2647 | W87: GJ | Y87: 6800 | Z87: -6800
A88: 80000 | B88: 46022 | C88: 46022 | E88: Acct Cleanup-Unknown amount due from Mobile Tech Service. | G88: OHIO | I88: Data Path OHIO LLC | V88: 2647 | W88: GJ | X88: 3674.15 | Z88: 3674.15
A89: 80000 | B89: 46022 | C89: 46022 | E89: Acct Cleanup-Unknown balance for services paid in advance | G89: OHIO | I89: Data Path OHIO LLC | V89: 2647 | W89: GJ | Y89: 996 | Z89: -996
A90: 80000 | B90: 46022 | C90: 46022 | E90: Adjust Earnout for MTS | G90: OHIO | I90: Data Path OHIO LLC | V90: 2680 | W90: GJ | Y90: 238615.42 | Z90: -238615.42
A91: 80000 | B91: 46022 | C91: 46022 | E91: Post sale of Dodge | G91: OHIO | I91: Data Path OHIO LLC | V91: 2720 | W91: GJ | X91: 7 | Z91: 7
A92: 80100 | B92: 46022 | C92: 46022 | E92: Write off for Customer Aging Report | G92: DP | I92: Datapath, Inc. | V92: 2722 | W92: GJ | X92: 35377.06 | Z92: 35377.06
A93: 80100 | B93: 46022 | C93: 46022 | E93: To write off old AP | G93: DP | I93: Datapath, Inc. | V93: 2749 | W93: GJ | Y93: 47924.17 | Z93: -47924.17
A94: 80100 | B94: 46022 | C94: 46022 | E94: Write off Luther Memorial | G94: L-020 | I94: Ohio | V94: 2683 | W94: GJ | X94: 12430.83 | Z94: 12430.83
A95: 80300 | B95: 46022 | C95: 46022 | E95: Post sale of Dodge | G95: OHIO | I95: Data Path OHIO LLC | V95: 2720 | W95: GJ | X95: 20002.55 | Z95: 20002.55
A96: 80300 | B96: 46022 | C96: 46022 | E96: To write off Chrysler vehicle loan | G96: OHIO | I96: Data Path OHIO LLC | V96: 2745 | W96: GJ | Y96: 23249.53 | Z96: -23249.53
